Workbook
Name BPTCat: Lists!$E$2:$E$4
Name CYBCat: Lists!$G$2:$G$4
Name OnOff: Lists!$C$2:$C$3
Name SADCat: Lists!$F$2:$F$4
Name SquadSizes: Lists!$B$2:$B$5
Name SquadTypes: Lists!$A$2:$A$8
Name SupportPct: Lists!$D$2:$D$10

Sheet Exec Summary
B2: TDD Operating Model - Executive Summary
B4: Why this workbook exists
B5: Purpose: each GM designed a new operating model against set squad archetypes (type x size = people and cost). This workbook prices the archetypes and checks the actual design against them.
B6: The test: can each portfolio fund its archetype cost (TDD + business)? If yes, live within it. If not, start with the vacancies (4.x GM tabs), then archetype size (1.x dropdowns).
B7: Each portfolio tab (1.x) shows the squads, sizes, support %, budget draw-downs and what is left to fund.
B8: Next step: agree funding for what is left to fund, and decide which vacancies to hire or hold.
B10: How the model is built - key decisions
B11: Squads are priced from the archetype library on 0.3 Squad Archetypes (type x size). Offshore is priced at the offshore rate set on 0.3 Squad Archetypes.
B12: Each portfolio pays one overhead: Head of Tech, Business Partner and Domain Architect shares, and leadership - rates on 0.2 Data Config.
B13: Strategic programs (AmPOS, CTRM, EGI) are priced at their entered cost. EGI is funded from Significant Items, not overheads.
B14: TDD Cyber is priced from its actual roles on 2.3 Cyber Roles, not archetypes.
B15: Business Partner & Domain Architect money sits inside the portfolio overheads, so it is taken out of the COE total - never counted twice.
... B18: The TDD budget
B19: Total TDD people budget ($m) | C19: ='0.2 Data Config'!$E$27 -> 53.8
B20: Allocated to portfolios + COEs ($m) | C20: ='2.5 Group Summary'!$C$30 -> 43.5
B21: Not yet allocated ($m) | C21: ='0.2 Data Config'!$E$27-'2.5 Group Summary'!$C$30 -> 10.3
B22: What the archetype model costs
B23: TDD Cost - funded by TDD ($m) | C23: ='2.5 Group Summary'!$D$24 -> 62.417348
B24: Funded outside TDD ($m) | C24: ='2.5 Group Summary'!$G$24 -> 30.672
B25: Less: BP & Domain Architect already funded in portfolio overheads ($m) | C25: ='2.6 Total Cost'!$C$23 -> -3.432
B26: Total archetype model cost ($m) | C26: ='2.6 Total Cost'!$C$24 -> 89.657348
B27: of which TDD pays - after the double-count ($m) | C27: ='2.5 Group Summary'!$D$24+'2.6 Total Cost'!$C$23 -> 58.985348
B28: Left to fund - portfolios + COEs ($m) | C28: ='2.5 Group Summary'!$I$24 -> 21.113297
B29: What the org actually costs today
B30: All roles today - filled + vacant ($m) | C30: ='2.6 Total Cost'!$I$24 -> 118.19871
B31: of which filled ($m) | C31: ='2.6 Total Cost'!$E$24 -> 84.832646
B32: of which vacant ($m) | C32: ='2.6 Total Cost'!$G$24 -> 33.36606
B33: Difference vs archetype model ($m) | C33: ='2.6 Total Cost'!$K$24 -> 28.541358
B35: The people - archetypes vs the org
B36: Roles the archetypes allow - squads at their set sizes | C36: ='2.7 Squad Detail'!$G$4 -> 328.5
B37: Roles actually raised in those squads - filled + vacant | C37: ='2.7 Squad Detail'!$G$95+'2.7 Squad Detail'!$K$95 -> 328
B38: Roles raised beyond the archetypes | C38: ='2.7 Squad Detail'!$H$4 -> -0.5
B39: Roles in squads priced outside archetypes (AmPOS, EGI, cyber) | C39: ='2.7 Squad Detail'!$J$95-'2.7 Squad Detail'!$G$95-'2.7 Squad Detail'!$K$95 -> 94
B40: All org roles (squads + leadership + COEs + unmapped) | C40: ='2.7 Squad Detail'!$C$4 -> 536
B41: Filled - people in roles today | C41: ='2.7 Squad Detail'!$D$4 -> 370
B42: Vacant - raised, not yet hired | C42: ='2.7 Squad Detail'!$E$4 -> 166
B43: of which squad roles - the GM hire or hold lever | C43: =COUNTIFS(Squads!$Q:$Q,"Squad",Squads!$R:$R,"Vacant")+COUNTIFS(Squads!$Q:$Q,"Strategic Program",Squads!$R:$R,"Vacant") -> 124
B44: of which leadership, COE and unmapped roles | C44: ='2.7 Squad Detail'!$E$4-COUNTIFS(Squads!$Q:$Q,"Squad",Squads!$R:$R,"Vacant")-COUNTIFS(Squads!$Q:$Q,"Strategic Program",Squads!$R:$R,"Vacant") -> 42
B45: Vacancy rate | C45: ='2.7 Squad Detail'!$F$4 -> 0.30970149
B46: Vacant = open roles in the raw data. Sheet2 status updates (Paused, ring-fenced) show on 2.1 to 2.3 and 5.0.
B48: What it means
B49: Today's filled roles cost ($m) | C49: ='2.6 Total Cost'!$E$24 -> 84.832646
B50: Filled roles over/(under) the archetype cost ($m) | C50: =ROUND('2.6 Total Cost'!$E$24-'2.6 Total Cost'!$C$24,6) -> -4.824702
B51: Hiring every vacancy would add ($m) | C51: ='2.6 Total Cost'!$G$24 -> 33.36606
B52: of which squad roles - the 4.x GM lever ($m) | C52: ='4.1 Ampol Retail'!$C$16+'4.2 Customer'!$C$14+'4.3 Enterprise Data'!$C$11+'4.4 TDD Group Functions'!$C$12+'4.5 P&C'!$C$10+'4.6 Finance'!$C$10+'4.7 Infrastructure'!$C$11+'4.8 Energy Solutions & B2B'!$C$10+'4.9 Commercial Fuels'!$C$11+'4.10 Z Retail'!$C$10+'4.11 TDD Cyber'!$C$8 -> 24.651394
B53: Vacant roles are priced at standard title rates - indicative until an offer is made.
B54: Taking the design OVER the archetypes by ($m) | C54: ='2.6 Total Cost'!$K$24 -> 28.541358
B55: The main lever is the vacancies: they are raised but not hired, so holding them impacts nobody. Make the call role by role on the 4.x GM tab.
B56: Resizing the archetypes themselves (squad size, support %, onshore or offshore) is done with the dropdowns on the 1.x tabs - cost, variance and left to fund update live.
B57: Roles not mapped to any squad or COE ($m) | C57: ='2.6 Total Cost'!$I$22 -> 9.1627083
B58: TDD Cyber - needs more than its budget, see 1.11 ($m) | C58: ='2.3 Cyber Roles'!$C$15 -> 8.330489
B59: COEs - left to fund after budgets, see 2.4 ($m) | C59: ='2.4 COE Summary'!$F$13 -> 2.1212968
B61: Portfolio drill-down
B62: Yellow cell = dropdown input - pick a portfolio
B63: Portfolio | C63: Ampol Retail
B64: TDD Lights On budget ($m) | C64: =INDEX('2.5 Group Summary'!$C$6:$C$16,MATCH($C$63,'2.5 Group Summary'!$B$6:$B$16,0)) -> 2.5
B65: TDD Cost ($m) | C65: =INDEX('2.5 Group Summary'!$D$6:$D$16,MATCH($C$63,'2.5 Group Summary'!$B$6:$B$16,0)) -> 5.6265
B66: TDD Variance - to fund ($m) | C66: =MAX(0,-INDEX('2.5 Group Summary'!$E$6:$E$16,MATCH($C$63,'2.5 Group Summary'!$B$6:$B$16,0))) -> 3.1265
B67: Funded outside TDD ($m) | C67: =INDEX('2.5 Group Summary'!$G$6:$G$16,MATCH($C$63,'2.5 Group Summary'!$B$6:$B$16,0)) -> 4.728
B68: Allocated outside TDD ($m) | C68: =INDEX('2.5 Group Summary'!$H$6:$H$16,MATCH($C$63,'2.5 Group Summary'!$B$6:$B$16,0)) -> 0
B69: Left to fund ($m) | C69: =INDEX('2.5 Group Summary'!$I$6:$I$16,MATCH($C$63,'2.5 Group Summary'!$B$6:$B$16,0)) -> 4.728
B70: Total cost ($m) | C70: =INDEX('2.5 Group Summary'!$K$6:$J$16,MATCH($C$63,'2.5 Group Summary'!$B$6:$B$16,0)) -> #REF!
B71: Archetype squad roles allowed | C71: =INDEX(Lists!$K$2:$K$12,MATCH($C$63,Lists!$J$2:$J$12,0)) -> 60.5
B72: Org roles (excl leadership) | C72: =COUNTIFS(Squads!$N:$N,$C$63)-COUNTIFS(Squads!$N:$N,$C$63,Squads!$Q:$Q,"Leadership") -> 75
B73: Filled | C73: =COUNTIFS(Squads!$N:$N,$C$63,Squads!$R:$R,"Filled")-COUNTIFS(Squads!$N:$N,$C$63,Squads!$Q:$Q,"Leadership",Squads!$R:$R,"Filled") -> 47
B74: Vacant | C74: =COUNTIFS(Squads!$N:$N,$C$63,Squads!$R:$R,"Vacant")-COUNTIFS(Squads!$N:$N,$C$63,Squads!$Q:$Q,"Leadership",Squads!$R:$R,"Vacant") -> 28
B75: Leadership roles | C75: =COUNTIFS(Squads!$N:$N,$C$63,Squads!$Q:$Q,"Leadership") -> 5
B76: Org roles include roles outside the archetype model; squad-only counts are on 2.7 Squad Detail.

Sheet - INPUTS -
B2: INPUTS >>>

Sheet 0.0 Guide
B2: How this workbook flows
B4: The flow - two streams that meet in the middle
B5: STREAM 1, THE DESIGN: 0.1 Budget Table (the money Finance gave) feeds 0.2 Data Config (how it is allocated per portfolio, AU and NZ, plus overhead rates and the four $2m COE allocations). 0.3 Squad Archetypes prices the contract (type x size). Each GM's design sits on 1.1 to 1.11, priced from 0.3 and funded per 0.2.
B6: STREAM 2, THE ORG: the Squads tab holds every role actually raised (536, filled and vacant) and its model mapping. Sheet2 holds the updated rosters for BP&T, SA&D, Cyber and EGI. Added data holds what each person actually costs.
B7: THE ROLL-UP: the COE rosters (2.1 BP&T, 2.2 SA&D, 2.3 Cyber Roles) and their funding roll into 2.4 COE Summary. 2.5 Group Summary answers: can the budgets fund the design (with AU and NZ variance). 2.6 Total Cost is the test: the design vs what the org actually costs. 2.7 Squad Detail is the same test squad by squad.
B8: THE DECISIONS: tabs 4.1 to 4.14 - every role in the organisation appears on exactly one of them. GMs mark Hire or Hold on every vacancy. The Exec Summary tells the result. 5.0 Data QA is the evidence behind every number.
B9: What you can edit (yellow cells are inputs)
B10: 0.2 Data Config: budgets, rates, allocations. | 0.3 Squad Archetypes: prices and the offshore rate. | 1.x: squad type, size, On/Off, support %, Fund (AU or NZ). | 4.x: the Hire or Hold Call cells. | Squads / Sheet2 / Added data: your source data.
B11: If you change X, Y updates
B12: A squad's type, size, On/Off, support % or Fund toggle on 1.x updates 2.5, 2.6, 2.7 and the Exec Summary.
B13: A status or mapping in the Squads tab updates every role count: 2.6, 2.7 and the 4.x tabs.
B14: A person or cost in Sheet2 updates 2.1, 2.2, 2.3, the EGI roster, 2.4, the COE lines of 2.5 and 2.6, and tabs 4.12 to 4.14.
... B22: Every row labelled Check must read 0. All reconciliations, the Sheet2 update log, the mapping change log and the raw data audit live on 5.0 Data QA. Every role has exactly one 4.x home - if one were missed, the checks would not foot.

Sheet 0.1 Budget Table (Fin)
B3: BUSINESS | C3: EGM Sponsor | D3: GM Sponsor | E3: Domain Architect | F3: HO Technology | G3: Lights-on | M3: Depreciation | N3: Initiatives | O3: Sig Items | P3: Capex | Q3: Total Budget | S3: Existing | T3: Aligned Delivery | U3: Aligned COE's | V3: Total Budget
B4: SEGMENT | G4: People | H4: HW | I4: SW | J4: Network | K4: Vendor | L4: Sub-Total | Q4: FY2026 | V4: FY2026
B5: TDD Corporate (1) | C5: Brad Blyth | G5: 35.2 | H5: 2.9 | I5: 25.6 | J5: 2.1 | K5: 13.1 | L5: =SUM(G5:K5) -> 78.9 | M5: 5.8 | N5: 3 | O5: 20.2 | P5: 4.9 | Q5: =SUM(L5:P5) -> 112.8 | U5: =SUM(W25:W29) -> 91.6 | V5: =SUM(S5:U5) -> 91.6
B6: Z-Energy (2) | C6: Lindis Jones | D6: Vance Anderson | G6: 17.6 | H6: 19.8 | I6: 11.6 | J6: 0.6 | K6: 2.6 | L6: =SUM(G6:K6) -> 52.2 | M6: 11.3 | N6: 1.4 | O6: - | P6: 11.7 | Q6: =SUM(L6:P6) -> 76.6 | S6: =Q6 -> 76.6 | V6: =SUM(S6:U6) -> 76.6
B7: EnergySolutions | C7: Brent Merrick | D7: Roanne Steele | G7: 1 | H7: 1.5 | I7: 1.4 | L7: =SUM(G7:K7) -> 3.9 | N7: 1 | P7: 2.3 | Q7: =SUM(L7:P7) -> 7.2 | S7: =Q7 -> 7.2 | V7: =SUM(S7:U7) -> 7.2 | Y7: =SUM(L9,N9,O9,P9) -> 33.8
B8: Commercial Fuels | C8: Brent Merrick | D8: Roanne Steele | H8: 2.5 | I8: 9.4 | J8: 1.5 | L8: =SUM(G8:K8) -> 13.4 | N8: 6.1 | O8: 14.2 | P8: 6.8 | Q8: =SUM(L8:P8) -> 40.5 | S8: =Q8 -> 40.5 | T8: =S19 -> 1.2 | V8: =SUM(S8:U8) -> 41.7
B9: Retail | C9: Kate Thomson | D9: Roanne Steele | H9: 5.3 | I9: 6.4 | J9: 2.2 | L9: =SUM(G9:K9) -> 13.9 | N9: 1.3 | O9: 6.8 | P9: 11.8 | Q9: =SUM(L9:P9) -> 33.8 | S9: =Q9 -> 33.8 | T9: =S20 -> 5.2 | V9: =SUM(S9:U9) -> 39
B10: Infrastructure | C10: Michelle Bardy | D10: Roanne Steele | H10: 1.9 | I10: 2 | L10: =SUM(G10:K10) -> 3.9 | N10: 0.4 | P10: 5 | Q10: =SUM(L10:P10) -> 9.3 | S10: =Q10 -> 9.3 | T10: =S21 -> 2.2 | V10: =SUM(S10:U10) -> 11.5
B11: Corporate Finance | C11: Greg Barnes | D11: Emily Mogic | H11: 0.5 | I11: 2.1 | L11: =SUM(G11:K11) -> 2.6 | N11: 0.9 | Q11: =SUM(L11:P11) -> 3.5 | S11: =Q11 -> 3.5 | T11: =S22 -> 9 | V11: =SUM(S11:U11) -> 12.5
B12: P&C | C12: Meaghan Davis | D12: Emily Mogic | H12: 0.3 | I12: 1.8 | L12: =SUM(G12:K12) -> 2.1 | N12: 2 | O12: 1.4 | P12: 0.3 | Q12: =SUM(L12:P12) -> 5.8 | S12: =Q12 -> 5.8 | T12: =S23 -> 0 | V12: =SUM(S12:U12) -> 5.8
B13: Customer | C13: Kate Thomson | D13: Vance Anderson | H13: 0.1 | I13: 1.6 | L13: =SUM(G13:K13) -> 1.7 | O13: 5 | P13: 5 | Q13: =SUM(L13:P13) -> 11.7 | S13: =Q13 -> 11.7 | T13: =S24 -> 3.7 | V13: =SUM(S13:U13) -> 15.4
B14: Total Technology | G14: =SUM(G5:G13) -> 53.8 | H14: =SUM(H5:H13) -> 34.8 | I14: =SUM(I5:I13) -> 61.9 | J14: =SUM(J5:J13) -> 6.4 | K14: =SUM(K5:K13) -> 15.7 | L14: =SUM(L5:L13) -> 172.6 | M14: =SUM(M5:M13) -> 17.1 | N14: =SUM(N5:N13) -> 16.1 | ... Q14: =SUM(Q5:Q13) -> 301.2 | S14: =SUM(S6:S13) -> 188.4 | T14: =SUM(T8:T13) -> 21.3 | U14: =U5 -> 91.6 | V14: =SUM(V5:V13) -> 301.3
B17: BUSINESS SEGMENT | E17: EGM Sponsor | F17: GM Sponsor | G17: Domain Architect | H17: HO Technology | I17: Lights-on | O17: Depreciation | P17: Initiatives | Q17: Sig Items | R17: Capex | S17: Total Budget | U17: Existing | V17: Aligned Delivery | W17: Aligned | X17: Total Budget
I18: People | J18: HW | K18: SW | L18: Network | M18: Vendor | N18: Sub-Total | S18: FY2026 | W18: COE's | X18: FY2026
D19: Commercial Fuels | I19: 1.2 | J19: 0 | K19: 0 | L19: - | M19: - | N19: =SUM(I19:M19) -> 1.2 | O19: - | S19: =SUM(N19:R19) -> 1.2 | X19: -
D20: Retail | I20: 3.4 | J20: 0.2 | K20: 0.9 | L20: - | M20: 0.7 | N20: =SUM(I20:M20) -> 5.2 | O20: - | S20: =SUM(N20:R20) -> 5.2 | X20: -
D21: Infrastructure | I21: 2 | J21: - | K21: 0.2 | L21: - | M21: - | N21: =SUM(I21:M21) -> 2.2 | O21: - | S21: =SUM(N21:R21) -> 2.2 | X21: -
D22: Corporate Finance | I22: 1.3 | J22: - | K22: 4.2 | L22: - | M22: 3.5 | N22: =SUM(I22:M22) -> 9 | O22: - | S22: =SUM(N22:R22) -> 9 | X22: -
D23: P&C | I23: 0 | J23: - | K23: - | L23: - | M23: - | N23: =SUM(I23:M23) -> 0 | O23: - | S23: =SUM(N23:R23) -> 0 | X23: -
D24: Customer | I24: 1.2 | J24: - | K24: 0.6 | L24: 0 | M24: 1 | N24: =SUM(I24:M24) -> 2.8 | O24: 0.9 | S24: =SUM(N24:R24) -> 3.7 | X24: -
D25: TDD | F25: Emily Mogic | I25: 4.5 | J25: 2.5 | K25: 14.5 | L25: 0 | M25: 0.8 | N25: =SUM(I25:M25) -> 22.3 | O25: 4.9 | S25: =SUM(N25:R25) -> 27.2 | W25: =S25 -> 27.2 | X25: =W25 -> 27.2
D26: TDDEGM | F26: Brad Blyth | I26: 6.5 | J26: - | K26: - | L26: - | M26: 3.6 | N26: =SUM(I26:M26) -> 10.1 | O26: - | P26: 3 | Q26: 20.2 | R26: 4.9 | S26: =SUM(N26:R26) -> 38.2 | W26: =S26 -> 38.2 | X26: =W26 -> 38.2
D27: Strategy, Architecture and Data | F27: Matt Ashley | I27: 5.3 | J27: - | K27: 1 | L27: - | M27: 0.6 | N27: =SUM(I27:M27) -> 6.9 | O27: - | S27: =SUM(N27:R27) -> 6.9 | W27: =S27 -> 6.9 | X27: =W27 -> 6.9
D28: Cyber Risk and Operations | F28: Frances Bouzo | I28: 7.6 | J28: 0.2 | K28: 4.3 | L28: 2 | M28: 2.9 | N28: =SUM(I28:M28) -> 17 | O28: - | S28: =SUM(N28:R28) -> 17 | W28: =S28 -> 17 | X28: =W28 -> 17
D29: Business Partnering and Governance | F29: Michael Schofield | I29: 2.3 | J29: - | K29: - | L29: - | M29: - | N29: =SUM(I29:M29) -> 2.3 | O29: - | S29: =SUM(N29:R29) -> 2.3 | W29: =S29 -> 2.3 | X29: =W29 -> 2.3
B30: TDD Corporate (1) | E30: Brad Blyth | I30: =G5 -> 35.2 | J30: =H5 -> 2.9 | K30: =I5 -> 25.6 | L30: =J5 -> 2.1 | M30: =K5 -> 13.1 | N30: =L5 -> 78.9 | O30: =M5 -> 5.8 | P30: =N5 -> 3 | ... S30: =Q5 -> 112.8 | W30: =U5 -> 91.6 | X30: =W30 -> 91.6
C31: Z-Energy (Direct TDD) | I31: 17.6 | J31: 12.1 | K31: 6.3 | L31: 0.6 | M31: 2.6 | N31: 39.3 | O31: 11.3 | P31: 1.4 | R31: 11.7 | S31: 63.7 | X31: -
C32: Z-Energy (Other IT Spend for Supplies, Customer) | J32: 7.6 | K32: 5.3 | N32: 13 | S32: 13 | X32: -
B33: Z-Energy (2) | E33: Lindis Jones | F33: Vance Anderson | I33: =G6 -> 17.6 | J33: =H6 -> 19.8 | K33: =I6 -> 11.6 | L33: =J6 -> 0.6 | M33: =K6 -> 2.6 | N33: =L6 -> 52.2 | O33: =M6 -> 11.3 | P33: =N6 -> 1.4 | ... S33: =Q6 -> 76.6 | U33: =S6 -> 76.6 | X33: =U33 -> 76.6

Sheet 0.2 Data Config
B2: Data Config
B4: TDD Budget Allocation ($m) | I4: Portfolio Overhead (roles, $m)
B5: Portfolio | C5: AU | D5: NZ | E5: Total | F5: Spend | G5: Variance | I5: Role | J5: Cost ($m) | K5: Allocation % | L5: Portfolio cost ($m)
B6: COE - Strategy Architecture | C6: 1.5 | D6: 0.5 | E6: =C6+D6 -> 2 | F6: ='2.4 COE Summary'!$D$8 -> 4.320561 | G6: =SUM(E6-F6) -> -2.320561 | I6: Head of Tech | J6: 0.275 | K6: 0.5 | L6: =J6*K6 -> 0.1375
B7: COE - Cyber, Risk & Service Ops (rolled into 1.11 TDD Cyber) | C7: 0 | D7: 0 | E7: =C7+D7 -> 0 | F7: ='2.4 COE Summary'!$D$9 -> 0 | G7: =SUM(E7-F7) -> 0 | I7: Business Partner | J7: 0.43 | K7: 0.4 | L7: =J7*K7 -> 0.172
B8: COE - Transformation | C8: 1.5 | D8: 0.5 | E8: =C8+D8 -> 2 | F8: ='2.4 COE Summary'!$D$10 -> 3.1079992 | G8: =SUM(E8-F8) -> -1.1079992 | I8: Domain Architect | J8: 0.28 | K8: 0.5 | L8: =J8*K8 -> 0.14
B9: COE - Business Partnering | C9: 1.5 | D9: 0.5 | E9: =C9+D9 -> 2 | F9: ='2.4 COE Summary'!$D$11 -> 3.2925626 | G9: =SUM(E9-F9) -> -1.2925626 | I9: Leadership Overhead | J9: 1 | K9: 0.3 | L9: =J9*K9 -> 0.3
B10: COE - Data | C10: 1.5 | D10: 0.5 | E10: =C10+D10 -> 2 | F10: ='2.4 COE Summary'!$D$12 -> 2.2327366 | G10: =SUM(E10-F10) -> -0.23273662 | I10: Portfolio overhead subtotal | L10: =SUM(L6:L9) -> 0.7495
B11: Ampol Retail | C11: 2.5 | D11: 0 | E11: =C11+D11 -> 2.5 | F11: ='1.1 Ampol Retail'!$C$9 -> 5.6265 | G11: =SUM(E11-F11) -> -3.1265
B12: Z Retail | C12: 0 | D12: 2.5 | E12: =C12+D12 -> 2.5 | F12: ='1.10 Z Retail'!$C$9 -> 5.3995 | G12: =SUM(E12-F12) -> -2.8995 | I12: Platform Overhead (roles, $m)
B13: Ampol Customer | C13: 2.5 | D13: 0 | E13: =C13+D13 -> 2.5 | F13: ='1.2 Customer'!$C$9 -> 9.0245 | G13: =SUM(E13:E14)-F13 -> -2.5245 | I13: Role | J13: Cost ($m) | K13: Alloc % | L13: Platform cost ($m)
B14: Z Customer | C14: 0 | D14: 4 | E14: =C14+D14 -> 4 | I14: Delivery Manager | J14: 0.28 | K14: 0.3 | L14: =J14*K14 -> 0.084
B15: Commercial Fuels | C15: 2.5 | D15: 0 | E15: =C15+D15 -> 2.5 | F15: ='1.9 Commercial Fuels'!C9 -> 2.0845 | G15: =SUM(E15-F15) -> 0.4155 | I15: Tech Manager | J15: 0.27 | K15: 0.3 | L15: =J15*K15 -> 0.081
B16: Energy Solutions & B2B | C16: 2.5 | D16: 0 | E16: =C16+D16 -> 2.5 | F16: ='1.8 Energy Solutions & B2B'!$C$9 -> 2.5095 | G16: =SUM(E16-F16) -> -0.0095 | I16: Platform overhead subtotal (per platform) | L16: =SUM(L14:L15) -> 0.165
B17: Infrastructure | C17: 2.5 | D17: 0 | E17: =C17+D17 -> 2.5 | F17: ='1.7 Infrastructure'!$C$10 -> 2.5245 | G17: =SUM(E17-F17) -> -0.0245
B18: P&C | C18: 1 | D18: 1 | E18: =C18+D18 -> 2 | F18: ='1.5 P&C'!$C$9 -> 1.2745 | G18: =SUM(E18-F18) -> 0.7255
B19: Finance | C19: 1 | D19: 1 | E19: =C19+D19 -> 2 | F19: ='1.6 Finance'!$C$9 -> 1.4145 | G19: =SUM(E19-F19) -> 0.5855
B20: Legal | C20: 0 | D20: 0 | E20: =C20+D20 -> 0
B21: TDD | C21: 4.5 | D21: 1 | E21: =C21+D21 -> 5.5 | F21: ='1.4 TDD Group Functions'!$C$9 -> 3.6645 | G21: =SUM(E21-F21) -> 1.8355
B22: TDD Data | C22: 2.5 | D22: 1 | E22: =C22+D22 -> 3.5 | F22: ='1.3 Enterprise Data'!$C$9 -> 4.1105 | G22: =SUM(E22-F22) -> -0.6105
B23: TDD Cyber | C23: 2.5 | D23: 1 | E23: =C23+D23 -> 3.5 | F23: ='1.11 TDD Cyber'!$C$9 -> 11.830489 | G23: =SUM(E23-F23) -> -8.330489
B24: EG | C24: 0 | D24: 0 | E24: =C24+D24 -> 0
B25: EGI | C25: 0 | D25: 0 | E25: =C25+D25 -> 0
B26: Total | C26: =SUM(C6:C25) -> 30 | D26: =SUM(D6:D25) -> 13.5 | E26: =SUM(E6:E25) -> 43.5 | F26: =SUM(F6:F25) -> 62.417348 | G26: =SUM(G6:G25) -> -18.917348
B27: Budget | C27: ='0.1 Budget Table (Fin)'!G5 +1 -> 36.2 | D27: ='0.1 Budget Table (Fin)'!G6 -> 17.6 | E27: ='0.1 Budget Table (Fin)'!G14 -> 53.8
B28: Variance | C28: =C27-C26 -> 6.2 | D28: =D27-D26 -> 4.1 | E28: =E27-E26 -> 10.3

Sheet 0.3 Squad Archetypes
C2: Squad Cost Lookup
A4: Key | C4: Squad Type | D4: Size | E4: Archetype | F4: # of roles | G4: Onshore Cost ($m) | H4: Offshore Cost ($m) | I4: Use When | K4: Offshore rate
A5: Engineering|S | C5: Engineering | D5: S | E5: Lean build squad | F5: 4.5 | G5: 0.8 | H5: =G5*$K$5 -> 0.32 | I5: Simple platforms, incremental changes | K5: 0.4
A6: Engineering|M | C6: Engineering | D6: M | E6: Standard Engineering Squad | F6: 9 | G6: 2 | H6: =G6*$K$5 -> 0.8 | I6: Medium complexity platforms
A7: Engineering|L | C7: Engineering | D7: L | E7: High-scale squad | F7: 12 | G7: 2.7 | H7: =G7*$K$5 -> 1.08 | I7: Scalable platforms, high volume output
A8: Configuration / Integration|XS | C8: Configuration / Integration | D8: XS | E8: MS Squad | F8: 1 | G8: 3.2 | H8: =G8*$K$5 -> 1.28 | I8: Work managed by a vendor
A9: Configuration / Integration|S | C9: Configuration / Integration | D9: S | E9: Simple Configuration Squad | F9: 6 | G9: 0.4 | H9: =G9*$K$5 -> 0.16 | I9: Simple configuration, limited integration
A10: Configuration / Integration|M | C10: Configuration / Integration | D10: M | E10: Standard Configuration Squad | F10: 9 | G10: 1.4 | H10: =G10*$K$5 -> 0.56 | I10: Standard configuration, medium complexity
A11: Configuration / Integration|L | C11: Configuration / Integration | D11: L | E11: Complex Integration Squad | F11: 14 | G11: 2.1 | H11: =G11*$K$5 -> 0.84 | I11: Complex config or custom build, high integration
A12: Product|S | C12: Product | D12: S | E12: Lean Product Squad | F12: 5.5 | G12: 1.3 | H12: =G12*$K$5 -> 0.52 | I12: Early stage product testing or low complexity
A13: Product|M | C13: Product | D13: M | E13: Balanced Product Squad | F13: 8.5 | G13: 1.9 | H13: =G13*$K$5 -> 0.76 | I13: Ongoing product development, moderate complexity
A14: Product|L | C14: Product | D14: L | E14: Scaled Product Squad | F14: 12 | G14: 2.8 | H14: =G14*$K$5 -> 1.12 | I14: Mature product
A15: Operations|S | C15: Operations | D15: S | E15: Lean operations squad | F15: 4 | G15: 0.8 | H15: =G15*$K$5 -> 0.32 | I15: Low change, stable platforms
A16: Operations|M | C16: Operations | D16: M | E16: Balanced operations squad | F16: 6 | G16: 1.4 | H16: =G16*$K$5 -> 0.56 | I16: Moderate support plus improvements
A17: Operations|L | C17: Operations | D17: L | E17: High demand operations squad | F17: 10 | G17: 2.3 | H17: =G17*$K$5 -> 0.92 | I17: High ticket volume, critical systems
... A23: Build and Run|L | C23: Build and Run | D23: L | E23: Scaled build and run squad | F23: 13 | G23: 2.8 | H23: =G23*$K$5 -> 1.12 | I23: High traffic or business critical, 24/7
C24: Exceptions (will need to incl. rules) | E24: TBC | I24: TBC
C27: Exception for ES EVCI - 6 FTE vs 4.5 FTE

Sheet 0.4 Presentation Pack
B3: BUSINESS SEGMENTS | C3: TDD GM | D3: TOTAL YTD (Jun-2026) | I3: OPEX: LIGHTS ON + INITIATIVES (YTD) | N3: OPEX: LIGHTS ON (YTD) | S3: OPEX: INITIATIVES (YTD) | X3: OPEX: DEPRECIATION (YTD) | AC3: SIGNIFICANT ITEMS (YTD) | AH3: CAPEX (YTD) | AN3: FY2026
D4: A | E4: B | F4: V | G4: V % | H4: Trend | I4: A | J4: B | K4: V | L4: V % | M4: Trend | N4: A | O4: B | P4: V | R4: Trend | S4: A | T4: B | U4: V | V4: V % | W4: Trend | X4: A | Y4: B | Z4: V | AA4: V % | AB4: Trend | AC4: A | AD4: B | AE4: V | AF4: V % | AG4: Trend | AH4: A | AI4: B | AJ4: V | AK4: V % | AL4: Trend | AN4: F | AO4: B | AP4: V | AR4: Trend
A5: TDD (Corporate)1 | B5: TDD (Corporate)1 | C5: Brad Blyth Greg Cassis | D5: =I5+AC5+AH5+X5 -> 53.575006 | E5: =J5+AD5+AI5+Y5 -> 56.158125 | F5: =E5-D5 -> 2.5831189 | G5: =IFERROR(F5/E5,"-") -> 0.045997243 | H5: G | I5: 41.773797 | J5: 41.933694 | K5: =J5-I5 -> 0.15989672 | L5: =IFERROR(K5/J5,"-") -> 0.0038130846 | M5: G | N5: =I5-S5 -> 40.972956 | O5: =J5-T5 -> 40.433694 | P5: =O5-N5 -> -0.53926205 | Q5: =IFERROR(P5/O5,"-") -> -0.013336947 | R5: A | S5: 0.80084123 | T5: 1.5 | U5: =T5-S5 -> 0.69915877 | V5: =IFERROR(U5/T5,"-") -> 0.46610585 | W5: G | X5: 2.7852211 | Y5: 2.9338979 | Z5: =Y5-X5 -> 0.14867679 | AA5: =IFERROR(Z5/Y5,"-") -> 0.050675516 | AB5: G | AC5: 8.8400082 | AD5: 9.2622 | AE5: =AD5-AC5 -> 0.4221918 | AF5: =IFERROR(AE5/AD5,"-") -> 0.045582237 | AG5: G | AH5: 0.17597979 | AI5: 2.0283334 | AJ5: =AI5-AH5 -> 1.8523536 | AK5: =IFERROR(AJ5/AI5,"-") -> 0.91323922 | AL5: G | AN5: =I21+AC21+AH21+X21 -> 117.95714 | AO5: =J21+AD21+AI21+Y21 -> 112.75951 | AP5: =AO5-AN5 -> -5.1976273 | AQ5: =IFERROR(AP5/AO5,"-") -> -0.046094801 | AR5: A
A6: Z-Energy | B6: Z- Energy | C6: Vance Anderson Harley Giles | D6: =I6+AC6+AH6+X6 -> 35.257858 | E6: =J6+AD6+AI6+Y6 -> 38.25416 | F6: =E6-D6 -> 2.9963016 | G6: =IFERROR(F6/E6,"-") -> 0.078326164 | H6: G | I6: 26.455513 | J6: 26.80099 | K6: =J6-I6 -> 0.34547723 | L6: =IFERROR(K6/J6,"-") -> 0.012890465 | M6: G | N6: =I6-S6 -> 26.455513 | O6: =J6-T6 -> 26.07787 | P6: =O6-N6 -> -0.37764277 | Q6: =IFERROR(P6/O6,"-") -> -0.01448135 | R6: A | S6: 0 | T6: 0.72312 | U6: =T6-S6 -> 0.72312 | V6: =IFERROR(U6/T6,"-") -> 1 | W6: G | X6: 4.8357552 | Y6: 5.1436863 | Z6: =Y6-X6 -> 0.30793102 | AA6: =IFERROR(Z6/Y6,"-") -> 0.059865825 | AB6: G | AC6: 0 | AD6: 0 | AE6: =AD6-AC6 -> 0 | AF6: =IFERROR(AE6/AD6,"-") -> - | AH6: 3.9665899 | AI6: 6.3094833 | AJ6: =AI6-AH6 -> 2.3428933 | AK6: =IFERROR(AJ6/AI6,"-") -> 0.37132888 | AL6: G | AN6: =I22+AC22+AH22+X22 -> 73.108391 | AO6: =J22+AD22+AI22+Y22 -> 76.703514 | AP6: =AO6-AN6 -> 3.5951226 | AQ6: =IFERROR(AP6/AO6,"-") -> 0.046870376 | AR6: G
A7: Commercial Fuels | B7: Commercial Fuels | C7: Roanne Steele | D7: =I7+AC7+AH7+X7 -> 12.401562 | E7: =J7+AD7+AI7+Y7 -> 18.777378 | F7: =E7-D7 -> 6.3758153 | G7: =IFERROR(F7/E7,"-") -> 0.3395477 | H7: G | I7: 7.1072414 | J7: 8.2847223 | K7: =J7-I7 -> 1.1774809 | L7: =IFERROR(K7/J7,"-") -> 0.14212678 | M7: G | N7: =I7-S7 -> 5.0186846 | O7: =J7-T7 -> 5.3538618 | P7: =O7-N7 -> 0.33517727 | Q7: =IFERROR(P7/O7,"-") -> 0.062604767 | R7: G | S7: 2.0885568 | T7: 2.9308605 | U7: =T7-S7 -> 0.84230361 | V7: =IFERROR(U7/T7,"-") -> 0.28739124 | W7: G | Z7: =Y7-X7 -> 0 | AA7: =IFERROR(Z7/Y7,"-") -> - | AC7: 4.7285415 | AD7: 7.109604 | AE7: =AD7-AC7 -> 2.3810625 | AF7: =IFERROR(AE7/AD7,"-") -> 0.3349079 | AG7: G | AH7: 0.56577941 | AI7: 3.3830513 | AJ7: =AI7-AH7 -> 2.8172719 | AK7: =IFERROR(AJ7/AI7,"-") -> 0.83276062 | AL7: G | AN7: =I23+AC23+AH23+X23 -> 32.768998 | AO7: =J23+AD23+AI23+Y23 -> 40.534223 | AP7: =AO7-AN7 -> 7.7652255 | AQ7: =IFERROR(AP7/AO7,"-") -> 0.19157208 | AR7: G
A8: Retail | B8: Retail | C8: Vance Anderson | D8: =I8+AC8+AH8+X8 -> 14.290549 | E8: =J8+AD8+AI8+Y8 -> 18.065295 | F8: =E8-D8 -> 3.7747465 | G8: =IFERROR(F8/E8,"-") -> 0.20895017 | H8: G | I8: 6.854453 | J8: 7.0852951 | K8: =J8-I8 -> 0.23084214 | L8: =IFERROR(K8/J8,"-") -> 0.032580455 | M8: G | N8: =I8-S8 -> 6.4596074 | O8: =J8-T8 -> 6.4302951 | P8: =O8-N8 -> -0.02931227 | Q8: =IFERROR(P8/O8,"-") -> -0.0045584642 | R8: G | S8: 0.39484559 | T8: 0.655 | U8: =T8-S8 -> 0.26015441 | V8: =IFERROR(U8/T8,"-") -> 0.39718231 | W8: G | Z8: =Y8-X8 -> 0 | AA8: =IFERROR(Z8/Y8,"-") -> - | AC8: 3.3546059 | AD8: 5.08 | AE8: =AD8-AC8 -> 1.7253941 | AF8: =IFERROR(AE8/AD8,"-") -> 0.33964451 | AG8: G | AH8: 4.0814897 | AI8: 5.9 | AJ8: =AI8-AH8 -> 1.8185103 | AK8: =IFERROR(AJ8/AI8,"-") -> 0.30822208 | AL8: G | AN8: =I24+AC24+AH24+X24 -> 35.260356 | AO8: =J24+AD24+AI24+Y24 -> 33.880855 | AP8: =AO8-AN8 -> -1.3795012 | AQ8: =IFERROR(AP8/AO8,"-") -> -0.040716245 | AR8: R
A9: Energy Solutions | B9: Energy Solutions | C9: Roanne Steele | D9: =I9+AC9+AH9+X9 -> 4.138504 | E9: =J9+AD9+AI9+Y9 -> 3.8066795 | F9: =E9-D9 -> -0.33182446 | G9: =IFERROR(F9/E9,"-") -> -0.087169002 | H9: R | I9: 2.8789003 | J9: 2.5160191 | K9: =J9-I9 -> -0.36288119 | L9: =IFERROR(K9/J9,"-") -> -0.14422831 | M9: R | N9: =I9-S9 -> 2.5452916 | O9: =J9-T9 -> 2.0310192 | P9: =O9-N9 -> -0.51427247 | Q9: =IFERROR(P9/O9,"-") -> -0.25320907 | R9: R | S9: 0.33360872 | T9: 0.485 | U9: =T9-S9 -> 0.15139128 | V9: =IFERROR(U9/T9,"-") -> 0.31214697 | W9: G | Z9: =Y9-X9 -> 0 | AA9: =IFERROR(Z9/Y9,"-") -> - | AE9: =AD9-AC9 -> 0 | AF9: =IFERROR(AE9/AD9,"-") -> - | AH9: 1.2596037 | AI9: 1.2906604 | AJ9: =AI9-AH9 -> 0.031056732 | AK9: =IFERROR(AJ9/AI9,"-") -> 0.024062667 | AL9: G | AN9: =I25+AC25+AH25+X25 -> 7.830666 | AO9: =J25+AD25+AI25+Y25 -> 8.0095244 | AP9: =AO9-AN9 -> 0.17885836 | AQ9: =IFERROR(AP9/AO9,"-") -> 0.022330709 | AR9: R
A10: Infrastructure | B10: Infrastructure | C10: Roanne Steele | D10: =I10+AC10+AH10+X10 -> 2.6905766 | E10: =J10+AD10+AI10+Y10 -> 4.277083 | F10: =E10-D10 -> 1.5865064 | G10: =IFERROR(F10/E10,"-") -> 0.37093187 | H10: G | I10: 1.7562082 | J10: 1.831374 | K10: =J10-I10 -> 0.07516578 | L10: =IFERROR(K10/J10,"-") -> 0.041043381 | M10: G | N10: =I10-S10 -> 1.4404499 | O10: =J10-T10 -> 1.449693 | P10: =O10-N10 -> 0.00924308 | Q10: =IFERROR(P10/O10,"-") -> 0.0063758879 | R10: G | S10: 0.3157583 | T10: 0.381681 | U10: =T10-S10 -> 0.0659227 | V10: =IFERROR(U10/T10,"-") -> 0.17271675 | W10: G | Z10: =Y10-X10 -> 0 | AA10: =IFERROR(Z10/Y10,"-") -> - | AE10: =AD10-AC10 -> 0 | AF10: =IFERROR(AE10/AD10,"-") -> - | AH10: 0.93436839 | AI10: 2.445709 | AJ10: =AI10-AH10 -> 1.5113406 | AK10: =IFERROR(AJ10/AI10,"-") -> 0.61795602 | AL10: G | AN10: =I26+AC26+AH26+X26 -> 8.4185471 | AO10: =J26+AD26+AI26+Y26 -> 9.249376 | AP10: =AO10-AN10 -> 0.83082882 | AQ10: =IFERROR(AP10/AO10,"-") -> 0.089825392 | AR10: G
A11: Finance & Other Corp | B11: Finance & Other Corp | C11: Emily Mogic | D11: =I11+AC11+AH11+X11 -> 2.8468529 | E11: =J11+AD11+AI11+Y11 -> 2.1223538 | F11: =E11-D11 -> -0.72449911 | G11: =IFERROR(F11/E11,"-") -> -0.34136585 | H11: R | I11: 2.8468529 | J11: 2.1223538 | K11: =J11-I11 -> -0.72449911 | L11: =IFERROR(K11/J11,"-") -> -0.34136585 | M11: R | N11: =I11-S11 -> 2.0786006 | O11: =J11-T11 -> 1.6546105 | P11: =O11-N11 -> -0.42399014 | Q11: =IFERROR(P11/O11,"-") -> -0.25624771 | R11: R | S11: 0.76825227 | T11: 0.4677433 | U11: =T11-S11 -> -0.30050896 | V11: =IFERROR(U11/T11,"-") -> -0.64246556 | W11: R | Z11: =Y11-X11 -> 0 | AA11: =IFERROR(Z11/Y11,"-") -> - | AE11: =AD11-AC11 -> 0 | AF11: =IFERROR(AE11/AD11,"-") -> - | AH11: 0 | AI11: 0 | AJ11: =AI11-AH11 -> 0 | AK11: =IFERROR(AJ11/AI11,"-") -> - | AN11: =I27+AC27+AH27+X27 -> 5.2721119 | AO11: =J27+AD27+AI27+Y27 -> 3.8807737 | AP11: =AO11-AN11 -> -1.3913382 | AQ11: =IFERROR(AP11/AO11,"-") -> -0.35852084 | AR11: G
A12: People & Culture | B12: P&C | C12: Emily Mogic | D12: =I12+AC12+AH12+X12 -> 1.9651397 | E12: =J12+AD12+AI12+Y12 -> 2.460508 | F12: =E12-D12 -> 0.49536834 | G12: =IFERROR(F12/E12,"-") -> 0.20132767 | H12: G | I12: 1.6178184 | J12: 1.860608 | K12: =J12-I12 -> 0.2427896 | L12: =IFERROR(K12/J12,"-") -> 0.13048939 | M12: G | N12: =I12-S12 -> 0.70035539 | O12: =J12-T12 -> 0.87310804 | P12: =O12-N12 -> 0.17275265 | Q12: =IFERROR(P12/O12,"-") -> 0.19785942 | R12: G | S12: 0.91746305 | T12: 0.9875 | U12: =T12-S12 -> 0.07003695 | V12: =IFERROR(U12/T12,"-") -> 0.070923494 | W12: G | Z12: =Y12-X12 -> 0 | AA12: =IFERROR(Z12/Y12,"-") -> - | AC12: 0.34732126 | AD12: 0.4624 | AE12: =AD12-AC12 -> 0.11507874 | AF12: =IFERROR(AE12/AD12,"-") -> 0.24887271 | AG12: G | AH12: 0 | AI12: 0.1375 | AJ12: =AI12-AH12 -> 0.1375 | AK12: =IFERROR(AJ12/AI12,"-") -> 1 | AL12: G | AN12: =I28+AC28+AH28+X28 -> 5.4932256 | AO12: =J28+AD28+AI28+Y28 -> 5.813038 | AP12: =AO12-AN12 -> 0.31981243 | AQ12: =IFERROR(AP12/AO12,"-") -> 0.055016401 | AR12: G
A13: Customer | B13: Customer | C13: Harley Giles | D13: =I13+AC13+AH13+X13 -> 2.4105283 | E13: =J13+AD13+AI13+Y13 -> 5.4047457 | F13: =E13-D13 -> 2.9942174 | G13: =IFERROR(F13/E13,"-") -> 0.55399783 | H13: G | I13: 0.98861064 | J13: 0.82141236 | K13: =J13-I13 -> -0.16719828 | L13: =IFERROR(K13/J13,"-") -> -0.20354975 | M13: R | N13: =I13-S13 -> 0.98861064 | O13: =J13-T13 -> 0.82141236 | P13: =O13-N13 -> -0.16719828 | Q13: =IFERROR(P13/O13,"-") -> -0.20354975 | R13: R | S13: 0 | T13: 0 | U13: =T13-S13 -> 0 | V13: =IFERROR(U13/T13,"-") -> - | Z13: =Y13-X13 -> 0 | AA13: =IFERROR(Z13/Y13,"-") -> - | AC13: 0 | AD13: 2.5 | AE13: =AD13-AC13 -> 2.5 | AF13: =IFERROR(AE13/AD13,"-") -> 1 | AG13: G | AH13: 1.4219177 | AI13: 2.0833333 | AJ13: =AI13-AH13 -> 0.66141564 | AK13: =IFERROR(AJ13/AI13,"-") -> 0.31747951 | AL13: G | AN13: =I29+AC29+AH29+X29 -> 10.983783 | AO13: =J29+AD29+AI29+Y29 -> 11.691533 | AP13: =AO13-AN13 -> 0.70775018 | AQ13: =IFERROR(AP13/AO13,"-") -> 0.060535277 | AR13: G
B14: Total Technology | D14: =SUM(D5:D13) -> 129.57658 | E14: =SUM(E5:E13) -> 149.32633 | F14: =SUM(F5:F13) -> 19.749751 | G14: =F14/E14 -> 0.132259 | H14: G | I14: =SUM(I5:I13) -> 92.279395 | J14: =SUM(J5:J13) -> 93.256469 | K14: =SUM(K5:K13) -> 0.97707378 | L14: =K14/J14 -> 0.010477276 | M14: G | N14: =SUM(N5:N13) -> 86.660069 | O14: =SUM(O5:O13) -> 85.125564 | P14: =SUM(P5:P13) -> -1.534505 | Q14: =P14/O14 -> -0.018026371 | R14: A | S14: =SUM(S5:S13) -> 5.619326 | T14: =SUM(T5:T13) -> 8.1309048 | U14: =SUM(U5:U13) -> 2.5115788 | V14: =U14/T14 -> 0.3088929 | W14: G | X14: =SUM(X5:X13) -> 7.6209764 | Y14: =SUM(Y5:Y13) -> 8.0775842 | Z14: =SUM(Z5:Z13) -> 0.45660781 | AA14: =Z14/Y14 -> 0.056527769 | AB14: G | AC14: =SUM(AC5:AC13) -> 17.270477 | AD14: =SUM(AD5:AD13) -> 24.414204 | AE14: =SUM(AE5:AE13) -> 7.1437272 | AF14: =AE14/AD14 -> 0.29260537 | AG14: G | AH14: =SUM(AH5:AH13) -> 12.405729 | AI14: =SUM(AI5:AI13) -> 23.578071 | AJ14: =SUM(AJ5:AJ13) -> 11.172342 | AK14: =AJ14/AI14 -> 0.47384463 | AL14: G | AN14: =SUM(AN5:AN13) -> 297.09322 | AO14: =SUM(AO5:AO13) -> 302.52235 | AP14: =SUM(AP5:AP13) -> 5.4291311 | AQ14: =AP14/AO14 -> 0.017946215 | AR14: G
F15: =F14/E14 -> 0.132259 | I15: =I14/$D14 -> 0.71216108 | J15: ` | K15: =K14/J14 -> 0.010477276 | N15: =N14/$D14 -> 0.66879425 | P15: =P14/O14 -> -0.018026371 | S15: =S14/$D14 -> 0.043366835 | U15: =U14/T14 -> 0.3088929 | X15: =X14/$D14 -> 0.05881446 | Z15: =Z14/Y14 -> 0.056527769 | AC15: =AC14/$D14 -> 0.13328394 | AE15: =AE14/AD14 -> 0.29260537 | AH15: =AH14/$D14 -> 0.095740518 | AJ15: =AJ14/AI14 -> 0.47384463
B19: BUSINESS SEGMENTS | C19: TDD GM | D19: FY2026 - TOTAL | I19: OPEX: LIGHTS ON + INITIATIVES | N19: OPEX:LIGHTS ON | S19: OPEX: INITIATIVES | X19: OPEX: DEPRECIATION | AC19: OPEX: SIGNIFICANT ITEMS | AH19: CAPEX
D20: F | E20: B | F20: V | G20: V % | H20: Trend | I20: F | J20: B | K20: V | L20: V % | M20: Trend | N20: F | O20: B | P20: V | Q20: V % | R20: Trend | S20: F | T20: B | U20: V | V20: V % | W20: Trend | X20: F | Y20: B | Z20: V | AA20: V % | AB20: Trend | AC20: F | AD20: B | AE20: V | AF20: V % | AG20: Trend | AH20: F | AI20: B | AJ20: V | AK20: V % | AL20: Trend
A21: TDD (Corporate)1 | B21: TDD (Corporate)1 | C21: Brad Blyth Greg Cassis | D21: =I21+AC21+AH21+X21 -> 117.95714 | E21: =J21+AD21+AI21+Y21 -> 112.75951 | F21: =E21-D21 -> -5.1976273 | G21: =IFERROR(F21/E21,"-") -> -0.046094801 | H21: R | I21: 82.087877 | J21: 81.894863 | K21: =J21-I21 -> -0.19301366 | L21: =IFERROR(K21/J21,"-") -> -0.002356847 | M21: G | N21: =I21-S21 -> 79.310436 | O21: =J21-T21 -> 78.894863 | P21: =O21-N21 -> -0.41557243 | Q21: =IFERROR(P21/O21,"-") -> -0.0052674206 | R21: A | S21: 2.7774412 | T21: 3 | U21: =T21-S21 -> 0.22255877 | V21: =IFERROR(U21/T21,"-") -> 0.074186257 | W21: G | X21: 5.6865111 | Y21: 5.8000499 | Z21: =Y21-X21 -> 0.11353882 | AA21: =IFERROR(Z21/Y21,"-") -> 0.01957549 | AB21: G | AC21: 25.395773 | AD21: 20.1966 | AE21: =AD21-AC21 -> -5.1991726 | AF21: =IFERROR(AE21/AD21,"-") -> -0.25742811 | AG21: R | AH21: 4.7869798 | AI21: 4.868 | AJ21: =AI21-AH21 -> 0.08102017 | AK21: =IFERROR(AJ21/AI21,"-") -> 0.01664342 | AL21: G | AM21: =I21+X21 -> 87.774388 | AN21: input retail SI number manually
A22: Z-Energy | B22: Z- Energy | C22: Vance Anderson Harley Giles | D22: =I22+AC22+AH22+X22 -> 73.108391 | E22: =J22+AD22+AI22+Y22 -> 76.703514 | F22: =E22-D22 -> 3.5951226 | G22: =IFERROR(F22/E22,"-") -> 0.046870376 | H22: G | I22: 53.465434 | J22: 53.6715 | K22: =J22-I22 -> 0.20606573 | L22: =IFERROR(K22/J22,"-") -> 0.0038393884 | M22: G | N22: =I22-S22 -> 53.465434 | O22: =J22-T22 -> 52.22526 | P22: =O22-N22 -> -1.2401743 | Q22: =IFERROR(P22/O22,"-") -> -0.023746637 | R22: A | S22: 0 | T22: 1.44624 | U22: =T22-S22 -> 1.44624 | V22: =IFERROR(U22/T22,"-") -> 1 | W22: G | X22: 10.161498 | Y22: 11.306521 | Z22: =Y22-X22 -> 1.1450224 | AA22: =IFERROR(Z22/Y22,"-") -> 0.10127098 | AB22: G | AC22: 0 | AD22: 0 | AE22: =AD22-AC22 -> 0 | AF22: =IFERROR(AE22/AD22,"-") -> - | AH22: 9.4814594 | AI22: 11.725494 | AJ22: =AI22-AH22 -> 2.2440344 | AK22: =IFERROR(AJ22/AI22,"-") -> 0.1913808 | AL22: G | AM22: =I22+X22 -> 63.626932
A23: Commercial Fuels | B23: Commercial Fuels | C23: Roanne Steele | D23: =I23+AC23+AH23+X23 -> 32.768998 | E23: =J23+AD23+AI23+Y23 -> 40.534223 | F23: =E23-D23 -> 7.7652255 | G23: =IFERROR(F23/E23,"-") -> 0.19157208 | H23: G | I23: 18.07582 | J23: 19.517302 | K23: =J23-I23 -> 1.4414818 | L23: =IFERROR(K23/J23,"-") -> 0.073856612 | M23: G | N23: =I23-S23 -> 12.122014 | O23: =J23-T23 -> 13.655581 | P23: =O23-N23 -> 1.533567 | Q23: =IFERROR(P23/O23,"-") -> 0.11230331 | R23: G | S23: 5.9538061 | T23: 5.8617209 | U23: =T23-S23 -> -0.092085221 | V23: =IFERROR(U23/T23,"-") -> -0.015709588 | W23: A | Z23: =Y23-X23 -> 0 | AA23: =IFERROR(Z23/Y23,"-") -> - | AC23: 8.927316 | AD23: 14.219208 | AE23: =AD23-AC23 -> 5.291892 | AF23: =IFERROR(AE23/AD23,"-") -> 0.37216503 | AG23: G | AH23: 5.7658612 | AI23: 6.7977128 | AJ23: =AI23-AH23 -> 1.0318517 | AK23: =IFERROR(AJ23/AI23,"-") -> 0.15179395 | AL23: G
A24: Retail | B24: Retail | C24: Vance Anderson | D24: =I24+AC24+AH24+X24 -> 35.260356 | E24: =J24+AD24+AI24+Y24 -> 33.880855 | F24: =E24-D24 -> -1.3795012 | G24: =IFERROR(F24/E24,"-") -> -0.040716245 | H24: A | I24: 15.230723 | J24: 15.235855 | K24: =J24-I24 -> 0.0051319 | L24: =IFERROR(K24/J24,"-") -> 0.00033683047 | M24: G | N24: =I24-S24 -> 14.481085 | O24: =J24-T24 -> 13.925855 | P24: =O24-N24 -> -0.55523051 | Q24: =IFERROR(P24/O24,"-") -> -0.03987048 | R24: A | S24: 0.74963759 | T24: 1.31 | U24: =T24-S24 -> 0.56036241 | V24: =IFERROR(U24/T24,"-") -> 0.42775756 | W24: G | Z24: =Y24-X24 -> 0 | AA24: =IFERROR(Z24/Y24,"-") -> - | AC24: 8.64 | AD24: 6.845 | AE24: =AD24-AC24 -> -1.795 | AF24: =IFERROR(AE24/AD24,"-") -> -0.26223521 | AG24: R | AH24: 11.389633 | AI24: 11.8 | AJ24: =AI24-AH24 -> 0.41036692 | AK24: =IFERROR(AJ24/AI24,"-") -> 0.034776858 | AL24: G
A25: Energy Solutions | B25: Energy Solutions | C25: Roanne Steele | D25: =I25+AC25+AH25+X25 -> 7.830666 | E25: =J25+AD25+AI25+Y25 -> 8.0095244 | F25: =E25-D25 -> 0.17885836 | G25: =IFERROR(F25/E25,"-") -> 0.022330709 | H25: G | I25: 5.0440983 | J25: 5.0119394 | K25: =J25-I25 -> -0.0321589 | L25: =IFERROR(K25/J25,"-") -> -0.0064164582 | M25: A | N25: =I25-S25 -> 4.5362156 | O25: =J25-T25 -> 4.0419395 | P25: =O25-N25 -> -0.49427618 | Q25: =IFERROR(P25/O25,"-") -> -0.12228688 | R25: R | S25: 0.50788272 | T25: 0.97 | U25: =T25-S25 -> 0.46211728 | V25: =IFERROR(U25/T25,"-") -> 0.47640957 | W25: G | Z25: =Y25-X25 -> 0 | AA25: =IFERROR(Z25/Y25,"-") -> - | AE25: =AD25-AC25 -> 0 | AF25: =IFERROR(AE25/AD25,"-") -> - | AH25: 2.7865677 | AI25: 2.9975849 | AJ25: =AI25-AH25 -> 0.21101726 | AK25: =IFERROR(AJ25/AI25,"-") -> 0.070395758 | AL25: G
A26: Infrastructure | B26: Infrastructure | C26: Roanne Steele | D26: =I26+AC26+AH26+X26 -> 8.4185471 | E26: =J26+AD26+AI26+Y26 -> 9.249376 | F26: =E26-D26 -> 0.83082882 | G26: =IFERROR(F26/E26,"-") -> 0.089825392 | H26: G | I26: 4.2749786 | J26: 4.357958 | K26: =J26-I26 -> 0.08297936 | L26: =IFERROR(K26/J26,"-") -> 0.019040881 | M26: G | N26: =I26-S26 -> 3.3010253 | O26: =J26-T26 -> 3.594596 | P26: =O26-N26 -> 0.29357066 | Q26: =IFERROR(P26/O26,"-") -> 0.081670001 | R26: G | S26: 0.9739533 | T26: 0.763362 | U26: =T26-S26 -> -0.2105913 | V26: =IFERROR(U26/T26,"-") -> -0.27587344 | W26: R | Z26: =Y26-X26 -> 0 | AA26: =IFERROR(Z26/Y26,"-") -> - | AE26: =AD26-AC26 -> 0 | AF26: =IFERROR(AE26/AD26,"-") -> - | AH26: 4.1435685 | AI26: 4.891418 | AJ26: =AI26-AH26 -> 0.74784946 | AK26: =IFERROR(AJ26/AI26,"-") -> 0.15289012 | AL26: G
A27: Finance & Other Corp | B27: Finance & Other Corp | C27: Emily Mogic | D27: =I27+AC27+AH27+X27 -> 5.2721119 | E27: =J27+AD27+AI27+Y27 -> 3.8807737 | F27: =E27-D27 -> -1.3913382 | G27: =IFERROR(F27/E27,"-") -> -0.35852084 | H27: R | I27: 5.2721119 | J27: 3.8807737 | K27: =J27-I27 -> -1.3913382 | L27: =IFERROR(K27/J27,"-") -> -0.35852084 | M27: R | N27: =I27-S27 -> 4.3588956 | O27: =J27-T27 -> 2.9452871 | P27: =O27-N27 -> -1.4136086 | Q27: =IFERROR(P27/O27,"-") -> -0.47995613 | R27: R | S27: 0.91321627 | T27: 0.93548661 | U27: =T27-S27 -> 0.02227034 | V27: =IFERROR(U27/T27,"-") -> 0.023806156 | W27: G | Z27: =Y27-X27 -> 0 | AA27: =IFERROR(Z27/Y27,"-") -> - | AE27: =AD27-AC27 -> 0 | AF27: =IFERROR(AE27/AD27,"-") -> - | AH27: 0 | AI27: 0 | AJ27: =AI27-AH27 -> 0 | AK27: =IFERROR(AJ27/AI27,"-") -> - | AL27: G
A28: People & Culture | B28: P&C | C28: Emily Mogic | D28: =I28+AC28+AH28+X28 -> 5.4932256 | E28: =J28+AD28+AI28+Y28 -> 5.813038 | F28: =E28-D28 -> 0.31981243 | G28: =IFERROR(F28/E28,"-") -> 0.055016401 | H28: G | I28: 3.8516861 | J28: 4.123038 | K28: =J28-I28 -> 0.27135188 | L28: =IFERROR(K28/J28,"-") -> 0.065813577 | M28: G | N28: =I28-S28 -> 1.9121353 | O28: =J28-T28 -> 2.148038 | P28: =O28-N28 -> 0.23590273 | Q28: =IFERROR(P28/O28,"-") -> 0.10982242 | R28: G | S28: 1.9395508 | T28: 1.975 | U28: =T28-S28 -> 0.035449154 | V28: =IFERROR(U28/T28,"-") -> 0.017948939 | W28: G | Z28: =Y28-X28 -> 0 | AA28: =IFERROR(Z28/Y28,"-") -> - | AC28: 1.3115394 | AD28: 1.36 | AE28: =AD28-AC28 -> 0.04846055 | AF28: =IFERROR(AE28/AD28,"-") -> 0.035632757 | AG28: G | AH28: 0.33 | AI28: 0.33 | AJ28: =AI28-AH28 -> 0 | AK28: =IFERROR(AJ28/AI28,"-") -> 0 | AL28: G
A29: Customer | B29: Customer | C29: Harley Giles | D29: =I29+AC29+AH29+X29 -> 10.983783 | E29: =J29+AD29+AI29+Y29 -> 11.691533 | F29: =E29-D29 -> 0.70775018 | G29: =IFERROR(F29/E29,"-") -> 0.060535277 | H29: G | I29: 2.74505 | J29: 1.6915328 | K29: =J29-I29 -> -1.0535172 | L29: =IFERROR(K29/J29,"-") -> -0.62281806 | M29: R | N29: =I29-S29 -> 2.74505 | O29: =J29-T29 -> 1.6915328 | P29: =O29-N29 -> -1.0535172 | Q29: =IFERROR(P29/O29,"-") -> -0.62281806 | R29: R | S29: 0 | T29: 0 | U29: =T29-S29 -> 0 | V29: =IFERROR(U29/T29,"-") -> - | Z29: =Y29-X29 -> 0 | AA29: =IFERROR(Z29/Y29,"-") -> - | AC29: 3.832387 | AD29: 5 | AE29: =AD29-AC29 -> 1.1676131 | AF29: =IFERROR(AE29/AD29,"-") -> 0.23352261 | AG29: G | AH29: 4.4063457 | AI29: 5 | AJ29: =AI29-AH29 -> 0.59365431 | AK29: =IFERROR(AJ29/AI29,"-") -> 0.11873086 | AL29: G
B30: Total Technology | D30: =SUM(D21:D29) -> 297.09322 | E30: =SUM(E21:E29) -> 302.52235 | F30: =SUM(F21:F29) -> 5.4291311 | G30: =F30/E30 -> 0.017946215 | H30: G | I30: =SUM(I21:I29) -> 190.04778 | J30: =SUM(J21:J29) -> 189.38476 | K30: =SUM(K21:K29) -> -0.66301729 | L30: =K30/J30 -> -0.0035009009 | M30: A | N30: =SUM(N21:N29) -> 176.23229 | O30: =SUM(O21:O29) -> 173.12295 | P30: =SUM(P21:P29) -> -3.1093387 | Q30: =P30/O30 -> -0.017960292 | R30: A | S30: =SUM(S21:S29) -> 13.815488 | T30: =SUM(T21:T29) -> 16.26181 | U30: =SUM(U21:U29) -> 2.4463214 | V30: =U30/T30 -> 0.15043353 | W30: G | X30: =SUM(X21:X29) -> 15.848009 | Y30: =SUM(Y21:Y29) -> 17.10657 | Z30: =SUM(Z21:Z29) -> 1.2585612 | AA30: =Z30/Y30 -> 0.073571802 | AB30: G | AC30: =SUM(AC21:AC29) -> 48.107015 | AD30: =SUM(AD21:AD29) -> 47.620808 | AE30: =SUM(AE21:AE29) -> -0.48620701 | AF30: =AE30/AD30 -> -0.01020997 | AG30: A | AH30: =SUM(AH21:AH29) -> 43.090415 | AI30: =SUM(AI21:AI29) -> 48.41021 | AJ30: =SUM(AJ21:AJ29) -> 5.3197942 | AK30: =AJ30/AI30 -> 0.10988992 | AL30: G
I31: =I30/$D30 -> 0.63969073 | N31: =N30/$D30 -> 0.59318853 | S31: =S30/$D30 -> 0.046502199 | X31: =X30/$D30 -> 0.053343558 | AC31: =AC30/$D30 -> 0.16192566 | AH31: =AH30/$D30 -> 0.14504005
AO32: =E30-297 -> 5.5223497
D35: =D3 -> TOTAL YTD (Jun-2026) | I35: TOTAL TECHNOLOGY Full Year 2026
B36: Spend Type | D36: A | E36: B | F36: V | G36: V % | H36: Trend | I36: F | J36: B | K36: V | L36: V % | M36: Trend
B37: Lights on | D37: =N14 -> 86.660069 | E37: =O14 -> 85.125564 | F37: =E37-D37 -> -1.534505 | G37: =IFERROR(F37/E37,"-") -> -0.018026371 | H37: A | I37: =N30 -> 176.23229 | J37: =O30 -> 173.12295 | K37: =J37-I37 -> -3.1093387 | L37: =IFERROR(K37/J37,"-") -> -0.017960292 | M37: A
B38: Depreciation | D38: =X14 -> 7.6209764 | E38: =Y14 -> 8.0775842 | F38: =E38-D38 -> 0.45660781 | G38: =IFERROR(F38/E38,"-") -> 0.056527769 | H38: G | I38: =X30 -> 15.848009 | J38: =Y30 -> 17.10657 | K38: =J38-I38 -> 1.2585612 | L38: =IFERROR(K38/J38,"-") -> 0.073571802 | M38: G
B39: Lights on + Depreciation | D39: =SUM(D37:D38) -> 94.281045 | E39: =SUM(E37:E38) -> 93.203148 | F39: =SUM(F37:F38) -> -1.0778972 | G39: =IFERROR(F39/E39,"-") -> -0.01156503 | H39: A | I39: =SUM(I37:I38) -> 192.0803 | J39: =SUM(J37:J38) -> 190.22952 | K39: =SUM(K37:K38) -> -1.8507775 | L39: =IFERROR(K39/J39,"-") -> -0.0097291812 | M39: A
B40: Opex Initiatives | D40: =S14 -> 5.619326 | E40: =T14 -> 8.1309048 | F40: =E40-D40 -> 2.5115788 | G40: =IFERROR(F40/E40,"-") -> 0.3088929 | H40: G | I40: =S30 -> 13.815488 | J40: =T30 -> 16.26181 | K40: =J40-I40 -> 2.4463214 | L40: =IFERROR(K40/J40,"-") -> 0.15043353 | M40: G
B41: Capex | D41: =AH14 -> 12.405729 | E41: =AI14 -> 23.578071 | F41: =E41-D41 -> 11.172342 | G41: =IFERROR(F41/E41,"-") -> 0.47384463 | H41: G | I41: =AH30 -> 43.090415 | J41: =AI30 -> 48.41021 | K41: =J41-I41 -> 5.3197942 | L41: =IFERROR(K41/J41,"-") -> 0.10988992 | M41: G
B42: Significant Items | D42: =AC14 -> 17.270477 | E42: =AD14 -> 24.414204 | F42: =E42-D42 -> 7.1437272 | G42: =IFERROR(F42/E42,"-") -> 0.29260537 | H42: G | I42: =AC30 -> 48.107015 | J42: =AD30 -> 47.620808 | K42: =J42-I42 -> -0.48620701 | L42: =IFERROR(K42/J42,"-") -> -0.01020997 | M42: A
B43: Projects | D43: =SUM(D40:D42) -> 35.295531 | E43: =SUM(E40:E42) -> 56.123179 | F43: =SUM(F40:F42) -> 20.827648 | G43: =IFERROR(F43/E43,"-") -> 0.37110599 | H43: G | I43: =SUM(I40:I42) -> 105.01292 | J43: =SUM(J40:J42) -> 112.29283 | K43: =SUM(K40:K42) -> 7.2799086 | L43: =IFERROR(K43/J43,"-") -> 0.064829685 | M43: G
B44: Total Technology | D44: =SUM(D43,D39) -> 129.57658 | E44: =SUM(E43,E39) -> 149.32633 | F44: =SUM(F43,F39) -> 19.749751 | G44: =IFERROR(F44/E44,"-") -> 0.132259 | H44: G | I44: =SUM(I43,I39) -> 297.09322 | J44: =SUM(J43,J39) -> 302.52235 | K44: =SUM(K43,K39) -> 5.4291311 | L44: =IFERROR(K44/J44,"-") -> 0.017946215 | M44: G
B47: SPEND CATEGORY | D47: =D3 -> TOTAL YTD (Jun-2026) | I47: TOTAL TECHNOLOGY YTD (May-2026)
D48: A | E48: B | F48: V | G48: V % | H48: Trend | I48: A | J48: B | K48: V | L48: V % | M48: Trend
B49: Opex | D49: =I14+X14 -> 99.900371 | E49: =J14+Y14 -> 101.33405 | F49: =E49-D49 -> 1.4336816 | G49: =IFERROR(F49/E49,"-") -> 0.014148073 | H49: G | I49: =I30+X30 -> 205.89579 | J49: =J30+Y30 -> 206.49133 | K49: =J49-I49 -> 0.59554393 | L49: =IFERROR(K49/J49,"-") -> 0.002884111 | M49: G
B50: Significant Items | D50: =AC14 -> 17.270477 | E50: =AD14 -> 24.414204 | F50: =E50-D50 -> 7.1437272 | G50: =IFERROR(F50/E50,"-") -> 0.29260537 | H50: G | I50: =AC30 -> 48.107015 | J50: =AD30 -> 47.620808 | K50: =J50-I50 -> -0.48620701 | L50: =IFERROR(K50/J50,"-") -> -0.01020997 | M50: A
B51: Capex | D51: =AH14 -> 12.405729 | E51: =AI14 -> 23.578071 | F51: =E51-D51 -> 11.172342 | G51: =IFERROR(F51/E51,"-") -> 0.47384463 | H51: G | I51: =AH30 -> 43.090415 | J51: =AI30 -> 48.41021 | K51: =J51-I51 -> 5.3197942 | L51: =IFERROR(K51/J51,"-") -> 0.10988992 | M51: G
B52: Total Technology | D52: =SUM(D49:D51) -> 129.57658 | E52: =SUM(E49:E51) -> 149.32633 | F52: =SUM(F49:F51) -> 19.749751 | G52: =IFERROR(F52/E52,"-") -> 0.132259 | H52: G | I52: =SUM(I49:I51) -> 297.09322 | J52: =SUM(J49:J51) -> 302.52235 | K52: =SUM(K49:K51) -> 5.4291311 | L52: =IFERROR(K52/J52,"-") -> 0.017946215 | M52: G

Sheet - DESIGNS -
B2: DESIGNS >>>

Sheet 1.1 Ampol Retail
B2: Ampol Retail
B4: Portfolio Summary | G4: Budget vs TDD Cost
B5: Cost | C5: TDD ($m) | D5: Other ($m) | E5: Total Retail Cost ($m) | G5: TDD Lights On Budget (people - 0.2 Data Config) | H5: ='0.2 Data Config'!$E$11 -> 2.5
B6: Portfolio Overhead (see 0.2 Data Config) | C6: ='0.2 Data Config'!$L$10 -> 0.7495 | E6: =C6 -> 0.7495 | G6: Overheads & Support (this model) | H6: =C9 -> 5.6265
B7: Platform Overheads | C7: =SUM(H27,H34,H47,H53,H59) -> 0.825 | E7: =C7 -> 0.825 | G7: Variance (budget less cost) | H7: =H5-H6 -> -3.1265
B8: Squad Support Costs | C8: =SUM(H23,H24,H25,H26,H32,H33,H46,H52,H58,H64) -> 4.052 | D8: =SUM(I23,I24,I25,I26,I32,I33,I46,I52,I58,I64) -> 4.728 | E8: =C8+D8 -> 8.78
B9: Total Cost | C9: =SUM(C6:C8) -> 5.6265 | D9: =SUM(D6:D8) -> 4.728 | E9: =C9+D9 -> 10.3545
G10: Other funding
B11: Total Retail budget | E11: =SUM(H12:H16) -> 33.8 | G11: Budget line | H11: Budget ($m) | I11: Amount that can be allocated to people | J11: Remaining for non-people ($m)
B12: Reconciled to Finance | E12: ='0.1 Budget Table (Fin)'!Q9 -> 33.8 | G12: Retail Lights On | H12: ='0.1 Budget Table (Fin)'!L9 -> 13.9 | I12: ='0.1 Budget Table (Fin)'!G9 -> 0 | J12: =IFERROR(H12-I12,0) -> 13.9
G13: OpEx Initiatives | H13: ='0.1 Budget Table (Fin)'!N9 -> 1.3 | I13: 0 | J13: =IFERROR(H13-I13,0) -> 1.3
B14: Total to fund | G14: Retail CapEx | H14: ='0.1 Budget Table (Fin)'!P9 -> 11.8 | J14: =IFERROR(H14-I14,0) -> 11.8
B15: TDD Variance | C15: =MAX(0,-H7) -> 3.1265 | G15: Significant Items | H15: ='0.1 Budget Table (Fin)'!O9 -> 6.8 | I15: =I46 -> 0 | J15: =IFERROR(H15-I15,0) -> 6.8
B16: Other Variance | C16: =MAX(0,I19) -> 4.728 | G16: Significant Items EGI | I16: =I64 -> 0
B17: Total | C17: =C15+C16 -> 7.8545 | G17: Total applied | I17: =SUM(I12:I16) -> 0
G18: Other cost (this model) | I18: =D9 -> 4.728
G19: Left to fund | I19: =I18-I17 -> 4.728
B21: Platform: Store Operations
B22: Squad | C22: Squad Type | D22: Size | E22: On/Off | F22: Support % | G22: Total Squad Cost ($m) | H22: TDD Cost ($m) | I22: Funded outside TDD ($m) | K22: Fund
B23: POS | C23: Configuration / Integration | D23: M | E23: Onshore | F23: 0.7 | G23: =IFERROR(IF($E23="Onshore",INDEX('0.3 Squad Archetypes'!$G$5:$G$23,MATCH($C23&"|"&$D23,'0.3 Squad Archetypes'!$A$5:$A$23,0)),INDEX('0.3 Squad Archetypes'!$H$5:$H$23,MATCH($C23&"|"&$D23,'0.3 Squad Archetypes'!$A$5:$A$23,0))),"check size") -> 1.4 | H23: =IFERROR($G23*$F23,"") -> 0.98 | I23: =IFERROR($G23*(1-$F23),"") -> 0.42 | K23: AU
B24: Payments | C24: Configuration / Integration | D24: S | E24: Onshore | F24: 0.2 | G24: =IFERROR(IF($E24="Onshore",INDEX('0.3 Squad Archetypes'!$G$5:$G$23,MATCH($C24&"|"&$D24,'0.3 Squad Archetypes'!$A$5:$A$23,0)),INDEX('0.3 Squad Archetypes'!$H$5:$H$23,MATCH($C24&"|"&$D24,'0.3 Squad Archetypes'!$A$5:$A$23,0))),"check size") -> 0.4 | H24: =IFERROR($G24*$F24,"") -> 0.08 | I24: =IFERROR($G24*(1-$F24),"") -> 0.32 | K24: AU
B25: Store Operations | C25: Operations | D25: M | E25: Onshore | F25: 1 | G25: =IFERROR(IF($E25="Onshore",INDEX('0.3 Squad Archetypes'!$G$5:$G$23,MATCH($C25&"|"&$D25,'0.3 Squad Archetypes'!$A$5:$A$23,0)),INDEX('0.3 Squad Archetypes'!$H$5:$H$23,MATCH($C25&"|"&$D25,'0.3 Squad Archetypes'!$A$5:$A$23,0))),"check size") -> 1.4 | H25: =IFERROR($G25*$F25,"") -> 1.4 | I25: =IFERROR($G25*(1-$F25),"") -> 0 | K25: AU
B26: Deployment | C26: Configuration / Integration | D26: M | E26: Onshore | F26: 0.2 | G26: =IFERROR(IF($E26="Onshore",INDEX('0.3 Squad Archetypes'!$G$5:$G$23,MATCH($C26&"|"&$D26,'0.3 Squad Archetypes'!$A$5:$A$23,0)),INDEX('0.3 Squad Archetypes'!$H$5:$H$23,MATCH($C26&"|"&$D26,'0.3 Squad Archetypes'!$A$5:$A$23,0))),"check size") -> 1.4 | H26: =IFERROR($G26*$F26,"") -> 0.28 | I26: =IFERROR($G26*(1-$F26),"") -> 1.12 | K26: AU
B27: Platform Overhead | H27: ='0.2 Data Config'!$L$16 -> 0.165
B28: Store Operations Total | G28: =SUM(G23:G26) -> 4.6 | H28: =SUM(H23:H27) -> 2.905 | I28: =SUM(I23:I26) -> 1.86
B30: Platform: Above Store
B31: Squad | C31: Squad Type | D31: Size | E31: On/Off | F31: Support % | G31: Total Squad Cost ($m) | H31: TDD Cost ($m) | I31: Funded outside TDD ($m) | K31: Fund
B32: Above Store | C32: Configuration / Integration | D32: L | E32: Onshore | F32: 0.2 | G32: =IFERROR(IF($E32="Onshore",INDEX('0.3 Squad Archetypes'!$G$5:$G$23,MATCH($C32&"|"&$D32,'0.3 Squad Archetypes'!$A$5:$A$23,0)),INDEX('0.3 Squad Archetypes'!$H$5:$H$23,MATCH($C32&"|"&$D32,'0.3 Squad Archetypes'!$A$5:$A$23,0))),"check size") -> 2.1 | H32: =IFERROR($G32*$F32,"") -> 0.42 | I32: =IFERROR($G32*(1-$F32),"") -> 1.68 | K32: AU
J33: Will combine - takes out 4 roles. New platform Above Store & new squad Above Store
B34: Platform Overhead | H34: ='0.2 Data Config'!$L$16 -> 0.165
B35: Above Store Total | G35: =SUM(G32:G33) -> 2.1 | H35: =SUM(H32:H34) -> 0.585 | I35: =SUM(I32:I33) -> 1.68
B37: Platform: Pricing & WFM - combined into Above Store
B38: Squad | C38: Squad Type | D38: Size | E38: On/Off | F38: Support % | G38: Total Squad Cost ($m) | H38: TDD Cost ($m) | I38: Funded outside TDD ($m)
B41: Platform Overhead
B42: (combined into Above Store)
B44: Platform: AmPOS
B45: Squad | C45: Squad Type | D45: Size | E45: On/Off | F45: Support % | G45: Total Squad Cost ($m) | H45: TDD Cost ($m) | I45: Funded outside TDD ($m) | K45: Fund
B46: AmPOS | C46: Strategic Programs | E46: Onshore | F46: 0 | G46: 0 | H46: =IFERROR($G46*$F46,"") -> 0 | I46: =IFERROR($G46*(1-$F46),"") -> 0 | J46: Change this to strat projects; impact on price | K46: AU | L46: 7 FTE in AmPOS
B47: Platform Overhead | H47: ='0.2 Data Config'!$L$16 -> 0.165 | J47: Take some roles from POS and put into Pos
B48: AmPOS Total | G48: =SUM(G46:G46) -> 0 | H48: =SUM(H46:H47) -> 0.165 | I48: =SUM(I46:I46) -> 0
B50: Platform: Network / QSR | J50: z
B51: Squad | C51: Squad Type | D51: Size | E51: On/Off | F51: Support % | G51: Total Squad Cost ($m) | H51: TDD Cost ($m) | I51: Funded outside TDD ($m) | K51: Fund
B52: Network / QSR | C52: Configuration / Integration | D52: M | E52: Onshore | F52: 0.2 | G52: =IFERROR(IF($E52="Onshore",INDEX('0.3 Squad Archetypes'!$G$5:$G$23,MATCH($C52&"|"&$D52,'0.3 Squad Archetypes'!$A$5:$A$23,0)),INDEX('0.3 Squad Archetypes'!$H$5:$H$23,MATCH($C52&"|"&$D52,'0.3 Squad Archetypes'!$A$5:$A$23,0))),"check size") -> 1.4 | H52: =IFERROR($G52*$F52,"") -> 0.28 | I52: =IFERROR($G52*(1-$F52),"") -> 1.12 | K52: AU
B53: Platform Overhead | H53: ='0.2 Data Config'!$L$16 -> 0.165
B54: Network / QSR Total | G54: =SUM(G52:G52) -> 1.4 | H54: =SUM(H52:H53) -> 0.445 | I54: =SUM(I52:I52) -> 1.12
B56: Platform: Data AU
B57: Squad | C57: Squad Type | D57: Size | E57: On/Off | F57: Support % | G57: Total Squad Cost ($m) | H57: TDD Cost ($m) | I57: Funded outside TDD ($m) | K57: Fund
B58: Data AU | C58: Enterprise Data and Insights | D58: M | E58: Offshore | F58: 0.9 | G58: =IFERROR(IF($E58="Onshore",INDEX('0.3 Squad Archetypes'!$G$5:$G$23,MATCH($C58&"|"&$D58,'0.3 Squad Archetypes'!$A$5:$A$23,0)),INDEX('0.3 Squad Archetypes'!$H$5:$H$23,MATCH($C58&"|"&$D58,'0.3 Squad Archetypes'!$A$5:$A$23,0))),"check size") -> 0.68 | H58: =IFERROR($G58*$F58,"") -> 0.612 | I58: =IFERROR($G58*(1-$F58),"") -> 0.068 | J58: Subject to support Ampos | K58: AU
B59: Platform Overhead | H59: ='0.2 Data Config'!$L$16 -> 0.165
B60: Data AU Total | G60: =SUM(G58:G58) -> 0.68 | H60: =SUM(H58:H59) -> 0.777 | I60: =SUM(I58:I58) -> 0.068
B62: Platform: EGI Retail
B63: Squad | C63: Squad Type | D63: Size | E63: On/Off | F63: Support % | G63: Total Squad Cost ($m) | H63: TDD Cost ($m) | I63: Funded outside TDD ($m) | J63: Update - EGI | K63: Fund
B64: EGI Retail | C64: Strategic Programs | E64: Onshore | F64: 0 | G64: 0 | H64: =IFERROR($G64*$F64,"") -> 0 | I64: =IFERROR($G64*(1-$F64),"") -> 0 | K64: AU
B66: EGI Retail Total | G66: =SUM(G64:G64) -> 0 | H66: =SUM(H64:H64) -> 0 | I66: =SUM(I64:I64) -> 0
B68: TDD squad cost - AU funded (Fund toggles) ($m) | C68: =SUMIF(K23:K26,"AU",H23:H26)+SUMIF(K32:K32,"AU",H32:H32)+SUMIF(K46:K46,"AU",H46:H46)+SUMIF(K52:K52,"AU",H52:H52)+SUMIF(K58:K58,"AU",H58:H58)+SUMIF(K64:K64,"AU",H64:H64) -> 4.052
B69: TDD squad cost - NZ funded (Fund toggles) ($m) | C69: =SUMIF(K23:K26,"NZ",H23:H26)+SUMIF(K32:K32,"NZ",H32:H32)+SUMIF(K46:K46,"NZ",H46:H46)+SUMIF(K52:K52,"NZ",H52:H52)+SUMIF(K58:K58,"NZ",H58:H58)+SUMIF(K64:K64,"NZ",H64:H64) -> 0

Sheet 1.2 Customer
B2: Customer
B4: Portfolio Summary | G4: Budget vs TDD Cost
B5: Cost | C5: TDD ($m) | D5: Other ($m) | E5: Total Customer Cost ($m) | G5: TDD Lights On Budget (people - 0.2 Data Config) | H5: ='0.2 Data Config'!$E$13+'0.2 Data Config'!$E$14 -> 6.5
B6: Portfolio Overhead (see 0.2 Data Config) | C6: ='0.2 Data Config'!$L$10 -> 0.7495 | E6: =C6 -> 0.7495 | G6: Overheads & Support (this model) | H6: =C9 -> 9.0245
B7: Platform Overheads | C7: =SUM(H32,H40,H47) -> 0.495 | E7: =C7 -> 0.495 | G7: Variance (budget less cost) | H7: =H5-H6 -> -2.5245
B8: Squad Support Costs | C8: =SUM(H29,H30,H31,H37,H38,H39,H45,H46,H52) -> 7.78 | D8: =SUM(I29,I30,I31,I37,I38,I39,I45,I46,I52) -> 5.92 | E8: =C8+D8 -> 13.7
B9: Total Cost | C9: =SUM(C6:C8) -> 9.0245 | D9: =SUM(D6:D8) -> 5.92 | E9: =C9+D9 -> 14.9445
G10: Other funding
B11: Total Customer budget | E11: =SUM(H12:H21) -> 11.7 | G11: Budget line | H11: Budget ($m) | I11: Amount that can be allocated to people | J11: Remaining for non-people ($m)
B12: Reconciled to Finance | E12: ='0.1 Budget Table (Fin)'!Q13 -> 11.7 | G12: Customer Lights On | H12: ='0.1 Budget Table (Fin)'!L13 -> 1.7 | I12: ='0.1 Budget Table (Fin)'!G13 -> 0 | J12: =IFERROR(H12-I12,0) -> 1.7
G13: OpEx Initiatives | H13: ='0.1 Budget Table (Fin)'!N13 -> 0 | I13: 0 | J13: =IFERROR(H13-I13,0) -> 0
B14: Total to fund | G14: CapEx | H14: ='0.1 Budget Table (Fin)'!P13 -> 5 | I14: 2 | J14: =IFERROR(H14-I14,0) -> 3
B15: TDD Variance | C15: =MAX(0,-H7) -> 2.5245 | G15: Significant Items EGI | I15: =I52 -> 0
B16: Other Variance | C16: =MAX(0,I24) -> 1.92 | G16: Significant Items | H16: ='0.1 Budget Table (Fin)'!O13 -> 5 | I16: 2 | J16: =IFERROR(H16-I16,0) -> 3
B17: Total | C17: =C15+C16 -> 4.4445 | G17: Sig Items EG
G18: Z OpEx Initiatives
G19: Z CapEx
G20: Z Sig items
G21: Depreciation | H21: ='0.1 Budget Table (Fin)'!M13 -> 0 | I21: 0 | J21: =IFERROR(H21-I21,0) -> 0
G22: Total applied | I22: =SUM(I12:I21) -> 4
G23: Other cost (this model) | I23: =D9 -> 5.92
G24: Left to fund | I24: =I23-I22 -> 1.92
B27: Platform: Ampol Digital
B28: Squad | C28: Squad Type | D28: Size | E28: On/Off | F28: Support % | G28: Total Squad Cost ($m) | H28: TDD Cost ($m) | I28: Funded outside TDD ($m) | J28: FTE | L28: Fund
B29: Ampol App | C29: Product | D29: L | E29: Onshore | F29: 0.2 | G29: =IFERROR(IF($E29="Onshore",INDEX('0.3 Squad Archetypes'!$G$5:$G$23,MATCH($C29&"|"&$D29,'0.3 Squad Archetypes'!$A$5:$A$23,0)),INDEX('0.3 Squad Archetypes'!$H$5:$H$23,MATCH($C29&"|"&$D29,'0.3 Squad Archetypes'!$A$5:$A$23,0))),"check size") -> 2.8 | H29: =IFERROR($G29*$F29,"") -> 0.56 | I29: =IFERROR($G29*(1-$F29),"") -> 2.24 | J29: 15 | L29: AU
B30: Ampol Web | C30: Product | D30: M | E30: Onshore | F30: 0.2 | G30: =IFERROR(IF($E30="Onshore",INDEX('0.3 Squad Archetypes'!$G$5:$G$23,MATCH($C30&"|"&$D30,'0.3 Squad Archetypes'!$A$5:$A$23,0)),INDEX('0.3 Squad Archetypes'!$H$5:$H$23,MATCH($C30&"|"&$D30,'0.3 Squad Archetypes'!$A$5:$A$23,0))),"check size") -> 1.9 | H30: =IFERROR($G30*$F30,"") -> 0.38 | I30: =IFERROR($G30*(1-$F30),"") -> 1.52 | J30: 9 | L30: AU
B31: Digital Operations | C31: Operations | D31: M | E31: Onshore | F31: 1 | G31: =IFERROR(IF($E31="Onshore",INDEX('0.3 Squad Archetypes'!$G$5:$G$23,MATCH($C31&"|"&$D31,'0.3 Squad Archetypes'!$A$5:$A$23,0)),INDEX('0.3 Squad Archetypes'!$H$5:$H$23,MATCH($C31&"|"&$D31,'0.3 Squad Archetypes'!$A$5:$A$23,0))),"check size") -> 1.4 | H31: =IFERROR($G31*$F31,"") -> 1.4 | I31: =IFERROR($G31*(1-$F31),"") -> 0 | J31: 6 | L31: AU
B32: Platform Overhead | H32: ='0.2 Data Config'!$L$16 -> 0.165
B33: Ampol Digital Total | G33: =SUM(G29:G31) -> 6.1 | H33: =SUM(H29:H32) -> 2.505 | I33: =SUM(I29:I31) -> 3.76
B35: Platform: Customer Z
B36: Squad | C36: Squad Type | D36: Size | E36: On/Off | F36: Support % | G36: Total Squad Cost ($m) | H36: TDD Cost ($m) | I36: Funded outside TDD ($m) | L36: Fund
B37: Z Energy Apps | C37: Product | D37: S | E37: Onshore | F37: 1 | G37: =IFERROR(IF($E37="Onshore",INDEX('0.3 Squad Archetypes'!$G$5:$G$23,MATCH($C37&"|"&$D37,'0.3 Squad Archetypes'!$A$5:$A$23,0)),INDEX('0.3 Squad Archetypes'!$H$5:$H$23,MATCH($C37&"|"&$D37,'0.3 Squad Archetypes'!$A$5:$A$23,0))),"check size") -> 1.3 | H37: =IFERROR($G37*$F37,"") -> 1.3 | I37: =IFERROR($G37*(1-$F37),"") -> 0 | J37: Z funded incl. in the lights on budget. Needs to be under group customer platforms | K37: 5 | L37: NZ
B38: Z Energy Martech | C38: Product | D38: L | E38: Onshore | F38: 1 | G38: =IFERROR(IF($E38="Onshore",INDEX('0.3 Squad Archetypes'!$G$5:$G$23,MATCH($C38&"|"&$D38,'0.3 Squad Archetypes'!$A$5:$A$23,0)),INDEX('0.3 Squad Archetypes'!$H$5:$H$23,MATCH($C38&"|"&$D38,'0.3 Squad Archetypes'!$A$5:$A$23,0))),"check size") -> 2.8 | H38: =IFERROR($G38*$F38,"") -> 2.8 | I38: =IFERROR($G38*(1-$F38),"") -> 0 | J38: Z funded incl. in the lights on budget. Needs to be under group customer platforms | K38: 16 | L38: NZ
A39: Net New | B39: Digital Support NZ | C39: Operations | D39: S | E39: Onshore | F39: 1 | G39: =IFERROR(IF($E39="Onshore",INDEX('0.3 Squad Archetypes'!$G$5:$G$23,MATCH($C39&"|"&$D39,'0.3 Squad Archetypes'!$A$5:$A$23,0)),INDEX('0.3 Squad Archetypes'!$H$5:$H$23,MATCH($C39&"|"&$D39,'0.3 Squad Archetypes'!$A$5:$A$23,0))),"check size") -> 0.8 | H39: =IFERROR($G39*$F39,"") -> 0.8 | I39: =IFERROR($G39*(1-$F39),"") -> 0 | J39: Z funded incl. in the lights on budget. Needs to be under group customer platforms | L39: NZ
B40: Platform Overhead | H40: ='0.2 Data Config'!$L$16 -> 0.165
B41: Customer Z Total | G41: =SUM(G37:G39) -> 4.9 | H41: =SUM(H37:H40) -> 5.065 | I41: =SUM(I37:I39) -> 0
M42: 2 B2B Vacant FTEs
B43: Platform: Group Customer Platforms
B44: Squad | C44: Squad Type | D44: Size | E44: On/Off | F44: Support % | G44: Total Squad Cost ($m) | H44: TDD Cost ($m) | I44: Funded outside TDD ($m) | L44: Fund
B45: AU CRM & Martech | C45: Product | D45: M | E45: Onshore | F45: 0.2 | G45: =IFERROR(IF($E45="Onshore",INDEX('0.3 Squad Archetypes'!$G$5:$G$23,MATCH($C45&"|"&$D45,'0.3 Squad Archetypes'!$A$5:$A$23,0)),INDEX('0.3 Squad Archetypes'!$H$5:$H$23,MATCH($C45&"|"&$D45,'0.3 Squad Archetypes'!$A$5:$A$23,0))),"check size") -> 1.9 | H45: =IFERROR($G45*$F45,"") -> 0.38 | I45: =IFERROR($G45*(1-$F45),"") -> 1.52 | J45: 7 | L45: AU
A46: Net New - 3FTE | B46: AI Enablement | C46: Engineering | D46: S | E46: Onshore | F46: 0.2 | G46: =IFERROR(IF($E46="Onshore",INDEX('0.3 Squad Archetypes'!$G$5:$G$23,MATCH($C46&"|"&$D46,'0.3 Squad Archetypes'!$A$5:$A$23,0)),INDEX('0.3 Squad Archetypes'!$H$5:$H$23,MATCH($C46&"|"&$D46,'0.3 Squad Archetypes'!$A$5:$A$23,0))),"check size") -> 0.8 | H46: =IFERROR($G46*$F46,"") -> 0.16 | I46: =IFERROR($G46*(1-$F46),"") -> 0.64 | L46: AU
B47: Platform Overhead | H47: ='0.2 Data Config'!$L$16 -> 0.165
B48: Group Customer Platforms Total | G48: =SUM(G45:G46) -> 2.7 | H48: =SUM(H45:H47) -> 0.705 | I48: =SUM(I45:I46) -> 2.16
B50: Platform: EGI Customer
B51: Squad | C51: Squad Type | D51: Size | E51: On/Off | F51: Support % | G51: Total Squad Cost ($m) | H51: TDD Cost ($m) | I51: Funded outside TDD ($m) | L51: Fund
B52: EGI Customer | C52: Strategic Programs | E52: Onshore | F52: 0 | G52: 0 | H52: =IFERROR($G52*$F52,"") -> 0 | I52: =IFERROR($G52*(1-$F52),"") -> 0 | J52: 9 | K52: EGI completely separate funded by EGI not within sig items budget | L52: AU
K53: 2.25
B54: EGI Customer Total | G54: =SUM(G52:G52) -> 0 | H54: =SUM(H52:H52) -> 0 | I54: =SUM(I52:I52) -> 0
B56: TDD squad cost - AU funded (Fund toggles) ($m) | C56: =SUMIF(L29:L31,"AU",H29:H31)+SUMIF(L37:L39,"AU",H37:H39)+SUMIF(L45:L46,"AU",H45:H46)+SUMIF(L52:L52,"AU",H52:H52) -> 2.88
B57: TDD squad cost - NZ funded (Fund toggles) ($m) | C57: =SUMIF(L29:L31,"NZ",H29:H31)+SUMIF(L37:L39,"NZ",H37:H39)+SUMIF(L45:L46,"NZ",H45:H46)+SUMIF(L52:L52,"NZ",H52:H52) -> 4.9

Sheet 1.3 Enterprise Data
B2: Enterprise Data
B4: Portfolio Summary | G4: Budget vs TDD Cost
B5: Cost | C5: TDD ($m) | D5: Other ($m) | E5: Total Enterprise Data Cost ($m) | G5: TDD Lights On Budget (people - 0.2 Data Config) | H5: ='0.2 Data Config'!$E$22 -> 3.5
B6: Portfolio Overhead (see 0.2 Data Config) | C6: ='0.2 Data Config'!$L$10 -> 0.7495 | E6: =C6 -> 0.7495 | G6: Overheads & Support (this model) | H6: =C9 -> 4.1105
B7: Platform Overheads | C7: =SUM(H29) -> 0.165 | E7: =C7 -> 0.165 | G7: Variance (budget less cost) | H7: =H5-H6 -> -0.6105
B8: Squad Support Costs | C8: =SUM(H24,H25,H26,H27,H28) -> 3.196 | D8: =SUM(I24,I25,I26,I27,I28) -> 1.904 | E8: =C8+D8 -> 5.1
B9: Total Cost | C9: =SUM(C6:C8) -> 4.1105 | D9: =SUM(D6:D8) -> 1.904 | E9: =C9+D9 -> 6.0145
G10: Other funding
G11: Funding position
G12: Other cost (this model) | I12: =D9 -> 1.904
B13: Total to fund | G13: Funded from TDD Corporate pool (2.4 COE Summary) | I13: 0
B14: TDD Variance | C14: =MAX(0,-H7) -> 0.6105 | G14: Left to fund | I14: =I12-I13 -> 1.904
B15: Other Variance | C15: =MAX(0,I14) -> 1.904
B16: Total | C16: =C14+C15 -> 2.5145
B22: Platform: Group Data
B23: Squad | C23: Squad Type | D23: Size | E23: On/Off | F23: Support % | G23: Total Squad Cost ($m) | H23: TDD Cost ($m) | I23: Funded outside TDD ($m) | K23: Fund
B24: Data Science | C24: Enterprise Data and Insights | D24: M | E24: Onshore | F24: 0.2 | G24: =IFERROR(IF($E24="Onshore",INDEX('0.3 Squad Archetypes'!$G$5:$G$23,MATCH($C24&"|"&$D24,'0.3 Squad Archetypes'!$A$5:$A$23,0)),INDEX('0.3 Squad Archetypes'!$H$5:$H$23,MATCH($C24&"|"&$D24,'0.3 Squad Archetypes'!$A$5:$A$23,0))),"check size") -> 1.7 | H24: =IFERROR($G24*$F24,"") -> 0.34 | I24: =IFERROR($G24*(1-$F24),"") -> 1.36 | K24: AU
B25: Operations | C25: Operations | D25: L | E25: Offshore | F25: 1 | G25: =IFERROR(IF($E25="Onshore",INDEX('0.3 Squad Archetypes'!$G$5:$G$23,MATCH($C25&"|"&$D25,'0.3 Squad Archetypes'!$A$5:$A$23,0)),INDEX('0.3 Squad Archetypes'!$H$5:$H$23,MATCH($C25&"|"&$D25,'0.3 Squad Archetypes'!$A$5:$A$23,0))),"check size") -> 0.92 | H25: =IFERROR($G25*$F25,"") -> 0.92 | I25: =IFERROR($G25*(1-$F25),"") -> 0 | J25: 2 Large to 1 big ops squad offshore and 2 small data squads onshore | K25: AU
B26: Reporting & Analytics | C26: Enterprise Data and Insights | D26: S | E26: Onshore | F26: 1 | G26: =IFERROR(IF($E26="Onshore",INDEX('0.3 Squad Archetypes'!$G$5:$G$23,MATCH($C26&"|"&$D26,'0.3 Squad Archetypes'!$A$5:$A$23,0)),INDEX('0.3 Squad Archetypes'!$H$5:$H$23,MATCH($C26&"|"&$D26,'0.3 Squad Archetypes'!$A$5:$A$23,0))),"check size") -> 0.9 | H26: =IFERROR($G26*$F26,"") -> 0.9 | I26: =IFERROR($G26*(1-$F26),"") -> 0 | K26: AU
B27: Data Platforms | C27: Enterprise Data and Insights | D27: S | E27: Onshore | F27: 1 | G27: =IFERROR(IF($E27="Onshore",INDEX('0.3 Squad Archetypes'!$G$5:$G$23,MATCH($C27&"|"&$D27,'0.3 Squad Archetypes'!$A$5:$A$23,0)),INDEX('0.3 Squad Archetypes'!$H$5:$H$23,MATCH($C27&"|"&$D27,'0.3 Squad Archetypes'!$A$5:$A$23,0))),"check size") -> 0.9 | H27: =IFERROR($G27*$F27,"") -> 0.9 | I27: =IFERROR($G27*(1-$F27),"") -> 0 | K27: AU
B28: Enterprise Data Delivery | C28: Enterprise Data and Insights | D28: M | E28: Offshore | F28: 0.2 | G28: =IFERROR(IF($E28="Onshore",INDEX('0.3 Squad Archetypes'!$G$5:$G$23,MATCH($C28&"|"&$D28,'0.3 Squad Archetypes'!$A$5:$A$23,0)),INDEX('0.3 Squad Archetypes'!$H$5:$H$23,MATCH($C28&"|"&$D28,'0.3 Squad Archetypes'!$A$5:$A$23,0))),"check size") -> 0.68 | H28: =IFERROR($G28*$F28,"") -> 0.136 | I28: =IFERROR($G28*(1-$F28),"") -> 0.544 | K28: AU
B29: Platform Overhead | H29: ='0.2 Data Config'!$L$16 -> 0.165
B30: Group Data Total | G30: =SUM(G24:G28) -> 5.1 | H30: =SUM(H24:H29) -> 3.361 | I30: =SUM(I24:I28) -> 1.904
B32: TDD squad cost - AU funded (Fund toggles) ($m) | C32: =SUMIF(K24:K28,"AU",H24:H28) -> 3.196
B33: TDD squad cost - NZ funded (Fund toggles) ($m) | C33: =SUMIF(K24:K28,"NZ",H24:H28) -> 0

Sheet 1.4 TDD Group Functions
B2: TDD Group Functions
B4: Portfolio Summary | G4: Budget vs TDD Cost
B5: Cost | C5: TDD ($m) | D5: Other ($m) | E5: Total TDD Group Functions Cost ($m) | G5: TDD Lights On Budget (people - 0.2 Data Config) | H5: ='0.2 Data Config'!$E$21 -> 5.5
B6: Portfolio Overhead (see 0.2 Data Config) | C6: ='0.2 Data Config'!$L$10 -> 0.7495 | E6: =C6 -> 0.7495 | G6: Overheads & Support (this model) | H6: =C9 -> 3.6645
B7: Platform Overheads | C7: =SUM(H28) -> 0.165 | E7: =C7 -> 0.165 | G7: Variance (budget less cost) | H7: =H5-H6 -> 1.8355
B8: Squad Support Costs | C8: =SUM(H24,H25,H26,H27,H33) -> 2.75 | D8: =SUM(I24,I25,I26,I27,I33) -> 1.15 | E8: =C8+D8 -> 3.9
B9: Total Cost | C9: =SUM(C6:C8) -> 3.6645 | D9: =SUM(D6:D8) -> 1.15 | E9: =C9+D9 -> 4.8145
G10: Other funding
B11: Lights On funded from the TDD allocation above (Data Config). Shared TDD Corporate pool sits on 2.4 COE Summary. | G11: Funding position
G12: Other cost (this model) | I12: =D9 -> 1.15
B13: Total to fund | G13: Funded from TDD Corporate pool (2.4 COE Summary) | I13: =I33 -> 0
B14: TDD Variance | C14: =MAX(0,-H7) -> 0 | G14: Left to fund | I14: =I12-I13 -> 1.15
B15: Other Variance | C15: =MAX(0,I14) -> 1.15
B16: Total | C16: =C14+C15 -> 1.15
B22: Platform: TDD Group Functions
B23: Squad | C23: Squad Type | D23: Size | E23: On/Off | F23: Support % | G23: Total Squad Cost ($m) | H23: TDD Cost ($m) | I23: Funded outside TDD ($m) | K23: Fund
B24: Workplace & Enterprise Tooling | C24: Configuration / Integration | D24: S | E24: Onshore | F24: 1 | G24: =IFERROR(IF($E24="Onshore",INDEX('0.3 Squad Archetypes'!$G$5:$G$23,MATCH($C24&"|"&$D24,'0.3 Squad Archetypes'!$A$5:$A$23,0)),INDEX('0.3 Squad Archetypes'!$H$5:$H$23,MATCH($C24&"|"&$D24,'0.3 Squad Archetypes'!$A$5:$A$23,0))),"check size") -> 0.4 | H24: =IFERROR($G24*$F24,"") -> 0.4 | I24: =IFERROR($G24*(1-$F24),"") -> 0 | K24: AU
B25: Network & Infrastructure | C25: Operations | D25: L | E25: Onshore | F25: 0.5 | G25: =IFERROR(IF($E25="Onshore",INDEX('0.3 Squad Archetypes'!$G$5:$G$23,MATCH($C25&"|"&$D25,'0.3 Squad Archetypes'!$A$5:$A$23,0)),INDEX('0.3 Squad Archetypes'!$H$5:$H$23,MATCH($C25&"|"&$D25,'0.3 Squad Archetypes'!$A$5:$A$23,0))),"check size") -> 2.3 | H25: =IFERROR($G25*$F25,"") -> 1.15 | I25: =IFERROR($G25*(1-$F25),"") -> 1.15 | J25: Could be 50% support | K25: AU
B26: DevOps & Engineering | C26: Engineering | D26: S | E26: Onshore | F26: 1 | G26: =IFERROR(IF($E26="Onshore",INDEX('0.3 Squad Archetypes'!$G$5:$G$23,MATCH($C26&"|"&$D26,'0.3 Squad Archetypes'!$A$5:$A$23,0)),INDEX('0.3 Squad Archetypes'!$H$5:$H$23,MATCH($C26&"|"&$D26,'0.3 Squad Archetypes'!$A$5:$A$23,0))),"check size") -> 0.8 | H26: =IFERROR($G26*$F26,"") -> 0.8 | I26: =IFERROR($G26*(1-$F26),"") -> 0 | J26: Support could be more than 20% | K26: AU
B27: Integration | C27: Configuration / Integration | D27: S | E27: Onshore | F27: 1 | G27: =IFERROR(IF($E27="Onshore",INDEX('0.3 Squad Archetypes'!$G$5:$G$23,MATCH($C27&"|"&$D27,'0.3 Squad Archetypes'!$A$5:$A$23,0)),INDEX('0.3 Squad Archetypes'!$H$5:$H$23,MATCH($C27&"|"&$D27,'0.3 Squad Archetypes'!$A$5:$A$23,0))),"check size") -> 0.4 | H27: =IFERROR($G27*$F27,"") -> 0.4 | I27: =IFERROR($G27*(1-$F27),"") -> 0 | K27: AU
B28: Platform Overhead | H28: ='0.2 Data Config'!$L$16 -> 0.165
B29: TDD Group Functions Total | G29: =SUM(G24:G27) -> 3.9 | H29: =SUM(H24:H28) -> 2.915 | I29: =SUM(I24:I27) -> 1.15
B31: Platform: EGI TDD
B32: Squad | C32: Squad Type | D32: Size | E32: On/Off | F32: Support % | G32: Total Squad Cost ($m) | H32: TDD Cost ($m) | I32: Funded outside TDD ($m) | K32: Fund
B33: EGI TDD | C33: Strategic Programs | E33: Onshore | F33: 0.2 | G33: 0 | H33: =IFERROR($G33*$F33,"") -> 0 | I33: =IFERROR($G33*(1-$F33),"") -> 0 | K33: AU
B34: EGI TDD Total | G34: =SUM(G33:G33) -> 0 | H34: =SUM(H33:H33) -> 0 | I34: =SUM(I33:I33) -> 0
B36: TDD squad cost - AU funded (Fund toggles) ($m) | C36: =SUMIF(K24:K27,"AU",H24:H27)+SUMIF(K33:K33,"AU",H33:H33) -> 2.75
B37: TDD squad cost - NZ funded (Fund toggles) ($m) | C37: =SUMIF(K24:K27,"NZ",H24:H27)+SUMIF(K33:K33,"NZ",H33:H33) -> 0

Sheet 1.5 P&C
B2: P&C
B4: Portfolio Summary | G4: Budget vs TDD Cost
B5: Cost | C5: TDD ($m) | D5: Other ($m) | E5: Total P&C Cost ($m) | G5: TDD Lights On Budget (people - 0.2 Data Config) | H5: ='0.2 Data Config'!$E$18 -> 2
B6: Portfolio Overhead (see 0.2 Data Config) | C6: ='0.2 Data Config'!$L$10 -> 0.7495 | E6: =C6 -> 0.7495 | G6: Overheads & Support (this model) | H6: =C9 -> 1.2745
B7: Platform Overheads | C7: =SUM(H26) -> 0.165 | E7: =C7 -> 0.165 | G7: Variance (budget less cost) | H7: =H5-H6 -> 0.7255
B8: Squad Support Costs | C8: =SUM(H24,H25,H31) -> 0.36 | D8: =SUM(I24,I25,I31) -> 1.44 | E8: =C8+D8 -> 1.8
B9: Total Cost | C9: =SUM(C6:C8) -> 1.2745 | D9: =SUM(D6:D8) -> 1.44 | E9: =C9+D9 -> 2.7145
G10: Other funding
B11: Total P&C budget | E11: =SUM(H12:H17) -> 5.8 | G11: Budget line | H11: Budget ($m) | I11: Amount that can be allocated to people | J11: Remaining for non-people ($m)
B12: Reconciled to Finance | E12: ='0.1 Budget Table (Fin)'!Q12 -> 5.8 | G12: P&C Lights On | H12: ='0.1 Budget Table (Fin)'!L12 -> 2.1 | I12: ='0.1 Budget Table (Fin)'!G12 -> 0 | J12: =IFERROR(H12-I12,0) -> 2.1
G13: OpEx Initiatives | H13: ='0.1 Budget Table (Fin)'!N12 -> 2 | I13: 0 | J13: =IFERROR(H13-I13,0) -> 2
B14: Total to fund | G14: CapEx | H14: ='0.1 Budget Table (Fin)'!P12 -> 0.3 | I14: 0 | J14: =IFERROR(H14-I14,0) -> 0.3
B15: TDD Variance | C15: =MAX(0,-H7) -> 0 | G15: Significant Items | H15: ='0.1 Budget Table (Fin)'!O12 -> 1.4 | I15: 0 | J15: =IFERROR(H15-I15,0) -> 1.4
B16: Other Variance | C16: =MAX(0,I20) -> 1.44 | G16: Significant Items EGI | I16: =I31 -> 0
B17: Total | C17: =C15+C16 -> 1.44 | G17: Depreciation | H17: ='0.1 Budget Table (Fin)'!M12 -> 0 | I17: 0 | J17: =IFERROR(H17-I17,0) -> 0
G18: Total applied | I18: =SUM(I12:I17) -> 0
G19: Other cost (this model) | I19: =D9 -> 1.44
G20: Left to fund | I20: =I19-I18 -> 1.44
B22: Platform: P&C
B23: Squad | C23: Squad Type | D23: Size | E23: On/Off | F23: Support % | G23: Total Squad Cost ($m) | H23: TDD Cost ($m) | I23: Funded outside TDD ($m) | J23: Fund
B24: P&C | C24: Configuration / Integration | D24: M | E24: Onshore | F24: 0.2 | G24: =IFERROR(IF($E24="Onshore",INDEX('0.3 Squad Archetypes'!$G$5:$G$23,MATCH($C24&"|"&$D24,'0.3 Squad Archetypes'!$A$5:$A$23,0)),INDEX('0.3 Squad Archetypes'!$H$5:$H$23,MATCH($C24&"|"&$D24,'0.3 Squad Archetypes'!$A$5:$A$23,0))),"check size") -> 1.4 | H24: =IFERROR($G24*$F24,"") -> 0.28 | I24: =IFERROR($G24*(1-$F24),"") -> 1.12 | J24: AU
B25: P&C - RTA | C25: Configuration / Integration | D25: S | E25: Onshore | F25: 0.2 | G25: =IFERROR(IF($E25="Onshore",INDEX('0.3 Squad Archetypes'!$G$5:$G$23,MATCH($C25&"|"&$D25,'0.3 Squad Archetypes'!$A$5:$A$23,0)),INDEX('0.3 Squad Archetypes'!$H$5:$H$23,MATCH($C25&"|"&$D25,'0.3 Squad Archetypes'!$A$5:$A$23,0))),"check size") -> 0.4 | H25: =IFERROR($G25*$F25,"") -> 0.08 | I25: =IFERROR($G25*(1-$F25),"") -> 0.32 | J25: AU
B26: Platform Overhead | H26: ='0.2 Data Config'!$L$16 -> 0.165
B27: P&C Total | G27: =SUM(G24:G25) -> 1.8 | H27: =SUM(H24:H26) -> 0.525 | I27: =SUM(I24:I25) -> 1.44
B29: Platform: EGI P&C
B30: Squad | C30: Squad Type | D30: Size | E30: On/Off | F30: Support % | G30: Total Squad Cost ($m) | H30: TDD Cost ($m) | I30: Funded outside TDD ($m) | J30: Fund
B31: EGI P&C | C31: Strategic Programs | E31: Onshore | F31: 0.2 | G31: 0 | H31: =IFERROR($G31*$F31,"") -> 0 | I31: =IFERROR($G31*(1-$F31),"") -> 0 | J31: AU
B32: EGI P&C Total | G32: =SUM(G31:G31) -> 0 | H32: =SUM(H31:H31) -> 0 | I32: =SUM(I31:I31) -> 0
B34: TDD squad cost - AU funded (Fund toggles) ($m) | C34: =SUMIF(J24:J25,"AU",H24:H25)+SUMIF(J31:J31,"AU",H31:H31) -> 0.36
B35: TDD squad cost - NZ funded (Fund toggles) ($m) | C35: =SUMIF(J24:J25,"NZ",H24:H25)+SUMIF(J31:J31,"NZ",H31:H31) -> 0

Sheet 1.6 Finance
B2: Finance
B4: Portfolio Summary | G4: Budget vs TDD Cost
B5: Cost | C5: TDD ($m) | D5: Other ($m) | E5: Total Finance Cost ($m) | G5: TDD Lights On Budget (people - 0.2 Data Config) | H5: ='0.2 Data Config'!$E$19 -> 2
B6: Portfolio Overhead (see 0.2 Data Config) | C6: ='0.2 Data Config'!$L$10 -> 0.7495 | E6: =C6 -> 0.7495 | G6: Overheads & Support (this model) | H6: =C9 -> 1.4145
B7: Platform Overheads | C7: =SUM(H26) -> 0.165 | E7: =C7 -> 0.165 | G7: Variance (budget less cost) | H7: =H5-H6 -> 0.5855
B8: Squad Support Costs | C8: =SUM(H24,H25,H31) -> 0.5 | D8: =SUM(I24,I25,I31) -> 2 | E8: =C8+D8 -> 2.5
B9: Total Cost | C9: =SUM(C6:C8) -> 1.4145 | D9: =SUM(D6:D8) -> 2 | E9: =C9+D9 -> 3.4145
G10: Other funding
B11: Total Corporate Finance budget | E11: =SUM(H12:H17) -> 3.5 | G11: Budget line | H11: Budget ($m) | I11: Amount that can be allocated to people | J11: Remaining for non-people ($m)
B12: Reconciled to Finance | E12: ='0.1 Budget Table (Fin)'!Q11 -> 3.5 | G12: Corporate Finance Lights On | H12: ='0.1 Budget Table (Fin)'!L11 -> 2.6 | I12: ='0.1 Budget Table (Fin)'!G11 -> 0 | J12: =IFERROR(H12-I12,0) -> 2.6
G13: OpEx Initiatives | H13: ='0.1 Budget Table (Fin)'!N11 -> 0.9 | I13: 0 | J13: =IFERROR(H13-I13,0) -> 0.9
B14: Total to fund | G14: CapEx | H14: ='0.1 Budget Table (Fin)'!P11 -> 0 | I14: 0 | J14: =IFERROR(H14-I14,0) -> 0
B15: TDD Variance | C15: =MAX(0,-H7) -> 0 | G15: Significant Items | H15: ='0.1 Budget Table (Fin)'!O11 -> 0 | I15: 0 | J15: =IFERROR(H15-I15,0) -> 0
B16: Other Variance | C16: =MAX(0,I20) -> 2 | G16: Significant Items EGI | I16: =I31 -> 0
B17: Total | C17: =C15+C16 -> 2 | G17: Depreciation | H17: ='0.1 Budget Table (Fin)'!M11 -> 0 | I17: 0 | J17: =IFERROR(H17-I17,0) -> 0
G18: Total applied | I18: =SUM(I12:I17) -> 0
G19: Other cost (this model) | I19: =D9 -> 2
G20: Left to fund | I20: =I19-I18 -> 2
B22: Platform: Finance
B23: Squad | C23: Squad Type | D23: Size | E23: On/Off | F23: Support % | G23: Total Squad Cost ($m) | H23: TDD Cost ($m) | I23: Funded outside TDD ($m) | J23: Fund
B24: AU Finance | C24: Configuration / Integration | D24: L | E24: Onshore | F24: 0.2 | G24: =IFERROR(IF($E24="Onshore",INDEX('0.3 Squad Archetypes'!$G$5:$G$23,MATCH($C24&"|"&$D24,'0.3 Squad Archetypes'!$A$5:$A$23,0)),INDEX('0.3 Squad Archetypes'!$H$5:$H$23,MATCH($C24&"|"&$D24,'0.3 Squad Archetypes'!$A$5:$A$23,0))),"check size") -> 2.1 | H24: =IFERROR($G24*$F24,"") -> 0.42 | I24: =IFERROR($G24*(1-$F24),"") -> 1.68 | J24: AU
B25: NZ Finance | C25: Configuration / Integration | D25: S | E25: Onshore | F25: 0.2 | G25: =IFERROR(IF($E25="Onshore",INDEX('0.3 Squad Archetypes'!$G$5:$G$23,MATCH($C25&"|"&$D25,'0.3 Squad Archetypes'!$A$5:$A$23,0)),INDEX('0.3 Squad Archetypes'!$H$5:$H$23,MATCH($C25&"|"&$D25,'0.3 Squad Archetypes'!$A$5:$A$23,0))),"check size") -> 0.4 | H25: =IFERROR($G25*$F25,"") -> 0.08 | I25: =IFERROR($G25*(1-$F25),"") -> 0.32 | J25: AU
B26: Platform Overhead | H26: ='0.2 Data Config'!$L$16 -> 0.165
B27: Finance Total | G27: =SUM(G24:G25) -> 2.5 | H27: =SUM(H24:H26) -> 0.665 | I27: =SUM(I24:I25) -> 2
B29: Platform: EGI Finance
B30: Squad | C30: Squad Type | D30: Size | E30: On/Off | F30: Support % | G30: Total Squad Cost ($m) | H30: TDD Cost ($m) | I30: Funded outside TDD ($m) | J30: Fund
B31: EGI Finance | C31: Strategic Programs | E31: Onshore | F31: 0.2 | G31: 0 | H31: =IFERROR($G31*$F31,"") -> 0 | I31: =IFERROR($G31*(1-$F31),"") -> 0 | J31: AU
B32: EGI Finance Total | G32: =SUM(G31:G31) -> 0 | H32: =SUM(H31:H31) -> 0 | I32: =SUM(I31:I31) -> 0
B34: TDD squad cost - AU funded (Fund toggles) ($m) | C34: =SUMIF(J24:J25,"AU",H24:H25)+SUMIF(J31:J31,"AU",H31:H31) -> 0.5
B35: TDD squad cost - NZ funded (Fund toggles) ($m) | C35: =SUMIF(J24:J25,"NZ",H24:H25)+SUMIF(J31:J31,"NZ",H31:H31) -> 0

Sheet 1.7 Infrastructure
B2: Infrastructure
B5: Portfolio Summary | G5: Budget vs TDD Cost
B6: Cost | C6: TDD ($m) | D6: Other ($m) | E6: Total Infrastructure Cost ($m) | G6: TDD Lights On Budget (people - 0.2 Data Config) | H6: ='0.2 Data Config'!$E$17 -> 2.5
B7: Portfolio Overhead (see 0.2 Data Config) | C7: ='0.2 Data Config'!$L$10 -> 0.7495 | E7: =C7 -> 0.7495 | G7: Overheads & Support (this model) | H7: =C10 -> 2.5245
B8: Platform Overheads | C8: =SUM(H26,H33,H39) -> 0.495 | E8: =C8 -> 0.495 | G8: Variance (budget less cost) | H8: =H6-H7 -> -0.0245
B9: Squad Support Costs | C9: =SUM(H25,H31,H32,H38) -> 1.28 | D9: =SUM(I25,I31,I32,I38) -> 2.72 | E9: =C9+D9 -> 4
B10: Total Cost | C10: =SUM(C7:C9) -> 2.5245 | D10: =SUM(D7:D9) -> 2.72 | E10: =C10+D10 -> 5.2445
G11: Other funding
B12: Total Infrastructure budget | E12: =SUM(H13:H17) -> 9.3 | G12: Budget line | H12: Budget ($m) | I12: Amount that can be allocated to people | J12: Remaining for non-people ($m)
B13: Reconciled to Finance | E13: ='0.1 Budget Table (Fin)'!Q10 -> 9.3 | G13: Infrastructure Lights On | H13: ='0.1 Budget Table (Fin)'!L10 -> 3.9 | I13: ='0.1 Budget Table (Fin)'!G10 -> 0 | J13: =IFERROR(H13-I13,0) -> 3.9
G14: OpEx Initiatives | H14: ='0.1 Budget Table (Fin)'!N10 -> 0.4 | I14: 0 | J14: =IFERROR(H14-I14,0) -> 0.4
B15: Total to fund | G15: CapEx | H15: ='0.1 Budget Table (Fin)'!P10 -> 5 | I15: 0 | J15: =IFERROR(H15-I15,0) -> 5
B16: TDD Variance | C16: =MAX(0,-H8) -> 0.0245 | G16: Significant Items | H16: ='0.1 Budget Table (Fin)'!O10 -> 0 | I16: 0 | J16: =IFERROR(H16-I16,0) -> 0
B17: Other Variance | C17: =MAX(0,I20) -> 2.72 | G17: Depreciation | H17: ='0.1 Budget Table (Fin)'!M10 -> 0 | I17: 0 | J17: =IFERROR(H17-I17,0) -> 0
B18: Total | C18: =C16+C17 -> 2.7445 | G18: Total applied | I18: =SUM(I13:I17) -> 0
G19: Other cost (this model) | I19: =D10 -> 2.72
G20: Left to fund | I20: =I19-I18 -> 2.72
B23: Platform: Distribution
B24: Squad | C24: Squad Type | D24: Size | E24: On/Off | F24: Support % | G24: Total Squad Cost ($m) | H24: TDD Cost ($m) | I24: Funded outside TDD ($m) | K24: Fund
B25: Distribution, Sales & Services | C25: Configuration / Integration | D25: M | E25: Onshore | F25: 0.2 | G25: =IFERROR(IF($E25="Onshore",INDEX('0.3 Squad Archetypes'!$G$5:$G$23,MATCH($C25&"|"&$D25,'0.3 Squad Archetypes'!$A$5:$A$23,0)),INDEX('0.3 Squad Archetypes'!$H$5:$H$23,MATCH($C25&"|"&$D25,'0.3 Squad Archetypes'!$A$5:$A$23,0))),"check size") -> 1.4 | H25: =IFERROR($G25*$F25,"") -> 0.28 | I25: =IFERROR($G25*(1-$F25),"") -> 1.12 | K25: AU
B26: Platform Overhead | H26: ='0.2 Data Config'!$L$16 -> 0.165
B27: Distribution Total | G27: =SUM(G25:G25) -> 1.4 | H27: =SUM(H25:H26) -> 0.445 | I27: =SUM(I25:I25) -> 1.12
B29: Platform: Manufacturing
B30: Squad | C30: Squad Type | D30: Size | E30: On/Off | F30: Support % | G30: Total Squad Cost ($m) | H30: TDD Cost ($m) | I30: Funded outside TDD ($m) | K30: Fund
B31: Manufacturing & Group Projects | C31: Configuration / Integration | D31: M | E31: Onshore | F31: 0.2 | G31: =IFERROR(IF($E31="Onshore",INDEX('0.3 Squad Archetypes'!$G$5:$G$23,MATCH($C31&"|"&$D31,'0.3 Squad Archetypes'!$A$5:$A$23,0)),INDEX('0.3 Squad Archetypes'!$H$5:$H$23,MATCH($C31&"|"&$D31,'0.3 Squad Archetypes'!$A$5:$A$23,0))),"check size") -> 1.4 | H31: =IFERROR($G31*$F31,"") -> 0.28 | I31: =IFERROR($G31*(1-$F31),"") -> 1.12 | K31: AU
B32: Technology Support | C32: Operations | D32: S | E32: Onshore | F32: 0.8 | G32: =IFERROR(IF($E32="Onshore",INDEX('0.3 Squad Archetypes'!$G$5:$G$23,MATCH($C32&"|"&$D32,'0.3 Squad Archetypes'!$A$5:$A$23,0)),INDEX('0.3 Squad Archetypes'!$H$5:$H$23,MATCH($C32&"|"&$D32,'0.3 Squad Archetypes'!$A$5:$A$23,0))),"check size") -> 0.8 | H32: =IFERROR($G32*$F32,"") -> 0.64 | I32: =IFERROR($G32*(1-$F32),"") -> 0.16 | K32: AU
B33: Platform Overhead | H33: ='0.2 Data Config'!$L$16 -> 0.165
B34: Manufacturing Total | G34: =SUM(G31:G32) -> 2.2 | H34: =SUM(H31:H33) -> 1.085 | I34: =SUM(I31:I32) -> 1.28
B36: Platform: Data & Insights
B37: Squad | C37: Squad Type | D37: Size | E37: On/Off | F37: Support % | G37: Total Squad Cost ($m) | H37: TDD Cost ($m) | I37: Funded outside TDD ($m) | K37: Fund
B38: Data & Insights | C38: Configuration / Integration | D38: S | E38: Onshore | F38: 0.2 | G38: =IFERROR(IF($E38="Onshore",INDEX('0.3 Squad Archetypes'!$G$5:$G$23,MATCH($C38&"|"&$D38,'0.3 Squad Archetypes'!$A$5:$A$23,0)),INDEX('0.3 Squad Archetypes'!$H$5:$H$23,MATCH($C38&"|"&$D38,'0.3 Squad Archetypes'!$A$5:$A$23,0))),"check size") -> 0.4 | H38: =IFERROR($G38*$F38,"") -> 0.08 | I38: =IFERROR($G38*(1-$F38),"") -> 0.32 | J38: Data team to be worked out | K38: AU
B39: Platform Overhead | H39: ='0.2 Data Config'!$L$16 -> 0.165
B40: Data & Insights Total | G40: =SUM(G38:G38) -> 0.4 | H40: =SUM(H38:H39) -> 0.245 | I40: =SUM(I38:I38) -> 0.32
B42: TDD squad cost - AU funded (Fund toggles) ($m) | C42: =SUMIF(K25:K25,"AU",H25:H25)+SUMIF(K31:K32,"AU",H31:H32)+SUMIF(K38:K38,"AU",H38:H38) -> 1.28
B43: TDD squad cost - NZ funded (Fund toggles) ($m) | C43: =SUMIF(K25:K25,"NZ",H25:H25)+SUMIF(K31:K32,"NZ",H31:H32)+SUMIF(K38:K38,"NZ",H38:H38) -> 0

Sheet 1.8 Energy Solutions & B2B
B2: Energy Solutions & B2B
B4: Portfolio Summary | G4: Budget vs TDD Cost
B5: Cost | C5: TDD ($m) | D5: Other ($m) | E5: Total ES & B2B Cost ($m) | G5: TDD Lights On Budget (people - 0.2 Data Config) | H5: ='0.2 Data Config'!$E$16 -> 2.5
B6: Portfolio Overhead (see 0.2 Data Config) | C6: ='0.2 Data Config'!$L$10 -> 0.7495 | E6: =C6 -> 0.7495 | G6: Overheads & Support (this model) | H6: =C9 -> 2.5095 | J6: Will need to split out B2B for budget
B7: Platform Overheads | C7: =SUM(H29,H35) -> 0.33 | E7: =C7 -> 0.33 | G7: Variance (budget less cost) | H7: =H5-H6 -> -0.0095
B8: Squad Support Costs | C8: =SUM(H27,H28,H34) -> 1.43 | D8: =SUM(I27,I28,I34) -> 4.67 | E8: =C8+D8 -> 6.1
B9: Total Cost | C9: =SUM(C6:C8) -> 2.5095 | D9: =SUM(D6:D8) -> 4.67 | E9: =C9+D9 -> 7.1795
G10: Other funding
B11: Total Energy Solutions budget | E11: =SUM(H12:H19) -> 12.4 | G11: Budget line | H11: Budget ($m) | I11: Amount that can be allocated to people | J11: Remaining for non-people ($m)
B12: Reconciled to Finance | E12: ='0.1 Budget Table (Fin)'!Q7 -> 7.2 | G12: Energy Solutions Lights On | H12: ='0.1 Budget Table (Fin)'!L7 -> 3.9 | I12: ='0.1 Budget Table (Fin)'!G7 -> 1 | J12: =IFERROR(H12-I12,0) -> 2.9
G13: ES OpEx Initiatives | H13: ='0.1 Budget Table (Fin)'!N7 -> 1 | I13: 0 | J13: =IFERROR(H13-I13,0) -> 1
B14: Total to fund | G14: ES CapEx | H14: ='0.1 Budget Table (Fin)'!P7 -> 2.3 | I14: 1 | J14: =IFERROR(H14-I14,0) -> 1.3
B15: TDD Variance | C15: =MAX(0,-H7) -> 0.0095 | G15: B2B Lights On
B16: Other Variance | C16: =MAX(0,I22) -> 1.17 | E16: What is the B2B initiatives #? | G16: B2B OpEx Initiatives
B17: Total | C17: =C15+C16 -> 1.1795 | E17: What is the B2B CapEx? | G17: B2B CapEx | H17: 5.2 | I17: 1.5
G18: Significant Items | H18: ='0.1 Budget Table (Fin)'!O7 -> 0 | I18: 0 | J18: =IFERROR(H18-I18,0) -> 0
G19: Depreciation | H19: ='0.1 Budget Table (Fin)'!M7 -> 0 | I19: 0 | J19: =IFERROR(H19-I19,0) -> 0
G20: Total applied | I20: =SUM(I12:I19) -> 3.5
G21: Other cost (this model) | I21: =D9 -> 4.67
G22: Left to fund | I22: =I21-I20 -> 1.17
B25: Platform: Energy Solutions
B26: Squad | C26: Squad Type | D26: Size | E26: On/Off | F26: Support % | G26: Total Squad Cost ($m) | H26: TDD Cost ($m) | I26: Funded outside TDD ($m) | K26: Fund
B27: Energy | C27: Engineering | D27: M | E27: Onshore | F27: 0.2 | G27: =IFERROR(IF($E27="Onshore",INDEX('0.3 Squad Archetypes'!$G$5:$G$23,MATCH($C27&"|"&$D27,'0.3 Squad Archetypes'!$A$5:$A$23,0)),INDEX('0.3 Squad Archetypes'!$H$5:$H$23,MATCH($C27&"|"&$D27,'0.3 Squad Archetypes'!$A$5:$A$23,0))),"check size") -> 2 | H27: =IFERROR($G27*$F27,"") -> 0.4 | I27: =IFERROR($G27*(1-$F27),"") -> 1.6 | K27: AU
B28: EVCI | C28: Engineering | D28: M | E28: Onshore | F28: 0.2 | G28: =IFERROR(IF($E28="Onshore",INDEX('0.3 Squad Archetypes'!$G$5:$G$23,MATCH($C28&"|"&$D28,'0.3 Squad Archetypes'!$A$5:$A$23,0)),INDEX('0.3 Squad Archetypes'!$H$5:$H$23,MATCH($C28&"|"&$D28,'0.3 Squad Archetypes'!$A$5:$A$23,0))),"check size") -> 2 | H28: =IFERROR($G28*$F28,"") -> 0.4 | I28: =IFERROR($G28*(1-$F28),"") -> 1.6 | J28: current FTE 6 | K28: AU
B29: Platform Overhead | H29: ='0.2 Data Config'!$L$16 -> 0.165
B30: Energy Solutions Total | G30: =SUM(G27:G28) -> 4 | H30: =SUM(H27:H29) -> 0.965 | I30: =SUM(I27:I28) -> 3.2
B32: Platform: B2B
B33: Squad | C33: Squad Type | D33: Size | E33: On/Off | F33: Support % | G33: Total Squad Cost ($m) | H33: TDD Cost ($m) | I33: Funded outside TDD ($m) | K33: Fund
B34: B2B | C34: Configuration / Integration | D34: L | E34: Onshore | F34: 0.3 | G34: =IFERROR(IF($E34="Onshore",INDEX('0.3 Squad Archetypes'!$G$5:$G$23,MATCH($C34&"|"&$D34,'0.3 Squad Archetypes'!$A$5:$A$23,0)),INDEX('0.3 Squad Archetypes'!$H$5:$H$23,MATCH($C34&"|"&$D34,'0.3 Squad Archetypes'!$A$5:$A$23,0))),"check size") -> 2.1 | H34: =IFERROR($G34*$F34,"") -> 0.63 | I34: =IFERROR($G34*(1-$F34),"") -> 1.47 | K34: AU
B35: Platform Overhead | H35: ='0.2 Data Config'!$L$16 -> 0.165
B36: B2B Total | G36: =SUM(G34:G34) -> 2.1 | H36: =SUM(H34:H35) -> 0.795 | I36: =SUM(I34:I34) -> 1.47
B38: TDD squad cost - AU funded (Fund toggles) ($m) | C38: =SUMIF(K27:K28,"AU",H27:H28)+SUMIF(K34:K34,"AU",H34:H34) -> 1.43
B39: TDD squad cost - NZ funded (Fund toggles) ($m) | C39: =SUMIF(K27:K28,"NZ",H27:H28)+SUMIF(K34:K34,"NZ",H34:H34) -> 0

Sheet 1.9 Commercial Fuels
B2: Commercial Fuels
B4: Portfolio Summary | G4: Budget vs TDD Cost
B5: Cost | C5: TDD ($m) | D5: Other ($m) | E5: Total Commercial Fuels Cost ($m) | G5: TDD Lights On Budget (people - 0.2 Data Config) | H5: ='0.2 Data Config'!$E$15 -> 2.5
B6: Portfolio Overhead (see 0.2 Data Config) | C6: ='0.2 Data Config'!$L$10 -> 0.7495 | E6: =C6 -> 0.7495 | G6: Overheads & Support (this model) | H6: =C9 -> 2.0845
B7: Platform Overheads | C7: =SUM(H27,H33,H39) -> 0.495 | E7: =C7 -> 0.495 | G7: Variance (budget less cost) | H7: =H5-H6 -> 0.4155
B8: Squad Support Costs | C8: =SUM(H25,H26,H32,H38) -> 0.84 | D8: =SUM(I25,I26,I32,I38) -> 5.06 | E8: =C8+D8 -> 5.9
B9: Total Cost | C9: =SUM(C6:C8) -> 2.0845 | D9: =SUM(D6:D8) -> 5.06 | E9: =C9+D9 -> 7.1445
G10: Other funding
B11: Total Commercial Fuels budget | E11: =SUM(H12:H17) -> 45.4 | G11: Budget line | H11: Budget ($m) | I11: Amount that can be allocated to people | J11: Remaining for non-people ($m)
B12: Reconciled to Finance | E12: ='0.1 Budget Table (Fin)'!Q8 -> 40.5 | G12: Commercial Fuels Lights On | H12: ='0.1 Budget Table (Fin)'!L8 -> 13.4 | I12: ='0.1 Budget Table (Fin)'!G8 -> 0 | J12: =IFERROR(H12-I12,0) -> 13.4
G13: OpEx Initiatives | H13: ='0.1 Budget Table (Fin)'!N8 -> 6.1 | I13: 0 | J13: =IFERROR(H13-I13,0) -> 6.1
B14: Total to fund | G14: CapEx | H14: ='0.1 Budget Table (Fin)'!P8 -> 6.8 | I14: 1.7 | J14: =IFERROR(H14-I14,0) -> 5.1
B15: TDD Variance | C15: =MAX(0,-H7) -> 0 | G15: TDD CapEx | H15: ='0.1 Budget Table (Fin)'!P5 -> 4.9 | J15: =IFERROR(H15-I15,0) -> 4.9
B16: Other Variance | C16: =MAX(0,I20) -> 1.96 | G16: Significant Items | H16: ='0.1 Budget Table (Fin)'!O8 -> 14.2 | I16: =I38 -> 1.4 | J16: =IFERROR(H16-I16,0) -> 12.8
B17: Total | C17: =C15+C16 -> 1.96 | G17: Depreciation | H17: ='0.1 Budget Table (Fin)'!M8 -> 0 | I17: 0 | J17: =IFERROR(H17-I17,0) -> 0
G18: Total applied | I18: =SUM(I12:I17) -> 3.1
G19: Other cost (this model) | I19: =D9 -> 5.06
G20: Left to fund | I20: =I19-I18 -> 1.96
B23: Platform: Trading & Shipping
B24: Squad | C24: Squad Type | D24: Size | E24: On/Off | F24: Support % | G24: Total Squad Cost ($m) | H24: TDD Cost ($m) | I24: Funded outside TDD ($m) | K24: Fund
B25: Trading & Shipping | C25: Configuration / Integration | D25: M | E25: Onshore | F25: 0.4 | G25: =IFERROR(IF($E25="Onshore",INDEX('0.3 Squad Archetypes'!$G$5:$G$23,MATCH($C25&"|"&$D25,'0.3 Squad Archetypes'!$A$5:$A$23,0)),INDEX('0.3 Squad Archetypes'!$H$5:$H$23,MATCH($C25&"|"&$D25,'0.3 Squad Archetypes'!$A$5:$A$23,0))),"check size") -> 1.4 | H25: =IFERROR($G25*$F25,"") -> 0.56 | I25: =IFERROR($G25*(1-$F25),"") -> 0.84 | K25: AU
B26: Trading & Shipping Data | C26: Enterprise Data and Insights | D26: M | E26: Onshore | F26: 0 | G26: =IFERROR(IF($E26="Onshore",INDEX('0.3 Squad Archetypes'!$G$5:$G$23,MATCH($C26&"|"&$D26,'0.3 Squad Archetypes'!$A$5:$A$23,0)),INDEX('0.3 Squad Archetypes'!$H$5:$H$23,MATCH($C26&"|"&$D26,'0.3 Squad Archetypes'!$A$5:$A$23,0))),"check size") -> 1.7 | H26: =IFERROR($G26*$F26,"") -> 0 | I26: =IFERROR($G26*(1-$F26),"") -> 1.7 | J26: Fully funded by CF | K26: AU
B27: Platform Overhead | H27: ='0.2 Data Config'!$L$16 -> 0.165
B28: Trading & Shipping Total | G28: =SUM(G25:G26) -> 3.1 | H28: =SUM(H25:H27) -> 0.725 | I28: =SUM(I25:I26) -> 2.54
B30: Platform: Supply
B31: Squad | C31: Squad Type | D31: Size | E31: On/Off | F31: Support % | G31: Total Squad Cost ($m) | H31: TDD Cost ($m) | I31: Funded outside TDD ($m) | K31: Fund
B32: Supply | C32: Configuration / Integration | D32: M | E32: Onshore | F32: 0.2 | G32: =IFERROR(IF($E32="Onshore",INDEX('0.3 Squad Archetypes'!$G$5:$G$23,MATCH($C32&"|"&$D32,'0.3 Squad Archetypes'!$A$5:$A$23,0)),INDEX('0.3 Squad Archetypes'!$H$5:$H$23,MATCH($C32&"|"&$D32,'0.3 Squad Archetypes'!$A$5:$A$23,0))),"check size") -> 1.4 | H32: =IFERROR($G32*$F32,"") -> 0.28 | I32: =IFERROR($G32*(1-$F32),"") -> 1.12 | K32: AU
B33: Platform Overhead | H33: ='0.2 Data Config'!$L$16 -> 0.165
B34: Supply Total | G34: =SUM(G32:G32) -> 1.4 | H34: =SUM(H32:H33) -> 0.445 | I34: =SUM(I32:I32) -> 1.12
B36: Platform: CTRM
B37: Squad | C37: Squad Type | D37: Size | E37: On/Off | F37: Support % | G37: Total Squad Cost ($m) | H37: TDD Cost ($m) | I37: Funded outside TDD ($m) | K37: Fund
B38: CTRM | C38: Strategic Programs | E38: Onshore | F38: 0 | G38: 1.4 | H38: =IFERROR($G38*$F38,"") -> 0 | I38: =IFERROR($G38*(1-$F38),"") -> 1.4 | J38: Fully funded by CTRM | K38: AU
B39: Platform Overhead | H39: ='0.2 Data Config'!$L$16 -> 0.165
B40: CTRM Total | G40: =SUM(G38:G38) -> 1.4 | H40: =SUM(H38:H39) -> 0.165 | I40: =SUM(I38:I38) -> 1.4
B42: TDD squad cost - AU funded (Fund toggles) ($m) | C42: =SUMIF(K25:K26,"AU",H25:H26)+SUMIF(K32:K32,"AU",H32:H32)+SUMIF(K38:K38,"AU",H38:H38) -> 0.84
B43: TDD squad cost - NZ funded (Fund toggles) ($m) | C43: =SUMIF(K25:K26,"NZ",H25:H26)+SUMIF(K32:K32,"NZ",H32:H32)+SUMIF(K38:K38,"NZ",H38:H38) -> 0

Sheet 1.10 Z Retail
B2: Z Retail
B4: Portfolio Summary | G4: Budget vs TDD Cost
B5: Cost | C5: TDD ($m) | D5: Other ($m) | E5: Total Z Retail Cost ($m) | G5: TDD Lights On Budget (people - 0.2 Data Config) | H5: ='0.2 Data Config'!$E$12 -> 2.5
B6: Portfolio Overhead (see 0.2 Data Config) | C6: ='0.2 Data Config'!$L$10 -> 0.7495 | E6: =C6 -> 0.7495 | G6: Overheads & Support (this model) | H6: =C9 -> 5.3995
B7: Platform Overheads | C7: =SUM(H25,H32) -> 0.33 | E7: =C7 -> 0.33 | G7: Variance (budget less cost) | H7: =H5-H6 -> -2.8995 | I7: Z funded - out of Z OpEx
B8: Squad Support Costs | C8: =SUM(H24,H30,H31) -> 4.32 | D8: =SUM(I24,I30,I31) -> 1.08 | E8: =C8+D8 -> 5.4
B9: Total Cost | C9: =SUM(C6:C8) -> 5.3995 | D9: =SUM(D6:D8) -> 1.08 | E9: =C9+D9 -> 6.4795
G10: Other funding
B11: Total Z-Energy budget | E11: =SUM(H12:H16) -> 76.6 | G11: Budget line | H11: Budget ($m) | I11: Amount that can be allocated to people | J11: Remaining for non-people ($m)
B12: Reconciled to Finance | E12: ='0.1 Budget Table (Fin)'!Q6 -> 76.6 | G12: Z-Energy Lights On | H12: ='0.1 Budget Table (Fin)'!L6 -> 52.2 | J12: =IFERROR(H12-I12,0) -> 52.2
G13: OpEx Initiatives | H13: ='0.1 Budget Table (Fin)'!N6 -> 1.4 | I13: 0 | J13: =IFERROR(H13-I13,0) -> 1.4
B14: Total to fund | G14: CapEx | H14: ='0.1 Budget Table (Fin)'!P6 -> 11.7 | I14: 1.08 | J14: =IFERROR(H14-I14,0) -> 10.62
B15: TDD Variance | C15: =MAX(0,-H7) -> 2.8995 | G15: Significant Items | H15: ='0.1 Budget Table (Fin)'!$O$6 -> - | I15: 0 | J15: =IFERROR(H15-I15,0) -> 0
B16: Other Variance | C16: =MAX(0,I19) -> 0 | G16: Depreciation | H16: ='0.1 Budget Table (Fin)'!M6 -> 11.3 | I16: 0 | J16: =IFERROR(H16-I16,0) -> 11.3
B17: Total | C17: =C15+C16 -> 2.8995 | G17: Total applied | I17: =SUM(I12:I16) -> 1.08
G18: Other cost (this model) | I18: =D9 -> 1.08
G19: Left to fund | I19: =MAX(0,ROUND(I18-I17,6)) -> 0
B22: Platform: Z Supply
B23: Squad | C23: Squad Type | D23: Size | E23: On/Off | F23: Support % | G23: Total Squad Cost ($m) | H23: TDD Cost ($m) | I23: Funded outside TDD ($m) | K23: Fund
B24: Z Supply | C24: Build and Run | D24: M | E24: Onshore | F24: 0.8 | G24: =IFERROR(IF($E24="Onshore",INDEX('0.3 Squad Archetypes'!$G$5:$G$23,MATCH($C24&"|"&$D24,'0.3 Squad Archetypes'!$A$5:$A$23,0)),INDEX('0.3 Squad Archetypes'!$H$5:$H$23,MATCH($C24&"|"&$D24,'0.3 Squad Archetypes'!$A$5:$A$23,0))),"check size") -> 2 | H24: =IFERROR($G24*$F24,"") -> 1.6 | I24: =IFERROR($G24*(1-$F24),"") -> 0.4 | J24: 100% Z covered | K24: NZ
B25: Platform Overhead | H25: ='0.2 Data Config'!$L$16 -> 0.165
B26: Z Supply Total | G26: =SUM(G24:G24) -> 2 | H26: =SUM(H24:H25) -> 1.765 | I26: =SUM(I24:I24) -> 0.4
B28: Platform: Z Customer
B29: Squad | C29: Squad Type | D29: Size | E29: On/Off | F29: Support % | G29: Total Squad Cost ($m) | H29: TDD Cost ($m) | I29: Funded outside TDD ($m) | K29: Fund
B30: Site Systems | C30: Configuration / Integration | D30: M | E30: Onshore | F30: 0.8 | G30: =IFERROR(IF($E30="Onshore",INDEX('0.3 Squad Archetypes'!$G$5:$G$23,MATCH($C30&"|"&$D30,'0.3 Squad Archetypes'!$A$5:$A$23,0)),INDEX('0.3 Squad Archetypes'!$H$5:$H$23,MATCH($C30&"|"&$D30,'0.3 Squad Archetypes'!$A$5:$A$23,0))),"check size") -> 1.4 | H30: =IFERROR($G30*$F30,"") -> 1.12 | I30: =IFERROR($G30*(1-$F30),"") -> 0.28 | J30: 20% is CapEx | K30: NZ
B31: Z Retail Backend | C31: Build and Run | D31: M | E31: Onshore | F31: 0.8 | G31: =IFERROR(IF($E31="Onshore",INDEX('0.3 Squad Archetypes'!$G$5:$G$23,MATCH($C31&"|"&$D31,'0.3 Squad Archetypes'!$A$5:$A$23,0)),INDEX('0.3 Squad Archetypes'!$H$5:$H$23,MATCH($C31&"|"&$D31,'0.3 Squad Archetypes'!$A$5:$A$23,0))),"check size") -> 2 | H31: =IFERROR($G31*$F31,"") -> 1.6 | I31: =IFERROR($G31*(1-$F31),"") -> 0.4 | K31: NZ
B32: Platform Overhead | H32: ='0.2 Data Config'!$L$16 -> 0.165
B33: Z Customer Total | G33: =SUM(G30:G31) -> 3.4 | H33: =SUM(H30:H32) -> 2.885 | I33: =SUM(I30:I31) -> 0.68
B35: TDD squad cost - AU funded (Fund toggles) ($m) | C35: =SUMIF(K24:K24,"AU",H24:H24)+SUMIF(K30:K31,"AU",H30:H31) -> 0
B36: TDD squad cost - NZ funded (Fund toggles) ($m) | C36: =SUMIF(K24:K24,"NZ",H24:H24)+SUMIF(K30:K31,"NZ",H30:H31) -> 4.32

Sheet 1.11 TDD Cyber
B2: TDD Cyber
B4: Portfolio Summary | G4: Budget vs TDD Cost
B5: Cost | C5: TDD ($m) | D5: Other ($m) | E5: Total TDD Cyber Cost ($m) | G5: TDD Lights On Budget (people - 0.2 Data Config) | H5: ='0.2 Data Config'!$E$23 -> 3.5
B6: Portfolio Overhead (see 0.2 Data Config) | C6: ='0.2 Data Config'!$L$10 -> 0.7495 | E6: =C6 -> 0.7495 | G6: Overheads & Support (this model) | H6: =C9 -> 11.830489
B7: Platform Overheads | C7: =SUM(H26) -> 0.165 | E7: =C7 -> 0.165 | G7: Variance (budget less cost) | H7: =H5-H6 -> -8.330489
B8: Squad Support Costs | C8: =SUM(H24,H25) -> 10.915989 | D8: =SUM(I24,I25) -> 0 | E8: =C8+D8 -> 10.915989
B9: Total Cost | C9: =SUM(C6:C8) -> 11.830489 | D9: =SUM(D6:D8) -> 0 | E9: =C9+D9 -> 11.830489
G10: Other funding
B11: Lights On funded from the TDD allocation above (Data Config). Shared TDD Corporate pool sits on 2.4 COE Summary. | G11: Funding position
G12: Other cost (this model) | I12: =D9 -> 0
B13: Total to fund | F13: Cyber uplift bucket | G13: Funded from TDD Corporate pool (2.4 COE Summary) | I13: 0
B14: TDD Variance | C14: =MAX(0,-H7) -> 8.330489 | G14: Left to fund | I14: =I12-I13-I16 -> 0
B15: Other Variance | C15: =MAX(0,I14) -> 0 | G15: Cyber funding buckets | H15: Budget ($m) | I15: Applied ($m) | J15: Remaining ($m)
B16: Total | C16: =C14+C15 -> 8.330489 | D16: Identity - can be charging back | G16: Cyber CapEx (Monitoring) | H16: 0.5 | I16: 0 | J16: =H16-I16 -> 0.5
B17: Cyber Architects could be charged back | D17: Governance, Risk & Complaince - Some can be charged back
B18: Initiatives within Cyber & outside
B19: 4x Architects can be charged out 100%
B22: Platform: TDD Cyber, Risk & Service Ops
B23: Squad | C23: Squad Type | D23: Size | E23: On/Off | F23: Support % | G23: Total Squad Cost ($m) | H23: TDD Cost ($m) | I23: Funded outside TDD ($m) | J23: Fund
B24: Cyber & Risk | C24: Strategic Programs | E24: Onshore | F24: 1 | G24: ='2.3 Cyber Roles'!$F$6 -> 6.5289684 | H24: =IFERROR($G24*$F24,"") -> 6.5289684 | I24: =IFERROR($G24*(1-$F24),"") -> 0 | J24: AU
B25: Service Operations | C25: Strategic Programs | E25: Onshore | F25: 1 | G25: ='2.3 Cyber Roles'!$F$7 -> 4.3870206 | H25: =IFERROR($G25*$F25,"") -> 4.3870206 | I25: =IFERROR($G25*(1-$F25),"") -> 0 | J25: AU
B26: Platform Overhead | H26: ='0.2 Data Config'!$L$16 -> 0.165
B27: TDD Cyber Total | G27: =SUM(G24:G25) -> 10.915989 | H27: =SUM(H24:H26) -> 11.080989 | I27: =SUM(I24:I25) -> 0
B29: TDD squad cost - AU funded (Fund toggles) ($m) | C29: =SUMIF(J24:J25,"AU",H24:H25) -> 10.915989
B30: TDD squad cost - NZ funded (Fund toggles) ($m) | C30: =SUMIF(J24:J25,"NZ",H24:H25) -> 0

Sheet - ROLL-UP -
B2: ROLL-UP >>>

Sheet 2.1 BP&T
B2: Business Partnering & Transformation - roles and funding
B4: Summary
B5: Category | C5: Roles | D5: Filled | E5: Vacant | F5: Planned spend ($m) | G5: Budget to draw down ($m) | H5: Left to fund ($m)
B6: Business Partnering | C6: =COUNTIF($G$21:$G$44,$B6) -> 10 | D6: =COUNTIFS($G$21:$G$44,$B6,$F$21:$F$44,"Filled") -> 9 | E6: =COUNTIFS($G$21:$G$44,$B6,$F$21:$F$44,"Vacant") -> 1 | F6: =SUMIF($G$21:$G$44,$B6,$J$21:$J$44) -> 3.2925626 | G6: =C15 -> 3.892 | H6: =MAX(0,F6-G6) -> 0
B7: Transformation | C7: =COUNTIF($G$21:$G$44,$B7) -> 14 | D7: =COUNTIFS($G$21:$G$44,$B7,$F$21:$F$44,"Filled") -> 6 | E7: =COUNTIFS($G$21:$G$44,$B7,$F$21:$F$44,"Vacant") -> 8 | F7: =SUMIF($G$21:$G$44,$B7,$J$21:$J$44) -> 3.1079992 | G7: =C16 -> 2 | H7: =MAX(0,F7-G7) -> 1.1079992
B8: Total | C8: =SUM(C6:C7) -> 24 | D8: =SUM(D6:D7) -> 15 | E8: =SUM(E6:E7) -> 9 | F8: =SUM(F6:F7) -> 6.4005618 | G8: =SUM(G6:G7) -> 5.892 | H8: =SUM(H6:H7) -> 1.1079992
B10: Portfolios funded (2.0 Group Summary) | C10: =COUNTA('2.5 Group Summary'!$B$6:$B$16) -> 11 | E10: Cost - AU and other funded ($m) | F10: =SUMIF($E$21:$E$44,"<>NZ",$J$21:$J$44) -> 5.6586105
B11: Business Partner allocation per portfolio (FTE - 0.2 Data Config) | C11: ='0.2 Data Config'!$K$7 -> 0.4 | E11: Cost - NZ funded ($m) | F11: =SUMIF($E$21:$E$44,"NZ",$J$21:$J$44) -> 0.74195127
B12: Business Partner FTEs funded by portfolio overheads | C12: =C10*C11 -> 4.4
B13: Business Partner funding from portfolio overheads ($m) | C13: =COUNTA('2.5 Group Summary'!$B$6:$B$16)*'0.2 Data Config'!$L$7 -> 1.892
B14: COE - Business Partnering allocation ($m) - 0.2 Data Config | C14: ='0.2 Data Config'!$E$9 -> 2
B15: Total Business Partnering budget ($m) | C15: =C13+C14 -> 3.892
B16: COE - Transformation allocation ($m) - 0.2 Data Config | C16: ='0.2 Data Config'!$E$8 -> 2
B17: Total budget to draw down ($m) | C17: =C15+C16 -> 5.892
B19: Roles
B20: Name | C20: Position Title | D20: Department | E20: Country | F20: Status | G20: Category | H20: On/Off | I20: Full Cost AUD ($) | J20: Model cost ($m)
B21: =Sheet2!$B$70 -> Briony Scott | C21: =SUBSTITUTE(SUBSTITUTE(Sheet2!$C$70,"–","-"),"—","-") -> Service & Contract Specialist AU | D21: =Sheet2!$G$70 -> Commercial | E21: =Sheet2!$M$70 -> Australia | F21: =IF(LOWER(Sheet2!$Q$70)="v","Vacant",IF(LOWER(Sheet2!$Q$70)="pause","Paused",IF(LOWER(Sheet2!$Q$70)="cxc","Contractor","Filled"))) -> Filled | G21: =IF(Sheet2!$G$70="Transformation","Transformation","Business Partnering") -> Business Partnering | H21: Onshore | I21: =Sheet2!$AA$70 -> 205056 | J21: =IF($H21="Offshore",$I21*'0.3 Squad Archetypes'!$K$5,$I21)/1000000 -> 0.205056
B22: =Sheet2!$B$71 -> Conli Mills | C22: =SUBSTITUTE(SUBSTITUTE(Sheet2!$C$71,"–","-"),"—","-") -> TDD BP - Infrastructure | D22: =Sheet2!$G$71 -> TDD Business Partner | E22: =Sheet2!$M$71 -> Australia | F22: =IF(LOWER(Sheet2!$Q$71)="v","Vacant",IF(LOWER(Sheet2!$Q$71)="pause","Paused",IF(LOWER(Sheet2!$Q$71)="cxc","Contractor","Filled"))) -> Filled | G22: =IF(Sheet2!$G$71="Transformation","Transformation","Business Partnering") -> Business Partnering | H22: Onshore | I22: =Sheet2!$AA$71 -> 297150 | J22: =IF($H22="Offshore",$I22*'0.3 Squad Archetypes'!$K$5,$I22)/1000000 -> 0.29715
B23: =Sheet2!$B$72 -> Helen Ngu | C23: =SUBSTITUTE(SUBSTITUTE(Sheet2!$C$72,"–","-"),"—","-") -> Service & Contract Specialist NZ | D23: =Sheet2!$G$72 -> Commercial | E23: =Sheet2!$M$72 -> NZ | F23: =IF(LOWER(Sheet2!$Q$72)="v","Vacant",IF(LOWER(Sheet2!$Q$72)="pause","Paused",IF(LOWER(Sheet2!$Q$72)="cxc","Contractor","Filled"))) -> Filled | G23: =IF(Sheet2!$G$72="Transformation","Transformation","Business Partnering") -> Business Partnering | H23: Onshore | I23: =Sheet2!$AA$72 -> 151002.49 | J23: =IF($H23="Offshore",$I23*'0.3 Squad Archetypes'!$K$5,$I23)/1000000 -> 0.15100249
B24: =Sheet2!$B$73 -> Jane Esclandra | C24: =SUBSTITUTE(SUBSTITUTE(Sheet2!$C$73,"–","-"),"—","-") -> Software Asset Specialist | D24: =Sheet2!$G$73 -> Commercial | E24: =Sheet2!$M$73 -> Australia | F24: =IF(LOWER(Sheet2!$Q$73)="v","Vacant",IF(LOWER(Sheet2!$Q$73)="pause","Paused",IF(LOWER(Sheet2!$Q$73)="cxc","Contractor","Filled"))) -> Filled | G24: =IF(Sheet2!$G$73="Transformation","Transformation","Business Partnering") -> Business Partnering | H24: Onshore | I24: =Sheet2!$AA$73 -> 183455.7 | J24: =IF($H24="Offshore",$I24*'0.3 Squad Archetypes'!$K$5,$I24)/1000000 -> 0.1834557
B25: =Sheet2!$B$74 -> Jeannie Chu | C25: =SUBSTITUTE(SUBSTITUTE(Sheet2!$C$74,"–","-"),"—","-") -> Snr Finance Support Administrator | D25: =Sheet2!$G$74 -> Transformation | E25: =Sheet2!$M$74 -> Australia | F25: =IF(LOWER(Sheet2!$Q$74)="v","Vacant",IF(LOWER(Sheet2!$Q$74)="pause","Paused",IF(LOWER(Sheet2!$Q$74)="cxc","Contractor","Filled"))) -> Filled | G25: =IF(Sheet2!$G$74="Transformation","Transformation","Business Partnering") -> Transformation | H25: Onshore | I25: =Sheet2!$AA$74 -> 147687.65 | J25: =IF($H25="Offshore",$I25*'0.3 Squad Archetypes'!$K$5,$I25)/1000000 -> 0.14768765
B26: =Sheet2!$B$75 -> Jenny Chan | C26: =SUBSTITUTE(SUBSTITUTE(Sheet2!$C$75,"–","-"),"—","-") -> Project Finance Lead | D26: =Sheet2!$G$75 -> Transformation | E26: =Sheet2!$M$75 -> Australia | F26: =IF(LOWER(Sheet2!$Q$75)="v","Vacant",IF(LOWER(Sheet2!$Q$75)="pause","Paused",IF(LOWER(Sheet2!$Q$75)="cxc","Contractor","Filled"))) -> Filled | G26: =IF(Sheet2!$G$75="Transformation","Transformation","Business Partnering") -> Transformation | H26: Onshore | I26: =Sheet2!$AA$75 -> 206124 | J26: =IF($H26="Offshore",$I26*'0.3 Squad Archetypes'!$K$5,$I26)/1000000 -> 0.206124
B27: =Sheet2!$B$76 -> Malcolm Deare | C27: =SUBSTITUTE(SUBSTITUTE(Sheet2!$C$76,"–","-"),"—","-") -> TDD BP, Group Functions | D27: =Sheet2!$G$76 -> TDD Business Partner | E27: =Sheet2!$M$76 -> Australia | F27: =IF(LOWER(Sheet2!$Q$76)="v","Vacant",IF(LOWER(Sheet2!$Q$76)="pause","Paused",IF(LOWER(Sheet2!$Q$76)="cxc","Contractor","Filled"))) -> Filled | G27: =IF(Sheet2!$G$76="Transformation","Transformation","Business Partnering") -> Business Partnering | H27: Onshore | I27: =Sheet2!$AA$76 -> 298100 | J27: =IF($H27="Offshore",$I27*'0.3 Squad Archetypes'!$K$5,$I27)/1000000 -> 0.2981
B28: =Sheet2!$B$77 -> Maria Somera | C28: =SUBSTITUTE(SUBSTITUTE(Sheet2!$C$77,"–","-"),"—","-") -> Technology Finance Analyst | D28: =Sheet2!$G$77 -> Transformation | E28: =Sheet2!$M$77 -> Australia | F28: =IF(LOWER(Sheet2!$Q$77)="v","Vacant",IF(LOWER(Sheet2!$Q$77)="pause","Paused",IF(LOWER(Sheet2!$Q$77)="cxc","Contractor","Filled"))) -> Filled | G28: =IF(Sheet2!$G$77="Transformation","Transformation","Business Partnering") -> Transformation | H28: Onshore | I28: =Sheet2!$AA$77 -> 179313.4 | J28: =IF($H28="Offshore",$I28*'0.3 Squad Archetypes'!$K$5,$I28)/1000000 -> 0.1793134
B29: =Sheet2!$B$78 -> Matt Saunders | C29: =SUBSTITUTE(SUBSTITUTE(Sheet2!$C$78,"–","-"),"—","-") -> Scrum Master | D29: =Sheet2!$G$78 -> Transformation | E29: =Sheet2!$M$78 -> NZ | F29: =IF(LOWER(Sheet2!$Q$78)="v","Vacant",IF(LOWER(Sheet2!$Q$78)="pause","Paused",IF(LOWER(Sheet2!$Q$78)="cxc","Contractor","Filled"))) -> Filled | G29: =IF(Sheet2!$G$78="Transformation","Transformation","Business Partnering") -> Transformation | H29: Onshore | I29: =Sheet2!$AA$78 -> 147754.8 | J29: =IF($H29="Offshore",$I29*'0.3 Squad Archetypes'!$K$5,$I29)/1000000 -> 0.1477548
B30: =Sheet2!$B$79 -> Neil Reilly | C30: =SUBSTITUTE(SUBSTITUTE(Sheet2!$C$79,"–","-"),"—","-") -> TDD BP - T&S | D30: =Sheet2!$G$79 -> TDD Business Partner | E30: =Sheet2!$M$79 -> Singapore | F30: =IF(LOWER(Sheet2!$Q$79)="v","Vacant",IF(LOWER(Sheet2!$Q$79)="pause","Paused",IF(LOWER(Sheet2!$Q$79)="cxc","Contractor","Filled"))) -> Filled | G30: =IF(Sheet2!$G$79="Transformation","Transformation","Business Partnering") -> Business Partnering | H30: Onshore | I30: =Sheet2!$AA$79 -> 666087.5 | J30: =IF($H30="Offshore",$I30*'0.3 Squad Archetypes'!$K$5,$I30)/1000000 -> 0.6660875
B31: =Sheet2!$B$80 -> Ruth Chou | C31: =SUBSTITUTE(SUBSTITUTE(Sheet2!$C$80,"–","-"),"—","-") -> Portfolio Reporting Manager | D31: =Sheet2!$G$80 -> Transformation | E31: =Sheet2!$M$80 -> Australia | F31: =IF(LOWER(Sheet2!$Q$80)="v","Vacant",IF(LOWER(Sheet2!$Q$80)="pause","Paused",IF(LOWER(Sheet2!$Q$80)="cxc","Contractor","Filled"))) -> Filled | G31: =IF(Sheet2!$G$80="Transformation","Transformation","Business Partnering") -> Transformation | H31: Onshore | I31: =Sheet2!$AA$80 -> 293316.85 | J31: =IF($H31="Offshore",$I31*'0.3 Squad Archetypes'!$K$5,$I31)/1000000 -> 0.29331685
B32: =Sheet2!$B$81 -> Sam Chan | C32: =SUBSTITUTE(SUBSTITUTE(Sheet2!$C$81,"–","-"),"—","-") -> FinOps Manager | D32: =Sheet2!$G$81 -> Transformation | E32: =Sheet2!$M$81 -> Australia | F32: =IF(LOWER(Sheet2!$Q$81)="v","Vacant",IF(LOWER(Sheet2!$Q$81)="pause","Paused",IF(LOWER(Sheet2!$Q$81)="cxc","Contractor","Filled"))) -> Filled | G32: =IF(Sheet2!$G$81="Transformation","Transformation","Business Partnering") -> Transformation | H32: Onshore | I32: =Sheet2!$AA$81 -> 225788.55 | J32: =IF($H32="Offshore",$I32*'0.3 Squad Archetypes'!$K$5,$I32)/1000000 -> 0.22578855
B33: =Sheet2!$B$82 -> Shelley Crawford | C33: =SUBSTITUTE(SUBSTITUTE(Sheet2!$C$82,"–","-"),"—","-") -> TDD BP - Z | D33: =Sheet2!$G$82 -> TDD Business Partner | E33: =Sheet2!$M$82 -> NZ | F33: =IF(LOWER(Sheet2!$Q$82)="v","Vacant",IF(LOWER(Sheet2!$Q$82)="pause","Paused",IF(LOWER(Sheet2!$Q$82)="cxc","Contractor","Filled"))) -> Filled | G33: =IF(Sheet2!$G$82="Transformation","Transformation","Business Partnering") -> Business Partnering | H33: Onshore | I33: =Sheet2!$AA$82 -> 291422 | J33: =IF($H33="Offshore",$I33*'0.3 Squad Archetypes'!$K$5,$I33)/1000000 -> 0.291422
B34: =Sheet2!$B$83 -> Thomas Reid | C34: =SUBSTITUTE(SUBSTITUTE(Sheet2!$C$83,"–","-"),"—","-") -> TDD BP - Retail & Customer - Store Digital | D34: =Sheet2!$G$83 -> TDD Business Partner | E34: =Sheet2!$M$83 -> Australia | F34: =IF(LOWER(Sheet2!$Q$83)="v","Vacant",IF(LOWER(Sheet2!$Q$83)="pause","Paused",IF(LOWER(Sheet2!$Q$83)="cxc","Contractor","Filled"))) -> Filled | G34: =IF(Sheet2!$G$83="Transformation","Transformation","Business Partnering") -> Business Partnering | H34: Onshore | I34: =Sheet2!$AA$83 -> 417425 | J34: =IF($H34="Offshore",$I34*'0.3 Squad Archetypes'!$K$5,$I34)/1000000 -> 0.417425
B35: =Sheet2!$B$84 -> Vacant | C35: =SUBSTITUTE(SUBSTITUTE(Sheet2!$C$84,"–","-"),"—","-") -> Commercial Director | D35: =Sheet2!$G$84 -> Commercial | E35: =Sheet2!$M$84 -> Australia | F35: =IF(LOWER(Sheet2!$Q$84)="v","Vacant",IF(LOWER(Sheet2!$Q$84)="pause","Paused",IF(LOWER(Sheet2!$Q$84)="cxc","Contractor","Filled"))) -> Vacant | G35: =IF(Sheet2!$G$84="Transformation","Transformation","Business Partnering") -> Business Partnering | H35: Onshore | I35: =Sheet2!$AA$84 -> 439500 | J35: =IF($H35="Offshore",$I35*'0.3 Squad Archetypes'!$K$5,$I35)/1000000 -> 0.4395
B36: =Sheet2!$B$85 -> Vacant | C36: =SUBSTITUTE(SUBSTITUTE(Sheet2!$C$85,"–","-"),"—","-") -> Head of Transformation | D36: =Sheet2!$G$85 -> Transformation | E36: =Sheet2!$M$85 -> Australia | F36: =IF(LOWER(Sheet2!$Q$85)="v","Vacant",IF(LOWER(Sheet2!$Q$85)="pause","Paused",IF(LOWER(Sheet2!$Q$85)="cxc","Contractor","Filled"))) -> Vacant | G36: =IF(Sheet2!$G$85="Transformation","Transformation","Business Partnering") -> Transformation | H36: Onshore | I36: =Sheet2!$AA$85 -> 367900 | J36: =IF($H36="Offshore",$I36*'0.3 Squad Archetypes'!$K$5,$I36)/1000000 -> 0.3679
B37: =Sheet2!$B$86 -> Vacant | C37: =SUBSTITUTE(SUBSTITUTE(Sheet2!$C$86,"–","-"),"—","-") -> Delivery Systems Analyst | D37: =Sheet2!$G$86 -> Transformation | E37: =Sheet2!$M$86 -> Australia | F37: =IF(LOWER(Sheet2!$Q$86)="v","Vacant",IF(LOWER(Sheet2!$Q$86)="pause","Paused",IF(LOWER(Sheet2!$Q$86)="cxc","Contractor","Filled"))) -> Vacant | G37: =IF(Sheet2!$G$86="Transformation","Transformation","Business Partnering") -> Transformation | H37: Onshore | I37: =Sheet2!$AA$86 -> 202853.25 | J37: =IF($H37="Offshore",$I37*'0.3 Squad Archetypes'!$K$5,$I37)/1000000 -> 0.20285325
B38: =Sheet2!$B$87 -> Vacant | C38: =SUBSTITUTE(SUBSTITUTE(Sheet2!$C$87,"–","-"),"—","-") -> Business Analysis Practice Lead | D38: =Sheet2!$G$87 -> Transformation | E38: =Sheet2!$M$87 -> Australia | F38: =IF(LOWER(Sheet2!$Q$87)="v","Vacant",IF(LOWER(Sheet2!$Q$87)="pause","Paused",IF(LOWER(Sheet2!$Q$87)="cxc","Contractor","Filled"))) -> Vacant | G38: =IF(Sheet2!$G$87="Transformation","Transformation","Business Partnering") -> Transformation | H38: Onshore | I38: =Sheet2!$AA$87 -> 231689.25 | J38: =IF($H38="Offshore",$I38*'0.3 Squad Archetypes'!$K$5,$I38)/1000000 -> 0.23168925
B39: =Sheet2!$B$88 -> Vacant | C39: =SUBSTITUTE(SUBSTITUTE(Sheet2!$C$88,"–","-"),"—","-") -> Delivery Assurance Manager | D39: =Sheet2!$G$88 -> Transformation | E39: =Sheet2!$M$88 -> Australia | F39: =IF(LOWER(Sheet2!$Q$88)="v","Vacant",IF(LOWER(Sheet2!$Q$88)="pause","Paused",IF(LOWER(Sheet2!$Q$88)="cxc","Contractor","Filled"))) -> Vacant | G39: =IF(Sheet2!$G$88="Transformation","Transformation","Business Partnering") -> Transformation | H39: Onshore | I39: =Sheet2!$AA$88 -> 275810.25 | J39: =IF($H39="Offshore",$I39*'0.3 Squad Archetypes'!$K$5,$I39)/1000000 -> 0.27581025
B40: =Sheet2!$B$89 -> Vacant | C40: =SUBSTITUTE(SUBSTITUTE(Sheet2!$C$89,"–","-"),"—","-") -> Delivery Capacity & Assurance Lead | D40: =Sheet2!$G$89 -> Transformation | E40: =Sheet2!$M$89 -> Australia | F40: =IF(LOWER(Sheet2!$Q$89)="v","Vacant",IF(LOWER(Sheet2!$Q$89)="pause","Paused",IF(LOWER(Sheet2!$Q$89)="cxc","Contractor","Filled"))) -> Vacant | G40: =IF(Sheet2!$G$89="Transformation","Transformation","Business Partnering") -> Transformation | H40: Onshore | I40: =Sheet2!$AA$89 -> 231689.25 | J40: =IF($H40="Offshore",$I40*'0.3 Squad Archetypes'!$K$5,$I40)/1000000 -> 0.23168925
B41: =Sheet2!$B$90 -> Vacant | C41: =SUBSTITUTE(SUBSTITUTE(Sheet2!$C$90,"–","-"),"—","-") -> Delivery Excellence Manager | D41: =Sheet2!$G$90 -> Transformation | E41: =Sheet2!$M$90 -> Australia | F41: =IF(LOWER(Sheet2!$Q$90)="v","Vacant",IF(LOWER(Sheet2!$Q$90)="pause","Paused",IF(LOWER(Sheet2!$Q$90)="cxc","Contractor","Filled"))) -> Vacant | G41: =IF(Sheet2!$G$90="Transformation","Transformation","Business Partnering") -> Transformation | H41: Onshore | I41: =Sheet2!$AA$90 -> 275810.25 | J41: =IF($H41="Offshore",$I41*'0.3 Squad Archetypes'!$K$5,$I41)/1000000 -> 0.27581025
B42: =Sheet2!$B$91 -> Vacant | C42: =SUBSTITUTE(SUBSTITUTE(Sheet2!$C$91,"–","-"),"—","-") -> Scrum Master | D42: =Sheet2!$G$91 -> Transformation | E42: =Sheet2!$M$91 -> NZ | F42: =IF(LOWER(Sheet2!$Q$91)="v","Vacant",IF(LOWER(Sheet2!$Q$91)="pause","Paused",IF(LOWER(Sheet2!$Q$91)="cxc","Contractor","Filled"))) -> Vacant | G42: =IF(Sheet2!$G$91="Transformation","Transformation","Business Partnering") -> Transformation | H42: Onshore | I42: =Sheet2!$AA$91 -> 151771.98 | J42: =IF($H42="Offshore",$I42*'0.3 Squad Archetypes'!$K$5,$I42)/1000000 -> 0.15177198
B43: =Sheet2!$B$92 -> Vacant | C43: =SUBSTITUTE(SUBSTITUTE(Sheet2!$C$92,"–","-"),"—","-") -> Portfolio Analyst | D43: =Sheet2!$G$92 -> Transformation | E43: =Sheet2!$M$92 -> Australia | F43: =IF(LOWER(Sheet2!$Q$92)="v","Vacant",IF(LOWER(Sheet2!$Q$92)="pause","Paused",IF(LOWER(Sheet2!$Q$92)="cxc","Contractor","Filled"))) -> Vacant | G43: =IF(Sheet2!$G$92="Transformation","Transformation","Business Partnering") -> Transformation | H43: Onshore | I43: =Sheet2!$AA$92 -> 170489.75 | J43: =IF($H43="Offshore",$I43*'0.3 Squad Archetypes'!$K$5,$I43)/1000000 -> 0.17048975
B44: =Sheet2!$B$93 -> Vaughn Scott | C44: =SUBSTITUTE(SUBSTITUTE(Sheet2!$C$93,"–","-"),"—","-") -> TDD BP - ES | D44: =Sheet2!$G$93 -> TDD Business Partner | E44: =Sheet2!$M$93 -> Australia | F44: =IF(LOWER(Sheet2!$Q$93)="v","Vacant",IF(LOWER(Sheet2!$Q$93)="pause","Paused",IF(LOWER(Sheet2!$Q$93)="cxc","Contractor","Filled"))) -> Filled | G44: =IF(Sheet2!$G$93="Transformation","Transformation","Business Partnering") -> Business Partnering | H44: Onshore | I44: =Sheet2!$AA$93 -> 343363.9 | J44: =IF($H44="Offshore",$I44*'0.3 Squad Archetypes'!$K$5,$I44)/1000000 -> 0.3433639
B45: Check - roles listed vs counted (must be 0) | C45: =COUNTA(B21:B44)-C8 -> 0
B47: Commercial roles sit in the Business Partnering bucket - the Department column shows where each role reports.

Sheet 2.2 SA&D
B2: Strategy, Architecture & Data - roles and funding
B4: Summary
B5: Category | C5: Roles | D5: Filled | E5: Vacant | F5: Paused | G5: Planned spend ($m) | H5: Budget to draw down ($m) | I5: Left to fund ($m)
B6: Strategy & Architecture | C6: =COUNTIF($G$22:$G$50,$B6) -> 20 | D6: =COUNTIFS($G$22:$G$50,$B6,$F$22:$F$50,"Filled") -> 7 | E6: =COUNTIFS($G$22:$G$50,$B6,$F$22:$F$50,"Vacant") -> 11 | F6: =COUNTIFS($G$22:$G$50,$B6,$F$22:$F$50,"Paused") -> 2 | G6: =SUMIF($G$22:$G$50,$B6,$J$22:$J$50) -> 4.320561 | H6: =C15 -> 3.54 | I6: =MAX(0,G6-H6) -> 0.780561
B7: Data | C7: =COUNTIF($G$22:$G$50,$B7) -> 9 | D7: =COUNTIFS($G$22:$G$50,$B7,$F$22:$F$50,"Filled") -> 7 | E7: =COUNTIFS($G$22:$G$50,$B7,$F$22:$F$50,"Vacant") -> 1 | F7: =COUNTIFS($G$22:$G$50,$B7,$F$22:$F$50,"Paused") -> 1 | G7: =SUMIF($G$22:$G$50,$B7,$J$22:$J$50) -> 2.2327366 | H7: =C16 -> 2 | I7: =MAX(0,G7-H7) -> 0.23273662
B8: Total | C8: =SUM(C6:C7) -> 29 | D8: =SUM(D6:D7) -> 14 | E8: =SUM(E6:E7) -> 12 | F8: =SUM(F6:F7) -> 3 | G8: =SUM(G6:G7) -> 6.5532976 | H8: =SUM(H6:H7) -> 5.54 | I8: =SUM(I6:I7) -> 1.0132976
B10: Portfolios funded (2.0 Group Summary) | C10: =COUNTA('2.5 Group Summary'!$B$6:$B$16) -> 11 | E10: Cost - AU and other funded ($m) | F10: =SUMIF($E$22:$E$50,"<>NZ",$J$22:$J$50) -> 5.5239061
B11: Domain Architect allocation per portfolio (FTE - 0.2 Data Config) | C11: ='0.2 Data Config'!$K$8 -> 0.5 | E11: Cost - NZ funded ($m) | F11: =SUMIF($E$22:$E$50,"NZ",$J$22:$J$50) -> 1.0293915
B12: Domain Architect FTEs funded by portfolio overheads | C12: =C10*C11 -> 5.5
B13: Domain Architect funding from portfolio overheads ($m) | C13: =COUNTA('2.5 Group Summary'!$B$6:$B$16)*'0.2 Data Config'!$L$8 -> 1.54
B14: COE - Strategy Architecture allocation ($m) - 0.2 Data Config | C14: ='0.2 Data Config'!$E$6 -> 2
B15: Total Strategy & Architecture budget ($m) | C15: =C13+C14 -> 3.54
B16: COE - Data allocation ($m) - 0.2 Data Config | C16: ='0.2 Data Config'!$E$10 -> 2
B17: Total budget to draw down ($m) | C17: =C15+C16 -> 5.54
B18: Paused roles - cost if released ($m) | C18: =SUMIFS($I$22:$I$50,$F$22:$F$50,"Paused")/1000000 -> 0.75447375
B20: Roles
B21: Name | C21: Position Title | D21: Department | E21: Country | F21: Status | G21: Category | H21: On/Off | I21: Full Cost AUD ($) | J21: Model cost ($m)
B22: =Sheet2!$B$97 -> Craig Ambrose | C22: =SUBSTITUTE(SUBSTITUTE(Sheet2!$C$97,"–","-"),"—","-") -> Domain Architect - Group Functions | D22: =Sheet2!$G$97 -> Architecture | E22: =Sheet2!$M$97 -> NZ | F22: =IF(LOWER(Sheet2!$Q$97)="v","Vacant",IF(LOWER(Sheet2!$Q$97)="pause","Paused",IF(LOWER(Sheet2!$Q$97)="cxc","Contractor","Filled"))) -> Filled | G22: =IF(Sheet2!$G$97="Group Data","Data","Strategy & Architecture") -> Strategy & Architecture | H22: Onshore | I22: =Sheet2!$AA$97 -> 242741.3 | J22: =IF($F22="Paused",0,IF($H22="Offshore",$I22*'0.3 Squad Archetypes'!$K$5,$I22)/1000000) -> 0.2427413
B23: =Sheet2!$B$100 -> James Holgate | C23: =SUBSTITUTE(SUBSTITUTE(Sheet2!$C$100,"–","-"),"—","-") -> Head of Technology, Group Data | D23: =Sheet2!$G$100 -> Group Data | E23: =Sheet2!$M$100 -> Australia | F23: =IF(LOWER(Sheet2!$Q$100)="v","Vacant",IF(LOWER(Sheet2!$Q$100)="pause","Paused",IF(LOWER(Sheet2!$Q$100)="cxc","Contractor","Filled"))) -> Filled | G23: =IF(Sheet2!$G$100="Group Data","Data","Strategy & Architecture") -> Data | H23: Onshore | I23: =Sheet2!$AA$100 -> 409755.7 | J23: =IF($F23="Paused",0,IF($H23="Offshore",$I23*'0.3 Squad Archetypes'!$K$5,$I23)/1000000) -> 0.4097557
B24: =Sheet2!$B$102 -> Joel Vijayakumar | C24: =SUBSTITUTE(SUBSTITUTE(Sheet2!$C$102,"–","-"),"—","-") -> Delivery Manager, Strategy, Architecture & Data | D24: =Sheet2!$G$102 -> Delivery, SADA | E24: =Sheet2!$M$102 -> Australia | F24: =IF(LOWER(Sheet2!$Q$102)="v","Vacant",IF(LOWER(Sheet2!$Q$102)="pause","Paused",IF(LOWER(Sheet2!$Q$102)="cxc","Contractor","Filled"))) -> Filled | G24: =IF(Sheet2!$G$102="Group Data","Data","Strategy & Architecture") -> Strategy & Architecture | H24: Onshore | I24: =Sheet2!$AA$102 -> 369088.6 | J24: =IF($F24="Paused",0,IF($H24="Offshore",$I24*'0.3 Squad Archetypes'!$K$5,$I24)/1000000) -> 0.3690886
B25: =Sheet2!$B$103 -> John Forde | C25: =SUBSTITUTE(SUBSTITUTE(Sheet2!$C$103,"–","-"),"—","-") -> Enterprise Architect | D25: =Sheet2!$G$103 -> Architecture | E25: =Sheet2!$M$103 -> NZ | F25: =IF(LOWER(Sheet2!$Q$103)="v","Vacant",IF(LOWER(Sheet2!$Q$103)="pause","Paused",IF(LOWER(Sheet2!$Q$103)="cxc","Contractor","Filled"))) -> Filled | G25: =IF(Sheet2!$G$103="Group Data","Data","Strategy & Architecture") -> Strategy & Architecture | H25: Onshore | I25: =Sheet2!$AA$103 -> 214270.25 | J25: =IF($F25="Paused",0,IF($H25="Offshore",$I25*'0.3 Squad Archetypes'!$K$5,$I25)/1000000) -> 0.21427025
B26: =Sheet2!$B$106 -> Lynn Yiew | C26: =SUBSTITUTE(SUBSTITUTE(Sheet2!$C$106,"–","-"),"—","-") -> Data Governance Specialist | D26: =Sheet2!$G$106 -> Group Data | E26: =Sheet2!$M$106 -> NZ | F26: =IF(LOWER(Sheet2!$Q$106)="v","Vacant",IF(LOWER(Sheet2!$Q$106)="pause","Paused",IF(LOWER(Sheet2!$Q$106)="cxc","Contractor","Filled"))) -> Filled | G26: =IF(Sheet2!$G$106="Group Data","Data","Strategy & Architecture") -> Data | H26: Onshore | I26: =Sheet2!$AA$106 -> 149746.42 | J26: =IF($F26="Paused",0,IF($H26="Offshore",$I26*'0.3 Squad Archetypes'!$K$5,$I26)/1000000) -> 0.14974642
B27: =Sheet2!$B$107 -> Mike Gilbert | C27: =SUBSTITUTE(SUBSTITUTE(Sheet2!$C$107,"–","-"),"—","-") -> Domain Architect - CFE & Infrastructure | D27: =Sheet2!$G$107 -> Architecture | E27: =Sheet2!$M$107 -> NZ | F27: =IF(LOWER(Sheet2!$Q$107)="v","Vacant",IF(LOWER(Sheet2!$Q$107)="pause","Paused",IF(LOWER(Sheet2!$Q$107)="cxc","Contractor","Filled"))) -> Filled | G27: =IF(Sheet2!$G$107="Group Data","Data","Strategy & Architecture") -> Strategy & Architecture | H27: Onshore | I27: =Sheet2!$AA$107 -> 236856.98 | J27: =IF($F27="Paused",0,IF($H27="Offshore",$I27*'0.3 Squad Archetypes'!$K$5,$I27)/1000000) -> 0.23685698
B28: =Sheet2!$B$108 -> Milan Patel | C28: =SUBSTITUTE(SUBSTITUTE(Sheet2!$C$108,"–","-"),"—","-") -> Platform Architect | D28: =Sheet2!$G$108 -> Group Data | E28: =Sheet2!$M$108 -> Australia | F28: =IF(LOWER(Sheet2!$Q$108)="v","Vacant",IF(LOWER(Sheet2!$Q$108)="pause","Paused",IF(LOWER(Sheet2!$Q$108)="cxc","Contractor","Filled"))) -> Filled | G28: =IF(Sheet2!$G$108="Group Data","Data","Strategy & Architecture") -> Data | H28: Onshore | I28: =Sheet2!$AA$108 -> 265584.9 | J28: =IF($F28="Paused",0,IF($H28="Offshore",$I28*'0.3 Squad Archetypes'!$K$5,$I28)/1000000) -> 0.2655849
B29: =Sheet2!$B$109 -> Mitchell Clarke | C29: =SUBSTITUTE(SUBSTITUTE(Sheet2!$C$109,"–","-"),"—","-") -> Snr Data Governance Specialist | D29: =Sheet2!$G$109 -> Group Data | E29: =Sheet2!$M$109 -> Australia | F29: =IF(LOWER(Sheet2!$Q$109)="v","Vacant",IF(LOWER(Sheet2!$Q$109)="pause","Paused",IF(LOWER(Sheet2!$Q$109)="cxc","Contractor","Filled"))) -> Filled | G29: =IF(Sheet2!$G$109="Group Data","Data","Strategy & Architecture") -> Data | H29: Onshore | I29: =Sheet2!$AA$109 -> 225988.8 | J29: =IF($F29="Paused",0,IF($H29="Offshore",$I29*'0.3 Squad Archetypes'!$K$5,$I29)/1000000) -> 0.2259888
B30: =Sheet2!$B$114 -> Raymond Bai | C30: =SUBSTITUTE(SUBSTITUTE(Sheet2!$C$114,"–","-"),"—","-") -> Data Adoption Specialist | D30: =Sheet2!$G$114 -> Group Data | E30: =Sheet2!$M$114 -> Australia | F30: =IF(LOWER(Sheet2!$Q$114)="v","Vacant",IF(LOWER(Sheet2!$Q$114)="pause","Paused",IF(LOWER(Sheet2!$Q$114)="cxc","Contractor","Filled"))) -> Filled | G30: =IF(Sheet2!$G$114="Group Data","Data","Strategy & Architecture") -> Data | H30: Onshore | I30: =Sheet2!$AA$114 -> 175872.9 | J30: =IF($F30="Paused",0,IF($H30="Offshore",$I30*'0.3 Squad Archetypes'!$K$5,$I30)/1000000) -> 0.1758729
B31: =Sheet2!$B$115 -> Renosh Matthew Thomas | C31: =SUBSTITUTE(SUBSTITUTE(Sheet2!$C$115,"–","-"),"—","-") -> Data Enablement Lead | D31: =Sheet2!$G$115 -> Group Data | E31: =Sheet2!$M$115 -> Australia | F31: =IF(LOWER(Sheet2!$Q$115)="v","Vacant",IF(LOWER(Sheet2!$Q$115)="pause","Paused",IF(LOWER(Sheet2!$Q$115)="cxc","Contractor","Filled"))) -> Filled | G31: =IF(Sheet2!$G$115="Group Data","Data","Strategy & Architecture") -> Data | H31: Onshore | I31: =Sheet2!$AA$115 -> 227056.8 | J31: =IF($F31="Paused",0,IF($H31="Offshore",$I31*'0.3 Squad Archetypes'!$K$5,$I31)/1000000) -> 0.2270568
B32: =Sheet2!$B$116 -> Rihan Schalkwyk | C32: =SUBSTITUTE(SUBSTITUTE(Sheet2!$C$116,"–","-"),"—","-") -> Senior Business Analyst | D32: =Sheet2!$G$116 -> Delivery, SADA | E32: =Sheet2!$M$116 -> Australia | F32: =IF(LOWER(Sheet2!$Q$116)="v","Vacant",IF(LOWER(Sheet2!$Q$116)="pause","Paused",IF(LOWER(Sheet2!$Q$116)="cxc","Contractor","Filled"))) -> Filled | G32: =IF(Sheet2!$G$116="Group Data","Data","Strategy & Architecture") -> Strategy & Architecture | H32: Onshore | I32: =Sheet2!$AA$116 -> 249124.35 | J32: =IF($F32="Paused",0,IF($H32="Offshore",$I32*'0.3 Squad Archetypes'!$K$5,$I32)/1000000) -> 0.24912435
B33: =Sheet2!$B$117 -> ring fenced | C33: =SUBSTITUTE(SUBSTITUTE(Sheet2!$C$117,"–","-"),"—","-") -> Enterprise Architect | D33: =Sheet2!$G$117 -> Architecture | E33: =Sheet2!$M$117 -> Australia | F33: =IF(LOWER(Sheet2!$Q$117)="v","Vacant",IF(LOWER(Sheet2!$Q$117)="pause","Paused",IF(LOWER(Sheet2!$Q$117)="cxc","Contractor","Filled"))) -> Paused | G33: =IF(Sheet2!$G$117="Group Data","Data","Strategy & Architecture") -> Strategy & Architecture | H33: Onshore | I33: =Sheet2!$AA$117 -> 275810.25 | J33: =IF($F33="Paused",0,IF($H33="Offshore",$I33*'0.3 Squad Archetypes'!$K$5,$I33)/1000000) -> 0
B34: =Sheet2!$B$118 -> ring fenced | C34: =SUBSTITUTE(SUBSTITUTE(Sheet2!$C$118,"–","-"),"—","-") -> Domain Architect - Customer & Digital Tech | D34: =Sheet2!$G$118 -> Architecture | E34: =Sheet2!$M$118 -> Australia | F34: =IF(LOWER(Sheet2!$Q$118)="v","Vacant",IF(LOWER(Sheet2!$Q$118)="pause","Paused",IF(LOWER(Sheet2!$Q$118)="cxc","Contractor","Filled"))) -> Vacant | G34: =IF(Sheet2!$G$118="Group Data","Data","Strategy & Architecture") -> Strategy & Architecture | H34: Onshore | I34: =Sheet2!$AA$118 -> 231689.25 | J34: =IF($F34="Paused",0,IF($H34="Offshore",$I34*'0.3 Squad Archetypes'!$K$5,$I34)/1000000) -> 0.23168925
B35: =Sheet2!$B$119 -> ring fenced | C35: =SUBSTITUTE(SUBSTITUTE(Sheet2!$C$119,"–","-"),"—","-") -> Domain Architect - Retail & Z | D35: =Sheet2!$G$119 -> Architecture | E35: =Sheet2!$M$119 -> Australia | F35: =IF(LOWER(Sheet2!$Q$119)="v","Vacant",IF(LOWER(Sheet2!$Q$119)="pause","Paused",IF(LOWER(Sheet2!$Q$119)="cxc","Contractor","Filled"))) -> Vacant | G35: =IF(Sheet2!$G$119="Group Data","Data","Strategy & Architecture") -> Strategy & Architecture | H35: Onshore | I35: =Sheet2!$AA$119 -> 231689.25 | J35: =IF($F35="Paused",0,IF($H35="Offshore",$I35*'0.3 Squad Archetypes'!$K$5,$I35)/1000000) -> 0.23168925
B36: =Sheet2!$B$120 -> ring fenced | C36: =SUBSTITUTE(SUBSTITUTE(Sheet2!$C$120,"–","-"),"—","-") -> Domain Architect - TDD | D36: =Sheet2!$G$120 -> Architecture | E36: =Sheet2!$M$120 -> Australia | F36: =IF(LOWER(Sheet2!$Q$120)="v","Vacant",IF(LOWER(Sheet2!$Q$120)="pause","Paused",IF(LOWER(Sheet2!$Q$120)="cxc","Contractor","Filled"))) -> Vacant | G36: =IF(Sheet2!$G$120="Group Data","Data","Strategy & Architecture") -> Strategy & Architecture | H36: Onshore | I36: =Sheet2!$AA$120 -> 231689.25 | J36: =IF($F36="Paused",0,IF($H36="Offshore",$I36*'0.3 Squad Archetypes'!$K$5,$I36)/1000000) -> 0.23168925
B37: =Sheet2!$B$121 -> Roger Blazey | C37: =SUBSTITUTE(SUBSTITUTE(Sheet2!$C$121,"–","-"),"—","-") -> Architect (AI Innovation) | D37: =Sheet2!$G$121 -> Technology Strategy & AI Capability | E37: =Sheet2!$M$121 -> Australia | F37: =IF(LOWER(Sheet2!$Q$121)="v","Vacant",IF(LOWER(Sheet2!$Q$121)="pause","Paused",IF(LOWER(Sheet2!$Q$121)="cxc","Contractor","Filled"))) -> Filled | G37: =IF(Sheet2!$G$121="Group Data","Data","Strategy & Architecture") -> Strategy & Architecture | H37: Onshore | I37: =Sheet2!$AA$121 -> 250245.75 | J37: =IF($F37="Paused",0,IF($H37="Offshore",$I37*'0.3 Squad Archetypes'!$K$5,$I37)/1000000) -> 0.25024575
B38: =Sheet2!$B$124 -> Sanjay Tikoo | C38: =SUBSTITUTE(SUBSTITUTE(Sheet2!$C$124,"–","-"),"—","-") -> Principal, Data Architecture & Governance | D38: =Sheet2!$G$124 -> Group Data | E38: =Sheet2!$M$124 -> Australia | F38: =IF(LOWER(Sheet2!$Q$124)="v","Vacant",IF(LOWER(Sheet2!$Q$124)="pause","Paused",IF(LOWER(Sheet2!$Q$124)="cxc","Contractor","Filled"))) -> Filled | G38: =IF(Sheet2!$G$124="Group Data","Data","Strategy & Architecture") -> Data | H38: Onshore | I38: =Sheet2!$AA$124 -> 389125 | J38: =IF($F38="Paused",0,IF($H38="Offshore",$I38*'0.3 Squad Archetypes'!$K$5,$I38)/1000000) -> 0.389125
B39: =Sheet2!$B$127 -> Tim Snedden | C39: =SUBSTITUTE(SUBSTITUTE(Sheet2!$C$127,"–","-"),"—","-") -> Delivery Lead | D39: =Sheet2!$G$127 -> Delivery, SADA | E39: =Sheet2!$M$127 -> NZ | F39: =IF(LOWER(Sheet2!$Q$127)="v","Vacant",IF(LOWER(Sheet2!$Q$127)="pause","Paused",IF(LOWER(Sheet2!$Q$127)="cxc","Contractor","Filled"))) -> Filled | G39: =IF(Sheet2!$G$127="Group Data","Data","Strategy & Architecture") -> Strategy & Architecture | H39: Onshore | I39: =Sheet2!$AA$127 -> 185776.56 | J39: =IF($F39="Paused",0,IF($H39="Offshore",$I39*'0.3 Squad Archetypes'!$K$5,$I39)/1000000) -> 0.18577656
B40: =Sheet2!$B$133 -> Vacant | C40: =SUBSTITUTE(SUBSTITUTE(Sheet2!$C$133,"–","-"),"—","-") -> Business Analyst | D40: =Sheet2!$G$133 -> Delivery, SADA | E40: =Sheet2!$M$133 -> Australia | F40: =IF(LOWER(Sheet2!$Q$133)="v","Vacant",IF(LOWER(Sheet2!$Q$133)="pause","Paused",IF(LOWER(Sheet2!$Q$133)="cxc","Contractor","Filled"))) -> Vacant | G40: =IF(Sheet2!$G$133="Group Data","Data","Strategy & Architecture") -> Strategy & Architecture | H40: Onshore | I40: =Sheet2!$AA$133 -> 202853.25 | J40: =IF($F40="Paused",0,IF($H40="Offshore",$I40*'0.3 Squad Archetypes'!$K$5,$I40)/1000000) -> 0.20285325
B41: =Sheet2!$B$134 -> Vacant | C41: =SUBSTITUTE(SUBSTITUTE(Sheet2!$C$134,"–","-"),"—","-") -> Business Analyst | D41: =Sheet2!$G$134 -> Delivery, SADA | E41: =Sheet2!$M$134 -> Australia | F41: =IF(LOWER(Sheet2!$Q$134)="v","Vacant",IF(LOWER(Sheet2!$Q$134)="pause","Paused",IF(LOWER(Sheet2!$Q$134)="cxc","Contractor","Filled"))) -> Paused | G41: =IF(Sheet2!$G$134="Group Data","Data","Strategy & Architecture") -> Strategy & Architecture | H41: Onshore | I41: =Sheet2!$AA$134 -> 202853.25 | J41: =IF($F41="Paused",0,IF($H41="Offshore",$I41*'0.3 Squad Archetypes'!$K$5,$I41)/1000000) -> 0
B42: =Sheet2!$B$141 -> Vacant | C42: =SUBSTITUTE(SUBSTITUTE(Sheet2!$C$141,"–","-"),"—","-") -> Data Governance Lead | D42: =Sheet2!$G$141 -> Group Data | E42: =Sheet2!$M$141 -> australia | F42: =IF(LOWER(Sheet2!$Q$141)="v","Vacant",IF(LOWER(Sheet2!$Q$141)="pause","Paused",IF(LOWER(Sheet2!$Q$141)="cxc","Contractor","Filled"))) -> Vacant | G42: =IF(Sheet2!$G$141="Group Data","Data","Strategy & Architecture") -> Data | H42: Onshore | I42: =Sheet2!$AA$141 -> 389606.1 | J42: =IF($F42="Paused",0,IF($H42="Offshore",$I42*'0.3 Squad Archetypes'!$K$5,$I42)/1000000) -> 0.3896061
B43: =Sheet2!$B$142 -> Vacant | C43: =SUBSTITUTE(SUBSTITUTE(Sheet2!$C$142,"–","-"),"—","-") -> Head of Architecture | D43: =Sheet2!$G$142 -> Architecture | E43: =Sheet2!$M$142 -> Australia | F43: =IF(LOWER(Sheet2!$Q$142)="v","Vacant",IF(LOWER(Sheet2!$Q$142)="pause","Paused",IF(LOWER(Sheet2!$Q$142)="cxc","Contractor","Filled"))) -> Vacant | G43: =IF(Sheet2!$G$142="Group Data","Data","Strategy & Architecture") -> Strategy & Architecture | H43: Onshore | I43: =Sheet2!$AA$142 -> 334972.95 | J43: =IF($F43="Paused",0,IF($H43="Offshore",$I43*'0.3 Squad Archetypes'!$K$5,$I43)/1000000) -> 0.33497295
B44: =Sheet2!$B$143 -> Vacant | C44: =SUBSTITUTE(SUBSTITUTE(Sheet2!$C$143,"–","-"),"—","-") -> Head of Technology Strategy & AI Capability | D44: =Sheet2!$G$143 -> Technology Strategy & AI Capability | E44: =Sheet2!$M$143 -> Australia | F44: =IF(LOWER(Sheet2!$Q$143)="v","Vacant",IF(LOWER(Sheet2!$Q$143)="pause","Paused",IF(LOWER(Sheet2!$Q$143)="cxc","Contractor","Filled"))) -> Vacant | G44: =IF(Sheet2!$G$143="Group Data","Data","Strategy & Architecture") -> Strategy & Architecture | H44: Onshore | I44: =Sheet2!$AA$143 -> 333020.25 | J44: =IF($F44="Paused",0,IF($H44="Offshore",$I44*'0.3 Squad Archetypes'!$K$5,$I44)/1000000) -> 0.33302025
B45: =Sheet2!$B$144 -> Vacant | C45: =SUBSTITUTE(SUBSTITUTE(Sheet2!$C$144,"–","-"),"—","-") -> Senior Communications Advisor | D45: =Sheet2!$G$144 -> na | E45: =Sheet2!$M$144 -> Australia | F45: =IF(LOWER(Sheet2!$Q$144)="v","Vacant",IF(LOWER(Sheet2!$Q$144)="pause","Paused",IF(LOWER(Sheet2!$Q$144)="cxc","Contractor","Filled"))) -> Vacant | G45: =IF(Sheet2!$G$144="Group Data","Data","Strategy & Architecture") -> Strategy & Architecture | H45: Onshore | I45: =Sheet2!$AA$144 -> 186900 | J45: =IF($F45="Paused",0,IF($H45="Offshore",$I45*'0.3 Squad Archetypes'!$K$5,$I45)/1000000) -> 0.1869
B46: =Sheet2!$B$145 -> Vacant | C46: =SUBSTITUTE(SUBSTITUTE(Sheet2!$C$145,"–","-"),"—","-") -> Enterprise Data Architect | D46: =Sheet2!$G$145 -> Group Data | E46: =Sheet2!$M$145 -> Australia | F46: =IF(LOWER(Sheet2!$Q$145)="v","Vacant",IF(LOWER(Sheet2!$Q$145)="pause","Paused",IF(LOWER(Sheet2!$Q$145)="cxc","Contractor","Filled"))) -> Paused | G46: =IF(Sheet2!$G$145="Group Data","Data","Strategy & Architecture") -> Data | H46: Onshore | I46: =Sheet2!$AA$145 -> 275810.25 | J46: =IF($F46="Paused",0,IF($H46="Offshore",$I46*'0.3 Squad Archetypes'!$K$5,$I46)/1000000) -> 0
B47: =Sheet2!$B$146 -> Vacant | C47: =SUBSTITUTE(SUBSTITUTE(Sheet2!$C$146,"–","-"),"—","-") -> AI Capability Lead | D47: =Sheet2!$G$146 -> Technology Strategy & AI Capability | E47: =Sheet2!$M$146 -> Australia | F47: =IF(LOWER(Sheet2!$Q$146)="v","Vacant",IF(LOWER(Sheet2!$Q$146)="pause","Paused",IF(LOWER(Sheet2!$Q$146)="cxc","Contractor","Filled"))) -> Vacant | G47: =IF(Sheet2!$G$146="Group Data","Data","Strategy & Architecture") -> Strategy & Architecture | H47: Onshore | I47: =Sheet2!$AA$146 -> 275810.25 | J47: =IF($F47="Paused",0,IF($H47="Offshore",$I47*'0.3 Squad Archetypes'!$K$5,$I47)/1000000) -> 0.27581025
B48: =Sheet2!$B$147 -> Vacant | C48: =SUBSTITUTE(SUBSTITUTE(Sheet2!$C$147,"–","-"),"—","-") -> Enterprise Process Lead | D48: =Sheet2!$G$147 -> Technology Strategy & AI Capability | E48: =Sheet2!$M$147 -> Australia | F48: =IF(LOWER(Sheet2!$Q$147)="v","Vacant",IF(LOWER(Sheet2!$Q$147)="pause","Paused",IF(LOWER(Sheet2!$Q$147)="cxc","Contractor","Filled"))) -> Vacant | G48: =IF(Sheet2!$G$147="Group Data","Data","Strategy & Architecture") -> Strategy & Architecture | H48: Onshore | I48: =Sheet2!$AA$147 -> 202853.25 | J48: =IF($F48="Paused",0,IF($H48="Offshore",$I48*'0.3 Squad Archetypes'!$K$5,$I48)/1000000) -> 0.20285325
B49: =Sheet2!$B$148 -> Vacant | C49: =SUBSTITUTE(SUBSTITUTE(Sheet2!$C$148,"–","-"),"—","-") -> EnterpriseProcess Analyst | D49: =Sheet2!$G$148 -> Technology Strategy & AI Capability | E49: =Sheet2!$M$148 -> Australia | F49: =IF(LOWER(Sheet2!$Q$148)="v","Vacant",IF(LOWER(Sheet2!$Q$148)="pause","Paused",IF(LOWER(Sheet2!$Q$148)="cxc","Contractor","Filled"))) -> Vacant | G49: =IF(Sheet2!$G$148="Group Data","Data","Strategy & Architecture") -> Strategy & Architecture | H49: Onshore | I49: =Sheet2!$AA$148 -> 170489.75 | J49: =IF($F49="Paused",0,IF($H49="Offshore",$I49*'0.3 Squad Archetypes'!$K$5,$I49)/1000000) -> 0.17048975
B50: =Sheet2!$B$149 -> Vacant | C50: =SUBSTITUTE(SUBSTITUTE(Sheet2!$C$149,"–","-"),"—","-") -> Strategy Analyst | D50: =Sheet2!$G$149 -> Technology Strategy & AI Capability | E50: =Sheet2!$M$149 -> Australia | F50: =IF(LOWER(Sheet2!$Q$149)="v","Vacant",IF(LOWER(Sheet2!$Q$149)="pause","Paused",IF(LOWER(Sheet2!$Q$149)="cxc","Contractor","Filled"))) -> Vacant | G50: =IF(Sheet2!$G$149="Group Data","Data","Strategy & Architecture") -> Strategy & Architecture | H50: Onshore | I50: =Sheet2!$AA$149 -> 170489.75 | J50: =IF($F50="Paused",0,IF($H50="Offshore",$I50*'0.3 Squad Archetypes'!$K$5,$I50)/1000000) -> 0.17048975
B51: Check - roles listed vs counted (must be 0) | C51: =COUNTA(B22:B50)-C8 -> 0
B53: Squad-based SA&D roles sit in their portfolio squads (1.3 / 4.3). Leadership roles sit on 2.7 Squad Detail. Planned spend excludes Paused roles - their cost is the memo line above.

Sheet 2.3 Cyber Roles
B2: Cyber, Risk & Service Operations roles and funding
B4: Summary
B5: Category | C5: Roles | D5: Filled | E5: Vacant | F5: Planned spend ($m) | G5: Budget to draw down ($m) | H5: Left to fund ($m)
B6: Cyber & Risk | C6: =COUNTIF($G$19:$G$70,$B6) -> 28 | D6: =COUNTIFS($G$19:$G$70,$B6,$F$19:$F$70,"Filled") -> 25 | E6: =COUNTIFS($G$19:$G$70,$B6,$F$19:$F$70,"Vacant") -> 3 | F6: =SUMIF($G$19:$G$70,$B6,$J$19:$J$70) -> 6.5289684
B7: Service Operations | C7: =COUNTIF($G$19:$G$70,$B7) -> 24 | D7: =COUNTIFS($G$19:$G$70,$B7,$F$19:$F$70,"Filled") -> 17 | E7: =COUNTIFS($G$19:$G$70,$B7,$F$19:$F$70,"Vacant") -> 7 | F7: =SUMIF($G$19:$G$70,$B7,$J$19:$J$70) -> 4.3870206
B8: Total | C8: =SUM(C6:C7) -> 52 | D8: =SUM(D6:D7) -> 42 | E8: =SUM(E6:E7) -> 10 | F8: =SUM(F6:F7) -> 10.915989 | G8: ='0.2 Data Config'!$E$23 -> 3.5 | H8: =MAX(0,F8-G8) -> 7.415989
B10: TDD Cyber people budget - Data Config ($m) | C10: ='0.2 Data Config'!$E$23 -> 3.5 | E10: Cost - AU and other funded ($m) | F10: =SUMIF($E$19:$E$70,"<>NZ",$J$19:$J$70) -> 9.8579918
B11: Cyber CapEx - Monitoring, tracked separately ($m) | C11: ='1.11 TDD Cyber'!$H$16 -> 0.5 | E11: Cost - NZ funded ($m) | F11: =SUMIF($E$19:$E$70,"NZ",$J$19:$J$70) -> 1.0579972
B12: Planned spend - all cyber roles ($m) | C12: =F8 -> 10.915989
B13: Left to fund - roles vs people budget ($m) | C13: =H8 -> 7.415989
B14: Portfolio + platform overheads charged on 1.11 ($m) | C14: ='1.11 TDD Cyber'!$C$6+'1.11 TDD Cyber'!$C$7 -> 0.9145
B15: Total to fund - ties to 1.11 TDD Cyber ($m) | C15: =C13+C14 -> 8.330489
B17: Roles
B18: Name | C18: Position Title | D18: Department | E18: Country | F18: Status | G18: Category | H18: On/Off | I18: Full Cost AUD ($) | J18: Model cost ($m)
B19: =Sheet2!$B$2 -> Ashley Mueller | C19: =SUBSTITUTE(SUBSTITUTE(Sheet2!$C$2,"–","-"),"—","-") -> Lead - Service Assurance | D19: =Sheet2!$G$2 -> Service Op & Assurance | E19: =Sheet2!$M$2 -> NZ | F19: =IF(LOWER(Sheet2!$Q$2)="v","Vacant",IF(LOWER(Sheet2!$Q$2)="pause","Paused",IF(LOWER(Sheet2!$Q$2)="cxc","Contractor","Filled"))) -> Filled | G19: =IF(Sheet2!$G$2="Service Op & Assurance","Service Operations","Cyber & Risk") -> Service Operations | H19: Onshore | I19: =Sheet2!$AA$2 -> 189974.8 | J19: =IF($H19="Offshore",$I19*'0.3 Squad Archetypes'!$K$5,$I19)/1000000 -> 0.1899748
B20: =Sheet2!$B$3 -> Belinda Hoskens | C20: =SUBSTITUTE(SUBSTITUTE(Sheet2!$C$3,"–","-"),"—","-") -> Technology Support Engineer | D20: =Sheet2!$G$3 -> Service Op & Assurance | E20: =Sheet2!$M$3 -> Australia | F20: =IF(LOWER(Sheet2!$Q$3)="v","Vacant",IF(LOWER(Sheet2!$Q$3)="pause","Paused",IF(LOWER(Sheet2!$Q$3)="cxc","Contractor","Filled"))) -> Filled | G20: =IF(Sheet2!$G$3="Service Op & Assurance","Service Operations","Cyber & Risk") -> Service Operations | H20: Onshore | I20: =Sheet2!$AA$3 -> 162139.5 | J20: =IF($H20="Offshore",$I20*'0.3 Squad Archetypes'!$K$5,$I20)/1000000 -> 0.1621395
B21: =Sheet2!$B$4 -> Brian Gates | C21: =SUBSTITUTE(SUBSTITUTE(Sheet2!$C$4,"–","-"),"—","-") -> Manager Risk & Resilience | D21: =Sheet2!$G$4 -> Cyber Risk | E21: =Sheet2!$M$4 -> Australia | F21: =IF(LOWER(Sheet2!$Q$4)="v","Vacant",IF(LOWER(Sheet2!$Q$4)="pause","Paused",IF(LOWER(Sheet2!$Q$4)="cxc","Contractor","Filled"))) -> Filled | G21: =IF(Sheet2!$G$4="Service Op & Assurance","Service Operations","Cyber & Risk") -> Cyber & Risk | H21: Onshore | I21: =Sheet2!$AA$4 -> 287043.2 | J21: =IF($H21="Offshore",$I21*'0.3 Squad Archetypes'!$K$5,$I21)/1000000 -> 0.2870432
B22: =Sheet2!$B$5 -> Cameron Watman | C22: =SUBSTITUTE(SUBSTITUTE(Sheet2!$C$5,"–","-"),"—","-") -> Engineer - IDAM | D22: =Sheet2!$G$5 -> Cyber Strat & Tech | E22: =Sheet2!$M$5 -> Australia | F22: =IF(LOWER(Sheet2!$Q$5)="v","Vacant",IF(LOWER(Sheet2!$Q$5)="pause","Paused",IF(LOWER(Sheet2!$Q$5)="cxc","Contractor","Filled"))) -> Filled | G22: =IF(Sheet2!$G$5="Service Op & Assurance","Service Operations","Cyber & Risk") -> Cyber & Risk | H22: Onshore | I22: =Sheet2!$AA$5 -> 173132.9 | J22: =IF($H22="Offshore",$I22*'0.3 Squad Archetypes'!$K$5,$I22)/1000000 -> 0.1731329
B23: =Sheet2!$B$6 -> Catherine Gire | C23: =SUBSTITUTE(SUBSTITUTE(Sheet2!$C$6,"–","-"),"—","-") -> Cyber Technical Business Analyst | D23: =Sheet2!$G$6 -> Cyber Strat & Tech | E23: =Sheet2!$M$6 -> Australia | F23: =IF(LOWER(Sheet2!$Q$6)="v","Vacant",IF(LOWER(Sheet2!$Q$6)="pause","Paused",IF(LOWER(Sheet2!$Q$6)="cxc","Contractor","Filled"))) -> Filled | G23: =IF(Sheet2!$G$6="Service Op & Assurance","Service Operations","Cyber & Risk") -> Cyber & Risk | H23: Onshore | I23: =Sheet2!$AA$6 -> 227163.6 | J23: =IF($H23="Offshore",$I23*'0.3 Squad Archetypes'!$K$5,$I23)/1000000 -> 0.2271636
B24: =Sheet2!$B$7 -> Chris Lyons | C24: =SUBSTITUTE(SUBSTITUTE(Sheet2!$C$7,"–","-"),"—","-") -> Cyber Security Architect | D24: =Sheet2!$G$7 -> Cyber Strat & Tech | E24: =Sheet2!$M$7 -> Australia | F24: =IF(LOWER(Sheet2!$Q$7)="v","Vacant",IF(LOWER(Sheet2!$Q$7)="pause","Paused",IF(LOWER(Sheet2!$Q$7)="cxc","Contractor","Filled"))) -> Filled | G24: =IF(Sheet2!$G$7="Service Op & Assurance","Service Operations","Cyber & Risk") -> Cyber & Risk | H24: Onshore | I24: =Sheet2!$AA$7 -> 283353.75 | J24: =IF($H24="Offshore",$I24*'0.3 Squad Archetypes'!$K$5,$I24)/1000000 -> 0.28335375
B25: =Sheet2!$B$8 -> Chris Rojas | C25: =SUBSTITUTE(SUBSTITUTE(Sheet2!$C$8,"–","-"),"—","-") -> Manager, Customer Support Operations | D25: =Sheet2!$G$8 -> Service Op & Assurance | E25: =Sheet2!$M$8 -> Australia | F25: =IF(LOWER(Sheet2!$Q$8)="v","Vacant",IF(LOWER(Sheet2!$Q$8)="pause","Paused",IF(LOWER(Sheet2!$Q$8)="cxc","Contractor","Filled"))) -> Filled | G25: =IF(Sheet2!$G$8="Service Op & Assurance","Service Operations","Cyber & Risk") -> Service Operations | H25: Onshore | I25: =Sheet2!$AA$8 -> 243303.75 | J25: =IF($H25="Offshore",$I25*'0.3 Squad Archetypes'!$K$5,$I25)/1000000 -> 0.24330375
B26: =Sheet2!$B$9 -> Dan Balsamo | C26: =SUBSTITUTE(SUBSTITUTE(Sheet2!$C$9,"–","-"),"—","-") -> Senior Cyber Project Manager | D26: =Sheet2!$G$9 -> Cyber Strat & Tech | E26: =Sheet2!$M$9 -> Australia | F26: =IF(LOWER(Sheet2!$Q$9)="v","Vacant",IF(LOWER(Sheet2!$Q$9)="pause","Paused",IF(LOWER(Sheet2!$Q$9)="cxc","Contractor","Filled"))) -> Filled | G26: =IF(Sheet2!$G$9="Service Op & Assurance","Service Operations","Cyber & Risk") -> Cyber & Risk | H26: Onshore | I26: =Sheet2!$AA$9 -> 258576.15 | J26: =IF($H26="Offshore",$I26*'0.3 Squad Archetypes'!$K$5,$I26)/1000000 -> 0.25857615
B27: =Sheet2!$B$10 -> Daniel Jolley | C27: =SUBSTITUTE(SUBSTITUTE(Sheet2!$C$10,"–","-"),"—","-") -> Tech Support Technician | D27: =Sheet2!$G$10 -> Service Op & Assurance | E27: =Sheet2!$M$10 -> Australia | F27: =IF(LOWER(Sheet2!$Q$10)="v","Vacant",IF(LOWER(Sheet2!$Q$10)="pause","Paused",IF(LOWER(Sheet2!$Q$10)="cxc","Contractor","Filled"))) -> Filled | G27: =IF(Sheet2!$G$10="Service Op & Assurance","Service Operations","Cyber & Risk") -> Service Operations | H27: Onshore | I27: =Sheet2!$AA$10 -> 115851.5 | J27: =IF($H27="Offshore",$I27*'0.3 Squad Archetypes'!$K$5,$I27)/1000000 -> 0.1158515
B28: =Sheet2!$B$11 -> Darren Koller | C28: =SUBSTITUTE(SUBSTITUTE(Sheet2!$C$11,"–","-"),"—","-") -> Manager, Service Management & Major Incident Mgmt Lead | D28: =Sheet2!$G$11 -> Service Op & Assurance | E28: =Sheet2!$M$11 -> Australia | F28: =IF(LOWER(Sheet2!$Q$11)="v","Vacant",IF(LOWER(Sheet2!$Q$11)="pause","Paused",IF(LOWER(Sheet2!$Q$11)="cxc","Contractor","Filled"))) -> Filled | G28: =IF(Sheet2!$G$11="Service Op & Assurance","Service Operations","Cyber & Risk") -> Service Operations | H28: Onshore | I28: =Sheet2!$AA$11 -> 274943.25 | J28: =IF($H28="Offshore",$I28*'0.3 Squad Archetypes'!$K$5,$I28)/1000000 -> 0.27494325
B29: =Sheet2!$B$12 -> Darshan Suvama | C29: =SUBSTITUTE(SUBSTITUTE(Sheet2!$C$12,"–","-"),"—","-") -> Cyber Offensive Security Lead | D29: =Sheet2!$G$12 -> Cyber Strat & Tech | E29: =Sheet2!$M$12 -> Australia | F29: =IF(LOWER(Sheet2!$Q$12)="v","Vacant",IF(LOWER(Sheet2!$Q$12)="pause","Paused",IF(LOWER(Sheet2!$Q$12)="cxc","Contractor","Filled"))) -> Filled | G29: =IF(Sheet2!$G$12="Service Op & Assurance","Service Operations","Cyber & Risk") -> Cyber & Risk | H29: Onshore | I29: =Sheet2!$AA$12 -> 285342.9 | J29: =IF($H29="Offshore",$I29*'0.3 Squad Archetypes'!$K$5,$I29)/1000000 -> 0.2853429
B30: =Sheet2!$B$13 -> Diya Thomas | C30: =SUBSTITUTE(SUBSTITUTE(Sheet2!$C$13,"–","-"),"—","-") -> Manager Cyber Security GRC | D30: =Sheet2!$G$13 -> Cyber GRC | E30: =Sheet2!$M$13 -> Australia | F30: =IF(LOWER(Sheet2!$Q$13)="v","Vacant",IF(LOWER(Sheet2!$Q$13)="pause","Paused",IF(LOWER(Sheet2!$Q$13)="cxc","Contractor","Filled"))) -> Filled | G30: =IF(Sheet2!$G$13="Service Op & Assurance","Service Operations","Cyber & Risk") -> Cyber & Risk | H30: Onshore | I30: =Sheet2!$AA$13 -> 287043.2 | J30: =IF($H30="Offshore",$I30*'0.3 Squad Archetypes'!$K$5,$I30)/1000000 -> 0.2870432
B31: =Sheet2!$B$14 -> Ethan Lamhert (FT) | C31: =SUBSTITUTE(SUBSTITUTE(Sheet2!$C$14,"–","-"),"—","-") -> Tech Support Technician | D31: =Sheet2!$G$14 -> Service Op & Assurance | E31: =Sheet2!$M$14 -> NZ | F31: =IF(LOWER(Sheet2!$Q$14)="v","Vacant",IF(LOWER(Sheet2!$Q$14)="pause","Paused",IF(LOWER(Sheet2!$Q$14)="cxc","Contractor","Filled"))) -> Filled | G31: =IF(Sheet2!$G$14="Service Op & Assurance","Service Operations","Cyber & Risk") -> Service Operations | H31: Onshore | I31: =Sheet2!$AA$14 -> 89758 | J31: =IF($H31="Offshore",$I31*'0.3 Squad Archetypes'!$K$5,$I31)/1000000 -> 0.089758
B32: =Sheet2!$B$15 -> Iwan Wibisono | C32: =SUBSTITUTE(SUBSTITUTE(Sheet2!$C$15,"–","-"),"—","-") -> Engineer - IDAM | D32: =Sheet2!$G$15 -> Cyber Strat & Tech | E32: =Sheet2!$M$15 -> Australia | F32: =IF(LOWER(Sheet2!$Q$15)="v","Vacant",IF(LOWER(Sheet2!$Q$15)="pause","Paused",IF(LOWER(Sheet2!$Q$15)="cxc","Contractor","Filled"))) -> Filled | G32: =IF(Sheet2!$G$15="Service Op & Assurance","Service Operations","Cyber & Risk") -> Cyber & Risk | H32: Onshore | I32: =Sheet2!$AA$15 -> 215682.6 | J32: =IF($H32="Offshore",$I32*'0.3 Squad Archetypes'!$K$5,$I32)/1000000 -> 0.2156826
B33: =Sheet2!$B$16 -> Jack Jenkins | C33: =SUBSTITUTE(SUBSTITUTE(Sheet2!$C$16,"–","-"),"—","-") -> Asset Analyst | D33: =Sheet2!$G$16 -> Service Op & Assurance | E33: =Sheet2!$M$16 -> Australia | F33: =IF(LOWER(Sheet2!$Q$16)="v","Vacant",IF(LOWER(Sheet2!$Q$16)="pause","Paused",IF(LOWER(Sheet2!$Q$16)="cxc","Contractor","Filled"))) -> Filled | G33: =IF(Sheet2!$G$16="Service Op & Assurance","Service Operations","Cyber & Risk") -> Service Operations | H33: Onshore | I33: =Sheet2!$AA$16 -> 139008.65 | J33: =IF($H33="Offshore",$I33*'0.3 Squad Archetypes'!$K$5,$I33)/1000000 -> 0.13900865
B34: =Sheet2!$B$17 -> James Byrne | C34: =SUBSTITUTE(SUBSTITUTE(Sheet2!$C$17,"–","-"),"—","-") -> Head of Cyber Strategy & Technology | D34: =Sheet2!$G$17 -> Cyber Strat & Tech | E34: =Sheet2!$M$17 -> Australia | F34: =IF(LOWER(Sheet2!$Q$17)="v","Vacant",IF(LOWER(Sheet2!$Q$17)="pause","Paused",IF(LOWER(Sheet2!$Q$17)="cxc","Contractor","Filled"))) -> Filled | G34: =IF(Sheet2!$G$17="Service Op & Assurance","Service Operations","Cyber & Risk") -> Cyber & Risk | H34: Onshore | I34: =Sheet2!$AA$17 -> 382587.7 | J34: =IF($H34="Offshore",$I34*'0.3 Squad Archetypes'!$K$5,$I34)/1000000 -> 0.3825877
B35: =Sheet2!$B$18 -> Jas Mann | C35: =SUBSTITUTE(SUBSTITUTE(Sheet2!$C$18,"–","-"),"—","-") -> Technology Support Engineer | D35: =Sheet2!$G$18 -> Service Op & Assurance | E35: =Sheet2!$M$18 -> Australia | F35: =IF(LOWER(Sheet2!$Q$18)="v","Vacant",IF(LOWER(Sheet2!$Q$18)="pause","Paused",IF(LOWER(Sheet2!$Q$18)="cxc","Contractor","Filled"))) -> Filled | G35: =IF(Sheet2!$G$18="Service Op & Assurance","Service Operations","Cyber & Risk") -> Service Operations | H35: Onshore | I35: =Sheet2!$AA$18 -> 146885.5 | J35: =IF($H35="Offshore",$I35*'0.3 Squad Archetypes'!$K$5,$I35)/1000000 -> 0.1468855
B36: =Sheet2!$B$19 -> Joe Nahma | C36: =SUBSTITUTE(SUBSTITUTE(Sheet2!$C$19,"–","-"),"—","-") -> Manager Identity & Access Management | D36: =Sheet2!$G$19 -> Cyber Strat & Tech | E36: =Sheet2!$M$19 -> Australia | F36: =IF(LOWER(Sheet2!$Q$19)="v","Vacant",IF(LOWER(Sheet2!$Q$19)="pause","Paused",IF(LOWER(Sheet2!$Q$19)="cxc","Contractor","Filled"))) -> Filled | G36: =IF(Sheet2!$G$19="Service Op & Assurance","Service Operations","Cyber & Risk") -> Cyber & Risk | H36: Onshore | I36: =Sheet2!$AA$19 -> 258709.65 | J36: =IF($H36="Offshore",$I36*'0.3 Squad Archetypes'!$K$5,$I36)/1000000 -> 0.25870965
B37: =Sheet2!$B$20 -> Kaaviya Salai Manimudian | C37: =SUBSTITUTE(SUBSTITUTE(Sheet2!$C$20,"–","-"),"—","-") -> Graduate | D37: =Sheet2!$G$20 -> Service Op & Assurance | E37: =Sheet2!$M$20 -> Australia | F37: =IF(LOWER(Sheet2!$Q$20)="v","Vacant",IF(LOWER(Sheet2!$Q$20)="pause","Paused",IF(LOWER(Sheet2!$Q$20)="cxc","Contractor","Filled"))) -> Filled | G37: =IF(Sheet2!$G$20="Service Op & Assurance","Service Operations","Cyber & Risk") -> Service Operations | H37: Onshore | I37: =Sheet2!$AA$20 -> 110075 | J37: =IF($H37="Offshore",$I37*'0.3 Squad Archetypes'!$K$5,$I37)/1000000 -> 0.110075
B38: =Sheet2!$B$21 -> Kevin Sheerin | C38: =SUBSTITUTE(SUBSTITUTE(Sheet2!$C$21,"–","-"),"—","-") -> Cyber Architecture Lead | D38: =Sheet2!$G$21 -> Cyber Strat & Tech | E38: =Sheet2!$M$21 -> Australia | F38: =IF(LOWER(Sheet2!$Q$21)="v","Vacant",IF(LOWER(Sheet2!$Q$21)="pause","Paused",IF(LOWER(Sheet2!$Q$21)="cxc","Contractor","Filled"))) -> Filled | G38: =IF(Sheet2!$G$21="Service Op & Assurance","Service Operations","Cyber & Risk") -> Cyber & Risk | H38: Onshore | I38: =Sheet2!$AA$21 -> 284982.45 | J38: =IF($H38="Offshore",$I38*'0.3 Squad Archetypes'!$K$5,$I38)/1000000 -> 0.28498245
B39: =Sheet2!$B$22 -> Lisa Ng | C39: =SUBSTITUTE(SUBSTITUTE(Sheet2!$C$22,"–","-"),"—","-") -> Cyber Security Analyst | D39: =Sheet2!$G$22 -> Cyber Sec Ops | E39: =Sheet2!$M$22 -> NZ | F39: =IF(LOWER(Sheet2!$Q$22)="v","Vacant",IF(LOWER(Sheet2!$Q$22)="pause","Paused",IF(LOWER(Sheet2!$Q$22)="cxc","Contractor","Filled"))) -> Filled | G39: =IF(Sheet2!$G$22="Service Op & Assurance","Service Operations","Cyber & Risk") -> Cyber & Risk | H39: Onshore | I39: =Sheet2!$AA$22 -> 147800.06 | J39: =IF($H39="Offshore",$I39*'0.3 Squad Archetypes'!$K$5,$I39)/1000000 -> 0.14780006
B40: =Sheet2!$B$23 -> Lynda Niewidok | C40: =SUBSTITUTE(SUBSTITUTE(Sheet2!$C$23,"–","-"),"—","-") -> Lead - Service Desk | D40: =Sheet2!$G$23 -> Service Op & Assurance | E40: =Sheet2!$M$23 -> Australia | F40: =IF(LOWER(Sheet2!$Q$23)="v","Vacant",IF(LOWER(Sheet2!$Q$23)="pause","Paused",IF(LOWER(Sheet2!$Q$23)="cxc","Contractor","Filled"))) -> Filled | G40: =IF(Sheet2!$G$23="Service Op & Assurance","Service Operations","Cyber & Risk") -> Service Operations | H40: Onshore | I40: =Sheet2!$AA$23 -> 203988 | J40: =IF($H40="Offshore",$I40*'0.3 Squad Archetypes'!$K$5,$I40)/1000000 -> 0.203988
B41: =Sheet2!$B$24 -> Mark Pearson | C41: =SUBSTITUTE(SUBSTITUTE(Sheet2!$C$24,"–","-"),"—","-") -> Lead - Technology Support | D41: =Sheet2!$G$24 -> Service Op & Assurance | E41: =Sheet2!$M$24 -> Australia | F41: =IF(LOWER(Sheet2!$Q$24)="v","Vacant",IF(LOWER(Sheet2!$Q$24)="pause","Paused",IF(LOWER(Sheet2!$Q$24)="cxc","Contractor","Filled"))) -> Filled | G41: =IF(Sheet2!$G$24="Service Op & Assurance","Service Operations","Cyber & Risk") -> Service Operations | H41: Onshore | I41: =Sheet2!$AA$24 -> 203841.15 | J41: =IF($H41="Offshore",$I41*'0.3 Squad Archetypes'!$K$5,$I41)/1000000 -> 0.20384115
B42: =Sheet2!$B$25 -> Mary-Grace Rivera | C42: =SUBSTITUTE(SUBSTITUTE(Sheet2!$C$25,"–","-"),"—","-") -> Lead, Service Management | D42: =Sheet2!$G$25 -> Service Op & Assurance | E42: =Sheet2!$M$25 -> Australia | F42: =IF(LOWER(Sheet2!$Q$25)="v","Vacant",IF(LOWER(Sheet2!$Q$25)="pause","Paused",IF(LOWER(Sheet2!$Q$25)="cxc","Contractor","Filled"))) -> Filled | G42: =IF(Sheet2!$G$25="Service Op & Assurance","Service Operations","Cyber & Risk") -> Service Operations | H42: Onshore | I42: =Sheet2!$AA$25 -> 180970.3 | J42: =IF($H42="Offshore",$I42*'0.3 Squad Archetypes'!$K$5,$I42)/1000000 -> 0.1809703
B43: =Sheet2!$B$26 -> Mick Collins | C43: =SUBSTITUTE(SUBSTITUTE(Sheet2!$C$26,"–","-"),"—","-") -> Manager, Service Performance & Assurance | D43: =Sheet2!$G$26 -> Service Op & Assurance | E43: =Sheet2!$M$26 -> Australia | F43: =IF(LOWER(Sheet2!$Q$26)="v","Vacant",IF(LOWER(Sheet2!$Q$26)="pause","Paused",IF(LOWER(Sheet2!$Q$26)="cxc","Contractor","Filled"))) -> Filled | G43: =IF(Sheet2!$G$26="Service Op & Assurance","Service Operations","Cyber & Risk") -> Service Operations | H43: Onshore | I43: =Sheet2!$AA$26 -> 272070.45 | J43: =IF($H43="Offshore",$I43*'0.3 Squad Archetypes'!$K$5,$I43)/1000000 -> 0.27207045
B44: =Sheet2!$B$27 -> Nischal Bhusal | C44: =SUBSTITUTE(SUBSTITUTE(Sheet2!$C$27,"–","-"),"—","-") -> Cyber Security Analyst | D44: =Sheet2!$G$27 -> Cyber Sec Ops | E44: =Sheet2!$M$27 -> Australia | F44: =IF(LOWER(Sheet2!$Q$27)="v","Vacant",IF(LOWER(Sheet2!$Q$27)="pause","Paused",IF(LOWER(Sheet2!$Q$27)="cxc","Contractor","Filled"))) -> Filled | G44: =IF(Sheet2!$G$27="Service Op & Assurance","Service Operations","Cyber & Risk") -> Cyber & Risk | H44: Onshore | I44: =Sheet2!$AA$27 -> 215629.2 | J44: =IF($H44="Offshore",$I44*'0.3 Squad Archetypes'!$K$5,$I44)/1000000 -> 0.2156292
B45: =Sheet2!$B$28 -> Pooja Kuperkar | C45: =SUBSTITUTE(SUBSTITUTE(Sheet2!$C$28,"–","-"),"—","-") -> Cyber GRC Analyst | D45: =Sheet2!$G$28 -> Cyber GRC | E45: =Sheet2!$M$28 -> Australia | F45: =IF(LOWER(Sheet2!$Q$28)="v","Vacant",IF(LOWER(Sheet2!$Q$28)="pause","Paused",IF(LOWER(Sheet2!$Q$28)="cxc","Contractor","Filled"))) -> Filled | G45: =IF(Sheet2!$G$28="Service Op & Assurance","Service Operations","Cyber & Risk") -> Cyber & Risk | H45: Onshore | I45: =Sheet2!$AA$28 -> 203440.65 | J45: =IF($H45="Offshore",$I45*'0.3 Squad Archetypes'!$K$5,$I45)/1000000 -> 0.20344065
B46: =Sheet2!$B$29 -> Prashanth Chandran | C46: =SUBSTITUTE(SUBSTITUTE(Sheet2!$C$29,"–","-"),"—","-") -> Senior Cyber GRC Specialist | D46: =Sheet2!$G$29 -> Cyber GRC | E46: =Sheet2!$M$29 -> Australia | F46: =IF(LOWER(Sheet2!$Q$29)="v","Vacant",IF(LOWER(Sheet2!$Q$29)="pause","Paused",IF(LOWER(Sheet2!$Q$29)="cxc","Contractor","Filled"))) -> Filled | G46: =IF(Sheet2!$G$29="Service Op & Assurance","Service Operations","Cyber & Risk") -> Cyber & Risk | H46: Onshore | I46: =Sheet2!$AA$29 -> 220275 | J46: =IF($H46="Offshore",$I46*'0.3 Squad Archetypes'!$K$5,$I46)/1000000 -> 0.220275
B47: =Sheet2!$B$30 -> Rahul Sahni | C47: =SUBSTITUTE(SUBSTITUTE(Sheet2!$C$30,"–","-"),"—","-") -> Cyber Security Architect | D47: =Sheet2!$G$30 -> Cyber Strat & Tech | E47: =Sheet2!$M$30 -> Australia | F47: =IF(LOWER(Sheet2!$Q$30)="v","Vacant",IF(LOWER(Sheet2!$Q$30)="pause","Paused",IF(LOWER(Sheet2!$Q$30)="cxc","Contractor","Filled"))) -> Filled | G47: =IF(Sheet2!$G$30="Service Op & Assurance","Service Operations","Cyber & Risk") -> Cyber & Risk | H47: Onshore | I47: =Sheet2!$AA$30 -> 226282.5 | J47: =IF($H47="Offshore",$I47*'0.3 Squad Archetypes'!$K$5,$I47)/1000000 -> 0.2262825
B48: =Sheet2!$B$31 -> Rajini Onteddu Reddy | C48: =SUBSTITUTE(SUBSTITUTE(Sheet2!$C$31,"–","-"),"—","-") -> Head of Service Operations & Assurance | D48: =Sheet2!$G$31 -> Service Op & Assurance | E48: =Sheet2!$M$31 -> Australia | F48: =IF(LOWER(Sheet2!$Q$31)="v","Vacant",IF(LOWER(Sheet2!$Q$31)="pause","Paused",IF(LOWER(Sheet2!$Q$31)="cxc","Contractor","Filled"))) -> Filled | G48: =IF(Sheet2!$G$31="Service Op & Assurance","Service Operations","Cyber & Risk") -> Service Operations | H48: Onshore | I48: =Sheet2!$AA$31 -> 400671.4 | J48: =IF($H48="Offshore",$I48*'0.3 Squad Archetypes'!$K$5,$I48)/1000000 -> 0.4006714
B49: =Sheet2!$B$32 -> Raymond Cheung | C49: =SUBSTITUTE(SUBSTITUTE(Sheet2!$C$32,"–","-"),"—","-") -> Engineer - IDAM | D49: =Sheet2!$G$32 -> Cyber Strat & Tech | E49: =Sheet2!$M$32 -> Australia | F49: =IF(LOWER(Sheet2!$Q$32)="v","Vacant",IF(LOWER(Sheet2!$Q$32)="pause","Paused",IF(LOWER(Sheet2!$Q$32)="cxc","Contractor","Filled"))) -> Filled | G49: =IF(Sheet2!$G$32="Service Op & Assurance","Service Operations","Cyber & Risk") -> Cyber & Risk | H49: Onshore | I49: =Sheet2!$AA$32 -> 190675 | J49: =IF($H49="Offshore",$I49*'0.3 Squad Archetypes'!$K$5,$I49)/1000000 -> 0.190675
B50: =Sheet2!$B$33 -> Remya Pookat | C50: =SUBSTITUTE(SUBSTITUTE(Sheet2!$C$33,"–","-"),"—","-") -> Lead - Change & Release Management | D50: =Sheet2!$G$33 -> Service Op & Assurance | E50: =Sheet2!$M$33 -> Australia | F50: =IF(LOWER(Sheet2!$Q$33)="v","Vacant",IF(LOWER(Sheet2!$Q$33)="pause","Paused",IF(LOWER(Sheet2!$Q$33)="cxc","Contractor","Filled"))) -> Filled | G50: =IF(Sheet2!$G$33="Service Op & Assurance","Service Operations","Cyber & Risk") -> Service Operations | H50: Onshore | I50: =Sheet2!$AA$33 -> 220875.75 | J50: =IF($H50="Offshore",$I50*'0.3 Squad Archetypes'!$K$5,$I50)/1000000 -> 0.22087575
B51: =Sheet2!$B$34 -> Ritika Salaria | C51: =SUBSTITUTE(SUBSTITUTE(Sheet2!$C$34,"–","-"),"—","-") -> Configuration Analyst | D51: =Sheet2!$G$34 -> Service Op & Assurance | E51: =Sheet2!$M$34 -> Australia | F51: =IF(LOWER(Sheet2!$Q$34)="v","Vacant",IF(LOWER(Sheet2!$Q$34)="pause","Paused",IF(LOWER(Sheet2!$Q$34)="cxc","Contractor","Filled"))) -> Filled | G51: =IF(Sheet2!$G$34="Service Op & Assurance","Service Operations","Cyber & Risk") -> Service Operations | H51: Onshore | I51: =Sheet2!$AA$34 -> 173106.6 | J51: =IF($H51="Offshore",$I51*'0.3 Squad Archetypes'!$K$5,$I51)/1000000 -> 0.1731066
B52: =Sheet2!$B$35 -> Sameer Pattanaik | C52: =SUBSTITUTE(SUBSTITUTE(Sheet2!$C$35,"–","-"),"—","-") -> Cyber Security Operations Lead | D52: =Sheet2!$G$35 -> Cyber Sec Ops | E52: =Sheet2!$M$35 -> NZ | F52: =IF(LOWER(Sheet2!$Q$35)="v","Vacant",IF(LOWER(Sheet2!$Q$35)="pause","Paused",IF(LOWER(Sheet2!$Q$35)="cxc","Contractor","Filled"))) -> Filled | G52: =IF(Sheet2!$G$35="Service Op & Assurance","Service Operations","Cyber & Risk") -> Cyber & Risk | H52: Onshore | I52: =Sheet2!$AA$35 -> 212878.38 | J52: =IF($H52="Offshore",$I52*'0.3 Squad Archetypes'!$K$5,$I52)/1000000 -> 0.21287838
B53: =Sheet2!$B$36 -> Shomiya Shayal | C53: =SUBSTITUTE(SUBSTITUTE(Sheet2!$C$36,"–","-"),"—","-") -> Risk & Resilience Lead | D53: =Sheet2!$G$36 -> Cyber Risk | E53: =Sheet2!$M$36 -> NZ | F53: =IF(LOWER(Sheet2!$Q$36)="v","Vacant",IF(LOWER(Sheet2!$Q$36)="pause","Paused",IF(LOWER(Sheet2!$Q$36)="cxc","Contractor","Filled"))) -> Filled | G53: =IF(Sheet2!$G$36="Service Op & Assurance","Service Operations","Cyber & Risk") -> Cyber & Risk | H53: Onshore | I53: =Sheet2!$AA$36 -> 188515.03 | J53: =IF($H53="Offshore",$I53*'0.3 Squad Archetypes'!$K$5,$I53)/1000000 -> 0.18851503
B54: =Sheet2!$B$37 -> Shruti Manchanda | C54: =SUBSTITUTE(SUBSTITUTE(Sheet2!$C$37,"–","-"),"—","-") -> Cyber GRC Analyst | D54: =Sheet2!$G$37 -> Cyber GRC | E54: =Sheet2!$M$37 -> Australia | F54: =IF(LOWER(Sheet2!$Q$37)="v","Vacant",IF(LOWER(Sheet2!$Q$37)="pause","Paused",IF(LOWER(Sheet2!$Q$37)="cxc","Contractor","Filled"))) -> Filled | G54: =IF(Sheet2!$G$37="Service Op & Assurance","Service Operations","Cyber & Risk") -> Cyber & Risk | H54: Onshore | I54: =Sheet2!$AA$37 -> 228885.75 | J54: =IF($H54="Offshore",$I54*'0.3 Squad Archetypes'!$K$5,$I54)/1000000 -> 0.22888575
B55: =Sheet2!$B$38 -> Spoilagi Bhutwala | C55: =SUBSTITUTE(SUBSTITUTE(Sheet2!$C$38,"–","-"),"—","-") -> Tech Support Technician | D55: =Sheet2!$G$38 -> Service Op & Assurance | E55: =Sheet2!$M$38 -> NZ | F55: =IF(LOWER(Sheet2!$Q$38)="v","Vacant",IF(LOWER(Sheet2!$Q$38)="pause","Paused",IF(LOWER(Sheet2!$Q$38)="cxc","Contractor","Filled"))) -> Filled | G55: =IF(Sheet2!$G$38="Service Op & Assurance","Service Operations","Cyber & Risk") -> Service Operations | H55: Onshore | I55: =Sheet2!$AA$38 -> 97237.784 | J55: =IF($H55="Offshore",$I55*'0.3 Squad Archetypes'!$K$5,$I55)/1000000 -> 0.097237784
B56: =Sheet2!$B$39 -> Stafford Dowling | C56: =SUBSTITUTE(SUBSTITUTE(Sheet2!$C$39,"–","-"),"—","-") -> Cyber Security Analyst | D56: =Sheet2!$G$39 -> Cyber Sec Ops | E56: =Sheet2!$M$39 -> Australia | F56: =IF(LOWER(Sheet2!$Q$39)="v","Vacant",IF(LOWER(Sheet2!$Q$39)="pause","Paused",IF(LOWER(Sheet2!$Q$39)="cxc","Contractor","Filled"))) -> Filled | G56: =IF(Sheet2!$G$39="Service Op & Assurance","Service Operations","Cyber & Risk") -> Cyber & Risk | H56: Onshore | I56: =Sheet2!$AA$39 -> 218713.05 | J56: =IF($H56="Offshore",$I56*'0.3 Squad Archetypes'!$K$5,$I56)/1000000 -> 0.21871305
B57: =Sheet2!$B$40 -> Steven Atcheson | C57: =SUBSTITUTE(SUBSTITUTE(Sheet2!$C$40,"–","-"),"—","-") -> Manager Cyber Security Operations | D57: =Sheet2!$G$40 -> Cyber Sec Ops | E57: =Sheet2!$M$40 -> Australia | F57: =IF(LOWER(Sheet2!$Q$40)="v","Vacant",IF(LOWER(Sheet2!$Q$40)="pause","Paused",IF(LOWER(Sheet2!$Q$40)="cxc","Contractor","Filled"))) -> Filled | G57: =IF(Sheet2!$G$40="Service Op & Assurance","Service Operations","Cyber & Risk") -> Cyber & Risk | H57: Onshore | I57: =Sheet2!$AA$40 -> 316568.65 | J57: =IF($H57="Offshore",$I57*'0.3 Squad Archetypes'!$K$5,$I57)/1000000 -> 0.31656865
B58: =Sheet2!$B$41 -> Tony Keeler | C58: =SUBSTITUTE(SUBSTITUTE(Sheet2!$C$41,"–","-"),"—","-") -> Cyber Business Analyst | D58: =Sheet2!$G$41 -> Cyber Strat & Tech | E58: =Sheet2!$M$41 -> Australia | F58: =IF(LOWER(Sheet2!$Q$41)="v","Vacant",IF(LOWER(Sheet2!$Q$41)="pause","Paused",IF(LOWER(Sheet2!$Q$41)="cxc","Contractor","Filled"))) -> Filled | G58: =IF(Sheet2!$G$41="Service Op & Assurance","Service Operations","Cyber & Risk") -> Cyber & Risk | H58: Onshore | I58: =Sheet2!$AA$41 -> 213600 | J58: =IF($H58="Offshore",$I58*'0.3 Squad Archetypes'!$K$5,$I58)/1000000 -> 0.2136
B59: =Sheet2!$B$42 -> Vacant | C59: =SUBSTITUTE(SUBSTITUTE(Sheet2!$C$42,"–","-"),"—","-") -> Lead - Problem Management | D59: =Sheet2!$G$42 -> Service Op & Assurance | E59: =Sheet2!$M$42 -> Australia | F59: =IF(LOWER(Sheet2!$Q$42)="v","Vacant",IF(LOWER(Sheet2!$Q$42)="pause","Paused",IF(LOWER(Sheet2!$Q$42)="cxc","Contractor","Filled"))) -> Vacant | G59: =IF(Sheet2!$G$42="Service Op & Assurance","Service Operations","Cyber & Risk") -> Service Operations | H59: Onshore | I59: =Sheet2!$AA$42 -> 170489.75 | J59: =IF($H59="Offshore",$I59*'0.3 Squad Archetypes'!$K$5,$I59)/1000000 -> 0.17048975
B60: =Sheet2!$B$43 -> Vacant | C60: =SUBSTITUTE(SUBSTITUTE(Sheet2!$C$43,"–","-"),"—","-") -> Cyber Architect (backfill for EGI Secondment) | D60: =Sheet2!$G$43 -> Cyber Strat & Tech | E60: =Sheet2!$M$43 -> Australia | F60: =IF(LOWER(Sheet2!$Q$43)="v","Vacant",IF(LOWER(Sheet2!$Q$43)="pause","Paused",IF(LOWER(Sheet2!$Q$43)="cxc","Contractor","Filled"))) -> Vacant | G60: =IF(Sheet2!$G$43="Service Op & Assurance","Service Operations","Cyber & Risk") -> Cyber & Risk | H60: Onshore | I60: =Sheet2!$AA$43 -> 213600 | J60: =IF($H60="Offshore",$I60*'0.3 Squad Archetypes'!$K$5,$I60)/1000000 -> 0.2136
B61: =Sheet2!$B$44 -> Vacant | C61: =SUBSTITUTE(SUBSTITUTE(Sheet2!$C$44,"–","-"),"—","-") -> Lead - Asset & Configuration | D61: =Sheet2!$G$44 -> Service Op & Assurance | E61: =Sheet2!$M$44 -> Australia | F61: =IF(LOWER(Sheet2!$Q$44)="v","Vacant",IF(LOWER(Sheet2!$Q$44)="pause","Paused",IF(LOWER(Sheet2!$Q$44)="cxc","Contractor","Filled"))) -> Vacant | G61: =IF(Sheet2!$G$44="Service Op & Assurance","Service Operations","Cyber & Risk") -> Service Operations | H61: Onshore | I61: =Sheet2!$AA$44 -> 202853.25 | J61: =IF($H61="Offshore",$I61*'0.3 Squad Archetypes'!$K$5,$I61)/1000000 -> 0.20285325
B62: =Sheet2!$B$45 -> Vacant | C62: =SUBSTITUTE(SUBSTITUTE(Sheet2!$C$45,"–","-"),"—","-") -> Lead - Service Performance & Insights | D62: =Sheet2!$G$45 -> Service Op & Assurance | E62: =Sheet2!$M$45 -> Australia | F62: =IF(LOWER(Sheet2!$Q$45)="v","Vacant",IF(LOWER(Sheet2!$Q$45)="pause","Paused",IF(LOWER(Sheet2!$Q$45)="cxc","Contractor","Filled"))) -> Vacant | G62: =IF(Sheet2!$G$45="Service Op & Assurance","Service Operations","Cyber & Risk") -> Service Operations | H62: Onshore | I62: =Sheet2!$AA$45 -> 202853.25 | J62: =IF($H62="Offshore",$I62*'0.3 Squad Archetypes'!$K$5,$I62)/1000000 -> 0.20285325
B63: =Sheet2!$B$46 -> Vacant | C63: =SUBSTITUTE(SUBSTITUTE(Sheet2!$C$46,"–","-"),"—","-") -> Operations Analyst | D63: =Sheet2!$G$46 -> Service Op & Assurance | E63: =Sheet2!$M$46 -> Australia | F63: =IF(LOWER(Sheet2!$Q$46)="v","Vacant",IF(LOWER(Sheet2!$Q$46)="pause","Paused",IF(LOWER(Sheet2!$Q$46)="cxc","Contractor","Filled"))) -> Vacant | G63: =IF(Sheet2!$G$46="Service Op & Assurance","Service Operations","Cyber & Risk") -> Service Operations | H63: Onshore | I63: =Sheet2!$AA$46 -> 170489.75 | J63: =IF($H63="Offshore",$I63*'0.3 Squad Archetypes'!$K$5,$I63)/1000000 -> 0.17048975
B64: =Sheet2!$B$47 -> Vacant | C64: =SUBSTITUTE(SUBSTITUTE(Sheet2!$C$47,"–","-"),"—","-") -> Operations Analyst | D64: =Sheet2!$G$47 -> Service Op & Assurance | E64: =Sheet2!$M$47 -> Australia | F64: =IF(LOWER(Sheet2!$Q$47)="v","Vacant",IF(LOWER(Sheet2!$Q$47)="pause","Paused",IF(LOWER(Sheet2!$Q$47)="cxc","Contractor","Filled"))) -> Vacant | G64: =IF(Sheet2!$G$47="Service Op & Assurance","Service Operations","Cyber & Risk") -> Service Operations | H64: Onshore | I64: =Sheet2!$AA$47 -> 170489.75 | J64: =IF($H64="Offshore",$I64*'0.3 Squad Archetypes'!$K$5,$I64)/1000000 -> 0.17048975
B65: =Sheet2!$B$48 -> Vacant | C65: =SUBSTITUTE(SUBSTITUTE(Sheet2!$C$48,"–","-"),"—","-") -> Data Risk Analyst | D65: =Sheet2!$G$48 -> Cyber Risk | E65: =Sheet2!$M$48 -> Australia | F65: =IF(LOWER(Sheet2!$Q$48)="v","Vacant",IF(LOWER(Sheet2!$Q$48)="pause","Paused",IF(LOWER(Sheet2!$Q$48)="cxc","Contractor","Filled"))) -> Vacant | G65: =IF(Sheet2!$G$48="Service Op & Assurance","Service Operations","Cyber & Risk") -> Cyber & Risk | H65: Onshore | I65: =Sheet2!$AA$48 -> 170489.75 | J65: =IF($H65="Offshore",$I65*'0.3 Squad Archetypes'!$K$5,$I65)/1000000 -> 0.17048975
B66: =Sheet2!$B$49 -> Vacant | C66: =SUBSTITUTE(SUBSTITUTE(Sheet2!$C$49,"–","-"),"—","-") -> Data Risk Analyst | D66: =Sheet2!$G$49 -> Cyber Risk | E66: =Sheet2!$M$49 -> Australia | F66: =IF(LOWER(Sheet2!$Q$49)="v","Vacant",IF(LOWER(Sheet2!$Q$49)="pause","Paused",IF(LOWER(Sheet2!$Q$49)="cxc","Contractor","Filled"))) -> Vacant | G66: =IF(Sheet2!$G$49="Service Op & Assurance","Service Operations","Cyber & Risk") -> Cyber & Risk | H66: Onshore | I66: =Sheet2!$AA$49 -> 170489.75 | J66: =IF($H66="Offshore",$I66*'0.3 Squad Archetypes'!$K$5,$I66)/1000000 -> 0.17048975
B67: =Sheet2!$B$50 -> Vacant (AKL ) | C67: =SUBSTITUTE(SUBSTITUTE(Sheet2!$C$50,"–","-"),"—","-") -> Tech Support Technician | D67: =Sheet2!$G$50 -> Service Op & Assurance | E67: =Sheet2!$M$50 -> Australia | F67: =IF(LOWER(Sheet2!$Q$50)="v","Vacant",IF(LOWER(Sheet2!$Q$50)="pause","Paused",IF(LOWER(Sheet2!$Q$50)="cxc","Contractor","Filled"))) -> Vacant | G67: =IF(Sheet2!$G$50="Service Op & Assurance","Service Operations","Cyber & Risk") -> Service Operations | H67: Onshore | I67: =Sheet2!$AA$50 -> 122571.75 | J67: =IF($H67="Offshore",$I67*'0.3 Squad Archetypes'!$K$5,$I67)/1000000 -> 0.12257175
B68: =Sheet2!$B$51 -> Vacant (SYD) | C68: =SUBSTITUTE(SUBSTITUTE(Sheet2!$C$51,"–","-"),"—","-") -> Tech Support Technician | D68: =Sheet2!$G$51 -> Service Op & Assurance | E68: =Sheet2!$M$51 -> Australia | F68: =IF(LOWER(Sheet2!$Q$51)="v","Vacant",IF(LOWER(Sheet2!$Q$51)="pause","Paused",IF(LOWER(Sheet2!$Q$51)="cxc","Contractor","Filled"))) -> Vacant | G68: =IF(Sheet2!$G$51="Service Op & Assurance","Service Operations","Cyber & Risk") -> Service Operations | H68: Onshore | I68: =Sheet2!$AA$51 -> 122571.75 | J68: =IF($H68="Offshore",$I68*'0.3 Squad Archetypes'!$K$5,$I68)/1000000 -> 0.12257175
B69: =Sheet2!$B$52 -> Vanessa Castro | C69: =SUBSTITUTE(SUBSTITUTE(Sheet2!$C$52,"–","-"),"—","-") -> Cyber GRC Analyst | D69: =Sheet2!$G$52 -> Cyber GRC | E69: =Sheet2!$M$52 -> NZ | F69: =IF(LOWER(Sheet2!$Q$52)="v","Vacant",IF(LOWER(Sheet2!$Q$52)="pause","Paused",IF(LOWER(Sheet2!$Q$52)="cxc","Contractor","Filled"))) -> Filled | G69: =IF(Sheet2!$G$52="Service Op & Assurance","Service Operations","Cyber & Risk") -> Cyber & Risk | H69: Onshore | I69: =Sheet2!$AA$52 -> 131833.19 | J69: =IF($H69="Offshore",$I69*'0.3 Squad Archetypes'!$K$5,$I69)/1000000 -> 0.13183319
B70: =Sheet2!$B$53 -> Vivienne Vasak | C70: =SUBSTITUTE(SUBSTITUTE(Sheet2!$C$53,"–","-"),"—","-") -> Portfolio Manager Cyber Security | D70: =Sheet2!$G$53 -> Cyber Strat & Tech | E70: =Sheet2!$M$53 -> Australia | F70: =IF(LOWER(Sheet2!$Q$53)="v","Vacant",IF(LOWER(Sheet2!$Q$53)="pause","Paused",IF(LOWER(Sheet2!$Q$53)="cxc","Contractor","Filled"))) -> Filled | G70: =IF(Sheet2!$G$53="Service Op & Assurance","Service Operations","Cyber & Risk") -> Cyber & Risk | H70: Onshore | I70: =Sheet2!$AA$53 -> 315674.35 | J70: =IF($H70="Offshore",$I70*'0.3 Squad Archetypes'!$K$5,$I70)/1000000 -> 0.31567435
B71: Check - roles listed vs counted (must be 0) | C71: =COUNTA(B19:B70)-C8 -> 0
B73: Roles and costs come straight from Sheet2 (updated cyber, risk and operations roster).

Sheet 2.4 COE Summary
B2: COE Budget View
B3: Roll-up only - edit budgets on 0.2 Data Config, rosters on Sheet2. Detail on 2.1 / 2.2 / 2.3.
B6: COE Budgets
B7: COE | C7: TDD Lights On Budget ($m) | D7: Planned spend ($m) | E7: Budget to draw down ($m) | F7: Left to fund ($m) | G7: Total cost ($m) | K7: Other Architecture | L7: 1.1
B8: COE - Strategy Architecture | C8: ='0.2 Data Config'!$E$6 -> 2 | D8: ='2.2 SA&D'!$G$6 -> 4.320561 | E8: ='0.2 Data Config'!$E$6+COUNTA('2.5 Group Summary'!$B$6:$B$16)*'0.2 Data Config'!$L$8 -> 3.54 | F8: ='2.2 SA&D'!$I$6 -> 0.780561 | G8: =D8 -> 4.320561 | K8: Domain Architects are an overhead | L8: -1.1
B9: COE - Cyber, Risk & Service Ops (rolled into 1.11 TDD Cyber) | C9: ='0.2 Data Config'!$E$7 -> 0 | D9: =0 -> 0 | E9: =0 -> 0 | F9: =D9-E9 -> 0 | G9: =D9 -> 0 | K9: Strategy | L9: 1.7
B10: COE - Transformation | C10: ='0.2 Data Config'!$E$8 -> 2 | D10: ='2.1 BP&T'!$F$7 -> 3.1079992 | E10: ='0.2 Data Config'!$E$8 -> 2 | F10: ='2.1 BP&T'!$H$7 -> 1.1079992 | G10: =D10 -> 3.1079992
B11: COE - Business Partnering | C11: ='0.2 Data Config'!$E$9 -> 2 | D11: ='2.1 BP&T'!$F$6 -> 3.2925626 | E11: ='0.2 Data Config'!$E$9+COUNTA('2.5 Group Summary'!$B$6:$B$16)*'0.2 Data Config'!$L$7 -> 3.892 | F11: ='2.1 BP&T'!$H$6 -> 0 | G11: =D11 -> 3.2925626 | K11: Data | L11: 2.2
B12: COE - Data | C12: ='0.2 Data Config'!$E$10 -> 2 | D12: ='2.2 SA&D'!$G$7 -> 2.2327366 | E12: ='0.2 Data Config'!$E$10 -> 2 | F12: ='2.2 SA&D'!$I$7 -> 0.23273662 | G12: =D12 -> 2.2327366
B13: Total | C13: =SUM(C8:C12) -> 8 | D13: =SUM(D8:D12) -> 12.953859 | E13: =SUM(E8:E12) -> 11.432 | F13: =SUM(F8:F12) -> 2.1212968 | G13: =SUM(G8:G12) -> 12.953859
B16: TDD Corporate funding pool ($m)
B17: Funding line | C17: Pool ($m) | D17: Drawn ($m) | E17: Remaining ($m)
B18: OpEx Initiatives | C18: ='0.1 Budget Table (Fin)'!$N$5 -> 3 | D18: 0 | E18: =C18-D18 -> 3
B19: Significant Items | C19: ='0.1 Budget Table (Fin)'!$O$5 -> 20.2 | D19: ='1.3 Enterprise Data'!$I$13+'1.4 TDD Group Functions'!$I$13+'1.11 TDD Cyber'!$I$13 -> 0 | E19: =C19-D19 -> 20.2
B20: CapEx | C20: ='0.1 Budget Table (Fin)'!$P$5 -> 4.9 | D20: ='1.9 Commercial Fuels'!$I$15 -> 0 | E20: =C20-D20 -> 4.9
B21: Total | C21: =SUM(C18:C20) -> 28.1 | D21: =SUM(D18:D20) -> 0 | E21: =SUM(E18:E20) -> 28.1
B23: Every COE role is now mapped on 2.1, 2.2 or 2.3 from the updated rosters on Sheet2 - no unspecified roles remain.

Sheet 2.5 Group Summary
B2: TDD Summary - all portfolios
B3: Archetype view: what the designed model costs against the TDD budgets. The actual organisation is on 2.6.
B4: TDD Cost vs TDD Lights On budget, by portfolio
B5: Portfolio | C5: TDD Lights On Budget ($m) | D5: Support Cost ($m) | E5: Variance ($m) = budget - cost | G5: Cost of non-TDD funding ($m) | H5: Amount that can be recharged ($m) | I5: Left to fund outside TDD ($m) | J5: Total still left to fund ($m) | K5: Total Cost ($m)
B6: Ampol Retail | C6: ='1.1 Ampol Retail'!$H$5 -> 2.5 | D6: ='1.1 Ampol Retail'!$C$9 -> 5.6265 | E6: ='1.1 Ampol Retail'!$H$7 -> -3.1265 | G6: ='1.1 Ampol Retail'!$D$9 -> 4.728 | H6: ='1.1 Ampol Retail'!$I$17 -> 0 | I6: ='1.1 Ampol Retail'!$I$19 -> 4.728 | J6: =MAX(0,-E6)+I6 -> 7.8545 | K6: ='1.1 Ampol Retail'!$E$9 -> 10.3545
B7: Customer | C7: ='1.2 Customer'!$H$5 -> 6.5 | D7: ='1.2 Customer'!$C$9 -> 9.0245 | E7: ='1.2 Customer'!$H$7 -> -2.5245 | G7: ='1.2 Customer'!$D$9 -> 5.92 | H7: ='1.2 Customer'!$I$22 -> 4 | I7: ='1.2 Customer'!$I$24 -> 1.92 | J7: =MAX(0,-E7)+I7 -> 4.4445 | K7: ='1.2 Customer'!$E$9 -> 14.9445
B8: Enterprise Data | C8: ='1.3 Enterprise Data'!$H$5 -> 3.5 | D8: ='1.3 Enterprise Data'!$C$9 -> 4.1105 | E8: ='1.3 Enterprise Data'!$H$7 -> -0.6105 | G8: ='1.3 Enterprise Data'!$D$9 -> 1.904 | H8: ='1.3 Enterprise Data'!$I$13 -> 0 | I8: ='1.3 Enterprise Data'!$I$14 -> 1.904 | J8: =MAX(0,-E8)+I8 -> 2.5145 | K8: ='1.3 Enterprise Data'!$E$9 -> 6.0145
B9: TDD Group Functions | C9: ='1.4 TDD Group Functions'!$H$5 -> 5.5 | D9: ='1.4 TDD Group Functions'!$C$9 -> 3.6645 | E9: ='1.4 TDD Group Functions'!$H$7 -> 1.8355 | G9: ='1.4 TDD Group Functions'!$D$9 -> 1.15 | H9: ='1.4 TDD Group Functions'!$I$13 -> 0 | I9: ='1.4 TDD Group Functions'!$I$14 -> 1.15 | J9: =MAX(0,-E9)+I9 -> 1.15 | K9: ='1.4 TDD Group Functions'!$E$9 -> 4.8145
B10: P&C | C10: ='1.5 P&C'!$H$5 -> 2 | D10: ='1.5 P&C'!$C$9 -> 1.2745 | E10: ='1.5 P&C'!$H$7 -> 0.7255 | G10: ='1.5 P&C'!$D$9 -> 1.44 | H10: ='1.5 P&C'!$I$18 -> 0 | I10: ='1.5 P&C'!$I$20 -> 1.44 | J10: =MAX(0,-E10)+I10 -> 1.44 | K10: ='1.5 P&C'!$E$9 -> 2.7145
B11: Finance | C11: ='1.6 Finance'!$H$5 -> 2 | D11: ='1.6 Finance'!$C$9 -> 1.4145 | E11: ='1.6 Finance'!$H$7 -> 0.5855 | G11: ='1.6 Finance'!$D$9 -> 2 | H11: ='1.6 Finance'!$I$18 -> 0 | I11: ='1.6 Finance'!$I$20 -> 2 | J11: =MAX(0,-E11)+I11 -> 2 | K11: ='1.6 Finance'!$E$9 -> 3.4145
B12: Infrastructure | C12: ='1.7 Infrastructure'!$H$6 -> 2.5 | D12: ='1.7 Infrastructure'!$C$10 -> 2.5245 | E12: ='1.7 Infrastructure'!$H$8 -> -0.0245 | G12: ='1.7 Infrastructure'!$D$10 -> 2.72 | H12: ='1.7 Infrastructure'!$I$18 -> 0 | I12: ='1.7 Infrastructure'!$I$20 -> 2.72 | J12: =MAX(0,-E12)+I12 -> 2.7445 | K12: ='1.7 Infrastructure'!$E$10 -> 5.2445
B13: Energy Solutions & B2B | C13: ='1.8 Energy Solutions & B2B'!$H$5 -> 2.5 | D13: ='1.8 Energy Solutions & B2B'!$C$9 -> 2.5095 | E13: ='1.8 Energy Solutions & B2B'!$H$7 -> -0.0095 | G13: ='1.8 Energy Solutions & B2B'!$D$9 -> 4.67 | H13: ='1.8 Energy Solutions & B2B'!$I$20 -> 3.5 | I13: ='1.8 Energy Solutions & B2B'!$I$22 -> 1.17 | J13: =MAX(0,-E13)+I13 -> 1.1795 | K13: ='1.8 Energy Solutions & B2B'!$E$9 -> 7.1795
B14: Commercial Fuels | C14: ='1.9 Commercial Fuels'!$H$5 -> 2.5 | D14: ='1.9 Commercial Fuels'!$C$9 -> 2.0845 | E14: ='1.9 Commercial Fuels'!$H$7 -> 0.4155 | G14: ='1.9 Commercial Fuels'!$D$9 -> 5.06 | H14: ='1.9 Commercial Fuels'!$I$18 -> 3.1 | I14: ='1.9 Commercial Fuels'!$I$20 -> 1.96 | J14: =MAX(0,-E14)+I14 -> 1.96 | K14: ='1.9 Commercial Fuels'!$E$9 -> 7.1445
B15: Z Retail | C15: ='1.10 Z Retail'!$H$5 -> 2.5 | D15: ='1.10 Z Retail'!$C$9 -> 5.3995 | E15: ='1.10 Z Retail'!$H$7 -> -2.8995 | G15: ='1.10 Z Retail'!$D$9 -> 1.08 | H15: ='1.10 Z Retail'!$I$17 -> 1.08 | I15: ='1.10 Z Retail'!$I$19 -> 0 | J15: =MAX(0,-E15)+I15 -> 2.8995 | K15: ='1.10 Z Retail'!$E$9 -> 6.4795
B16: TDD Cyber | C16: ='1.11 TDD Cyber'!$H$5 -> 3.5 | D16: ='1.11 TDD Cyber'!$C$9 -> 11.830489 | E16: ='1.11 TDD Cyber'!$H$7 -> -8.330489 | G16: ='1.11 TDD Cyber'!$D$9 -> 0 | H16: ='1.11 TDD Cyber'!$I$13 -> 0 | I16: ='1.11 TDD Cyber'!$I$14 -> 0 | J16: =MAX(0,-E16)+I16 -> 8.330489 | K16: ='1.11 TDD Cyber'!$E$9 -> 11.830489
B17: Total - all portfolios | C17: =SUM(C6:C16) -> 35.5 | D17: =SUM(D6:D16) -> 49.463489 | E17: =SUM(E6:E16) -> -13.963489 | G17: =SUM(G6:G16) -> 30.672 | H17: =SUM(H6:H16) -> 11.68 | I17: =SUM(I6:I16) -> 18.992 | J17: =SUM(J6:J16) -> 36.517489 | K17: =SUM(K6:K16) -> 80.135489
B18: COE - Strategy Architecture | C18: ='0.2 Data Config'!$E$6 -> 2 | D18: ='2.4 COE Summary'!$D$8 -> 4.320561 | E18: =C18-D18 -> -2.320561 | G18: 0 | H18: ='2.4 COE Summary'!$E$8 -> 3.54 | I18: ='2.4 COE Summary'!$F$8 -> 0.780561 | J18: =MAX(0,-E18)+I18 -> 3.101122 | K18: ='2.4 COE Summary'!$G$8 -> 4.320561
B19: COE - Cyber, Risk & Service Ops (rolled into 1.11 TDD Cyber) | C19: ='0.2 Data Config'!$E$7 -> 0 | D19: ='2.4 COE Summary'!$D$9 -> 0 | E19: =C19-D19 -> 0 | G19: 0 | H19: ='2.4 COE Summary'!$E$9 -> 0 | I19: ='2.4 COE Summary'!$F$9 -> 0 | J19: =MAX(0,-E19)+I19 -> 0 | K19: ='2.4 COE Summary'!$G$9 -> 0
B20: COE - Transformation | C20: ='0.2 Data Config'!$E$8 -> 2 | D20: ='2.4 COE Summary'!$D$10 -> 3.1079992 | E20: =C20-D20 -> -1.1079992 | G20: 0 | H20: ='2.4 COE Summary'!$E$10 -> 2 | I20: ='2.4 COE Summary'!$F$10 -> 1.1079992 | J20: =MAX(0,-E20)+I20 -> 2.2159985 | K20: ='2.4 COE Summary'!$G$10 -> 3.1079992
B21: COE - Business Partnering | C21: ='0.2 Data Config'!$E$9 -> 2 | D21: ='2.4 COE Summary'!$D$11 -> 3.2925626 | E21: =C21-D21 -> -1.2925626 | G21: 0 | H21: ='2.4 COE Summary'!$E$11 -> 3.892 | I21: ='2.4 COE Summary'!$F$11 -> 0 | J21: =MAX(0,-E21)+I21 -> 1.2925626 | K21: ='2.4 COE Summary'!$G$11 -> 3.2925626
B22: COE - Data | C22: ='0.2 Data Config'!$E$10 -> 2 | D22: ='2.4 COE Summary'!$D$12 -> 2.2327366 | E22: =C22-D22 -> -0.23273662 | G22: 0 | H22: ='2.4 COE Summary'!$E$12 -> 2 | I22: ='2.4 COE Summary'!$F$12 -> 0.23273662 | J22: =MAX(0,-E22)+I22 -> 0.46547323 | K22: ='2.4 COE Summary'!$G$12 -> 2.2327366
B24: Total - portfolios + COEs | C24: =SUM(C17,C18,C19,C20,C21,C22) -> 43.5 | D24: =SUM(D17,D18,D19,D20,D21,D22) -> 62.417348 | E24: =SUM(E17,E18,E19,E20,E21,E22) -> -18.917348 | G24: =SUM(G17,G18,G19,G20,G21,G22) -> 30.672 | H24: =SUM(H17,H18,H19,H20,H21,H22) -> 23.112 | I24: =SUM(I17,I18,I19,I20,I21,I22) -> 21.113297 | J24: =SUM(J17,J18,J19,J20,J21,J22) -> 43.592645 | K24: =SUM(K17,K18,K19,K20,K21,K22) -> 93.089348
B25: Less: BP & Domain Architect already funded in portfolio overheads (see 2.1) | K25: ='2.6 Total Cost'!$C$23 -> -3.432
B26: Net operating model cost - ties to 2.1 Total Cost ($m) | K26: =K24+'2.6 Total Cost'!$C$23 -> 89.657348
B27: Reconciliation to Data Config TDD budget allocation
B28: Portfolio budgets (above) | C28: =C17 -> 35.5
B29: COE allocations (2.4 COE Summary) | C29: ='2.4 COE Summary'!$C$13 -> 8
B30: Total allocation accounted for | C30: =C28+C29 -> 43.5
B31: Data Config total allocation | C31: ='0.2 Data Config'!$E$26 -> 43.5
B32: Check (should be 0) | C32: =C30-C31 -> 0
B33: Unallocated TDD budget (headroom) | C33: ='0.2 Data Config'!$E$27-'0.2 Data Config'!$E$26 -> 10.3
B34: Total TDD Lights On budget (Finance) | C34: ='0.2 Data Config'!$E$27 -> 53.8
B35: % of TDD budget allocated | C35: =C30/C34 -> 0.80855019
B37: AU / NZ funding split - from the squad Fund toggles on the 1.x tabs
B38: AU budget - 0.2 Data Config ($m) | C38: ='0.2 Data Config'!$C$27 -> 36.2
B39: AU allocated to COEs - 0.2 Data Config ($m) | C39: =SUM('0.2 Data Config'!$C$6:$C$10) -> 6
B40: TDD squad cost - AU funded ($m) | C40: ='1.1 Ampol Retail'!$C$68+'1.2 Customer'!$C$56+'1.3 Enterprise Data'!$C$32+'1.4 TDD Group Functions'!$C$36+'1.5 P&C'!$C$34+'1.6 Finance'!$C$34+'1.7 Infrastructure'!$C$42+'1.8 Energy Solutions & B2B'!$C$38+'1.9 Commercial Fuels'!$C$42+'1.10 Z Retail'!$C$35+'1.11 TDD Cyber'!$C$29 -> 28.203989
B41: Variance vs AU budget ($m) | C41: =C38-C39-C40 -> 1.996011
B42: NZ budget - 0.2 Data Config ($m) | C42: ='0.2 Data Config'!$D$27 -> 17.6
B43: NZ allocated to COEs - 0.2 Data Config ($m) | C43: =SUM('0.2 Data Config'!$D$6:$D$10) -> 2
B44: TDD squad cost - NZ funded ($m) | C44: ='1.1 Ampol Retail'!$C$69+'1.2 Customer'!$C$57+'1.3 Enterprise Data'!$C$33+'1.4 TDD Group Functions'!$C$37+'1.5 P&C'!$C$35+'1.6 Finance'!$C$35+'1.7 Infrastructure'!$C$43+'1.8 Energy Solutions & B2B'!$C$39+'1.9 Commercial Fuels'!$C$43+'1.10 Z Retail'!$C$36+'1.11 TDD Cyber'!$C$30 -> 9.22
B45: Variance vs NZ budget ($m) | C45: =C42-C43-C44 -> 6.38
B46: Portfolio overheads and platform overheads sit inside the COE and portfolio allocations on 0.2 Data Config.

Sheet 2.6 Total Cost
B2: Total Cost - archetype model vs actual organisation
B4: Portfolio cost in one number - squads, strategic programs, leadership and overheads
B5: Portfolio | C5: Archetype cost ($m) | D5: Archetype squad FTE | E5: Actual Filled ($m) | F5: Filled FTE | G5: Actual Vacant ($m) | H5: Vacant FTE | I5: Actual Total ($m) | J5: Total FTE | K5: Over/(under) archetype ($m) | L5: FTE vs archetype
B6: ='1.1 Ampol Retail'!$B$2 -> Ampol Retail | C6: ='1.1 Ampol Retail'!$E$9 -> 10.3545 | D6: ='2.7 Squad Detail'!$G$22 -> 60.5 | E6: =(SUMIFS('Added data'!$AA:$AA,'Added data'!$AC:$AC,$B6,'Added data'!$AF:$AF,"Squad",'Added data'!$AG:$AG,"Filled")+SUMIFS('Added data'!$AA:$AA,'Added data'!$AC:$AC,$B6,'Added data'!$AF:$AF,"Strategic Program",'Added data'!$AG:$AG,"Filled")+SUMIFS('Added data'!$AA:$AA,'Added data'!$AC:$AC,$B6,'Added data'!$AF:$AF,"Leadership",'Added data'!$AG:$AG,"Filled"))/1000000 -> 8.5633248 | F6: =COUNTIFS(Squads!$N:$N,$B6,Squads!$Q:$Q,"Squad",Squads!$R:$R,"Filled")+COUNTIFS(Squads!$N:$N,$B6,Squads!$Q:$Q,"Strategic Program",Squads!$R:$R,"Filled")+COUNTIFS(Squads!$N:$N,$B6,Squads!$Q:$Q,"Leadership",Squads!$R:$R,"Filled") -> 52 | G6: =(SUMIFS('Added data'!$AA:$AA,'Added data'!$AC:$AC,$B6,'Added data'!$AF:$AF,"Squad",'Added data'!$AG:$AG,"Vacant")+SUMIFS('Added data'!$AA:$AA,'Added data'!$AC:$AC,$B6,'Added data'!$AF:$AF,"Strategic Program",'Added data'!$AG:$AG,"Vacant")+SUMIFS('Added data'!$AA:$AA,'Added data'!$AC:$AC,$B6,'Added data'!$AF:$AF,"Leadership",'Added data'!$AG:$AG,"Vacant"))/1000000 -> 4.0203139 | H6: =COUNTIFS(Squads!$N:$N,$B6,Squads!$Q:$Q,"Squad",Squads!$R:$R,"Vacant")+COUNTIFS(Squads!$N:$N,$B6,Squads!$Q:$Q,"Strategic Program",Squads!$R:$R,"Vacant")+COUNTIFS(Squads!$N:$N,$B6,Squads!$Q:$Q,"Leadership",Squads!$R:$R,"Vacant") -> 28 | I6: =E6+G6 -> 12.583639 | J6: =F6+H6 -> 80 | K6: =ROUND(I6-C6,6) -> 2.229139 | L6: =ROUND(J6-D6,1) -> 19.5
B7: ='1.2 Customer'!$B$2 -> Customer | C7: ='1.2 Customer'!$E$9 -> 14.9445 | D7: ='2.7 Squad Detail'!$G$36 -> 61 | E7: =(SUMIFS('Added data'!$AA:$AA,'Added data'!$AC:$AC,$B7,'Added data'!$AF:$AF,"Squad",'Added data'!$AG:$AG,"Filled")+SUMIFS('Added data'!$AA:$AA,'Added data'!$AC:$AC,$B7,'Added data'!$AF:$AF,"Strategic Program",'Added data'!$AG:$AG,"Filled")+SUMIFS('Added data'!$AA:$AA,'Added data'!$AC:$AC,$B7,'Added data'!$AF:$AF,"Leadership",'Added data'!$AG:$AG,"Filled"))/1000000 -> 13.37083 | F7: =COUNTIFS(Squads!$N:$N,$B7,Squads!$Q:$Q,"Squad",Squads!$R:$R,"Filled")+COUNTIFS(Squads!$N:$N,$B7,Squads!$Q:$Q,"Strategic Program",Squads!$R:$R,"Filled")+COUNTIFS(Squads!$N:$N,$B7,Squads!$Q:$Q,"Leadership",Squads!$R:$R,"Filled") -> 69 | G7: =(SUMIFS('Added data'!$AA:$AA,'Added data'!$AC:$AC,$B7,'Added data'!$AF:$AF,"Squad",'Added data'!$AG:$AG,"Vacant")+SUMIFS('Added data'!$AA:$AA,'Added data'!$AC:$AC,$B7,'Added data'!$AF:$AF,"Strategic Program",'Added data'!$AG:$AG,"Vacant")+SUMIFS('Added data'!$AA:$AA,'Added data'!$AC:$AC,$B7,'Added data'!$AF:$AF,"Leadership",'Added data'!$AG:$AG,"Vacant"))/1000000 -> 3.8347271 | H7: =COUNTIFS(Squads!$N:$N,$B7,Squads!$Q:$Q,"Squad",Squads!$R:$R,"Vacant")+COUNTIFS(Squads!$N:$N,$B7,Squads!$Q:$Q,"Strategic Program",Squads!$R:$R,"Vacant")+COUNTIFS(Squads!$N:$N,$B7,Squads!$Q:$Q,"Leadership",Squads!$R:$R,"Vacant") -> 19 | I7: =E7+G7 -> 17.205557 | J7: =F7+H7 -> 88 | K7: =ROUND(I7-C7,6) -> 2.261057 | L7: =ROUND(J7-D7,1) -> 27
B8: ='1.3 Enterprise Data'!$B$2 -> Enterprise Data | C8: ='1.3 Enterprise Data'!$E$9 -> 6.0145 | D8: ='2.7 Squad Detail'!$G$43 -> 33 | E8: =(SUMIFS('Added data'!$AA:$AA,'Added data'!$AC:$AC,$B8,'Added data'!$AF:$AF,"Squad",'Added data'!$AG:$AG,"Filled")+SUMIFS('Added data'!$AA:$AA,'Added data'!$AC:$AC,$B8,'Added data'!$AF:$AF,"Strategic Program",'Added data'!$AG:$AG,"Filled")+SUMIFS('Added data'!$AA:$AA,'Added data'!$AC:$AC,$B8,'Added data'!$AF:$AF,"Leadership",'Added data'!$AG:$AG,"Filled"))/1000000 -> 4.7635442 | F8: =COUNTIFS(Squads!$N:$N,$B8,Squads!$Q:$Q,"Squad",Squads!$R:$R,"Filled")+COUNTIFS(Squads!$N:$N,$B8,Squads!$Q:$Q,"Strategic Program",Squads!$R:$R,"Filled")+COUNTIFS(Squads!$N:$N,$B8,Squads!$Q:$Q,"Leadership",Squads!$R:$R,"Filled") -> 16 | G8: =(SUMIFS('Added data'!$AA:$AA,'Added data'!$AC:$AC,$B8,'Added data'!$AF:$AF,"Squad",'Added data'!$AG:$AG,"Vacant")+SUMIFS('Added data'!$AA:$AA,'Added data'!$AC:$AC,$B8,'Added data'!$AF:$AF,"Strategic Program",'Added data'!$AG:$AG,"Vacant")+SUMIFS('Added data'!$AA:$AA,'Added data'!$AC:$AC,$B8,'Added data'!$AF:$AF,"Leadership",'Added data'!$AG:$AG,"Vacant"))/1000000 -> 2.1641223 | H8: =COUNTIFS(Squads!$N:$N,$B8,Squads!$Q:$Q,"Squad",Squads!$R:$R,"Vacant")+COUNTIFS(Squads!$N:$N,$B8,Squads!$Q:$Q,"Strategic Program",Squads!$R:$R,"Vacant")+COUNTIFS(Squads!$N:$N,$B8,Squads!$Q:$Q,"Leadership",Squads!$R:$R,"Vacant") -> 14 | I8: =E8+G8 -> 6.9276665 | J8: =F8+H8 -> 30 | K8: =ROUND(I8-C8,6) -> 0.913166 | L8: =ROUND(J8-D8,1) -> -3
B9: ='1.4 TDD Group Functions'!$B$2 -> TDD Group Functions | C9: ='1.4 TDD Group Functions'!$E$9 -> 4.8145 | D9: ='2.7 Squad Detail'!$G$51 -> 26.5 | E9: =(SUMIFS('Added data'!$AA:$AA,'Added data'!$AC:$AC,$B9,'Added data'!$AF:$AF,"Squad",'Added data'!$AG:$AG,"Filled")+SUMIFS('Added data'!$AA:$AA,'Added data'!$AC:$AC,$B9,'Added data'!$AF:$AF,"Strategic Program",'Added data'!$AG:$AG,"Filled")+SUMIFS('Added data'!$AA:$AA,'Added data'!$AC:$AC,$B9,'Added data'!$AF:$AF,"Leadership",'Added data'!$AG:$AG,"Filled"))/1000000 -> 6.9850175 | F9: =COUNTIFS(Squads!$N:$N,$B9,Squads!$Q:$Q,"Squad",Squads!$R:$R,"Filled")+COUNTIFS(Squads!$N:$N,$B9,Squads!$Q:$Q,"Strategic Program",Squads!$R:$R,"Filled")+COUNTIFS(Squads!$N:$N,$B9,Squads!$Q:$Q,"Leadership",Squads!$R:$R,"Filled") -> 31 | G9: =(SUMIFS('Added data'!$AA:$AA,'Added data'!$AC:$AC,$B9,'Added data'!$AF:$AF,"Squad",'Added data'!$AG:$AG,"Vacant")+SUMIFS('Added data'!$AA:$AA,'Added data'!$AC:$AC,$B9,'Added data'!$AF:$AF,"Strategic Program",'Added data'!$AG:$AG,"Vacant")+SUMIFS('Added data'!$AA:$AA,'Added data'!$AC:$AC,$B9,'Added data'!$AF:$AF,"Leadership",'Added data'!$AG:$AG,"Vacant"))/1000000 -> 3.345912 | H9: =COUNTIFS(Squads!$N:$N,$B9,Squads!$Q:$Q,"Squad",Squads!$R:$R,"Vacant")+COUNTIFS(Squads!$N:$N,$B9,Squads!$Q:$Q,"Strategic Program",Squads!$R:$R,"Vacant")+COUNTIFS(Squads!$N:$N,$B9,Squads!$Q:$Q,"Leadership",Squads!$R:$R,"Vacant") -> 14 | I9: =E9+G9 -> 10.330929 | J9: =F9+H9 -> 45 | K9: =ROUND(I9-C9,6) -> 5.516429 | L9: =ROUND(J9-D9,1) -> 18.5
B10: ='1.5 P&C'!$B$2 -> P&C | C10: ='1.5 P&C'!$E$9 -> 2.7145 | D10: ='2.7 Squad Detail'!$G$57 -> 15 | E10: =(SUMIFS('Added data'!$AA:$AA,'Added data'!$AC:$AC,$B10,'Added data'!$AF:$AF,"Squad",'Added data'!$AG:$AG,"Filled")+SUMIFS('Added data'!$AA:$AA,'Added data'!$AC:$AC,$B10,'Added data'!$AF:$AF,"Strategic Program",'Added data'!$AG:$AG,"Filled")+SUMIFS('Added data'!$AA:$AA,'Added data'!$AC:$AC,$B10,'Added data'!$AF:$AF,"Leadership",'Added data'!$AG:$AG,"Filled"))/1000000 -> 2.070036 | F10: =COUNTIFS(Squads!$N:$N,$B10,Squads!$Q:$Q,"Squad",Squads!$R:$R,"Filled")+COUNTIFS(Squads!$N:$N,$B10,Squads!$Q:$Q,"Strategic Program",Squads!$R:$R,"Filled")+COUNTIFS(Squads!$N:$N,$B10,Squads!$Q:$Q,"Leadership",Squads!$R:$R,"Filled") -> 9 | G10: =(SUMIFS('Added data'!$AA:$AA,'Added data'!$AC:$AC,$B10,'Added data'!$AF:$AF,"Squad",'Added data'!$AG:$AG,"Vacant")+SUMIFS('Added data'!$AA:$AA,'Added data'!$AC:$AC,$B10,'Added data'!$AF:$AF,"Strategic Program",'Added data'!$AG:$AG,"Vacant")+SUMIFS('Added data'!$AA:$AA,'Added data'!$AC:$AC,$B10,'Added data'!$AF:$AF,"Leadership",'Added data'!$AG:$AG,"Vacant"))/1000000 -> 2.1144049 | H10: =COUNTIFS(Squads!$N:$N,$B10,Squads!$Q:$Q,"Squad",Squads!$R:$R,"Vacant")+COUNTIFS(Squads!$N:$N,$B10,Squads!$Q:$Q,"Strategic Program",Squads!$R:$R,"Vacant")+COUNTIFS(Squads!$N:$N,$B10,Squads!$Q:$Q,"Leadership",Squads!$R:$R,"Vacant") -> 9 | I10: =E10+G10 -> 4.1844409 | J10: =F10+H10 -> 18 | K10: =ROUND(I10-C10,6) -> 1.469941 | L10: =ROUND(J10-D10,1) -> 3
B11: ='1.6 Finance'!$B$2 -> Finance | C11: ='1.6 Finance'!$E$9 -> 3.4145 | D11: ='2.7 Squad Detail'!$G$63 -> 20 | E11: =(SUMIFS('Added data'!$AA:$AA,'Added data'!$AC:$AC,$B11,'Added data'!$AF:$AF,"Squad",'Added data'!$AG:$AG,"Filled")+SUMIFS('Added data'!$AA:$AA,'Added data'!$AC:$AC,$B11,'Added data'!$AF:$AF,"Strategic Program",'Added data'!$AG:$AG,"Filled")+SUMIFS('Added data'!$AA:$AA,'Added data'!$AC:$AC,$B11,'Added data'!$AF:$AF,"Leadership",'Added data'!$AG:$AG,"Filled"))/1000000 -> 1.6927347 | F11: =COUNTIFS(Squads!$N:$N,$B11,Squads!$Q:$Q,"Squad",Squads!$R:$R,"Filled")+COUNTIFS(Squads!$N:$N,$B11,Squads!$Q:$Q,"Strategic Program",Squads!$R:$R,"Filled")+COUNTIFS(Squads!$N:$N,$B11,Squads!$Q:$Q,"Leadership",Squads!$R:$R,"Filled") -> 8 | G11: =(SUMIFS('Added data'!$AA:$AA,'Added data'!$AC:$AC,$B11,'Added data'!$AF:$AF,"Squad",'Added data'!$AG:$AG,"Vacant")+SUMIFS('Added data'!$AA:$AA,'Added data'!$AC:$AC,$B11,'Added data'!$AF:$AF,"Strategic Program",'Added data'!$AG:$AG,"Vacant")+SUMIFS('Added data'!$AA:$AA,'Added data'!$AC:$AC,$B11,'Added data'!$AF:$AF,"Leadership",'Added data'!$AG:$AG,"Vacant"))/1000000 -> 1.7966814 | H11: =COUNTIFS(Squads!$N:$N,$B11,Squads!$Q:$Q,"Squad",Squads!$R:$R,"Vacant")+COUNTIFS(Squads!$N:$N,$B11,Squads!$Q:$Q,"Strategic Program",Squads!$R:$R,"Vacant")+COUNTIFS(Squads!$N:$N,$B11,Squads!$Q:$Q,"Leadership",Squads!$R:$R,"Vacant") -> 8 | I11: =E11+G11 -> 3.4894161 | J11: =F11+H11 -> 16 | K11: =ROUND(I11-C11,6) -> 0.074916 | L11: =ROUND(J11-D11,1) -> -4
B12: ='1.7 Infrastructure'!$B$2 -> Infrastructure | C12: ='1.7 Infrastructure'!$E$10 -> 5.2445 | D12: ='2.7 Squad Detail'!$G$71 -> 28 | E12: =(SUMIFS('Added data'!$AA:$AA,'Added data'!$AC:$AC,$B12,'Added data'!$AF:$AF,"Squad",'Added data'!$AG:$AG,"Filled")+SUMIFS('Added data'!$AA:$AA,'Added data'!$AC:$AC,$B12,'Added data'!$AF:$AF,"Strategic Program",'Added data'!$AG:$AG,"Filled")+SUMIFS('Added data'!$AA:$AA,'Added data'!$AC:$AC,$B12,'Added data'!$AF:$AF,"Leadership",'Added data'!$AG:$AG,"Filled"))/1000000 -> 5.1035768 | F12: =COUNTIFS(Squads!$N:$N,$B12,Squads!$Q:$Q,"Squad",Squads!$R:$R,"Filled")+COUNTIFS(Squads!$N:$N,$B12,Squads!$Q:$Q,"Strategic Program",Squads!$R:$R,"Filled")+COUNTIFS(Squads!$N:$N,$B12,Squads!$Q:$Q,"Leadership",Squads!$R:$R,"Filled") -> 21 | G12: =(SUMIFS('Added data'!$AA:$AA,'Added data'!$AC:$AC,$B12,'Added data'!$AF:$AF,"Squad",'Added data'!$AG:$AG,"Vacant")+SUMIFS('Added data'!$AA:$AA,'Added data'!$AC:$AC,$B12,'Added data'!$AF:$AF,"Strategic Program",'Added data'!$AG:$AG,"Vacant")+SUMIFS('Added data'!$AA:$AA,'Added data'!$AC:$AC,$B12,'Added data'!$AF:$AF,"Leadership",'Added data'!$AG:$AG,"Vacant"))/1000000 -> 2.4419335 | H12: =COUNTIFS(Squads!$N:$N,$B12,Squads!$Q:$Q,"Squad",Squads!$R:$R,"Vacant")+COUNTIFS(Squads!$N:$N,$B12,Squads!$Q:$Q,"Strategic Program",Squads!$R:$R,"Vacant")+COUNTIFS(Squads!$N:$N,$B12,Squads!$Q:$Q,"Leadership",Squads!$R:$R,"Vacant") -> 14 | I12: =E12+G12 -> 7.5455103 | J12: =F12+H12 -> 35 | K12: =ROUND(I12-C12,6) -> 2.30101 | L12: =ROUND(J12-D12,1) -> 7
B13: ='1.8 Energy Solutions & B2B'!$B$2 -> Energy Solutions & B2B | C13: ='1.8 Energy Solutions & B2B'!$E$9 -> 7.1795 | D13: ='2.7 Squad Detail'!$G$77 -> 32 | E13: =(SUMIFS('Added data'!$AA:$AA,'Added data'!$AC:$AC,$B13,'Added data'!$AF:$AF,"Squad",'Added data'!$AG:$AG,"Filled")+SUMIFS('Added data'!$AA:$AA,'Added data'!$AC:$AC,$B13,'Added data'!$AF:$AF,"Strategic Program",'Added data'!$AG:$AG,"Filled")+SUMIFS('Added data'!$AA:$AA,'Added data'!$AC:$AC,$B13,'Added data'!$AF:$AF,"Leadership",'Added data'!$AG:$AG,"Filled"))/1000000 -> 4.9610175 | F13: =COUNTIFS(Squads!$N:$N,$B13,Squads!$Q:$Q,"Squad",Squads!$R:$R,"Filled")+COUNTIFS(Squads!$N:$N,$B13,Squads!$Q:$Q,"Strategic Program",Squads!$R:$R,"Filled")+COUNTIFS(Squads!$N:$N,$B13,Squads!$Q:$Q,"Leadership",Squads!$R:$R,"Filled") -> 25 | G13: =(SUMIFS('Added data'!$AA:$AA,'Added data'!$AC:$AC,$B13,'Added data'!$AF:$AF,"Squad",'Added data'!$AG:$AG,"Vacant")+SUMIFS('Added data'!$AA:$AA,'Added data'!$AC:$AC,$B13,'Added data'!$AF:$AF,"Strategic Program",'Added data'!$AG:$AG,"Vacant")+SUMIFS('Added data'!$AA:$AA,'Added data'!$AC:$AC,$B13,'Added data'!$AF:$AF,"Leadership",'Added data'!$AG:$AG,"Vacant"))/1000000 -> 1.826412 | H13: =COUNTIFS(Squads!$N:$N,$B13,Squads!$Q:$Q,"Squad",Squads!$R:$R,"Vacant")+COUNTIFS(Squads!$N:$N,$B13,Squads!$Q:$Q,"Strategic Program",Squads!$R:$R,"Vacant")+COUNTIFS(Squads!$N:$N,$B13,Squads!$Q:$Q,"Leadership",Squads!$R:$R,"Vacant") -> 12 | I13: =E13+G13 -> 6.7874295 | J13: =F13+H13 -> 37 | K13: =ROUND(I13-C13,6) -> -0.39207 | L13: =ROUND(J13-D13,1) -> 5
B14: ='1.9 Commercial Fuels'!$B$2 -> Commercial Fuels | C14: ='1.9 Commercial Fuels'!$E$9 -> 7.1445 | D14: ='2.7 Squad Detail'!$G$85 -> 25.5 | E14: =(SUMIFS('Added data'!$AA:$AA,'Added data'!$AC:$AC,$B14,'Added data'!$AF:$AF,"Squad",'Added data'!$AG:$AG,"Filled")+SUMIFS('Added data'!$AA:$AA,'Added data'!$AC:$AC,$B14,'Added data'!$AF:$AF,"Strategic Program",'Added data'!$AG:$AG,"Filled")+SUMIFS('Added data'!$AA:$AA,'Added data'!$AC:$AC,$B14,'Added data'!$AF:$AF,"Leadership",'Added data'!$AG:$AG,"Filled"))/1000000 -> 8.4839027 | F14: =COUNTIFS(Squads!$N:$N,$B14,Squads!$Q:$Q,"Squad",Squads!$R:$R,"Filled")+COUNTIFS(Squads!$N:$N,$B14,Squads!$Q:$Q,"Strategic Program",Squads!$R:$R,"Filled")+COUNTIFS(Squads!$N:$N,$B14,Squads!$Q:$Q,"Leadership",Squads!$R:$R,"Filled") -> 32 | G14: =(SUMIFS('Added data'!$AA:$AA,'Added data'!$AC:$AC,$B14,'Added data'!$AF:$AF,"Squad",'Added data'!$AG:$AG,"Vacant")+SUMIFS('Added data'!$AA:$AA,'Added data'!$AC:$AC,$B14,'Added data'!$AF:$AF,"Strategic Program",'Added data'!$AG:$AG,"Vacant")+SUMIFS('Added data'!$AA:$AA,'Added data'!$AC:$AC,$B14,'Added data'!$AF:$AF,"Leadership",'Added data'!$AG:$AG,"Vacant"))/1000000 -> 1.713767 | H14: =COUNTIFS(Squads!$N:$N,$B14,Squads!$Q:$Q,"Squad",Squads!$R:$R,"Vacant")+COUNTIFS(Squads!$N:$N,$B14,Squads!$Q:$Q,"Strategic Program",Squads!$R:$R,"Vacant")+COUNTIFS(Squads!$N:$N,$B14,Squads!$Q:$Q,"Leadership",Squads!$R:$R,"Vacant") -> 8 | I14: =E14+G14 -> 10.19767 | J14: =F14+H14 -> 40 | K14: =ROUND(I14-C14,6) -> 3.05317 | L14: =ROUND(J14-D14,1) -> 14.5
B15: ='1.10 Z Retail'!$B$2 -> Z Retail | C15: ='1.10 Z Retail'!$E$9 -> 6.4795 | D15: ='2.7 Squad Detail'!$G$91 -> 27 | E15: =(SUMIFS('Added data'!$AA:$AA,'Added data'!$AC:$AC,$B15,'Added data'!$AF:$AF,"Squad",'Added data'!$AG:$AG,"Filled")+SUMIFS('Added data'!$AA:$AA,'Added data'!$AC:$AC,$B15,'Added data'!$AF:$AF,"Strategic Program",'Added data'!$AG:$AG,"Filled")+SUMIFS('Added data'!$AA:$AA,'Added data'!$AC:$AC,$B15,'Added data'!$AF:$AF,"Leadership",'Added data'!$AG:$AG,"Filled"))/1000000 -> 3.8550338 | F15: =COUNTIFS(Squads!$N:$N,$B15,Squads!$Q:$Q,"Squad",Squads!$R:$R,"Filled")+COUNTIFS(Squads!$N:$N,$B15,Squads!$Q:$Q,"Strategic Program",Squads!$R:$R,"Filled")+COUNTIFS(Squads!$N:$N,$B15,Squads!$Q:$Q,"Leadership",Squads!$R:$R,"Filled") -> 23 | G15: =(SUMIFS('Added data'!$AA:$AA,'Added data'!$AC:$AC,$B15,'Added data'!$AF:$AF,"Squad",'Added data'!$AG:$AG,"Vacant")+SUMIFS('Added data'!$AA:$AA,'Added data'!$AC:$AC,$B15,'Added data'!$AF:$AF,"Strategic Program",'Added data'!$AG:$AG,"Vacant")+SUMIFS('Added data'!$AA:$AA,'Added data'!$AC:$AC,$B15,'Added data'!$AF:$AF,"Leadership",'Added data'!$AG:$AG,"Vacant"))/1000000 -> 1.723885 | H15: =COUNTIFS(Squads!$N:$N,$B15,Squads!$Q:$Q,"Squad",Squads!$R:$R,"Vacant")+COUNTIFS(Squads!$N:$N,$B15,Squads!$Q:$Q,"Strategic Program",Squads!$R:$R,"Vacant")+COUNTIFS(Squads!$N:$N,$B15,Squads!$Q:$Q,"Leadership",Squads!$R:$R,"Vacant") -> 5 | I15: =E15+G15 -> 5.5789188 | J15: =F15+H15 -> 28 | K15: =ROUND(I15-C15,6) -> -0.900581 | L15: =ROUND(J15-D15,1) -> 1
B16: ='1.11 TDD Cyber'!$B$2 -> TDD Cyber | C16: ='1.11 TDD Cyber'!$E$9 -> 11.830489 | D16: ="-" -> - | E16: =(SUMIFS('Added data'!$AA:$AA,'Added data'!$AC:$AC,$B16,'Added data'!$AF:$AF,"Squad",'Added data'!$AG:$AG,"Filled")+SUMIFS('Added data'!$AA:$AA,'Added data'!$AC:$AC,$B16,'Added data'!$AF:$AF,"Strategic Program",'Added data'!$AG:$AG,"Filled")+SUMIFS('Added data'!$AA:$AA,'Added data'!$AC:$AC,$B16,'Added data'!$AF:$AF,"Leadership",'Added data'!$AG:$AG,"Filled"))/1000000 -> 9.4442338 | F16: =COUNTIFS(Squads!$N:$N,$B16,Squads!$Q:$Q,"Squad",Squads!$R:$R,"Filled")+COUNTIFS(Squads!$N:$N,$B16,Squads!$Q:$Q,"Strategic Program",Squads!$R:$R,"Filled")+COUNTIFS(Squads!$N:$N,$B16,Squads!$Q:$Q,"Leadership",Squads!$R:$R,"Filled") -> 40 | G16: =(SUMIFS('Added data'!$AA:$AA,'Added data'!$AC:$AC,$B16,'Added data'!$AF:$AF,"Squad",'Added data'!$AG:$AG,"Vacant")+SUMIFS('Added data'!$AA:$AA,'Added data'!$AC:$AC,$B16,'Added data'!$AF:$AF,"Strategic Program",'Added data'!$AG:$AG,"Vacant")+SUMIFS('Added data'!$AA:$AA,'Added data'!$AC:$AC,$B16,'Added data'!$AF:$AF,"Leadership",'Added data'!$AG:$AG,"Vacant"))/1000000 -> 1.4717552 | H16: =COUNTIFS(Squads!$N:$N,$B16,Squads!$Q:$Q,"Squad",Squads!$R:$R,"Vacant")+COUNTIFS(Squads!$N:$N,$B16,Squads!$Q:$Q,"Strategic Program",Squads!$R:$R,"Vacant")+COUNTIFS(Squads!$N:$N,$B16,Squads!$Q:$Q,"Leadership",Squads!$R:$R,"Vacant") -> 8 | I16: =E16+G16 -> 10.915989 | J16: =F16+H16 -> 48 | K16: =ROUND(I16-C16,6) -> -0.9145 | L16: ="-" -> -
B17: ='2.4 COE Summary'!$B$11 -> COE - Business Partnering | C17: ='2.1 BP&T'!$F$6 -> 3.2925626 | D17: ="-" -> - | E17: =SUMIFS('2.1 BP&T'!$J$21:$J$44,'2.1 BP&T'!$F$21:$F$44,"Filled",'2.1 BP&T'!$G$21:$G$44,'2.1 BP&T'!$B$6) -> 2.8530626 | F17: ="-" -> - | G17: =SUMIFS('2.1 BP&T'!$J$21:$J$44,'2.1 BP&T'!$F$21:$F$44,"Vacant",'2.1 BP&T'!$G$21:$G$44,'2.1 BP&T'!$B$6) -> 0.4395 | H17: ="-" -> - | I17: =E17+G17 -> 3.2925626 | J17: ="-" -> - | K17: =ROUND(I17-C17,6) -> 0 | L17: ="-" -> -
B18: ='2.4 COE Summary'!$B$10 -> COE - Transformation | C18: ='2.1 BP&T'!$F$7 -> 3.1079992 | D18: ="-" -> - | E18: =SUMIFS('2.1 BP&T'!$J$21:$J$44,'2.1 BP&T'!$F$21:$F$44,"Filled",'2.1 BP&T'!$G$21:$G$44,'2.1 BP&T'!$B$7) -> 1.1999852 | F18: ="-" -> - | G18: =SUMIFS('2.1 BP&T'!$J$21:$J$44,'2.1 BP&T'!$F$21:$F$44,"Vacant",'2.1 BP&T'!$G$21:$G$44,'2.1 BP&T'!$B$7) -> 1.908014 | H18: ="-" -> - | I18: =E18+G18 -> 3.1079992 | J18: ="-" -> - | K18: =ROUND(I18-C18,6) -> 0 | L18: ="-" -> -
B19: ='2.4 COE Summary'!$B$8 -> COE - Strategy Architecture | C19: ='2.2 SA&D'!$G$6 -> 4.320561 | D19: ="-" -> - | E19: =SUMIFS('2.2 SA&D'!$J$22:$J$50,'2.2 SA&D'!$F$22:$F$50,"Filled",'2.2 SA&D'!$G$22:$G$50,'2.2 SA&D'!$B$6) -> 1.7481038 | F19: ="-" -> - | G19: =SUMIFS('2.2 SA&D'!$J$22:$J$50,'2.2 SA&D'!$F$22:$F$50,"Vacant",'2.2 SA&D'!$G$22:$G$50,'2.2 SA&D'!$B$6) -> 2.5724572 | H19: ="-" -> - | I19: =E19+G19 -> 4.320561 | J19: ="-" -> - | K19: =ROUND(I19-C19,6) -> 0 | L19: ="-" -> -
B20: ='2.4 COE Summary'!$B$12 -> COE - Data | C20: ='2.2 SA&D'!$G$7 -> 2.2327366 | D20: ="-" -> - | E20: =SUMIFS('2.2 SA&D'!$J$22:$J$50,'2.2 SA&D'!$F$22:$F$50,"Filled",'2.2 SA&D'!$G$22:$G$50,'2.2 SA&D'!$B$7) -> 1.8431305 | F20: ="-" -> - | G20: =SUMIFS('2.2 SA&D'!$J$22:$J$50,'2.2 SA&D'!$F$22:$F$50,"Vacant",'2.2 SA&D'!$G$22:$G$50,'2.2 SA&D'!$B$7) -> 0.3896061 | H20: ="-" -> - | I20: =E20+G20 -> 2.2327366 | J20: ="-" -> - | K20: =ROUND(I20-C20,6) -> 0 | L20: ="-" -> -
B21: Central leadership (COE + unmapped) - funded by overheads | C21: =0 -> 0 | D21: ="-" -> - | E21: =(SUMIFS('Added data'!$AA:$AA,'Added data'!$AC:$AC,"COE",'Added data'!$AF:$AF,"Leadership",'Added data'!$AG:$AG,"Filled")+SUMIFS('Added data'!$AA:$AA,'Added data'!$AC:$AC,"Unmapped",'Added data'!$AF:$AF,"Leadership",'Added data'!$AG:$AG,"Filled"))/1000000 -> 0 | F21: =COUNTIFS(Squads!$N:$N,"COE",Squads!$Q:$Q,"Leadership",Squads!$R:$R,"Filled")+COUNTIFS(Squads!$N:$N,"Unmapped",Squads!$Q:$Q,"Leadership",Squads!$R:$R,"Filled") -> 3 | G21: =(SUMIFS('Added data'!$AA:$AA,'Added data'!$AC:$AC,"COE",'Added data'!$AF:$AF,"Leadership",'Added data'!$AG:$AG,"Vacant")+SUMIFS('Added data'!$AA:$AA,'Added data'!$AC:$AC,"Unmapped",'Added data'!$AF:$AF,"Leadership",'Added data'!$AG:$AG,"Vacant"))/1000000 -> 0.33497295 | H21: =COUNTIFS(Squads!$N:$N,"COE",Squads!$Q:$Q,"Leadership",Squads!$R:$R,"Vacant")+COUNTIFS(Squads!$N:$N,"Unmapped",Squads!$Q:$Q,"Leadership",Squads!$R:$R,"Vacant") -> 1 | I21: =E21+G21 -> 0.33497295 | J21: =F21+H21 -> 4 | K21: =ROUND(I21-C21,6) -> 0.334973 | L21: ="-" -> -
B22: Roles not mapped to any squad or COE | C22: =0 -> 0 | D22: ="-" -> - | E22: =(SUMIFS('Added data'!$AA:$AA,'Added data'!$AF:$AF,"Unmapped",'Added data'!$AG:$AG,"Filled"))/1000000 -> 7.8951125 | F22: =COUNTIFS(Squads!$Q:$Q,"Unmapped",Squads!$R:$R,"Filled") -> 11 | G22: =(SUMIFS('Added data'!$AA:$AA,'Added data'!$AF:$AF,"Unmapped",'Added data'!$AG:$AG,"Vacant"))/1000000 -> 1.2675959 | H22: =COUNTIFS(Squads!$Q:$Q,"Unmapped",Squads!$R:$R,"Vacant") -> 6 | I22: =E22+G22 -> 9.1627083 | J22: =F22+H22 -> 17 | K22: =ROUND(I22-C22,6) -> 9.162708 | L22: ="-" -> -
