Workbook

Sheet Exec Summary
B2: TDD operating model - executive summary
B4: The organisation today
B5: Roles in the ledger | C5: ='3.1 Cost Bridge'!$H$41 -> 525
B6: Filled | C6: ='3.1 Cost Bridge'!$I$41 -> 390
B7: Vacant | C7: ='3.1 Cost Bridge'!$J$41 -> 135
B8: Cost of the 525 roles in the ledger ($m) | C8: ='3.1 Cost Bridge'!$E$41 -> 115.283
B9: Of which filled roles ($m) | C9: =SUMIFS('REVIEW - Complete Role Mapping'!$AA$2:$AA$528,'REVIEW - Complete Role Mapping'!$AK$2:$AK$528,"Filled")/1000000 -> 86.74851
B10: Of which vacancies not yet filled ($m) | C10: =SUMIFS('REVIEW - Complete Role Mapping'!$AA$2:$AA$528,'REVIEW - Complete Role Mapping'!$AK$2:$AK$528,"Vacant")/1000000 -> 28.534492
B11: The 8 GMs, outside the ledger ($m) | C11: =N(Lists!$AG$12) -> 5.1
B12: Cost today including the GM layer ($m) | C12: ='3.1 Cost Bridge'!$E$43 -> 120.383
B14: Against the archetype
B15: Squads priced by an archetype - archetype cost ($m) | C15: ='3.1 Cost Bridge'!$D$17 -> 64.2
B16: Squads priced by an archetype - actual ($m) | C16: ='3.1 Cost Bridge'!$E$17 -> 63.980998
B17: Squads priced by an archetype - over/(under) ($m) | C17: ='3.1 Cost Bridge'!$F$17 -> -0.219002
B18: Directly funded programmes - over/(under) funded ($m) | C18: ='3.1 Cost Bridge'!$F$27 -> -0.165942
B19: COEs and EGI - over/(under) their 1.x planned spend ($m) | C19: ='3.1 Cost Bridge'!$F$34 -> -
B20: Overhead roles - not covered by the allowance ($m) | C20: ='3.1 Cost Bridge'!$F$35 -> 5.32923
B21: The 8 GMs - over/(under) their allowance ($m) | C21: ='3.1 Cost Bridge'!$F$42 -> 2.1
B22: Total over/(under) archetype, everything comparable ($m) | C22: ='3.1 Cost Bridge'!$F$36+'3.1 Cost Bridge'!$F$42 -> 7.044285
B23: Groups with no archetype and no funded figure ($m) | C23: ='3.1 Cost Bridge'!$E$40 -> 1.3049171
B25: The vacancy decision
B26: Vacant roles | C26: ='3.1 Cost Bridge'!$J$41 -> 135
B27: Vacancies set to hire | C27: =N('2.1 Ampol Retail'!$I$29)+N('2.2 Customer'!$I$27)+N('2.3 Enterprise Data'!$I$22)+N('2.4 TDD Group Functions'!$I$24)+N('2.5 P&C'!$I$22)+N('2.6 Finance'!$I$20)+N('2.7 Infrastructure'!$I$24)+N('2.8 Energy Solutions & B2B'!$I$23)+N('2.9 Commercial Fuels'!$I$23)+N('2.10 Z Retail'!$I$24)+N('2.11 COE Cyber'!$I$23)+N('2.12 COE BP&T'!$I$21)+N('2.13 COE SA&D'!$I$23)+N('2.14 EGI'!$I$19) -> 135
B28: Roles set to offshore | C28: =N('2.1 Ampol Retail'!$J$29)+N('2.2 Customer'!$J$27)+N('2.3 Enterprise Data'!$J$22)+N('2.4 TDD Group Functions'!$J$24)+N('2.5 P&C'!$J$22)+N('2.6 Finance'!$J$20)+N('2.7 Infrastructure'!$J$24)+N('2.8 Energy Solutions & B2B'!$J$23)+N('2.9 Commercial Fuels'!$J$23)+N('2.10 Z Retail'!$J$24)+N('2.11 COE Cyber'!$J$23)+N('2.12 COE BP&T'!$J$21)+N('2.13 COE SA&D'!$J$23)+N('2.14 EGI'!$J$19) -> 0
B29: Roles put on hold | C29: =N('2.1 Ampol Retail'!$K$29)+N('2.2 Customer'!$K$27)+N('2.3 Enterprise Data'!$K$22)+N('2.4 TDD Group Functions'!$K$24)+N('2.5 P&C'!$K$22)+N('2.6 Finance'!$K$20)+N('2.7 Infrastructure'!$K$24)+N('2.8 Energy Solutions & B2B'!$K$23)+N('2.9 Commercial Fuels'!$K$23)+N('2.10 Z Retail'!$K$24)+N('2.11 COE Cyber'!$K$23)+N('2.12 COE BP&T'!$K$21)+N('2.13 COE SA&D'!$K$23)+N('2.14 EGI'!$K$19) -> 0
B30: Roles after the decisions set today | C30: ='3.1 Cost Bridge'!$K$41 -> 525
B31: Cost after the decisions set today ($m) | C31: ='3.1 Cost Bridge'!$G$41 -> 115.283
B32: Impact of those decisions ($m) | C32: ='3.1 Cost Bridge'!$G$41-'3.1 Cost Bridge'!$E$41 -> 0
B34: Portfolio drill-down
B35: Pick a portfolio | C35: Ampol Retail
B36: Roles | C36: =ROUND(SUMIFS('3.3 Squad Detail'!$H$6:$H$109,'3.3 Squad Detail'!$B$6:$B$109,$C$35),6) -> 70
B37: Filled | C37: =ROUND(SUMIFS('3.3 Squad Detail'!$I$6:$I$109,'3.3 Squad Detail'!$B$6:$B$109,$C$35),6) -> 48
B38: Vacant | C38: =ROUND(SUMIFS('3.3 Squad Detail'!$J$6:$J$109,'3.3 Squad Detail'!$B$6:$B$109,$C$35),6) -> 22
B39: Roles after decisions | C39: =ROUND(SUMIFS('3.3 Squad Detail'!$K$6:$K$109,'3.3 Squad Detail'!$B$6:$B$109,$C$35),6) -> 70
B40: Actual cost ($m) | C40: =ROUND(SUMIFS('3.3 Squad Detail'!$M$6:$M$109,'3.3 Squad Detail'!$B$6:$B$109,$C$35),6) -> 14.005227
B41: Of which overhead roles ($m) | C41: =ROUND(SUMIFS('3.3 Squad Detail'!$M$6:$M$109,'3.3 Squad Detail'!$B$6:$B$109,$C$35,'3.3 Squad Detail'!$C$6:$C$109,"Overhead"),6) -> 1.255616
B42: Squads priced by an archetype - over/(under) archetype ($m) | C42: =ROUND(SUMIFS('3.3 Squad Detail'!$N$6:$N$109,'3.3 Squad Detail'!$B$6:$B$109,$C$35,'3.3 Squad Detail'!$C$6:$C$109,"Archetype"),6) -> -0.766475
B43: Directly funded programmes - over/(under) funded ($m) | C43: =ROUND(SUMIFS('3.3 Squad Detail'!$N$6:$N$109,'3.3 Squad Detail'!$B$6:$B$109,$C$35,'3.3 Squad Detail'!$C$6:$C$109,"Directly funded"),6) -> 0.412299
B44: Cost after vacancy decisions ($m) | C44: =ROUND(SUMIFS('3.3 Squad Detail'!$O$6:$O$109,'3.3 Squad Detail'!$B$6:$B$109,$C$35),6) -> 14.005227

Sheet - INPUTS -
B2: INPUTS >>>

Sheet 0.1 Budget Table (Fin)
B3: BUSINESS | C3: EGM Sponsor | D3: GM Sponsor | E3: Domain Architect | F3: HO Technology | G3: Lights-on | M3: Depreciation | N3: Initiatives | O3: Sig Items | P3: Capex | Q3: Total Budget | S3: Existing | T3: Aligned Delivery | U3: Aligned COE's | V3: Total Budget
B4: SEGMENT | G4: People | H4: HW | I4: SW | J4: Network | K4: Vendor | L4: Sub-Total | Q4: FY2026 | V4: FY2026
B5: TDD Corporate (1) | C5: Brad Blyth | G5: 35.2 | H5: 2.9 | I5: 25.6 | J5: 2.1 | K5: 13.1 | L5: =SUM(G5:K5) -> 78.9 | M5: 5.8 | N5: 3 | O5: 20.2 | P5: 4.9 | Q5: =SUM(L5:P5) -> 112.8 | U5: =SUM(W25:W29) -> 91.6 | V5: =SUM(S5:U5) -> 91.6
B6: Z-Energy (2) | C6: Lindis Jones | D6: Vance Anderson | G6: 17.6 | H6: 19.8 | I6: 11.6 | J6: 0.6 | K6: 2.6 | L6: =SUM(G6:K6) -> 52.2 | M6: 11.3 | N6: 1.4 | O6: - | P6: 11.7 | Q6: =SUM(L6:P6) -> 76.6 | S6: =Q6 -> 76.6 | V6: =SUM(S6:U6) -> 76.6
B7: EnergySolutions | C7: Brent Merrick | D7: Roanne Steele | G7: 1 | H7: 1.5 | I7: 1.4 | L7: =SUM(G7:K7) -> 3.9 | N7: 1 | P7: 2.3 | Q7: =SUM(L7:P7) -> 7.2 | S7: =Q7 -> 7.2 | V7: =SUM(S7:U7) -> 7.2 | Y7: =SUM(L9,N9,O9,P9) -> 33.8
B8: Commercial Fuels | C8: Brent Merrick | D8: Roanne Steele | H8: 2.5 | I8: 9.4 | J8: 1.5 | L8: =SUM(G8:K8) -> 13.4 | N8: 6.1 | O8: 14.2 | P8: 6.8 | Q8: =SUM(L8:P8) -> 40.5 | S8: =Q8 -> 40.5 | T8: =S19 -> 1.2 | V8: =SUM(S8:U8) -> 41.7
B9: Retail | C9: Kate Thomson | D9: Roanne Steele | H9: 5.3 | I9: 6.4 | J9: 2.2 | L9: =SUM(G9:K9) -> 13.9 | N9: 1.3 | O9: 6.8 | P9: 11.8 | Q9: =SUM(L9:P9) -> 33.8 | S9: =Q9 -> 33.8 | T9: =S20 -> 5.2 | V9: =SUM(S9:U9) -> 39
B10: Infrastructure | C10: Michelle Bardy | D10: Roanne Steele | H10: 1.9 | I10: 2 | L10: =SUM(G10:K10) -> 3.9 | N10: 0.4 | P10: 5 | Q10: =SUM(L10:P10) -> 9.3 | S10: =Q10 -> 9.3 | T10: =S21 -> 2.2 | V10: =SUM(S10:U10) -> 11.5
B11: Corporate Finance | C11: Greg Barnes | D11: Emily Mogic | H11: 0.5 | I11: 2.1 | L11: =SUM(G11:K11) -> 2.6 | N11: 0.9 | Q11: =SUM(L11:P11) -> 3.5 | S11: =Q11 -> 3.5 | T11: =S22 -> 9 | V11: =SUM(S11:U11) -> 12.5
B12: P&C | C12: Meaghan Davis | D12: Emily Mogic | H12: 0.3 | I12: 1.8 | L12: =SUM(G12:K12) -> 2.1 | N12: 2 | O12: 1.4 | P12: 0.3 | Q12: =SUM(L12:P12) -> 5.8 | S12: =Q12 -> 5.8 | T12: =S23 -> 0 | V12: =SUM(S12:U12) -> 5.8
B13: Customer | C13: Kate Thomson | D13: Vance Anderson | H13: 0.1 | I13: 1.6 | L13: =SUM(G13:K13) -> 1.7 | O13: 5 | P13: 5 | Q13: =SUM(L13:P13) -> 11.7 | S13: =Q13 -> 11.7 | T13: =S24 -> 3.7 | V13: =SUM(S13:U13) -> 15.4
B14: Total Technology | G14: =SUM(G5:G13) -> 53.8 | H14: =SUM(H5:H13) -> 34.8 | I14: =SUM(I5:I13) -> 61.9 | J14: =SUM(J5:J13) -> 6.4 | K14: =SUM(K5:K13) -> 15.7 | L14: =SUM(L5:L13) -> 172.6 | M14: =SUM(M5:M13) -> 17.1 | N14: =SUM(N5:N13) -> 16.1 | ... Q14: =SUM(Q5:Q13) -> 301.2 | S14: =SUM(S6:S13) -> 188.4 | T14: =SUM(T8:T13) -> 21.3 | U14: =U5 -> 91.6 | V14: =SUM(V5:V13) -> 301.3
B17: BUSINESS SEGMENT | E17: EGM Sponsor | F17: GM Sponsor | G17: Domain Architect | H17: HO Technology | I17: Lights-on | O17: Depreciation | P17: Initiatives | Q17: Sig Items | R17: Capex | S17: Total Budget | U17: Existing | V17: Aligned Delivery | W17: Aligned | X17: Total Budget
I18: People | J18: HW | K18: SW | L18: Network | M18: Vendor | N18: Sub-Total | S18: FY2026 | W18: COE's | X18: FY2026
D19: Commercial Fuels | I19: 1.2 | J19: 0 | K19: 0 | L19: - | M19: - | N19: =SUM(I19:M19) -> 1.2 | O19: - | S19: =SUM(N19:R19) -> 1.2 | X19: -
D20: Retail | I20: 3.4 | J20: 0.2 | K20: 0.9 | L20: - | M20: 0.7 | N20: =SUM(I20:M20) -> 5.2 | O20: - | S20: =SUM(N20:R20) -> 5.2 | X20: -
D21: Infrastructure | I21: 2 | J21: - | K21: 0.2 | L21: - | M21: - | N21: =SUM(I21:M21) -> 2.2 | O21: - | S21: =SUM(N21:R21) -> 2.2 | X21: -
D22: Corporate Finance | I22: 1.3 | J22: - | K22: 4.2 | L22: - | M22: 3.5 | N22: =SUM(I22:M22) -> 9 | O22: - | S22: =SUM(N22:R22) -> 9 | X22: -
D23: P&C | I23: 0 | J23: - | K23: - | L23: - | M23: - | N23: =SUM(I23:M23) -> 0 | O23: - | S23: =SUM(N23:R23) -> 0 | X23: -
D24: Customer | I24: 1.2 | J24: - | K24: 0.6 | L24: 0 | M24: 1 | N24: =SUM(I24:M24) -> 2.8 | O24: 0.9 | S24: =SUM(N24:R24) -> 3.7 | X24: -
D25: TDD | F25: Emily Mogic | I25: 4.5 | J25: 2.5 | K25: 14.5 | L25: 0 | M25: 0.8 | N25: =SUM(I25:M25) -> 22.3 | O25: 4.9 | S25: =SUM(N25:R25) -> 27.2 | W25: =S25 -> 27.2 | X25: =W25 -> 27.2
D26: TDDEGM | F26: Brad Blyth | I26: 6.5 | J26: - | K26: - | L26: - | M26: 3.6 | N26: =SUM(I26:M26) -> 10.1 | O26: - | P26: 3 | Q26: 20.2 | R26: 4.9 | S26: =SUM(N26:R26) -> 38.2 | W26: =S26 -> 38.2 | X26: =W26 -> 38.2
D27: Strategy, Architecture and Data | F27: Matt Ashley | I27: 5.3 | J27: - | K27: 1 | L27: - | M27: 0.6 | N27: =SUM(I27:M27) -> 6.9 | O27: - | S27: =SUM(N27:R27) -> 6.9 | W27: =S27 -> 6.9 | X27: =W27 -> 6.9
D28: Cyber Risk and Operations | F28: Frances Bouzo | I28: 7.6 | J28: 0.2 | K28: 4.3 | L28: 2 | M28: 2.9 | N28: =SUM(I28:M28) -> 17 | O28: - | S28: =SUM(N28:R28) -> 17 | W28: =S28 -> 17 | X28: =W28 -> 17
D29: Business Partnering and Governance | F29: Michael Schofield | I29: 2.3 | J29: - | K29: - | L29: - | M29: - | N29: =SUM(I29:M29) -> 2.3 | O29: - | S29: =SUM(N29:R29) -> 2.3 | W29: =S29 -> 2.3 | X29: =W29 -> 2.3
B30: TDD Corporate (1) | E30: Brad Blyth | I30: =G5 -> 35.2 | J30: =H5 -> 2.9 | K30: =I5 -> 25.6 | L30: =J5 -> 2.1 | M30: =K5 -> 13.1 | N30: =L5 -> 78.9 | O30: =M5 -> 5.8 | P30: =N5 -> 3 | ... S30: =Q5 -> 112.8 | W30: =U5 -> 91.6 | X30: =W30 -> 91.6
C31: Z-Energy (Direct TDD) | I31: 17.6 | J31: 12.1 | K31: 6.3 | L31: 0.6 | M31: 2.6 | N31: 39.3 | O31: 11.3 | P31: 1.4 | R31: 11.7 | S31: 63.7 | X31: -
C32: Z-Energy (Other IT Spend for Supplies, Customer) | J32: 7.6 | K32: 5.3 | N32: 13 | S32: 13 | X32: -
B33: Z-Energy (2) | E33: Lindis Jones | F33: Vance Anderson | I33: =G6 -> 17.6 | J33: =H6 -> 19.8 | K33: =I6 -> 11.6 | L33: =J6 -> 0.6 | M33: =K6 -> 2.6 | N33: =L6 -> 52.2 | O33: =M6 -> 11.3 | P33: =N6 -> 1.4 | ... S33: =Q6 -> 76.6 | U33: =S6 -> 76.6 | X33: =U33 -> 76.6

Sheet 0.2 Data Config
B2: Data Config
B4: TDD Budget Allocation ($m) | I4: Portfolio Overhead (roles, $m)
B5: Portfolio | C5: AU | D5: NZ | E5: Total | F5: Actual cost ($m) | G5: Over/(under) budget ($m) | I5: Role | J5: Cost ($m) | K5: Allocation % | L5: Portfolio cost ($m)
B6: COE - Strategy Architecture | C6: 1.5 | D6: 0.5 | E6: =C6+D6 -> 2 | F6: =SUMIFS('REVIEW - Complete Role Mapping'!$AA$2:$AA$528,'REVIEW - Complete Role Mapping'!$AJ$2:$AJ$528,"COE SA&D")/1000000 -> 6.5294941 | G6: =$F6-$E6 -> 4.5294941 | I6: Head of Tech | J6: 0.275 | K6: 0.5 | L6: =J6*K6 -> 0.1375
B7: COE - Cyber, Risk & Service Ops (see 1.13 Cyber Roles) | C7: 0 | D7: 0 | E7: =C7+D7 -> 0 | F7: 0 | G7: =$F7-$E7 -> 0 | I7: Business Partner | J7: 0.44 | K7: 0.5 | L7: =J7*K7 -> 0.22
B8: COE - Transformation | C8: 1.5 | D8: 0.5 | E8: =C8+D8 -> 2 | F8: =SUMIFS('REVIEW - Complete Role Mapping'!$AA$2:$AA$528,'REVIEW - Complete Role Mapping'!$AJ$2:$AJ$528,"COE BP&T")/1000000 -> 6.4005618 | G8: =$F8-$E8 -> 4.4005618 | I8: Domain Architect | J8: 0.28 | K8: 0.5 | L8: =J8*K8 -> 0.14
B9: COE - Business Partnering | C9: 1.5 | D9: 0.5 | E9: =C9+D9 -> 2 | F9: 0 | G9: =$F9-$E9 -> -2 | I9: Leadership Overhead | J9: 1 | K9: 0.3 | L9: =J9*K9 -> 0.3
B10: COE - Data | C10: 1.5 | D10: 0.5 | E10: =C10+D10 -> 2 | F10: 0 | G10: =$F10-$E10 -> -2 | I10: Portfolio overhead subtotal | L10: =SUM(L6:L9) -> 0.7975
B11: Ampol Retail | C11: 5.5 | D11: 0 | E11: =C11+D11 -> 5.5 | F11: =SUMIFS('REVIEW - Complete Role Mapping'!$AA$2:$AA$528,'REVIEW - Complete Role Mapping'!$AJ$2:$AJ$528,"Ampol Retail")/1000000 -> 14.005227 | G11: =$F11-$E11 -> 8.5052275
B12: Z Retail | C12: 0 | D12: 6.5 | E12: =C12+D12 -> 6.5 | F12: =SUMIFS('REVIEW - Complete Role Mapping'!$AA$2:$AA$528,'REVIEW - Complete Role Mapping'!$AJ$2:$AJ$528,"Z Retail")/1000000 -> 7.3372944 | G12: =$F12-$E12 -> 0.83729435 | I12: Platform Overhead (roles, $m)
B13: Ampol Customer | C13: 2.5 | D13: 0 | E13: =C13+D13 -> 2.5 | F13: =SUMIFS('REVIEW - Complete Role Mapping'!$AA$2:$AA$528,'REVIEW - Complete Role Mapping'!$AJ$2:$AJ$528,"Customer")/1000000 -> 17.126867 | G13: =$F13-$E13 -> 14.626867 | I13: Role | J13: Cost ($m) | K13: Alloc % | L13: Platform cost ($m)
B14: Z Customer | C14: 0 | D14: 4 | E14: =C14+D14 -> 4 | F14: 0 | I14: Delivery Manager | J14: 0.28 | K14: 0.3 | L14: =J14*K14 -> 0.084
B15: Commercial Fuels | C15: 2.5 | D15: 0 | E15: =C15+D15 -> 2.5 | F15: =SUMIFS('REVIEW - Complete Role Mapping'!$AA$2:$AA$528,'REVIEW - Complete Role Mapping'!$AJ$2:$AJ$528,"Commercial Fuels")/1000000 -> 10.19767 | G15: =$F15-$E15 -> 7.6976697 | I15: Tech Manager | J15: 0.27 | K15: 0.3 | L15: =J15*K15 -> 0.081
B16: Energy Solutions & B2B | C16: 2.5 | D16: 0 | E16: =C16+D16 -> 2.5 | F16: =SUMIFS('REVIEW - Complete Role Mapping'!$AA$2:$AA$528,'REVIEW - Complete Role Mapping'!$AJ$2:$AJ$528,"Energy Solutions & B2B")/1000000 -> 6.4478163 | G16: =$F16-$E16 -> 3.9478163 | I16: Platform overhead subtotal (per platform) | L16: =SUM(L14:L15) -> 0.165
B17: Infrastructure | C17: 2.5 | D17: 0 | E17: =C17+D17 -> 2.5 | F17: =SUMIFS('REVIEW - Complete Role Mapping'!$AA$2:$AA$528,'REVIEW - Complete Role Mapping'!$AJ$2:$AJ$528,"Infrastructure")/1000000 -> 7.7483635 | G17: =$F17-$E17 -> 5.2483635
B18: P&C | C18: 1 | D18: 1 | E18: =C18+D18 -> 2 | F18: =SUMIFS('REVIEW - Complete Role Mapping'!$AA$2:$AA$528,'REVIEW - Complete Role Mapping'!$AJ$2:$AJ$528,"P&C")/1000000 -> 4.1844409 | G18: =$F18-$E18 -> 2.1844409
B19: Finance | C19: 1 | D19: 1 | E19: =C19+D19 -> 2 | F19: =SUMIFS('REVIEW - Complete Role Mapping'!$AA$2:$AA$528,'REVIEW - Complete Role Mapping'!$AJ$2:$AJ$528,"Finance")/1000000 -> 3.8446161 | G19: =$F19-$E19 -> 1.8446161
B20: Legal | C20: 0 | D20: 0 | E20: =C20+D20 -> 0 | F20: 0 | G20: =$F20-$E20 -> 0
B21: TDD | C21: 4.5 | D21: 1 | E21: =C21+D21 -> 5.5 | F21: =SUMIFS('REVIEW - Complete Role Mapping'!$AA$2:$AA$528,'REVIEW - Complete Role Mapping'!$AJ$2:$AJ$528,"TDD Group Functions")/1000000 -> 10.200969 | G21: =$F21-$E21 -> 4.7009695
B22: TDD Data | C22: 2.5 | D22: 1 | E22: =C22+D22 -> 3.5 | F22: =SUMIFS('REVIEW - Complete Role Mapping'!$AA$2:$AA$528,'REVIEW - Complete Role Mapping'!$AJ$2:$AJ$528,"Enterprise Data")/1000000 -> 6.4184038 | G22: =$F22-$E22 -> 2.9184038
B23: TDD Cyber | C23: 2.5 | D23: 1 | E23: =C23+D23 -> 3.5 | F23: =SUMIFS('REVIEW - Complete Role Mapping'!$AA$2:$AA$528,'REVIEW - Complete Role Mapping'!$AJ$2:$AJ$528,"COE Cyber")/1000000 -> 9.8978583 | G23: =$F23-$E23 -> 6.3978583
B25: EGI | C25: 0 | D25: 0 | E25: =C25+D25 -> 0 | F25: =SUMIFS('REVIEW - Complete Role Mapping'!$AA$2:$AA$528,'REVIEW - Complete Role Mapping'!$AJ$2:$AJ$528,"EGI")/1000000 -> 4.9434194 | G25: =$F25-$E25 -> 4.9434194
B26: Total | C26: =SUM(C6:C25) -> 33 | D26: =SUM(D6:D25) -> 17.5 | E26: =SUM(E6:E25) -> 50.5 | F26: =SUM(F6:F25) -> 115.283 | G26: =$F26-$E26 -> 64.783002
B27: Budget | C27: ='0.1 Budget Table (Fin)'!G5+'0.1 Budget Table (Fin)'!G7 -> 36.2 | D27: ='0.1 Budget Table (Fin)'!G6 -> 17.6 | E27: ='0.1 Budget Table (Fin)'!G14 -> 53.8
B28: Variance | C28: =C27-C26 -> 3.2 | D28: =D27-D26 -> 0.1 | E28: =E27-E26 -> 3.3

Sheet 0.3 Squad Archetypes
B2: Squad Archetypes - the cost library | C2: Squad Cost Lookup
A4: Key | C4: Squad Type | D4: Size | E4: Archetype | F4: # of roles | G4: Onshore Cost ($m) | H4: Offshore Cost ($m) | I4: Use When | K4: Offshore rate
A5: =$C5&"|"&$D5 -> Engineering|S | C5: Engineering | D5: S | E5: Lean build squad | F5: 4.5 | G5: 0.8 | H5: =G5*$K$5 -> 0.32 | I5: Simple platforms, incremental changes | K5: 0.4
A6: =$C6&"|"&$D6 -> Engineering|M | C6: Engineering | D6: M | E6: Standard Engineering Squad | F6: 9 | G6: 2 | H6: =G6*$K$5 -> 0.8 | I6: Medium complexity platforms
A7: =$C7&"|"&$D7 -> Engineering|L | C7: Engineering | D7: L | E7: High-scale squad | F7: 12 | G7: 2.7 | H7: =G7*$K$5 -> 1.08 | I7: Scalable platforms, high volume output
A8: =$C8&"|"&$D8 -> Configuration / Integration|XS | C8: Configuration / Integration | D8: XS | E8: MS Squad | F8: 1 | G8: 0.4 | H8: =G8*$K$5 -> 0.16 | I8: Work managed by a vendor
A9: =$C9&"|"&$D9 -> Configuration / Integration|S | C9: Configuration / Integration | D9: S | E9: Simple Configuration Squad | F9: 6 | G9: 1.4 | H9: =G9*$K$5 -> 0.56 | I9: Simple configuration, limited integration
A10: =$C10&"|"&$D10 -> Configuration / Integration|M | C10: Configuration / Integration | D10: M | E10: Standard Configuration Squad | F10: 9 | G10: 2.1 | H10: =G10*$K$5 -> 0.84 | I10: Standard configuration, medium complexity
A11: =$C11&"|"&$D11 -> Configuration / Integration|L | C11: Configuration / Integration | D11: L | E11: Complex Integration Squad | F11: 14 | G11: 3.2 | H11: =G11*$K$5 -> 1.28 | I11: Complex config or custom build, high integration
A12: =$C12&"|"&$D12 -> Product|S | C12: Product | D12: S | E12: Lean Product Squad | F12: 5.5 | G12: 1.3 | H12: =G12*$K$5 -> 0.52 | I12: Early stage product testing or low complexity
A13: =$C13&"|"&$D13 -> Product|M | C13: Product | D13: M | E13: Balanced Product Squad | F13: 8.5 | G13: 1.9 | H13: =G13*$K$5 -> 0.76 | I13: Ongoing product development, moderate complexity
A14: =$C14&"|"&$D14 -> Product|L | C14: Product | D14: L | E14: Scaled Product Squad | F14: 12 | G14: 2.8 | H14: =G14*$K$5 -> 1.12 | I14: Mature product
A15: =$C15&"|"&$D15 -> Operations|S | C15: Operations | D15: S | E15: Lean operations squad | F15: 4 | G15: 0.8 | H15: =G15*$K$5 -> 0.32 | I15: Low change, stable platforms
A16: =$C16&"|"&$D16 -> Operations|M | C16: Operations | D16: M | E16: Balanced operations squad | F16: 6 | G16: 1.4 | H16: =G16*$K$5 -> 0.56 | I16: Moderate support plus improvements
A17: =$C17&"|"&$D17 -> Operations|L | C17: Operations | D17: L | E17: High demand operations squad | F17: 10 | G17: 2.3 | H17: =G17*$K$5 -> 0.92 | I17: High ticket volume, critical systems
... A23: =$C23&"|"&$D23 -> Build and Run|L | C23: Build and Run | D23: L | E23: Scaled build and run squad | F23: 13 | G23: 2.8 | H23: =G23*$K$5 -> 1.12 | I23: High traffic or business critical, 24/7
C24: Exceptions (will need to incl. rules) | E24: TBC | I24: TBC
C27: Exception for ES EVCI - 6 FTE vs 4.5 FTE
C29: Exception for TDD DevOps - no BA, DL 6 FTE vs 4.5 FTE

Sheet 0.4 Presentation Pack
B3: BUSINESS SEGMENTS | C3: TDD GM | D3: TOTAL YTD (Jun-2026) | I3: OPEX: LIGHTS ON + INITIATIVES (YTD) | N3: OPEX: LIGHTS ON (YTD) | S3: OPEX: INITIATIVES (YTD) | X3: OPEX: DEPRECIATION (YTD) | AC3: SIGNIFICANT ITEMS (YTD) | AH3: CAPEX (YTD) | AN3: FY2026
D4: A | E4: B | F4: V | G4: V % | H4: Trend | I4: A | J4: B | K4: V | L4: V % | M4: Trend | N4: A | O4: B | P4: V | R4: Trend | S4: A | T4: B | U4: V | V4: V % | W4: Trend | X4: A | Y4: B | Z4: V | AA4: V % | AB4: Trend | AC4: A | AD4: B | AE4: V | AF4: V % | AG4: Trend | AH4: A | AI4: B | AJ4: V | AK4: V % | AL4: Trend | AN4: F | AO4: B | AP4: V | AR4: Trend
A5: TDD (Corporate)1 | B5: TDD (Corporate)1 | C5: Brad Blyth Greg Cassis | D5: =I5+AC5+AH5+X5 -> 53.575006 | E5: =J5+AD5+AI5+Y5 -> 56.158125 | F5: =E5-D5 -> 2.5831189 | G5: =IFERROR(F5/E5,"-") -> 0.045997243 | H5: G | I5: 41.773797 | J5: 41.933694 | K5: =J5-I5 -> 0.15989672 | L5: =IFERROR(K5/J5,"-") -> 0.0038130846 | M5: G | N5: =I5-S5 -> 40.972956 | O5: =J5-T5 -> 40.433694 | P5: =O5-N5 -> -0.53926205 | Q5: =IFERROR(P5/O5,"-") -> -0.013336947 | R5: A | S5: 0.80084123 | T5: 1.5 | U5: =T5-S5 -> 0.69915877 | V5: =IFERROR(U5/T5,"-") -> 0.46610585 | W5: G | X5: 2.7852211 | Y5: 2.9338979 | Z5: =Y5-X5 -> 0.14867679 | AA5: =IFERROR(Z5/Y5,"-") -> 0.050675516 | AB5: G | AC5: 8.8400082 | AD5: 9.2622 | AE5: =AD5-AC5 -> 0.4221918 | AF5: =IFERROR(AE5/AD5,"-") -> 0.045582237 | AG5: G | AH5: 0.17597979 | AI5: 2.0283334 | AJ5: =AI5-AH5 -> 1.8523536 | AK5: =IFERROR(AJ5/AI5,"-") -> 0.91323922 | AL5: G | AN5: =I21+AC21+AH21+X21 -> 117.95714 | AO5: =J21+AD21+AI21+Y21 -> 112.75951 | AP5: =AO5-AN5 -> -5.1976273 | AQ5: =IFERROR(AP5/AO5,"-") -> -0.046094801 | AR5: A
A6: Z-Energy | B6: Z- Energy | C6: Vance Anderson Harley Giles | D6: =I6+AC6+AH6+X6 -> 35.257858 | E6: =J6+AD6+AI6+Y6 -> 38.25416 | F6: =E6-D6 -> 2.9963016 | G6: =IFERROR(F6/E6,"-") -> 0.078326164 | H6: G | I6: 26.455513 | J6: 26.80099 | K6: =J6-I6 -> 0.34547723 | L6: =IFERROR(K6/J6,"-") -> 0.012890465 | M6: G | N6: =I6-S6 -> 26.455513 | O6: =J6-T6 -> 26.07787 | P6: =O6-N6 -> -0.37764277 | Q6: =IFERROR(P6/O6,"-") -> -0.01448135 | R6: A | S6: 0 | T6: 0.72312 | U6: =T6-S6 -> 0.72312 | V6: =IFERROR(U6/T6,"-") -> 1 | W6: G | X6: 4.8357552 | Y6: 5.1436863 | Z6: =Y6-X6 -> 0.30793102 | AA6: =IFERROR(Z6/Y6,"-") -> 0.059865825 | AB6: G | AC6: 0 | AD6: 0 | AE6: =AD6-AC6 -> 0 | AF6: =IFERROR(AE6/AD6,"-") -> - | AH6: 3.9665899 | AI6: 6.3094833 | AJ6: =AI6-AH6 -> 2.3428933 | AK6: =IFERROR(AJ6/AI6,"-") -> 0.37132888 | AL6: G | AN6: =I22+AC22+AH22+X22 -> 73.108391 | AO6: =J22+AD22+AI22+Y22 -> 76.703514 | AP6: =AO6-AN6 -> 3.5951226 | AQ6: =IFERROR(AP6/AO6,"-") -> 0.046870376 | AR6: G
A7: Commercial Fuels | B7: Commercial Fuels | C7: Roanne Steele | D7: =I7+AC7+AH7+X7 -> 12.401562 | E7: =J7+AD7+AI7+Y7 -> 18.777378 | F7: =E7-D7 -> 6.3758153 | G7: =IFERROR(F7/E7,"-") -> 0.3395477 | H7: G | I7: 7.1072414 | J7: 8.2847223 | K7: =J7-I7 -> 1.1774809 | L7: =IFERROR(K7/J7,"-") -> 0.14212678 | M7: G | N7: =I7-S7 -> 5.0186846 | O7: =J7-T7 -> 5.3538618 | P7: =O7-N7 -> 0.33517727 | Q7: =IFERROR(P7/O7,"-") -> 0.062604767 | R7: G | S7: 2.0885568 | T7: 2.9308605 | U7: =T7-S7 -> 0.84230361 | V7: =IFERROR(U7/T7,"-") -> 0.28739124 | W7: G | Z7: =Y7-X7 -> 0 | AA7: =IFERROR(Z7/Y7,"-") -> - | AC7: 4.7285415 | AD7: 7.109604 | AE7: =AD7-AC7 -> 2.3810625 | AF7: =IFERROR(AE7/AD7,"-") -> 0.3349079 | AG7: G | AH7: 0.56577941 | AI7: 3.3830513 | AJ7: =AI7-AH7 -> 2.8172719 | AK7: =IFERROR(AJ7/AI7,"-") -> 0.83276062 | AL7: G | AN7: =I23+AC23+AH23+X23 -> 32.768998 | AO7: =J23+AD23+AI23+Y23 -> 40.534223 | AP7: =AO7-AN7 -> 7.7652255 | AQ7: =IFERROR(AP7/AO7,"-") -> 0.19157208 | AR7: G
A8: Retail | B8: Retail | C8: Vance Anderson | D8: =I8+AC8+AH8+X8 -> 14.290549 | E8: =J8+AD8+AI8+Y8 -> 18.065295 | F8: =E8-D8 -> 3.7747465 | G8: =IFERROR(F8/E8,"-") -> 0.20895017 | H8: G | I8: 6.854453 | J8: 7.0852951 | K8: =J8-I8 -> 0.23084214 | L8: =IFERROR(K8/J8,"-") -> 0.032580455 | M8: G | N8: =I8-S8 -> 6.4596074 | O8: =J8-T8 -> 6.4302951 | P8: =O8-N8 -> -0.02931227 | Q8: =IFERROR(P8/O8,"-") -> -0.0045584642 | R8: G | S8: 0.39484559 | T8: 0.655 | U8: =T8-S8 -> 0.26015441 | V8: =IFERROR(U8/T8,"-") -> 0.39718231 | W8: G | Z8: =Y8-X8 -> 0 | AA8: =IFERROR(Z8/Y8,"-") -> - | AC8: 3.3546059 | AD8: 5.08 | AE8: =AD8-AC8 -> 1.7253941 | AF8: =IFERROR(AE8/AD8,"-") -> 0.33964451 | AG8: G | AH8: 4.0814897 | AI8: 5.9 | AJ8: =AI8-AH8 -> 1.8185103 | AK8: =IFERROR(AJ8/AI8,"-") -> 0.30822208 | AL8: G | AN8: =I24+AC24+AH24+X24 -> 35.260356 | AO8: =J24+AD24+AI24+Y24 -> 33.880855 | AP8: =AO8-AN8 -> -1.3795012 | AQ8: =IFERROR(AP8/AO8,"-") -> -0.040716245 | AR8: R
A9: Energy Solutions | B9: Energy Solutions | C9: Roanne Steele | D9: =I9+AC9+AH9+X9 -> 4.138504 | E9: =J9+AD9+AI9+Y9 -> 3.8066795 | F9: =E9-D9 -> -0.33182446 | G9: =IFERROR(F9/E9,"-") -> -0.087169002 | H9: R | I9: 2.8789003 | J9: 2.5160191 | K9: =J9-I9 -> -0.36288119 | L9: =IFERROR(K9/J9,"-") -> -0.14422831 | M9: R | N9: =I9-S9 -> 2.5452916 | O9: =J9-T9 -> 2.0310192 | P9: =O9-N9 -> -0.51427247 | Q9: =IFERROR(P9/O9,"-") -> -0.25320907 | R9: R | S9: 0.33360872 | T9: 0.485 | U9: =T9-S9 -> 0.15139128 | V9: =IFERROR(U9/T9,"-") -> 0.31214697 | W9: G | Z9: =Y9-X9 -> 0 | AA9: =IFERROR(Z9/Y9,"-") -> - | AE9: =AD9-AC9 -> 0 | AF9: =IFERROR(AE9/AD9,"-") -> - | AH9: 1.2596037 | AI9: 1.2906604 | AJ9: =AI9-AH9 -> 0.031056732 | AK9: =IFERROR(AJ9/AI9,"-") -> 0.024062667 | AL9: G | AN9: =I25+AC25+AH25+X25 -> 7.830666 | AO9: =J25+AD25+AI25+Y25 -> 8.0095244 | AP9: =AO9-AN9 -> 0.17885836 | AQ9: =IFERROR(AP9/AO9,"-") -> 0.022330709 | AR9: R
A10: Infrastructure | B10: Infrastructure | C10: Roanne Steele | D10: =I10+AC10+AH10+X10 -> 2.6905766 | E10: =J10+AD10+AI10+Y10 -> 4.277083 | F10: =E10-D10 -> 1.5865064 | G10: =IFERROR(F10/E10,"-") -> 0.37093187 | H10: G | I10: 1.7562082 | J10: 1.831374 | K10: =J10-I10 -> 0.07516578 | L10: =IFERROR(K10/J10,"-") -> 0.041043381 | M10: G | N10: =I10-S10 -> 1.4404499 | O10: =J10-T10 -> 1.449693 | P10: =O10-N10 -> 0.00924308 | Q10: =IFERROR(P10/O10,"-") -> 0.0063758879 | R10: G | S10: 0.3157583 | T10: 0.381681 | U10: =T10-S10 -> 0.0659227 | V10: =IFERROR(U10/T10,"-") -> 0.17271675 | W10: G | Z10: =Y10-X10 -> 0 | AA10: =IFERROR(Z10/Y10,"-") -> - | AE10: =AD10-AC10 -> 0 | AF10: =IFERROR(AE10/AD10,"-") -> - | AH10: 0.93436839 | AI10: 2.445709 | AJ10: =AI10-AH10 -> 1.5113406 | AK10: =IFERROR(AJ10/AI10,"-") -> 0.61795602 | AL10: G | AN10: =I26+AC26+AH26+X26 -> 8.4185471 | AO10: =J26+AD26+AI26+Y26 -> 9.249376 | AP10: =AO10-AN10 -> 0.83082882 | AQ10: =IFERROR(AP10/AO10,"-") -> 0.089825392 | AR10: G
A11: Finance & Other Corp | B11: Finance & Other Corp | C11: Emily Mogic | D11: =I11+AC11+AH11+X11 -> 2.8468529 | E11: =J11+AD11+AI11+Y11 -> 2.1223538 | F11: =E11-D11 -> -0.72449911 | G11: =IFERROR(F11/E11,"-") -> -0.34136585 | H11: R | I11: 2.8468529 | J11: 2.1223538 | K11: =J11-I11 -> -0.72449911 | L11: =IFERROR(K11/J11,"-") -> -0.34136585 | M11: R | N11: =I11-S11 -> 2.0786006 | O11: =J11-T11 -> 1.6546105 | P11: =O11-N11 -> -0.42399014 | Q11: =IFERROR(P11/O11,"-") -> -0.25624771 | R11: R | S11: 0.76825227 | T11: 0.4677433 | U11: =T11-S11 -> -0.30050897 | V11: =IFERROR(U11/T11,"-") -> -0.64246556 | W11: R | Z11: =Y11-X11 -> 0 | AA11: =IFERROR(Z11/Y11,"-") -> - | AE11: =AD11-AC11 -> 0 | AF11: =IFERROR(AE11/AD11,"-") -> - | AH11: 0 | AI11: 0 | AJ11: =AI11-AH11 -> 0 | AK11: =IFERROR(AJ11/AI11,"-") -> - | AN11: =I27+AC27+AH27+X27 -> 5.2721119 | AO11: =J27+AD27+AI27+Y27 -> 3.8807737 | AP11: =AO11-AN11 -> -1.3913382 | AQ11: =IFERROR(AP11/AO11,"-") -> -0.35852084 | AR11: G
A12: People & Culture | B12: P&C | C12: Emily Mogic | D12: =I12+AC12+AH12+X12 -> 1.9651397 | E12: =J12+AD12+AI12+Y12 -> 2.460508 | F12: =E12-D12 -> 0.49536834 | G12: =IFERROR(F12/E12,"-") -> 0.20132767 | H12: G | I12: 1.6178184 | J12: 1.860608 | K12: =J12-I12 -> 0.2427896 | L12: =IFERROR(K12/J12,"-") -> 0.13048939 | M12: G | N12: =I12-S12 -> 0.70035539 | O12: =J12-T12 -> 0.87310804 | P12: =O12-N12 -> 0.17275265 | Q12: =IFERROR(P12/O12,"-") -> 0.19785942 | R12: G | S12: 0.91746305 | T12: 0.9875 | U12: =T12-S12 -> 0.07003695 | V12: =IFERROR(U12/T12,"-") -> 0.070923494 | W12: G | Z12: =Y12-X12 -> 0 | AA12: =IFERROR(Z12/Y12,"-") -> - | AC12: 0.34732126 | AD12: 0.4624 | AE12: =AD12-AC12 -> 0.11507874 | AF12: =IFERROR(AE12/AD12,"-") -> 0.24887271 | AG12: G | AH12: 0 | AI12: 0.1375 | AJ12: =AI12-AH12 -> 0.1375 | AK12: =IFERROR(AJ12/AI12,"-") -> 1 | AL12: G | AN12: =I28+AC28+AH28+X28 -> 5.4932256 | AO12: =J28+AD28+AI28+Y28 -> 5.813038 | AP12: =AO12-AN12 -> 0.31981243 | AQ12: =IFERROR(AP12/AO12,"-") -> 0.055016401 | AR12: G
A13: Customer | B13: Customer | C13: Harley Giles | D13: =I13+AC13+AH13+X13 -> 2.4105283 | E13: =J13+AD13+AI13+Y13 -> 5.4047457 | F13: =E13-D13 -> 2.9942174 | G13: =IFERROR(F13/E13,"-") -> 0.55399783 | H13: G | I13: 0.98861064 | J13: 0.82141236 | K13: =J13-I13 -> -0.16719828 | L13: =IFERROR(K13/J13,"-") -> -0.20354975 | M13: R | N13: =I13-S13 -> 0.98861064 | O13: =J13-T13 -> 0.82141236 | P13: =O13-N13 -> -0.16719828 | Q13: =IFERROR(P13/O13,"-") -> -0.20354975 | R13: R | S13: 0 | T13: 0 | U13: =T13-S13 -> 0 | V13: =IFERROR(U13/T13,"-") -> - | Z13: =Y13-X13 -> 0 | AA13: =IFERROR(Z13/Y13,"-") -> - | AC13: 0 | AD13: 2.5 | AE13: =AD13-AC13 -> 2.5 | AF13: =IFERROR(AE13/AD13,"-") -> 1 | AG13: G | AH13: 1.4219177 | AI13: 2.0833333 | AJ13: =AI13-AH13 -> 0.66141564 | AK13: =IFERROR(AJ13/AI13,"-") -> 0.31747951 | AL13: G | AN13: =I29+AC29+AH29+X29 -> 10.983783 | AO13: =J29+AD29+AI29+Y29 -> 11.691533 | AP13: =AO13-AN13 -> 0.70775018 | AQ13: =IFERROR(AP13/AO13,"-") -> 0.060535277 | AR13: G
B14: Total Technology | D14: =SUM(D5:D13) -> 129.57658 | E14: =SUM(E5:E13) -> 149.32633 | F14: =SUM(F5:F13) -> 19.749751 | G14: =F14/E14 -> 0.132259 | H14: G | I14: =SUM(I5:I13) -> 92.279395 | J14: =SUM(J5:J13) -> 93.256469 | K14: =SUM(K5:K13) -> 0.97707378 | L14: =K14/J14 -> 0.010477276 | M14: G | N14: =SUM(N5:N13) -> 86.660069 | O14: =SUM(O5:O13) -> 85.125564 | P14: =SUM(P5:P13) -> -1.534505 | Q14: =P14/O14 -> -0.018026371 | R14: A | S14: =SUM(S5:S13) -> 5.619326 | T14: =SUM(T5:T13) -> 8.1309048 | U14: =SUM(U5:U13) -> 2.5115788 | V14: =U14/T14 -> 0.3088929 | W14: G | X14: =SUM(X5:X13) -> 7.6209764 | Y14: =SUM(Y5:Y13) -> 8.0775842 | Z14: =SUM(Z5:Z13) -> 0.45660781 | AA14: =Z14/Y14 -> 0.056527769 | AB14: G | AC14: =SUM(AC5:AC13) -> 17.270477 | AD14: =SUM(AD5:AD13) -> 24.414204 | AE14: =SUM(AE5:AE13) -> 7.1437272 | AF14: =AE14/AD14 -> 0.29260537 | AG14: G | AH14: =SUM(AH5:AH13) -> 12.405729 | AI14: =SUM(AI5:AI13) -> 23.578071 | AJ14: =SUM(AJ5:AJ13) -> 11.172342 | AK14: =AJ14/AI14 -> 0.47384463 | AL14: G | AN14: =SUM(AN5:AN13) -> 297.09322 | AO14: =SUM(AO5:AO13) -> 302.52235 | AP14: =SUM(AP5:AP13) -> 5.4291311 | AQ14: =AP14/AO14 -> 0.017946215 | AR14: G
F15: =F14/E14 -> 0.132259 | I15: =I14/$D14 -> 0.71216108 | J15: ` | K15: =K14/J14 -> 0.010477276 | N15: =N14/$D14 -> 0.66879425 | P15: =P14/O14 -> -0.018026371 | S15: =S14/$D14 -> 0.043366835 | U15: =U14/T14 -> 0.3088929 | X15: =X14/$D14 -> 0.05881446 | Z15: =Z14/Y14 -> 0.056527769 | AC15: =AC14/$D14 -> 0.13328394 | AE15: =AE14/AD14 -> 0.29260537 | AH15: =AH14/$D14 -> 0.095740518 | AJ15: =AJ14/AI14 -> 0.47384463
B19: BUSINESS SEGMENTS | C19: TDD GM | D19: FY2026 - TOTAL | I19: OPEX: LIGHTS ON + INITIATIVES | N19: OPEX:LIGHTS ON | S19: OPEX: INITIATIVES | X19: OPEX: DEPRECIATION | AC19: OPEX: SIGNIFICANT ITEMS | AH19: CAPEX
D20: F | E20: B | F20: V | G20: V % | H20: Trend | I20: F | J20: B | K20: V | L20: V % | M20: Trend | N20: F | O20: B | P20: V | Q20: V % | R20: Trend | S20: F | T20: B | U20: V | V20: V % | W20: Trend | X20: F | Y20: B | Z20: V | AA20: V % | AB20: Trend | AC20: F | AD20: B | AE20: V | AF20: V % | AG20: Trend | AH20: F | AI20: B | AJ20: V | AK20: V % | AL20: Trend
A21: TDD (Corporate)1 | B21: TDD (Corporate)1 | C21: Brad Blyth Greg Cassis | D21: =I21+AC21+AH21+X21 -> 117.95714 | E21: =J21+AD21+AI21+Y21 -> 112.75951 | F21: =E21-D21 -> -5.1976273 | G21: =IFERROR(F21/E21,"-") -> -0.046094801 | H21: R | I21: 82.087877 | J21: 81.894863 | K21: =J21-I21 -> -0.19301366 | L21: =IFERROR(K21/J21,"-") -> -0.002356847 | M21: G | N21: =I21-S21 -> 79.310436 | O21: =J21-T21 -> 78.894863 | P21: =O21-N21 -> -0.41557243 | Q21: =IFERROR(P21/O21,"-") -> -0.0052674206 | R21: A | S21: 2.7774412 | T21: 3 | U21: =T21-S21 -> 0.22255877 | V21: =IFERROR(U21/T21,"-") -> 0.074186257 | W21: G | X21: 5.6865111 | Y21: 5.8000499 | Z21: =Y21-X21 -> 0.11353882 | AA21: =IFERROR(Z21/Y21,"-") -> 0.01957549 | AB21: G | AC21: 25.395773 | AD21: 20.1966 | AE21: =AD21-AC21 -> -5.1991726 | AF21: =IFERROR(AE21/AD21,"-") -> -0.25742811 | AG21: R | AH21: 4.7869798 | AI21: 4.868 | AJ21: =AI21-AH21 -> 0.08102017 | AK21: =IFERROR(AJ21/AI21,"-") -> 0.01664342 | AL21: G | AM21: =I21+X21 -> 87.774388 | AN21: input retail SI number manually
A22: Z-Energy | B22: Z- Energy | C22: Vance Anderson Harley Giles | D22: =I22+AC22+AH22+X22 -> 73.108391 | E22: =J22+AD22+AI22+Y22 -> 76.703514 | F22: =E22-D22 -> 3.5951226 | G22: =IFERROR(F22/E22,"-") -> 0.046870376 | H22: G | I22: 53.465434 | J22: 53.6715 | K22: =J22-I22 -> 0.20606573 | L22: =IFERROR(K22/J22,"-") -> 0.0038393884 | M22: G | N22: =I22-S22 -> 53.465434 | O22: =J22-T22 -> 52.22526 | P22: =O22-N22 -> -1.2401743 | Q22: =IFERROR(P22/O22,"-") -> -0.023746637 | R22: A | S22: 0 | T22: 1.44624 | U22: =T22-S22 -> 1.44624 | V22: =IFERROR(U22/T22,"-") -> 1 | W22: G | X22: 10.161498 | Y22: 11.306521 | Z22: =Y22-X22 -> 1.1450224 | AA22: =IFERROR(Z22/Y22,"-") -> 0.10127098 | AB22: G | AC22: 0 | AD22: 0 | AE22: =AD22-AC22 -> 0 | AF22: =IFERROR(AE22/AD22,"-") -> - | AH22: 9.4814594 | AI22: 11.725494 | AJ22: =AI22-AH22 -> 2.2440344 | AK22: =IFERROR(AJ22/AI22,"-") -> 0.1913808 | AL22: G | AM22: =I22+X22 -> 63.626932
A23: Commercial Fuels | B23: Commercial Fuels | C23: Roanne Steele | D23: =I23+AC23+AH23+X23 -> 32.768998 | E23: =J23+AD23+AI23+Y23 -> 40.534223 | F23: =E23-D23 -> 7.7652255 | G23: =IFERROR(F23/E23,"-") -> 0.19157208 | H23: G | I23: 18.07582 | J23: 19.517302 | K23: =J23-I23 -> 1.4414818 | L23: =IFERROR(K23/J23,"-") -> 0.073856612 | M23: G | N23: =I23-S23 -> 12.122014 | O23: =J23-T23 -> 13.655581 | P23: =O23-N23 -> 1.533567 | Q23: =IFERROR(P23/O23,"-") -> 0.11230331 | R23: G | S23: 5.9538061 | T23: 5.8617209 | U23: =T23-S23 -> -0.092085221 | V23: =IFERROR(U23/T23,"-") -> -0.015709588 | W23: A | Z23: =Y23-X23 -> 0 | AA23: =IFERROR(Z23/Y23,"-") -> - | AC23: 8.927316 | AD23: 14.219208 | AE23: =AD23-AC23 -> 5.291892 | AF23: =IFERROR(AE23/AD23,"-") -> 0.37216503 | AG23: G | AH23: 5.7658612 | AI23: 6.7977128 | AJ23: =AI23-AH23 -> 1.0318517 | AK23: =IFERROR(AJ23/AI23,"-") -> 0.15179395 | AL23: G
A24: Retail | B24: Retail | C24: Vance Anderson | D24: =I24+AC24+AH24+X24 -> 35.260356 | E24: =J24+AD24+AI24+Y24 -> 33.880855 | F24: =E24-D24 -> -1.3795012 | G24: =IFERROR(F24/E24,"-") -> -0.040716245 | H24: A | I24: 15.230723 | J24: 15.235855 | K24: =J24-I24 -> 0.0051319 | L24: =IFERROR(K24/J24,"-") -> 0.00033683047 | M24: G | N24: =I24-S24 -> 14.481085 | O24: =J24-T24 -> 13.925855 | P24: =O24-N24 -> -0.55523051 | Q24: =IFERROR(P24/O24,"-") -> -0.03987048 | R24: A | S24: 0.74963759 | T24: 1.31 | U24: =T24-S24 -> 0.56036241 | V24: =IFERROR(U24/T24,"-") -> 0.42775756 | W24: G | Z24: =Y24-X24 -> 0 | AA24: =IFERROR(Z24/Y24,"-") -> - | AC24: 8.64 | AD24: 6.845 | AE24: =AD24-AC24 -> -1.795 | AF24: =IFERROR(AE24/AD24,"-") -> -0.26223521 | AG24: R | AH24: 11.389633 | AI24: 11.8 | AJ24: =AI24-AH24 -> 0.41036692 | AK24: =IFERROR(AJ24/AI24,"-") -> 0.034776858 | AL24: G
A25: Energy Solutions | B25: Energy Solutions | C25: Roanne Steele | D25: =I25+AC25+AH25+X25 -> 7.830666 | E25: =J25+AD25+AI25+Y25 -> 8.0095244 | F25: =E25-D25 -> 0.17885836 | G25: =IFERROR(F25/E25,"-") -> 0.022330709 | H25: G | I25: 5.0440983 | J25: 5.0119394 | K25: =J25-I25 -> -0.0321589 | L25: =IFERROR(K25/J25,"-") -> -0.0064164582 | M25: A | N25: =I25-S25 -> 4.5362156 | O25: =J25-T25 -> 4.0419395 | P25: =O25-N25 -> -0.49427618 | Q25: =IFERROR(P25/O25,"-") -> -0.12228688 | R25: R | S25: 0.50788272 | T25: 0.97 | U25: =T25-S25 -> 0.46211728 | V25: =IFERROR(U25/T25,"-") -> 0.47640957 | W25: G | Z25: =Y25-X25 -> 0 | AA25: =IFERROR(Z25/Y25,"-") -> - | AE25: =AD25-AC25 -> 0 | AF25: =IFERROR(AE25/AD25,"-") -> - | AH25: 2.7865677 | AI25: 2.9975849 | AJ25: =AI25-AH25 -> 0.21101726 | AK25: =IFERROR(AJ25/AI25,"-") -> 0.070395758 | AL25: G
A26: Infrastructure | B26: Infrastructure | C26: Roanne Steele | D26: =I26+AC26+AH26+X26 -> 8.4185471 | E26: =J26+AD26+AI26+Y26 -> 9.249376 | F26: =E26-D26 -> 0.83082882 | G26: =IFERROR(F26/E26,"-") -> 0.089825392 | H26: G | I26: 4.2749786 | J26: 4.357958 | K26: =J26-I26 -> 0.08297936 | L26: =IFERROR(K26/J26,"-") -> 0.019040881 | M26: G | N26: =I26-S26 -> 3.3010253 | O26: =J26-T26 -> 3.594596 | P26: =O26-N26 -> 0.29357066 | Q26: =IFERROR(P26/O26,"-") -> 0.081670001 | R26: G | S26: 0.9739533 | T26: 0.763362 | U26: =T26-S26 -> -0.2105913 | V26: =IFERROR(U26/T26,"-") -> -0.27587344 | W26: R | Z26: =Y26-X26 -> 0 | AA26: =IFERROR(Z26/Y26,"-") -> - | AE26: =AD26-AC26 -> 0 | AF26: =IFERROR(AE26/AD26,"-") -> - | AH26: 4.1435685 | AI26: 4.891418 | AJ26: =AI26-AH26 -> 0.74784946 | AK26: =IFERROR(AJ26/AI26,"-") -> 0.15289012 | AL26: G
A27: Finance & Other Corp | B27: Finance & Other Corp | C27: Emily Mogic | D27: =I27+AC27+AH27+X27 -> 5.2721119 | E27: =J27+AD27+AI27+Y27 -> 3.8807737 | F27: =E27-D27 -> -1.3913382 | G27: =IFERROR(F27/E27,"-") -> -0.35852084 | H27: R | I27: 5.2721119 | J27: 3.8807737 | K27: =J27-I27 -> -1.3913382 | L27: =IFERROR(K27/J27,"-") -> -0.35852084 | M27: R | N27: =I27-S27 -> 4.3588956 | O27: =J27-T27 -> 2.9452871 | P27: =O27-N27 -> -1.4136086 | Q27: =IFERROR(P27/O27,"-") -> -0.47995613 | R27: R | S27: 0.91321627 | T27: 0.93548661 | U27: =T27-S27 -> 0.02227034 | V27: =IFERROR(U27/T27,"-") -> 0.023806156 | W27: G | Z27: =Y27-X27 -> 0 | AA27: =IFERROR(Z27/Y27,"-") -> - | AE27: =AD27-AC27 -> 0 | AF27: =IFERROR(AE27/AD27,"-") -> - | AH27: 0 | AI27: 0 | AJ27: =AI27-AH27 -> 0 | AK27: =IFERROR(AJ27/AI27,"-") -> - | AL27: G
A28: People & Culture | B28: P&C | C28: Emily Mogic | D28: =I28+AC28+AH28+X28 -> 5.4932256 | E28: =J28+AD28+AI28+Y28 -> 5.813038 | F28: =E28-D28 -> 0.31981243 | G28: =IFERROR(F28/E28,"-") -> 0.055016401 | H28: G | I28: 3.8516861 | J28: 4.123038 | K28: =J28-I28 -> 0.27135188 | L28: =IFERROR(K28/J28,"-") -> 0.065813577 | M28: G | N28: =I28-S28 -> 1.9121353 | O28: =J28-T28 -> 2.148038 | P28: =O28-N28 -> 0.23590273 | Q28: =IFERROR(P28/O28,"-") -> 0.10982242 | R28: G | S28: 1.9395508 | T28: 1.975 | U28: =T28-S28 -> 0.035449154 | V28: =IFERROR(U28/T28,"-") -> 0.017948939 | W28: G | Z28: =Y28-X28 -> 0 | AA28: =IFERROR(Z28/Y28,"-") -> - | AC28: 1.3115394 | AD28: 1.36 | AE28: =AD28-AC28 -> 0.04846055 | AF28: =IFERROR(AE28/AD28,"-") -> 0.035632757 | AG28: G | AH28: 0.33 | AI28: 0.33 | AJ28: =AI28-AH28 -> 0 | AK28: =IFERROR(AJ28/AI28,"-") -> 0 | AL28: G
A29: Customer | B29: Customer | C29: Harley Giles | D29: =I29+AC29+AH29+X29 -> 10.983783 | E29: =J29+AD29+AI29+Y29 -> 11.691533 | F29: =E29-D29 -> 0.70775018 | G29: =IFERROR(F29/E29,"-") -> 0.060535277 | H29: G | I29: 2.74505 | J29: 1.6915328 | K29: =J29-I29 -> -1.0535172 | L29: =IFERROR(K29/J29,"-") -> -0.62281806 | M29: R | N29: =I29-S29 -> 2.74505 | O29: =J29-T29 -> 1.6915328 | P29: =O29-N29 -> -1.0535172 | Q29: =IFERROR(P29/O29,"-") -> -0.62281806 | R29: R | S29: 0 | T29: 0 | U29: =T29-S29 -> 0 | V29: =IFERROR(U29/T29,"-") -> - | Z29: =Y29-X29 -> 0 | AA29: =IFERROR(Z29/Y29,"-") -> - | AC29: 3.832387 | AD29: 5 | AE29: =AD29-AC29 -> 1.1676131 | AF29: =IFERROR(AE29/AD29,"-") -> 0.23352261 | AG29: G | AH29: 4.4063457 | AI29: 5 | AJ29: =AI29-AH29 -> 0.59365431 | AK29: =IFERROR(AJ29/AI29,"-") -> 0.11873086 | AL29: G
B30: Total Technology | D30: =SUM(D21:D29) -> 297.09322 | E30: =SUM(E21:E29) -> 302.52235 | F30: =SUM(F21:F29) -> 5.4291311 | G30: =F30/E30 -> 0.017946215 | H30: G | I30: =SUM(I21:I29) -> 190.04778 | J30: =SUM(J21:J29) -> 189.38476 | K30: =SUM(K21:K29) -> -0.66301729 | L30: =K30/J30 -> -0.0035009009 | M30: A | N30: =SUM(N21:N29) -> 176.23229 | O30: =SUM(O21:O29) -> 173.12295 | P30: =SUM(P21:P29) -> -3.1093387 | Q30: =P30/O30 -> -0.017960292 | R30: A | S30: =SUM(S21:S29) -> 13.815488 | T30: =SUM(T21:T29) -> 16.26181 | U30: =SUM(U21:U29) -> 2.4463214 | V30: =U30/T30 -> 0.15043353 | W30: G | X30: =SUM(X21:X29) -> 15.848009 | Y30: =SUM(Y21:Y29) -> 17.10657 | Z30: =SUM(Z21:Z29) -> 1.2585612 | AA30: =Z30/Y30 -> 0.073571802 | AB30: G | AC30: =SUM(AC21:AC29) -> 48.107015 | AD30: =SUM(AD21:AD29) -> 47.620808 | AE30: =SUM(AE21:AE29) -> -0.48620701 | AF30: =AE30/AD30 -> -0.01020997 | AG30: A | AH30: =SUM(AH21:AH29) -> 43.090415 | AI30: =SUM(AI21:AI29) -> 48.41021 | AJ30: =SUM(AJ21:AJ29) -> 5.3197942 | AK30: =AJ30/AI30 -> 0.10988992 | AL30: G
I31: =I30/$D30 -> 0.63969073 | N31: =N30/$D30 -> 0.59318853 | S31: =S30/$D30 -> 0.046502199 | X31: =X30/$D30 -> 0.053343558 | AC31: =AC30/$D30 -> 0.16192566 | AH31: =AH30/$D30 -> 0.14504005
AO32: =E30-297 -> 5.5223497
D35: =D3 -> TOTAL YTD (Jun-2026) | I35: TOTAL TECHNOLOGY Full Year 2026
B36: Spend Type | D36: A | E36: B | F36: V | G36: V % | H36: Trend | I36: F | J36: B | K36: V | L36: V % | M36: Trend
B37: Lights on | D37: =N14 -> 86.660069 | E37: =O14 -> 85.125564 | F37: =E37-D37 -> -1.534505 | G37: =IFERROR(F37/E37,"-") -> -0.018026371 | H37: A | I37: =N30 -> 176.23229 | J37: =O30 -> 173.12295 | K37: =J37-I37 -> -3.1093387 | L37: =IFERROR(K37/J37,"-") -> -0.017960292 | M37: A
B38: Depreciation | D38: =X14 -> 7.6209764 | E38: =Y14 -> 8.0775842 | F38: =E38-D38 -> 0.45660781 | G38: =IFERROR(F38/E38,"-") -> 0.056527769 | H38: G | I38: =X30 -> 15.848009 | J38: =Y30 -> 17.10657 | K38: =J38-I38 -> 1.2585612 | L38: =IFERROR(K38/J38,"-") -> 0.073571802 | M38: G
B39: Lights on + Depreciation | D39: =SUM(D37:D38) -> 94.281045 | E39: =SUM(E37:E38) -> 93.203148 | F39: =SUM(F37:F38) -> -1.0778972 | G39: =IFERROR(F39/E39,"-") -> -0.01156503 | H39: A | I39: =SUM(I37:I38) -> 192.0803 | J39: =SUM(J37:J38) -> 190.22952 | K39: =SUM(K37:K38) -> -1.8507775 | L39: =IFERROR(K39/J39,"-") -> -0.0097291812 | M39: A
B40: Opex Initiatives | D40: =S14 -> 5.619326 | E40: =T14 -> 8.1309048 | F40: =E40-D40 -> 2.5115788 | G40: =IFERROR(F40/E40,"-") -> 0.3088929 | H40: G | I40: =S30 -> 13.815488 | J40: =T30 -> 16.26181 | K40: =J40-I40 -> 2.4463214 | L40: =IFERROR(K40/J40,"-") -> 0.15043353 | M40: G
B41: Capex | D41: =AH14 -> 12.405729 | E41: =AI14 -> 23.578071 | F41: =E41-D41 -> 11.172342 | G41: =IFERROR(F41/E41,"-") -> 0.47384463 | H41: G | I41: =AH30 -> 43.090415 | J41: =AI30 -> 48.41021 | K41: =J41-I41 -> 5.3197942 | L41: =IFERROR(K41/J41,"-") -> 0.10988992 | M41: G
B42: Significant Items | D42: =AC14 -> 17.270477 | E42: =AD14 -> 24.414204 | F42: =E42-D42 -> 7.1437272 | G42: =IFERROR(F42/E42,"-") -> 0.29260537 | H42: G | I42: =AC30 -> 48.107015 | J42: =AD30 -> 47.620808 | K42: =J42-I42 -> -0.48620701 | L42: =IFERROR(K42/J42,"-") -> -0.01020997 | M42: A
B43: Projects | D43: =SUM(D40:D42) -> 35.295531 | E43: =SUM(E40:E42) -> 56.123179 | F43: =SUM(F40:F42) -> 20.827648 | G43: =IFERROR(F43/E43,"-") -> 0.37110599 | H43: G | I43: =SUM(I40:I42) -> 105.01292 | J43: =SUM(J40:J42) -> 112.29283 | K43: =SUM(K40:K42) -> 7.2799086 | L43: =IFERROR(K43/J43,"-") -> 0.064829685 | M43: G
B44: Total Technology | D44: =SUM(D43,D39) -> 129.57658 | E44: =SUM(E43,E39) -> 149.32633 | F44: =SUM(F43,F39) -> 19.749751 | G44: =IFERROR(F44/E44,"-") -> 0.132259 | H44: G | I44: =SUM(I43,I39) -> 297.09322 | J44: =SUM(J43,J39) -> 302.52235 | K44: =SUM(K43,K39) -> 5.4291311 | L44: =IFERROR(K44/J44,"-") -> 0.017946215 | M44: G
B47: SPEND CATEGORY | D47: =D3 -> TOTAL YTD (Jun-2026) | I47: TOTAL TECHNOLOGY YTD (May-2026)
D48: A | E48: B | F48: V | G48: V % | H48: Trend | I48: A | J48: B | K48: V | L48: V % | M48: Trend
B49: Opex | D49: =I14+X14 -> 99.900371 | E49: =J14+Y14 -> 101.33405 | F49: =E49-D49 -> 1.4336816 | G49: =IFERROR(F49/E49,"-") -> 0.014148073 | H49: G | I49: =I30+X30 -> 205.89579 | J49: =J30+Y30 -> 206.49133 | K49: =J49-I49 -> 0.59554393 | L49: =IFERROR(K49/J49,"-") -> 0.002884111 | M49: G
B50: Significant Items | D50: =AC14 -> 17.270477 | E50: =AD14 -> 24.414204 | F50: =E50-D50 -> 7.1437272 | G50: =IFERROR(F50/E50,"-") -> 0.29260537 | H50: G | I50: =AC30 -> 48.107015 | J50: =AD30 -> 47.620808 | K50: =J50-I50 -> -0.48620701 | L50: =IFERROR(K50/J50,"-") -> -0.01020997 | M50: A
B51: Capex | D51: =AH14 -> 12.405729 | E51: =AI14 -> 23.578071 | F51: =E51-D51 -> 11.172342 | G51: =IFERROR(F51/E51,"-") -> 0.47384463 | H51: G | I51: =AH30 -> 43.090415 | J51: =AI30 -> 48.41021 | K51: =J51-I51 -> 5.3197942 | L51: =IFERROR(K51/J51,"-") -> 0.10988992 | M51: G
B52: Total Technology | D52: =SUM(D49:D51) -> 129.57658 | E52: =SUM(E49:E51) -> 149.32633 | F52: =SUM(F49:F51) -> 19.749751 | G52: =IFERROR(F52/E52,"-") -> 0.132259 | H52: G | I52: =SUM(I49:I51) -> 297.09322 | J52: =SUM(J49:J51) -> 302.52235 | K52: =SUM(K49:K51) -> 5.4291311 | L52: =IFERROR(K52/J52,"-") -> 0.017946215 | M52: G

Sheet REVIEW - Complete Role Mapping
A1: EE Number | B1: Name | C1: Position Title | D1: Reports to name | E1: Reports to Position | F1: Division (GM) | G1: Department (GM-1) | H1: Team (GM-2) | I1: Portfolio | J1: Platform | K1: Squad | L1: CC | M1: Country | N1: Job Level | O1: FTE | Q1: Type | R1: Unit | S1: day rate | T1: FTE Base Local | U1: FTE Base AUD | V1: STI | W1: Payroll | X1: Pensions | Y1: medical | Z1: CPI | AA1: Full Cost AUD | AB1: MyHR ee no | AJ1: MTab | AK1: MStatus | AL1: MAUNZ | AM1: MRank | AN1: MKey | AP1: Squad (canonical, from col K) | AQ1: Leadership | AR1: Overhead line | AS1: Squad name on the 1.x tab | AT1: Squad or overhead line | AU1: Agreed cost override (AUD)
A2: 99999101533 | B2: Adrian Alcance | C2: Senior Engineer - DevOps | D2: Vacant | E2: Technology Manager, Engineering | F2: Ampol Retail & Z | G2: Z & Group Retail | H2: Z & Group Retail, Engineering | I2: Z | J2: Z Customer | K2: Z Retail Backend | M2: NZ | N2: CIA | O2: 1 | Q2: Permanent - Full Time | T2: 123710 | U2: 113813.2 | V2: 0.15 | X2: 0.05 | Y2: 2910 | Z2: 0.03 | AA2: =IF(TRIM($B2)="","",IF(N($AU2)>0,$AU2,IF(N($S2)>0,$S2*Lists!$AG$15*(1+N($Z2)),N($U2)*(1+N($V2)+N($W2)+N($X2)+N($Z2))+N($Y2)))) -> 142900.24 | AJ2: =IF(TRIM($B2)="","",IF(IFERROR(INDEX(Lists!$AO$2:$AO$11,MATCH(ROW(),Lists!$AN$2:$AN$11,0)),"")<>"",IFERROR(INDEX(Lists!$AO$2:$AO$11,MATCH(ROW(),Lists!$AN$2:$AN$11,0)),""),IFERROR(INDEX(Lists!$U:$U,MATCH(TRIM($I2),Lists!$T:$T,0)),TRIM($I2)))) -> Z Retail | AK2: =IF(ISNUMBER(SEARCH("vacant",$B2)),"Vacant","Filled") -> Filled | AL2: =IF($M2="NZ","NZ","AU") -> NZ | AM2: =COUNTIF($AJ$2:$AJ2,$AJ2) -> 1 | AN2: =$AJ2&"|"&$AM2 -> Z Retail|1 | AP2: =IF(TRIM($B2)="","",IF($AQ2=1,"Leadership",IFERROR(INDEX(Lists!$X:$X,MATCH(TRIM($K2),Lists!$W:$W,0)),IF(OR(TRIM($K2)="",LOWER(TRIM($K2))="na"),IF(TRIM($G2)="","Unassigned",TRIM($G2)),TRIM($K2))))) -> Z Retail Backend | AQ2: =IF(TRIM($B2)="","",--OR(TRIM($K2)="Leadership",TRIM($J2)="Leadership")) -> FALSE | AR2: =IF(TRIM($B2)="","",IF(IFERROR(INDEX(Lists!$AQ$2:$AQ$11,MATCH(ROW(),Lists!$AN$2:$AN$11,0)),"")<>"",IFERROR(INDEX(Lists!$AQ$2:$AQ$11,MATCH(ROW(),Lists!$AN$2:$AN$11,0)),""),IF(ISNUMBER(SEARCH("head of ",$C2)),"Head of Technology",IF(ISNUMBER(SEARCH("TDD BP",$C2)),"Business Partner",IF(OR(ISNUMBER(SEARCH("domain architect",$C2)),ISNUMBER(SEARCH("enterprise architect",$C2))),"Domain Architect",IF(ISNUMBER(SEARCH("delivery man",$C2)),"Delivery Manager",IF(OR(ISNUMBER(SEARCH("technology manager",$C2)),ISNUMBER(SEARCH("technology manger",$C2)),ISNUMBER(SEARCH("tech manager",$C2))),"Technology Manager","Squad"))))))) -> Squad | AS2: =IF(TRIM($B2)="","",IFERROR(INDEX(Lists!$AA:$AA,MATCH($AP2,Lists!$Z:$Z,0)),$AP2)) -> Z Retail Backend | AT2: =IF(TRIM($B2)="","",IF(IFERROR(INDEX(Lists!$AP$2:$AP$11,MATCH(ROW(),Lists!$AN$2:$AN$11,0)),"")<>"",IFERROR(INDEX(Lists!$AP$2:$AP$11,MATCH(ROW(),Lists!$AN$2:$AN$11,0)),""),IF(OR(LEFT($AJ2,3)="COE",$AJ2="EGI"),$AP2,IF($AR2<>"Squad",$AR2,$AP2)))) -> Z Retail Backend
A3: 110388 | B3: Adrian Lueng | C3: Quality Assurance | D3: Vedran Jukic | E3: Technology Manager, Retail | F3: Ampol Retail & Z | G3: Ampol Retail | H3: Ampol Retail, Technology | I3: Retail | J3: Network/QSR | K3: Network & QSR | M3: Australia | N3: CIA | O3: 1 | Q3: Permanent - Full Time | T3: 120030 | U3: 120030 | V3: 0.1 | W3: 0.055 | X3: 0.12 | Z3: 0.04 | AA3: =IF(TRIM($B3)="","",IF(N($AU3)>0,$AU3,IF(N($S3)>0,$S3*Lists!$AG$15*(1+N($Z3)),N($U3)*(1+N($V3)+N($W3)+N($X3)+N($Z3))+N($Y3)))) -> 157839.45 | AH3: 374 | AJ3: =IF(TRIM($B3)="","",IF(IFERROR(INDEX(Lists!$AO$2:$AO$11,MATCH(ROW(),Lists!$AN$2:$AN$11,0)),"")<>"",IFERROR(INDEX(Lists!$AO$2:$AO$11,MATCH(ROW(),Lists!$AN$2:$AN$11,0)),""),IFERROR(INDEX(Lists!$U:$U,MATCH(TRIM($I3),Lists!$T:$T,0)),TRIM($I3)))) -> Ampol Retail | AK3: =IF(ISNUMBER(SEARCH("vacant",$B3)),"Vacant","Filled") -> Filled | AL3: =IF($M3="NZ","NZ","AU") -> AU | AM3: =COUNTIF($AJ$2:$AJ3,$AJ3) -> 1 | AN3: =$AJ3&"|"&$AM3 -> Ampol Retail|1 | AP3: =IF(TRIM($B3)="","",IF($AQ3=1,"Leadership",IFERROR(INDEX(Lists!$X:$X,MATCH(TRIM($K3),Lists!$W:$W,0)),IF(OR(TRIM($K3)="",LOWER(TRIM($K3))="na"),IF(TRIM($G3)="","Unassigned",TRIM($G3)),TRIM($K3))))) -> Network & QSR | AQ3: =IF(TRIM($B3)="","",--OR(TRIM($K3)="Leadership",TRIM($J3)="Leadership")) -> FALSE | AR3: =IF(TRIM($B3)="","",IF(IFERROR(INDEX(Lists!$AQ$2:$AQ$11,MATCH(ROW(),Lists!$AN$2:$AN$11,0)),"")<>"",IFERROR(INDEX(Lists!$AQ$2:$AQ$11,MATCH(ROW(),Lists!$AN$2:$AN$11,0)),""),IF(ISNUMBER(SEARCH("head of ",$C3)),"Head of Technology",IF(ISNUMBER(SEARCH("TDD BP",$C3)),"Business Partner",IF(OR(ISNUMBER(SEARCH("domain architect",$C3)),ISNUMBER(SEARCH("enterprise architect",$C3))),"Domain Architect",IF(ISNUMBER(SEARCH("delivery man",$C3)),"Delivery Manager",IF(OR(ISNUMBER(SEARCH("technology manager",$C3)),ISNUMBER(SEARCH("technology manger",$C3)),ISNUMBER(SEARCH("tech manager",$C3))),"Technology Manager","Squad"))))))) -> Squad | AS3: =IF(TRIM($B3)="","",IFERROR(INDEX(Lists!$AA:$AA,MATCH($AP3,Lists!$Z:$Z,0)),$AP3)) -> Network & QSR | AT3: =IF(TRIM($B3)="","",IF(IFERROR(INDEX(Lists!$AP$2:$AP$11,MATCH(ROW(),Lists!$AN$2:$AN$11,0)),"")<>"",IFERROR(INDEX(Lists!$AP$2:$AP$11,MATCH(ROW(),Lists!$AN$2:$AN$11,0)),""),IF(OR(LEFT($AJ3,3)="COE",$AJ3="EGI"),$AP3,IF($AR3<>"Squad",$AR3,$AP3)))) -> Network & QSR
A4: C | B4: Alex Prakhiy | C4: Business Analyst | D4: Vanessa Allen | E4: Delivery Manager, Ampol Retail | F4: Ampol Retail & Z | G4: Ampol Retail | H4: Ampol Retail, Delivery | I4: Ampol Retail | J4: EGI | K4: EGI Retail | M4: Australia | N4: NA | O4: 1 | Q4: cxc | R4: Daily | S4: 1000 | T4: 0 | AA4: =IF(TRIM($B4)="","",IF(N($AU4)>0,$AU4,IF(N($S4)>0,$S4*Lists!$AG$15*(1+N($Z4)),N($U4)*(1+N($V4)+N($W4)+N($X4)+N($Z4))+N($Y4)))) -> 222000 | AH4: 374 | AJ4: =IF(TRIM($B4)="","",IF(IFERROR(INDEX(Lists!$AO$2:$AO$11,MATCH(ROW(),Lists!$AN$2:$AN$11,0)),"")<>"",IFERROR(INDEX(Lists!$AO$2:$AO$11,MATCH(ROW(),Lists!$AN$2:$AN$11,0)),""),IFERROR(INDEX(Lists!$U:$U,MATCH(TRIM($I4),Lists!$T:$T,0)),TRIM($I4)))) -> Ampol Retail | AK4: =IF(ISNUMBER(SEARCH("vacant",$B4)),"Vacant","Filled") -> Filled | AL4: =IF($M4="NZ","NZ","AU") -> AU | AM4: =COUNTIF($AJ$2:$AJ4,$AJ4) -> 2 | AN4: =$AJ4&"|"&$AM4 -> Ampol Retail|2 | AP4: =IF(TRIM($B4)="","",IF($AQ4=1,"Leadership",IFERROR(INDEX(Lists!$X:$X,MATCH(TRIM($K4),Lists!$W:$W,0)),IF(OR(TRIM($K4)="",LOWER(TRIM($K4))="na"),IF(TRIM($G4)="","Unassigned",TRIM($G4)),TRIM($K4))))) -> EGI Retail | AQ4: =IF(TRIM($B4)="","",--OR(TRIM($K4)="Leadership",TRIM($J4)="Leadership")) -> FALSE | AR4: =IF(TRIM($B4)="","",IF(IFERROR(INDEX(Lists!$AQ$2:$AQ$11,MATCH(ROW(),Lists!$AN$2:$AN$11,0)),"")<>"",IFERROR(INDEX(Lists!$AQ$2:$AQ$11,MATCH(ROW(),Lists!$AN$2:$AN$11,0)),""),IF(ISNUMBER(SEARCH("head of ",$C4)),"Head of Technology",IF(ISNUMBER(SEARCH("TDD BP",$C4)),"Business Partner",IF(OR(ISNUMBER(SEARCH("domain architect",$C4)),ISNUMBER(SEARCH("enterprise architect",$C4))),"Domain Architect",IF(ISNUMBER(SEARCH("delivery man",$C4)),"Delivery Manager",IF(OR(ISNUMBER(SEARCH("technology manager",$C4)),ISNUMBER(SEARCH("technology manger",$C4)),ISNUMBER(SEARCH("tech manager",$C4))),"Technology Manager","Squad"))))))) -> Squad | AS4: =IF(TRIM($B4)="","",IFERROR(INDEX(Lists!$AA:$AA,MATCH($AP4,Lists!$Z:$Z,0)),$AP4)) -> EGI Retail | AT4: =IF(TRIM($B4)="","",IF(IFERROR(INDEX(Lists!$AP$2:$AP$11,MATCH(ROW(),Lists!$AN$2:$AN$11,0)),"")<>"",IFERROR(INDEX(Lists!$AP$2:$AP$11,MATCH(ROW(),Lists!$AN$2:$AN$11,0)),""),IF(OR(LEFT($AJ4,3)="COE",$AJ4="EGI"),$AP4,IF($AR4<>"Squad",$AR4,$AP4)))) -> EGI Retail
A5: 99999101643 | B5: Alex Sutherland | C5: Site Systems Analyst | D5: Callan McLaughlin | E5: Technology Manager, Site Systems | F5: Ampol Retail & Z | G5: Z & Group Retail | H5: Z & Group Retail, Site Systems | I5: Z | J5: Z Customer | K5: Site Systems | M5: NZ | N5: CDB | O5: 1 | Q5: Permanent - Full Time | T5: 86540 | U5: 79616.8 | V5: 0.1 | X5: 0.05 | Y5: 2910 | Z5: 0.03 | AA5: =IF(TRIM($B5)="","",IF(N($AU5)>0,$AU5,IF(N($S5)>0,$S5*Lists!$AG$15*(1+N($Z5)),N($U5)*(1+N($V5)+N($W5)+N($X5)+N($Z5))+N($Y5)))) -> 96857.824 | AJ5: =IF(TRIM($B5)="","",IF(IFERROR(INDEX(Lists!$AO$2:$AO$11,MATCH(ROW(),Lists!$AN$2:$AN$11,0)),"")<>"",IFERROR(INDEX(Lists!$AO$2:$AO$11,MATCH(ROW(),Lists!$AN$2:$AN$11,0)),""),IFERROR(INDEX(Lists!$U:$U,MATCH(TRIM($I5),Lists!$T:$T,0)),TRIM($I5)))) -> Z Retail | AK5: =IF(ISNUMBER(SEARCH("vacant",$B5)),"Vacant","Filled") -> Filled | AL5: =IF($M5="NZ","NZ","AU") -> NZ | AM5: =COUNTIF($AJ$2:$AJ5,$AJ5) -> 2 | AN5: =$AJ5&"|"&$AM5 -> Z Retail|2 | AP5: =IF(TRIM($B5)="","",IF($AQ5=1,"Leadership",IFERROR(INDEX(Lists!$X:$X,MATCH(TRIM($K5),Lists!$W:$W,0)),IF(OR(TRIM($K5)="",LOWER(TRIM($K5))="na"),IF(TRIM($G5)="","Unassigned",TRIM($G5)),TRIM($K5))))) -> Site Systems | AQ5: =IF(TRIM($B5)="","",--OR(TRIM($K5)="Leadership",TRIM($J5)="Leadership")) -> FALSE | AR5: =IF(TRIM($B5)="","",IF(IFERROR(INDEX(Lists!$AQ$2:$AQ$11,MATCH(ROW(),Lists!$AN$2:$AN$11,0)),"")<>"",IFERROR(INDEX(Lists!$AQ$2:$AQ$11,MATCH(ROW(),Lists!$AN$2:$AN$11,0)),""),IF(ISNUMBER(SEARCH("head of ",$C5)),"Head of Technology",IF(ISNUMBER(SEARCH("TDD BP",$C5)),"Business Partner",IF(OR(ISNUMBER(SEARCH("domain architect",$C5)),ISNUMBER(SEARCH("enterprise architect",$C5))),"Domain Architect",IF(ISNUMBER(SEARCH("delivery man",$C5)),"Delivery Manager",IF(OR(ISNUMBER(SEARCH("technology manager",$C5)),ISNUMBER(SEARCH("technology manger",$C5)),ISNUMBER(SEARCH("tech manager",$C5))),"Technology Manager","Squad"))))))) -> Squad | AS5: =IF(TRIM($B5)="","",IFERROR(INDEX(Lists!$AA:$AA,MATCH($AP5,Lists!$Z:$Z,0)),$AP5)) -> Site Systems | AT5: =IF(TRIM($B5)="","",IF(IFERROR(INDEX(Lists!$AP$2:$AP$11,MATCH(ROW(),Lists!$AN$2:$AN$11,0)),"")<>"",IFERROR(INDEX(Lists!$AP$2:$AP$11,MATCH(ROW(),Lists!$AN$2:$AN$11,0)),""),IF(OR(LEFT($AJ5,3)="COE",$AJ5="EGI"),$AP5,IF($AR5<>"Squad",$AR5,$AP5)))) -> Site Systems
A6: 99999101548 | B6: Allana Arbuckle | C6: Business Analyst | D6: Vacant | E6: Delivery Manager, Z and Retail Data | F6: Ampol Retail & Z | G6: Z & Group Retail | H6: Z & Group Retail, Delivery | I6: Z | J6: Z Customer | K6: Z Retail Backend | M6: NZ | N6: CDB | O6: 1 | Q6: Permanent - Full Time | T6: 100900 | U6: 92828 | V6: 0.1 | X6: 0.05 | Y6: 2910 | Z6: 0.03 | AA6: =IF(TRIM($B6)="","",IF(N($AU6)>0,$AU6,IF(N($S6)>0,$S6*Lists!$AG$15*(1+N($Z6)),N($U6)*(1+N($V6)+N($W6)+N($X6)+N($Z6))+N($Y6)))) -> 112447.04 | AJ6: =IF(TRIM($B6)="","",IF(IFERROR(INDEX(Lists!$AO$2:$AO$11,MATCH(ROW(),Lists!$AN$2:$AN$11,0)),"")<>"",IFERROR(INDEX(Lists!$AO$2:$AO$11,MATCH(ROW(),Lists!$AN$2:$AN$11,0)),""),IFERROR(INDEX(Lists!$U:$U,MATCH(TRIM($I6),Lists!$T:$T,0)),TRIM($I6)))) -> Z Retail | AK6: =IF(ISNUMBER(SEARCH("vacant",$B6)),"Vacant","Filled") -> Filled | AL6: =IF($M6="NZ","NZ","AU") -> NZ | AM6: =COUNTIF($AJ$2:$AJ6,$AJ6) -> 3 | AN6: =$AJ6&"|"&$AM6 -> Z Retail|3 | AP6: =IF(TRIM($B6)="","",IF($AQ6=1,"Leadership",IFERROR(INDEX(Lists!$X:$X,MATCH(TRIM($K6),Lists!$W:$W,0)),IF(OR(TRIM($K6)="",LOWER(TRIM($K6))="na"),IF(TRIM($G6)="","Unassigned",TRIM($G6)),TRIM($K6))))) -> Z Retail Backend | AQ6: =IF(TRIM($B6)="","",--OR(TRIM($K6)="Leadership",TRIM($J6)="Leadership")) -> FALSE | AR6: =IF(TRIM($B6)="","",IF(IFERROR(INDEX(Lists!$AQ$2:$AQ$11,MATCH(ROW(),Lists!$AN$2:$AN$11,0)),"")<>"",IFERROR(INDEX(Lists!$AQ$2:$AQ$11,MATCH(ROW(),Lists!$AN$2:$AN$11,0)),""),IF(ISNUMBER(SEARCH("head of ",$C6)),"Head of Technology",IF(ISNUMBER(SEARCH("TDD BP",$C6)),"Business Partner",IF(OR(ISNUMBER(SEARCH("domain architect",$C6)),ISNUMBER(SEARCH("enterprise architect",$C6))),"Domain Architect",IF(ISNUMBER(SEARCH("delivery man",$C6)),"Delivery Manager",IF(OR(ISNUMBER(SEARCH("technology manager",$C6)),ISNUMBER(SEARCH("technology manger",$C6)),ISNUMBER(SEARCH("tech manager",$C6))),"Technology Manager","Squad"))))))) -> Squad | AS6: =IF(TRIM($B6)="","",IFERROR(INDEX(Lists!$AA:$AA,MATCH($AP6,Lists!$Z:$Z,0)),$AP6)) -> Z Retail Backend | AT6: =IF(TRIM($B6)="","",IF(IFERROR(INDEX(Lists!$AP$2:$AP$11,MATCH(ROW(),Lists!$AN$2:$AN$11,0)),"")<>"",IFERROR(INDEX(Lists!$AP$2:$AP$11,MATCH(ROW(),Lists!$AN$2:$AN$11,0)),""),IF(OR(LEFT($AJ6,3)="COE",$AJ6="EGI"),$AP6,IF($AR6<>"Squad",$AR6,$AP6)))) -> Z Retail Backend
A7: 4534 | B7: Andrew Whitford | C7: Field Systems Operations Lead - WA | D7: Ephriam Adan | E7: Manager, AU Retail Operations | F7: Ampol Retail & Z | G7: Ampol Retail | H7: Ampol Retail, Technology | I7: Retail | J7: Store Operations | K7: Store Operations | M7: Australia | N7: CIA | O7: 1 | Q7: Permanent - Full Time | T7: 124740 | U7: 124740 | V7: 0.1 | W7: 0.055 | X7: 0.12 | Z7: 0.04 | AA7: =IF(TRIM($B7)="","",IF(N($AU7)>0,$AU7,IF(N($S7)>0,$S7*Lists!$AG$15*(1+N($Z7)),N($U7)*(1+N($V7)+N($W7)+N($X7)+N($Z7))+N($Y7)))) -> 164033.1 | AJ7: =IF(TRIM($B7)="","",IF(IFERROR(INDEX(Lists!$AO$2:$AO$11,MATCH(ROW(),Lists!$AN$2:$AN$11,0)),"")<>"",IFERROR(INDEX(Lists!$AO$2:$AO$11,MATCH(ROW(),Lists!$AN$2:$AN$11,0)),""),IFERROR(INDEX(Lists!$U:$U,MATCH(TRIM($I7),Lists!$T:$T,0)),TRIM($I7)))) -> Ampol Retail | AK7: =IF(ISNUMBER(SEARCH("vacant",$B7)),"Vacant","Filled") -> Filled | AL7: =IF($M7="NZ","NZ","AU") -> AU | AM7: =COUNTIF($AJ$2:$AJ7,$AJ7) -> 3 | AN7: =$AJ7&"|"&$AM7 -> Ampol Retail|3 | AP7: =IF(TRIM($B7)="","",IF($AQ7=1,"Leadership",IFERROR(INDEX(Lists!$X:$X,MATCH(TRIM($K7),Lists!$W:$W,0)),IF(OR(TRIM($K7)="",LOWER(TRIM($K7))="na"),IF(TRIM($G7)="","Unassigned",TRIM($G7)),TRIM($K7))))) -> Store Operations | AQ7: =IF(TRIM($B7)="","",--OR(TRIM($K7)="Leadership",TRIM($J7)="Leadership")) -> FALSE | AR7: =IF(TRIM($B7)="","",IF(IFERROR(INDEX(Lists!$AQ$2:$AQ$11,MATCH(ROW(),Lists!$AN$2:$AN$11,0)),"")<>"",IFERROR(INDEX(Lists!$AQ$2:$AQ$11,MATCH(ROW(),Lists!$AN$2:$AN$11,0)),""),IF(ISNUMBER(SEARCH("head of ",$C7)),"Head of Technology",IF(ISNUMBER(SEARCH("TDD BP",$C7)),"Business Partner",IF(OR(ISNUMBER(SEARCH("domain architect",$C7)),ISNUMBER(SEARCH("enterprise architect",$C7))),"Domain Architect",IF(ISNUMBER(SEARCH("delivery man",$C7)),"Delivery Manager",IF(OR(ISNUMBER(SEARCH("technology manager",$C7)),ISNUMBER(SEARCH("technology manger",$C7)),ISNUMBER(SEARCH("tech manager",$C7))),"Technology Manager","Squad"))))))) -> Squad | AS7: =IF(TRIM($B7)="","",IFERROR(INDEX(Lists!$AA:$AA,MATCH($AP7,Lists!$Z:$Z,0)),$AP7)) -> Store Operations | AT7: =IF(TRIM($B7)="","",IF(IFERROR(INDEX(Lists!$AP$2:$AP$11,MATCH(ROW(),Lists!$AN$2:$AN$11,0)),"")<>"",IFERROR(INDEX(Lists!$AP$2:$AP$11,MATCH(ROW(),Lists!$AN$2:$AN$11,0)),""),IF(OR(LEFT($AJ7,3)="COE",$AJ7="EGI"),$AP7,IF($AR7<>"Squad",$AR7,$AP7)))) -> Store Operations
A8: 111451 | B8: Aniket Banerji | C8: Deployment Lead | D8: Matthew Patane | E8: Release & Deployment Manager | F8: Ampol Retail & Z | G8: Ampol Retail | H8: Ampol Retail, Technology | I8: Retail | J8: Store Operations | K8: Deployment | M8: Australia | N8: CIB | O8: 1 | Q8: Temporary - Full Time | T8: 150000 | U8: 150000 | V8: 0.12 | W8: 0.055 | X8: 0.12 | Z8: 0.04 | AA8: =IF(TRIM($B8)="","",IF(N($AU8)>0,$AU8,IF(N($S8)>0,$S8*Lists!$AG$15*(1+N($Z8)),N($U8)*(1+N($V8)+N($W8)+N($X8)+N($Z8))+N($Y8)))) -> 200250 | AJ8: =IF(TRIM($B8)="","",IF(IFERROR(INDEX(Lists!$AO$2:$AO$11,MATCH(ROW(),Lists!$AN$2:$AN$11,0)),"")<>"",IFERROR(INDEX(Lists!$AO$2:$AO$11,MATCH(ROW(),Lists!$AN$2:$AN$11,0)),""),IFERROR(INDEX(Lists!$U:$U,MATCH(TRIM($I8),Lists!$T:$T,0)),TRIM($I8)))) -> Ampol Retail | AK8: =IF(ISNUMBER(SEARCH("vacant",$B8)),"Vacant","Filled") -> Filled | AL8: =IF($M8="NZ","NZ","AU") -> AU | AM8: =COUNTIF($AJ$2:$AJ8,$AJ8) -> 4 | AN8: =$AJ8&"|"&$AM8 -> Ampol Retail|4 | AP8: =IF(TRIM($B8)="","",IF($AQ8=1,"Leadership",IFERROR(INDEX(Lists!$X:$X,MATCH(TRIM($K8),Lists!$W:$W,0)),IF(OR(TRIM($K8)="",LOWER(TRIM($K8))="na"),IF(TRIM($G8)="","Unassigned",TRIM($G8)),TRIM($K8))))) -> Deployment | AQ8: =IF(TRIM($B8)="","",--OR(TRIM($K8)="Leadership",TRIM($J8)="Leadership")) -> FALSE | AR8: =IF(TRIM($B8)="","",IF(IFERROR(INDEX(Lists!$AQ$2:$AQ$11,MATCH(ROW(),Lists!$AN$2:$AN$11,0)),"")<>"",IFERROR(INDEX(Lists!$AQ$2:$AQ$11,MATCH(ROW(),Lists!$AN$2:$AN$11,0)),""),IF(ISNUMBER(SEARCH("head of ",$C8)),"Head of Technology",IF(ISNUMBER(SEARCH("TDD BP",$C8)),"Business Partner",IF(OR(ISNUMBER(SEARCH("domain architect",$C8)),ISNUMBER(SEARCH("enterprise architect",$C8))),"Domain Architect",IF(ISNUMBER(SEARCH("delivery man",$C8)),"Delivery Manager",IF(OR(ISNUMBER(SEARCH("technology manager",$C8)),ISNUMBER(SEARCH("technology manger",$C8)),ISNUMBER(SEARCH("tech manager",$C8))),"Technology Manager","Squad"))))))) -> Squad | AS8: =IF(TRIM($B8)="","",IFERROR(INDEX(Lists!$AA:$AA,MATCH($AP8,Lists!$Z:$Z,0)),$AP8)) -> Deployment | AT8: =IF(TRIM($B8)="","",IF(IFERROR(INDEX(Lists!$AP$2:$AP$11,MATCH(ROW(),Lists!$AN$2:$AN$11,0)),"")<>"",IFERROR(INDEX(Lists!$AP$2:$AP$11,MATCH(ROW(),Lists!$AN$2:$AN$11,0)),""),IF(OR(LEFT($AJ8,3)="COE",$AJ8="EGI"),$AP8,IF($AR8<>"Squad",$AR8,$AP8)))) -> Deployment
A9: 99999101214 | B9: Anna Koot | C9: Senior Business Analyst | D9: Vacant | E9: Delivery Manager, Z and Retail Data | F9: Ampol Retail & Z | G9: Z & Group Retail | H9: Z & Group Retail, Delivery | I9: Z | J9: Z Supply | K9: Z Supply | M9: NZ | N9: CIA | O9: 1 | Q9: Permanent - Full Time | T9: 133320 | U9: 122654.4 | V9: 0.15 | X9: 0.05 | Y9: 2910 | Z9: 0.03 | AA9: =IF(TRIM($B9)="","",IF(N($AU9)>0,$AU9,IF(N($S9)>0,$S9*Lists!$AG$15*(1+N($Z9)),N($U9)*(1+N($V9)+N($W9)+N($X9)+N($Z9))+N($Y9)))) -> 153774.91 | AJ9: =IF(TRIM($B9)="","",IF(IFERROR(INDEX(Lists!$AO$2:$AO$11,MATCH(ROW(),Lists!$AN$2:$AN$11,0)),"")<>"",IFERROR(INDEX(Lists!$AO$2:$AO$11,MATCH(ROW(),Lists!$AN$2:$AN$11,0)),""),IFERROR(INDEX(Lists!$U:$U,MATCH(TRIM($I9),Lists!$T:$T,0)),TRIM($I9)))) -> Z Retail | AK9: =IF(ISNUMBER(SEARCH("vacant",$B9)),"Vacant","Filled") -> Filled | AL9: =IF($M9="NZ","NZ","AU") -> NZ | AM9: =COUNTIF($AJ$2:$AJ9,$AJ9) -> 4 | AN9: =$AJ9&"|"&$AM9 -> Z Retail|4 | AP9: =IF(TRIM($B9)="","",IF($AQ9=1,"Leadership",IFERROR(INDEX(Lists!$X:$X,MATCH(TRIM($K9),Lists!$W:$W,0)),IF(OR(TRIM($K9)="",LOWER(TRIM($K9))="na"),IF(TRIM($G9)="","Unassigned",TRIM($G9)),TRIM($K9))))) -> Z Supply | AQ9: =IF(TRIM($B9)="","",--OR(TRIM($K9)="Leadership",TRIM($J9)="Leadership")) -> FALSE | AR9: =IF(TRIM($B9)="","",IF(IFERROR(INDEX(Lists!$AQ$2:$AQ$11,MATCH(ROW(),Lists!$AN$2:$AN$11,0)),"")<>"",IFERROR(INDEX(Lists!$AQ$2:$AQ$11,MATCH(ROW(),Lists!$AN$2:$AN$11,0)),""),IF(ISNUMBER(SEARCH("head of ",$C9)),"Head of Technology",IF(ISNUMBER(SEARCH("TDD BP",$C9)),"Business Partner",IF(OR(ISNUMBER(SEARCH("domain architect",$C9)),ISNUMBER(SEARCH("enterprise architect",$C9))),"Domain Architect",IF(ISNUMBER(SEARCH("delivery man",$C9)),"Delivery Manager",IF(OR(ISNUMBER(SEARCH("technology manager",$C9)),ISNUMBER(SEARCH("technology manger",$C9)),ISNUMBER(SEARCH("tech manager",$C9))),"Technology Manager","Squad"))))))) -> Squad | AS9: =IF(TRIM($B9)="","",IFERROR(INDEX(Lists!$AA:$AA,MATCH($AP9,Lists!$Z:$Z,0)),$AP9)) -> Z Supply | AT9: =IF(TRIM($B9)="","",IF(IFERROR(INDEX(Lists!$AP$2:$AP$11,MATCH(ROW(),Lists!$AN$2:$AN$11,0)),"")<>"",IFERROR(INDEX(Lists!$AP$2:$AP$11,MATCH(ROW(),Lists!$AN$2:$AN$11,0)),""),IF(OR(LEFT($AJ9,3)="COE",$AJ9="EGI"),$AP9,IF($AR9<>"Squad",$AR9,$AP9)))) -> Z Supply
A10: 9999970029518 | B10: Anne Pretorius | C10: Lead Business Analyst | D10: Vacant | E10: Delivery Manager, Z and Retail Data | F10: Ampol Retail & Z | G10: Z & Group Retail | H10: Z & Group Retail, Delivery | I10: Ampol Retail | J10: EGI | K10: EGI Retail | M10: NZ | N10: CIC | O10: 0.8 | Q10: Permanent - Part Time | T10: 170290 | U10: 156666.8 | V10: 0.15 | X10: 0.05 | Y10: 2910 | Z10: 0.03 | AA10: =IF(TRIM($B10)="","",IF(N($AU10)>0,$AU10,IF(N($S10)>0,$S10*Lists!$AG$15*(1+N($Z10)),N($U10)*(1+N($V10)+N($W10)+N($X10)+N($Z10))+N($Y10)))) -> 195610.16 | AJ10: =IF(TRIM($B10)="","",IF(IFERROR(INDEX(Lists!$AO$2:$AO$11,MATCH(ROW(),Lists!$AN$2:$AN$11,0)),"")<>"",IFERROR(INDEX(Lists!$AO$2:$AO$11,MATCH(ROW(),Lists!$AN$2:$AN$11,0)),""),IFERROR(INDEX(Lists!$U:$U,MATCH(TRIM($I10),Lists!$T:$T,0)),TRIM($I10)))) -> Ampol Retail | AK10: =IF(ISNUMBER(SEARCH("vacant",$B10)),"Vacant","Filled") -> Filled | AL10: =IF($M10="NZ","NZ","AU") -> NZ | AM10: =COUNTIF($AJ$2:$AJ10,$AJ10) -> 5 | AN10: =$AJ10&"|"&$AM10 -> Ampol Retail|5 | AP10: =IF(TRIM($B10)="","",IF($AQ10=1,"Leadership",IFERROR(INDEX(Lists!$X:$X,MATCH(TRIM($K10),Lists!$W:$W,0)),IF(OR(TRIM($K10)="",LOWER(TRIM($K10))="na"),IF(TRIM($G10)="","Unassigned",TRIM($G10)),TRIM($K10))))) -> EGI Retail | AQ10: =IF(TRIM($B10)="","",--OR(TRIM($K10)="Leadership",TRIM($J10)="Leadership")) -> FALSE | AR10: =IF(TRIM($B10)="","",IF(IFERROR(INDEX(Lists!$AQ$2:$AQ$11,MATCH(ROW(),Lists!$AN$2:$AN$11,0)),"")<>"",IFERROR(INDEX(Lists!$AQ$2:$AQ$11,MATCH(ROW(),Lists!$AN$2:$AN$11,0)),""),IF(ISNUMBER(SEARCH("head of ",$C10)),"Head of Technology",IF(ISNUMBER(SEARCH("TDD BP",$C10)),"Business Partner",IF(OR(ISNUMBER(SEARCH("domain architect",$C10)),ISNUMBER(SEARCH("enterprise architect",$C10))),"Domain Architect",IF(ISNUMBER(SEARCH("delivery man",$C10)),"Delivery Manager",IF(OR(ISNUMBER(SEARCH("technology manager",$C10)),ISNUMBER(SEARCH("technology manger",$C10)),ISNUMBER(SEARCH("tech manager",$C10))),"Technology Manager","Squad"))))))) -> Squad | AS10: =IF(TRIM($B10)="","",IFERROR(INDEX(Lists!$AA:$AA,MATCH($AP10,Lists!$Z:$Z,0)),$AP10)) -> EGI Retail | AT10: =IF(TRIM($B10)="","",IF(IFERROR(INDEX(Lists!$AP$2:$AP$11,MATCH(ROW(),Lists!$AN$2:$AN$11,0)),"")<>"",IFERROR(INDEX(Lists!$AP$2:$AP$11,MATCH(ROW(),Lists!$AN$2:$AN$11,0)),""),IF(OR(LEFT($AJ10,3)="COE",$AJ10="EGI"),$AP10,IF($AR10<>"Squad",$AR10,$AP10)))) -> EGI Retail
A11: 110197 | B11: Anthony Dumbrell | C11: Technology & Lab Specialist Stores | D11: Vedran Jukic | E11: Technology Manager, Retail | F11: Ampol Retail & Z | G11: Ampol Retail | H11: Ampol Retail, Technology | I11: Retail | J11: Store Operations | K11: Deployment | M11: Australia | N11: CIB | O11: 1 | Q11: Permanent - Full Time | T11: 154360 | U11: 154360 | V11: 0.12 | W11: 0.055 | X11: 0.12 | Z11: 0.04 | AA11: =IF(TRIM($B11)="","",IF(N($AU11)>0,$AU11,IF(N($S11)>0,$S11*Lists!$AG$15*(1+N($Z11)),N($U11)*(1+N($V11)+N($W11)+N($X11)+N($Z11))+N($Y11)))) -> 206070.6 | AJ11: =IF(TRIM($B11)="","",IF(IFERROR(INDEX(Lists!$AO$2:$AO$11,MATCH(ROW(),Lists!$AN$2:$AN$11,0)),"")<>"",IFERROR(INDEX(Lists!$AO$2:$AO$11,MATCH(ROW(),Lists!$AN$2:$AN$11,0)),""),IFERROR(INDEX(Lists!$U:$U,MATCH(TRIM($I11),Lists!$T:$T,0)),TRIM($I11)))) -> Ampol Retail | AK11: =IF(ISNUMBER(SEARCH("vacant",$B11)),"Vacant","Filled") -> Filled | AL11: =IF($M11="NZ","NZ","AU") -> AU | AM11: =COUNTIF($AJ$2:$AJ11,$AJ11) -> 6 | AN11: =$AJ11&"|"&$AM11 -> Ampol Retail|6 | AP11: =IF(TRIM($B11)="","",IF($AQ11=1,"Leadership",IFERROR(INDEX(Lists!$X:$X,MATCH(TRIM($K11),Lists!$W:$W,0)),IF(OR(TRIM($K11)="",LOWER(TRIM($K11))="na"),IF(TRIM($G11)="","Unassigned",TRIM($G11)),TRIM($K11))))) -> Deployment | AQ11: =IF(TRIM($B11)="","",--OR(TRIM($K11)="Leadership",TRIM($J11)="Leadership")) -> FALSE | AR11: =IF(TRIM($B11)="","",IF(IFERROR(INDEX(Lists!$AQ$2:$AQ$11,MATCH(ROW(),Lists!$AN$2:$AN$11,0)),"")<>"",IFERROR(INDEX(Lists!$AQ$2:$AQ$11,MATCH(ROW(),Lists!$AN$2:$AN$11,0)),""),IF(ISNUMBER(SEARCH("head of ",$C11)),"Head of Technology",IF(ISNUMBER(SEARCH("TDD BP",$C11)),"Business Partner",IF(OR(ISNUMBER(SEARCH("domain architect",$C11)),ISNUMBER(SEARCH("enterprise architect",$C11))),"Domain Architect",IF(ISNUMBER(SEARCH("delivery man",$C11)),"Delivery Manager",IF(OR(ISNUMBER(SEARCH("technology manager",$C11)),ISNUMBER(SEARCH("technology manger",$C11)),ISNUMBER(SEARCH("tech manager",$C11))),"Technology Manager","Squad"))))))) -> Squad | AS11: =IF(TRIM($B11)="","",IFERROR(INDEX(Lists!$AA:$AA,MATCH($AP11,Lists!$Z:$Z,0)),$AP11)) -> Deployment | AT11: =IF(TRIM($B11)="","",IF(IFERROR(INDEX(Lists!$AP$2:$AP$11,MATCH(ROW(),Lists!$AN$2:$AN$11,0)),"")<>"",IFERROR(INDEX(Lists!$AP$2:$AP$11,MATCH(ROW(),Lists!$AN$2:$AN$11,0)),""),IF(OR(LEFT($AJ11,3)="COE",$AJ11="EGI"),$AP11,IF($AR11<>"Squad",$AR11,$AP11)))) -> Deployment
A12: 99999101647 | B12: Ash Muthumala | C12: Senior QA Analyst | D12: Vacant | E12: Technology Manager, Data | F12: Ampol Retail & Z | G12: Z & Group Retail | H12: Z & Group Retail, Data | I12: Z | J12: Z Customer & Z Supply | K12: Data - NZ | M12: NZ | N12: CIA | O12: 1 | Q12: Permanent - Full Time | T12: 121830 | U12: 112083.6 | V12: 0.15 | X12: 0.05 | Y12: 2910 | Z12: 0.03 | AA12: =IF(TRIM($B12)="","",IF(N($AU12)>0,$AU12,IF(N($S12)>0,$S12*Lists!$AG$15*(1+N($Z12)),N($U12)*(1+N($V12)+N($W12)+N($X12)+N($Z12))+N($Y12)))) -> 140772.83 | AJ12: =IF(TRIM($B12)="","",IF(IFERROR(INDEX(Lists!$AO$2:$AO$11,MATCH(ROW(),Lists!$AN$2:$AN$11,0)),"")<>"",IFERROR(INDEX(Lists!$AO$2:$AO$11,MATCH(ROW(),Lists!$AN$2:$AN$11,0)),""),IFERROR(INDEX(Lists!$U:$U,MATCH(TRIM($I12),Lists!$T:$T,0)),TRIM($I12)))) -> Z Retail | AK12: =IF(ISNUMBER(SEARCH("vacant",$B12)),"Vacant","Filled") -> Filled | AL12: =IF($M12="NZ","NZ","AU") -> NZ | AM12: =COUNTIF($AJ$2:$AJ12,$AJ12) -> 5 | AN12: =$AJ12&"|"&$AM12 -> Z Retail|5 | AP12: =IF(TRIM($B12)="","",IF($AQ12=1,"Leadership",IFERROR(INDEX(Lists!$X:$X,MATCH(TRIM($K12),Lists!$W:$W,0)),IF(OR(TRIM($K12)="",LOWER(TRIM($K12))="na"),IF(TRIM($G12)="","Unassigned",TRIM($G12)),TRIM($K12))))) -> Data NZ | AQ12: =IF(TRIM($B12)="","",--OR(TRIM($K12)="Leadership",TRIM($J12)="Leadership")) -> FALSE | AR12: =IF(TRIM($B12)="","",IF(IFERROR(INDEX(Lists!$AQ$2:$AQ$11,MATCH(ROW(),Lists!$AN$2:$AN$11,0)),"")<>"",IFERROR(INDEX(Lists!$AQ$2:$AQ$11,MATCH(ROW(),Lists!$AN$2:$AN$11,0)),""),IF(ISNUMBER(SEARCH("head of ",$C12)),"Head of Technology",IF(ISNUMBER(SEARCH("TDD BP",$C12)),"Business Partner",IF(OR(ISNUMBER(SEARCH("domain architect",$C12)),ISNUMBER(SEARCH("enterprise architect",$C12))),"Domain Architect",IF(ISNUMBER(SEARCH("delivery man",$C12)),"Delivery Manager",IF(OR(ISNUMBER(SEARCH("technology manager",$C12)),ISNUMBER(SEARCH("technology manger",$C12)),ISNUMBER(SEARCH("tech manager",$C12))),"Technology Manager","Squad"))))))) -> Squad | AS12: =IF(TRIM($B12)="","",IFERROR(INDEX(Lists!$AA:$AA,MATCH($AP12,Lists!$Z:$Z,0)),$AP12)) -> Data NZ | AT12: =IF(TRIM($B12)="","",IF(IFERROR(INDEX(Lists!$AP$2:$AP$11,MATCH(ROW(),Lists!$AN$2:$AN$11,0)),"")<>"",IFERROR(INDEX(Lists!$AP$2:$AP$11,MATCH(ROW(),Lists!$AN$2:$AN$11,0)),""),IF(OR(LEFT($AJ12,3)="COE",$AJ12="EGI"),$AP12,IF($AR12<>"Squad",$AR12,$AP12)))) -> Data NZ
A13: 97784 | B13: Balaji Murugan | C13: Delivery Lead | D13: Vanessa Allen | E13: Delivery Manager, Ampol Retail | F13: Ampol Retail & Z | G13: Ampol Retail | H13: Ampol Retail, Delivery | I13: Retail | J13: AMPOS | K13: AmPos | M13: Australia | N13: CIC | O13: 1 | Q13: Permanent - Full Time | T13: 178018 | U13: 178018 | V13: 0.12 | W13: 0.055 | X13: 0.12 | Z13: 0.04 | AA13: =IF(TRIM($B13)="","",IF(N($AU13)>0,$AU13,IF(N($S13)>0,$S13*Lists!$AG$15*(1+N($Z13)),N($U13)*(1+N($V13)+N($W13)+N($X13)+N($Z13))+N($Y13)))) -> 237654.03 | AJ13: =IF(TRIM($B13)="","",IF(IFERROR(INDEX(Lists!$AO$2:$AO$11,MATCH(ROW(),Lists!$AN$2:$AN$11,0)),"")<>"",IFERROR(INDEX(Lists!$AO$2:$AO$11,MATCH(ROW(),Lists!$AN$2:$AN$11,0)),""),IFERROR(INDEX(Lists!$U:$U,MATCH(TRIM($I13),Lists!$T:$T,0)),TRIM($I13)))) -> Ampol Retail | AK13: =IF(ISNUMBER(SEARCH("vacant",$B13)),"Vacant","Filled") -> Filled | AL13: =IF($M13="NZ","NZ","AU") -> AU | AM13: =COUNTIF($AJ$2:$AJ13,$AJ13) -> 7 | AN13: =$AJ13&"|"&$AM13 -> Ampol Retail|7 | AP13: =IF(TRIM($B13)="","",IF($AQ13=1,"Leadership",IFERROR(INDEX(Lists!$X:$X,MATCH(TRIM($K13),Lists!$W:$W,0)),IF(OR(TRIM($K13)="",LOWER(TRIM($K13))="na"),IF(TRIM($G13)="","Unassigned",TRIM($G13)),TRIM($K13))))) -> AmPOS | AQ13: =IF(TRIM($B13)="","",--OR(TRIM($K13)="Leadership",TRIM($J13)="Leadership")) -> FALSE | AR13: =IF(TRIM($B13)="","",IF(IFERROR(INDEX(Lists!$AQ$2:$AQ$11,MATCH(ROW(),Lists!$AN$2:$AN$11,0)),"")<>"",IFERROR(INDEX(Lists!$AQ$2:$AQ$11,MATCH(ROW(),Lists!$AN$2:$AN$11,0)),""),IF(ISNUMBER(SEARCH("head of ",$C13)),"Head of Technology",IF(ISNUMBER(SEARCH("TDD BP",$C13)),"Business Partner",IF(OR(ISNUMBER(SEARCH("domain architect",$C13)),ISNUMBER(SEARCH("enterprise architect",$C13))),"Domain Architect",IF(ISNUMBER(SEARCH("delivery man",$C13)),"Delivery Manager",IF(OR(ISNUMBER(SEARCH("technology manager",$C13)),ISNUMBER(SEARCH("technology manger",$C13)),ISNUMBER(SEARCH("tech manager",$C13))),"Technology Manager","Squad"))))))) -> Squad | AS13: =IF(TRIM($B13)="","",IFERROR(INDEX(Lists!$AA:$AA,MATCH($AP13,Lists!$Z:$Z,0)),$AP13)) -> AmPOS | AT13: =IF(TRIM($B13)="","",IF(IFERROR(INDEX(Lists!$AP$2:$AP$11,MATCH(ROW(),Lists!$AN$2:$AN$11,0)),"")<>"",IFERROR(INDEX(Lists!$AP$2:$AP$11,MATCH(ROW(),Lists!$AN$2:$AN$11,0)),""),IF(OR(LEFT($AJ13,3)="COE",$AJ13="EGI"),$AP13,IF($AR13<>"Squad",$AR13,$AP13)))) -> AmPOS
A14: 97847 | B14: Beenu Murali | C14: Quality Assurance | D14: Vacant | E14: Lead Quality Assurance | F14: Ampol Retail & Z | G14: Ampol Retail | H14: Ampol Retail, Store Platforms | I14: Retail | J14: Store Operations | K14: Payments | M14: Australia | N14: CDC | O14: 1 | Q14: Permanent - Full Time | T14: 111090 | U14: 111090 | V14: 0.1 | W14: 0.055 | X14: 0.12 | Z14: 0.04 | AA14: =IF(TRIM($B14)="","",IF(N($AU14)>0,$AU14,IF(N($S14)>0,$S14*Lists!$AG$15*(1+N($Z14)),N($U14)*(1+N($V14)+N($W14)+N($X14)+N($Z14))+N($Y14)))) -> 146083.35 | AJ14: =IF(TRIM($B14)="","",IF(IFERROR(INDEX(Lists!$AO$2:$AO$11,MATCH(ROW(),Lists!$AN$2:$AN$11,0)),"")<>"",IFERROR(INDEX(Lists!$AO$2:$AO$11,MATCH(ROW(),Lists!$AN$2:$AN$11,0)),""),IFERROR(INDEX(Lists!$U:$U,MATCH(TRIM($I14),Lists!$T:$T,0)),TRIM($I14)))) -> Ampol Retail | AK14: =IF(ISNUMBER(SEARCH("vacant",$B14)),"Vacant","Filled") -> Filled | AL14: =IF($M14="NZ","NZ","AU") -> AU | AM14: =COUNTIF($AJ$2:$AJ14,$AJ14) -> 8 | AN14: =$AJ14&"|"&$AM14 -> Ampol Retail|8 | AP14: =IF(TRIM($B14)="","",IF($AQ14=1,"Leadership",IFERROR(INDEX(Lists!$X:$X,MATCH(TRIM($K14),Lists!$W:$W,0)),IF(OR(TRIM($K14)="",LOWER(TRIM($K14))="na"),IF(TRIM($G14)="","Unassigned",TRIM($G14)),TRIM($K14))))) -> Payments | AQ14: =IF(TRIM($B14)="","",--OR(TRIM($K14)="Leadership",TRIM($J14)="Leadership")) -> FALSE | AR14: =IF(TRIM($B14)="","",IF(IFERROR(INDEX(Lists!$AQ$2:$AQ$11,MATCH(ROW(),Lists!$AN$2:$AN$11,0)),"")<>"",IFERROR(INDEX(Lists!$AQ$2:$AQ$11,MATCH(ROW(),Lists!$AN$2:$AN$11,0)),""),IF(ISNUMBER(SEARCH("head of ",$C14)),"Head of Technology",IF(ISNUMBER(SEARCH("TDD BP",$C14)),"Business Partner",IF(OR(ISNUMBER(SEARCH("domain architect",$C14)),ISNUMBER(SEARCH("enterprise architect",$C14))),"Domain Architect",IF(ISNUMBER(SEARCH("delivery man",$C14)),"Delivery Manager",IF(OR(ISNUMBER(SEARCH("technology manager",$C14)),ISNUMBER(SEARCH("technology manger",$C14)),ISNUMBER(SEARCH("tech manager",$C14))),"Technology Manager","Squad"))))))) -> Squad | AS14: =IF(TRIM($B14)="","",IFERROR(INDEX(Lists!$AA:$AA,MATCH($AP14,Lists!$Z:$Z,0)),$AP14)) -> Payments | AT14: =IF(TRIM($B14)="","",IF(IFERROR(INDEX(Lists!$AP$2:$AP$11,MATCH(ROW(),Lists!$AN$2:$AN$11,0)),"")<>"",IFERROR(INDEX(Lists!$AP$2:$AP$11,MATCH(ROW(),Lists!$AN$2:$AN$11,0)),""),IF(OR(LEFT($AJ14,3)="COE",$AJ14="EGI"),$AP14,IF($AR14<>"Squad",$AR14,$AP14)))) -> Payments
A15: 99999101333 | B15: Benjamin Sheffield | C15: Lead Engineer - Software | D15: Vacant | E15: Technology Manager, Engineering | F15: Ampol Retail & Z | G15: Z & Group Retail | H15: Z & Group Retail, Engineering | I15: Z | J15: Z Supply | K15: Z Supply | M15: NZ | N15: CIC | O15: 1 | Q15: Permanent - Full Time | T15: 160250 | U15: 147430 | V15: 0.15 | X15: 0.05 | Y15: 2910 | Z15: 0.03 | AA15: =IF(TRIM($B15)="","",IF(N($AU15)>0,$AU15,IF(N($S15)>0,$S15*Lists!$AG$15*(1+N($Z15)),N($U15)*(1+N($V15)+N($W15)+N($X15)+N($Z15))+N($Y15)))) -> 184248.9 | AJ15: =IF(TRIM($B15)="","",IF(IFERROR(INDEX(Lists!$AO$2:$AO$11,MATCH(ROW(),Lists!$AN$2:$AN$11,0)),"")<>"",IFERROR(INDEX(Lists!$AO$2:$AO$11,MATCH(ROW(),Lists!$AN$2:$AN$11,0)),""),IFERROR(INDEX(Lists!$U:$U,MATCH(TRIM($I15),Lists!$T:$T,0)),TRIM($I15)))) -> Z Retail | AK15: =IF(ISNUMBER(SEARCH("vacant",$B15)),"Vacant","Filled") -> Filled | AL15: =IF($M15="NZ","NZ","AU") -> NZ | AM15: =COUNTIF($AJ$2:$AJ15,$AJ15) -> 6 | AN15: =$AJ15&"|"&$AM15 -> Z Retail|6 | AP15: =IF(TRIM($B15)="","",IF($AQ15=1,"Leadership",IFERROR(INDEX(Lists!$X:$X,MATCH(TRIM($K15),Lists!$W:$W,0)),IF(OR(TRIM($K15)="",LOWER(TRIM($K15))="na"),IF(TRIM($G15)="","Unassigned",TRIM($G15)),TRIM($K15))))) -> Z Supply | AQ15: =IF(TRIM($B15)="","",--OR(TRIM($K15)="Leadership",TRIM($J15)="Leadership")) -> FALSE | AR15: =IF(TRIM($B15)="","",IF(IFERROR(INDEX(Lists!$AQ$2:$AQ$11,MATCH(ROW(),Lists!$AN$2:$AN$11,0)),"")<>"",IFERROR(INDEX(Lists!$AQ$2:$AQ$11,MATCH(ROW(),Lists!$AN$2:$AN$11,0)),""),IF(ISNUMBER(SEARCH("head of ",$C15)),"Head of Technology",IF(ISNUMBER(SEARCH("TDD BP",$C15)),"Business Partner",IF(OR(ISNUMBER(SEARCH("domain architect",$C15)),ISNUMBER(SEARCH("enterprise architect",$C15))),"Domain Architect",IF(ISNUMBER(SEARCH("delivery man",$C15)),"Delivery Manager",IF(OR(ISNUMBER(SEARCH("technology manager",$C15)),ISNUMBER(SEARCH("technology manger",$C15)),ISNUMBER(SEARCH("tech manager",$C15))),"Technology Manager","Squad"))))))) -> Squad | AS15: =IF(TRIM($B15)="","",IFERROR(INDEX(Lists!$AA:$AA,MATCH($AP15,Lists!$Z:$Z,0)),$AP15)) -> Z Supply | AT15: =IF(TRIM($B15)="","",IF(IFERROR(INDEX(Lists!$AP$2:$AP$11,MATCH(ROW(),Lists!$AN$2:$AN$11,0)),"")<>"",IFERROR(INDEX(Lists!$AP$2:$AP$11,MATCH(ROW(),Lists!$AN$2:$AN$11,0)),""),IF(OR(LEFT($AJ15,3)="COE",$AJ15="EGI"),$AP15,IF($AR15<>"Squad",$AR15,$AP15)))) -> Z Supply
A16: 99999101553 | B16: Bradley Cunningham | C16: Site Systems Analyst | D16: Callan McLaughlin | E16: Technology Manager, Site Systems | F16: Ampol Retail & Z | G16: Z & Group Retail | H16: Z & Group Retail, Site Systems | I16: Z | J16: Z Customer | K16: Site Systems | M16: NZ | N16: CDC | O16: 1 | Q16: Permanent - Full Time | T16: 96110 | U16: 88421.2 | V16: 0.1 | X16: 0.05 | Y16: 2910 | Z16: 0.03 | AA16: =IF(TRIM($B16)="","",IF(N($AU16)>0,$AU16,IF(N($S16)>0,$S16*Lists!$AG$15*(1+N($Z16)),N($U16)*(1+N($V16)+N($W16)+N($X16)+N($Z16))+N($Y16)))) -> 107247.02 | AJ16: =IF(TRIM($B16)="","",IF(IFERROR(INDEX(Lists!$AO$2:$AO$11,MATCH(ROW(),Lists!$AN$2:$AN$11,0)),"")<>"",IFERROR(INDEX(Lists!$AO$2:$AO$11,MATCH(ROW(),Lists!$AN$2:$AN$11,0)),""),IFERROR(INDEX(Lists!$U:$U,MATCH(TRIM($I16),Lists!$T:$T,0)),TRIM($I16)))) -> Z Retail | AK16: =IF(ISNUMBER(SEARCH("vacant",$B16)),"Vacant","Filled") -> Filled | AL16: =IF($M16="NZ","NZ","AU") -> NZ | AM16: =COUNTIF($AJ$2:$AJ16,$AJ16) -> 7 | AN16: =$AJ16&"|"&$AM16 -> Z Retail|7 | AP16: =IF(TRIM($B16)="","",IF($AQ16=1,"Leadership",IFERROR(INDEX(Lists!$X:$X,MATCH(TRIM($K16),Lists!$W:$W,0)),IF(OR(TRIM($K16)="",LOWER(TRIM($K16))="na"),IF(TRIM($G16)="","Unassigned",TRIM($G16)),TRIM($K16))))) -> Site Systems | AQ16: =IF(TRIM($B16)="","",--OR(TRIM($K16)="Leadership",TRIM($J16)="Leadership")) -> FALSE | AR16: =IF(TRIM($B16)="","",IF(IFERROR(INDEX(Lists!$AQ$2:$AQ$11,MATCH(ROW(),Lists!$AN$2:$AN$11,0)),"")<>"",IFERROR(INDEX(Lists!$AQ$2:$AQ$11,MATCH(ROW(),Lists!$AN$2:$AN$11,0)),""),IF(ISNUMBER(SEARCH("head of ",$C16)),"Head of Technology",IF(ISNUMBER(SEARCH("TDD BP",$C16)),"Business Partner",IF(OR(ISNUMBER(SEARCH("domain architect",$C16)),ISNUMBER(SEARCH("enterprise architect",$C16))),"Domain Architect",IF(ISNUMBER(SEARCH("delivery man",$C16)),"Delivery Manager",IF(OR(ISNUMBER(SEARCH("technology manager",$C16)),ISNUMBER(SEARCH("technology manger",$C16)),ISNUMBER(SEARCH("tech manager",$C16))),"Technology Manager","Squad"))))))) -> Squad | AS16: =IF(TRIM($B16)="","",IFERROR(INDEX(Lists!$AA:$AA,MATCH($AP16,Lists!$Z:$Z,0)),$AP16)) -> Site Systems | AT16: =IF(TRIM($B16)="","",IF(IFERROR(INDEX(Lists!$AP$2:$AP$11,MATCH(ROW(),Lists!$AN$2:$AN$11,0)),"")<>"",IFERROR(INDEX(Lists!$AP$2:$AP$11,MATCH(ROW(),Lists!$AN$2:$AN$11,0)),""),IF(OR(LEFT($AJ16,3)="COE",$AJ16="EGI"),$AP16,IF($AR16<>"Squad",$AR16,$AP16)))) -> Site Systems
A17: 99999101959 | B17: Brian Lai | C17: Engineer - Data | D17: Vacant | E17: Technology Manager, Data | F17: Ampol Retail & Z | G17: Z & Group Retail | H17: Z & Group Retail, Data | I17: Z | J17: Z Customer & Z Supply | K17: Data - NZ | M17: NZ | N17: CIA | O17: 1 | Q17: Permanent - Full Time | T17: 135000 | U17: 124200 | V17: 0.15 | X17: 0.05 | Y17: 2910 | Z17: 0.03 | AA17: =IF(TRIM($B17)="","",IF(N($AU17)>0,$AU17,IF(N($S17)>0,$S17*Lists!$AG$15*(1+N($Z17)),N($U17)*(1+N($V17)+N($W17)+N($X17)+N($Z17))+N($Y17)))) -> 155676 | AJ17: =IF(TRIM($B17)="","",IF(IFERROR(INDEX(Lists!$AO$2:$AO$11,MATCH(ROW(),Lists!$AN$2:$AN$11,0)),"")<>"",IFERROR(INDEX(Lists!$AO$2:$AO$11,MATCH(ROW(),Lists!$AN$2:$AN$11,0)),""),IFERROR(INDEX(Lists!$U:$U,MATCH(TRIM($I17),Lists!$T:$T,0)),TRIM($I17)))) -> Z Retail | AK17: =IF(ISNUMBER(SEARCH("vacant",$B17)),"Vacant","Filled") -> Filled | AL17: =IF($M17="NZ","NZ","AU") -> NZ | AM17: =COUNTIF($AJ$2:$AJ17,$AJ17) -> 8 | AN17: =$AJ17&"|"&$AM17 -> Z Retail|8 | AP17: =IF(TRIM($B17)="","",IF($AQ17=1,"Leadership",IFERROR(INDEX(Lists!$X:$X,MATCH(TRIM($K17),Lists!$W:$W,0)),IF(OR(TRIM($K17)="",LOWER(TRIM($K17))="na"),IF(TRIM($G17)="","Unassigned",TRIM($G17)),TRIM($K17))))) -> Data NZ | AQ17: =IF(TRIM($B17)="","",--OR(TRIM($K17)="Leadership",TRIM($J17)="Leadership")) -> FALSE | AR17: =IF(TRIM($B17)="","",IF(IFERROR(INDEX(Lists!$AQ$2:$AQ$11,MATCH(ROW(),Lists!$AN$2:$AN$11,0)),"")<>"",IFERROR(INDEX(Lists!$AQ$2:$AQ$11,MATCH(ROW(),Lists!$AN$2:$AN$11,0)),""),IF(ISNUMBER(SEARCH("head of ",$C17)),"Head of Technology",IF(ISNUMBER(SEARCH("TDD BP",$C17)),"Business Partner",IF(OR(ISNUMBER(SEARCH("domain architect",$C17)),ISNUMBER(SEARCH("enterprise architect",$C17))),"Domain Architect",IF(ISNUMBER(SEARCH("delivery man",$C17)),"Delivery Manager",IF(OR(ISNUMBER(SEARCH("technology manager",$C17)),ISNUMBER(SEARCH("technology manger",$C17)),ISNUMBER(SEARCH("tech manager",$C17))),"Technology Manager","Squad"))))))) -> Squad | AS17: =IF(TRIM($B17)="","",IFERROR(INDEX(Lists!$AA:$AA,MATCH($AP17,Lists!$Z:$Z,0)),$AP17)) -> Data NZ | AT17: =IF(TRIM($B17)="","",IF(IFERROR(INDEX(Lists!$AP$2:$AP$11,MATCH(ROW(),Lists!$AN$2:$AN$11,0)),"")<>"",IFERROR(INDEX(Lists!$AP$2:$AP$11,MATCH(ROW(),Lists!$AN$2:$AN$11,0)),""),IF(OR(LEFT($AJ17,3)="COE",$AJ17="EGI"),$AP17,IF($AR17<>"Squad",$AR17,$AP17)))) -> Data NZ
A18: 99999100418 | B18: Callan McLaughlin | C18: Technology Manager, Site Systems | D18: vacant | E18: Head of Technology, Z and Group Retail Platforms | F18: Ampol Retail & Z | G18: Z & Group Retail | H18: Z & Group Retail, Site Systems | I18: Z | J18: Z Customer & Z Supply | K18: Leadership | M18: NZ | N18: CSB | O18: 1 | Q18: Permanent - Full Time | T18: 183480 | U18: 168801.6 | V18: 0.15 | X18: 0.05 | Y18: 2910 | Z18: 0.03 | AA18: =IF(TRIM($B18)="","",IF(N($AU18)>0,$AU18,IF(N($S18)>0,$S18*Lists!$AG$15*(1+N($Z18)),N($U18)*(1+N($V18)+N($W18)+N($X18)+N($Z18))+N($Y18)))) -> 210535.97 | AJ18: =IF(TRIM($B18)="","",IF(IFERROR(INDEX(Lists!$AO$2:$AO$11,MATCH(ROW(),Lists!$AN$2:$AN$11,0)),"")<>"",IFERROR(INDEX(Lists!$AO$2:$AO$11,MATCH(ROW(),Lists!$AN$2:$AN$11,0)),""),IFERROR(INDEX(Lists!$U:$U,MATCH(TRIM($I18),Lists!$T:$T,0)),TRIM($I18)))) -> Z Retail | AK18: =IF(ISNUMBER(SEARCH("vacant",$B18)),"Vacant","Filled") -> Filled | AL18: =IF($M18="NZ","NZ","AU") -> NZ | AM18: =COUNTIF($AJ$2:$AJ18,$AJ18) -> 9 | AN18: =$AJ18&"|"&$AM18 -> Z Retail|9 | AP18: =IF(TRIM($B18)="","",IF($AQ18=1,"Leadership",IFERROR(INDEX(Lists!$X:$X,MATCH(TRIM($K18),Lists!$W:$W,0)),IF(OR(TRIM($K18)="",LOWER(TRIM($K18))="na"),IF(TRIM($G18)="","Unassigned",TRIM($G18)),TRIM($K18))))) -> Leadership | AQ18: =IF(TRIM($B18)="","",--OR(TRIM($K18)="Leadership",TRIM($J18)="Leadership")) -> TRUE | AR18: =IF(TRIM($B18)="","",IF(IFERROR(INDEX(Lists!$AQ$2:$AQ$11,MATCH(ROW(),Lists!$AN$2:$AN$11,0)),"")<>"",IFERROR(INDEX(Lists!$AQ$2:$AQ$11,MATCH(ROW(),Lists!$AN$2:$AN$11,0)),""),IF(ISNUMBER(SEARCH("head of ",$C18)),"Head of Technology",IF(ISNUMBER(SEARCH("TDD BP",$C18)),"Business Partner",IF(OR(ISNUMBER(SEARCH("domain architect",$C18)),ISNUMBER(SEARCH("enterprise architect",$C18))),"Domain Architect",IF(ISNUMBER(SEARCH("delivery man",$C18)),"Delivery Manager",IF(OR(ISNUMBER(SEARCH("technology manager",$C18)),ISNUMBER(SEARCH("technology manger",$C18)),ISNUMBER(SEARCH("tech manager",$C18))),"Technology Manager","Squad"))))))) -> Technology Manager | AS18: =IF(TRIM($B18)="","",IFERROR(INDEX(Lists!$AA:$AA,MATCH($AP18,Lists!$Z:$Z,0)),$AP18)) -> Leadership | AT18: =IF(TRIM($B18)="","",IF(IFERROR(INDEX(Lists!$AP$2:$AP$11,MATCH(ROW(),Lists!$AN$2:$AN$11,0)),"")<>"",IFERROR(INDEX(Lists!$AP$2:$AP$11,MATCH(ROW(),Lists!$AN$2:$AN$11,0)),""),IF(OR(LEFT($AJ18,3)="COE",$AJ18="EGI"),$AP18,IF($AR18<>"Squad",$AR18,$AP18)))) -> Technology Manager
A19: 99999100975 | B19: Chris Mitchell | C19: Deployment Lead | D19: Callan McLaughlin | E19: Technology Manager, Site Systems | F19: Ampol Retail & Z | G19: Z & Group Retail | H19: Z & Group Retail, Site Systems | I19: Z | J19: Z Customer | K19: Site Systems | M19: NZ | N19: CIA | O19: 1 | Q19: Permanent - Full Time | T19: 118000 | U19: 108560 | V19: 0.15 | X19: 0.05 | Y19: 2910 | Z19: 0.03 | AA19: =IF(TRIM($B19)="","",IF(N($AU19)>0,$AU19,IF(N($S19)>0,$S19*Lists!$AG$15*(1+N($Z19)),N($U19)*(1+N($V19)+N($W19)+N($X19)+N($Z19))+N($Y19)))) -> 136438.8 | AJ19: =IF(TRIM($B19)="","",IF(IFERROR(INDEX(Lists!$AO$2:$AO$11,MATCH(ROW(),Lists!$AN$2:$AN$11,0)),"")<>"",IFERROR(INDEX(Lists!$AO$2:$AO$11,MATCH(ROW(),Lists!$AN$2:$AN$11,0)),""),IFERROR(INDEX(Lists!$U:$U,MATCH(TRIM($I19),Lists!$T:$T,0)),TRIM($I19)))) -> Z Retail | AK19: =IF(ISNUMBER(SEARCH("vacant",$B19)),"Vacant","Filled") -> Filled | AL19: =IF($M19="NZ","NZ","AU") -> NZ | AM19: =COUNTIF($AJ$2:$AJ19,$AJ19) -> 10 | AN19: =$AJ19&"|"&$AM19 -> Z Retail|10 | AP19: =IF(TRIM($B19)="","",IF($AQ19=1,"Leadership",IFERROR(INDEX(Lists!$X:$X,MATCH(TRIM($K19),Lists!$W:$W,0)),IF(OR(TRIM($K19)="",LOWER(TRIM($K19))="na"),IF(TRIM($G19)="","Unassigned",TRIM($G19)),TRIM($K19))))) -> Site Systems | AQ19: =IF(TRIM($B19)="","",--OR(TRIM($K19)="Leadership",TRIM($J19)="Leadership")) -> FALSE | AR19: =IF(TRIM($B19)="","",IF(IFERROR(INDEX(Lists!$AQ$2:$AQ$11,MATCH(ROW(),Lists!$AN$2:$AN$11,0)),"")<>"",IFERROR(INDEX(Lists!$AQ$2:$AQ$11,MATCH(ROW(),Lists!$AN$2:$AN$11,0)),""),IF(ISNUMBER(SEARCH("head of ",$C19)),"Head of Technology",IF(ISNUMBER(SEARCH("TDD BP",$C19)),"Business Partner",IF(OR(ISNUMBER(SEARCH("domain architect",$C19)),ISNUMBER(SEARCH("enterprise architect",$C19))),"Domain Architect",IF(ISNUMBER(SEARCH("delivery man",$C19)),"Delivery Manager",IF(OR(ISNUMBER(SEARCH("technology manager",$C19)),ISNUMBER(SEARCH("technology manger",$C19)),ISNUMBER(SEARCH("tech manager",$C19))),"Technology Manager","Squad"))))))) -> Squad | AS19: =IF(TRIM($B19)="","",IFERROR(INDEX(Lists!$AA:$AA,MATCH($AP19,Lists!$Z:$Z,0)),$AP19)) -> Site Systems | AT19: =IF(TRIM($B19)="","",IF(IFERROR(INDEX(Lists!$AP$2:$AP$11,MATCH(ROW(),Lists!$AN$2:$AN$11,0)),"")<>"",IFERROR(INDEX(Lists!$AP$2:$AP$11,MATCH(ROW(),Lists!$AN$2:$AN$11,0)),""),IF(OR(LEFT($AJ19,3)="COE",$AJ19="EGI"),$AP19,IF($AR19<>"Squad",$AR19,$AP19)))) -> Site Systems
A20: 99999101233 | B20: Chris Wilson | C20: Solution Architect | D20: Callan McLaughlin | E20: Technology Manager, Site Systems | F20: Ampol Retail & Z | G20: Z & Group Retail | H20: Z & Group Retail, Site Systems | I20: Z | J20: Z Customer | K20: Site Systems | M20: NZ | N20: CIC | O20: 1 | Q20: Permanent - Full Time | T20: 161990 | U20: 149030.8 | V20: 0.15 | X20: 0.05 | Y20: 2910 | Z20: 0.03 | AA20: =IF(TRIM($B20)="","",IF(N($AU20)>0,$AU20,IF(N($S20)>0,$S20*Lists!$AG$15*(1+N($Z20)),N($U20)*(1+N($V20)+N($W20)+N($X20)+N($Z20))+N($Y20)))) -> 186217.88 | AJ20: =IF(TRIM($B20)="","",IF(IFERROR(INDEX(Lists!$AO$2:$AO$11,MATCH(ROW(),Lists!$AN$2:$AN$11,0)),"")<>"",IFERROR(INDEX(Lists!$AO$2:$AO$11,MATCH(ROW(),Lists!$AN$2:$AN$11,0)),""),IFERROR(INDEX(Lists!$U:$U,MATCH(TRIM($I20),Lists!$T:$T,0)),TRIM($I20)))) -> Z Retail | AK20: =IF(ISNUMBER(SEARCH("vacant",$B20)),"Vacant","Filled") -> Filled | AL20: =IF($M20="NZ","NZ","AU") -> NZ | AM20: =COUNTIF($AJ$2:$AJ20,$AJ20) -> 11 | AN20: =$AJ20&"|"&$AM20 -> Z Retail|11 | AP20: =IF(TRIM($B20)="","",IF($AQ20=1,"Leadership",IFERROR(INDEX(Lists!$X:$X,MATCH(TRIM($K20),Lists!$W:$W,0)),IF(OR(TRIM($K20)="",LOWER(TRIM($K20))="na"),IF(TRIM($G20)="","Unassigned",TRIM($G20)),TRIM($K20))))) -> Site Systems | AQ20: =IF(TRIM($B20)="","",--OR(TRIM($K20)="Leadership",TRIM($J20)="Leadership")) -> FALSE | AR20: =IF(TRIM($B20)="","",IF(IFERROR(INDEX(Lists!$AQ$2:$AQ$11,MATCH(ROW(),Lists!$AN$2:$AN$11,0)),"")<>"",IFERROR(INDEX(Lists!$AQ$2:$AQ$11,MATCH(ROW(),Lists!$AN$2:$AN$11,0)),""),IF(ISNUMBER(SEARCH("head of ",$C20)),"Head of Technology",IF(ISNUMBER(SEARCH("TDD BP",$C20)),"Business Partner",IF(OR(ISNUMBER(SEARCH("domain architect",$C20)),ISNUMBER(SEARCH("enterprise architect",$C20))),"Domain Architect",IF(ISNUMBER(SEARCH("delivery man",$C20)),"Delivery Manager",IF(OR(ISNUMBER(SEARCH("technology manager",$C20)),ISNUMBER(SEARCH("technology manger",$C20)),ISNUMBER(SEARCH("tech manager",$C20))),"Technology Manager","Squad"))))))) -> Squad | AS20: =IF(TRIM($B20)="","",IFERROR(INDEX(Lists!$AA:$AA,MATCH($AP20,Lists!$Z:$Z,0)),$AP20)) -> Site Systems | AT20: =IF(TRIM($B20)="","",IF(IFERROR(INDEX(Lists!$AP$2:$AP$11,MATCH(ROW(),Lists!$AN$2:$AN$11,0)),"")<>"",IFERROR(INDEX(Lists!$AP$2:$AP$11,MATCH(ROW(),Lists!$AN$2:$AN$11,0)),""),IF(OR(LEFT($AJ20,3)="COE",$AJ20="EGI"),$AP20,IF($AR20<>"Squad",$AR20,$AP20)))) -> Site Systems
A21: 99999102141 | B21: Christian Guo | C21: Solution Architect | D21: Callan McLaughlin | E21: Technology Manager, Site Systems | F21: Ampol Retail & Z | G21: Z & Group Retail | H21: Z & Group Retail, Site Systems | I21: Z | J21: Z Customer | K21: Z Retail Backend | M21: NZ | N21: CIC | O21: 1 | Q21: Permanent - Full Time | T21: 180000 | U21: 165600 | V21: 0.15 | X21: 0.05 | Y21: 2910 | Z21: 0.03 | AA21: =IF(TRIM($B21)="","",IF(N($AU21)>0,$AU21,IF(N($S21)>0,$S21*Lists!$AG$15*(1+N($Z21)),N($U21)*(1+N($V21)+N($W21)+N($X21)+N($Z21))+N($Y21)))) -> 206598 | AJ21: =IF(TRIM($B21)="","",IF(IFERROR(INDEX(Lists!$AO$2:$AO$11,MATCH(ROW(),Lists!$AN$2:$AN$11,0)),"")<>"",IFERROR(INDEX(Lists!$AO$2:$AO$11,MATCH(ROW(),Lists!$AN$2:$AN$11,0)),""),IFERROR(INDEX(Lists!$U:$U,MATCH(TRIM($I21),Lists!$T:$T,0)),TRIM($I21)))) -> Z Retail | AK21: =IF(ISNUMBER(SEARCH("vacant",$B21)),"Vacant","Filled") -> Filled | AL21: =IF($M21="NZ","NZ","AU") -> NZ | AM21: =COUNTIF($AJ$2:$AJ21,$AJ21) -> 12 | AN21: =$AJ21&"|"&$AM21 -> Z Retail|12 | AP21: =IF(TRIM($B21)="","",IF($AQ21=1,"Leadership",IFERROR(INDEX(Lists!$X:$X,MATCH(TRIM($K21),Lists!$W:$W,0)),IF(OR(TRIM($K21)="",LOWER(TRIM($K21))="na"),IF(TRIM($G21)="","Unassigned",TRIM($G21)),TRIM($K21))))) -> Z Retail Backend | AQ21: =IF(TRIM($B21)="","",--OR(TRIM($K21)="Leadership",TRIM($J21)="Leadership")) -> FALSE | AR21: =IF(TRIM($B21)="","",IF(IFERROR(INDEX(Lists!$AQ$2:$AQ$11,MATCH(ROW(),Lists!$AN$2:$AN$11,0)),"")<>"",IFERROR(INDEX(Lists!$AQ$2:$AQ$11,MATCH(ROW(),Lists!$AN$2:$AN$11,0)),""),IF(ISNUMBER(SEARCH("head of ",$C21)),"Head of Technology",IF(ISNUMBER(SEARCH("TDD BP",$C21)),"Business Partner",IF(OR(ISNUMBER(SEARCH("domain architect",$C21)),ISNUMBER(SEARCH("enterprise architect",$C21))),"Domain Architect",IF(ISNUMBER(SEARCH("delivery man",$C21)),"Delivery Manager",IF(OR(ISNUMBER(SEARCH("technology manager",$C21)),ISNUMBER(SEARCH("technology manger",$C21)),ISNUMBER(SEARCH("tech manager",$C21))),"Technology Manager","Squad"))))))) -> Squad | AS21: =IF(TRIM($B21)="","",IFERROR(INDEX(Lists!$AA:$AA,MATCH($AP21,Lists!$Z:$Z,0)),$AP21)) -> Z Retail Backend | AT21: =IF(TRIM($B21)="","",IF(IFERROR(INDEX(Lists!$AP$2:$AP$11,MATCH(ROW(),Lists!$AN$2:$AN$11,0)),"")<>"",IFERROR(INDEX(Lists!$AP$2:$AP$11,MATCH(ROW(),Lists!$AN$2:$AN$11,0)),""),IF(OR(LEFT($AJ21,3)="COE",$AJ21="EGI"),$AP21,IF($AR21<>"Squad",$AR21,$AP21)))) -> Z Retail Backend
A22: 95128 | B22: Deepak Kubendran | C22: Project Manager - Deployments | D22: Matthew Patane | E22: Release & Deployment Manager | F22: Ampol Retail & Z | G22: Ampol Retail | H22: Ampol Retail, Technology | I22: Retail | J22: Store Operations | K22: Deployment | M22: Australia | N22: CIB | O22: 1 | Q22: Permanent - Full Time | T22: 153920 | U22: 153920 | V22: 0.12 | W22: 0.055 | X22: 0.12 | Z22: 0.04 | AA22: =IF(TRIM($B22)="","",IF(N($AU22)>0,$AU22,IF(N($S22)>0,$S22*Lists!$AG$15*(1+N($Z22)),N($U22)*(1+N($V22)+N($W22)+N($X22)+N($Z22))+N($Y22)))) -> 205483.2 | AJ22: =IF(TRIM($B22)="","",IF(IFERROR(INDEX(Lists!$AO$2:$AO$11,MATCH(ROW(),Lists!$AN$2:$AN$11,0)),"")<>"",IFERROR(INDEX(Lists!$AO$2:$AO$11,MATCH(ROW(),Lists!$AN$2:$AN$11,0)),""),IFERROR(INDEX(Lists!$U:$U,MATCH(TRIM($I22),Lists!$T:$T,0)),TRIM($I22)))) -> Ampol Retail | AK22: =IF(ISNUMBER(SEARCH("vacant",$B22)),"Vacant","Filled") -> Filled | AL22: =IF($M22="NZ","NZ","AU") -> AU | AM22: =COUNTIF($AJ$2:$AJ22,$AJ22) -> 9 | AN22: =$AJ22&"|"&$AM22 -> Ampol Retail|9 | AP22: =IF(TRIM($B22)="","",IF($AQ22=1,"Leadership",IFERROR(INDEX(Lists!$X:$X,MATCH(TRIM($K22),Lists!$W:$W,0)),IF(OR(TRIM($K22)="",LOWER(TRIM($K22))="na"),IF(TRIM($G22)="","Unassigned",TRIM($G22)),TRIM($K22))))) -> Deployment | AQ22: =IF(TRIM($B22)="","",--OR(TRIM($K22)="Leadership",TRIM($J22)="Leadership")) -> FALSE | AR22: =IF(TRIM($B22)="","",IF(IFERROR(INDEX(Lists!$AQ$2:$AQ$11,MATCH(ROW(),Lists!$AN$2:$AN$11,0)),"")<>"",IFERROR(INDEX(Lists!$AQ$2:$AQ$11,MATCH(ROW(),Lists!$AN$2:$AN$11,0)),""),IF(ISNUMBER(SEARCH("head of ",$C22)),"Head of Technology",IF(ISNUMBER(SEARCH("TDD BP",$C22)),"Business Partner",IF(OR(ISNUMBER(SEARCH("domain architect",$C22)),ISNUMBER(SEARCH("enterprise architect",$C22))),"Domain Architect",IF(ISNUMBER(SEARCH("delivery man",$C22)),"Delivery Manager",IF(OR(ISNUMBER(SEARCH("technology manager",$C22)),ISNUMBER(SEARCH("technology manger",$C22)),ISNUMBER(SEARCH("tech manager",$C22))),"Technology Manager","Squad"))))))) -> Squad | AS22: =IF(TRIM($B22)="","",IFERROR(INDEX(Lists!$AA:$AA,MATCH($AP22,Lists!$Z:$Z,0)),$AP22)) -> Deployment | AT22: =IF(TRIM($B22)="","",IF(IFERROR(INDEX(Lists!$AP$2:$AP$11,MATCH(ROW(),Lists!$AN$2:$AN$11,0)),"")<>"",IFERROR(INDEX(Lists!$AP$2:$AP$11,MATCH(ROW(),Lists!$AN$2:$AN$11,0)),""),IF(OR(LEFT($AJ22,3)="COE",$AJ22="EGI"),$AP22,IF($AR22<>"Squad",$AR22,$AP22)))) -> Deployment
A23: ? | B23: Emma Natoli | C23: Technology Manager, Engineering | D23: Vacant | E23: Head of Technology, Z and Group Retail Platforms | F23: Ampol Retail & Z | G23: Z & Group Retail | H23: Z & Group Retail, Engineering | I23: Z | J23: Leadership | K23: Leadership | M23: Australia | N23: CSB | O23: 1 | Q23: Permanent - Full Time | T23: 177320 | U23: 177320 | V23: 0.12 | W23: 0.055 | X23: 0.12 | Z23: 0.04 | AA23: =IF(TRIM($B23)="","",IF(N($AU23)>0,$AU23,IF(N($S23)>0,$S23*Lists!$AG$15*(1+N($Z23)),N($U23)*(1+N($V23)+N($W23)+N($X23)+N($Z23))+N($Y23)))) -> 236722.2 | AJ23: =IF(TRIM($B23)="","",IF(IFERROR(INDEX(Lists!$AO$2:$AO$11,MATCH(ROW(),Lists!$AN$2:$AN$11,0)),"")<>"",IFERROR(INDEX(Lists!$AO$2:$AO$11,MATCH(ROW(),Lists!$AN$2:$AN$11,0)),""),IFERROR(INDEX(Lists!$U:$U,MATCH(TRIM($I23),Lists!$T:$T,0)),TRIM($I23)))) -> Z Retail | AK23: =IF(ISNUMBER(SEARCH("vacant",$B23)),"Vacant","Filled") -> Filled | AL23: =IF($M23="NZ","NZ","AU") -> AU | AM23: =COUNTIF($AJ$2:$AJ23,$AJ23) -> 13 | AN23: =$AJ23&"|"&$AM23 -> Z Retail|13 | AP23: =IF(TRIM($B23)="","",IF($AQ23=1,"Leadership",IFERROR(INDEX(Lists!$X:$X,MATCH(TRIM($K23),Lists!$W:$W,0)),IF(OR(TRIM($K23)="",LOWER(TRIM($K23))="na"),IF(TRIM($G23)="","Unassigned",TRIM($G23)),TRIM($K23))))) -> Leadership | AQ23: =IF(TRIM($B23)="","",--OR(TRIM($K23)="Leadership",TRIM($J23)="Leadership")) -> TRUE | AR23: =IF(TRIM($B23)="","",IF(IFERROR(INDEX(Lists!$AQ$2:$AQ$11,MATCH(ROW(),Lists!$AN$2:$AN$11,0)),"")<>"",IFERROR(INDEX(Lists!$AQ$2:$AQ$11,MATCH(ROW(),Lists!$AN$2:$AN$11,0)),""),IF(ISNUMBER(SEARCH("head of ",$C23)),"Head of Technology",IF(ISNUMBER(SEARCH("TDD BP",$C23)),"Business Partner",IF(OR(ISNUMBER(SEARCH("domain architect",$C23)),ISNUMBER(SEARCH("enterprise architect",$C23))),"Domain Architect",IF(ISNUMBER(SEARCH("delivery man",$C23)),"Delivery Manager",IF(OR(ISNUMBER(SEARCH("technology manager",$C23)),ISNUMBER(SEARCH("technology manger",$C23)),ISNUMBER(SEARCH("tech manager",$C23))),"Technology Manager","Squad"))))))) -> Technology Manager | AS23: =IF(TRIM($B23)="","",IFERROR(INDEX(Lists!$AA:$AA,MATCH($AP23,Lists!$Z:$Z,0)),$AP23)) -> Leadership | AT23: =IF(TRIM($B23)="","",IF(IFERROR(INDEX(Lists!$AP$2:$AP$11,MATCH(ROW(),Lists!$AN$2:$AN$11,0)),"")<>"",IFERROR(INDEX(Lists!$AP$2:$AP$11,MATCH(ROW(),Lists!$AN$2:$AN$11,0)),""),IF(OR(LEFT($AJ23,3)="COE",$AJ23="EGI"),$AP23,IF($AR23<>"Squad",$AR23,$AP23)))) -> Technology Manager
A24: 4259 | B24: Ephraim Adan | C24: Manager - AU Retail Operations | D24: Vedran Jukic | E24: Technology Manager, Retail | F24: Ampol Retail & Z | G24: Ampol Retail | H24: Ampol Retail, Technology | I24: Retail | J24: Store Operations | K24: Store Operations | M24: Australia | N24: CIC | O24: 1 | Q24: Permanent - Full Time | T24: 68900 | U24: 63388 | V24: 0.1 | X24: 0.05 | Y24: 2910 | Z24: 0.03 | AA24: =IF(TRIM($B24)="","",IF(N($AU24)>0,$AU24,IF(N($S24)>0,$S24*Lists!$AG$15*(1+N($Z24)),N($U24)*(1+N($V24)+N($W24)+N($X24)+N($Z24))+N($Y24)))) -> 77707.84 | AJ24: =IF(TRIM($B24)="","",IF(IFERROR(INDEX(Lists!$AO$2:$AO$11,MATCH(ROW(),Lists!$AN$2:$AN$11,0)),"")<>"",IFERROR(INDEX(Lists!$AO$2:$AO$11,MATCH(ROW(),Lists!$AN$2:$AN$11,0)),""),IFERROR(INDEX(Lists!$U:$U,MATCH(TRIM($I24),Lists!$T:$T,0)),TRIM($I24)))) -> Ampol Retail | AK24: =IF(ISNUMBER(SEARCH("vacant",$B24)),"Vacant","Filled") -> Filled | AL24: =IF($M24="NZ","NZ","AU") -> AU | AM24: =COUNTIF($AJ$2:$AJ24,$AJ24) -> 10 | AN24: =$AJ24&"|"&$AM24 -> Ampol Retail|10 | AP24: =IF(TRIM($B24)="","",IF($AQ24=1,"Leadership",IFERROR(INDEX(Lists!$X:$X,MATCH(TRIM($K24),Lists!$W:$W,0)),IF(OR(TRIM($K24)="",LOWER(TRIM($K24))="na"),IF(TRIM($G24)="","Unassigned",TRIM($G24)),TRIM($K24))))) -> Store Operations | AQ24: =IF(TRIM($B24)="","",--OR(TRIM($K24)="Leadership",TRIM($J24)="Leadership")) -> FALSE | AR24: =IF(TRIM($B24)="","",IF(IFERROR(INDEX(Lists!$AQ$2:$AQ$11,MATCH(ROW(),Lists!$AN$2:$AN$11,0)),"")<>"",IFERROR(INDEX(Lists!$AQ$2:$AQ$11,MATCH(ROW(),Lists!$AN$2:$AN$11,0)),""),IF(ISNUMBER(SEARCH("head of ",$C24)),"Head of Technology",IF(ISNUMBER(SEARCH("TDD BP",$C24)),"Business Partner",IF(OR(ISNUMBER(SEARCH("domain architect",$C24)),ISNUMBER(SEARCH("enterprise architect",$C24))),"Domain Architect",IF(ISNUMBER(SEARCH("delivery man",$C24)),"Delivery Manager",IF(OR(ISNUMBER(SEARCH("technology manager",$C24)),ISNUMBER(SEARCH("technology manger",$C24)),ISNUMBER(SEARCH("tech manager",$C24))),"Technology Manager","Squad"))))))) -> Squad | AS24: =IF(TRIM($B24)="","",IFERROR(INDEX(Lists!$AA:$AA,MATCH($AP24,Lists!$Z:$Z,0)),$AP24)) -> Store Operations | AT24: =IF(TRIM($B24)="","",IF(IFERROR(INDEX(Lists!$AP$2:$AP$11,MATCH(ROW(),Lists!$AN$2:$AN$11,0)),"")<>"",IFERROR(INDEX(Lists!$AP$2:$AP$11,MATCH(ROW(),Lists!$AN$2:$AN$11,0)),""),IF(OR(LEFT($AJ24,3)="COE",$AJ24="EGI"),$AP24,IF($AR24<>"Squad",$AR24,$AP24)))) -> Store Operations
A25: 99999102110 | B25: Eugene Yeo | C25: Engineer - DevOps | D25: Vacant | E25: Technology Manager, Engineering | F25: Ampol Retail & Z | G25: Z & Group Retail | H25: Z & Group Retail, Engineering | I25: Z | J25: Z Supply | K25: Z Supply | M25: NZ | N25: CDA | O25: 1 | Q25: Permanent - Full Time | T25: 105000 | U25: 96600 | V25: 0.1 | X25: 0.05 | Y25: 2910 | Z25: 0.03 | AA25: =IF(TRIM($B25)="","",IF(N($AU25)>0,$AU25,IF(N($S25)>0,$S25*Lists!$AG$15*(1+N($Z25)),N($U25)*(1+N($V25)+N($W25)+N($X25)+N($Z25))+N($Y25)))) -> 116898 | AJ25: =IF(TRIM($B25)="","",IF(IFERROR(INDEX(Lists!$AO$2:$AO$11,MATCH(ROW(),Lists!$AN$2:$AN$11,0)),"")<>"",IFERROR(INDEX(Lists!$AO$2:$AO$11,MATCH(ROW(),Lists!$AN$2:$AN$11,0)),""),IFERROR(INDEX(Lists!$U:$U,MATCH(TRIM($I25),Lists!$T:$T,0)),TRIM($I25)))) -> Z Retail | AK25: =IF(ISNUMBER(SEARCH("vacant",$B25)),"Vacant","Filled") -> Filled | AL25: =IF($M25="NZ","NZ","AU") -> NZ | AM25: =COUNTIF($AJ$2:$AJ25,$AJ25) -> 14 | AN25: =$AJ25&"|"&$AM25 -> Z Retail|14 | AP25: =IF(TRIM($B25)="","",IF($AQ25=1,"Leadership",IFERROR(INDEX(Lists!$X:$X,MATCH(TRIM($K25),Lists!$W:$W,0)),IF(OR(TRIM($K25)="",LOWER(TRIM($K25))="na"),IF(TRIM($G25)="","Unassigned",TRIM($G25)),TRIM($K25))))) -> Z Supply | AQ25: =IF(TRIM($B25)="","",--OR(TRIM($K25)="Leadership",TRIM($J25)="Leadership")) -> FALSE | AR25: =IF(TRIM($B25)="","",IF(IFERROR(INDEX(Lists!$AQ$2:$AQ$11,MATCH(ROW(),Lists!$AN$2:$AN$11,0)),"")<>"",IFERROR(INDEX(Lists!$AQ$2:$AQ$11,MATCH(ROW(),Lists!$AN$2:$AN$11,0)),""),IF(ISNUMBER(SEARCH("head of ",$C25)),"Head of Technology",IF(ISNUMBER(SEARCH("TDD BP",$C25)),"Business Partner",IF(OR(ISNUMBER(SEARCH("domain architect",$C25)),ISNUMBER(SEARCH("enterprise architect",$C25))),"Domain Architect",IF(ISNUMBER(SEARCH("delivery man",$C25)),"Delivery Manager",IF(OR(ISNUMBER(SEARCH("technology manager",$C25)),ISNUMBER(SEARCH("technology manger",$C25)),ISNUMBER(SEARCH("tech manager",$C25))),"Technology Manager","Squad"))))))) -> Squad | AS25: =IF(TRIM($B25)="","",IFERROR(INDEX(Lists!$AA:$AA,MATCH($AP25,Lists!$Z:$Z,0)),$AP25)) -> Z Supply | AT25: =IF(TRIM($B25)="","",IF(IFERROR(INDEX(Lists!$AP$2:$AP$11,MATCH(ROW(),Lists!$AN$2:$AN$11,0)),"")<>"",IFERROR(INDEX(Lists!$AP$2:$AP$11,MATCH(ROW(),Lists!$AN$2:$AN$11,0)),""),IF(OR(LEFT($AJ25,3)="COE",$AJ25="EGI"),$AP25,IF($AR25<>"Squad",$AR25,$AP25)))) -> Z Supply
A26: 99999102111 | B26: Gayan Liyana Arachchige | C26: Engineer - DevOps | D26: Vacant | E26: Technology Manager, Engineering | F26: Ampol Retail & Z | G26: Z & Group Retail | H26: Z & Group Retail, Engineering | I26: Z | J26: Z Supply | K26: Z Supply | M26: NZ | N26: CDB | O26: 1 | Q26: Permanent - Full Time | T26: 132710 | U26: 132710 | V26: 0.1 | W26: 0.055 | X26: 0.12 | Z26: 0.04 | AA26: =IF(TRIM($B26)="","",IF(N($AU26)>0,$AU26,IF(N($S26)>0,$S26*Lists!$AG$15*(1+N($Z26)),N($U26)*(1+N($V26)+N($W26)+N($X26)+N($Z26))+N($Y26)))) -> 174513.65 | AJ26: =IF(TRIM($B26)="","",IF(IFERROR(INDEX(Lists!$AO$2:$AO$11,MATCH(ROW(),Lists!$AN$2:$AN$11,0)),"")<>"",IFERROR(INDEX(Lists!$AO$2:$AO$11,MATCH(ROW(),Lists!$AN$2:$AN$11,0)),""),IFERROR(INDEX(Lists!$U:$U,MATCH(TRIM($I26),Lists!$T:$T,0)),TRIM($I26)))) -> Z Retail | AK26: =IF(ISNUMBER(SEARCH("vacant",$B26)),"Vacant","Filled") -> Filled | AL26: =IF($M26="NZ","NZ","AU") -> NZ | AM26: =COUNTIF($AJ$2:$AJ26,$AJ26) -> 15 | AN26: =$AJ26&"|"&$AM26 -> Z Retail|15 | AP26: =IF(TRIM($B26)="","",IF($AQ26=1,"Leadership",IFERROR(INDEX(Lists!$X:$X,MATCH(TRIM($K26),Lists!$W:$W,0)),IF(OR(TRIM($K26)="",LOWER(TRIM($K26))="na"),IF(TRIM($G26)="","Unassigned",TRIM($G26)),TRIM($K26))))) -> Z Supply | AQ26: =IF(TRIM($B26)="","",--OR(TRIM($K26)="Leadership",TRIM($J26)="Leadership")) -> FALSE | AR26: =IF(TRIM($B26)="","",IF(IFERROR(INDEX(Lists!$AQ$2:$AQ$11,MATCH(ROW(),Lists!$AN$2:$AN$11,0)),"")<>"",IFERROR(INDEX(Lists!$AQ$2:$AQ$11,MATCH(ROW(),Lists!$AN$2:$AN$11,0)),""),IF(ISNUMBER(SEARCH("head of ",$C26)),"Head of Technology",IF(ISNUMBER(SEARCH("TDD BP",$C26)),"Business Partner",IF(OR(ISNUMBER(SEARCH("domain architect",$C26)),ISNUMBER(SEARCH("enterprise architect",$C26))),"Domain Architect",IF(ISNUMBER(SEARCH("delivery man",$C26)),"Delivery Manager",IF(OR(ISNUMBER(SEARCH("technology manager",$C26)),ISNUMBER(SEARCH("technology manger",$C26)),ISNUMBER(SEARCH("tech manager",$C26))),"Technology Manager","Squad"))))))) -> Squad | AS26: =IF(TRIM($B26)="","",IFERROR(INDEX(Lists!$AA:$AA,MATCH($AP26,Lists!$Z:$Z,0)),$AP26)) -> Z Supply | AT26: =IF(TRIM($B26)="","",IF(IFERROR(INDEX(Lists!$AP$2:$AP$11,MATCH(ROW(),Lists!$AN$2:$AN$11,0)),"")<>"",IFERROR(INDEX(Lists!$AP$2:$AP$11,MATCH(ROW(),Lists!$AN$2:$AN$11,0)),""),IF(OR(LEFT($AJ26,3)="COE",$AJ26="EGI"),$AP26,IF($AR26<>"Squad",$AR26,$AP26)))) -> Z Supply
A27: 8445 | B27: Geoff Goddard | C27: Field Systems Operations Lead - VIC | D27: Ephraim Adan | E27: Manager, AU Retail Operations | F27: Ampol Retail & Z | G27: Ampol Retail | H27: Ampol Retail, Technology | I27: Retail | J27: Store Operations | K27: Store Operations | M27: Australia | N27: CIA | O27: 1 | Q27: Permanent - Full Time | T27: 127270 | U27: 127270 | V27: 0.1 | W27: 0.055 | X27: 0.12 | Z27: 0.04 | AA27: =IF(TRIM($B27)="","",IF(N($AU27)>0,$AU27,IF(N($S27)>0,$S27*Lists!$AG$15*(1+N($Z27)),N($U27)*(1+N($V27)+N($W27)+N($X27)+N($Z27))+N($Y27)))) -> 167360.05 | AJ27: =IF(TRIM($B27)="","",IF(IFERROR(INDEX(Lists!$AO$2:$AO$11,MATCH(ROW(),Lists!$AN$2:$AN$11,0)),"")<>"",IFERROR(INDEX(Lists!$AO$2:$AO$11,MATCH(ROW(),Lists!$AN$2:$AN$11,0)),""),IFERROR(INDEX(Lists!$U:$U,MATCH(TRIM($I27),Lists!$T:$T,0)),TRIM($I27)))) -> Ampol Retail | AK27: =IF(ISNUMBER(SEARCH("vacant",$B27)),"Vacant","Filled") -> Filled | AL27: =IF($M27="NZ","NZ","AU") -> AU | AM27: =COUNTIF($AJ$2:$AJ27,$AJ27) -> 11 | AN27: =$AJ27&"|"&$AM27 -> Ampol Retail|11 | AP27: =IF(TRIM($B27)="","",IF($AQ27=1,"Leadership",IFERROR(INDEX(Lists!$X:$X,MATCH(TRIM($K27),Lists!$W:$W,0)),IF(OR(TRIM($K27)="",LOWER(TRIM($K27))="na"),IF(TRIM($G27)="","Unassigned",TRIM($G27)),TRIM($K27))))) -> Store Operations | AQ27: =IF(TRIM($B27)="","",--OR(TRIM($K27)="Leadership",TRIM($J27)="Leadership")) -> FALSE | AR27: =IF(TRIM($B27)="","",IF(IFERROR(INDEX(Lists!$AQ$2:$AQ$11,MATCH(ROW(),Lists!$AN$2:$AN$11,0)),"")<>"",IFERROR(INDEX(Lists!$AQ$2:$AQ$11,MATCH(ROW(),Lists!$AN$2:$AN$11,0)),""),IF(ISNUMBER(SEARCH("head of ",$C27)),"Head of Technology",IF(ISNUMBER(SEARCH("TDD BP",$C27)),"Business Partner",IF(OR(ISNUMBER(SEARCH("domain architect",$C27)),ISNUMBER(SEARCH("enterprise architect",$C27))),"Domain Architect",IF(ISNUMBER(SEARCH("delivery man",$C27)),"Delivery Manager",IF(OR(ISNUMBER(SEARCH("technology manager",$C27)),ISNUMBER(SEARCH("technology manger",$C27)),ISNUMBER(SEARCH("tech manager",$C27))),"Technology Manager","Squad"))))))) -> Squad | AS27: =IF(TRIM($B27)="","",IFERROR(INDEX(Lists!$AA:$AA,MATCH($AP27,Lists!$Z:$Z,0)),$AP27)) -> Store Operations | AT27: =IF(TRIM($B27)="","",IF(IFERROR(INDEX(Lists!$AP$2:$AP$11,MATCH(ROW(),Lists!$AN$2:$AN$11,0)),"")<>"",IFERROR(INDEX(Lists!$AP$2:$AP$11,MATCH(ROW(),Lists!$AN$2:$AN$11,0)),""),IF(OR(LEFT($AJ27,3)="COE",$AJ27="EGI"),$AP27,IF($AR27<>"Squad",$AR27,$AP27)))) -> Store Operations
A28: 109974 | B28: Gerald Aguas | C28: Field Systems Operations Lead - NSW | D28: Ephraim Adan | E28: Manager, AU Retail Operations | F28: Ampol Retail & Z | G28: Ampol Retail | H28: Ampol Retail, Technology | I28: Retail | J28: Store Operations | K28: Store Operations | M28: Australia | N28: CIA | O28: 1 | Q28: Permanent - Full Time | T28: 165470 | U28: 152232.4 | V28: 0.15 | X28: 0.05 | Y28: 2910 | Z28: 0.03 | AA28: =IF(TRIM($B28)="","",IF(N($AU28)>0,$AU28,IF(N($S28)>0,$S28*Lists!$AG$15*(1+N($Z28)),N($U28)*(1+N($V28)+N($W28)+N($X28)+N($Z28))+N($Y28)))) -> 190155.85 | AJ28: =IF(TRIM($B28)="","",IF(IFERROR(INDEX(Lists!$AO$2:$AO$11,MATCH(ROW(),Lists!$AN$2:$AN$11,0)),"")<>"",IFERROR(INDEX(Lists!$AO$2:$AO$11,MATCH(ROW(),Lists!$AN$2:$AN$11,0)),""),IFERROR(INDEX(Lists!$U:$U,MATCH(TRIM($I28),Lists!$T:$T,0)),TRIM($I28)))) -> Ampol Retail | AK28: =IF(ISNUMBER(SEARCH("vacant",$B28)),"Vacant","Filled") -> Filled | AL28: =IF($M28="NZ","NZ","AU") -> AU | AM28: =COUNTIF($AJ$2:$AJ28,$AJ28) -> 12 | AN28: =$AJ28&"|"&$AM28 -> Ampol Retail|12 | AP28: =IF(TRIM($B28)="","",IF($AQ28=1,"Leadership",IFERROR(INDEX(Lists!$X:$X,MATCH(TRIM($K28),Lists!$W:$W,0)),IF(OR(TRIM($K28)="",LOWER(TRIM($K28))="na"),IF(TRIM($G28)="","Unassigned",TRIM($G28)),TRIM($K28))))) -> Store Operations | AQ28: =IF(TRIM($B28)="","",--OR(TRIM($K28)="Leadership",TRIM($J28)="Leadership")) -> FALSE | AR28: =IF(TRIM($B28)="","",IF(IFERROR(INDEX(Lists!$AQ$2:$AQ$11,MATCH(ROW(),Lists!$AN$2:$AN$11,0)),"")<>"",IFERROR(INDEX(Lists!$AQ$2:$AQ$11,MATCH(ROW(),Lists!$AN$2:$AN$11,0)),""),IF(ISNUMBER(SEARCH("head of ",$C28)),"Head of Technology",IF(ISNUMBER(SEARCH("TDD BP",$C28)),"Business Partner",IF(OR(ISNUMBER(SEARCH("domain architect",$C28)),ISNUMBER(SEARCH("enterprise architect",$C28))),"Domain Architect",IF(ISNUMBER(SEARCH("delivery man",$C28)),"Delivery Manager",IF(OR(ISNUMBER(SEARCH("technology manager",$C28)),ISNUMBER(SEARCH("technology manger",$C28)),ISNUMBER(SEARCH("tech manager",$C28))),"Technology Manager","Squad"))))))) -> Squad | AS28: =IF(TRIM($B28)="","",IFERROR(INDEX(Lists!$AA:$AA,MATCH($AP28,Lists!$Z:$Z,0)),$AP28)) -> Store Operations | AT28: =IF(TRIM($B28)="","",IF(IFERROR(INDEX(Lists!$AP$2:$AP$11,MATCH(ROW(),Lists!$AN$2:$AN$11,0)),"")<>"",IFERROR(INDEX(Lists!$AP$2:$AP$11,MATCH(ROW(),Lists!$AN$2:$AN$11,0)),""),IF(OR(LEFT($AJ28,3)="COE",$AJ28="EGI"),$AP28,IF($AR28<>"Squad",$AR28,$AP28)))) -> Store Operations
A29: 99999100699 | B29: Helen Jones | C29: Delivery Lead | D29: Vacant | E29: Delivery Manager, Z and Retail Data | F29: Ampol Retail & Z | G29: Z & Group Retail | H29: Z & Group Retail, Delivery | I29: Z | J29: Z Supply | K29: Z Supply | M29: NZ | N29: CIC | O29: 1 | Q29: Permanent - Full Time | T29: 179340 | U29: 179340 | V29: 0.12 | W29: 0.055 | X29: 0.12 | Z29: 0.04 | AA29: =IF(TRIM($B29)="","",IF(N($AU29)>0,$AU29,IF(N($S29)>0,$S29*Lists!$AG$15*(1+N($Z29)),N($U29)*(1+N($V29)+N($W29)+N($X29)+N($Z29))+N($Y29)))) -> 239418.9 | AJ29: =IF(TRIM($B29)="","",IF(IFERROR(INDEX(Lists!$AO$2:$AO$11,MATCH(ROW(),Lists!$AN$2:$AN$11,0)),"")<>"",IFERROR(INDEX(Lists!$AO$2:$AO$11,MATCH(ROW(),Lists!$AN$2:$AN$11,0)),""),IFERROR(INDEX(Lists!$U:$U,MATCH(TRIM($I29),Lists!$T:$T,0)),TRIM($I29)))) -> Z Retail | AK29: =IF(ISNUMBER(SEARCH("vacant",$B29)),"Vacant","Filled") -> Filled | AL29: =IF($M29="NZ","NZ","AU") -> NZ | AM29: =COUNTIF($AJ$2:$AJ29,$AJ29) -> 16 | AN29: =$AJ29&"|"&$AM29 -> Z Retail|16 | AP29: =IF(TRIM($B29)="","",IF($AQ29=1,"Leadership",IFERROR(INDEX(Lists!$X:$X,MATCH(TRIM($K29),Lists!$W:$W,0)),IF(OR(TRIM($K29)="",LOWER(TRIM($K29))="na"),IF(TRIM($G29)="","Unassigned",TRIM($G29)),TRIM($K29))))) -> Z Supply | AQ29: =IF(TRIM($B29)="","",--OR(TRIM($K29)="Leadership",TRIM($J29)="Leadership")) -> FALSE | AR29: =IF(TRIM($B29)="","",IF(IFERROR(INDEX(Lists!$AQ$2:$AQ$11,MATCH(ROW(),Lists!$AN$2:$AN$11,0)),"")<>"",IFERROR(INDEX(Lists!$AQ$2:$AQ$11,MATCH(ROW(),Lists!$AN$2:$AN$11,0)),""),IF(ISNUMBER(SEARCH("head of ",$C29)),"Head of Technology",IF(ISNUMBER(SEARCH("TDD BP",$C29)),"Business Partner",IF(OR(ISNUMBER(SEARCH("domain architect",$C29)),ISNUMBER(SEARCH("enterprise architect",$C29))),"Domain Architect",IF(ISNUMBER(SEARCH("delivery man",$C29)),"Delivery Manager",IF(OR(ISNUMBER(SEARCH("technology manager",$C29)),ISNUMBER(SEARCH("technology manger",$C29)),ISNUMBER(SEARCH("tech manager",$C29))),"Technology Manager","Squad"))))))) -> Squad | AS29: =IF(TRIM($B29)="","",IFERROR(INDEX(Lists!$AA:$AA,MATCH($AP29,Lists!$Z:$Z,0)),$AP29)) -> Z Supply | AT29: =IF(TRIM($B29)="","",IF(IFERROR(INDEX(Lists!$AP$2:$AP$11,MATCH(ROW(),Lists!$AN$2:$AN$11,0)),"")<>"",IFERROR(INDEX(Lists!$AP$2:$AP$11,MATCH(ROW(),Lists!$AN$2:$AN$11,0)),""),IF(OR(LEFT($AJ29,3)="COE",$AJ29="EGI"),$AP29,IF($AR29<>"Squad",$AR29,$AP29)))) -> Z Supply
A30: 110704 | B30: Irfan Zavahir | C30: Delivery Lead | D30: Vanessa Allen | E30: Delivery Manager, Ampol Retail | F30: Ampol Retail & Z | G30: Ampol Retail | H30: Ampol Retail, Delivery | I30: Retail | J30: AMPOS | K30: AmPos | M30: Australia | N30: CIC | O30: 1 | Q30: Permanent - Full Time | T30: 140000 | U30: 128800 | V30: 0.15 | X30: 0.05 | Y30: 2910 | Z30: 0.03 | AA30: =IF(TRIM($B30)="","",IF(N($AU30)>0,$AU30,IF(N($S30)>0,$S30*Lists!$AG$15*(1+N($Z30)),N($U30)*(1+N($V30)+N($W30)+N($X30)+N($Z30))+N($Y30)))) -> 161334 | AJ30: =IF(TRIM($B30)="","",IF(IFERROR(INDEX(Lists!$AO$2:$AO$11,MATCH(ROW(),Lists!$AN$2:$AN$11,0)),"")<>"",IFERROR(INDEX(Lists!$AO$2:$AO$11,MATCH(ROW(),Lists!$AN$2:$AN$11,0)),""),IFERROR(INDEX(Lists!$U:$U,MATCH(TRIM($I30),Lists!$T:$T,0)),TRIM($I30)))) -> Ampol Retail | AK30: =IF(ISNUMBER(SEARCH("vacant",$B30)),"Vacant","Filled") -> Filled | AL30: =IF($M30="NZ","NZ","AU") -> AU | AM30: =COUNTIF($AJ$2:$AJ30,$AJ30) -> 13 | AN30: =$AJ30&"|"&$AM30 -> Ampol Retail|13 | AP30: =IF(TRIM($B30)="","",IF($AQ30=1,"Leadership",IFERROR(INDEX(Lists!$X:$X,MATCH(TRIM($K30),Lists!$W:$W,0)),IF(OR(TRIM($K30)="",LOWER(TRIM($K30))="na"),IF(TRIM($G30)="","Unassigned",TRIM($G30)),TRIM($K30))))) -> AmPOS | AQ30: =IF(TRIM($B30)="","",--OR(TRIM($K30)="Leadership",TRIM($J30)="Leadership")) -> FALSE | AR30: =IF(TRIM($B30)="","",IF(IFERROR(INDEX(Lists!$AQ$2:$AQ$11,MATCH(ROW(),Lists!$AN$2:$AN$11,0)),"")<>"",IFERROR(INDEX(Lists!$AQ$2:$AQ$11,MATCH(ROW(),Lists!$AN$2:$AN$11,0)),""),IF(ISNUMBER(SEARCH("head of ",$C30)),"Head of Technology",IF(ISNUMBER(SEARCH("TDD BP",$C30)),"Business Partner",IF(OR(ISNUMBER(SEARCH("domain architect",$C30)),ISNUMBER(SEARCH("enterprise architect",$C30))),"Domain Architect",IF(ISNUMBER(SEARCH("delivery man",$C30)),"Delivery Manager",IF(OR(ISNUMBER(SEARCH("technology manager",$C30)),ISNUMBER(SEARCH("technology manger",$C30)),ISNUMBER(SEARCH("tech manager",$C30))),"Technology Manager","Squad"))))))) -> Squad | AS30: =IF(TRIM($B30)="","",IFERROR(INDEX(Lists!$AA:$AA,MATCH($AP30,Lists!$Z:$Z,0)),$AP30)) -> AmPOS | AT30: =IF(TRIM($B30)="","",IF(IFERROR(INDEX(Lists!$AP$2:$AP$11,MATCH(ROW(),Lists!$AN$2:$AN$11,0)),"")<>"",IFERROR(INDEX(Lists!$AP$2:$AP$11,MATCH(ROW(),Lists!$AN$2:$AN$11,0)),""),IF(OR(LEFT($AJ30,3)="COE",$AJ30="EGI"),$AP30,IF($AR30<>"Squad",$AR30,$AP30)))) -> AmPOS
A31: 99999102104 | B31: Isuru Herath | C31: Senior Engineer - Software | D31: Vacant | E31: Technology Manager, Engineering | F31: Ampol Retail & Z | G31: Z & Group Retail | H31: Z & Group Retail, Engineering | I31: Z | J31: Z Supply | K31: Z Supply | M31: NZ | N31: CIB | O31: 1 | Q31: Permanent - Full Time | T31: 168160 | U31: 168160 | V31: 0.12 | W31: 0.055 | X31: 0.12 | Z31: 0.04 | AA31: =IF(TRIM($B31)="","",IF(N($AU31)>0,$AU31,IF(N($S31)>0,$S31*Lists!$AG$15*(1+N($Z31)),N($U31)*(1+N($V31)+N($W31)+N($X31)+N($Z31))+N($Y31)))) -> 224493.6 | AJ31: =IF(TRIM($B31)="","",IF(IFERROR(INDEX(Lists!$AO$2:$AO$11,MATCH(ROW(),Lists!$AN$2:$AN$11,0)),"")<>"",IFERROR(INDEX(Lists!$AO$2:$AO$11,MATCH(ROW(),Lists!$AN$2:$AN$11,0)),""),IFERROR(INDEX(Lists!$U:$U,MATCH(TRIM($I31),Lists!$T:$T,0)),TRIM($I31)))) -> Z Retail | AK31: =IF(ISNUMBER(SEARCH("vacant",$B31)),"Vacant","Filled") -> Filled | AL31: =IF($M31="NZ","NZ","AU") -> NZ | AM31: =COUNTIF($AJ$2:$AJ31,$AJ31) -> 17 | AN31: =$AJ31&"|"&$AM31 -> Z Retail|17 | AP31: =IF(TRIM($B31)="","",IF($AQ31=1,"Leadership",IFERROR(INDEX(Lists!$X:$X,MATCH(TRIM($K31),Lists!$W:$W,0)),IF(OR(TRIM($K31)="",LOWER(TRIM($K31))="na"),IF(TRIM($G31)="","Unassigned",TRIM($G31)),TRIM($K31))))) -> Z Supply | AQ31: =IF(TRIM($B31)="","",--OR(TRIM($K31)="Leadership",TRIM($J31)="Leadership")) -> FALSE | AR31: =IF(TRIM($B31)="","",IF(IFERROR(INDEX(Lists!$AQ$2:$AQ$11,MATCH(ROW(),Lists!$AN$2:$AN$11,0)),"")<>"",IFERROR(INDEX(Lists!$AQ$2:$AQ$11,MATCH(ROW(),Lists!$AN$2:$AN$11,0)),""),IF(ISNUMBER(SEARCH("head of ",$C31)),"Head of Technology",IF(ISNUMBER(SEARCH("TDD BP",$C31)),"Business Partner",IF(OR(ISNUMBER(SEARCH("domain architect",$C31)),ISNUMBER(SEARCH("enterprise architect",$C31))),"Domain Architect",IF(ISNUMBER(SEARCH("delivery man",$C31)),"Delivery Manager",IF(OR(ISNUMBER(SEARCH("technology manager",$C31)),ISNUMBER(SEARCH("technology manger",$C31)),ISNUMBER(SEARCH("tech manager",$C31))),"Technology Manager","Squad"))))))) -> Squad | AS31: =IF(TRIM($B31)="","",IFERROR(INDEX(Lists!$AA:$AA,MATCH($AP31,Lists!$Z:$Z,0)),$AP31)) -> Z Supply | AT31: =IF(TRIM($B31)="","",IF(IFERROR(INDEX(Lists!$AP$2:$AP$11,MATCH(ROW(),Lists!$AN$2:$AN$11,0)),"")<>"",IFERROR(INDEX(Lists!$AP$2:$AP$11,MATCH(ROW(),Lists!$AN$2:$AN$11,0)),""),IF(OR(LEFT($AJ31,3)="COE",$AJ31="EGI"),$AP31,IF($AR31<>"Squad",$AR31,$AP31)))) -> Z Supply
A32: 91356 | B32: Javier Aguirre Castellanos | C32: Solution Architect | D32: Vedran Jukic | E32: Technology Manager, Retail | F32: Ampol Retail & Z | G32: Ampol Retail | H32: Ampol Retail, Technology | I32: Retail | J32: Network/QSR | K32: Network & QSR | M32: Australia | N32: CIB | O32: 1 | Q32: Permanent - Full Time | T32: 115000 | U32: 105800 | V32: 0.15 | X32: 0.05 | Y32: 2910 | Z32: 0.03 | AA32: =IF(TRIM($B32)="","",IF(N($AU32)>0,$AU32,IF(N($S32)>0,$S32*Lists!$AG$15*(1+N($Z32)),N($U32)*(1+N($V32)+N($W32)+N($X32)+N($Z32))+N($Y32)))) -> 133044 | AJ32: =IF(TRIM($B32)="","",IF(IFERROR(INDEX(Lists!$AO$2:$AO$11,MATCH(ROW(),Lists!$AN$2:$AN$11,0)),"")<>"",IFERROR(INDEX(Lists!$AO$2:$AO$11,MATCH(ROW(),Lists!$AN$2:$AN$11,0)),""),IFERROR(INDEX(Lists!$U:$U,MATCH(TRIM($I32),Lists!$T:$T,0)),TRIM($I32)))) -> Ampol Retail | AK32: =IF(ISNUMBER(SEARCH("vacant",$B32)),"Vacant","Filled") -> Filled | AL32: =IF($M32="NZ","NZ","AU") -> AU | AM32: =COUNTIF($AJ$2:$AJ32,$AJ32) -> 14 | AN32: =$AJ32&"|"&$AM32 -> Ampol Retail|14 | AP32: =IF(TRIM($B32)="","",IF($AQ32=1,"Leadership",IFERROR(INDEX(Lists!$X:$X,MATCH(TRIM($K32),Lists!$W:$W,0)),IF(OR(TRIM($K32)="",LOWER(TRIM($K32))="na"),IF(TRIM($G32)="","Unassigned",TRIM($G32)),TRIM($K32))))) -> Network & QSR | AQ32: =IF(TRIM($B32)="","",--OR(TRIM($K32)="Leadership",TRIM($J32)="Leadership")) -> FALSE | AR32: =IF(TRIM($B32)="","",IF(IFERROR(INDEX(Lists!$AQ$2:$AQ$11,MATCH(ROW(),Lists!$AN$2:$AN$11,0)),"")<>"",IFERROR(INDEX(Lists!$AQ$2:$AQ$11,MATCH(ROW(),Lists!$AN$2:$AN$11,0)),""),IF(ISNUMBER(SEARCH("head of ",$C32)),"Head of Technology",IF(ISNUMBER(SEARCH("TDD BP",$C32)),"Business Partner",IF(OR(ISNUMBER(SEARCH("domain architect",$C32)),ISNUMBER(SEARCH("enterprise architect",$C32))),"Domain Architect",IF(ISNUMBER(SEARCH("delivery man",$C32)),"Delivery Manager",IF(OR(ISNUMBER(SEARCH("technology manager",$C32)),ISNUMBER(SEARCH("technology manger",$C32)),ISNUMBER(SEARCH("tech manager",$C32))),"Technology Manager","Squad"))))))) -> Squad | AS32: =IF(TRIM($B32)="","",IFERROR(INDEX(Lists!$AA:$AA,MATCH($AP32,Lists!$Z:$Z,0)),$AP32)) -> Network & QSR | AT32: =IF(TRIM($B32)="","",IF(IFERROR(INDEX(Lists!$AP$2:$AP$11,MATCH(ROW(),Lists!$AN$2:$AN$11,0)),"")<>"",IFERROR(INDEX(Lists!$AP$2:$AP$11,MATCH(ROW(),Lists!$AN$2:$AN$11,0)),""),IF(OR(LEFT($AJ32,3)="COE",$AJ32="EGI"),$AP32,IF($AR32<>"Squad",$AR32,$AP32)))) -> Network & QSR
A33: 99999102123 | B33: Jodie Marquez | C33: Data Analyst | D33: Vacant | E33: Technology Manager, Data | F33: Ampol Retail & Z | G33: Z & Group Retail | H33: Z & Group Retail, Data | I33: Z | J33: Z Customer & Z Supply | K33: Data - NZ | M33: NZ | N33: CIA | O33: 1 | Q33: Permanent - Full Time | T33: 125250 | U33: 115230 | V33: 0.15 | X33: 0.05 | Y33: 2910 | Z33: 0.03 | AA33: =IF(TRIM($B33)="","",IF(N($AU33)>0,$AU33,IF(N($S33)>0,$S33*Lists!$AG$15*(1+N($Z33)),N($U33)*(1+N($V33)+N($W33)+N($X33)+N($Z33))+N($Y33)))) -> 144642.9 | AJ33: =IF(TRIM($B33)="","",IF(IFERROR(INDEX(Lists!$AO$2:$AO$11,MATCH(ROW(),Lists!$AN$2:$AN$11,0)),"")<>"",IFERROR(INDEX(Lists!$AO$2:$AO$11,MATCH(ROW(),Lists!$AN$2:$AN$11,0)),""),IFERROR(INDEX(Lists!$U:$U,MATCH(TRIM($I33),Lists!$T:$T,0)),TRIM($I33)))) -> Z Retail | AK33: =IF(ISNUMBER(SEARCH("vacant",$B33)),"Vacant","Filled") -> Filled | AL33: =IF($M33="NZ","NZ","AU") -> NZ | AM33: =COUNTIF($AJ$2:$AJ33,$AJ33) -> 18 | AN33: =$AJ33&"|"&$AM33 -> Z Retail|18 | AP33: =IF(TRIM($B33)="","",IF($AQ33=1,"Leadership",IFERROR(INDEX(Lists!$X:$X,MATCH(TRIM($K33),Lists!$W:$W,0)),IF(OR(TRIM($K33)="",LOWER(TRIM($K33))="na"),IF(TRIM($G33)="","Unassigned",TRIM($G33)),TRIM($K33))))) -> Data NZ | AQ33: =IF(TRIM($B33)="","",--OR(TRIM($K33)="Leadership",TRIM($J33)="Leadership")) -> FALSE | AR33: =IF(TRIM($B33)="","",IF(IFERROR(INDEX(Lists!$AQ$2:$AQ$11,MATCH(ROW(),Lists!$AN$2:$AN$11,0)),"")<>"",IFERROR(INDEX(Lists!$AQ$2:$AQ$11,MATCH(ROW(),Lists!$AN$2:$AN$11,0)),""),IF(ISNUMBER(SEARCH("head of ",$C33)),"Head of Technology",IF(ISNUMBER(SEARCH("TDD BP",$C33)),"Business Partner",IF(OR(ISNUMBER(SEARCH("domain architect",$C33)),ISNUMBER(SEARCH("enterprise architect",$C33))),"Domain Architect",IF(ISNUMBER(SEARCH("delivery man",$C33)),"Delivery Manager",IF(OR(ISNUMBER(SEARCH("technology manager",$C33)),ISNUMBER(SEARCH("technology manger",$C33)),ISNUMBER(SEARCH("tech manager",$C33))),"Technology Manager","Squad"))))))) -> Squad | AS33: =IF(TRIM($B33)="","",IFERROR(INDEX(Lists!$AA:$AA,MATCH($AP33,Lists!$Z:$Z,0)),$AP33)) -> Data NZ | AT33: =IF(TRIM($B33)="","",IF(IFERROR(INDEX(Lists!$AP$2:$AP$11,MATCH(ROW(),Lists!$AN$2:$AN$11,0)),"")<>"",IFERROR(INDEX(Lists!$AP$2:$AP$11,MATCH(ROW(),Lists!$AN$2:$AN$11,0)),""),IF(OR(LEFT($AJ33,3)="COE",$AJ33="EGI"),$AP33,IF($AR33<>"Squad",$AR33,$AP33)))) -> Data NZ
A34: 99999101542 | B34: Joe Kuttikkatt | C34: Senior Quality Assurance | D34: Vacant | E34: Technology Manager, Engineering | F34: Ampol Retail & Z | G34: Z & Group Retail | H34: Z & Group Retail, Engineering | I34: Z | J34: Z Supply | K34: Z Supply | M34: NZ | N34: CIA | O34: 1 | Q34: Permanent - Full Time | T34: 93640 | U34: 86148.8 | V34: 0.1 | X34: 0.05 | Y34: 2910 | Z34: 0.03 | AA34: =IF(TRIM($B34)="","",IF(N($AU34)>0,$AU34,IF(N($S34)>0,$S34*Lists!$AG$15*(1+N($Z34)),N($U34)*(1+N($V34)+N($W34)+N($X34)+N($Z34))+N($Y34)))) -> 104565.58 | AJ34: =IF(TRIM($B34)="","",IF(IFERROR(INDEX(Lists!$AO$2:$AO$11,MATCH(ROW(),Lists!$AN$2:$AN$11,0)),"")<>"",IFERROR(INDEX(Lists!$AO$2:$AO$11,MATCH(ROW(),Lists!$AN$2:$AN$11,0)),""),IFERROR(INDEX(Lists!$U:$U,MATCH(TRIM($I34),Lists!$T:$T,0)),TRIM($I34)))) -> Z Retail | AK34: =IF(ISNUMBER(SEARCH("vacant",$B34)),"Vacant","Filled") -> Filled | AL34: =IF($M34="NZ","NZ","AU") -> NZ | AM34: =COUNTIF($AJ$2:$AJ34,$AJ34) -> 19 | AN34: =$AJ34&"|"&$AM34 -> Z Retail|19 | AP34: =IF(TRIM($B34)="","",IF($AQ34=1,"Leadership",IFERROR(INDEX(Lists!$X:$X,MATCH(TRIM($K34),Lists!$W:$W,0)),IF(OR(TRIM($K34)="",LOWER(TRIM($K34))="na"),IF(TRIM($G34)="","Unassigned",TRIM($G34)),TRIM($K34))))) -> Z Supply | AQ34: =IF(TRIM($B34)="","",--OR(TRIM($K34)="Leadership",TRIM($J34)="Leadership")) -> FALSE | AR34: =IF(TRIM($B34)="","",IF(IFERROR(INDEX(Lists!$AQ$2:$AQ$11,MATCH(ROW(),Lists!$AN$2:$AN$11,0)),"")<>"",IFERROR(INDEX(Lists!$AQ$2:$AQ$11,MATCH(ROW(),Lists!$AN$2:$AN$11,0)),""),IF(ISNUMBER(SEARCH("head of ",$C34)),"Head of Technology",IF(ISNUMBER(SEARCH("TDD BP",$C34)),"Business Partner",IF(OR(ISNUMBER(SEARCH("domain architect",$C34)),ISNUMBER(SEARCH("enterprise architect",$C34))),"Domain Architect",IF(ISNUMBER(SEARCH("delivery man",$C34)),"Delivery Manager",IF(OR(ISNUMBER(SEARCH("technology manager",$C34)),ISNUMBER(SEARCH("technology manger",$C34)),ISNUMBER(SEARCH("tech manager",$C34))),"Technology Manager","Squad"))))))) -> Squad | AS34: =IF(TRIM($B34)="","",IFERROR(INDEX(Lists!$AA:$AA,MATCH($AP34,Lists!$Z:$Z,0)),$AP34)) -> Z Supply | AT34: =IF(TRIM($B34)="","",IF(IFERROR(INDEX(Lists!$AP$2:$AP$11,MATCH(ROW(),Lists!$AN$2:$AN$11,0)),"")<>"",IFERROR(INDEX(Lists!$AP$2:$AP$11,MATCH(ROW(),Lists!$AN$2:$AN$11,0)),""),IF(OR(LEFT($AJ34,3)="COE",$AJ34="EGI"),$AP34,IF($AR34<>"Squad",$AR34,$AP34)))) -> Z Supply
A35: 99999101620 | B35: Johanah Gloria | C35: Engineer - Software | D35: Vacant | E35: Technology Manager, Engineering | F35: Ampol Retail & Z | G35: Z & Group Retail | H35: Z & Group Retail, Engineering | I35: Z | J35: Z Supply | K35: Z Supply | M35: NZ | N35: CDB | O35: 1 | Q35: Permanent - Full Time | T35: 142360 | U35: 142360 | V35: 0.12 | W35: 0.055 | X35: 0.12 | Z35: 0.04 | AA35: =IF(TRIM($B35)="","",IF(N($AU35)>0,$AU35,IF(N($S35)>0,$S35*Lists!$AG$15*(1+N($Z35)),N($U35)*(1+N($V35)+N($W35)+N($X35)+N($Z35))+N($Y35)))) -> 190050.6 | AJ35: =IF(TRIM($B35)="","",IF(IFERROR(INDEX(Lists!$AO$2:$AO$11,MATCH(ROW(),Lists!$AN$2:$AN$11,0)),"")<>"",IFERROR(INDEX(Lists!$AO$2:$AO$11,MATCH(ROW(),Lists!$AN$2:$AN$11,0)),""),IFERROR(INDEX(Lists!$U:$U,MATCH(TRIM($I35),Lists!$T:$T,0)),TRIM($I35)))) -> Z Retail | AK35: =IF(ISNUMBER(SEARCH("vacant",$B35)),"Vacant","Filled") -> Filled | AL35: =IF($M35="NZ","NZ","AU") -> NZ | AM35: =COUNTIF($AJ$2:$AJ35,$AJ35) -> 20 | AN35: =$AJ35&"|"&$AM35 -> Z Retail|20 | AP35: =IF(TRIM($B35)="","",IF($AQ35=1,"Leadership",IFERROR(INDEX(Lists!$X:$X,MATCH(TRIM($K35),Lists!$W:$W,0)),IF(OR(TRIM($K35)="",LOWER(TRIM($K35))="na"),IF(TRIM($G35)="","Unassigned",TRIM($G35)),TRIM($K35))))) -> Z Supply | AQ35: =IF(TRIM($B35)="","",--OR(TRIM($K35)="Leadership",TRIM($J35)="Leadership")) -> FALSE | AR35: =IF(TRIM($B35)="","",IF(IFERROR(INDEX(Lists!$AQ$2:$AQ$11,MATCH(ROW(),Lists!$AN$2:$AN$11,0)),"")<>"",IFERROR(INDEX(Lists!$AQ$2:$AQ$11,MATCH(ROW(),Lists!$AN$2:$AN$11,0)),""),IF(ISNUMBER(SEARCH("head of ",$C35)),"Head of Technology",IF(ISNUMBER(SEARCH("TDD BP",$C35)),"Business Partner",IF(OR(ISNUMBER(SEARCH("domain architect",$C35)),ISNUMBER(SEARCH("enterprise architect",$C35))),"Domain Architect",IF(ISNUMBER(SEARCH("delivery man",$C35)),"Delivery Manager",IF(OR(ISNUMBER(SEARCH("technology manager",$C35)),ISNUMBER(SEARCH("technology manger",$C35)),ISNUMBER(SEARCH("tech manager",$C35))),"Technology Manager","Squad"))))))) -> Squad | AS35: =IF(TRIM($B35)="","",IFERROR(INDEX(Lists!$AA:$AA,MATCH($AP35,Lists!$Z:$Z,0)),$AP35)) -> Z Supply | AT35: =IF(TRIM($B35)="","",IF(IFERROR(INDEX(Lists!$AP$2:$AP$11,MATCH(ROW(),Lists!$AN$2:$AN$11,0)),"")<>"",IFERROR(INDEX(Lists!$AP$2:$AP$11,MATCH(ROW(),Lists!$AN$2:$AN$11,0)),""),IF(OR(LEFT($AJ35,3)="COE",$AJ35="EGI"),$AP35,IF($AR35<>"Squad",$AR35,$AP35)))) -> Z Supply
A36: 7001 | B36: Joseph Maroun | C36: Systems Analyst | D36: Tracy Lee Reaper | E36: Tech Manager, Merchandising & WFM | F36: Ampol Retail & Z | G36: Ampol Retail | H36: Ampol Retail, Merch & RTA | I36: Retail | J36: Above Store | K36: Above Store | M36: Australia | N36: CIB | O36: 1 | Q36: Permanent - Full Time | T36: 134270 | U36: 134270 | V36: 0.1 | W36: 0.055 | X36: 0.12 | Z36: 0.04 | AA36: =IF(TRIM($B36)="","",IF(N($AU36)>0,$AU36,IF(N($S36)>0,$S36*Lists!$AG$15*(1+N($Z36)),N($U36)*(1+N($V36)+N($W36)+N($X36)+N($Z36))+N($Y36)))) -> 176565.05 | AJ36: =IF(TRIM($B36)="","",IF(IFERROR(INDEX(Lists!$AO$2:$AO$11,MATCH(ROW(),Lists!$AN$2:$AN$11,0)),"")<>"",IFERROR(INDEX(Lists!$AO$2:$AO$11,MATCH(ROW(),Lists!$AN$2:$AN$11,0)),""),IFERROR(INDEX(Lists!$U:$U,MATCH(TRIM($I36),Lists!$T:$T,0)),TRIM($I36)))) -> Ampol Retail | AK36: =IF(ISNUMBER(SEARCH("vacant",$B36)),"Vacant","Filled") -> Filled | AL36: =IF($M36="NZ","NZ","AU") -> AU | AM36: =COUNTIF($AJ$2:$AJ36,$AJ36) -> 15 | AN36: =$AJ36&"|"&$AM36 -> Ampol Retail|15 | AP36: =IF(TRIM($B36)="","",IF($AQ36=1,"Leadership",IFERROR(INDEX(Lists!$X:$X,MATCH(TRIM($K36),Lists!$W:$W,0)),IF(OR(TRIM($K36)="",LOWER(TRIM($K36))="na"),IF(TRIM($G36)="","Unassigned",TRIM($G36)),TRIM($K36))))) -> Above Store | AQ36: =IF(TRIM($B36)="","",--OR(TRIM($K36)="Leadership",TRIM($J36)="Leadership")) -> FALSE | AR36: =IF(TRIM($B36)="","",IF(IFERROR(INDEX(Lists!$AQ$2:$AQ$11,MATCH(ROW(),Lists!$AN$2:$AN$11,0)),"")<>"",IFERROR(INDEX(Lists!$AQ$2:$AQ$11,MATCH(ROW(),Lists!$AN$2:$AN$11,0)),""),IF(ISNUMBER(SEARCH("head of ",$C36)),"Head of Technology",IF(ISNUMBER(SEARCH("TDD BP",$C36)),"Business Partner",IF(OR(ISNUMBER(SEARCH("domain architect",$C36)),ISNUMBER(SEARCH("enterprise architect",$C36))),"Domain Architect",IF(ISNUMBER(SEARCH("delivery man",$C36)),"Delivery Manager",IF(OR(ISNUMBER(SEARCH("technology manager",$C36)),ISNUMBER(SEARCH("technology manger",$C36)),ISNUMBER(SEARCH("tech manager",$C36))),"Technology Manager","Squad"))))))) -> Squad | AS36: =IF(TRIM($B36)="","",IFERROR(INDEX(Lists!$AA:$AA,MATCH($AP36,Lists!$Z:$Z,0)),$AP36)) -> Above Store | AT36: =IF(TRIM($B36)="","",IF(IFERROR(INDEX(Lists!$AP$2:$AP$11,MATCH(ROW(),Lists!$AN$2:$AN$11,0)),"")<>"",IFERROR(INDEX(Lists!$AP$2:$AP$11,MATCH(ROW(),Lists!$AN$2:$AN$11,0)),""),IF(OR(LEFT($AJ36,3)="COE",$AJ36="EGI"),$AP36,IF($AR36<>"Squad",$AR36,$AP36)))) -> Above Store
A37: 84413 | B37: Karthick Sathiyamoorthy | C37: Quality Assurance | D37: Vacant | E37: Lead Quality Assurance | F37: Ampol Retail & Z | G37: Ampol Retail | H37: Ampol Retail, Store Platforms | I37: Retail | J37: AMPOS | K37: AmPos | M37: Australia | N37: CIA | O37: 1 | Q37: Permanent - Full Time | T37: 145340 | U37: 145340 | V37: 0.12 | W37: 0.055 | X37: 0.12 | Z37: 0.04 | AA37: =IF(TRIM($B37)="","",IF(N($AU37)>0,$AU37,IF(N($S37)>0,$S37*Lists!$AG$15*(1+N($Z37)),N($U37)*(1+N($V37)+N($W37)+N($X37)+N($Z37))+N($Y37)))) -> 194028.9 | AJ37: =IF(TRIM($B37)="","",IF(IFERROR(INDEX(Lists!$AO$2:$AO$11,MATCH(ROW(),Lists!$AN$2:$AN$11,0)),"")<>"",IFERROR(INDEX(Lists!$AO$2:$AO$11,MATCH(ROW(),Lists!$AN$2:$AN$11,0)),""),IFERROR(INDEX(Lists!$U:$U,MATCH(TRIM($I37),Lists!$T:$T,0)),TRIM($I37)))) -> Ampol Retail | AK37: =IF(ISNUMBER(SEARCH("vacant",$B37)),"Vacant","Filled") -> Filled | AL37: =IF($M37="NZ","NZ","AU") -> AU | AM37: =COUNTIF($AJ$2:$AJ37,$AJ37) -> 16 | AN37: =$AJ37&"|"&$AM37 -> Ampol Retail|16 | AP37: =IF(TRIM($B37)="","",IF($AQ37=1,"Leadership",IFERROR(INDEX(Lists!$X:$X,MATCH(TRIM($K37),Lists!$W:$W,0)),IF(OR(TRIM($K37)="",LOWER(TRIM($K37))="na"),IF(TRIM($G37)="","Unassigned",TRIM($G37)),TRIM($K37))))) -> AmPOS | AQ37: =IF(TRIM($B37)="","",--OR(TRIM($K37)="Leadership",TRIM($J37)="Leadership")) -> FALSE | AR37: =IF(TRIM($B37)="","",IF(IFERROR(INDEX(Lists!$AQ$2:$AQ$11,MATCH(ROW(),Lists!$AN$2:$AN$11,0)),"")<>"",IFERROR(INDEX(Lists!$AQ$2:$AQ$11,MATCH(ROW(),Lists!$AN$2:$AN$11,0)),""),IF(ISNUMBER(SEARCH("head of ",$C37)),"Head of Technology",IF(ISNUMBER(SEARCH("TDD BP",$C37)),"Business Partner",IF(OR(ISNUMBER(SEARCH("domain architect",$C37)),ISNUMBER(SEARCH("enterprise architect",$C37))),"Domain Architect",IF(ISNUMBER(SEARCH("delivery man",$C37)),"Delivery Manager",IF(OR(ISNUMBER(SEARCH("technology manager",$C37)),ISNUMBER(SEARCH("technology manger",$C37)),ISNUMBER(SEARCH("tech manager",$C37))),"Technology Manager","Squad"))))))) -> Squad | AS37: =IF(TRIM($B37)="","",IFERROR(INDEX(Lists!$AA:$AA,MATCH($AP37,Lists!$Z:$Z,0)),$AP37)) -> AmPOS | AT37: =IF(TRIM($B37)="","",IF(IFERROR(INDEX(Lists!$AP$2:$AP$11,MATCH(ROW(),Lists!$AN$2:$AN$11,0)),"")<>"",IFERROR(INDEX(Lists!$AP$2:$AP$11,MATCH(ROW(),Lists!$AN$2:$AN$11,0)),""),IF(OR(LEFT($AJ37,3)="COE",$AJ37="EGI"),$AP37,IF($AR37<>"Squad",$AR37,$AP37)))) -> AmPOS
A38: 85321 | B38: Karthikeyan Kuppan | C38: Lead - AU Retail Operations | D38: Vaishnavi Viswanathan | E38: Technology Manager, Store Platform | F38: Ampol Retail & Z | G38: Ampol Retail | H38: Ampol Retail, Store Platforms | I38: Retail | J38: Store Operations | K38: Store Operations | M38: Australia | N38: CIB | O38: 1 | Q38: Permanent - Full Time | T38: 212110 | U38: 195141.2 | V38: 0.15 | X38: 0.05 | Y38: 2910 | Z38: 0.03 | AA38: =IF(TRIM($B38)="","",IF(N($AU38)>0,$AU38,IF(N($S38)>0,$S38*Lists!$AG$15*(1+N($Z38)),N($U38)*(1+N($V38)+N($W38)+N($X38)+N($Z38))+N($Y38)))) -> 242933.68 | AJ38: =IF(TRIM($B38)="","",IF(IFERROR(INDEX(Lists!$AO$2:$AO$11,MATCH(ROW(),Lists!$AN$2:$AN$11,0)),"")<>"",IFERROR(INDEX(Lists!$AO$2:$AO$11,MATCH(ROW(),Lists!$AN$2:$AN$11,0)),""),IFERROR(INDEX(Lists!$U:$U,MATCH(TRIM($I38),Lists!$T:$T,0)),TRIM($I38)))) -> Ampol Retail | AK38: =IF(ISNUMBER(SEARCH("vacant",$B38)),"Vacant","Filled") -> Filled | AL38: =IF($M38="NZ","NZ","AU") -> AU | AM38: =COUNTIF($AJ$2:$AJ38,$AJ38) -> 17 | AN38: =$AJ38&"|"&$AM38 -> Ampol Retail|17 | AP38: =IF(TRIM($B38)="","",IF($AQ38=1,"Leadership",IFERROR(INDEX(Lists!$X:$X,MATCH(TRIM($K38),Lists!$W:$W,0)),IF(OR(TRIM($K38)="",LOWER(TRIM($K38))="na"),IF(TRIM($G38)="","Unassigned",TRIM($G38)),TRIM($K38))))) -> Store Operations | AQ38: =IF(TRIM($B38)="","",--OR(TRIM($K38)="Leadership",TRIM($J38)="Leadership")) -> FALSE | AR38: =IF(TRIM($B38)="","",IF(IFERROR(INDEX(Lists!$AQ$2:$AQ$11,MATCH(ROW(),Lists!$AN$2:$AN$11,0)),"")<>"",IFERROR(INDEX(Lists!$AQ$2:$AQ$11,MATCH(ROW(),Lists!$AN$2:$AN$11,0)),""),IF(ISNUMBER(SEARCH("head of ",$C38)),"Head of Technology",IF(ISNUMBER(SEARCH("TDD BP",$C38)),"Business Partner",IF(OR(ISNUMBER(SEARCH("domain architect",$C38)),ISNUMBER(SEARCH("enterprise architect",$C38))),"Domain Architect",IF(ISNUMBER(SEARCH("delivery man",$C38)),"Delivery Manager",IF(OR(ISNUMBER(SEARCH("technology manager",$C38)),ISNUMBER(SEARCH("technology manger",$C38)),ISNUMBER(SEARCH("tech manager",$C38))),"Technology Manager","Squad"))))))) -> Squad | AS38: =IF(TRIM($B38)="","",IFERROR(INDEX(Lists!$AA:$AA,MATCH($AP38,Lists!$Z:$Z,0)),$AP38)) -> Store Operations | AT38: =IF(TRIM($B38)="","",IF(IFERROR(INDEX(Lists!$AP$2:$AP$11,MATCH(ROW(),Lists!$AN$2:$AN$11,0)),"")<>"",IFERROR(INDEX(Lists!$AP$2:$AP$11,MATCH(ROW(),Lists!$AN$2:$AN$11,0)),""),IF(OR(LEFT($AJ38,3)="COE",$AJ38="EGI"),$AP38,IF($AR38<>"Squad",$AR38,$AP38)))) -> Store Operations
A39: 99999101804 | B39: Kate Johnstone | C39: Program Manager POS | D39: Vance Anderson | E39: GM TDD, Ampol Retail & Z | F39: Ampol Retail & Z | G39: Program Management | I39: Retail | J39: AMPOS | K39: AmPos | M39: NZ | N39: CSB | O39: 1 | Q39: Permanent - Full Time | T39: 175960 | U39: 161883.2 | V39: 0.15 | X39: 0.05 | Y39: 2910 | Z39: 0.03 | AA39: =IF(TRIM($B39)="","",IF(N($AU39)>0,$AU39,IF(N($S39)>0,$S39*Lists!$AG$15*(1+N($Z39)),N($U39)*(1+N($V39)+N($W39)+N($X39)+N($Z39))+N($Y39)))) -> 202026.34 | AJ39: =IF(TRIM($B39)="","",IF(IFERROR(INDEX(Lists!$AO$2:$AO$11,MATCH(ROW(),Lists!$AN$2:$AN$11,0)),"")<>"",IFERROR(INDEX(Lists!$AO$2:$AO$11,MATCH(ROW(),Lists!$AN$2:$AN$11,0)),""),IFERROR(INDEX(Lists!$U:$U,MATCH(TRIM($I39),Lists!$T:$T,0)),TRIM($I39)))) -> Ampol Retail | AK39: =IF(ISNUMBER(SEARCH("vacant",$B39)),"Vacant","Filled") -> Filled | AL39: =IF($M39="NZ","NZ","AU") -> NZ | AM39: =COUNTIF($AJ$2:$AJ39,$AJ39) -> 18 | AN39: =$AJ39&"|"&$AM39 -> Ampol Retail|18 | AP39: =IF(TRIM($B39)="","",IF($AQ39=1,"Leadership",IFERROR(INDEX(Lists!$X:$X,MATCH(TRIM($K39),Lists!$W:$W,0)),IF(OR(TRIM($K39)="",LOWER(TRIM($K39))="na"),IF(TRIM($G39)="","Unassigned",TRIM($G39)),TRIM($K39))))) -> AmPOS | AQ39: =IF(TRIM($B39)="","",--OR(TRIM($K39)="Leadership",TRIM($J39)="Leadership")) -> FALSE | AR39: =IF(TRIM($B39)="","",IF(IFERROR(INDEX(Lists!$AQ$2:$AQ$11,MATCH(ROW(),Lists!$AN$2:$AN$11,0)),"")<>"",IFERROR(INDEX(Lists!$AQ$2:$AQ$11,MATCH(ROW(),Lists!$AN$2:$AN$11,0)),""),IF(ISNUMBER(SEARCH("head of ",$C39)),"Head of Technology",IF(ISNUMBER(SEARCH("TDD BP",$C39)),"Business Partner",IF(OR(ISNUMBER(SEARCH("domain architect",$C39)),ISNUMBER(SEARCH("enterprise architect",$C39))),"Domain Architect",IF(ISNUMBER(SEARCH("delivery man",$C39)),"Delivery Manager",IF(OR(ISNUMBER(SEARCH("technology manager",$C39)),ISNUMBER(SEARCH("technology manger",$C39)),ISNUMBER(SEARCH("tech manager",$C39))),"Technology Manager","Squad"))))))) -> Squad | AS39: =IF(TRIM($B39)="","",IFERROR(INDEX(Lists!$AA:$AA,MATCH($AP39,Lists!$Z:$Z,0)),$AP39)) -> AmPOS | AT39: =IF(TRIM($B39)="","",IF(IFERROR(INDEX(Lists!$AP$2:$AP$11,MATCH(ROW(),Lists!$AN$2:$AN$11,0)),"")<>"",IFERROR(INDEX(Lists!$AP$2:$AP$11,MATCH(ROW(),Lists!$AN$2:$AN$11,0)),""),IF(OR(LEFT($AJ39,3)="COE",$AJ39="EGI"),$AP39,IF($AR39<>"Squad",$AR39,$AP39)))) -> AmPOS
A40: 99999100476 | B40: Kelly Russell | C40: Lead Quality Assurance | D40: Callan McLaughlin | E40: Technology Manager, Site Systems | F40: Ampol Retail & Z | G40: Z & Group Retail | H40: Z & Group Retail, Site Systems | I40: Z | J40: Z Customer | K40: Site Systems | M40: NZ | N40: CIC | O40: 1 | Q40: Permanent - Full Time | T40: 72000 | U40: 66240 | V40: 0.1 | X40: 0.05 | Y40: 2910 | Z40: 0.03 | AA40: =IF(TRIM($B40)="","",IF(N($AU40)>0,$AU40,IF(N($S40)>0,$S40*Lists!$AG$15*(1+N($Z40)),N($U40)*(1+N($V40)+N($W40)+N($X40)+N($Z40))+N($Y40)))) -> 81073.2 | AJ40: =IF(TRIM($B40)="","",IF(IFERROR(INDEX(Lists!$AO$2:$AO$11,MATCH(ROW(),Lists!$AN$2:$AN$11,0)),"")<>"",IFERROR(INDEX(Lists!$AO$2:$AO$11,MATCH(ROW(),Lists!$AN$2:$AN$11,0)),""),IFERROR(INDEX(Lists!$U:$U,MATCH(TRIM($I40),Lists!$T:$T,0)),TRIM($I40)))) -> Z Retail | AK40: =IF(ISNUMBER(SEARCH("vacant",$B40)),"Vacant","Filled") -> Filled | AL40: =IF($M40="NZ","NZ","AU") -> NZ | AM40: =COUNTIF($AJ$2:$AJ40,$AJ40) -> 21 | AN40: =$AJ40&"|"&$AM40 -> Z Retail|21 | AP40: =IF(TRIM($B40)="","",IF($AQ40=1,"Leadership",IFERROR(INDEX(Lists!$X:$X,MATCH(TRIM($K40),Lists!$W:$W,0)),IF(OR(TRIM($K40)="",LOWER(TRIM($K40))="na"),IF(TRIM($G40)="","Unassigned",TRIM($G40)),TRIM($K40))))) -> Site Systems | AQ40: =IF(TRIM($B40)="","",--OR(TRIM($K40)="Leadership",TRIM($J40)="Leadership")) -> FALSE | AR40: =IF(TRIM($B40)="","",IF(IFERROR(INDEX(Lists!$AQ$2:$AQ$11,MATCH(ROW(),Lists!$AN$2:$AN$11,0)),"")<>"",IFERROR(INDEX(Lists!$AQ$2:$AQ$11,MATCH(ROW(),Lists!$AN$2:$AN$11,0)),""),IF(ISNUMBER(SEARCH("head of ",$C40)),"Head of Technology",IF(ISNUMBER(SEARCH("TDD BP",$C40)),"Business Partner",IF(OR(ISNUMBER(SEARCH("domain architect",$C40)),ISNUMBER(SEARCH("enterprise architect",$C40))),"Domain Architect",IF(ISNUMBER(SEARCH("delivery man",$C40)),"Delivery Manager",IF(OR(ISNUMBER(SEARCH("technology manager",$C40)),ISNUMBER(SEARCH("technology manger",$C40)),ISNUMBER(SEARCH("tech manager",$C40))),"Technology Manager","Squad"))))))) -> Squad | AS40: =IF(TRIM($B40)="","",IFERROR(INDEX(Lists!$AA:$AA,MATCH($AP40,Lists!$Z:$Z,0)),$AP40)) -> Site Systems | AT40: =IF(TRIM($B40)="","",IF(IFERROR(INDEX(Lists!$AP$2:$AP$11,MATCH(ROW(),Lists!$AN$2:$AN$11,0)),"")<>"",IFERROR(INDEX(Lists!$AP$2:$AP$11,MATCH(ROW(),Lists!$AN$2:$AN$11,0)),""),IF(OR(LEFT($AJ40,3)="COE",$AJ40="EGI"),$AP40,IF($AR40<>"Squad",$AR40,$AP40)))) -> Site Systems
A41: 99999102028 | B41: Lauren Lancaster | C41: Associate Engineer - Software | D41: Vacant | E41: Technology Manager, Engineering | F41: Ampol Retail & Z | G41: Z & Group Retail | H41: Z & Group Retail, Engineering | I41: Z | J41: Z Customer | K41: Z Retail Backend | M41: NZ | N41: CDA | O41: 1 | Q41: Permanent - Full Time | T41: 310000 | U41: 310000 | V41: 0.2 | W41: 0.055 | X41: 0.12 | Z41: 0.04 | AA41: =IF(TRIM($B41)="","",IF(N($AU41)>0,$AU41,IF(N($S41)>0,$S41*Lists!$AG$15*(1+N($Z41)),N($U41)*(1+N($V41)+N($W41)+N($X41)+N($Z41))+N($Y41)))) -> 438650 | AJ41: =IF(TRIM($B41)="","",IF(IFERROR(INDEX(Lists!$AO$2:$AO$11,MATCH(ROW(),Lists!$AN$2:$AN$11,0)),"")<>"",IFERROR(INDEX(Lists!$AO$2:$AO$11,MATCH(ROW(),Lists!$AN$2:$AN$11,0)),""),IFERROR(INDEX(Lists!$U:$U,MATCH(TRIM($I41),Lists!$T:$T,0)),TRIM($I41)))) -> Z Retail | AK41: =IF(ISNUMBER(SEARCH("vacant",$B41)),"Vacant","Filled") -> Filled | AL41: =IF($M41="NZ","NZ","AU") -> NZ | AM41: =COUNTIF($AJ$2:$AJ41,$AJ41) -> 22 | AN41: =$AJ41&"|"&$AM41 -> Z Retail|22 | AP41: =IF(TRIM($B41)="","",IF($AQ41=1,"Leadership",IFERROR(INDEX(Lists!$X:$X,MATCH(TRIM($K41),Lists!$W:$W,0)),IF(OR(TRIM($K41)="",LOWER(TRIM($K41))="na"),IF(TRIM($G41)="","Unassigned",TRIM($G41)),TRIM($K41))))) -> Z Retail Backend | AQ41: =IF(TRIM($B41)="","",--OR(TRIM($K41)="Leadership",TRIM($J41)="Leadership")) -> FALSE | AR41: =IF(TRIM($B41)="","",IF(IFERROR(INDEX(Lists!$AQ$2:$AQ$11,MATCH(ROW(),Lists!$AN$2:$AN$11,0)),"")<>"",IFERROR(INDEX(Lists!$AQ$2:$AQ$11,MATCH(ROW(),Lists!$AN$2:$AN$11,0)),""),IF(ISNUMBER(SEARCH("head of ",$C41)),"Head of Technology",IF(ISNUMBER(SEARCH("TDD BP",$C41)),"Business Partner",IF(OR(ISNUMBER(SEARCH("domain architect",$C41)),ISNUMBER(SEARCH("enterprise architect",$C41))),"Domain Architect",IF(ISNUMBER(SEARCH("delivery man",$C41)),"Delivery Manager",IF(OR(ISNUMBER(SEARCH("technology manager",$C41)),ISNUMBER(SEARCH("technology manger",$C41)),ISNUMBER(SEARCH("tech manager",$C41))),"Technology Manager","Squad"))))))) -> Squad | AS41: =IF(TRIM($B41)="","",IFERROR(INDEX(Lists!$AA:$AA,MATCH($AP41,Lists!$Z:$Z,0)),$AP41)) -> Z Retail Backend | AT41: =IF(TRIM($B41)="","",IF(IFERROR(INDEX(Lists!$AP$2:$AP$11,MATCH(ROW(),Lists!$AN$2:$AN$11,0)),"")<>"",IFERROR(INDEX(Lists!$AP$2:$AP$11,MATCH(ROW(),Lists!$AN$2:$AN$11,0)),""),IF(OR(LEFT($AJ41,3)="COE",$AJ41="EGI"),$AP41,IF($AR41<>"Squad",$AR41,$AP41)))) -> Z Retail Backend
A42: 110852 | B42: Madan Murthy | C42: Head of Technology, AU Retail | D42: Vance Anderson | E42: GM TDD, Ampol Retail & Z | F42: Ampol Retail & Z | G42: Ampol Retail | H42: na | I42: Retail | J42: (All Retail) | K42: Leadership | M42: Australia | N42: CSC | O42: 1 | Q42: Permanent - Full Time | T42: 139350 | U42: 139350 | V42: 0.12 | W42: 0.055 | X42: 0.12 | Z42: 0.04 | AA42: =IF(TRIM($B42)="","",IF(N($AU42)>0,$AU42,IF(N($S42)>0,$S42*Lists!$AG$15*(1+N($Z42)),N($U42)*(1+N($V42)+N($W42)+N($X42)+N($Z42))+N($Y42)))) -> 186032.25 | AJ42: =IF(TRIM($B42)="","",IF(IFERROR(INDEX(Lists!$AO$2:$AO$11,MATCH(ROW(),Lists!$AN$2:$AN$11,0)),"")<>"",IFERROR(INDEX(Lists!$AO$2:$AO$11,MATCH(ROW(),Lists!$AN$2:$AN$11,0)),""),IFERROR(INDEX(Lists!$U:$U,MATCH(TRIM($I42),Lists!$T:$T,0)),TRIM($I42)))) -> Ampol Retail | AK42: =IF(ISNUMBER(SEARCH("vacant",$B42)),"Vacant","Filled") -> Filled | AL42: =IF($M42="NZ","NZ","AU") -> AU | AM42: =COUNTIF($AJ$2:$AJ42,$AJ42) -> 19 | AN42: =$AJ42&"|"&$AM42 -> Ampol Retail|19 | AP42: =IF(TRIM($B42)="","",IF($AQ42=1,"Leadership",IFERROR(INDEX(Lists!$X:$X,MATCH(TRIM($K42),Lists!$W:$W,0)),IF(OR(TRIM($K42)="",LOWER(TRIM($K42))="na"),IF(TRIM($G42)="","Unassigned",TRIM($G42)),TRIM($K42))))) -> Leadership | AQ42: =IF(TRIM($B42)="","",--OR(TRIM($K42)="Leadership",TRIM($J42)="Leadership")) -> TRUE | AR42: =IF(TRIM($B42)="","",IF(IFERROR(INDEX(Lists!$AQ$2:$AQ$11,MATCH(ROW(),Lists!$AN$2:$AN$11,0)),"")<>"",IFERROR(INDEX(Lists!$AQ$2:$AQ$11,MATCH(ROW(),Lists!$AN$2:$AN$11,0)),""),IF(ISNUMBER(SEARCH("head of ",$C42)),"Head of Technology",IF(ISNUMBER(SEARCH("TDD BP",$C42)),"Business Partner",IF(OR(ISNUMBER(SEARCH("domain architect",$C42)),ISNUMBER(SEARCH("enterprise architect",$C42))),"Domain Architect",IF(ISNUMBER(SEARCH("delivery man",$C42)),"Delivery Manager",IF(OR(ISNUMBER(SEARCH("technology manager",$C42)),ISNUMBER(SEARCH("technology manger",$C42)),ISNUMBER(SEARCH("tech manager",$C42))),"Technology Manager","Squad"))))))) -> Head of Technology | AS42: =IF(TRIM($B42)="","",IFERROR(INDEX(Lists!$AA:$AA,MATCH($AP42,Lists!$Z:$Z,0)),$AP42)) -> Leadership | AT42: =IF(TRIM($B42)="","",IF(IFERROR(INDEX(Lists!$AP$2:$AP$11,MATCH(ROW(),Lists!$AN$2:$AN$11,0)),"")<>"",IFERROR(INDEX(Lists!$AP$2:$AP$11,MATCH(ROW(),Lists!$AN$2:$AN$11,0)),""),IF(OR(LEFT($AJ42,3)="COE",$AJ42="EGI"),$AP42,IF($AR42<>"Squad",$AR42,$AP42)))) -> Head of Technology
A43: 86743 | B43: Majdi Abedi | C43: Systems Analyst | D43: Tracy Lee Reaper | E43: Tech Manager, Merchandising & WFM | F43: Ampol Retail & Z | G43: Ampol Retail | H43: Ampol Retail, Merch & RTA | I43: Retail | J43: Above Store | K43: Above Store | M43: Australia | N43: CIB | O43: 1 | Q43: Permanent - Full Time | T43: 116170 | U43: 106876.4 | V43: 0.15 | X43: 0.05 | Y43: 2910 | Z43: 0.03 | AA43: =IF(TRIM($B43)="","",IF(N($AU43)>0,$AU43,IF(N($S43)>0,$S43*Lists!$AG$15*(1+N($Z43)),N($U43)*(1+N($V43)+N($W43)+N($X43)+N($Z43))+N($Y43)))) -> 134367.97 | AJ43: =IF(TRIM($B43)="","",IF(IFERROR(INDEX(Lists!$AO$2:$AO$11,MATCH(ROW(),Lists!$AN$2:$AN$11,0)),"")<>"",IFERROR(INDEX(Lists!$AO$2:$AO$11,MATCH(ROW(),Lists!$AN$2:$AN$11,0)),""),IFERROR(INDEX(Lists!$U:$U,MATCH(TRIM($I43),Lists!$T:$T,0)),TRIM($I43)))) -> Ampol Retail | AK43: =IF(ISNUMBER(SEARCH("vacant",$B43)),"Vacant","Filled") -> Filled | AL43: =IF($M43="NZ","NZ","AU") -> AU | AM43: =COUNTIF($AJ$2:$AJ43,$AJ43) -> 20 | AN43: =$AJ43&"|"&$AM43 -> Ampol Retail|20 | AP43: =IF(TRIM($B43)="","",IF($AQ43=1,"Leadership",IFERROR(INDEX(Lists!$X:$X,MATCH(TRIM($K43),Lists!$W:$W,0)),IF(OR(TRIM($K43)="",LOWER(TRIM($K43))="na"),IF(TRIM($G43)="","Unassigned",TRIM($G43)),TRIM($K43))))) -> Above Store | AQ43: =IF(TRIM($B43)="","",--OR(TRIM($K43)="Leadership",TRIM($J43)="Leadership")) -> FALSE | AR43: =IF(TRIM($B43)="","",IF(IFERROR(INDEX(Lists!$AQ$2:$AQ$11,MATCH(ROW(),Lists!$AN$2:$AN$11,0)),"")<>"",IFERROR(INDEX(Lists!$AQ$2:$AQ$11,MATCH(ROW(),Lists!$AN$2:$AN$11,0)),""),IF(ISNUMBER(SEARCH("head of ",$C43)),"Head of Technology",IF(ISNUMBER(SEARCH("TDD BP",$C43)),"Business Partner",IF(OR(ISNUMBER(SEARCH("domain architect",$C43)),ISNUMBER(SEARCH("enterprise architect",$C43))),"Domain Architect",IF(ISNUMBER(SEARCH("delivery man",$C43)),"Delivery Manager",IF(OR(ISNUMBER(SEARCH("technology manager",$C43)),ISNUMBER(SEARCH("technology manger",$C43)),ISNUMBER(SEARCH("tech manager",$C43))),"Technology Manager","Squad"))))))) -> Squad | AS43: =IF(TRIM($B43)="","",IFERROR(INDEX(Lists!$AA:$AA,MATCH($AP43,Lists!$Z:$Z,0)),$AP43)) -> Above Store | AT43: =IF(TRIM($B43)="","",IF(IFERROR(INDEX(Lists!$AP$2:$AP$11,MATCH(ROW(),Lists!$AN$2:$AN$11,0)),"")<>"",IFERROR(INDEX(Lists!$AP$2:$AP$11,MATCH(ROW(),Lists!$AN$2:$AN$11,0)),""),IF(OR(LEFT($AJ43,3)="COE",$AJ43="EGI"),$AP43,IF($AR43<>"Squad",$AR43,$AP43)))) -> Above Store
A44: 99999101222 | B44: Malachi Ah Hoi | C44: Senior Quality Assurance | D44: Vacant | E44: Technology Manager, Engineering | F44: Ampol Retail & Z | G44: Z & Group Retail | H44: Z & Group Retail, Engineering | I44: Z | J44: Z Customer | K44: Z Retail Backend | M44: NZ | N44: CIA | O44: 1 | Q44: Permanent - Full Time | T44: 173620 | U44: 159730.4 | V44: 0.15 | X44: 0.05 | Y44: 2910 | Z44: 0.03 | AA44: =IF(TRIM($B44)="","",IF(N($AU44)>0,$AU44,IF(N($S44)>0,$S44*Lists!$AG$15*(1+N($Z44)),N($U44)*(1+N($V44)+N($W44)+N($X44)+N($Z44))+N($Y44)))) -> 199378.39 | AJ44: =IF(TRIM($B44)="","",IF(IFERROR(INDEX(Lists!$AO$2:$AO$11,MATCH(ROW(),Lists!$AN$2:$AN$11,0)),"")<>"",IFERROR(INDEX(Lists!$AO$2:$AO$11,MATCH(ROW(),Lists!$AN$2:$AN$11,0)),""),IFERROR(INDEX(Lists!$U:$U,MATCH(TRIM($I44),Lists!$T:$T,0)),TRIM($I44)))) -> Z Retail | AK44: =IF(ISNUMBER(SEARCH("vacant",$B44)),"Vacant","Filled") -> Filled | AL44: =IF($M44="NZ","NZ","AU") -> NZ | AM44: =COUNTIF($AJ$2:$AJ44,$AJ44) -> 23 | AN44: =$AJ44&"|"&$AM44 -> Z Retail|23 | AP44: =IF(TRIM($B44)="","",IF($AQ44=1,"Leadership",IFERROR(INDEX(Lists!$X:$X,MATCH(TRIM($K44),Lists!$W:$W,0)),IF(OR(TRIM($K44)="",LOWER(TRIM($K44))="na"),IF(TRIM($G44)="","Unassigned",TRIM($G44)),TRIM($K44))))) -> Z Retail Backend | AQ44: =IF(TRIM($B44)="","",--OR(TRIM($K44)="Leadership",TRIM($J44)="Leadership")) -> FALSE | AR44: =IF(TRIM($B44)="","",IF(IFERROR(INDEX(Lists!$AQ$2:$AQ$11,MATCH(ROW(),Lists!$AN$2:$AN$11,0)),"")<>"",IFERROR(INDEX(Lists!$AQ$2:$AQ$11,MATCH(ROW(),Lists!$AN$2:$AN$11,0)),""),IF(ISNUMBER(SEARCH("head of ",$C44)),"Head of Technology",IF(ISNUMBER(SEARCH("TDD BP",$C44)),"Business Partner",IF(OR(ISNUMBER(SEARCH("domain architect",$C44)),ISNUMBER(SEARCH("enterprise architect",$C44))),"Domain Architect",IF(ISNUMBER(SEARCH("delivery man",$C44)),"Delivery Manager",IF(OR(ISNUMBER(SEARCH("technology manager",$C44)),ISNUMBER(SEARCH("technology manger",$C44)),ISNUMBER(SEARCH("tech manager",$C44))),"Technology Manager","Squad"))))))) -> Squad | AS44: =IF(TRIM($B44)="","",IFERROR(INDEX(Lists!$AA:$AA,MATCH($AP44,Lists!$Z:$Z,0)),$AP44)) -> Z Retail Backend | AT44: =IF(TRIM($B44)="","",IF(IFERROR(INDEX(Lists!$AP$2:$AP$11,MATCH(ROW(),Lists!$AN$2:$AN$11,0)),"")<>"",IFERROR(INDEX(Lists!$AP$2:$AP$11,MATCH(ROW(),Lists!$AN$2:$AN$11,0)),""),IF(OR(LEFT($AJ44,3)="COE",$AJ44="EGI"),$AP44,IF($AR44<>"Squad",$AR44,$AP44)))) -> Z Retail Backend
A45: V | B45: Manjot Kaur Malli | C45: Technology Manager, Data | D45: Vacant | E45: Head of Technology, Z and Group Retail Platforms | F45: Ampol Retail & Z | G45: Z & Group Retail | H45: Z & Group Retail, Data | I45: Z | J45: Z Customer & Z Supply | K45: Leadership | M45: Australia | N45: CSB | O45: 1 | Q45: v | T45: 203550 | U45: 203550 | V45: 0.14 | W45: 0.055 | X45: 0.12 | Z45: 0.04 | AA45: =IF(TRIM($B45)="","",IF(N($AU45)>0,$AU45,IF(N($S45)>0,$S45*Lists!$AG$15*(1+N($Z45)),N($U45)*(1+N($V45)+N($W45)+N($X45)+N($Z45))+N($Y45)))) -> 275810.25 | AJ45: =IF(TRIM($B45)="","",IF(IFERROR(INDEX(Lists!$AO$2:$AO$11,MATCH(ROW(),Lists!$AN$2:$AN$11,0)),"")<>"",IFERROR(INDEX(Lists!$AO$2:$AO$11,MATCH(ROW(),Lists!$AN$2:$AN$11,0)),""),IFERROR(INDEX(Lists!$U:$U,MATCH(TRIM($I45),Lists!$T:$T,0)),TRIM($I45)))) -> Z Retail | AK45: =IF(ISNUMBER(SEARCH("vacant",$B45)),"Vacant","Filled") -> Filled | AL45: =IF($M45="NZ","NZ","AU") -> AU | AM45: =COUNTIF($AJ$2:$AJ45,$AJ45) -> 24 | AN45: =$AJ45&"|"&$AM45 -> Z Retail|24 | AP45: =IF(TRIM($B45)="","",IF($AQ45=1,"Leadership",IFERROR(INDEX(Lists!$X:$X,MATCH(TRIM($K45),Lists!$W:$W,0)),IF(OR(TRIM($K45)="",LOWER(TRIM($K45))="na"),IF(TRIM($G45)="","Unassigned",TRIM($G45)),TRIM($K45))))) -> Leadership | AQ45: =IF(TRIM($B45)="","",--OR(TRIM($K45)="Leadership",TRIM($J45)="Leadership")) -> TRUE | AR45: =IF(TRIM($B45)="","",IF(IFERROR(INDEX(Lists!$AQ$2:$AQ$11,MATCH(ROW(),Lists!$AN$2:$AN$11,0)),"")<>"",IFERROR(INDEX(Lists!$AQ$2:$AQ$11,MATCH(ROW(),Lists!$AN$2:$AN$11,0)),""),IF(ISNUMBER(SEARCH("head of ",$C45)),"Head of Technology",IF(ISNUMBER(SEARCH("TDD BP",$C45)),"Business Partner",IF(OR(ISNUMBER(SEARCH("domain architect",$C45)),ISNUMBER(SEARCH("enterprise architect",$C45))),"Domain Architect",IF(ISNUMBER(SEARCH("delivery man",$C45)),"Delivery Manager",IF(OR(ISNUMBER(SEARCH("technology manager",$C45)),ISNUMBER(SEARCH("technology manger",$C45)),ISNUMBER(SEARCH("tech manager",$C45))),"Technology Manager","Squad"))))))) -> Technology Manager | AS45: =IF(TRIM($B45)="","",IFERROR(INDEX(Lists!$AA:$AA,MATCH($AP45,Lists!$Z:$Z,0)),$AP45)) -> Leadership | AT45: =IF(TRIM($B45)="","",IF(IFERROR(INDEX(Lists!$AP$2:$AP$11,MATCH(ROW(),Lists!$AN$2:$AN$11,0)),"")<>"",IFERROR(INDEX(Lists!$AP$2:$AP$11,MATCH(ROW(),Lists!$AN$2:$AN$11,0)),""),IF(OR(LEFT($AJ45,3)="COE",$AJ45="EGI"),$AP45,IF($AR45<>"Squad",$AR45,$AP45)))) -> Technology Manager
A46: 99999170431 | B46: Mark Dickson | C46: Delivery Lead | D46: Vacant | E46: Delivery Manager, Z and Retail Data | F46: Ampol Retail & Z | G46: Z & Group Retail | H46: Z & Group Retail, Delivery | I46: Z | J46: Z Customer | K46: Z Retail Backend | M46: NZ | N46: CIC | O46: 1 | Q46: Permanent - Full Time | T46: 135000 | U46: 135000 | V46: 0.12 | W46: 0.055 | X46: 0.12 | Z46: 0.04 | AA46: =IF(TRIM($B46)="","",IF(N($AU46)>0,$AU46,IF(N($S46)>0,$S46*Lists!$AG$15*(1+N($Z46)),N($U46)*(1+N($V46)+N($W46)+N($X46)+N($Z46))+N($Y46)))) -> 180225 | AJ46: =IF(TRIM($B46)="","",IF(IFERROR(INDEX(Lists!$AO$2:$AO$11,MATCH(ROW(),Lists!$AN$2:$AN$11,0)),"")<>"",IFERROR(INDEX(Lists!$AO$2:$AO$11,MATCH(ROW(),Lists!$AN$2:$AN$11,0)),""),IFERROR(INDEX(Lists!$U:$U,MATCH(TRIM($I46),Lists!$T:$T,0)),TRIM($I46)))) -> Z Retail | AK46: =IF(ISNUMBER(SEARCH("vacant",$B46)),"Vacant","Filled") -> Filled | AL46: =IF($M46="NZ","NZ","AU") -> NZ | AM46: =COUNTIF($AJ$2:$AJ46,$AJ46) -> 25 | AN46: =$AJ46&"|"&$AM46 -> Z Retail|25 | AP46: =IF(TRIM($B46)="","",IF($AQ46=1,"Leadership",IFERROR(INDEX(Lists!$X:$X,MATCH(TRIM($K46),Lists!$W:$W,0)),IF(OR(TRIM($K46)="",LOWER(TRIM($K46))="na"),IF(TRIM($G46)="","Unassigned",TRIM($G46)),TRIM($K46))))) -> Z Retail Backend | AQ46: =IF(TRIM($B46)="","",--OR(TRIM($K46)="Leadership",TRIM($J46)="Leadership")) -> FALSE | AR46: =IF(TRIM($B46)="","",IF(IFERROR(INDEX(Lists!$AQ$2:$AQ$11,MATCH(ROW(),Lists!$AN$2:$AN$11,0)),"")<>"",IFERROR(INDEX(Lists!$AQ$2:$AQ$11,MATCH(ROW(),Lists!$AN$2:$AN$11,0)),""),IF(ISNUMBER(SEARCH("head of ",$C46)),"Head of Technology",IF(ISNUMBER(SEARCH("TDD BP",$C46)),"Business Partner",IF(OR(ISNUMBER(SEARCH("domain architect",$C46)),ISNUMBER(SEARCH("enterprise architect",$C46))),"Domain Architect",IF(ISNUMBER(SEARCH("delivery man",$C46)),"Delivery Manager",IF(OR(ISNUMBER(SEARCH("technology manager",$C46)),ISNUMBER(SEARCH("technology manger",$C46)),ISNUMBER(SEARCH("tech manager",$C46))),"Technology Manager","Squad"))))))) -> Squad | AS46: =IF(TRIM($B46)="","",IFERROR(INDEX(Lists!$AA:$AA,MATCH($AP46,Lists!$Z:$Z,0)),$AP46)) -> Z Retail Backend | AT46: =IF(TRIM($B46)="","",IF(IFERROR(INDEX(Lists!$AP$2:$AP$11,MATCH(ROW(),Lists!$AN$2:$AN$11,0)),"")<>"",IFERROR(INDEX(Lists!$AP$2:$AP$11,MATCH(ROW(),Lists!$AN$2:$AN$11,0)),""),IF(OR(LEFT($AJ46,3)="COE",$AJ46="EGI"),$AP46,IF($AR46<>"Squad",$AR46,$AP46)))) -> Z Retail Backend
A47: 114616 | B47: Marty O'Shea | C47: Systems Analyst | D47: Vedran Jukic | E47: Technology Manager, Retail | F47: Ampol Retail & Z | G47: Ampol Retail | H47: Ampol Retail, Technology | I47: Ampol Retail | J47: EGI | K47: EGI Retail | M47: Australia | N47: CIB | O47: 1 | Q47: Permanent - Full Time | T47: 185140 | U47: 185140 | V47: 0.12 | W47: 0.055 | X47: 0.12 | Z47: 0.04 | AA47: =IF(TRIM($B47)="","",IF(N($AU47)>0,$AU47,IF(N($S47)>0,$S47*Lists!$AG$15*(1+N($Z47)),N($U47)*(1+N($V47)+N($W47)+N($X47)+N($Z47))+N($Y47)))) -> 247161.9 | AJ47: =IF(TRIM($B47)="","",IF(IFERROR(INDEX(Lists!$AO$2:$AO$11,MATCH(ROW(),Lists!$AN$2:$AN$11,0)),"")<>"",IFERROR(INDEX(Lists!$AO$2:$AO$11,MATCH(ROW(),Lists!$AN$2:$AN$11,0)),""),IFERROR(INDEX(Lists!$U:$U,MATCH(TRIM($I47),Lists!$T:$T,0)),TRIM($I47)))) -> Ampol Retail | AK47: =IF(ISNUMBER(SEARCH("vacant",$B47)),"Vacant","Filled") -> Filled | AL47: =IF($M47="NZ","NZ","AU") -> AU | AM47: =COUNTIF($AJ$2:$AJ47,$AJ47) -> 21 | AN47: =$AJ47&"|"&$AM47 -> Ampol Retail|21 | AP47: =IF(TRIM($B47)="","",IF($AQ47=1,"Leadership",IFERROR(INDEX(Lists!$X:$X,MATCH(TRIM($K47),Lists!$W:$W,0)),IF(OR(TRIM($K47)="",LOWER(TRIM($K47))="na"),IF(TRIM($G47)="","Unassigned",TRIM($G47)),TRIM($K47))))) -> EGI Retail | AQ47: =IF(TRIM($B47)="","",--OR(TRIM($K47)="Leadership",TRIM($J47)="Leadership")) -> FALSE | AR47: =IF(TRIM($B47)="","",IF(IFERROR(INDEX(Lists!$AQ$2:$AQ$11,MATCH(ROW(),Lists!$AN$2:$AN$11,0)),"")<>"",IFERROR(INDEX(Lists!$AQ$2:$AQ$11,MATCH(ROW(),Lists!$AN$2:$AN$11,0)),""),IF(ISNUMBER(SEARCH("head of ",$C47)),"Head of Technology",IF(ISNUMBER(SEARCH("TDD BP",$C47)),"Business Partner",IF(OR(ISNUMBER(SEARCH("domain architect",$C47)),ISNUMBER(SEARCH("enterprise architect",$C47))),"Domain Architect",IF(ISNUMBER(SEARCH("delivery man",$C47)),"Delivery Manager",IF(OR(ISNUMBER(SEARCH("technology manager",$C47)),ISNUMBER(SEARCH("technology manger",$C47)),ISNUMBER(SEARCH("tech manager",$C47))),"Technology Manager","Squad"))))))) -> Squad | AS47: =IF(TRIM($B47)="","",IFERROR(INDEX(Lists!$AA:$AA,MATCH($AP47,Lists!$Z:$Z,0)),$AP47)) -> EGI Retail | AT47: =IF(TRIM($B47)="","",IF(IFERROR(INDEX(Lists!$AP$2:$AP$11,MATCH(ROW(),Lists!$AN$2:$AN$11,0)),"")<>"",IFERROR(INDEX(Lists!$AP$2:$AP$11,MATCH(ROW(),Lists!$AN$2:$AN$11,0)),""),IF(OR(LEFT($AJ47,3)="COE",$AJ47="EGI"),$AP47,IF($AR47<>"Squad",$AR47,$AP47)))) -> EGI Retail
A48: 111835 | B48: Matthew Patane | C48: Release & Deployment Manager | D48: Vedran Jukic | E48: Technology Manager, Retail | F48: Ampol Retail & Z | G48: Ampol Retail | H48: Ampol Retail, Technology | I48: Retail | J48: Store Operations | K48: Deployment | M48: Australia | N48: CIC | O48: 1 | Q48: Permanent - Full Time | T48: 118020 | U48: 108578.4 | V48: 0.15 | X48: 0.05 | Y48: 2910 | Z48: 0.03 | AA48: =IF(TRIM($B48)="","",IF(N($AU48)>0,$AU48,IF(N($S48)>0,$S48*Lists!$AG$15*(1+N($Z48)),N($U48)*(1+N($V48)+N($W48)+N($X48)+N($Z48))+N($Y48)))) -> 136461.43 | AJ48: =IF(TRIM($B48)="","",IF(IFERROR(INDEX(Lists!$AO$2:$AO$11,MATCH(ROW(),Lists!$AN$2:$AN$11,0)),"")<>"",IFERROR(INDEX(Lists!$AO$2:$AO$11,MATCH(ROW(),Lists!$AN$2:$AN$11,0)),""),IFERROR(INDEX(Lists!$U:$U,MATCH(TRIM($I48),Lists!$T:$T,0)),TRIM($I48)))) -> Ampol Retail | AK48: =IF(ISNUMBER(SEARCH("vacant",$B48)),"Vacant","Filled") -> Filled | AL48: =IF($M48="NZ","NZ","AU") -> AU | AM48: =COUNTIF($AJ$2:$AJ48,$AJ48) -> 22 | AN48: =$AJ48&"|"&$AM48 -> Ampol Retail|22 | AP48: =IF(TRIM($B48)="","",IF($AQ48=1,"Leadership",IFERROR(INDEX(Lists!$X:$X,MATCH(TRIM($K48),Lists!$W:$W,0)),IF(OR(TRIM($K48)="",LOWER(TRIM($K48))="na"),IF(TRIM($G48)="","Unassigned",TRIM($G48)),TRIM($K48))))) -> Deployment | AQ48: =IF(TRIM($B48)="","",--OR(TRIM($K48)="Leadership",TRIM($J48)="Leadership")) -> FALSE | AR48: =IF(TRIM($B48)="","",IF(IFERROR(INDEX(Lists!$AQ$2:$AQ$11,MATCH(ROW(),Lists!$AN$2:$AN$11,0)),"")<>"",IFERROR(INDEX(Lists!$AQ$2:$AQ$11,MATCH(ROW(),Lists!$AN$2:$AN$11,0)),""),IF(ISNUMBER(SEARCH("head of ",$C48)),"Head of Technology",IF(ISNUMBER(SEARCH("TDD BP",$C48)),"Business Partner",IF(OR(ISNUMBER(SEARCH("domain architect",$C48)),ISNUMBER(SEARCH("enterprise architect",$C48))),"Domain Architect",IF(ISNUMBER(SEARCH("delivery man",$C48)),"Delivery Manager",IF(OR(ISNUMBER(SEARCH("technology manager",$C48)),ISNUMBER(SEARCH("technology manger",$C48)),ISNUMBER(SEARCH("tech manager",$C48))),"Technology Manager","Squad"))))))) -> Squad | AS48: =IF(TRIM($B48)="","",IFERROR(INDEX(Lists!$AA:$AA,MATCH($AP48,Lists!$Z:$Z,0)),$AP48)) -> Deployment | AT48: =IF(TRIM($B48)="","",IF(IFERROR(INDEX(Lists!$AP$2:$AP$11,MATCH(ROW(),Lists!$AN$2:$AN$11,0)),"")<>"",IFERROR(INDEX(Lists!$AP$2:$AP$11,MATCH(ROW(),Lists!$AN$2:$AN$11,0)),""),IF(OR(LEFT($AJ48,3)="COE",$AJ48="EGI"),$AP48,IF($AR48<>"Squad",$AR48,$AP48)))) -> Deployment
A49: 99999101668 | B49: McKenzie Tournquist | C49: Data Analyst | D49: Vacant | E49: Technology Manager, Data | F49: Ampol Retail & Z | G49: Z & Group Retail | H49: Z & Group Retail, Data | I49: Z | J49: Z Customer & Z Supply | K49: Data - NZ | M49: NZ | N49: CIA | O49: 1 | Q49: Permanent - Full Time | T49: 81890 | U49: 75338.8 | V49: 0.1 | X49: 0.05 | Y49: 2910 | Z49: 0.03 | AA49: =IF(TRIM($B49)="","",IF(N($AU49)>0,$AU49,IF(N($S49)>0,$S49*Lists!$AG$15*(1+N($Z49)),N($U49)*(1+N($V49)+N($W49)+N($X49)+N($Z49))+N($Y49)))) -> 91809.784 | AJ49: =IF(TRIM($B49)="","",IF(IFERROR(INDEX(Lists!$AO$2:$AO$11,MATCH(ROW(),Lists!$AN$2:$AN$11,0)),"")<>"",IFERROR(INDEX(Lists!$AO$2:$AO$11,MATCH(ROW(),Lists!$AN$2:$AN$11,0)),""),IFERROR(INDEX(Lists!$U:$U,MATCH(TRIM($I49),Lists!$T:$T,0)),TRIM($I49)))) -> Z Retail | AK49: =IF(ISNUMBER(SEARCH("vacant",$B49)),"Vacant","Filled") -> Filled | AL49: =IF($M49="NZ","NZ","AU") -> NZ | AM49: =COUNTIF($AJ$2:$AJ49,$AJ49) -> 26 | AN49: =$AJ49&"|"&$AM49 -> Z Retail|26 | AP49: =IF(TRIM($B49)="","",IF($AQ49=1,"Leadership",IFERROR(INDEX(Lists!$X:$X,MATCH(TRIM($K49),Lists!$W:$W,0)),IF(OR(TRIM($K49)="",LOWER(TRIM($K49))="na"),IF(TRIM($G49)="","Unassigned",TRIM($G49)),TRIM($K49))))) -> Data NZ | AQ49: =IF(TRIM($B49)="","",--OR(TRIM($K49)="Leadership",TRIM($J49)="Leadership")) -> FALSE | AR49: =IF(TRIM($B49)="","",IF(IFERROR(INDEX(Lists!$AQ$2:$AQ$11,MATCH(ROW(),Lists!$AN$2:$AN$11,0)),"")<>"",IFERROR(INDEX(Lists!$AQ$2:$AQ$11,MATCH(ROW(),Lists!$AN$2:$AN$11,0)),""),IF(ISNUMBER(SEARCH("head of ",$C49)),"Head of Technology",IF(ISNUMBER(SEARCH("TDD BP",$C49)),"Business Partner",IF(OR(ISNUMBER(SEARCH("domain architect",$C49)),ISNUMBER(SEARCH("enterprise architect",$C49))),"Domain Architect",IF(ISNUMBER(SEARCH("delivery man",$C49)),"Delivery Manager",IF(OR(ISNUMBER(SEARCH("technology manager",$C49)),ISNUMBER(SEARCH("technology manger",$C49)),ISNUMBER(SEARCH("tech manager",$C49))),"Technology Manager","Squad"))))))) -> Squad | AS49: =IF(TRIM($B49)="","",IFERROR(INDEX(Lists!$AA:$AA,MATCH($AP49,Lists!$Z:$Z,0)),$AP49)) -> Data NZ | AT49: =IF(TRIM($B49)="","",IF(IFERROR(INDEX(Lists!$AP$2:$AP$11,MATCH(ROW(),Lists!$AN$2:$AN$11,0)),"")<>"",IFERROR(INDEX(Lists!$AP$2:$AP$11,MATCH(ROW(),Lists!$AN$2:$AN$11,0)),""),IF(OR(LEFT($AJ49,3)="COE",$AJ49="EGI"),$AP49,IF($AR49<>"Squad",$AR49,$AP49)))) -> Data NZ
A50: 99999101623 | B50: Michael Dasan | C50: Engineer - Data | D50: Vacant | E50: Technology Manager, Data | F50: Ampol Retail & Z | G50: Z & Group Retail | H50: Z & Group Retail, Data | I50: Z | J50: Z Customer & Z Supply | K50: Data - NZ | M50: NZ | N50: CDB | O50: 1 | Q50: Permanent - Full Time | T50: 159010 | U50: 159010 | V50: 0.12 | W50: 0.055 | X50: 0.12 | Z50: 0.04 | AA50: =IF(TRIM($B50)="","",IF(N($AU50)>0,$AU50,IF(N($S50)>0,$S50*Lists!$AG$15*(1+N($Z50)),N($U50)*(1+N($V50)+N($W50)+N($X50)+N($Z50))+N($Y50)))) -> 212278.35 | AJ50: =IF(TRIM($B50)="","",IF(IFERROR(INDEX(Lists!$AO$2:$AO$11,MATCH(ROW(),Lists!$AN$2:$AN$11,0)),"")<>"",IFERROR(INDEX(Lists!$AO$2:$AO$11,MATCH(ROW(),Lists!$AN$2:$AN$11,0)),""),IFERROR(INDEX(Lists!$U:$U,MATCH(TRIM($I50),Lists!$T:$T,0)),TRIM($I50)))) -> Z Retail | AK50: =IF(ISNUMBER(SEARCH("vacant",$B50)),"Vacant","Filled") -> Filled | AL50: =IF($M50="NZ","NZ","AU") -> NZ | AM50: =COUNTIF($AJ$2:$AJ50,$AJ50) -> 27 | AN50: =$AJ50&"|"&$AM50 -> Z Retail|27 | AP50: =IF(TRIM($B50)="","",IF($AQ50=1,"Leadership",IFERROR(INDEX(Lists!$X:$X,MATCH(TRIM($K50),Lists!$W:$W,0)),IF(OR(TRIM($K50)="",LOWER(TRIM($K50))="na"),IF(TRIM($G50)="","Unassigned",TRIM($G50)),TRIM($K50))))) -> Data NZ | AQ50: =IF(TRIM($B50)="","",--OR(TRIM($K50)="Leadership",TRIM($J50)="Leadership")) -> FALSE | AR50: =IF(TRIM($B50)="","",IF(IFERROR(INDEX(Lists!$AQ$2:$AQ$11,MATCH(ROW(),Lists!$AN$2:$AN$11,0)),"")<>"",IFERROR(INDEX(Lists!$AQ$2:$AQ$11,MATCH(ROW(),Lists!$AN$2:$AN$11,0)),""),IF(ISNUMBER(SEARCH("head of ",$C50)),"Head of Technology",IF(ISNUMBER(SEARCH("TDD BP",$C50)),"Business Partner",IF(OR(ISNUMBER(SEARCH("domain architect",$C50)),ISNUMBER(SEARCH("enterprise architect",$C50))),"Domain Architect",IF(ISNUMBER(SEARCH("delivery man",$C50)),"Delivery Manager",IF(OR(ISNUMBER(SEARCH("technology manager",$C50)),ISNUMBER(SEARCH("technology manger",$C50)),ISNUMBER(SEARCH("tech manager",$C50))),"Technology Manager","Squad"))))))) -> Squad | AS50: =IF(TRIM($B50)="","",IFERROR(INDEX(Lists!$AA:$AA,MATCH($AP50,Lists!$Z:$Z,0)),$AP50)) -> Data NZ | AT50: =IF(TRIM($B50)="","",IF(IFERROR(INDEX(Lists!$AP$2:$AP$11,MATCH(ROW(),Lists!$AN$2:$AN$11,0)),"")<>"",IFERROR(INDEX(Lists!$AP$2:$AP$11,MATCH(ROW(),Lists!$AN$2:$AN$11,0)),""),IF(OR(LEFT($AJ50,3)="COE",$AJ50="EGI"),$AP50,IF($AR50<>"Squad",$AR50,$AP50)))) -> Data NZ
A51: 85137 | B51: Mick Standen | C51: Systems Analyst | D51: Vaishnavi Viswanathan | E51: Technology Manager, Store Platform | F51: Ampol Retail & Z | G51: Ampol Retail | H51: Ampol Retail, Store Platforms | I51: Retail | J51: AMPOS | K51: AmPos | M51: Australia | N51: CIB | O51: 1 | Q51: Permanent - Full Time | T51: 196740 | U51: 196740 | V51: 0.12 | W51: 0.055 | X51: 0.12 | Z51: 0.04 | AA51: =IF(TRIM($B51)="","",IF(N($AU51)>0,$AU51,IF(N($S51)>0,$S51*Lists!$AG$15*(1+N($Z51)),N($U51)*(1+N($V51)+N($W51)+N($X51)+N($Z51))+N($Y51)))) -> 262647.9 | AJ51: =IF(TRIM($B51)="","",IF(IFERROR(INDEX(Lists!$AO$2:$AO$11,MATCH(ROW(),Lists!$AN$2:$AN$11,0)),"")<>"",IFERROR(INDEX(Lists!$AO$2:$AO$11,MATCH(ROW(),Lists!$AN$2:$AN$11,0)),""),IFERROR(INDEX(Lists!$U:$U,MATCH(TRIM($I51),Lists!$T:$T,0)),TRIM($I51)))) -> Ampol Retail | AK51: =IF(ISNUMBER(SEARCH("vacant",$B51)),"Vacant","Filled") -> Filled | AL51: =IF($M51="NZ","NZ","AU") -> AU | AM51: =COUNTIF($AJ$2:$AJ51,$AJ51) -> 23 | AN51: =$AJ51&"|"&$AM51 -> Ampol Retail|23 | AP51: =IF(TRIM($B51)="","",IF($AQ51=1,"Leadership",IFERROR(INDEX(Lists!$X:$X,MATCH(TRIM($K51),Lists!$W:$W,0)),IF(OR(TRIM($K51)="",LOWER(TRIM($K51))="na"),IF(TRIM($G51)="","Unassigned",TRIM($G51)),TRIM($K51))))) -> AmPOS | AQ51: =IF(TRIM($B51)="","",--OR(TRIM($K51)="Leadership",TRIM($J51)="Leadership")) -> FALSE | AR51: =IF(TRIM($B51)="","",IF(IFERROR(INDEX(Lists!$AQ$2:$AQ$11,MATCH(ROW(),Lists!$AN$2:$AN$11,0)),"")<>"",IFERROR(INDEX(Lists!$AQ$2:$AQ$11,MATCH(ROW(),Lists!$AN$2:$AN$11,0)),""),IF(ISNUMBER(SEARCH("head of ",$C51)),"Head of Technology",IF(ISNUMBER(SEARCH("TDD BP",$C51)),"Business Partner",IF(OR(ISNUMBER(SEARCH("domain architect",$C51)),ISNUMBER(SEARCH("enterprise architect",$C51))),"Domain Architect",IF(ISNUMBER(SEARCH("delivery man",$C51)),"Delivery Manager",IF(OR(ISNUMBER(SEARCH("technology manager",$C51)),ISNUMBER(SEARCH("technology manger",$C51)),ISNUMBER(SEARCH("tech manager",$C51))),"Technology Manager","Squad"))))))) -> Squad | AS51: =IF(TRIM($B51)="","",IFERROR(INDEX(Lists!$AA:$AA,MATCH($AP51,Lists!$Z:$Z,0)),$AP51)) -> AmPOS | AT51: =IF(TRIM($B51)="","",IF(IFERROR(INDEX(Lists!$AP$2:$AP$11,MATCH(ROW(),Lists!$AN$2:$AN$11,0)),"")<>"",IFERROR(INDEX(Lists!$AP$2:$AP$11,MATCH(ROW(),Lists!$AN$2:$AN$11,0)),""),IF(OR(LEFT($AJ51,3)="COE",$AJ51="EGI"),$AP51,IF($AR51<>"Squad",$AR51,$AP51)))) -> AmPOS
A52: 95286 | B52: Navneet Singh | C52: Solution Architect | D52: Vedran Jukic | E52: Technology Manager, Retail | F52: Ampol Retail & Z | G52: Ampol Retail | H52: Ampol Retail, Technology | I52: Ampol Retail | J52: EGI | K52: EGI Retail | M52: Australia | N52: CIC | O52: 1 | Q52: Permanent - Full Time | T52: 100000 | U52: 100000 | V52: 0.12 | W52: 0.055 | X52: 0.12 | Z52: 0.04 | AA52: =IF(TRIM($B52)="","",IF(N($AU52)>0,$AU52,IF(N($S52)>0,$S52*Lists!$AG$15*(1+N($Z52)),N($U52)*(1+N($V52)+N($W52)+N($X52)+N($Z52))+N($Y52)))) -> 133500 | AJ52: =IF(TRIM($B52)="","",IF(IFERROR(INDEX(Lists!$AO$2:$AO$11,MATCH(ROW(),Lists!$AN$2:$AN$11,0)),"")<>"",IFERROR(INDEX(Lists!$AO$2:$AO$11,MATCH(ROW(),Lists!$AN$2:$AN$11,0)),""),IFERROR(INDEX(Lists!$U:$U,MATCH(TRIM($I52),Lists!$T:$T,0)),TRIM($I52)))) -> Ampol Retail | AK52: =IF(ISNUMBER(SEARCH("vacant",$B52)),"Vacant","Filled") -> Filled | AL52: =IF($M52="NZ","NZ","AU") -> AU | AM52: =COUNTIF($AJ$2:$AJ52,$AJ52) -> 24 | AN52: =$AJ52&"|"&$AM52 -> Ampol Retail|24 | AP52: =IF(TRIM($B52)="","",IF($AQ52=1,"Leadership",IFERROR(INDEX(Lists!$X:$X,MATCH(TRIM($K52),Lists!$W:$W,0)),IF(OR(TRIM($K52)="",LOWER(TRIM($K52))="na"),IF(TRIM($G52)="","Unassigned",TRIM($G52)),TRIM($K52))))) -> EGI Retail | AQ52: =IF(TRIM($B52)="","",--OR(TRIM($K52)="Leadership",TRIM($J52)="Leadership")) -> FALSE | AR52: =IF(TRIM($B52)="","",IF(IFERROR(INDEX(Lists!$AQ$2:$AQ$11,MATCH(ROW(),Lists!$AN$2:$AN$11,0)),"")<>"",IFERROR(INDEX(Lists!$AQ$2:$AQ$11,MATCH(ROW(),Lists!$AN$2:$AN$11,0)),""),IF(ISNUMBER(SEARCH("head of ",$C52)),"Head of Technology",IF(ISNUMBER(SEARCH("TDD BP",$C52)),"Business Partner",IF(OR(ISNUMBER(SEARCH("domain architect",$C52)),ISNUMBER(SEARCH("enterprise architect",$C52))),"Domain Architect",IF(ISNUMBER(SEARCH("delivery man",$C52)),"Delivery Manager",IF(OR(ISNUMBER(SEARCH("technology manager",$C52)),ISNUMBER(SEARCH("technology manger",$C52)),ISNUMBER(SEARCH("tech manager",$C52))),"Technology Manager","Squad"))))))) -> Squad | AS52: =IF(TRIM($B52)="","",IFERROR(INDEX(Lists!$AA:$AA,MATCH($AP52,Lists!$Z:$Z,0)),$AP52)) -> EGI Retail | AT52: =IF(TRIM($B52)="","",IF(IFERROR(INDEX(Lists!$AP$2:$AP$11,MATCH(ROW(),Lists!$AN$2:$AN$11,0)),"")<>"",IFERROR(INDEX(Lists!$AP$2:$AP$11,MATCH(ROW(),Lists!$AN$2:$AN$11,0)),""),IF(OR(LEFT($AJ52,3)="COE",$AJ52="EGI"),$AP52,IF($AR52<>"Squad",$AR52,$AP52)))) -> EGI Retail
A53: 108357 | B53: Pahul Oberoi | C53: Systems Analyst | D53: Tracy Lee Reaper | E53: Tech Manager, Merchandising & WFM | F53: Ampol Retail & Z | G53: Ampol Retail | H53: Ampol Retail, Merch & RTA | I53: Retail | J53: Above Store | K53: Above Store | M53: Australia | N53: CIB | O53: 1 | Q53: Permanent - Full Time | T53: 123240 | U53: 123240 | V53: 0.1 | W53: 0.055 | X53: 0.12 | Z53: 0.04 | AA53: =IF(TRIM($B53)="","",IF(N($AU53)>0,$AU53,IF(N($S53)>0,$S53*Lists!$AG$15*(1+N($Z53)),N($U53)*(1+N($V53)+N($W53)+N($X53)+N($Z53))+N($Y53)))) -> 162060.6 | AJ53: =IF(TRIM($B53)="","",IF(IFERROR(INDEX(Lists!$AO$2:$AO$11,MATCH(ROW(),Lists!$AN$2:$AN$11,0)),"")<>"",IFERROR(INDEX(Lists!$AO$2:$AO$11,MATCH(ROW(),Lists!$AN$2:$AN$11,0)),""),IFERROR(INDEX(Lists!$U:$U,MATCH(TRIM($I53),Lists!$T:$T,0)),TRIM($I53)))) -> Ampol Retail | AK53: =IF(ISNUMBER(SEARCH("vacant",$B53)),"Vacant","Filled") -> Filled | AL53: =IF($M53="NZ","NZ","AU") -> AU | AM53: =COUNTIF($AJ$2:$AJ53,$AJ53) -> 25 | AN53: =$AJ53&"|"&$AM53 -> Ampol Retail|25 | AP53: =IF(TRIM($B53)="","",IF($AQ53=1,"Leadership",IFERROR(INDEX(Lists!$X:$X,MATCH(TRIM($K53),Lists!$W:$W,0)),IF(OR(TRIM($K53)="",LOWER(TRIM($K53))="na"),IF(TRIM($G53)="","Unassigned",TRIM($G53)),TRIM($K53))))) -> Above Store | AQ53: =IF(TRIM($B53)="","",--OR(TRIM($K53)="Leadership",TRIM($J53)="Leadership")) -> FALSE | AR53: =IF(TRIM($B53)="","",IF(IFERROR(INDEX(Lists!$AQ$2:$AQ$11,MATCH(ROW(),Lists!$AN$2:$AN$11,0)),"")<>"",IFERROR(INDEX(Lists!$AQ$2:$AQ$11,MATCH(ROW(),Lists!$AN$2:$AN$11,0)),""),IF(ISNUMBER(SEARCH("head of ",$C53)),"Head of Technology",IF(ISNUMBER(SEARCH("TDD BP",$C53)),"Business Partner",IF(OR(ISNUMBER(SEARCH("domain architect",$C53)),ISNUMBER(SEARCH("enterprise architect",$C53))),"Domain Architect",IF(ISNUMBER(SEARCH("delivery man",$C53)),"Delivery Manager",IF(OR(ISNUMBER(SEARCH("technology manager",$C53)),ISNUMBER(SEARCH("technology manger",$C53)),ISNUMBER(SEARCH("tech manager",$C53))),"Technology Manager","Squad"))))))) -> Squad | AS53: =IF(TRIM($B53)="","",IFERROR(INDEX(Lists!$AA:$AA,MATCH($AP53,Lists!$Z:$Z,0)),$AP53)) -> Above Store | AT53: =IF(TRIM($B53)="","",IF(IFERROR(INDEX(Lists!$AP$2:$AP$11,MATCH(ROW(),Lists!$AN$2:$AN$11,0)),"")<>"",IFERROR(INDEX(Lists!$AP$2:$AP$11,MATCH(ROW(),Lists!$AN$2:$AN$11,0)),""),IF(OR(LEFT($AJ53,3)="COE",$AJ53="EGI"),$AP53,IF($AR53<>"Squad",$AR53,$AP53)))) -> Above Store
A54: 90097 | B54: Patrick Ericson Nario | C54: Support Analyst - Field Operations | D54: Ephriam Adan | E54: Manager, AU Retail Operations | F54: Ampol Retail & Z | G54: Ampol Retail | H54: Ampol Retail, Technology | I54: Retail | J54: Store Operations | K54: Store Operations | M54: Australia | N54: CIA | O54: 1 | Q54: Permanent - Full Time | T54: 160460 | U54: 160460 | V54: 0.12 | W54: 0.055 | X54: 0.12 | Z54: 0.04 | AA54: =IF(TRIM($B54)="","",IF(N($AU54)>0,$AU54,IF(N($S54)>0,$S54*Lists!$AG$15*(1+N($Z54)),N($U54)*(1+N($V54)+N($W54)+N($X54)+N($Z54))+N($Y54)))) -> 214214.1 | AJ54: =IF(TRIM($B54)="","",IF(IFERROR(INDEX(Lists!$AO$2:$AO$11,MATCH(ROW(),Lists!$AN$2:$AN$11,0)),"")<>"",IFERROR(INDEX(Lists!$AO$2:$AO$11,MATCH(ROW(),Lists!$AN$2:$AN$11,0)),""),IFERROR(INDEX(Lists!$U:$U,MATCH(TRIM($I54),Lists!$T:$T,0)),TRIM($I54)))) -> Ampol Retail | AK54: =IF(ISNUMBER(SEARCH("vacant",$B54)),"Vacant","Filled") -> Filled | AL54: =IF($M54="NZ","NZ","AU") -> AU | AM54: =COUNTIF($AJ$2:$AJ54,$AJ54) -> 26 | AN54: =$AJ54&"|"&$AM54 -> Ampol Retail|26 | AP54: =IF(TRIM($B54)="","",IF($AQ54=1,"Leadership",IFERROR(INDEX(Lists!$X:$X,MATCH(TRIM($K54),Lists!$W:$W,0)),IF(OR(TRIM($K54)="",LOWER(TRIM($K54))="na"),IF(TRIM($G54)="","Unassigned",TRIM($G54)),TRIM($K54))))) -> Store Operations | AQ54: =IF(TRIM($B54)="","",--OR(TRIM($K54)="Leadership",TRIM($J54)="Leadership")) -> FALSE | AR54: =IF(TRIM($B54)="","",IF(IFERROR(INDEX(Lists!$AQ$2:$AQ$11,MATCH(ROW(),Lists!$AN$2:$AN$11,0)),"")<>"",IFERROR(INDEX(Lists!$AQ$2:$AQ$11,MATCH(ROW(),Lists!$AN$2:$AN$11,0)),""),IF(ISNUMBER(SEARCH("head of ",$C54)),"Head of Technology",IF(ISNUMBER(SEARCH("TDD BP",$C54)),"Business Partner",IF(OR(ISNUMBER(SEARCH("domain architect",$C54)),ISNUMBER(SEARCH("enterprise architect",$C54))),"Domain Architect",IF(ISNUMBER(SEARCH("delivery man",$C54)),"Delivery Manager",IF(OR(ISNUMBER(SEARCH("technology manager",$C54)),ISNUMBER(SEARCH("technology manger",$C54)),ISNUMBER(SEARCH("tech manager",$C54))),"Technology Manager","Squad"))))))) -> Squad | AS54: =IF(TRIM($B54)="","",IFERROR(INDEX(Lists!$AA:$AA,MATCH($AP54,Lists!$Z:$Z,0)),$AP54)) -> Store Operations | AT54: =IF(TRIM($B54)="","",IF(IFERROR(INDEX(Lists!$AP$2:$AP$11,MATCH(ROW(),Lists!$AN$2:$AN$11,0)),"")<>"",IFERROR(INDEX(Lists!$AP$2:$AP$11,MATCH(ROW(),Lists!$AN$2:$AN$11,0)),""),IF(OR(LEFT($AJ54,3)="COE",$AJ54="EGI"),$AP54,IF($AR54<>"Squad",$AR54,$AP54)))) -> Store Operations
A55: 94420 | B55: Peter Nicolopoulos | C55: Systems Analyst | D55: Vaishnavi Viswanathan | E55: Technology Manager, Store Platform | F55: Ampol Retail & Z | G55: Ampol Retail | H55: Ampol Retail, Store Platforms | I55: Retail | J55: AMPOS | K55: AmPos | M55: Australia | N55: CIB | O55: 1 | Q55: Permanent - Full Time | T55: 127740 | U55: 117520.8 | V55: 0.15 | X55: 0.05 | Y55: 2910 | Z55: 0.03 | AA55: =IF(TRIM($B55)="","",IF(N($AU55)>0,$AU55,IF(N($S55)>0,$S55*Lists!$AG$15*(1+N($Z55)),N($U55)*(1+N($V55)+N($W55)+N($X55)+N($Z55))+N($Y55)))) -> 147460.58 | AJ55: =IF(TRIM($B55)="","",IF(IFERROR(INDEX(Lists!$AO$2:$AO$11,MATCH(ROW(),Lists!$AN$2:$AN$11,0)),"")<>"",IFERROR(INDEX(Lists!$AO$2:$AO$11,MATCH(ROW(),Lists!$AN$2:$AN$11,0)),""),IFERROR(INDEX(Lists!$U:$U,MATCH(TRIM($I55),Lists!$T:$T,0)),TRIM($I55)))) -> Ampol Retail | AK55: =IF(ISNUMBER(SEARCH("vacant",$B55)),"Vacant","Filled") -> Filled | AL55: =IF($M55="NZ","NZ","AU") -> AU | AM55: =COUNTIF($AJ$2:$AJ55,$AJ55) -> 27 | AN55: =$AJ55&"|"&$AM55 -> Ampol Retail|27 | AP55: =IF(TRIM($B55)="","",IF($AQ55=1,"Leadership",IFERROR(INDEX(Lists!$X:$X,MATCH(TRIM($K55),Lists!$W:$W,0)),IF(OR(TRIM($K55)="",LOWER(TRIM($K55))="na"),IF(TRIM($G55)="","Unassigned",TRIM($G55)),TRIM($K55))))) -> AmPOS | AQ55: =IF(TRIM($B55)="","",--OR(TRIM($K55)="Leadership",TRIM($J55)="Leadership")) -> FALSE | AR55: =IF(TRIM($B55)="","",IF(IFERROR(INDEX(Lists!$AQ$2:$AQ$11,MATCH(ROW(),Lists!$AN$2:$AN$11,0)),"")<>"",IFERROR(INDEX(Lists!$AQ$2:$AQ$11,MATCH(ROW(),Lists!$AN$2:$AN$11,0)),""),IF(ISNUMBER(SEARCH("head of ",$C55)),"Head of Technology",IF(ISNUMBER(SEARCH("TDD BP",$C55)),"Business Partner",IF(OR(ISNUMBER(SEARCH("domain architect",$C55)),ISNUMBER(SEARCH("enterprise architect",$C55))),"Domain Architect",IF(ISNUMBER(SEARCH("delivery man",$C55)),"Delivery Manager",IF(OR(ISNUMBER(SEARCH("technology manager",$C55)),ISNUMBER(SEARCH("technology manger",$C55)),ISNUMBER(SEARCH("tech manager",$C55))),"Technology Manager","Squad"))))))) -> Squad | AS55: =IF(TRIM($B55)="","",IFERROR(INDEX(Lists!$AA:$AA,MATCH($AP55,Lists!$Z:$Z,0)),$AP55)) -> AmPOS | AT55: =IF(TRIM($B55)="","",IF(IFERROR(INDEX(Lists!$AP$2:$AP$11,MATCH(ROW(),Lists!$AN$2:$AN$11,0)),"")<>"",IFERROR(INDEX(Lists!$AP$2:$AP$11,MATCH(ROW(),Lists!$AN$2:$AN$11,0)),""),IF(OR(LEFT($AJ55,3)="COE",$AJ55="EGI"),$AP55,IF($AR55<>"Squad",$AR55,$AP55)))) -> AmPOS
A56: 99999101650 | B56: Sakshi Sachdeva | C56: Senior Quality Assurance | D56: Callan McLaughlin | E56: Technology Manager, Site Systems | F56: Ampol Retail & Z | G56: Z & Group Retail | H56: Z & Group Retail, Site Systems | I56: Z | J56: Z Customer | K56: Site Systems | M56: NZ | N56: CIA | O56: 1 | Q56: Permanent - Full Time | T56: 133110 | U56: 133110 | V56: 0.1 | W56: 0.055 | X56: 0.12 | Z56: 0.04 | AA56: =IF(TRIM($B56)="","",IF(N($AU56)>0,$AU56,IF(N($S56)>0,$S56*Lists!$AG$15*(1+N($Z56)),N($U56)*(1+N($V56)+N($W56)+N($X56)+N($Z56))+N($Y56)))) -> 175039.65 | AJ56: =IF(TRIM($B56)="","",IF(IFERROR(INDEX(Lists!$AO$2:$AO$11,MATCH(ROW(),Lists!$AN$2:$AN$11,0)),"")<>"",IFERROR(INDEX(Lists!$AO$2:$AO$11,MATCH(ROW(),Lists!$AN$2:$AN$11,0)),""),IFERROR(INDEX(Lists!$U:$U,MATCH(TRIM($I56),Lists!$T:$T,0)),TRIM($I56)))) -> Z Retail | AK56: =IF(ISNUMBER(SEARCH("vacant",$B56)),"Vacant","Filled") -> Filled | AL56: =IF($M56="NZ","NZ","AU") -> NZ | AM56: =COUNTIF($AJ$2:$AJ56,$AJ56) -> 28 | AN56: =$AJ56&"|"&$AM56 -> Z Retail|28 | AP56: =IF(TRIM($B56)="","",IF($AQ56=1,"Leadership",IFERROR(INDEX(Lists!$X:$X,MATCH(TRIM($K56),Lists!$W:$W,0)),IF(OR(TRIM($K56)="",LOWER(TRIM($K56))="na"),IF(TRIM($G56)="","Unassigned",TRIM($G56)),TRIM($K56))))) -> Site Systems | AQ56: =IF(TRIM($B56)="","",--OR(TRIM($K56)="Leadership",TRIM($J56)="Leadership")) -> FALSE | AR56: =IF(TRIM($B56)="","",IF(IFERROR(INDEX(Lists!$AQ$2:$AQ$11,MATCH(ROW(),Lists!$AN$2:$AN$11,0)),"")<>"",IFERROR(INDEX(Lists!$AQ$2:$AQ$11,MATCH(ROW(),Lists!$AN$2:$AN$11,0)),""),IF(ISNUMBER(SEARCH("head of ",$C56)),"Head of Technology",IF(ISNUMBER(SEARCH("TDD BP",$C56)),"Business Partner",IF(OR(ISNUMBER(SEARCH("domain architect",$C56)),ISNUMBER(SEARCH("enterprise architect",$C56))),"Domain Architect",IF(ISNUMBER(SEARCH("delivery man",$C56)),"Delivery Manager",IF(OR(ISNUMBER(SEARCH("technology manager",$C56)),ISNUMBER(SEARCH("technology manger",$C56)),ISNUMBER(SEARCH("tech manager",$C56))),"Technology Manager","Squad"))))))) -> Squad | AS56: =IF(TRIM($B56)="","",IFERROR(INDEX(Lists!$AA:$AA,MATCH($AP56,Lists!$Z:$Z,0)),$AP56)) -> Site Systems | AT56: =IF(TRIM($B56)="","",IF(IFERROR(INDEX(Lists!$AP$2:$AP$11,MATCH(ROW(),Lists!$AN$2:$AN$11,0)),"")<>"",IFERROR(INDEX(Lists!$AP$2:$AP$11,MATCH(ROW(),Lists!$AN$2:$AN$11,0)),""),IF(OR(LEFT($AJ56,3)="COE",$AJ56="EGI"),$AP56,IF($AR56<>"Squad",$AR56,$AP56)))) -> Site Systems
A57: 107164 | B57: Santiago Hernandez Arevalo | C57: Systems Analyst | D57: Vedran Jukic | E57: Technology Manager, Retail | F57: Ampol Retail & Z | G57: Ampol Retail | H57: Ampol Retail, Technology | I57: Retail | J57: Network/QSR | K57: Network & QSR | M57: Australia | N57: CIA | O57: 1 | Q57: Permanent - Full Time | T57: 154420 | U57: 154420 | V57: 0.12 | W57: 0.055 | X57: 0.12 | Z57: 0.04 | AA57: =IF(TRIM($B57)="","",IF(N($AU57)>0,$AU57,IF(N($S57)>0,$S57*Lists!$AG$15*(1+N($Z57)),N($U57)*(1+N($V57)+N($W57)+N($X57)+N($Z57))+N($Y57)))) -> 206150.7 | AJ57: =IF(TRIM($B57)="","",IF(IFERROR(INDEX(Lists!$AO$2:$AO$11,MATCH(ROW(),Lists!$AN$2:$AN$11,0)),"")<>"",IFERROR(INDEX(Lists!$AO$2:$AO$11,MATCH(ROW(),Lists!$AN$2:$AN$11,0)),""),IFERROR(INDEX(Lists!$U:$U,MATCH(TRIM($I57),Lists!$T:$T,0)),TRIM($I57)))) -> Ampol Retail | AK57: =IF(ISNUMBER(SEARCH("vacant",$B57)),"Vacant","Filled") -> Filled | AL57: =IF($M57="NZ","NZ","AU") -> AU | AM57: =COUNTIF($AJ$2:$AJ57,$AJ57) -> 28 | AN57: =$AJ57&"|"&$AM57 -> Ampol Retail|28 | AP57: =IF(TRIM($B57)="","",IF($AQ57=1,"Leadership",IFERROR(INDEX(Lists!$X:$X,MATCH(TRIM($K57),Lists!$W:$W,0)),IF(OR(TRIM($K57)="",LOWER(TRIM($K57))="na"),IF(TRIM($G57)="","Unassigned",TRIM($G57)),TRIM($K57))))) -> Network & QSR | AQ57: =IF(TRIM($B57)="","",--OR(TRIM($K57)="Leadership",TRIM($J57)="Leadership")) -> FALSE | AR57: =IF(TRIM($B57)="","",IF(IFERROR(INDEX(Lists!$AQ$2:$AQ$11,MATCH(ROW(),Lists!$AN$2:$AN$11,0)),"")<>"",IFERROR(INDEX(Lists!$AQ$2:$AQ$11,MATCH(ROW(),Lists!$AN$2:$AN$11,0)),""),IF(ISNUMBER(SEARCH("head of ",$C57)),"Head of Technology",IF(ISNUMBER(SEARCH("TDD BP",$C57)),"Business Partner",IF(OR(ISNUMBER(SEARCH("domain architect",$C57)),ISNUMBER(SEARCH("enterprise architect",$C57))),"Domain Architect",IF(ISNUMBER(SEARCH("delivery man",$C57)),"Delivery Manager",IF(OR(ISNUMBER(SEARCH("technology manager",$C57)),ISNUMBER(SEARCH("technology manger",$C57)),ISNUMBER(SEARCH("tech manager",$C57))),"Technology Manager","Squad"))))))) -> Squad | AS57: =IF(TRIM($B57)="","",IFERROR(INDEX(Lists!$AA:$AA,MATCH($AP57,Lists!$Z:$Z,0)),$AP57)) -> Network & QSR | AT57: =IF(TRIM($B57)="","",IF(IFERROR(INDEX(Lists!$AP$2:$AP$11,MATCH(ROW(),Lists!$AN$2:$AN$11,0)),"")<>"",IFERROR(INDEX(Lists!$AP$2:$AP$11,MATCH(ROW(),Lists!$AN$2:$AN$11,0)),""),IF(OR(LEFT($AJ57,3)="COE",$AJ57="EGI"),$AP57,IF($AR57<>"Squad",$AR57,$AP57)))) -> Network & QSR
A58: 11424 | B58: Sao Keawprasit | C58: Systems Analyst | D58: Tracy Lee Reaper | E58: Tech Manager, Merchandising & WFM | F58: Ampol Retail & Z | G58: Ampol Retail | H58: Ampol Retail, Merch & RTA | I58: Retail | J58: Above Store | K58: Above Store | M58: Australia | N58: CIB | O58: 1 | Q58: Permanent - Full Time | T58: 152220 | U58: 152220 | V58: 0.12 | W58: 0.055 | X58: 0.12 | Z58: 0.04 | AA58: =IF(TRIM($B58)="","",IF(N($AU58)>0,$AU58,IF(N($S58)>0,$S58*Lists!$AG$15*(1+N($Z58)),N($U58)*(1+N($V58)+N($W58)+N($X58)+N($Z58))+N($Y58)))) -> 203213.7 | AJ58: =IF(TRIM($B58)="","",IF(IFERROR(INDEX(Lists!$AO$2:$AO$11,MATCH(ROW(),Lists!$AN$2:$AN$11,0)),"")<>"",IFERROR(INDEX(Lists!$AO$2:$AO$11,MATCH(ROW(),Lists!$AN$2:$AN$11,0)),""),IFERROR(INDEX(Lists!$U:$U,MATCH(TRIM($I58),Lists!$T:$T,0)),TRIM($I58)))) -> Ampol Retail | AK58: =IF(ISNUMBER(SEARCH("vacant",$B58)),"Vacant","Filled") -> Filled | AL58: =IF($M58="NZ","NZ","AU") -> AU | AM58: =COUNTIF($AJ$2:$AJ58,$AJ58) -> 29 | AN58: =$AJ58&"|"&$AM58 -> Ampol Retail|29 | AP58: =IF(TRIM($B58)="","",IF($AQ58=1,"Leadership",IFERROR(INDEX(Lists!$X:$X,MATCH(TRIM($K58),Lists!$W:$W,0)),IF(OR(TRIM($K58)="",LOWER(TRIM($K58))="na"),IF(TRIM($G58)="","Unassigned",TRIM($G58)),TRIM($K58))))) -> Above Store | AQ58: =IF(TRIM($B58)="","",--OR(TRIM($K58)="Leadership",TRIM($J58)="Leadership")) -> FALSE | AR58: =IF(TRIM($B58)="","",IF(IFERROR(INDEX(Lists!$AQ$2:$AQ$11,MATCH(ROW(),Lists!$AN$2:$AN$11,0)),"")<>"",IFERROR(INDEX(Lists!$AQ$2:$AQ$11,MATCH(ROW(),Lists!$AN$2:$AN$11,0)),""),IF(ISNUMBER(SEARCH("head of ",$C58)),"Head of Technology",IF(ISNUMBER(SEARCH("TDD BP",$C58)),"Business Partner",IF(OR(ISNUMBER(SEARCH("domain architect",$C58)),ISNUMBER(SEARCH("enterprise architect",$C58))),"Domain Architect",IF(ISNUMBER(SEARCH("delivery man",$C58)),"Delivery Manager",IF(OR(ISNUMBER(SEARCH("technology manager",$C58)),ISNUMBER(SEARCH("technology manger",$C58)),ISNUMBER(SEARCH("tech manager",$C58))),"Technology Manager","Squad"))))))) -> Squad | AS58: =IF(TRIM($B58)="","",IFERROR(INDEX(Lists!$AA:$AA,MATCH($AP58,Lists!$Z:$Z,0)),$AP58)) -> Above Store | AT58: =IF(TRIM($B58)="","",IF(IFERROR(INDEX(Lists!$AP$2:$AP$11,MATCH(ROW(),Lists!$AN$2:$AN$11,0)),"")<>"",IFERROR(INDEX(Lists!$AP$2:$AP$11,MATCH(ROW(),Lists!$AN$2:$AN$11,0)),""),IF(OR(LEFT($AJ58,3)="COE",$AJ58="EGI"),$AP58,IF($AR58<>"Squad",$AR58,$AP58)))) -> Above Store
A59: 114003 | B59: Sayan Kar | C59: Systems Analyst | D59: Vaishnavi Viswanathan | E59: Technology Manager, Store Platform | F59: Ampol Retail & Z | G59: Ampol Retail | H59: Ampol Retail, Store Platforms | I59: Retail | J59: Store Operations | K59: Payments | M59: Australia | N59: CIB | O59: 1 | Q59: Permanent - Full Time | T59: 194190 | U59: 194190 | V59: 0.12 | W59: 0.055 | X59: 0.12 | Z59: 0.04 | AA59: =IF(TRIM($B59)="","",IF(N($AU59)>0,$AU59,IF(N($S59)>0,$S59*Lists!$AG$15*(1+N($Z59)),N($U59)*(1+N($V59)+N($W59)+N($X59)+N($Z59))+N($Y59)))) -> 259243.65 | AJ59: =IF(TRIM($B59)="","",IF(IFERROR(INDEX(Lists!$AO$2:$AO$11,MATCH(ROW(),Lists!$AN$2:$AN$11,0)),"")<>"",IFERROR(INDEX(Lists!$AO$2:$AO$11,MATCH(ROW(),Lists!$AN$2:$AN$11,0)),""),IFERROR(INDEX(Lists!$U:$U,MATCH(TRIM($I59),Lists!$T:$T,0)),TRIM($I59)))) -> Ampol Retail | AK59: =IF(ISNUMBER(SEARCH("vacant",$B59)),"Vacant","Filled") -> Filled | AL59: =IF($M59="NZ","NZ","AU") -> AU | AM59: =COUNTIF($AJ$2:$AJ59,$AJ59) -> 30 | AN59: =$AJ59&"|"&$AM59 -> Ampol Retail|30 | AP59: =IF(TRIM($B59)="","",IF($AQ59=1,"Leadership",IFERROR(INDEX(Lists!$X:$X,MATCH(TRIM($K59),Lists!$W:$W,0)),IF(OR(TRIM($K59)="",LOWER(TRIM($K59))="na"),IF(TRIM($G59)="","Unassigned",TRIM($G59)),TRIM($K59))))) -> Payments | AQ59: =IF(TRIM($B59)="","",--OR(TRIM($K59)="Leadership",TRIM($J59)="Leadership")) -> FALSE | AR59: =IF(TRIM($B59)="","",IF(IFERROR(INDEX(Lists!$AQ$2:$AQ$11,MATCH(ROW(),Lists!$AN$2:$AN$11,0)),"")<>"",IFERROR(INDEX(Lists!$AQ$2:$AQ$11,MATCH(ROW(),Lists!$AN$2:$AN$11,0)),""),IF(ISNUMBER(SEARCH("head of ",$C59)),"Head of Technology",IF(ISNUMBER(SEARCH("TDD BP",$C59)),"Business Partner",IF(OR(ISNUMBER(SEARCH("domain architect",$C59)),ISNUMBER(SEARCH("enterprise architect",$C59))),"Domain Architect",IF(ISNUMBER(SEARCH("delivery man",$C59)),"Delivery Manager",IF(OR(ISNUMBER(SEARCH("technology manager",$C59)),ISNUMBER(SEARCH("technology manger",$C59)),ISNUMBER(SEARCH("tech manager",$C59))),"Technology Manager","Squad"))))))) -> Squad | AS59: =IF(TRIM($B59)="","",IFERROR(INDEX(Lists!$AA:$AA,MATCH($AP59,Lists!$Z:$Z,0)),$AP59)) -> Payments | AT59: =IF(TRIM($B59)="","",IF(IFERROR(INDEX(Lists!$AP$2:$AP$11,MATCH(ROW(),Lists!$AN$2:$AN$11,0)),"")<>"",IFERROR(INDEX(Lists!$AP$2:$AP$11,MATCH(ROW(),Lists!$AN$2:$AN$11,0)),""),IF(OR(LEFT($AJ59,3)="COE",$AJ59="EGI"),$AP59,IF($AR59<>"Squad",$AR59,$AP59)))) -> Payments
A60: 98007 | B60: Sendhil Vinayagam (75% EGI) | C60: Solution Architect | D60: Vedran Jukic | E60: Technology Manager, Retail | F60: Ampol Retail & Z | G60: Ampol Retail | H60: Ampol Retail, Technology | I60: Ampol Retail | J60: EGI | K60: EGI Retail | M60: Australia | N60: CIC | O60: 1 | Q60: Permanent - Full Time | T60: 200410 | U60: 200410 | V60: 0.12 | W60: 0.055 | X60: 0.12 | Z60: 0.04 | AA60: =IF(TRIM($B60)="","",IF(N($AU60)>0,$AU60,IF(N($S60)>0,$S60*Lists!$AG$15*(1+N($Z60)),N($U60)*(1+N($V60)+N($W60)+N($X60)+N($Z60))+N($Y60)))) -> 267547.35 | AJ60: =IF(TRIM($B60)="","",IF(IFERROR(INDEX(Lists!$AO$2:$AO$11,MATCH(ROW(),Lists!$AN$2:$AN$11,0)),"")<>"",IFERROR(INDEX(Lists!$AO$2:$AO$11,MATCH(ROW(),Lists!$AN$2:$AN$11,0)),""),IFERROR(INDEX(Lists!$U:$U,MATCH(TRIM($I60),Lists!$T:$T,0)),TRIM($I60)))) -> Ampol Retail | AK60: =IF(ISNUMBER(SEARCH("vacant",$B60)),"Vacant","Filled") -> Filled | AL60: =IF($M60="NZ","NZ","AU") -> AU | AM60: =COUNTIF($AJ$2:$AJ60,$AJ60) -> 31 | AN60: =$AJ60&"|"&$AM60 -> Ampol Retail|31 | AP60: =IF(TRIM($B60)="","",IF($AQ60=1,"Leadership",IFERROR(INDEX(Lists!$X:$X,MATCH(TRIM($K60),Lists!$W:$W,0)),IF(OR(TRIM($K60)="",LOWER(TRIM($K60))="na"),IF(TRIM($G60)="","Unassigned",TRIM($G60)),TRIM($K60))))) -> EGI Retail | AQ60: =IF(TRIM($B60)="","",--OR(TRIM($K60)="Leadership",TRIM($J60)="Leadership")) -> FALSE | AR60: =IF(TRIM($B60)="","",IF(IFERROR(INDEX(Lists!$AQ$2:$AQ$11,MATCH(ROW(),Lists!$AN$2:$AN$11,0)),"")<>"",IFERROR(INDEX(Lists!$AQ$2:$AQ$11,MATCH(ROW(),Lists!$AN$2:$AN$11,0)),""),IF(ISNUMBER(SEARCH("head of ",$C60)),"Head of Technology",IF(ISNUMBER(SEARCH("TDD BP",$C60)),"Business Partner",IF(OR(ISNUMBER(SEARCH("domain architect",$C60)),ISNUMBER(SEARCH("enterprise architect",$C60))),"Domain Architect",IF(ISNUMBER(SEARCH("delivery man",$C60)),"Delivery Manager",IF(OR(ISNUMBER(SEARCH("technology manager",$C60)),ISNUMBER(SEARCH("technology manger",$C60)),ISNUMBER(SEARCH("tech manager",$C60))),"Technology Manager","Squad"))))))) -> Squad | AS60: =IF(TRIM($B60)="","",IFERROR(INDEX(Lists!$AA:$AA,MATCH($AP60,Lists!$Z:$Z,0)),$AP60)) -> EGI Retail | AT60: =IF(TRIM($B60)="","",IF(IFERROR(INDEX(Lists!$AP$2:$AP$11,MATCH(ROW(),Lists!$AN$2:$AN$11,0)),"")<>"",IFERROR(INDEX(Lists!$AP$2:$AP$11,MATCH(ROW(),Lists!$AN$2:$AN$11,0)),""),IF(OR(LEFT($AJ60,3)="COE",$AJ60="EGI"),$AP60,IF($AR60<>"Squad",$AR60,$AP60)))) -> EGI Retail
A61: 95017 | B61: Sjoerd Van Sluijs | C61: Senior PM PEP1, PEP18 | D61: Greg Cassis | E61: GM TDD, EGI | F61: Ampol Retail & Z | G61: EGI | H61: EGI | I61: Ampol Retail | J61: EGI | K61: EGI Retail | M61: Australia | N61: CIC | O61: 1 | Q61: Permanent - Full Time | T61: 118280 | U61: 118280 | V61: 0.1 | W61: 0.055 | X61: 0.12 | Z61: 0.04 | AA61: =IF(TRIM($B61)="","",IF(N($AU61)>0,$AU61,IF(N($S61)>0,$S61*Lists!$AG$15*(1+N($Z61)),N($U61)*(1+N($V61)+N($W61)+N($X61)+N($Z61))+N($Y61)))) -> 155538.2 | AJ61: =IF(TRIM($B61)="","",IF(IFERROR(INDEX(Lists!$AO$2:$AO$11,MATCH(ROW(),Lists!$AN$2:$AN$11,0)),"")<>"",IFERROR(INDEX(Lists!$AO$2:$AO$11,MATCH(ROW(),Lists!$AN$2:$AN$11,0)),""),IFERROR(INDEX(Lists!$U:$U,MATCH(TRIM($I61),Lists!$T:$T,0)),TRIM($I61)))) -> Ampol Retail | AK61: =IF(ISNUMBER(SEARCH("vacant",$B61)),"Vacant","Filled") -> Filled | AL61: =IF($M61="NZ","NZ","AU") -> AU | AM61: =COUNTIF($AJ$2:$AJ61,$AJ61) -> 32 | AN61: =$AJ61&"|"&$AM61 -> Ampol Retail|32 | AP61: =IF(TRIM($B61)="","",IF($AQ61=1,"Leadership",IFERROR(INDEX(Lists!$X:$X,MATCH(TRIM($K61),Lists!$W:$W,0)),IF(OR(TRIM($K61)="",LOWER(TRIM($K61))="na"),IF(TRIM($G61)="","Unassigned",TRIM($G61)),TRIM($K61))))) -> EGI Retail | AQ61: =IF(TRIM($B61)="","",--OR(TRIM($K61)="Leadership",TRIM($J61)="Leadership")) -> FALSE | AR61: =IF(TRIM($B61)="","",IF(IFERROR(INDEX(Lists!$AQ$2:$AQ$11,MATCH(ROW(),Lists!$AN$2:$AN$11,0)),"")<>"",IFERROR(INDEX(Lists!$AQ$2:$AQ$11,MATCH(ROW(),Lists!$AN$2:$AN$11,0)),""),IF(ISNUMBER(SEARCH("head of ",$C61)),"Head of Technology",IF(ISNUMBER(SEARCH("TDD BP",$C61)),"Business Partner",IF(OR(ISNUMBER(SEARCH("domain architect",$C61)),ISNUMBER(SEARCH("enterprise architect",$C61))),"Domain Architect",IF(ISNUMBER(SEARCH("delivery man",$C61)),"Delivery Manager",IF(OR(ISNUMBER(SEARCH("technology manager",$C61)),ISNUMBER(SEARCH("technology manger",$C61)),ISNUMBER(SEARCH("tech manager",$C61))),"Technology Manager","Squad"))))))) -> Squad | AS61: =IF(TRIM($B61)="","",IFERROR(INDEX(Lists!$AA:$AA,MATCH($AP61,Lists!$Z:$Z,0)),$AP61)) -> EGI Retail | AT61: =IF(TRIM($B61)="","",IF(IFERROR(INDEX(Lists!$AP$2:$AP$11,MATCH(ROW(),Lists!$AN$2:$AN$11,0)),"")<>"",IFERROR(INDEX(Lists!$AP$2:$AP$11,MATCH(ROW(),Lists!$AN$2:$AN$11,0)),""),IF(OR(LEFT($AJ61,3)="COE",$AJ61="EGI"),$AP61,IF($AR61<>"Squad",$AR61,$AP61)))) -> EGI Retail
A62: 113783 | B62: Tabitha Raharadjo | C62: Project Coordinator | D62: Vanessa Allen | E62: Delivery Manager, Ampol Retail | F62: Ampol Retail & Z | G62: Ampol Retail | H62: Ampol Retail, Delivery | I62: Retail | J62: AMPOS | K62: AmPos | M62: Australia | N62: CDC | O62: 1 | Q62: Permanent - Full Time | T62: 173230 | U62: 159371.6 | V62: 0.15 | X62: 0.05 | Y62: 2910 | Z62: 0.03 | AA62: =IF(TRIM($B62)="","",IF(N($AU62)>0,$AU62,IF(N($S62)>0,$S62*Lists!$AG$15*(1+N($Z62)),N($U62)*(1+N($V62)+N($W62)+N($X62)+N($Z62))+N($Y62)))) -> 198937.07 | AJ62: =IF(TRIM($B62)="","",IF(IFERROR(INDEX(Lists!$AO$2:$AO$11,MATCH(ROW(),Lists!$AN$2:$AN$11,0)),"")<>"",IFERROR(INDEX(Lists!$AO$2:$AO$11,MATCH(ROW(),Lists!$AN$2:$AN$11,0)),""),IFERROR(INDEX(Lists!$U:$U,MATCH(TRIM($I62),Lists!$T:$T,0)),TRIM($I62)))) -> Ampol Retail | AK62: =IF(ISNUMBER(SEARCH("vacant",$B62)),"Vacant","Filled") -> Filled | AL62: =IF($M62="NZ","NZ","AU") -> AU | AM62: =COUNTIF($AJ$2:$AJ62,$AJ62) -> 33 | AN62: =$AJ62&"|"&$AM62 -> Ampol Retail|33 | AP62: =IF(TRIM($B62)="","",IF($AQ62=1,"Leadership",IFERROR(INDEX(Lists!$X:$X,MATCH(TRIM($K62),Lists!$W:$W,0)),IF(OR(TRIM($K62)="",LOWER(TRIM($K62))="na"),IF(TRIM($G62)="","Unassigned",TRIM($G62)),TRIM($K62))))) -> AmPOS | AQ62: =IF(TRIM($B62)="","",--OR(TRIM($K62)="Leadership",TRIM($J62)="Leadership")) -> FALSE | AR62: =IF(TRIM($B62)="","",IF(IFERROR(INDEX(Lists!$AQ$2:$AQ$11,MATCH(ROW(),Lists!$AN$2:$AN$11,0)),"")<>"",IFERROR(INDEX(Lists!$AQ$2:$AQ$11,MATCH(ROW(),Lists!$AN$2:$AN$11,0)),""),IF(ISNUMBER(SEARCH("head of ",$C62)),"Head of Technology",IF(ISNUMBER(SEARCH("TDD BP",$C62)),"Business Partner",IF(OR(ISNUMBER(SEARCH("domain architect",$C62)),ISNUMBER(SEARCH("enterprise architect",$C62))),"Domain Architect",IF(ISNUMBER(SEARCH("delivery man",$C62)),"Delivery Manager",IF(OR(ISNUMBER(SEARCH("technology manager",$C62)),ISNUMBER(SEARCH("technology manger",$C62)),ISNUMBER(SEARCH("tech manager",$C62))),"Technology Manager","Squad"))))))) -> Squad | AS62: =IF(TRIM($B62)="","",IFERROR(INDEX(Lists!$AA:$AA,MATCH($AP62,Lists!$Z:$Z,0)),$AP62)) -> AmPOS | AT62: =IF(TRIM($B62)="","",IF(IFERROR(INDEX(Lists!$AP$2:$AP$11,MATCH(ROW(),Lists!$AN$2:$AN$11,0)),"")<>"",IFERROR(INDEX(Lists!$AP$2:$AP$11,MATCH(ROW(),Lists!$AN$2:$AN$11,0)),""),IF(OR(LEFT($AJ62,3)="COE",$AJ62="EGI"),$AP62,IF($AR62<>"Squad",$AR62,$AP62)))) -> AmPOS
A63: 9999922690 | B63: Tim Gurnsey | C63: Delivery Lead | D63: Vacant | E63: Delivery Manager, Z and Retail Data | F63: Ampol Retail & Z | G63: Z & Group Retail | H63: Z & Group Retail, Delivery | I63: Z | J63: Z Customer | K63: Site Systems | M63: NZ | N63: CIC | O63: 1 | Q63: Permanent - Full Time | T63: 189604 | U63: 189604 | V63: 0.14 | W63: 0.055 | X63: 0.12 | Z63: 0.04 | AA63: =IF(TRIM($B63)="","",IF(N($AU63)>0,$AU63,IF(N($S63)>0,$S63*Lists!$AG$15*(1+N($Z63)),N($U63)*(1+N($V63)+N($W63)+N($X63)+N($Z63))+N($Y63)))) -> 256913.42 | AJ63: =IF(TRIM($B63)="","",IF(IFERROR(INDEX(Lists!$AO$2:$AO$11,MATCH(ROW(),Lists!$AN$2:$AN$11,0)),"")<>"",IFERROR(INDEX(Lists!$AO$2:$AO$11,MATCH(ROW(),Lists!$AN$2:$AN$11,0)),""),IFERROR(INDEX(Lists!$U:$U,MATCH(TRIM($I63),Lists!$T:$T,0)),TRIM($I63)))) -> Z Retail | AK63: =IF(ISNUMBER(SEARCH("vacant",$B63)),"Vacant","Filled") -> Filled | AL63: =IF($M63="NZ","NZ","AU") -> NZ | AM63: =COUNTIF($AJ$2:$AJ63,$AJ63) -> 29 | AN63: =$AJ63&"|"&$AM63 -> Z Retail|29 | AP63: =IF(TRIM($B63)="","",IF($AQ63=1,"Leadership",IFERROR(INDEX(Lists!$X:$X,MATCH(TRIM($K63),Lists!$W:$W,0)),IF(OR(TRIM($K63)="",LOWER(TRIM($K63))="na"),IF(TRIM($G63)="","Unassigned",TRIM($G63)),TRIM($K63))))) -> Site Systems | AQ63: =IF(TRIM($B63)="","",--OR(TRIM($K63)="Leadership",TRIM($J63)="Leadership")) -> FALSE | AR63: =IF(TRIM($B63)="","",IF(IFERROR(INDEX(Lists!$AQ$2:$AQ$11,MATCH(ROW(),Lists!$AN$2:$AN$11,0)),"")<>"",IFERROR(INDEX(Lists!$AQ$2:$AQ$11,MATCH(ROW(),Lists!$AN$2:$AN$11,0)),""),IF(ISNUMBER(SEARCH("head of ",$C63)),"Head of Technology",IF(ISNUMBER(SEARCH("TDD BP",$C63)),"Business Partner",IF(OR(ISNUMBER(SEARCH("domain architect",$C63)),ISNUMBER(SEARCH("enterprise architect",$C63))),"Domain Architect",IF(ISNUMBER(SEARCH("delivery man",$C63)),"Delivery Manager",IF(OR(ISNUMBER(SEARCH("technology manager",$C63)),ISNUMBER(SEARCH("technology manger",$C63)),ISNUMBER(SEARCH("tech manager",$C63))),"Technology Manager","Squad"))))))) -> Squad | AS63: =IF(TRIM($B63)="","",IFERROR(INDEX(Lists!$AA:$AA,MATCH($AP63,Lists!$Z:$Z,0)),$AP63)) -> Site Systems | AT63: =IF(TRIM($B63)="","",IF(IFERROR(INDEX(Lists!$AP$2:$AP$11,MATCH(ROW(),Lists!$AN$2:$AN$11,0)),"")<>"",IFERROR(INDEX(Lists!$AP$2:$AP$11,MATCH(ROW(),Lists!$AN$2:$AN$11,0)),""),IF(OR(LEFT($AJ63,3)="COE",$AJ63="EGI"),$AP63,IF($AR63<>"Squad",$AR63,$AP63)))) -> Site Systems
A64: 95285 | B64: Tracy Lee Reaper | C64: Technology Manager, Merchandising & WFM | D64: Madan Murthy | E64: Head of Technology, Ampol Retail | F64: Ampol Retail & Z | G64: Ampol Retail | H64: Ampol Retail, Merch & RTA | I64: Retail | J64: Above Store | K64: Leadership | M64: Australia | N64: CSB | O64: 1 | Q64: Permanent - Full Time | T64: 195680 | U64: 180025.6 | V64: 0.15 | X64: 0.05 | Y64: 2910 | Z64: 0.03 | AA64: =IF(TRIM($B64)="","",IF(N($AU64)>0,$AU64,IF(N($S64)>0,$S64*Lists!$AG$15*(1+N($Z64)),N($U64)*(1+N($V64)+N($W64)+N($X64)+N($Z64))+N($Y64)))) -> 224341.49 | AJ64: =IF(TRIM($B64)="","",IF(IFERROR(INDEX(Lists!$AO$2:$AO$11,MATCH(ROW(),Lists!$AN$2:$AN$11,0)),"")<>"",IFERROR(INDEX(Lists!$AO$2:$AO$11,MATCH(ROW(),Lists!$AN$2:$AN$11,0)),""),IFERROR(INDEX(Lists!$U:$U,MATCH(TRIM($I64),Lists!$T:$T,0)),TRIM($I64)))) -> Ampol Retail | AK64: =IF(ISNUMBER(SEARCH("vacant",$B64)),"Vacant","Filled") -> Filled | AL64: =IF($M64="NZ","NZ","AU") -> AU | AM64: =COUNTIF($AJ$2:$AJ64,$AJ64) -> 34 | AN64: =$AJ64&"|"&$AM64 -> Ampol Retail|34 | AP64: =IF(TRIM($B64)="","",IF($AQ64=1,"Leadership",IFERROR(INDEX(Lists!$X:$X,MATCH(TRIM($K64),Lists!$W:$W,0)),IF(OR(TRIM($K64)="",LOWER(TRIM($K64))="na"),IF(TRIM($G64)="","Unassigned",TRIM($G64)),TRIM($K64))))) -> Leadership | AQ64: =IF(TRIM($B64)="","",--OR(TRIM($K64)="Leadership",TRIM($J64)="Leadership")) -> TRUE | AR64: =IF(TRIM($B64)="","",IF(IFERROR(INDEX(Lists!$AQ$2:$AQ$11,MATCH(ROW(),Lists!$AN$2:$AN$11,0)),"")<>"",IFERROR(INDEX(Lists!$AQ$2:$AQ$11,MATCH(ROW(),Lists!$AN$2:$AN$11,0)),""),IF(ISNUMBER(SEARCH("head of ",$C64)),"Head of Technology",IF(ISNUMBER(SEARCH("TDD BP",$C64)),"Business Partner",IF(OR(ISNUMBER(SEARCH("domain architect",$C64)),ISNUMBER(SEARCH("enterprise architect",$C64))),"Domain Architect",IF(ISNUMBER(SEARCH("delivery man",$C64)),"Delivery Manager",IF(OR(ISNUMBER(SEARCH("technology manager",$C64)),ISNUMBER(SEARCH("technology manger",$C64)),ISNUMBER(SEARCH("tech manager",$C64))),"Technology Manager","Squad"))))))) -> Technology Manager | AS64: =IF(TRIM($B64)="","",IFERROR(INDEX(Lists!$AA:$AA,MATCH($AP64,Lists!$Z:$Z,0)),$AP64)) -> Leadership | AT64: =IF(TRIM($B64)="","",IF(IFERROR(INDEX(Lists!$AP$2:$AP$11,MATCH(ROW(),Lists!$AN$2:$AN$11,0)),"")<>"",IFERROR(INDEX(Lists!$AP$2:$AP$11,MATCH(ROW(),Lists!$AN$2:$AN$11,0)),""),IF(OR(LEFT($AJ64,3)="COE",$AJ64="EGI"),$AP64,IF($AR64<>"Squad",$AR64,$AP64)))) -> Technology Manager
A65: 99999101426 | B65: Trevor Weaver | C65: Lead Engineer - Software | D65: Vacant | E65: Technology Manager, Engineering | F65: Ampol Retail & Z | G65: Z & Group Retail | H65: Z & Group Retail, Engineering | I65: Z | J65: Z Customer | K65: Z Retail Backend | M65: NZ | N65: CIC | O65: 1 | Q65: Permanent - Full Time | T65: 133300 | U65: 133300 | V65: 0.1 | W65: 0.055 | X65: 0.12 | Z65: 0.04 | AA65: =IF(TRIM($B65)="","",IF(N($AU65)>0,$AU65,IF(N($S65)>0,$S65*Lists!$AG$15*(1+N($Z65)),N($U65)*(1+N($V65)+N($W65)+N($X65)+N($Z65))+N($Y65)))) -> 175289.5 | AJ65: =IF(TRIM($B65)="","",IF(IFERROR(INDEX(Lists!$AO$2:$AO$11,MATCH(ROW(),Lists!$AN$2:$AN$11,0)),"")<>"",IFERROR(INDEX(Lists!$AO$2:$AO$11,MATCH(ROW(),Lists!$AN$2:$AN$11,0)),""),IFERROR(INDEX(Lists!$U:$U,MATCH(TRIM($I65),Lists!$T:$T,0)),TRIM($I65)))) -> Z Retail | AK65: =IF(ISNUMBER(SEARCH("vacant",$B65)),"Vacant","Filled") -> Filled | AL65: =IF($M65="NZ","NZ","AU") -> NZ | AM65: =COUNTIF($AJ$2:$AJ65,$AJ65) -> 30 | AN65: =$AJ65&"|"&$AM65 -> Z Retail|30 | AP65: =IF(TRIM($B65)="","",IF($AQ65=1,"Leadership",IFERROR(INDEX(Lists!$X:$X,MATCH(TRIM($K65),Lists!$W:$W,0)),IF(OR(TRIM($K65)="",LOWER(TRIM($K65))="na"),IF(TRIM($G65)="","Unassigned",TRIM($G65)),TRIM($K65))))) -> Z Retail Backend | AQ65: =IF(TRIM($B65)="","",--OR(TRIM($K65)="Leadership",TRIM($J65)="Leadership")) -> FALSE | AR65: =IF(TRIM($B65)="","",IF(IFERROR(INDEX(Lists!$AQ$2:$AQ$11,MATCH(ROW(),Lists!$AN$2:$AN$11,0)),"")<>"",IFERROR(INDEX(Lists!$AQ$2:$AQ$11,MATCH(ROW(),Lists!$AN$2:$AN$11,0)),""),IF(ISNUMBER(SEARCH("head of ",$C65)),"Head of Technology",IF(ISNUMBER(SEARCH("TDD BP",$C65)),"Business Partner",IF(OR(ISNUMBER(SEARCH("domain architect",$C65)),ISNUMBER(SEARCH("enterprise architect",$C65))),"Domain Architect",IF(ISNUMBER(SEARCH("delivery man",$C65)),"Delivery Manager",IF(OR(ISNUMBER(SEARCH("technology manager",$C65)),ISNUMBER(SEARCH("technology manger",$C65)),ISNUMBER(SEARCH("tech manager",$C65))),"Technology Manager","Squad"))))))) -> Squad | AS65: =IF(TRIM($B65)="","",IFERROR(INDEX(Lists!$AA:$AA,MATCH($AP65,Lists!$Z:$Z,0)),$AP65)) -> Z Retail Backend | AT65: =IF(TRIM($B65)="","",IF(IFERROR(INDEX(Lists!$AP$2:$AP$11,MATCH(ROW(),Lists!$AN$2:$AN$11,0)),"")<>"",IFERROR(INDEX(Lists!$AP$2:$AP$11,MATCH(ROW(),Lists!$AN$2:$AN$11,0)),""),IF(OR(LEFT($AJ65,3)="COE",$AJ65="EGI"),$AP65,IF($AR65<>"Squad",$AR65,$AP65)))) -> Z Retail Backend
A66: 85136 | B66: Tuan Edwards | C66: Field Systems Operations Lead - QLD | D66: Ephraim Adan | E66: Manager, AU Retail Operations | F66: Ampol Retail & Z | G66: Ampol Retail | H66: Ampol Retail, Technology | I66: Retail | J66: Store Operations | K66: Store Operations | M66: Australia | N66: CIA | O66: 1 | Q66: V | T66: 151950 | U66: 151950 | V66: 0.12 | W66: 0.055 | X66: 0.12 | Z66: 0.04 | AA66: =IF(TRIM($B66)="","",IF(N($AU66)>0,$AU66,IF(N($S66)>0,$S66*Lists!$AG$15*(1+N($Z66)),N($U66)*(1+N($V66)+N($W66)+N($X66)+N($Z66))+N($Y66)))) -> 202853.25 | AJ66: =IF(TRIM($B66)="","",IF(IFERROR(INDEX(Lists!$AO$2:$AO$11,MATCH(ROW(),Lists!$AN$2:$AN$11,0)),"")<>"",IFERROR(INDEX(Lists!$AO$2:$AO$11,MATCH(ROW(),Lists!$AN$2:$AN$11,0)),""),IFERROR(INDEX(Lists!$U:$U,MATCH(TRIM($I66),Lists!$T:$T,0)),TRIM($I66)))) -> Ampol Retail | AK66: =IF(ISNUMBER(SEARCH("vacant",$B66)),"Vacant","Filled") -> Filled | AL66: =IF($M66="NZ","NZ","AU") -> AU | AM66: =COUNTIF($AJ$2:$AJ66,$AJ66) -> 35 | AN66: =$AJ66&"|"&$AM66 -> Ampol Retail|35 | AP66: =IF(TRIM($B66)="","",IF($AQ66=1,"Leadership",IFERROR(INDEX(Lists!$X:$X,MATCH(TRIM($K66),Lists!$W:$W,0)),IF(OR(TRIM($K66)="",LOWER(TRIM($K66))="na"),IF(TRIM($G66)="","Unassigned",TRIM($G66)),TRIM($K66))))) -> Store Operations | AQ66: =IF(TRIM($B66)="","",--OR(TRIM($K66)="Leadership",TRIM($J66)="Leadership")) -> FALSE | AR66: =IF(TRIM($B66)="","",IF(IFERROR(INDEX(Lists!$AQ$2:$AQ$11,MATCH(ROW(),Lists!$AN$2:$AN$11,0)),"")<>"",IFERROR(INDEX(Lists!$AQ$2:$AQ$11,MATCH(ROW(),Lists!$AN$2:$AN$11,0)),""),IF(ISNUMBER(SEARCH("head of ",$C66)),"Head of Technology",IF(ISNUMBER(SEARCH("TDD BP",$C66)),"Business Partner",IF(OR(ISNUMBER(SEARCH("domain architect",$C66)),ISNUMBER(SEARCH("enterprise architect",$C66))),"Domain Architect",IF(ISNUMBER(SEARCH("delivery man",$C66)),"Delivery Manager",IF(OR(ISNUMBER(SEARCH("technology manager",$C66)),ISNUMBER(SEARCH("technology manger",$C66)),ISNUMBER(SEARCH("tech manager",$C66))),"Technology Manager","Squad"))))))) -> Squad | AS66: =IF(TRIM($B66)="","",IFERROR(INDEX(Lists!$AA:$AA,MATCH($AP66,Lists!$Z:$Z,0)),$AP66)) -> Store Operations | AT66: =IF(TRIM($B66)="","",IF(IFERROR(INDEX(Lists!$AP$2:$AP$11,MATCH(ROW(),Lists!$AN$2:$AN$11,0)),"")<>"",IFERROR(INDEX(Lists!$AP$2:$AP$11,MATCH(ROW(),Lists!$AN$2:$AN$11,0)),""),IF(OR(LEFT($AJ66,3)="COE",$AJ66="EGI"),$AP66,IF($AR66<>"Squad",$AR66,$AP66)))) -> Store Operations
A67: V | B67: Vacant | C67: Business Analyst | D67: Vanessa Allen | E67: Delivery Manager, Ampol Retail | F67: Ampol Retail & Z | G67: Ampol Retail | H67: Ampol Retail, Delivery | I67: Retail | J67: Above Store | K67: Above Store | M67: Australia | N67: CIB | O67: 1 | Q67: V | T67: 151950 | U67: 151950 | V67: 0.12 | W67: 0.055 | X67: 0.12 | Z67: 0.04 | AA67: =IF(TRIM($B67)="","",IF(N($AU67)>0,$AU67,IF(N($S67)>0,$S67*Lists!$AG$15*(1+N($Z67)),N($U67)*(1+N($V67)+N($W67)+N($X67)+N($Z67))+N($Y67)))) -> 202853.25 | AJ67: =IF(TRIM($B67)="","",IF(IFERROR(INDEX(Lists!$AO$2:$AO$11,MATCH(ROW(),Lists!$AN$2:$AN$11,0)),"")<>"",IFERROR(INDEX(Lists!$AO$2:$AO$11,MATCH(ROW(),Lists!$AN$2:$AN$11,0)),""),IFERROR(INDEX(Lists!$U:$U,MATCH(TRIM($I67),Lists!$T:$T,0)),TRIM($I67)))) -> Ampol Retail | AK67: =IF(ISNUMBER(SEARCH("vacant",$B67)),"Vacant","Filled") -> Vacant | AL67: =IF($M67="NZ","NZ","AU") -> AU | AM67: =COUNTIF($AJ$2:$AJ67,$AJ67) -> 36 | AN67: =$AJ67&"|"&$AM67 -> Ampol Retail|36 | AP67: =IF(TRIM($B67)="","",IF($AQ67=1,"Leadership",IFERROR(INDEX(Lists!$X:$X,MATCH(TRIM($K67),Lists!$W:$W,0)),IF(OR(TRIM($K67)="",LOWER(TRIM($K67))="na"),IF(TRIM($G67)="","Unassigned",TRIM($G67)),TRIM($K67))))) -> Above Store | AQ67: =IF(TRIM($B67)="","",--OR(TRIM($K67)="Leadership",TRIM($J67)="Leadership")) -> FALSE | AR67: =IF(TRIM($B67)="","",IF(IFERROR(INDEX(Lists!$AQ$2:$AQ$11,MATCH(ROW(),Lists!$AN$2:$AN$11,0)),"")<>"",IFERROR(INDEX(Lists!$AQ$2:$AQ$11,MATCH(ROW(),Lists!$AN$2:$AN$11,0)),""),IF(ISNUMBER(SEARCH("head of ",$C67)),"Head of Technology",IF(ISNUMBER(SEARCH("TDD BP",$C67)),"Business Partner",IF(OR(ISNUMBER(SEARCH("domain architect",$C67)),ISNUMBER(SEARCH("enterprise architect",$C67))),"Domain Architect",IF(ISNUMBER(SEARCH("delivery man",$C67)),"Delivery Manager",IF(OR(ISNUMBER(SEARCH("technology manager",$C67)),ISNUMBER(SEARCH("technology manger",$C67)),ISNUMBER(SEARCH("tech manager",$C67))),"Technology Manager","Squad"))))))) -> Squad | AS67: =IF(TRIM($B67)="","",IFERROR(INDEX(Lists!$AA:$AA,MATCH($AP67,Lists!$Z:$Z,0)),$AP67)) -> Above Store | AT67: =IF(TRIM($B67)="","",IF(IFERROR(INDEX(Lists!$AP$2:$AP$11,MATCH(ROW(),Lists!$AN$2:$AN$11,0)),"")<>"",IFERROR(INDEX(Lists!$AP$2:$AP$11,MATCH(ROW(),Lists!$AN$2:$AN$11,0)),""),IF(OR(LEFT($AJ67,3)="COE",$AJ67="EGI"),$AP67,IF($AR67<>"Squad",$AR67,$AP67)))) -> Above Store
