Workbook

Sheet 1 Start here
B2: Offshore scenario builder
B4: Pick which roles move offshore and when. Compare up to three lists side by side and see the cost come out, month by month.
B8: Example | E8: List B | H8: List C
B10: ='3 Compare'!C9 -> 0.38966 | E10: ='3 Compare'!D9 -> 0 | H10: ='3 Compare'!E9 -> 0
B11: =TEXT('3 Compare'!C5,"0")&" roles · "&TEXT('3 Compare'!C6,"0.0")&" FTE · 2026 $"&TEXT('3 Compare'!C10,"0.00")&"m" -> 4 roles · 4.0 FTE · 2026 $0.07m | E11: =TEXT('3 Compare'!D5,"0")&" roles · "&TEXT('3 Compare'!D6,"0.0")&" FTE · 2026 $"&TEXT('3 Compare'!D10,"0.00")&"m" -> 0 roles · 0.0 FTE · 2026 $0.00m | H11: =TEXT('3 Compare'!E5,"0")&" roles · "&TEXT('3 Compare'!E6,"0.0")&" FTE · 2026 $"&TEXT('3 Compare'!E10,"0.00")&"m" -> 0 roles · 0.0 FTE · 2026 $0.00m
B12: =TEXT(IFERROR('3 Compare'!C9/'3 Compare'!C7,0),"0%")&" of what these roles cost today" -> 51% of what these roles cost today | E12: =TEXT(IFERROR('3 Compare'!D9/'3 Compare'!D7,0),"0%")&" of what these roles cost today" -> 0% of what these roles cost today | H12: =TEXT(IFERROR('3 Compare'!E9/'3 Compare'!E7,0),"0%")&" of what these roles cost today" -> 0% of what these roles cost today
B13: Type over a yellow title to rename that list. The Example list holds a worked example - clear it on the Pick roles tab and make your own.
B15: Ten biggest roles you've picked ($m a year)
B16: Role | E16: Portfolio | G16: Lists | H16: $m / yr
B17: =IF($N17<0.00001,"",INDEX('2 Pick roles'!$C$5:$C$544,$O17)) -> Snr Business Analyst | E17: =IF($N17<0.00001,"",INDEX('2 Pick roles'!$D$5:$D$544,$O17)) -> Ampol Customer | G17: =IF($N17<0.00001,"",INDEX('2 Pick roles'!$AF$5:$AF$544,$O17)) -> A | H17: =IF($N17<0.00001,"",INDEX('2 Pick roles'!$AD$5:$AD$544,$O17)) -> 0.16374 | N17: =IFERROR(LARGE('2 Pick roles'!$AE$5:$AE$544,1),0) -> 0.16374001 | O17: =IFERROR(MATCH($N17,'2 Pick roles'!$AE$5:$AE$544,0),0) -> 2
B18: =IF($N18<0.00001,"",INDEX('2 Pick roles'!$C$5:$C$544,$O18)) -> Systems Analyst | E18: =IF($N18<0.00001,"",INDEX('2 Pick roles'!$D$5:$D$544,$O18)) -> Retail | G18: =IF($N18<0.00001,"",INDEX('2 Pick roles'!$AF$5:$AF$544,$O18)) -> A | H18: =IF($N18<0.00001,"",INDEX('2 Pick roles'!$AD$5:$AD$544,$O18)) -> 0.12096 | N18: =IFERROR(LARGE('2 Pick roles'!$AE$5:$AE$544,2),0) -> 0.12096047 | O18: =IFERROR(MATCH($N18,'2 Pick roles'!$AE$5:$AE$544,0),0) -> 468
B19: =IF($N19<0.00001,"",INDEX('2 Pick roles'!$C$5:$C$544,$O19)) -> Integration Specialist (ASAPIO CTR | E19: =IF($N19<0.00001,"",INDEX('2 Pick roles'!$D$5:$D$544,$O19)) -> Finance | G19: =IF($N19<0.00001,"",INDEX('2 Pick roles'!$AF$5:$AF$544,$O19)) -> A | H19: =IF($N19<0.00001,"",INDEX('2 Pick roles'!$AD$5:$AD$544,$O19)) -> 0.10494 | N19: =IFERROR(LARGE('2 Pick roles'!$AE$5:$AE$544,3),0) -> 0.10494035 | O19: =IFERROR(MATCH($N19,'2 Pick roles'!$AE$5:$AE$544,0),0) -> 351
B20: =IF($N20<0.00001,"",INDEX('2 Pick roles'!$C$5:$C$544,$O20)) -> Lead Engineer - Mobile | E20: =IF($N20<0.00001,"",INDEX('2 Pick roles'!$D$5:$D$544,$O20)) -> Ampol Customer | G20: =IF($N20<0.00001,"",INDEX('2 Pick roles'!$AF$5:$AF$544,$O20)) -> A | H20: =IF($N20<0.00001,"",INDEX('2 Pick roles'!$AD$5:$AD$544,$O20)) -> 2e-05 | N20: =IFERROR(LARGE('2 Pick roles'!$AE$5:$AE$544,4),0) -> 2.0033e-05 | O20: =IFERROR(MATCH($N20,'2 Pick roles'!$AE$5:$AE$544,0),0) -> 29
B21: =IF($N21<0.00001,"",INDEX('2 Pick roles'!$C$5:$C$544,$O21)) | E21: =IF($N21<0.00001,"",INDEX('2 Pick roles'!$D$5:$D$544,$O21)) | G21: =IF($N21<0.00001,"",INDEX('2 Pick roles'!$AF$5:$AF$544,$O21)) | H21: =IF($N21<0.00001,"",INDEX('2 Pick roles'!$AD$5:$AD$544,$O21)) | N21: =IFERROR(LARGE('2 Pick roles'!$AE$5:$AE$544,5),0) -> 5.44e-07 | O21: =IFERROR(MATCH($N21,'2 Pick roles'!$AE$5:$AE$544,0),0) -> 540
B22: =IF($N22<0.00001,"",INDEX('2 Pick roles'!$C$5:$C$544,$O22)) | E22: =IF($N22<0.00001,"",INDEX('2 Pick roles'!$D$5:$D$544,$O22)) | G22: =IF($N22<0.00001,"",INDEX('2 Pick roles'!$AF$5:$AF$544,$O22)) | H22: =IF($N22<0.00001,"",INDEX('2 Pick roles'!$AD$5:$AD$544,$O22)) | N22: =IFERROR(LARGE('2 Pick roles'!$AE$5:$AE$544,6),0) -> 5.43e-07 | O22: =IFERROR(MATCH($N22,'2 Pick roles'!$AE$5:$AE$544,0),0) -> 539
B23: =IF($N23<0.00001,"",INDEX('2 Pick roles'!$C$5:$C$544,$O23)) | E23: =IF($N23<0.00001,"",INDEX('2 Pick roles'!$D$5:$D$544,$O23)) | G23: =IF($N23<0.00001,"",INDEX('2 Pick roles'!$AF$5:$AF$544,$O23)) | H23: =IF($N23<0.00001,"",INDEX('2 Pick roles'!$AD$5:$AD$544,$O23)) | N23: =IFERROR(LARGE('2 Pick roles'!$AE$5:$AE$544,7),0) -> 5.42e-07 | O23: =IFERROR(MATCH($N23,'2 Pick roles'!$AE$5:$AE$544,0),0) -> 538
B24: =IF($N24<0.00001,"",INDEX('2 Pick roles'!$C$5:$C$544,$O24)) | E24: =IF($N24<0.00001,"",INDEX('2 Pick roles'!$D$5:$D$544,$O24)) | G24: =IF($N24<0.00001,"",INDEX('2 Pick roles'!$AF$5:$AF$544,$O24)) | H24: =IF($N24<0.00001,"",INDEX('2 Pick roles'!$AD$5:$AD$544,$O24)) | N24: =IFERROR(LARGE('2 Pick roles'!$AE$5:$AE$544,8),0) -> 5.41e-07 | O24: =IFERROR(MATCH($N24,'2 Pick roles'!$AE$5:$AE$544,0),0) -> 537
B25: =IF($N25<0.00001,"",INDEX('2 Pick roles'!$C$5:$C$544,$O25)) | E25: =IF($N25<0.00001,"",INDEX('2 Pick roles'!$D$5:$D$544,$O25)) | G25: =IF($N25<0.00001,"",INDEX('2 Pick roles'!$AF$5:$AF$544,$O25)) | H25: =IF($N25<0.00001,"",INDEX('2 Pick roles'!$AD$5:$AD$544,$O25)) | N25: =IFERROR(LARGE('2 Pick roles'!$AE$5:$AE$544,9),0) -> 5.4e-07 | O25: =IFERROR(MATCH($N25,'2 Pick roles'!$AE$5:$AE$544,0),0) -> 536
B26: =IF($N26<0.00001,"",INDEX('2 Pick roles'!$C$5:$C$544,$O26)) | E26: =IF($N26<0.00001,"",INDEX('2 Pick roles'!$D$5:$D$544,$O26)) | G26: =IF($N26<0.00001,"",INDEX('2 Pick roles'!$AF$5:$AF$544,$O26)) | H26: =IF($N26<0.00001,"",INDEX('2 Pick roles'!$AD$5:$AD$544,$O26)) | N26: =IFERROR(LARGE('2 Pick roles'!$AE$5:$AE$544,10),0) -> 5.39e-07 | O26: =IFERROR(MATCH($N26,'2 Pick roles'!$AE$5:$AE$544,0),0) -> 535
B29: How to use it
B30: 1. Open the Pick roles tab and use the filter arrows to find the roles you want.
B31: 2. Set a role to Yes in List A, B or C, and choose the month it moves. It can sit in more than one list.
B32: 3. A role set to Yes turns green. If it has no month it flags red until you choose one.
B33: 4. This page and the Compare tab move as you go.
B35: How the money works
B36: A role that moves offshore costs 40% of its full onshore cost. What comes out is today's cost less that 40%.
B37: Roles on vendor day rates stay as they are. A held role costs nothing today, so moving it shows as added cost.
B38: The year is the calendar year (Ampol's December year-end). The horizon runs Jul-2026 to Dec-2027.
B39: Figures are A$ millions. NZ roles are converted at the planning rate.
B40: The tabs are locked so the sums can't break. Only the yellow cells take typing. Password to unlock: Tdd123.
B41: Built from the role mapping in TDD_FY27_Cost_Calc_0608 (11 August 2026), copied in full on the hidden data tab.

Sheet 2 Pick roles
B1: Pick roles
B2: Filter to find a role, set it to Yes in List A, B or C, and choose the month it moves. A role can sit in more than one list.
B4: Role ID | C4: Role | D4: Portfolio | E4: Squad or line | F4: AU / NZ | G4: Status | H4: FTE | I4: Cost today $m | J4: In A? | K4: A month | L4: In B? | M4: B month | N4: In C? | O4: C month | P4: Full onshore $m | Q4: Taken out A $m/yr | R4: pos A | S4: 2026 A $m | T4: 2027 A $m | U4: Taken out B $m/yr | V4: pos B | W4: 2026 B $m | X4: 2027 B $m | Y4: Taken out C $m/yr | Z4: pos C | AA4: 2026 C $m | AB4: 2027 C $m | AC4: In any list? | AD4: Best taken out $m/yr | AE4: rank | AF4: Lists
B5: R0001 | C5: Delivery Lead | D5: EGI Integration | E5: EGI Customer | F5: AU | G5: Filled | H5: 1 | I5: 0.2642 | J5: No | L5: No | N5: No | P5: 0.2642 | Q5: =IF(AND($J5="Yes",$G5<>"Vendor day rates"),$I5-0.4*$P5,0) -> 0 | R5: =IFERROR(MATCH($K5,MonthList,0),0) -> 0 | S5: =IF(OR($J5<>"Yes",$K5=""),0,$Q5*MAX(0,7-$R5)/12) -> 0 | T5: =IF(OR($J5<>"Yes",$K5=""),0,$Q5*IF($R5<=7,12,19-$R5)/12) -> 0 | U5: =IF(AND($L5="Yes",$G5<>"Vendor day rates"),$I5-0.4*$P5,0) -> 0 | V5: =IFERROR(MATCH($M5,MonthList,0),0) -> 0 | W5: =IF(OR($L5<>"Yes",$M5=""),0,$U5*MAX(0,7-$V5)/12) -> 0 | X5: =IF(OR($L5<>"Yes",$M5=""),0,$U5*IF($V5<=7,12,19-$V5)/12) -> 0 | Y5: =IF(AND($N5="Yes",$G5<>"Vendor day rates"),$I5-0.4*$P5,0) -> 0 | Z5: =IFERROR(MATCH($O5,MonthList,0),0) -> 0 | AA5: =IF(OR($N5<>"Yes",$O5=""),0,$Y5*MAX(0,7-$Z5)/12) -> 0 | AB5: =IF(OR($N5<>"Yes",$O5=""),0,$Y5*IF($Z5<=7,12,19-$Z5)/12) -> 0 | AC5: =IF(OR($J5="Yes",$L5="Yes",$N5="Yes"),"Yes","No") -> No | AD5: =MAX($Q5,$U5,$Y5) -> 0 | AE5: =$AD5+ROW()*0.000000001 -> 5e-09 | AF5: =IF($J5="Yes","A","")&IF($L5="Yes","B","")&IF($N5="Yes","C","")
B6: R0002 | C6: Snr Business Analyst | D6: Ampol Customer | E6: Ampol Web | F6: AU | G6: Filled | H6: 1 | I6: 0.2729 | J6: Yes | K6: Oct-2026 | L6: No | N6: No | P6: 0.2729 | Q6: =IF(AND($J6="Yes",$G6<>"Vendor day rates"),$I6-0.4*$P6,0) -> 0.16374 | R6: =IFERROR(MATCH($K6,MonthList,0),0) -> 4 | S6: =IF(OR($J6<>"Yes",$K6=""),0,$Q6*MAX(0,7-$R6)/12) -> 0.040935 | T6: =IF(OR($J6<>"Yes",$K6=""),0,$Q6*IF($R6<=7,12,19-$R6)/12) -> 0.16374 | U6: =IF(AND($L6="Yes",$G6<>"Vendor day rates"),$I6-0.4*$P6,0) -> 0 | V6: =IFERROR(MATCH($M6,MonthList,0),0) -> 0 | W6: =IF(OR($L6<>"Yes",$M6=""),0,$U6*MAX(0,7-$V6)/12) -> 0 | X6: =IF(OR($L6<>"Yes",$M6=""),0,$U6*IF($V6<=7,12,19-$V6)/12) -> 0 | Y6: =IF(AND($N6="Yes",$G6<>"Vendor day rates"),$I6-0.4*$P6,0) -> 0 | Z6: =IFERROR(MATCH($O6,MonthList,0),0) -> 0 | AA6: =IF(OR($N6<>"Yes",$O6=""),0,$Y6*MAX(0,7-$Z6)/12) -> 0 | AB6: =IF(OR($N6<>"Yes",$O6=""),0,$Y6*IF($Z6<=7,12,19-$Z6)/12) -> 0 | AC6: =IF(OR($J6="Yes",$L6="Yes",$N6="Yes"),"Yes","No") -> Yes | AD6: =MAX($Q6,$U6,$Y6) -> 0.16374 | AE6: =$AD6+ROW()*0.000000001 -> 0.16374001 | AF6: =IF($J6="Yes","A","")&IF($L6="Yes","B","")&IF($N6="Yes","C","") -> A
B7: R0003 | C7: Snr Business Analyst | D7: Ampol Customer | E7: Ampol App | F7: AU | G7: Filled | H7: 1 | I7: 0.2591 | J7: No | L7: No | N7: No | P7: 0.2591 | Q7: =IF(AND($J7="Yes",$G7<>"Vendor day rates"),$I7-0.4*$P7,0) -> 0 | R7: =IFERROR(MATCH($K7,MonthList,0),0) -> 0 | S7: =IF(OR($J7<>"Yes",$K7=""),0,$Q7*MAX(0,7-$R7)/12) -> 0 | T7: =IF(OR($J7<>"Yes",$K7=""),0,$Q7*IF($R7<=7,12,19-$R7)/12) -> 0 | U7: =IF(AND($L7="Yes",$G7<>"Vendor day rates"),$I7-0.4*$P7,0) -> 0 | V7: =IFERROR(MATCH($M7,MonthList,0),0) -> 0 | W7: =IF(OR($L7<>"Yes",$M7=""),0,$U7*MAX(0,7-$V7)/12) -> 0 | X7: =IF(OR($L7<>"Yes",$M7=""),0,$U7*IF($V7<=7,12,19-$V7)/12) -> 0 | Y7: =IF(AND($N7="Yes",$G7<>"Vendor day rates"),$I7-0.4*$P7,0) -> 0 | Z7: =IFERROR(MATCH($O7,MonthList,0),0) -> 0 | AA7: =IF(OR($N7<>"Yes",$O7=""),0,$Y7*MAX(0,7-$Z7)/12) -> 0 | AB7: =IF(OR($N7<>"Yes",$O7=""),0,$Y7*IF($Z7<=7,12,19-$Z7)/12) -> 0 | AC7: =IF(OR($J7="Yes",$L7="Yes",$N7="Yes"),"Yes","No") -> No | AD7: =MAX($Q7,$U7,$Y7) -> 0 | AE7: =$AD7+ROW()*0.000000001 -> 7e-09 | AF7: =IF($J7="Yes","A","")&IF($L7="Yes","B","")&IF($N7="Yes","C","")
B8: R0004 | C8: Business Analyst (SAP Payroll) | D8: EGI | E8: EGI | F8: AU | G8: Filled | H8: 1 | I8: 0.2442 | J8: No | L8: No | N8: No | P8: 0.2442 | Q8: =IF(AND($J8="Yes",$G8<>"Vendor day rates"),$I8-0.4*$P8,0) -> 0 | R8: =IFERROR(MATCH($K8,MonthList,0),0) -> 0 | S8: =IF(OR($J8<>"Yes",$K8=""),0,$Q8*MAX(0,7-$R8)/12) -> 0 | T8: =IF(OR($J8<>"Yes",$K8=""),0,$Q8*IF($R8<=7,12,19-$R8)/12) -> 0 | U8: =IF(AND($L8="Yes",$G8<>"Vendor day rates"),$I8-0.4*$P8,0) -> 0 | V8: =IFERROR(MATCH($M8,MonthList,0),0) -> 0 | W8: =IF(OR($L8<>"Yes",$M8=""),0,$U8*MAX(0,7-$V8)/12) -> 0 | X8: =IF(OR($L8<>"Yes",$M8=""),0,$U8*IF($V8<=7,12,19-$V8)/12) -> 0 | Y8: =IF(AND($N8="Yes",$G8<>"Vendor day rates"),$I8-0.4*$P8,0) -> 0 | Z8: =IFERROR(MATCH($O8,MonthList,0),0) -> 0 | AA8: =IF(OR($N8<>"Yes",$O8=""),0,$Y8*MAX(0,7-$Z8)/12) -> 0 | AB8: =IF(OR($N8<>"Yes",$O8=""),0,$Y8*IF($Z8<=7,12,19-$Z8)/12) -> 0 | AC8: =IF(OR($J8="Yes",$L8="Yes",$N8="Yes"),"Yes","No") -> No | AD8: =MAX($Q8,$U8,$Y8) -> 0 | AE8: =$AD8+ROW()*0.000000001 -> 8e-09 | AF8: =IF($J8="Yes","A","")&IF($L8="Yes","B","")&IF($N8="Yes","C","")
B9: R0005 | C9: Project Manager (PEP13-EGI-UKG) | D9: EGI | E9: EGI | F9: AU | G9: Filled | H9: 1 | I9: 0.2442 | J9: No | L9: No | N9: No | P9: 0.2442 | Q9: =IF(AND($J9="Yes",$G9<>"Vendor day rates"),$I9-0.4*$P9,0) -> 0 | R9: =IFERROR(MATCH($K9,MonthList,0),0) -> 0 | S9: =IF(OR($J9<>"Yes",$K9=""),0,$Q9*MAX(0,7-$R9)/12) -> 0 | T9: =IF(OR($J9<>"Yes",$K9=""),0,$Q9*IF($R9<=7,12,19-$R9)/12) -> 0 | U9: =IF(AND($L9="Yes",$G9<>"Vendor day rates"),$I9-0.4*$P9,0) -> 0 | V9: =IFERROR(MATCH($M9,MonthList,0),0) -> 0 | W9: =IF(OR($L9<>"Yes",$M9=""),0,$U9*MAX(0,7-$V9)/12) -> 0 | X9: =IF(OR($L9<>"Yes",$M9=""),0,$U9*IF($V9<=7,12,19-$V9)/12) -> 0 | Y9: =IF(AND($N9="Yes",$G9<>"Vendor day rates"),$I9-0.4*$P9,0) -> 0 | Z9: =IFERROR(MATCH($O9,MonthList,0),0) -> 0 | AA9: =IF(OR($N9<>"Yes",$O9=""),0,$Y9*MAX(0,7-$Z9)/12) -> 0 | AB9: =IF(OR($N9<>"Yes",$O9=""),0,$Y9*IF($Z9<=7,12,19-$Z9)/12) -> 0 | AC9: =IF(OR($J9="Yes",$L9="Yes",$N9="Yes"),"Yes","No") -> No | AD9: =MAX($Q9,$U9,$Y9) -> 0 | AE9: =$AD9+ROW()*0.000000001 -> 9e-09 | AF9: =IF($J9="Yes","A","")&IF($L9="Yes","B","")&IF($N9="Yes","C","")
B10: R0006 | C10: Program Architect | D10: EGI | E10: EGI | F10: AU | G10: Filled | H10: 1 | I10: 0.3108 | J10: No | L10: No | N10: No | P10: 0.3108 | Q10: =IF(AND($J10="Yes",$G10<>"Vendor day rates"),$I10-0.4*$P10,0) -> 0 | R10: =IFERROR(MATCH($K10,MonthList,0),0) -> 0 | S10: =IF(OR($J10<>"Yes",$K10=""),0,$Q10*MAX(0,7-$R10)/12) -> 0 | T10: =IF(OR($J10<>"Yes",$K10=""),0,$Q10*IF($R10<=7,12,19-$R10)/12) -> 0 | U10: =IF(AND($L10="Yes",$G10<>"Vendor day rates"),$I10-0.4*$P10,0) -> 0 | V10: =IFERROR(MATCH($M10,MonthList,0),0) -> 0 | W10: =IF(OR($L10<>"Yes",$M10=""),0,$U10*MAX(0,7-$V10)/12) -> 0 | X10: =IF(OR($L10<>"Yes",$M10=""),0,$U10*IF($V10<=7,12,19-$V10)/12) -> 0 | Y10: =IF(AND($N10="Yes",$G10<>"Vendor day rates"),$I10-0.4*$P10,0) -> 0 | Z10: =IFERROR(MATCH($O10,MonthList,0),0) -> 0 | AA10: =IF(OR($N10<>"Yes",$O10=""),0,$Y10*MAX(0,7-$Z10)/12) -> 0 | AB10: =IF(OR($N10<>"Yes",$O10=""),0,$Y10*IF($Z10<=7,12,19-$Z10)/12) -> 0 | AC10: =IF(OR($J10="Yes",$L10="Yes",$N10="Yes"),"Yes","No") -> No | AD10: =MAX($Q10,$U10,$Y10) -> 0 | AE10: =$AD10+ROW()*0.000000001 -> 1e-08 | AF10: =IF($J10="Yes","A","")&IF($L10="Yes","B","")&IF($N10="Yes","C","")
B11: R0007 | C11: TDD Strategic Delivery | D11: EGI | E11: EGI | F11: AU | G11: Filled | H11: 1 | I11: 0.2775 | J11: No | L11: No | N11: No | P11: 0.2775 | Q11: =IF(AND($J11="Yes",$G11<>"Vendor day rates"),$I11-0.4*$P11,0) -> 0 | R11: =IFERROR(MATCH($K11,MonthList,0),0) -> 0 | S11: =IF(OR($J11<>"Yes",$K11=""),0,$Q11*MAX(0,7-$R11)/12) -> 0 | T11: =IF(OR($J11<>"Yes",$K11=""),0,$Q11*IF($R11<=7,12,19-$R11)/12) -> 0 | U11: =IF(AND($L11="Yes",$G11<>"Vendor day rates"),$I11-0.4*$P11,0) -> 0 | V11: =IFERROR(MATCH($M11,MonthList,0),0) -> 0 | W11: =IF(OR($L11<>"Yes",$M11=""),0,$U11*MAX(0,7-$V11)/12) -> 0 | X11: =IF(OR($L11<>"Yes",$M11=""),0,$U11*IF($V11<=7,12,19-$V11)/12) -> 0 | Y11: =IF(AND($N11="Yes",$G11<>"Vendor day rates"),$I11-0.4*$P11,0) -> 0 | Z11: =IFERROR(MATCH($O11,MonthList,0),0) -> 0 | AA11: =IF(OR($N11<>"Yes",$O11=""),0,$Y11*MAX(0,7-$Z11)/12) -> 0 | AB11: =IF(OR($N11<>"Yes",$O11=""),0,$Y11*IF($Z11<=7,12,19-$Z11)/12) -> 0 | AC11: =IF(OR($J11="Yes",$L11="Yes",$N11="Yes"),"Yes","No") -> No | AD11: =MAX($Q11,$U11,$Y11) -> 0 | AE11: =$AD11+ROW()*0.000000001 -> 1.1e-08 | AF11: =IF($J11="Yes","A","")&IF($L11="Yes","B","")&IF($N11="Yes","C","")
B12: R0008 | C12: Strategic Delivery Consultant | D12: EGI | E12: EGI | F12: AU | G12: Filled | H12: 1 | I12: 0.3013 | J12: No | L12: No | N12: No | P12: 0.3013 | Q12: =IF(AND($J12="Yes",$G12<>"Vendor day rates"),$I12-0.4*$P12,0) -> 0 | R12: =IFERROR(MATCH($K12,MonthList,0),0) -> 0 | S12: =IF(OR($J12<>"Yes",$K12=""),0,$Q12*MAX(0,7-$R12)/12) -> 0 | T12: =IF(OR($J12<>"Yes",$K12=""),0,$Q12*IF($R12<=7,12,19-$R12)/12) -> 0 | U12: =IF(AND($L12="Yes",$G12<>"Vendor day rates"),$I12-0.4*$P12,0) -> 0 | V12: =IFERROR(MATCH($M12,MonthList,0),0) -> 0 | W12: =IF(OR($L12<>"Yes",$M12=""),0,$U12*MAX(0,7-$V12)/12) -> 0 | X12: =IF(OR($L12<>"Yes",$M12=""),0,$U12*IF($V12<=7,12,19-$V12)/12) -> 0 | Y12: =IF(AND($N12="Yes",$G12<>"Vendor day rates"),$I12-0.4*$P12,0) -> 0 | Z12: =IFERROR(MATCH($O12,MonthList,0),0) -> 0 | AA12: =IF(OR($N12<>"Yes",$O12=""),0,$Y12*MAX(0,7-$Z12)/12) -> 0 | AB12: =IF(OR($N12<>"Yes",$O12=""),0,$Y12*IF($Z12<=7,12,19-$Z12)/12) -> 0 | AC12: =IF(OR($J12="Yes",$L12="Yes",$N12="Yes"),"Yes","No") -> No | AD12: =MAX($Q12,$U12,$Y12) -> 0 | AE12: =$AD12+ROW()*0.000000001 -> 1.2e-08 | AF12: =IF($J12="Yes","A","")&IF($L12="Yes","B","")&IF($N12="Yes","C","")
B13: R0009 | C13: Program Manager (PEP13-EGI-UKG) | D13: EGI | E13: EGI | F13: AU | G13: Filled | H13: 1 | I13: 0.3432 | J13: No | L13: No | N13: No | P13: 0.3432 | Q13: =IF(AND($J13="Yes",$G13<>"Vendor day rates"),$I13-0.4*$P13,0) -> 0 | R13: =IFERROR(MATCH($K13,MonthList,0),0) -> 0 | S13: =IF(OR($J13<>"Yes",$K13=""),0,$Q13*MAX(0,7-$R13)/12) -> 0 | T13: =IF(OR($J13<>"Yes",$K13=""),0,$Q13*IF($R13<=7,12,19-$R13)/12) -> 0 | U13: =IF(AND($L13="Yes",$G13<>"Vendor day rates"),$I13-0.4*$P13,0) -> 0 | V13: =IFERROR(MATCH($M13,MonthList,0),0) -> 0 | W13: =IF(OR($L13<>"Yes",$M13=""),0,$U13*MAX(0,7-$V13)/12) -> 0 | X13: =IF(OR($L13<>"Yes",$M13=""),0,$U13*IF($V13<=7,12,19-$V13)/12) -> 0 | Y13: =IF(AND($N13="Yes",$G13<>"Vendor day rates"),$I13-0.4*$P13,0) -> 0 | Z13: =IFERROR(MATCH($O13,MonthList,0),0) -> 0 | AA13: =IF(OR($N13<>"Yes",$O13=""),0,$Y13*MAX(0,7-$Z13)/12) -> 0 | AB13: =IF(OR($N13<>"Yes",$O13=""),0,$Y13*IF($Z13<=7,12,19-$Z13)/12) -> 0 | AC13: =IF(OR($J13="Yes",$L13="Yes",$N13="Yes"),"Yes","No") -> No | AD13: =MAX($Q13,$U13,$Y13) -> 0 | AE13: =$AD13+ROW()*0.000000001 -> 1.3e-08 | AF13: =IF($J13="Yes","A","")&IF($L13="Yes","B","")&IF($N13="Yes","C","")
B14: R0010 | C14: Program Manager Tech & P&C | D14: EGI | E14: EGI | F14: AU | G14: Filled | H14: 1 | I14: 0.2664 | J14: No | L14: No | N14: No | P14: 0.2664 | Q14: =IF(AND($J14="Yes",$G14<>"Vendor day rates"),$I14-0.4*$P14,0) -> 0 | R14: =IFERROR(MATCH($K14,MonthList,0),0) -> 0 | S14: =IF(OR($J14<>"Yes",$K14=""),0,$Q14*MAX(0,7-$R14)/12) -> 0 | T14: =IF(OR($J14<>"Yes",$K14=""),0,$Q14*IF($R14<=7,12,19-$R14)/12) -> 0 | U14: =IF(AND($L14="Yes",$G14<>"Vendor day rates"),$I14-0.4*$P14,0) -> 0 | V14: =IFERROR(MATCH($M14,MonthList,0),0) -> 0 | W14: =IF(OR($L14<>"Yes",$M14=""),0,$U14*MAX(0,7-$V14)/12) -> 0 | X14: =IF(OR($L14<>"Yes",$M14=""),0,$U14*IF($V14<=7,12,19-$V14)/12) -> 0 | Y14: =IF(AND($N14="Yes",$G14<>"Vendor day rates"),$I14-0.4*$P14,0) -> 0 | Z14: =IFERROR(MATCH($O14,MonthList,0),0) -> 0 | AA14: =IF(OR($N14<>"Yes",$O14=""),0,$Y14*MAX(0,7-$Z14)/12) -> 0 | AB14: =IF(OR($N14<>"Yes",$O14=""),0,$Y14*IF($Z14<=7,12,19-$Z14)/12) -> 0 | AC14: =IF(OR($J14="Yes",$L14="Yes",$N14="Yes"),"Yes","No") -> No | AD14: =MAX($Q14,$U14,$Y14) -> 0 | AE14: =$AD14+ROW()*0.000000001 -> 1.4e-08 | AF14: =IF($J14="Yes","A","")&IF($L14="Yes","B","")&IF($N14="Yes","C","")
B15: R0011 | C15: Project Manager Retail | D15: EGI | E15: EGI | F15: AU | G15: Filled | H15: 1 | I15: 0.4884 | J15: No | L15: No | N15: No | P15: 0.4884 | Q15: =IF(AND($J15="Yes",$G15<>"Vendor day rates"),$I15-0.4*$P15,0) -> 0 | R15: =IFERROR(MATCH($K15,MonthList,0),0) -> 0 | S15: =IF(OR($J15<>"Yes",$K15=""),0,$Q15*MAX(0,7-$R15)/12) -> 0 | T15: =IF(OR($J15<>"Yes",$K15=""),0,$Q15*IF($R15<=7,12,19-$R15)/12) -> 0 | U15: =IF(AND($L15="Yes",$G15<>"Vendor day rates"),$I15-0.4*$P15,0) -> 0 | V15: =IFERROR(MATCH($M15,MonthList,0),0) -> 0 | W15: =IF(OR($L15<>"Yes",$M15=""),0,$U15*MAX(0,7-$V15)/12) -> 0 | X15: =IF(OR($L15<>"Yes",$M15=""),0,$U15*IF($V15<=7,12,19-$V15)/12) -> 0 | Y15: =IF(AND($N15="Yes",$G15<>"Vendor day rates"),$I15-0.4*$P15,0) -> 0 | Z15: =IFERROR(MATCH($O15,MonthList,0),0) -> 0 | AA15: =IF(OR($N15<>"Yes",$O15=""),0,$Y15*MAX(0,7-$Z15)/12) -> 0 | AB15: =IF(OR($N15<>"Yes",$O15=""),0,$Y15*IF($Z15<=7,12,19-$Z15)/12) -> 0 | AC15: =IF(OR($J15="Yes",$L15="Yes",$N15="Yes"),"Yes","No") -> No | AD15: =MAX($Q15,$U15,$Y15) -> 0 | AE15: =$AD15+ROW()*0.000000001 -> 1.5e-08 | AF15: =IF($J15="Yes","A","")&IF($L15="Yes","B","")&IF($N15="Yes","C","")
B16: R0012 | C16: Strategic Delivery Consultant | D16: EGI | E16: EGI | F16: AU | G16: Filled | H16: 1 | I16: 0.2997 | J16: No | L16: No | N16: No | P16: 0.2997 | Q16: =IF(AND($J16="Yes",$G16<>"Vendor day rates"),$I16-0.4*$P16,0) -> 0 | R16: =IFERROR(MATCH($K16,MonthList,0),0) -> 0 | S16: =IF(OR($J16<>"Yes",$K16=""),0,$Q16*MAX(0,7-$R16)/12) -> 0 | T16: =IF(OR($J16<>"Yes",$K16=""),0,$Q16*IF($R16<=7,12,19-$R16)/12) -> 0 | U16: =IF(AND($L16="Yes",$G16<>"Vendor day rates"),$I16-0.4*$P16,0) -> 0 | V16: =IFERROR(MATCH($M16,MonthList,0),0) -> 0 | W16: =IF(OR($L16<>"Yes",$M16=""),0,$U16*MAX(0,7-$V16)/12) -> 0 | X16: =IF(OR($L16<>"Yes",$M16=""),0,$U16*IF($V16<=7,12,19-$V16)/12) -> 0 | Y16: =IF(AND($N16="Yes",$G16<>"Vendor day rates"),$I16-0.4*$P16,0) -> 0 | Z16: =IFERROR(MATCH($O16,MonthList,0),0) -> 0 | AA16: =IF(OR($N16<>"Yes",$O16=""),0,$Y16*MAX(0,7-$Z16)/12) -> 0 | AB16: =IF(OR($N16<>"Yes",$O16=""),0,$Y16*IF($Z16<=7,12,19-$Z16)/12) -> 0 | AC16: =IF(OR($J16="Yes",$L16="Yes",$N16="Yes"),"Yes","No") -> No | AD16: =MAX($Q16,$U16,$Y16) -> 0 | AE16: =$AD16+ROW()*0.000000001 -> 1.6e-08 | AF16: =IF($J16="Yes","A","")&IF($L16="Yes","B","")&IF($N16="Yes","C","")
B17: R0013 | C17: Strategic Delivery Consultant | D17: EGI | E17: EGI | F17: AU | G17: Filled | H17: 1 | I17: 0.2304 | J17: No | L17: No | N17: No | P17: 0.2304 | Q17: =IF(AND($J17="Yes",$G17<>"Vendor day rates"),$I17-0.4*$P17,0) -> 0 | R17: =IFERROR(MATCH($K17,MonthList,0),0) -> 0 | S17: =IF(OR($J17<>"Yes",$K17=""),0,$Q17*MAX(0,7-$R17)/12) -> 0 | T17: =IF(OR($J17<>"Yes",$K17=""),0,$Q17*IF($R17<=7,12,19-$R17)/12) -> 0 | U17: =IF(AND($L17="Yes",$G17<>"Vendor day rates"),$I17-0.4*$P17,0) -> 0 | V17: =IFERROR(MATCH($M17,MonthList,0),0) -> 0 | W17: =IF(OR($L17<>"Yes",$M17=""),0,$U17*MAX(0,7-$V17)/12) -> 0 | X17: =IF(OR($L17<>"Yes",$M17=""),0,$U17*IF($V17<=7,12,19-$V17)/12) -> 0 | Y17: =IF(AND($N17="Yes",$G17<>"Vendor day rates"),$I17-0.4*$P17,0) -> 0 | Z17: =IFERROR(MATCH($O17,MonthList,0),0) -> 0 | AA17: =IF(OR($N17<>"Yes",$O17=""),0,$Y17*MAX(0,7-$Z17)/12) -> 0 | AB17: =IF(OR($N17<>"Yes",$O17=""),0,$Y17*IF($Z17<=7,12,19-$Z17)/12) -> 0 | AC17: =IF(OR($J17="Yes",$L17="Yes",$N17="Yes"),"Yes","No") -> No | AD17: =MAX($Q17,$U17,$Y17) -> 0 | AE17: =$AD17+ROW()*0.000000001 -> 1.7e-08 | AF17: =IF($J17="Yes","A","")&IF($L17="Yes","B","")&IF($N17="Yes","C","")
B18: R0014 | C18: Project Manager Deployment | E18: EGI | F18: AU | G18: Filled | H18: 1 | I18: 0.2664 | J18: No | L18: No | N18: No | P18: 0.2664 | Q18: =IF(AND($J18="Yes",$G18<>"Vendor day rates"),$I18-0.4*$P18,0) -> 0 | R18: =IFERROR(MATCH($K18,MonthList,0),0) -> 0 | S18: =IF(OR($J18<>"Yes",$K18=""),0,$Q18*MAX(0,7-$R18)/12) -> 0 | T18: =IF(OR($J18<>"Yes",$K18=""),0,$Q18*IF($R18<=7,12,19-$R18)/12) -> 0 | U18: =IF(AND($L18="Yes",$G18<>"Vendor day rates"),$I18-0.4*$P18,0) -> 0 | V18: =IFERROR(MATCH($M18,MonthList,0),0) -> 0 | W18: =IF(OR($L18<>"Yes",$M18=""),0,$U18*MAX(0,7-$V18)/12) -> 0 | X18: =IF(OR($L18<>"Yes",$M18=""),0,$U18*IF($V18<=7,12,19-$V18)/12) -> 0 | Y18: =IF(AND($N18="Yes",$G18<>"Vendor day rates"),$I18-0.4*$P18,0) -> 0 | Z18: =IFERROR(MATCH($O18,MonthList,0),0) -> 0 | AA18: =IF(OR($N18<>"Yes",$O18=""),0,$Y18*MAX(0,7-$Z18)/12) -> 0 | AB18: =IF(OR($N18<>"Yes",$O18=""),0,$Y18*IF($Z18<=7,12,19-$Z18)/12) -> 0 | AC18: =IF(OR($J18="Yes",$L18="Yes",$N18="Yes"),"Yes","No") -> No | AD18: =MAX($Q18,$U18,$Y18) -> 0 | AE18: =$AD18+ROW()*0.000000001 -> 1.8e-08 | AF18: =IF($J18="Yes","A","")&IF($L18="Yes","B","")&IF($N18="Yes","C","")
B19: R0015 | C19: Reporting Analyst | D19: Infrastructure | E19: Data & Insights | F19: AU | G19: Filled | H19: 1 | I19: 0.1976 | J19: No | L19: No | N19: No | P19: 0.1976 | Q19: =IF(AND($J19="Yes",$G19<>"Vendor day rates"),$I19-0.4*$P19,0) -> 0 | R19: =IFERROR(MATCH($K19,MonthList,0),0) -> 0 | S19: =IF(OR($J19<>"Yes",$K19=""),0,$Q19*MAX(0,7-$R19)/12) -> 0 | T19: =IF(OR($J19<>"Yes",$K19=""),0,$Q19*IF($R19<=7,12,19-$R19)/12) -> 0 | U19: =IF(AND($L19="Yes",$G19<>"Vendor day rates"),$I19-0.4*$P19,0) -> 0 | V19: =IFERROR(MATCH($M19,MonthList,0),0) -> 0 | W19: =IF(OR($L19<>"Yes",$M19=""),0,$U19*MAX(0,7-$V19)/12) -> 0 | X19: =IF(OR($L19<>"Yes",$M19=""),0,$U19*IF($V19<=7,12,19-$V19)/12) -> 0 | Y19: =IF(AND($N19="Yes",$G19<>"Vendor day rates"),$I19-0.4*$P19,0) -> 0 | Z19: =IFERROR(MATCH($O19,MonthList,0),0) -> 0 | AA19: =IF(OR($N19<>"Yes",$O19=""),0,$Y19*MAX(0,7-$Z19)/12) -> 0 | AB19: =IF(OR($N19<>"Yes",$O19=""),0,$Y19*IF($Z19<=7,12,19-$Z19)/12) -> 0 | AC19: =IF(OR($J19="Yes",$L19="Yes",$N19="Yes"),"Yes","No") -> No | AD19: =MAX($Q19,$U19,$Y19) -> 0 | AE19: =$AD19+ROW()*0.000000001 -> 1.9e-08 | AF19: =IF($J19="Yes","A","")&IF($L19="Yes","B","")&IF($N19="Yes","C","")
B20: R0016 | C20: QA / Tester / Mid | D20: Ampol Customer | E20: Ampol Loyalty & Martech | F20: AU | G20: Vendor day rates | H20: 1 | I20: 0.0733 | J20: No | L20: No | N20: No | P20: 0.0733 | Q20: =IF(AND($J20="Yes",$G20<>"Vendor day rates"),$I20-0.4*$P20,0) -> 0 | R20: =IFERROR(MATCH($K20,MonthList,0),0) -> 0 | S20: =IF(OR($J20<>"Yes",$K20=""),0,$Q20*MAX(0,7-$R20)/12) -> 0 | T20: =IF(OR($J20<>"Yes",$K20=""),0,$Q20*IF($R20<=7,12,19-$R20)/12) -> 0 | U20: =IF(AND($L20="Yes",$G20<>"Vendor day rates"),$I20-0.4*$P20,0) -> 0 | V20: =IFERROR(MATCH($M20,MonthList,0),0) -> 0 | W20: =IF(OR($L20<>"Yes",$M20=""),0,$U20*MAX(0,7-$V20)/12) -> 0 | X20: =IF(OR($L20<>"Yes",$M20=""),0,$U20*IF($V20<=7,12,19-$V20)/12) -> 0 | Y20: =IF(AND($N20="Yes",$G20<>"Vendor day rates"),$I20-0.4*$P20,0) -> 0 | Z20: =IFERROR(MATCH($O20,MonthList,0),0) -> 0 | AA20: =IF(OR($N20<>"Yes",$O20=""),0,$Y20*MAX(0,7-$Z20)/12) -> 0 | AB20: =IF(OR($N20<>"Yes",$O20=""),0,$Y20*IF($Z20<=7,12,19-$Z20)/12) -> 0 | AC20: =IF(OR($J20="Yes",$L20="Yes",$N20="Yes"),"Yes","No") -> No | AD20: =MAX($Q20,$U20,$Y20) -> 0 | AE20: =$AD20+ROW()*0.000000001 -> 2e-08 | AF20: =IF($J20="Yes","A","")&IF($L20="Yes","B","")&IF($N20="Yes","C","")
B21: R0017 | C21: Systems Analyst / Mid | D21: Ampol Customer | E21: Ampol Loyalty & Martech | F21: AU | G21: Vendor day rates | H21: 1 | I21: 0.0733 | J21: No | L21: No | N21: No | P21: 0.0733 | Q21: =IF(AND($J21="Yes",$G21<>"Vendor day rates"),$I21-0.4*$P21,0) -> 0 | R21: =IFERROR(MATCH($K21,MonthList,0),0) -> 0 | S21: =IF(OR($J21<>"Yes",$K21=""),0,$Q21*MAX(0,7-$R21)/12) -> 0 | T21: =IF(OR($J21<>"Yes",$K21=""),0,$Q21*IF($R21<=7,12,19-$R21)/12) -> 0 | U21: =IF(AND($L21="Yes",$G21<>"Vendor day rates"),$I21-0.4*$P21,0) -> 0 | V21: =IFERROR(MATCH($M21,MonthList,0),0) -> 0 | W21: =IF(OR($L21<>"Yes",$M21=""),0,$U21*MAX(0,7-$V21)/12) -> 0 | X21: =IF(OR($L21<>"Yes",$M21=""),0,$U21*IF($V21<=7,12,19-$V21)/12) -> 0 | Y21: =IF(AND($N21="Yes",$G21<>"Vendor day rates"),$I21-0.4*$P21,0) -> 0 | Z21: =IFERROR(MATCH($O21,MonthList,0),0) -> 0 | AA21: =IF(OR($N21<>"Yes",$O21=""),0,$Y21*MAX(0,7-$Z21)/12) -> 0 | AB21: =IF(OR($N21<>"Yes",$O21=""),0,$Y21*IF($Z21<=7,12,19-$Z21)/12) -> 0 | AC21: =IF(OR($J21="Yes",$L21="Yes",$N21="Yes"),"Yes","No") -> No | AD21: =MAX($Q21,$U21,$Y21) -> 0 | AE21: =$AD21+ROW()*0.000000001 -> 2.1e-08 | AF21: =IF($J21="Yes","A","")&IF($L21="Yes","B","")&IF($N21="Yes","C","")
B22: R0018 | C22: Data Migration Lead | D22: EGI Integration | E22: EGI TDD | F22: AU | G22: Filled | H22: 1 | I22: 0.2997 | J22: No | L22: No | N22: No | P22: 0.2997 | Q22: =IF(AND($J22="Yes",$G22<>"Vendor day rates"),$I22-0.4*$P22,0) -> 0 | R22: =IFERROR(MATCH($K22,MonthList,0),0) -> 0 | S22: =IF(OR($J22<>"Yes",$K22=""),0,$Q22*MAX(0,7-$R22)/12) -> 0 | T22: =IF(OR($J22<>"Yes",$K22=""),0,$Q22*IF($R22<=7,12,19-$R22)/12) -> 0 | U22: =IF(AND($L22="Yes",$G22<>"Vendor day rates"),$I22-0.4*$P22,0) -> 0 | V22: =IFERROR(MATCH($M22,MonthList,0),0) -> 0 | W22: =IF(OR($L22<>"Yes",$M22=""),0,$U22*MAX(0,7-$V22)/12) -> 0 | X22: =IF(OR($L22<>"Yes",$M22=""),0,$U22*IF($V22<=7,12,19-$V22)/12) -> 0 | Y22: =IF(AND($N22="Yes",$G22<>"Vendor day rates"),$I22-0.4*$P22,0) -> 0 | Z22: =IFERROR(MATCH($O22,MonthList,0),0) -> 0 | AA22: =IF(OR($N22<>"Yes",$O22=""),0,$Y22*MAX(0,7-$Z22)/12) -> 0 | AB22: =IF(OR($N22<>"Yes",$O22=""),0,$Y22*IF($Z22<=7,12,19-$Z22)/12) -> 0 | AC22: =IF(OR($J22="Yes",$L22="Yes",$N22="Yes"),"Yes","No") -> No | AD22: =MAX($Q22,$U22,$Y22) -> 0 | AE22: =$AD22+ROW()*0.000000001 -> 2.2e-08 | AF22: =IF($J22="Yes","A","")&IF($L22="Yes","B","")&IF($N22="Yes","C","")
B23: R0019 | C23: .NET Back End Developer / Mid | D23: Ampol Customer | E23: Digital Operations | F23: AU | G23: Vendor day rates | H23: 1 | I23: 0.0733 | J23: No | L23: No | N23: No | P23: 0.0733 | Q23: =IF(AND($J23="Yes",$G23<>"Vendor day rates"),$I23-0.4*$P23,0) -> 0 | R23: =IFERROR(MATCH($K23,MonthList,0),0) -> 0 | S23: =IF(OR($J23<>"Yes",$K23=""),0,$Q23*MAX(0,7-$R23)/12) -> 0 | T23: =IF(OR($J23<>"Yes",$K23=""),0,$Q23*IF($R23<=7,12,19-$R23)/12) -> 0 | U23: =IF(AND($L23="Yes",$G23<>"Vendor day rates"),$I23-0.4*$P23,0) -> 0 | V23: =IFERROR(MATCH($M23,MonthList,0),0) -> 0 | W23: =IF(OR($L23<>"Yes",$M23=""),0,$U23*MAX(0,7-$V23)/12) -> 0 | X23: =IF(OR($L23<>"Yes",$M23=""),0,$U23*IF($V23<=7,12,19-$V23)/12) -> 0 | Y23: =IF(AND($N23="Yes",$G23<>"Vendor day rates"),$I23-0.4*$P23,0) -> 0 | Z23: =IFERROR(MATCH($O23,MonthList,0),0) -> 0 | AA23: =IF(OR($N23<>"Yes",$O23=""),0,$Y23*MAX(0,7-$Z23)/12) -> 0 | AB23: =IF(OR($N23<>"Yes",$O23=""),0,$Y23*IF($Z23<=7,12,19-$Z23)/12) -> 0 | AC23: =IF(OR($J23="Yes",$L23="Yes",$N23="Yes"),"Yes","No") -> No | AD23: =MAX($Q23,$U23,$Y23) -> 0 | AE23: =$AD23+ROW()*0.000000001 -> 2.3e-08 | AF23: =IF($J23="Yes","A","")&IF($L23="Yes","B","")&IF($N23="Yes","C","")
B24: R0020 | C24: .NET Back End Developer / Mid | D24: Ampol Customer | E24: Digital Operations | F24: AU | G24: Vendor day rates | H24: 1 | I24: 0.0733 | J24: No | L24: No | N24: No | P24: 0.0733 | Q24: =IF(AND($J24="Yes",$G24<>"Vendor day rates"),$I24-0.4*$P24,0) -> 0 | R24: =IFERROR(MATCH($K24,MonthList,0),0) -> 0 | S24: =IF(OR($J24<>"Yes",$K24=""),0,$Q24*MAX(0,7-$R24)/12) -> 0 | T24: =IF(OR($J24<>"Yes",$K24=""),0,$Q24*IF($R24<=7,12,19-$R24)/12) -> 0 | U24: =IF(AND($L24="Yes",$G24<>"Vendor day rates"),$I24-0.4*$P24,0) -> 0 | V24: =IFERROR(MATCH($M24,MonthList,0),0) -> 0 | W24: =IF(OR($L24<>"Yes",$M24=""),0,$U24*MAX(0,7-$V24)/12) -> 0 | X24: =IF(OR($L24<>"Yes",$M24=""),0,$U24*IF($V24<=7,12,19-$V24)/12) -> 0 | Y24: =IF(AND($N24="Yes",$G24<>"Vendor day rates"),$I24-0.4*$P24,0) -> 0 | Z24: =IFERROR(MATCH($O24,MonthList,0),0) -> 0 | AA24: =IF(OR($N24<>"Yes",$O24=""),0,$Y24*MAX(0,7-$Z24)/12) -> 0 | AB24: =IF(OR($N24<>"Yes",$O24=""),0,$Y24*IF($Z24<=7,12,19-$Z24)/12) -> 0 | AC24: =IF(OR($J24="Yes",$L24="Yes",$N24="Yes"),"Yes","No") -> No | AD24: =MAX($Q24,$U24,$Y24) -> 0 | AE24: =$AD24+ROW()*0.000000001 -> 2.4e-08 | AF24: =IF($J24="Yes","A","")&IF($L24="Yes","B","")&IF($N24="Yes","C","")
B25: R0021 | C25: .NET Back End Developer / Mid | D25: Ampol Customer | E25: Digital Operations | F25: AU | G25: Vendor day rates | H25: 1 | I25: 0.0733 | J25: No | L25: No | N25: No | P25: 0.0733 | Q25: =IF(AND($J25="Yes",$G25<>"Vendor day rates"),$I25-0.4*$P25,0) -> 0 | R25: =IFERROR(MATCH($K25,MonthList,0),0) -> 0 | S25: =IF(OR($J25<>"Yes",$K25=""),0,$Q25*MAX(0,7-$R25)/12) -> 0 | T25: =IF(OR($J25<>"Yes",$K25=""),0,$Q25*IF($R25<=7,12,19-$R25)/12) -> 0 | U25: =IF(AND($L25="Yes",$G25<>"Vendor day rates"),$I25-0.4*$P25,0) -> 0 | V25: =IFERROR(MATCH($M25,MonthList,0),0) -> 0 | W25: =IF(OR($L25<>"Yes",$M25=""),0,$U25*MAX(0,7-$V25)/12) -> 0 | X25: =IF(OR($L25<>"Yes",$M25=""),0,$U25*IF($V25<=7,12,19-$V25)/12) -> 0 | Y25: =IF(AND($N25="Yes",$G25<>"Vendor day rates"),$I25-0.4*$P25,0) -> 0 | Z25: =IFERROR(MATCH($O25,MonthList,0),0) -> 0 | AA25: =IF(OR($N25<>"Yes",$O25=""),0,$Y25*MAX(0,7-$Z25)/12) -> 0 | AB25: =IF(OR($N25<>"Yes",$O25=""),0,$Y25*IF($Z25<=7,12,19-$Z25)/12) -> 0 | AC25: =IF(OR($J25="Yes",$L25="Yes",$N25="Yes"),"Yes","No") -> No | AD25: =MAX($Q25,$U25,$Y25) -> 0 | AE25: =$AD25+ROW()*0.000000001 -> 2.5e-08 | AF25: =IF($J25="Yes","A","")&IF($L25="Yes","B","")&IF($N25="Yes","C","")
B26: R0022 | C26: QA / Tester / Mid | D26: Ampol Customer | E26: Digital Operations | F26: AU | G26: Vendor day rates | H26: 1 | I26: 0.0733 | J26: No | L26: No | N26: No | P26: 0.0733 | Q26: =IF(AND($J26="Yes",$G26<>"Vendor day rates"),$I26-0.4*$P26,0) -> 0 | R26: =IFERROR(MATCH($K26,MonthList,0),0) -> 0 | S26: =IF(OR($J26<>"Yes",$K26=""),0,$Q26*MAX(0,7-$R26)/12) -> 0 | T26: =IF(OR($J26<>"Yes",$K26=""),0,$Q26*IF($R26<=7,12,19-$R26)/12) -> 0 | U26: =IF(AND($L26="Yes",$G26<>"Vendor day rates"),$I26-0.4*$P26,0) -> 0 | V26: =IFERROR(MATCH($M26,MonthList,0),0) -> 0 | W26: =IF(OR($L26<>"Yes",$M26=""),0,$U26*MAX(0,7-$V26)/12) -> 0 | X26: =IF(OR($L26<>"Yes",$M26=""),0,$U26*IF($V26<=7,12,19-$V26)/12) -> 0 | Y26: =IF(AND($N26="Yes",$G26<>"Vendor day rates"),$I26-0.4*$P26,0) -> 0 | Z26: =IFERROR(MATCH($O26,MonthList,0),0) -> 0 | AA26: =IF(OR($N26<>"Yes",$O26=""),0,$Y26*MAX(0,7-$Z26)/12) -> 0 | AB26: =IF(OR($N26<>"Yes",$O26=""),0,$Y26*IF($Z26<=7,12,19-$Z26)/12) -> 0 | AC26: =IF(OR($J26="Yes",$L26="Yes",$N26="Yes"),"Yes","No") -> No | AD26: =MAX($Q26,$U26,$Y26) -> 0 | AE26: =$AD26+ROW()*0.000000001 -> 2.6e-08 | AF26: =IF($J26="Yes","A","")&IF($L26="Yes","B","")&IF($N26="Yes","C","")
B27: R0023 | C27: Integration Architect (C) - Boomi | D27: EGI | E27: EGI TDD | F27: AU | G27: Filled | H27: 1 | I27: 0.3481 | J27: No | L27: No | N27: No | P27: 0.3481 | Q27: =IF(AND($J27="Yes",$G27<>"Vendor day rates"),$I27-0.4*$P27,0) -> 0 | R27: =IFERROR(MATCH($K27,MonthList,0),0) -> 0 | S27: =IF(OR($J27<>"Yes",$K27=""),0,$Q27*MAX(0,7-$R27)/12) -> 0 | T27: =IF(OR($J27<>"Yes",$K27=""),0,$Q27*IF($R27<=7,12,19-$R27)/12) -> 0 | U27: =IF(AND($L27="Yes",$G27<>"Vendor day rates"),$I27-0.4*$P27,0) -> 0 | V27: =IFERROR(MATCH($M27,MonthList,0),0) -> 0 | W27: =IF(OR($L27<>"Yes",$M27=""),0,$U27*MAX(0,7-$V27)/12) -> 0 | X27: =IF(OR($L27<>"Yes",$M27=""),0,$U27*IF($V27<=7,12,19-$V27)/12) -> 0 | Y27: =IF(AND($N27="Yes",$G27<>"Vendor day rates"),$I27-0.4*$P27,0) -> 0 | Z27: =IFERROR(MATCH($O27,MonthList,0),0) -> 0 | AA27: =IF(OR($N27<>"Yes",$O27=""),0,$Y27*MAX(0,7-$Z27)/12) -> 0 | AB27: =IF(OR($N27<>"Yes",$O27=""),0,$Y27*IF($Z27<=7,12,19-$Z27)/12) -> 0 | AC27: =IF(OR($J27="Yes",$L27="Yes",$N27="Yes"),"Yes","No") -> No | AD27: =MAX($Q27,$U27,$Y27) -> 0 | AE27: =$AD27+ROW()*0.000000001 -> 2.7e-08 | AF27: =IF($J27="Yes","A","")&IF($L27="Yes","B","")&IF($N27="Yes","C","")
B28: R0024 | C28: Integration Architect (C) | D28: EGI | E28: EGI TDD | F28: NZ | G28: Filled | H28: 1 | I28: 0.2664 | J28: No | L28: No | N28: No | P28: 0.2664 | Q28: =IF(AND($J28="Yes",$G28<>"Vendor day rates"),$I28-0.4*$P28,0) -> 0 | R28: =IFERROR(MATCH($K28,MonthList,0),0) -> 0 | S28: =IF(OR($J28<>"Yes",$K28=""),0,$Q28*MAX(0,7-$R28)/12) -> 0 | T28: =IF(OR($J28<>"Yes",$K28=""),0,$Q28*IF($R28<=7,12,19-$R28)/12) -> 0 | U28: =IF(AND($L28="Yes",$G28<>"Vendor day rates"),$I28-0.4*$P28,0) -> 0 | V28: =IFERROR(MATCH($M28,MonthList,0),0) -> 0 | W28: =IF(OR($L28<>"Yes",$M28=""),0,$U28*MAX(0,7-$V28)/12) -> 0 | X28: =IF(OR($L28<>"Yes",$M28=""),0,$U28*IF($V28<=7,12,19-$V28)/12) -> 0 | Y28: =IF(AND($N28="Yes",$G28<>"Vendor day rates"),$I28-0.4*$P28,0) -> 0 | Z28: =IFERROR(MATCH($O28,MonthList,0),0) -> 0 | AA28: =IF(OR($N28<>"Yes",$O28=""),0,$Y28*MAX(0,7-$Z28)/12) -> 0 | AB28: =IF(OR($N28<>"Yes",$O28=""),0,$Y28*IF($Z28<=7,12,19-$Z28)/12) -> 0 | AC28: =IF(OR($J28="Yes",$L28="Yes",$N28="Yes"),"Yes","No") -> No | AD28: =MAX($Q28,$U28,$Y28) -> 0 | AE28: =$AD28+ROW()*0.000000001 -> 2.8e-08 | AF28: =IF($J28="Yes","A","")&IF($L28="Yes","B","")&IF($N28="Yes","C","")
B29: R0025 | C29: Engineer - Mobile | D29: Ampol Customer | E29: Ampol App | F29: AU | G29: Filled | H29: 1 | I29: 0.1909 | J29: No | L29: No | N29: No | P29: 0.1909 | Q29: =IF(AND($J29="Yes",$G29<>"Vendor day rates"),$I29-0.4*$P29,0) -> 0 | R29: =IFERROR(MATCH($K29,MonthList,0),0) -> 0 | S29: =IF(OR($J29<>"Yes",$K29=""),0,$Q29*MAX(0,7-$R29)/12) -> 0 | T29: =IF(OR($J29<>"Yes",$K29=""),0,$Q29*IF($R29<=7,12,19-$R29)/12) -> 0 | U29: =IF(AND($L29="Yes",$G29<>"Vendor day rates"),$I29-0.4*$P29,0) -> 0 | V29: =IFERROR(MATCH($M29,MonthList,0),0) -> 0 | W29: =IF(OR($L29<>"Yes",$M29=""),0,$U29*MAX(0,7-$V29)/12) -> 0 | X29: =IF(OR($L29<>"Yes",$M29=""),0,$U29*IF($V29<=7,12,19-$V29)/12) -> 0 | Y29: =IF(AND($N29="Yes",$G29<>"Vendor day rates"),$I29-0.4*$P29,0) -> 0 | Z29: =IFERROR(MATCH($O29,MonthList,0),0) -> 0 | AA29: =IF(OR($N29<>"Yes",$O29=""),0,$Y29*MAX(0,7-$Z29)/12) -> 0 | AB29: =IF(OR($N29<>"Yes",$O29=""),0,$Y29*IF($Z29<=7,12,19-$Z29)/12) -> 0 | AC29: =IF(OR($J29="Yes",$L29="Yes",$N29="Yes"),"Yes","No") -> No | AD29: =MAX($Q29,$U29,$Y29) -> 0 | AE29: =$AD29+ROW()*0.000000001 -> 2.9e-08 | AF29: =IF($J29="Yes","A","")&IF($L29="Yes","B","")&IF($N29="Yes","C","")
B30: R0026 | C30: Solution Architect | D30: Ampol Customer | E30: Ampol Web | F30: AU | G30: Filled | H30: 1 | I30: 0.3219 | J30: No | L30: No | N30: No | P30: 0.3219 | Q30: =IF(AND($J30="Yes",$G30<>"Vendor day rates"),$I30-0.4*$P30,0) -> 0 | R30: =IFERROR(MATCH($K30,MonthList,0),0) -> 0 | S30: =IF(OR($J30<>"Yes",$K30=""),0,$Q30*MAX(0,7-$R30)/12) -> 0 | T30: =IF(OR($J30<>"Yes",$K30=""),0,$Q30*IF($R30<=7,12,19-$R30)/12) -> 0 | U30: =IF(AND($L30="Yes",$G30<>"Vendor day rates"),$I30-0.4*$P30,0) -> 0 | V30: =IFERROR(MATCH($M30,MonthList,0),0) -> 0 | W30: =IF(OR($L30<>"Yes",$M30=""),0,$U30*MAX(0,7-$V30)/12) -> 0 | X30: =IF(OR($L30<>"Yes",$M30=""),0,$U30*IF($V30<=7,12,19-$V30)/12) -> 0 | Y30: =IF(AND($N30="Yes",$G30<>"Vendor day rates"),$I30-0.4*$P30,0) -> 0 | Z30: =IFERROR(MATCH($O30,MonthList,0),0) -> 0 | AA30: =IF(OR($N30<>"Yes",$O30=""),0,$Y30*MAX(0,7-$Z30)/12) -> 0 | AB30: =IF(OR($N30<>"Yes",$O30=""),0,$Y30*IF($Z30<=7,12,19-$Z30)/12) -> 0 | AC30: =IF(OR($J30="Yes",$L30="Yes",$N30="Yes"),"Yes","No") -> No | AD30: =MAX($Q30,$U30,$Y30) -> 0 | AE30: =$AD30+ROW()*0.000000001 -> 3e-08 | AF30: =IF($J30="Yes","A","")&IF($L30="Yes","B","")&IF($N30="Yes","C","")
... B32: R0028 | C32: Quality Assurance | D32: Ampol Customer | E32: Ampol App | F32: AU | G32: Already at the offshore rate | H32: 1 | I32: 0.0717 | J32: No | L32: No | N32: No | P32: 0.1792 | Q32: =IF(AND($J32="Yes",$G32<>"Vendor day rates"),$I32-0.4*$P32,0) -> 0 | R32: =IFERROR(MATCH($K32,MonthList,0),0) -> 0 | S32: =IF(OR($J32<>"Yes",$K32=""),0,$Q32*MAX(0,7-$R32)/12) -> 0 | T32: =IF(OR($J32<>"Yes",$K32=""),0,$Q32*IF($R32<=7,12,19-$R32)/12) -> 0 | U32: =IF(AND($L32="Yes",$G32<>"Vendor day rates"),$I32-0.4*$P32,0) -> 0 | V32: =IFERROR(MATCH($M32,MonthList,0),0) -> 0 | W32: =IF(OR($L32<>"Yes",$M32=""),0,$U32*MAX(0,7-$V32)/12) -> 0 | X32: =IF(OR($L32<>"Yes",$M32=""),0,$U32*IF($V32<=7,12,19-$V32)/12) -> 0 | Y32: =IF(AND($N32="Yes",$G32<>"Vendor day rates"),$I32-0.4*$P32,0) -> 0 | Z32: =IFERROR(MATCH($O32,MonthList,0),0) -> 0 | AA32: =IF(OR($N32<>"Yes",$O32=""),0,$Y32*MAX(0,7-$Z32)/12) -> 0 | AB32: =IF(OR($N32<>"Yes",$O32=""),0,$Y32*IF($Z32<=7,12,19-$Z32)/12) -> 0 | AC32: =IF(OR($J32="Yes",$L32="Yes",$N32="Yes"),"Yes","No") -> No | AD32: =MAX($Q32,$U32,$Y32) -> 0 | AE32: =$AD32+ROW()*0.000000001 -> 3.2e-08 | AF32: =IF($J32="Yes","A","")&IF($L32="Yes","B","")&IF($N32="Yes","C","")
B33: R0029 | C33: Lead Engineer - Mobile | D33: Ampol Customer | E33: Ampol App | F33: AU | G33: Already at the offshore rate | H33: 1 | I33: 0.1113 | J33: Yes | K33: Oct-2026 | L33: No | N33: No | P33: 0.2782 | Q33: =IF(AND($J33="Yes",$G33<>"Vendor day rates"),$I33-0.4*$P33,0) -> 2e-05 | R33: =IFERROR(MATCH($K33,MonthList,0),0) -> 4 | S33: =IF(OR($J33<>"Yes",$K33=""),0,$Q33*MAX(0,7-$R33)/12) -> 5e-06 | T33: =IF(OR($J33<>"Yes",$K33=""),0,$Q33*IF($R33<=7,12,19-$R33)/12) -> 2e-05 | U33: =IF(AND($L33="Yes",$G33<>"Vendor day rates"),$I33-0.4*$P33,0) -> 0 | V33: =IFERROR(MATCH($M33,MonthList,0),0) -> 0 | W33: =IF(OR($L33<>"Yes",$M33=""),0,$U33*MAX(0,7-$V33)/12) -> 0 | X33: =IF(OR($L33<>"Yes",$M33=""),0,$U33*IF($V33<=7,12,19-$V33)/12) -> 0 | Y33: =IF(AND($N33="Yes",$G33<>"Vendor day rates"),$I33-0.4*$P33,0) -> 0 | Z33: =IFERROR(MATCH($O33,MonthList,0),0) -> 0 | AA33: =IF(OR($N33<>"Yes",$O33=""),0,$Y33*MAX(0,7-$Z33)/12) -> 0 | AB33: =IF(OR($N33<>"Yes",$O33=""),0,$Y33*IF($Z33<=7,12,19-$Z33)/12) -> 0 | AC33: =IF(OR($J33="Yes",$L33="Yes",$N33="Yes"),"Yes","No") -> Yes | AD33: =MAX($Q33,$U33,$Y33) -> 2e-05 | AE33: =$AD33+ROW()*0.000000001 -> 2.0033e-05 | AF33: =IF($J33="Yes","A","")&IF($L33="Yes","B","")&IF($N33="Yes","C","") -> A
B34: R0030 | C34: Solution Architect | D34: Ampol Customer | E34: Ampol Web | F34: AU | G34: Filled | H34: 1 | I34: 0.2431 | J34: No | L34: No | N34: No | P34: 0.2431 | Q34: =IF(AND($J34="Yes",$G34<>"Vendor day rates"),$I34-0.4*$P34,0) -> 0 | R34: =IFERROR(MATCH($K34,MonthList,0),0) -> 0 | S34: =IF(OR($J34<>"Yes",$K34=""),0,$Q34*MAX(0,7-$R34)/12) -> 0 | T34: =IF(OR($J34<>"Yes",$K34=""),0,$Q34*IF($R34<=7,12,19-$R34)/12) -> 0 | U34: =IF(AND($L34="Yes",$G34<>"Vendor day rates"),$I34-0.4*$P34,0) -> 0 | V34: =IFERROR(MATCH($M34,MonthList,0),0) -> 0 | W34: =IF(OR($L34<>"Yes",$M34=""),0,$U34*MAX(0,7-$V34)/12) -> 0 | X34: =IF(OR($L34<>"Yes",$M34=""),0,$U34*IF($V34<=7,12,19-$V34)/12) -> 0 | Y34: =IF(AND($N34="Yes",$G34<>"Vendor day rates"),$I34-0.4*$P34,0) -> 0 | Z34: =IFERROR(MATCH($O34,MonthList,0),0) -> 0 | AA34: =IF(OR($N34<>"Yes",$O34=""),0,$Y34*MAX(0,7-$Z34)/12) -> 0 | AB34: =IF(OR($N34<>"Yes",$O34=""),0,$Y34*IF($Z34<=7,12,19-$Z34)/12) -> 0 | AC34: =IF(OR($J34="Yes",$L34="Yes",$N34="Yes"),"Yes","No") -> No | AD34: =MAX($Q34,$U34,$Y34) -> 0 | AE34: =$AD34+ROW()*0.000000001 -> 3.4e-08 | AF34: =IF($J34="Yes","A","")&IF($L34="Yes","B","")&IF($N34="Yes","C","")
B35: R0031 | C35: Quality Assurance | D35: EGI Integration | E35: EGI Customer | F35: AU | G35: Filled | H35: 1 | I35: 0.2697 | J35: No | L35: No | N35: No | P35: 0.2697 | Q35: =IF(AND($J35="Yes",$G35<>"Vendor day rates"),$I35-0.4*$P35,0) -> 0 | R35: =IFERROR(MATCH($K35,MonthList,0),0) -> 0 | S35: =IF(OR($J35<>"Yes",$K35=""),0,$Q35*MAX(0,7-$R35)/12) -> 0 | T35: =IF(OR($J35<>"Yes",$K35=""),0,$Q35*IF($R35<=7,12,19-$R35)/12) -> 0 | U35: =IF(AND($L35="Yes",$G35<>"Vendor day rates"),$I35-0.4*$P35,0) -> 0 | V35: =IFERROR(MATCH($M35,MonthList,0),0) -> 0 | W35: =IF(OR($L35<>"Yes",$M35=""),0,$U35*MAX(0,7-$V35)/12) -> 0 | X35: =IF(OR($L35<>"Yes",$M35=""),0,$U35*IF($V35<=7,12,19-$V35)/12) -> 0 | Y35: =IF(AND($N35="Yes",$G35<>"Vendor day rates"),$I35-0.4*$P35,0) -> 0 | Z35: =IFERROR(MATCH($O35,MonthList,0),0) -> 0 | AA35: =IF(OR($N35<>"Yes",$O35=""),0,$Y35*MAX(0,7-$Z35)/12) -> 0 | AB35: =IF(OR($N35<>"Yes",$O35=""),0,$Y35*IF($Z35<=7,12,19-$Z35)/12) -> 0 | AC35: =IF(OR($J35="Yes",$L35="Yes",$N35="Yes"),"Yes","No") -> No | AD35: =MAX($Q35,$U35,$Y35) -> 0 | AE35: =$AD35+ROW()*0.000000001 -> 3.5e-08 | AF35: =IF($J35="Yes","A","")&IF($L35="Yes","B","")&IF($N35="Yes","C","")
B36: R0032 | C36: Delivery Lead - Integration | D36: EGI | E36: EGI | F36: AU | G36: Filled | H36: 1 | I36: 0.2735 | J36: No | L36: No | N36: No | P36: 0.2735 | Q36: =IF(AND($J36="Yes",$G36<>"Vendor day rates"),$I36-0.4*$P36,0) -> 0 | R36: =IFERROR(MATCH($K36,MonthList,0),0) -> 0 | S36: =IF(OR($J36<>"Yes",$K36=""),0,$Q36*MAX(0,7-$R36)/12) -> 0 | T36: =IF(OR($J36<>"Yes",$K36=""),0,$Q36*IF($R36<=7,12,19-$R36)/12) -> 0 | U36: =IF(AND($L36="Yes",$G36<>"Vendor day rates"),$I36-0.4*$P36,0) -> 0 | V36: =IFERROR(MATCH($M36,MonthList,0),0) -> 0 | W36: =IF(OR($L36<>"Yes",$M36=""),0,$U36*MAX(0,7-$V36)/12) -> 0 | X36: =IF(OR($L36<>"Yes",$M36=""),0,$U36*IF($V36<=7,12,19-$V36)/12) -> 0 | Y36: =IF(AND($N36="Yes",$G36<>"Vendor day rates"),$I36-0.4*$P36,0) -> 0 | Z36: =IFERROR(MATCH($O36,MonthList,0),0) -> 0 | AA36: =IF(OR($N36<>"Yes",$O36=""),0,$Y36*MAX(0,7-$Z36)/12) -> 0 | AB36: =IF(OR($N36<>"Yes",$O36=""),0,$Y36*IF($Z36<=7,12,19-$Z36)/12) -> 0 | AC36: =IF(OR($J36="Yes",$L36="Yes",$N36="Yes"),"Yes","No") -> No | AD36: =MAX($Q36,$U36,$Y36) -> 0 | AE36: =$AD36+ROW()*0.000000001 -> 3.6e-08 | AF36: =IF($J36="Yes","A","")&IF($L36="Yes","B","")&IF($N36="Yes","C","")
B37: R0033 | C37: SAP Solution Architect | E37: SAP ERP | F37: AU | G37: Filled | H37: 1 | I37: 0.3552 | J37: No | L37: No | N37: No | P37: 0.3552 | Q37: =IF(AND($J37="Yes",$G37<>"Vendor day rates"),$I37-0.4*$P37,0) -> 0 | R37: =IFERROR(MATCH($K37,MonthList,0),0) -> 0 | S37: =IF(OR($J37<>"Yes",$K37=""),0,$Q37*MAX(0,7-$R37)/12) -> 0 | T37: =IF(OR($J37<>"Yes",$K37=""),0,$Q37*IF($R37<=7,12,19-$R37)/12) -> 0 | U37: =IF(AND($L37="Yes",$G37<>"Vendor day rates"),$I37-0.4*$P37,0) -> 0 | V37: =IFERROR(MATCH($M37,MonthList,0),0) -> 0 | W37: =IF(OR($L37<>"Yes",$M37=""),0,$U37*MAX(0,7-$V37)/12) -> 0 | X37: =IF(OR($L37<>"Yes",$M37=""),0,$U37*IF($V37<=7,12,19-$V37)/12) -> 0 | Y37: =IF(AND($N37="Yes",$G37<>"Vendor day rates"),$I37-0.4*$P37,0) -> 0 | Z37: =IFERROR(MATCH($O37,MonthList,0),0) -> 0 | AA37: =IF(OR($N37<>"Yes",$O37=""),0,$Y37*MAX(0,7-$Z37)/12) -> 0 | AB37: =IF(OR($N37<>"Yes",$O37=""),0,$Y37*IF($Z37<=7,12,19-$Z37)/12) -> 0 | AC37: =IF(OR($J37="Yes",$L37="Yes",$N37="Yes"),"Yes","No") -> No | AD37: =MAX($Q37,$U37,$Y37) -> 0 | AE37: =$AD37+ROW()*0.000000001 -> 3.7e-08 | AF37: =IF($J37="Yes","A","")&IF($L37="Yes","B","")&IF($N37="Yes","C","")
B38: R0034 | C38: Project Manger | D38: EGI | E38: EGI | F38: AU | G38: Filled | H38: 1 | I38: 0.222 | J38: No | L38: No | N38: No | P38: 0.222 | Q38: =IF(AND($J38="Yes",$G38<>"Vendor day rates"),$I38-0.4*$P38,0) -> 0 | R38: =IFERROR(MATCH($K38,MonthList,0),0) -> 0 | S38: =IF(OR($J38<>"Yes",$K38=""),0,$Q38*MAX(0,7-$R38)/12) -> 0 | T38: =IF(OR($J38<>"Yes",$K38=""),0,$Q38*IF($R38<=7,12,19-$R38)/12) -> 0 | U38: =IF(AND($L38="Yes",$G38<>"Vendor day rates"),$I38-0.4*$P38,0) -> 0 | V38: =IFERROR(MATCH($M38,MonthList,0),0) -> 0 | W38: =IF(OR($L38<>"Yes",$M38=""),0,$U38*MAX(0,7-$V38)/12) -> 0 | X38: =IF(OR($L38<>"Yes",$M38=""),0,$U38*IF($V38<=7,12,19-$V38)/12) -> 0 | Y38: =IF(AND($N38="Yes",$G38<>"Vendor day rates"),$I38-0.4*$P38,0) -> 0 | Z38: =IFERROR(MATCH($O38,MonthList,0),0) -> 0 | AA38: =IF(OR($N38<>"Yes",$O38=""),0,$Y38*MAX(0,7-$Z38)/12) -> 0 | AB38: =IF(OR($N38<>"Yes",$O38=""),0,$Y38*IF($Z38<=7,12,19-$Z38)/12) -> 0 | AC38: =IF(OR($J38="Yes",$L38="Yes",$N38="Yes"),"Yes","No") -> No | AD38: =MAX($Q38,$U38,$Y38) -> 0 | AE38: =$AD38+ROW()*0.000000001 -> 3.8e-08 | AF38: =IF($J38="Yes","A","")&IF($L38="Yes","B","")&IF($N38="Yes","C","")
B39: R0035 | C39: strategic program architect | D39: EGI | E39: EGI | F39: AU | G39: Filled | H39: 1 | I39: 0.333 | J39: No | L39: No | N39: No | P39: 0.333 | Q39: =IF(AND($J39="Yes",$G39<>"Vendor day rates"),$I39-0.4*$P39,0) -> 0 | R39: =IFERROR(MATCH($K39,MonthList,0),0) -> 0 | S39: =IF(OR($J39<>"Yes",$K39=""),0,$Q39*MAX(0,7-$R39)/12) -> 0 | T39: =IF(OR($J39<>"Yes",$K39=""),0,$Q39*IF($R39<=7,12,19-$R39)/12) -> 0 | U39: =IF(AND($L39="Yes",$G39<>"Vendor day rates"),$I39-0.4*$P39,0) -> 0 | V39: =IFERROR(MATCH($M39,MonthList,0),0) -> 0 | W39: =IF(OR($L39<>"Yes",$M39=""),0,$U39*MAX(0,7-$V39)/12) -> 0 | X39: =IF(OR($L39<>"Yes",$M39=""),0,$U39*IF($V39<=7,12,19-$V39)/12) -> 0 | Y39: =IF(AND($N39="Yes",$G39<>"Vendor day rates"),$I39-0.4*$P39,0) -> 0 | Z39: =IFERROR(MATCH($O39,MonthList,0),0) -> 0 | AA39: =IF(OR($N39<>"Yes",$O39=""),0,$Y39*MAX(0,7-$Z39)/12) -> 0 | AB39: =IF(OR($N39<>"Yes",$O39=""),0,$Y39*IF($Z39<=7,12,19-$Z39)/12) -> 0 | AC39: =IF(OR($J39="Yes",$L39="Yes",$N39="Yes"),"Yes","No") -> No | AD39: =MAX($Q39,$U39,$Y39) -> 0 | AE39: =$AD39+ROW()*0.000000001 -> 3.9e-08 | AF39: =IF($J39="Yes","A","")&IF($L39="Yes","B","")&IF($N39="Yes","C","")
B40: R0036 | C40: Engineer - BE | D40: Ampol Customer | E40: Ampol Web | F40: AU | G40: Already at the offshore rate | H40: 1 | I40: 0.111 | J40: No | L40: No | N40: No | P40: 0.2775 | Q40: =IF(AND($J40="Yes",$G40<>"Vendor day rates"),$I40-0.4*$P40,0) -> 0 | R40: =IFERROR(MATCH($K40,MonthList,0),0) -> 0 | S40: =IF(OR($J40<>"Yes",$K40=""),0,$Q40*MAX(0,7-$R40)/12) -> 0 | T40: =IF(OR($J40<>"Yes",$K40=""),0,$Q40*IF($R40<=7,12,19-$R40)/12) -> 0 | U40: =IF(AND($L40="Yes",$G40<>"Vendor day rates"),$I40-0.4*$P40,0) -> 0 | V40: =IFERROR(MATCH($M40,MonthList,0),0) -> 0 | W40: =IF(OR($L40<>"Yes",$M40=""),0,$U40*MAX(0,7-$V40)/12) -> 0 | X40: =IF(OR($L40<>"Yes",$M40=""),0,$U40*IF($V40<=7,12,19-$V40)/12) -> 0 | Y40: =IF(AND($N40="Yes",$G40<>"Vendor day rates"),$I40-0.4*$P40,0) -> 0 | Z40: =IFERROR(MATCH($O40,MonthList,0),0) -> 0 | AA40: =IF(OR($N40<>"Yes",$O40=""),0,$Y40*MAX(0,7-$Z40)/12) -> 0 | AB40: =IF(OR($N40<>"Yes",$O40=""),0,$Y40*IF($Z40<=7,12,19-$Z40)/12) -> 0 | AC40: =IF(OR($J40="Yes",$L40="Yes",$N40="Yes"),"Yes","No") -> No | AD40: =MAX($Q40,$U40,$Y40) -> 0 | AE40: =$AD40+ROW()*0.000000001 -> 4e-08 | AF40: =IF($J40="Yes","A","")&IF($L40="Yes","B","")&IF($N40="Yes","C","")
B41: R0037 | C41: Engineer - BE | D41: Ampol Customer | E41: Ampol App | F41: AU | G41: Already at the offshore rate | H41: 1 | I41: 0.1082 | J41: No | L41: No | N41: No | P41: 0.2705 | Q41: =IF(AND($J41="Yes",$G41<>"Vendor day rates"),$I41-0.4*$P41,0) -> 0 | R41: =IFERROR(MATCH($K41,MonthList,0),0) -> 0 | S41: =IF(OR($J41<>"Yes",$K41=""),0,$Q41*MAX(0,7-$R41)/12) -> 0 | T41: =IF(OR($J41<>"Yes",$K41=""),0,$Q41*IF($R41<=7,12,19-$R41)/12) -> 0 | U41: =IF(AND($L41="Yes",$G41<>"Vendor day rates"),$I41-0.4*$P41,0) -> 0 | V41: =IFERROR(MATCH($M41,MonthList,0),0) -> 0 | W41: =IF(OR($L41<>"Yes",$M41=""),0,$U41*MAX(0,7-$V41)/12) -> 0 | X41: =IF(OR($L41<>"Yes",$M41=""),0,$U41*IF($V41<=7,12,19-$V41)/12) -> 0 | Y41: =IF(AND($N41="Yes",$G41<>"Vendor day rates"),$I41-0.4*$P41,0) -> 0 | Z41: =IFERROR(MATCH($O41,MonthList,0),0) -> 0 | AA41: =IF(OR($N41<>"Yes",$O41=""),0,$Y41*MAX(0,7-$Z41)/12) -> 0 | AB41: =IF(OR($N41<>"Yes",$O41=""),0,$Y41*IF($Z41<=7,12,19-$Z41)/12) -> 0 | AC41: =IF(OR($J41="Yes",$L41="Yes",$N41="Yes"),"Yes","No") -> No | AD41: =MAX($Q41,$U41,$Y41) -> 0 | AE41: =$AD41+ROW()*0.000000001 -> 4.1e-08 | AF41: =IF($J41="Yes","A","")&IF($L41="Yes","B","")&IF($N41="Yes","C","")
B42: R0038 | C42: Engineer - BE | D42: EGI Integration | E42: EGI Customer | F42: AU | G42: Filled | H42: 1 | I42: 0 | J42: No | L42: No | N42: No | P42: 0 | Q42: =IF(AND($J42="Yes",$G42<>"Vendor day rates"),$I42-0.4*$P42,0) -> 0 | R42: =IFERROR(MATCH($K42,MonthList,0),0) -> 0 | S42: =IF(OR($J42<>"Yes",$K42=""),0,$Q42*MAX(0,7-$R42)/12) -> 0 | T42: =IF(OR($J42<>"Yes",$K42=""),0,$Q42*IF($R42<=7,12,19-$R42)/12) -> 0 | U42: =IF(AND($L42="Yes",$G42<>"Vendor day rates"),$I42-0.4*$P42,0) -> 0 | V42: =IFERROR(MATCH($M42,MonthList,0),0) -> 0 | W42: =IF(OR($L42<>"Yes",$M42=""),0,$U42*MAX(0,7-$V42)/12) -> 0 | X42: =IF(OR($L42<>"Yes",$M42=""),0,$U42*IF($V42<=7,12,19-$V42)/12) -> 0 | Y42: =IF(AND($N42="Yes",$G42<>"Vendor day rates"),$I42-0.4*$P42,0) -> 0 | Z42: =IFERROR(MATCH($O42,MonthList,0),0) -> 0 | AA42: =IF(OR($N42<>"Yes",$O42=""),0,$Y42*MAX(0,7-$Z42)/12) -> 0 | AB42: =IF(OR($N42<>"Yes",$O42=""),0,$Y42*IF($Z42<=7,12,19-$Z42)/12) -> 0 | AC42: =IF(OR($J42="Yes",$L42="Yes",$N42="Yes"),"Yes","No") -> No | AD42: =MAX($Q42,$U42,$Y42) -> 0 | AE42: =$AD42+ROW()*0.000000001 -> 4.2e-08 | AF42: =IF($J42="Yes","A","")&IF($L42="Yes","B","")&IF($N42="Yes","C","")
B43: R0039 | C43: Engineer - BE | D43: EGI Integration | E43: EGI Customer | F43: AU | G43: Filled | H43: 1 | I43: 0.2642 | J43: No | L43: No | N43: No | P43: 0.2642 | Q43: =IF(AND($J43="Yes",$G43<>"Vendor day rates"),$I43-0.4*$P43,0) -> 0 | R43: =IFERROR(MATCH($K43,MonthList,0),0) -> 0 | S43: =IF(OR($J43<>"Yes",$K43=""),0,$Q43*MAX(0,7-$R43)/12) -> 0 | T43: =IF(OR($J43<>"Yes",$K43=""),0,$Q43*IF($R43<=7,12,19-$R43)/12) -> 0 | U43: =IF(AND($L43="Yes",$G43<>"Vendor day rates"),$I43-0.4*$P43,0) -> 0 | V43: =IFERROR(MATCH($M43,MonthList,0),0) -> 0 | W43: =IF(OR($L43<>"Yes",$M43=""),0,$U43*MAX(0,7-$V43)/12) -> 0 | X43: =IF(OR($L43<>"Yes",$M43=""),0,$U43*IF($V43<=7,12,19-$V43)/12) -> 0 | Y43: =IF(AND($N43="Yes",$G43<>"Vendor day rates"),$I43-0.4*$P43,0) -> 0 | Z43: =IFERROR(MATCH($O43,MonthList,0),0) -> 0 | AA43: =IF(OR($N43<>"Yes",$O43=""),0,$Y43*MAX(0,7-$Z43)/12) -> 0 | AB43: =IF(OR($N43<>"Yes",$O43=""),0,$Y43*IF($Z43<=7,12,19-$Z43)/12) -> 0 | AC43: =IF(OR($J43="Yes",$L43="Yes",$N43="Yes"),"Yes","No") -> No | AD43: =MAX($Q43,$U43,$Y43) -> 0 | AE43: =$AD43+ROW()*0.000000001 -> 4.3e-08 | AF43: =IF($J43="Yes","A","")&IF($L43="Yes","B","")&IF($N43="Yes","C","")
B44: R0040 | C44: Business Analyst | D44: EGI Integration | E44: EGI Retail | F44: AU | G44: Filled | H44: 1 | I44: 0.222 | J44: No | L44: No | N44: No | P44: 0.222 | Q44: =IF(AND($J44="Yes",$G44<>"Vendor day rates"),$I44-0.4*$P44,0) -> 0 | R44: =IFERROR(MATCH($K44,MonthList,0),0) -> 0 | S44: =IF(OR($J44<>"Yes",$K44=""),0,$Q44*MAX(0,7-$R44)/12) -> 0 | T44: =IF(OR($J44<>"Yes",$K44=""),0,$Q44*IF($R44<=7,12,19-$R44)/12) -> 0 | U44: =IF(AND($L44="Yes",$G44<>"Vendor day rates"),$I44-0.4*$P44,0) -> 0 | V44: =IFERROR(MATCH($M44,MonthList,0),0) -> 0 | W44: =IF(OR($L44<>"Yes",$M44=""),0,$U44*MAX(0,7-$V44)/12) -> 0 | X44: =IF(OR($L44<>"Yes",$M44=""),0,$U44*IF($V44<=7,12,19-$V44)/12) -> 0 | Y44: =IF(AND($N44="Yes",$G44<>"Vendor day rates"),$I44-0.4*$P44,0) -> 0 | Z44: =IFERROR(MATCH($O44,MonthList,0),0) -> 0 | AA44: =IF(OR($N44<>"Yes",$O44=""),0,$Y44*MAX(0,7-$Z44)/12) -> 0 | AB44: =IF(OR($N44<>"Yes",$O44=""),0,$Y44*IF($Z44<=7,12,19-$Z44)/12) -> 0 | AC44: =IF(OR($J44="Yes",$L44="Yes",$N44="Yes"),"Yes","No") -> No | AD44: =MAX($Q44,$U44,$Y44) -> 0 | AE44: =$AD44+ROW()*0.000000001 -> 4.4e-08 | AF44: =IF($J44="Yes","A","")&IF($L44="Yes","B","")&IF($N44="Yes","C","")
B45: R0041 | C45: DeveloperSAP ECC | D45: EGI | E45: EGI | F45: AU | G45: Filled | H45: 1 | I45: 0.2775 | J45: No | L45: No | N45: No | P45: 0.2775 | Q45: =IF(AND($J45="Yes",$G45<>"Vendor day rates"),$I45-0.4*$P45,0) -> 0 | R45: =IFERROR(MATCH($K45,MonthList,0),0) -> 0 | S45: =IF(OR($J45<>"Yes",$K45=""),0,$Q45*MAX(0,7-$R45)/12) -> 0 | T45: =IF(OR($J45<>"Yes",$K45=""),0,$Q45*IF($R45<=7,12,19-$R45)/12) -> 0 | U45: =IF(AND($L45="Yes",$G45<>"Vendor day rates"),$I45-0.4*$P45,0) -> 0 | V45: =IFERROR(MATCH($M45,MonthList,0),0) -> 0 | W45: =IF(OR($L45<>"Yes",$M45=""),0,$U45*MAX(0,7-$V45)/12) -> 0 | X45: =IF(OR($L45<>"Yes",$M45=""),0,$U45*IF($V45<=7,12,19-$V45)/12) -> 0 | Y45: =IF(AND($N45="Yes",$G45<>"Vendor day rates"),$I45-0.4*$P45,0) -> 0 | Z45: =IFERROR(MATCH($O45,MonthList,0),0) -> 0 | AA45: =IF(OR($N45<>"Yes",$O45=""),0,$Y45*MAX(0,7-$Z45)/12) -> 0 | AB45: =IF(OR($N45<>"Yes",$O45=""),0,$Y45*IF($Z45<=7,12,19-$Z45)/12) -> 0 | AC45: =IF(OR($J45="Yes",$L45="Yes",$N45="Yes"),"Yes","No") -> No | AD45: =MAX($Q45,$U45,$Y45) -> 0 | AE45: =$AD45+ROW()*0.000000001 -> 4.5e-08 | AF45: =IF($J45="Yes","A","")&IF($L45="Yes","B","")&IF($N45="Yes","C","")
B46: R0042 | C46: Commercial Director | D46: NA | E46: Commercial | F46: AU | G46: Vacant, hire planned | H46: 1 | I46: 0.4395 | J46: No | L46: No | N46: No | P46: 0.4395 | Q46: =IF(AND($J46="Yes",$G46<>"Vendor day rates"),$I46-0.4*$P46,0) -> 0 | R46: =IFERROR(MATCH($K46,MonthList,0),0) -> 0 | S46: =IF(OR($J46<>"Yes",$K46=""),0,$Q46*MAX(0,7-$R46)/12) -> 0 | T46: =IF(OR($J46<>"Yes",$K46=""),0,$Q46*IF($R46<=7,12,19-$R46)/12) -> 0 | U46: =IF(AND($L46="Yes",$G46<>"Vendor day rates"),$I46-0.4*$P46,0) -> 0 | V46: =IFERROR(MATCH($M46,MonthList,0),0) -> 0 | W46: =IF(OR($L46<>"Yes",$M46=""),0,$U46*MAX(0,7-$V46)/12) -> 0 | X46: =IF(OR($L46<>"Yes",$M46=""),0,$U46*IF($V46<=7,12,19-$V46)/12) -> 0 | Y46: =IF(AND($N46="Yes",$G46<>"Vendor day rates"),$I46-0.4*$P46,0) -> 0 | Z46: =IFERROR(MATCH($O46,MonthList,0),0) -> 0 | AA46: =IF(OR($N46<>"Yes",$O46=""),0,$Y46*MAX(0,7-$Z46)/12) -> 0 | AB46: =IF(OR($N46<>"Yes",$O46=""),0,$Y46*IF($Z46<=7,12,19-$Z46)/12) -> 0 | AC46: =IF(OR($J46="Yes",$L46="Yes",$N46="Yes"),"Yes","No") -> No | AD46: =MAX($Q46,$U46,$Y46) -> 0 | AE46: =$AD46+ROW()*0.000000001 -> 4.6e-08 | AF46: =IF($J46="Yes","A","")&IF($L46="Yes","B","")&IF($N46="Yes","C","")
B47: R0043 | C47: Head of Technology, Loyalty & Mart | D47: Z ENERGY (DIGITAL) | E47: Head of Technology | F47: NZ | G47: Filled | H47: 1 | I47: 0.3011 | J47: No | L47: No | N47: No | P47: 0.3011 | Q47: =IF(AND($J47="Yes",$G47<>"Vendor day rates"),$I47-0.4*$P47,0) -> 0 | R47: =IFERROR(MATCH($K47,MonthList,0),0) -> 0 | S47: =IF(OR($J47<>"Yes",$K47=""),0,$Q47*MAX(0,7-$R47)/12) -> 0 | T47: =IF(OR($J47<>"Yes",$K47=""),0,$Q47*IF($R47<=7,12,19-$R47)/12) -> 0 | U47: =IF(AND($L47="Yes",$G47<>"Vendor day rates"),$I47-0.4*$P47,0) -> 0 | V47: =IFERROR(MATCH($M47,MonthList,0),0) -> 0 | W47: =IF(OR($L47<>"Yes",$M47=""),0,$U47*MAX(0,7-$V47)/12) -> 0 | X47: =IF(OR($L47<>"Yes",$M47=""),0,$U47*IF($V47<=7,12,19-$V47)/12) -> 0 | Y47: =IF(AND($N47="Yes",$G47<>"Vendor day rates"),$I47-0.4*$P47,0) -> 0 | Z47: =IFERROR(MATCH($O47,MonthList,0),0) -> 0 | AA47: =IF(OR($N47<>"Yes",$O47=""),0,$Y47*MAX(0,7-$Z47)/12) -> 0 | AB47: =IF(OR($N47<>"Yes",$O47=""),0,$Y47*IF($Z47<=7,12,19-$Z47)/12) -> 0 | AC47: =IF(OR($J47="Yes",$L47="Yes",$N47="Yes"),"Yes","No") -> No | AD47: =MAX($Q47,$U47,$Y47) -> 0 | AE47: =$AD47+ROW()*0.000000001 -> 4.7e-08 | AF47: =IF($J47="Yes","A","")&IF($L47="Yes","B","")&IF($N47="Yes","C","")
B48: R0044 | C48: Head of Technology - Digital | D48: Ampol Customer | E48: Head of Technology | F48: NZ | G48: Filled | H48: 1 | I48: 0.2743 | J48: No | L48: No | N48: No | P48: 0.2743 | Q48: =IF(AND($J48="Yes",$G48<>"Vendor day rates"),$I48-0.4*$P48,0) -> 0 | R48: =IFERROR(MATCH($K48,MonthList,0),0) -> 0 | S48: =IF(OR($J48<>"Yes",$K48=""),0,$Q48*MAX(0,7-$R48)/12) -> 0 | T48: =IF(OR($J48<>"Yes",$K48=""),0,$Q48*IF($R48<=7,12,19-$R48)/12) -> 0 | U48: =IF(AND($L48="Yes",$G48<>"Vendor day rates"),$I48-0.4*$P48,0) -> 0 | V48: =IFERROR(MATCH($M48,MonthList,0),0) -> 0 | W48: =IF(OR($L48<>"Yes",$M48=""),0,$U48*MAX(0,7-$V48)/12) -> 0 | X48: =IF(OR($L48<>"Yes",$M48=""),0,$U48*IF($V48<=7,12,19-$V48)/12) -> 0 | Y48: =IF(AND($N48="Yes",$G48<>"Vendor day rates"),$I48-0.4*$P48,0) -> 0 | Z48: =IFERROR(MATCH($O48,MonthList,0),0) -> 0 | AA48: =IF(OR($N48<>"Yes",$O48=""),0,$Y48*MAX(0,7-$Z48)/12) -> 0 | AB48: =IF(OR($N48<>"Yes",$O48=""),0,$Y48*IF($Z48<=7,12,19-$Z48)/12) -> 0 | AC48: =IF(OR($J48="Yes",$L48="Yes",$N48="Yes"),"Yes","No") -> No | AD48: =MAX($Q48,$U48,$Y48) -> 0 | AE48: =$AD48+ROW()*0.000000001 -> 4.8e-08 | AF48: =IF($J48="Yes","A","")&IF($L48="Yes","B","")&IF($N48="Yes","C","")
B49: R0045 | C49: Head of Technology - TDD & Enginee | D49: TDD | E49: Head of Technology | F49: AU | G49: Vacant, hire planned | H49: 1 | I49: 0.333 | J49: No | L49: No | N49: No | P49: 0.333 | Q49: =IF(AND($J49="Yes",$G49<>"Vendor day rates"),$I49-0.4*$P49,0) -> 0 | R49: =IFERROR(MATCH($K49,MonthList,0),0) -> 0 | S49: =IF(OR($J49<>"Yes",$K49=""),0,$Q49*MAX(0,7-$R49)/12) -> 0 | T49: =IF(OR($J49<>"Yes",$K49=""),0,$Q49*IF($R49<=7,12,19-$R49)/12) -> 0 | U49: =IF(AND($L49="Yes",$G49<>"Vendor day rates"),$I49-0.4*$P49,0) -> 0 | V49: =IFERROR(MATCH($M49,MonthList,0),0) -> 0 | W49: =IF(OR($L49<>"Yes",$M49=""),0,$U49*MAX(0,7-$V49)/12) -> 0 | X49: =IF(OR($L49<>"Yes",$M49=""),0,$U49*IF($V49<=7,12,19-$V49)/12) -> 0 | Y49: =IF(AND($N49="Yes",$G49<>"Vendor day rates"),$I49-0.4*$P49,0) -> 0 | Z49: =IFERROR(MATCH($O49,MonthList,0),0) -> 0 | AA49: =IF(OR($N49<>"Yes",$O49=""),0,$Y49*MAX(0,7-$Z49)/12) -> 0 | AB49: =IF(OR($N49<>"Yes",$O49=""),0,$Y49*IF($Z49<=7,12,19-$Z49)/12) -> 0 | AC49: =IF(OR($J49="Yes",$L49="Yes",$N49="Yes"),"Yes","No") -> No | AD49: =MAX($Q49,$U49,$Y49) -> 0 | AE49: =$AD49+ROW()*0.000000001 -> 4.9e-08 | AF49: =IF($J49="Yes","A","")&IF($L49="Yes","B","")&IF($N49="Yes","C","")
... B54: R0050 | C54: Technology Manager, Data Engineeri | D54: Enterprise Data | E54: Technology Manager | F54: NZ | G54: Filled | H54: 1 | I54: 0.3209 | J54: No | L54: No | N54: No | P54: 0.3209 | Q54: =IF(AND($J54="Yes",$G54<>"Vendor day rates"),$I54-0.4*$P54,0) -> 0 | R54: =IFERROR(MATCH($K54,MonthList,0),0) -> 0 | S54: =IF(OR($J54<>"Yes",$K54=""),0,$Q54*MAX(0,7-$R54)/12) -> 0 | T54: =IF(OR($J54<>"Yes",$K54=""),0,$Q54*IF($R54<=7,12,19-$R54)/12) -> 0 | U54: =IF(AND($L54="Yes",$G54<>"Vendor day rates"),$I54-0.4*$P54,0) -> 0 | V54: =IFERROR(MATCH($M54,MonthList,0),0) -> 0 | W54: =IF(OR($L54<>"Yes",$M54=""),0,$U54*MAX(0,7-$V54)/12) -> 0 | X54: =IF(OR($L54<>"Yes",$M54=""),0,$U54*IF($V54<=7,12,19-$V54)/12) -> 0 | Y54: =IF(AND($N54="Yes",$G54<>"Vendor day rates"),$I54-0.4*$P54,0) -> 0 | Z54: =IFERROR(MATCH($O54,MonthList,0),0) -> 0 | AA54: =IF(OR($N54<>"Yes",$O54=""),0,$Y54*MAX(0,7-$Z54)/12) -> 0 | AB54: =IF(OR($N54<>"Yes",$O54=""),0,$Y54*IF($Z54<=7,12,19-$Z54)/12) -> 0 | AC54: =IF(OR($J54="Yes",$L54="Yes",$N54="Yes"),"Yes","No") -> No | AD54: =MAX($Q54,$U54,$Y54) -> 0 | AE54: =$AD54+ROW()*0.000000001 -> 5.4e-08 | AF54: =IF($J54="Yes","A","")&IF($L54="Yes","B","")&IF($N54="Yes","C","")
B55: R0051 | C55: Principal, Data Architecture & Gov | E55: Group Data | F55: AU | G55: Filled | H55: 1 | I55: 0.3891 | J55: No | L55: No | N55: No | P55: 0.3891 | Q55: =IF(AND($J55="Yes",$G55<>"Vendor day rates"),$I55-0.4*$P55,0) -> 0 | R55: =IFERROR(MATCH($K55,MonthList,0),0) -> 0 | S55: =IF(OR($J55<>"Yes",$K55=""),0,$Q55*MAX(0,7-$R55)/12) -> 0 | T55: =IF(OR($J55<>"Yes",$K55=""),0,$Q55*IF($R55<=7,12,19-$R55)/12) -> 0 | U55: =IF(AND($L55="Yes",$G55<>"Vendor day rates"),$I55-0.4*$P55,0) -> 0 | V55: =IFERROR(MATCH($M55,MonthList,0),0) -> 0 | W55: =IF(OR($L55<>"Yes",$M55=""),0,$U55*MAX(0,7-$V55)/12) -> 0 | X55: =IF(OR($L55<>"Yes",$M55=""),0,$U55*IF($V55<=7,12,19-$V55)/12) -> 0 | Y55: =IF(AND($N55="Yes",$G55<>"Vendor day rates"),$I55-0.4*$P55,0) -> 0 | Z55: =IFERROR(MATCH($O55,MonthList,0),0) -> 0 | AA55: =IF(OR($N55<>"Yes",$O55=""),0,$Y55*MAX(0,7-$Z55)/12) -> 0 | AB55: =IF(OR($N55<>"Yes",$O55=""),0,$Y55*IF($Z55<=7,12,19-$Z55)/12) -> 0 | AC55: =IF(OR($J55="Yes",$L55="Yes",$N55="Yes"),"Yes","No") -> No | AD55: =MAX($Q55,$U55,$Y55) -> 0 | AE55: =$AD55+ROW()*0.000000001 -> 5.5e-08 | AF55: =IF($J55="Yes","A","")&IF($L55="Yes","B","")&IF($N55="Yes","C","")
B56: R0052 | C56: Head of Technology, Group Data | D56: Enterprise Data | E56: Head of Technology | F56: AU | G56: Filled | H56: 1 | I56: 0.4098 | J56: No | L56: No | N56: No | P56: 0.4098 | Q56: =IF(AND($J56="Yes",$G56<>"Vendor day rates"),$I56-0.4*$P56,0) -> 0 | R56: =IFERROR(MATCH($K56,MonthList,0),0) -> 0 | S56: =IF(OR($J56<>"Yes",$K56=""),0,$Q56*MAX(0,7-$R56)/12) -> 0 | T56: =IF(OR($J56<>"Yes",$K56=""),0,$Q56*IF($R56<=7,12,19-$R56)/12) -> 0 | U56: =IF(AND($L56="Yes",$G56<>"Vendor day rates"),$I56-0.4*$P56,0) -> 0 | V56: =IFERROR(MATCH($M56,MonthList,0),0) -> 0 | W56: =IF(OR($L56<>"Yes",$M56=""),0,$U56*MAX(0,7-$V56)/12) -> 0 | X56: =IF(OR($L56<>"Yes",$M56=""),0,$U56*IF($V56<=7,12,19-$V56)/12) -> 0 | Y56: =IF(AND($N56="Yes",$G56<>"Vendor day rates"),$I56-0.4*$P56,0) -> 0 | Z56: =IFERROR(MATCH($O56,MonthList,0),0) -> 0 | AA56: =IF(OR($N56<>"Yes",$O56=""),0,$Y56*MAX(0,7-$Z56)/12) -> 0 | AB56: =IF(OR($N56<>"Yes",$O56=""),0,$Y56*IF($Z56<=7,12,19-$Z56)/12) -> 0 | AC56: =IF(OR($J56="Yes",$L56="Yes",$N56="Yes"),"Yes","No") -> No | AD56: =MAX($Q56,$U56,$Y56) -> 0 | AE56: =$AD56+ROW()*0.000000001 -> 5.6e-08 | AF56: =IF($J56="Yes","A","")&IF($L56="Yes","B","")&IF($N56="Yes","C","")
B57: R0053 | C57: Delivery Manager, Strategy, Archit | E57: Leadership | F57: AU | G57: Filled | H57: 1 | I57: 0.3691 | J57: No | L57: No | N57: No | P57: 0.3691 | Q57: =IF(AND($J57="Yes",$G57<>"Vendor day rates"),$I57-0.4*$P57,0) -> 0 | R57: =IFERROR(MATCH($K57,MonthList,0),0) -> 0 | S57: =IF(OR($J57<>"Yes",$K57=""),0,$Q57*MAX(0,7-$R57)/12) -> 0 | T57: =IF(OR($J57<>"Yes",$K57=""),0,$Q57*IF($R57<=7,12,19-$R57)/12) -> 0 | U57: =IF(AND($L57="Yes",$G57<>"Vendor day rates"),$I57-0.4*$P57,0) -> 0 | V57: =IFERROR(MATCH($M57,MonthList,0),0) -> 0 | W57: =IF(OR($L57<>"Yes",$M57=""),0,$U57*MAX(0,7-$V57)/12) -> 0 | X57: =IF(OR($L57<>"Yes",$M57=""),0,$U57*IF($V57<=7,12,19-$V57)/12) -> 0 | Y57: =IF(AND($N57="Yes",$G57<>"Vendor day rates"),$I57-0.4*$P57,0) -> 0 | Z57: =IFERROR(MATCH($O57,MonthList,0),0) -> 0 | AA57: =IF(OR($N57<>"Yes",$O57=""),0,$Y57*MAX(0,7-$Z57)/12) -> 0 | AB57: =IF(OR($N57<>"Yes",$O57=""),0,$Y57*IF($Z57<=7,12,19-$Z57)/12) -> 0 | AC57: =IF(OR($J57="Yes",$L57="Yes",$N57="Yes"),"Yes","No") -> No | AD57: =MAX($Q57,$U57,$Y57) -> 0 | AE57: =$AD57+ROW()*0.000000001 -> 5.7e-08 | AF57: =IF($J57="Yes","A","")&IF($L57="Yes","B","")&IF($N57="Yes","C","")
B58: R0054 | C58: Head of Architecture | E58: Leadership | F58: AU | G58: Vacant, hire planned | H58: 1 | I58: 0.335 | J58: No | L58: No | N58: No | P58: 0.335 | Q58: =IF(AND($J58="Yes",$G58<>"Vendor day rates"),$I58-0.4*$P58,0) -> 0 | R58: =IFERROR(MATCH($K58,MonthList,0),0) -> 0 | S58: =IF(OR($J58<>"Yes",$K58=""),0,$Q58*MAX(0,7-$R58)/12) -> 0 | T58: =IF(OR($J58<>"Yes",$K58=""),0,$Q58*IF($R58<=7,12,19-$R58)/12) -> 0 | U58: =IF(AND($L58="Yes",$G58<>"Vendor day rates"),$I58-0.4*$P58,0) -> 0 | V58: =IFERROR(MATCH($M58,MonthList,0),0) -> 0 | W58: =IF(OR($L58<>"Yes",$M58=""),0,$U58*MAX(0,7-$V58)/12) -> 0 | X58: =IF(OR($L58<>"Yes",$M58=""),0,$U58*IF($V58<=7,12,19-$V58)/12) -> 0 | Y58: =IF(AND($N58="Yes",$G58<>"Vendor day rates"),$I58-0.4*$P58,0) -> 0 | Z58: =IFERROR(MATCH($O58,MonthList,0),0) -> 0 | AA58: =IF(OR($N58<>"Yes",$O58=""),0,$Y58*MAX(0,7-$Z58)/12) -> 0 | AB58: =IF(OR($N58<>"Yes",$O58=""),0,$Y58*IF($Z58<=7,12,19-$Z58)/12) -> 0 | AC58: =IF(OR($J58="Yes",$L58="Yes",$N58="Yes"),"Yes","No") -> No | AD58: =MAX($Q58,$U58,$Y58) -> 0 | AE58: =$AD58+ROW()*0.000000001 -> 5.8e-08 | AF58: =IF($J58="Yes","A","")&IF($L58="Yes","B","")&IF($N58="Yes","C","")
B59: R0055 | C59: Head of Technology Strategy & AI C | E59: Leadership | F59: AU | G59: Vacant, hire planned | H59: 1 | I59: 0.333 | J59: No | L59: No | N59: No | P59: 0.333 | Q59: =IF(AND($J59="Yes",$G59<>"Vendor day rates"),$I59-0.4*$P59,0) -> 0 | R59: =IFERROR(MATCH($K59,MonthList,0),0) -> 0 | S59: =IF(OR($J59<>"Yes",$K59=""),0,$Q59*MAX(0,7-$R59)/12) -> 0 | T59: =IF(OR($J59<>"Yes",$K59=""),0,$Q59*IF($R59<=7,12,19-$R59)/12) -> 0 | U59: =IF(AND($L59="Yes",$G59<>"Vendor day rates"),$I59-0.4*$P59,0) -> 0 | V59: =IFERROR(MATCH($M59,MonthList,0),0) -> 0 | W59: =IF(OR($L59<>"Yes",$M59=""),0,$U59*MAX(0,7-$V59)/12) -> 0 | X59: =IF(OR($L59<>"Yes",$M59=""),0,$U59*IF($V59<=7,12,19-$V59)/12) -> 0 | Y59: =IF(AND($N59="Yes",$G59<>"Vendor day rates"),$I59-0.4*$P59,0) -> 0 | Z59: =IFERROR(MATCH($O59,MonthList,0),0) -> 0 | AA59: =IF(OR($N59<>"Yes",$O59=""),0,$Y59*MAX(0,7-$Z59)/12) -> 0 | AB59: =IF(OR($N59<>"Yes",$O59=""),0,$Y59*IF($Z59<=7,12,19-$Z59)/12) -> 0 | AC59: =IF(OR($J59="Yes",$L59="Yes",$N59="Yes"),"Yes","No") -> No | AD59: =MAX($Q59,$U59,$Y59) -> 0 | AE59: =$AD59+ROW()*0.000000001 -> 5.9e-08 | AF59: =IF($J59="Yes","A","")&IF($L59="Yes","B","")&IF($N59="Yes","C","")
B60: R0056 | C60: TDD BP - Infrastructure | D60: NA | E60: TDD Business Partner | F60: AU | G60: Filled | H60: 1 | I60: 0.2972 | J60: No | L60: No | N60: No | P60: 0.2972 | Q60: =IF(AND($J60="Yes",$G60<>"Vendor day rates"),$I60-0.4*$P60,0) -> 0 | R60: =IFERROR(MATCH($K60,MonthList,0),0) -> 0 | S60: =IF(OR($J60<>"Yes",$K60=""),0,$Q60*MAX(0,7-$R60)/12) -> 0 | T60: =IF(OR($J60<>"Yes",$K60=""),0,$Q60*IF($R60<=7,12,19-$R60)/12) -> 0 | U60: =IF(AND($L60="Yes",$G60<>"Vendor day rates"),$I60-0.4*$P60,0) -> 0 | V60: =IFERROR(MATCH($M60,MonthList,0),0) -> 0 | W60: =IF(OR($L60<>"Yes",$M60=""),0,$U60*MAX(0,7-$V60)/12) -> 0 | X60: =IF(OR($L60<>"Yes",$M60=""),0,$U60*IF($V60<=7,12,19-$V60)/12) -> 0 | Y60: =IF(AND($N60="Yes",$G60<>"Vendor day rates"),$I60-0.4*$P60,0) -> 0 | Z60: =IFERROR(MATCH($O60,MonthList,0),0) -> 0 | AA60: =IF(OR($N60<>"Yes",$O60=""),0,$Y60*MAX(0,7-$Z60)/12) -> 0 | AB60: =IF(OR($N60<>"Yes",$O60=""),0,$Y60*IF($Z60<=7,12,19-$Z60)/12) -> 0 | AC60: =IF(OR($J60="Yes",$L60="Yes",$N60="Yes"),"Yes","No") -> No | AD60: =MAX($Q60,$U60,$Y60) -> 0 | AE60: =$AD60+ROW()*0.000000001 -> 6e-08 | AF60: =IF($J60="Yes","A","")&IF($L60="Yes","B","")&IF($N60="Yes","C","")
B61: R0057 | C61: TDD BP - T&S | D61: NA | E61: TDD Business Partner | F61: AU | G61: Filled | H61: 1 | I61: 0.6661 | J61: No | L61: No | N61: No | P61: 0.6661 | Q61: =IF(AND($J61="Yes",$G61<>"Vendor day rates"),$I61-0.4*$P61,0) -> 0 | R61: =IFERROR(MATCH($K61,MonthList,0),0) -> 0 | S61: =IF(OR($J61<>"Yes",$K61=""),0,$Q61*MAX(0,7-$R61)/12) -> 0 | T61: =IF(OR($J61<>"Yes",$K61=""),0,$Q61*IF($R61<=7,12,19-$R61)/12) -> 0 | U61: =IF(AND($L61="Yes",$G61<>"Vendor day rates"),$I61-0.4*$P61,0) -> 0 | V61: =IFERROR(MATCH($M61,MonthList,0),0) -> 0 | W61: =IF(OR($L61<>"Yes",$M61=""),0,$U61*MAX(0,7-$V61)/12) -> 0 | X61: =IF(OR($L61<>"Yes",$M61=""),0,$U61*IF($V61<=7,12,19-$V61)/12) -> 0 | Y61: =IF(AND($N61="Yes",$G61<>"Vendor day rates"),$I61-0.4*$P61,0) -> 0 | Z61: =IFERROR(MATCH($O61,MonthList,0),0) -> 0 | AA61: =IF(OR($N61<>"Yes",$O61=""),0,$Y61*MAX(0,7-$Z61)/12) -> 0 | AB61: =IF(OR($N61<>"Yes",$O61=""),0,$Y61*IF($Z61<=7,12,19-$Z61)/12) -> 0 | AC61: =IF(OR($J61="Yes",$L61="Yes",$N61="Yes"),"Yes","No") -> No | AD61: =MAX($Q61,$U61,$Y61) -> 0 | AE61: =$AD61+ROW()*0.000000001 -> 6.1e-08 | AF61: =IF($J61="Yes","A","")&IF($L61="Yes","B","")&IF($N61="Yes","C","")
B62: R0058 | C62: TDD BP - Z | D62: NA | E62: TDD Business Partner | F62: NZ | G62: Filled | H62: 1 | I62: 0.2914 | J62: No | L62: No | N62: No | P62: 0.2914 | Q62: =IF(AND($J62="Yes",$G62<>"Vendor day rates"),$I62-0.4*$P62,0) -> 0 | R62: =IFERROR(MATCH($K62,MonthList,0),0) -> 0 | S62: =IF(OR($J62<>"Yes",$K62=""),0,$Q62*MAX(0,7-$R62)/12) -> 0 | T62: =IF(OR($J62<>"Yes",$K62=""),0,$Q62*IF($R62<=7,12,19-$R62)/12) -> 0 | U62: =IF(AND($L62="Yes",$G62<>"Vendor day rates"),$I62-0.4*$P62,0) -> 0 | V62: =IFERROR(MATCH($M62,MonthList,0),0) -> 0 | W62: =IF(OR($L62<>"Yes",$M62=""),0,$U62*MAX(0,7-$V62)/12) -> 0 | X62: =IF(OR($L62<>"Yes",$M62=""),0,$U62*IF($V62<=7,12,19-$V62)/12) -> 0 | Y62: =IF(AND($N62="Yes",$G62<>"Vendor day rates"),$I62-0.4*$P62,0) -> 0 | Z62: =IFERROR(MATCH($O62,MonthList,0),0) -> 0 | AA62: =IF(OR($N62<>"Yes",$O62=""),0,$Y62*MAX(0,7-$Z62)/12) -> 0 | AB62: =IF(OR($N62<>"Yes",$O62=""),0,$Y62*IF($Z62<=7,12,19-$Z62)/12) -> 0 | AC62: =IF(OR($J62="Yes",$L62="Yes",$N62="Yes"),"Yes","No") -> No | AD62: =MAX($Q62,$U62,$Y62) -> 0 | AE62: =$AD62+ROW()*0.000000001 -> 6.2e-08 | AF62: =IF($J62="Yes","A","")&IF($L62="Yes","B","")&IF($N62="Yes","C","")
B63: R0059 | C63: TDD BP - Retail & Customer - Store | D63: NA | E63: TDD Business Partner | F63: AU | G63: Filled | H63: 1 | I63: 0.4174 | J63: No | L63: No | N63: No | P63: 0.4174 | Q63: =IF(AND($J63="Yes",$G63<>"Vendor day rates"),$I63-0.4*$P63,0) -> 0 | R63: =IFERROR(MATCH($K63,MonthList,0),0) -> 0 | S63: =IF(OR($J63<>"Yes",$K63=""),0,$Q63*MAX(0,7-$R63)/12) -> 0 | T63: =IF(OR($J63<>"Yes",$K63=""),0,$Q63*IF($R63<=7,12,19-$R63)/12) -> 0 | U63: =IF(AND($L63="Yes",$G63<>"Vendor day rates"),$I63-0.4*$P63,0) -> 0 | V63: =IFERROR(MATCH($M63,MonthList,0),0) -> 0 | W63: =IF(OR($L63<>"Yes",$M63=""),0,$U63*MAX(0,7-$V63)/12) -> 0 | X63: =IF(OR($L63<>"Yes",$M63=""),0,$U63*IF($V63<=7,12,19-$V63)/12) -> 0 | Y63: =IF(AND($N63="Yes",$G63<>"Vendor day rates"),$I63-0.4*$P63,0) -> 0 | Z63: =IFERROR(MATCH($O63,MonthList,0),0) -> 0 | AA63: =IF(OR($N63<>"Yes",$O63=""),0,$Y63*MAX(0,7-$Z63)/12) -> 0 | AB63: =IF(OR($N63<>"Yes",$O63=""),0,$Y63*IF($Z63<=7,12,19-$Z63)/12) -> 0 | AC63: =IF(OR($J63="Yes",$L63="Yes",$N63="Yes"),"Yes","No") -> No | AD63: =MAX($Q63,$U63,$Y63) -> 0 | AE63: =$AD63+ROW()*0.000000001 -> 6.3e-08 | AF63: =IF($J63="Yes","A","")&IF($L63="Yes","B","")&IF($N63="Yes","C","")
B64: R0060 | C64: TDD BP - ES | D64: NA | E64: TDD Business Partner | F64: AU | G64: Filled | H64: 1 | I64: 0.3434 | J64: No | L64: No | N64: No | P64: 0.3434 | Q64: =IF(AND($J64="Yes",$G64<>"Vendor day rates"),$I64-0.4*$P64,0) -> 0 | R64: =IFERROR(MATCH($K64,MonthList,0),0) -> 0 | S64: =IF(OR($J64<>"Yes",$K64=""),0,$Q64*MAX(0,7-$R64)/12) -> 0 | T64: =IF(OR($J64<>"Yes",$K64=""),0,$Q64*IF($R64<=7,12,19-$R64)/12) -> 0 | U64: =IF(AND($L64="Yes",$G64<>"Vendor day rates"),$I64-0.4*$P64,0) -> 0 | V64: =IFERROR(MATCH($M64,MonthList,0),0) -> 0 | W64: =IF(OR($L64<>"Yes",$M64=""),0,$U64*MAX(0,7-$V64)/12) -> 0 | X64: =IF(OR($L64<>"Yes",$M64=""),0,$U64*IF($V64<=7,12,19-$V64)/12) -> 0 | Y64: =IF(AND($N64="Yes",$G64<>"Vendor day rates"),$I64-0.4*$P64,0) -> 0 | Z64: =IFERROR(MATCH($O64,MonthList,0),0) -> 0 | AA64: =IF(OR($N64<>"Yes",$O64=""),0,$Y64*MAX(0,7-$Z64)/12) -> 0 | AB64: =IF(OR($N64<>"Yes",$O64=""),0,$Y64*IF($Z64<=7,12,19-$Z64)/12) -> 0 | AC64: =IF(OR($J64="Yes",$L64="Yes",$N64="Yes"),"Yes","No") -> No | AD64: =MAX($Q64,$U64,$Y64) -> 0 | AE64: =$AD64+ROW()*0.000000001 -> 6.4e-08 | AF64: =IF($J64="Yes","A","")&IF($L64="Yes","B","")&IF($N64="Yes","C","")
B65: R0061 | C65: Head of Transformation | D65: NA | E65: Transformation | F65: AU | G65: Filled | H65: 1 | I65: 0.3679 | J65: No | L65: No | N65: No | P65: 0.3679 | Q65: =IF(AND($J65="Yes",$G65<>"Vendor day rates"),$I65-0.4*$P65,0) -> 0 | R65: =IFERROR(MATCH($K65,MonthList,0),0) -> 0 | S65: =IF(OR($J65<>"Yes",$K65=""),0,$Q65*MAX(0,7-$R65)/12) -> 0 | T65: =IF(OR($J65<>"Yes",$K65=""),0,$Q65*IF($R65<=7,12,19-$R65)/12) -> 0 | U65: =IF(AND($L65="Yes",$G65<>"Vendor day rates"),$I65-0.4*$P65,0) -> 0 | V65: =IFERROR(MATCH($M65,MonthList,0),0) -> 0 | W65: =IF(OR($L65<>"Yes",$M65=""),0,$U65*MAX(0,7-$V65)/12) -> 0 | X65: =IF(OR($L65<>"Yes",$M65=""),0,$U65*IF($V65<=7,12,19-$V65)/12) -> 0 | Y65: =IF(AND($N65="Yes",$G65<>"Vendor day rates"),$I65-0.4*$P65,0) -> 0 | Z65: =IFERROR(MATCH($O65,MonthList,0),0) -> 0 | AA65: =IF(OR($N65<>"Yes",$O65=""),0,$Y65*MAX(0,7-$Z65)/12) -> 0 | AB65: =IF(OR($N65<>"Yes",$O65=""),0,$Y65*IF($Z65<=7,12,19-$Z65)/12) -> 0 | AC65: =IF(OR($J65="Yes",$L65="Yes",$N65="Yes"),"Yes","No") -> No | AD65: =MAX($Q65,$U65,$Y65) -> 0 | AE65: =$AD65+ROW()*0.000000001 -> 6.5e-08 | AF65: =IF($J65="Yes","A","")&IF($L65="Yes","B","")&IF($N65="Yes","C","")
B66: R0062 | C66: Head of Technology, Fuel Infrastru | D66: Infrastructure | E66: Head of Technology | F66: AU | G66: Filled | H66: 1 | I66: 0.3636 | J66: No | L66: No | N66: No | P66: 0.3636 | Q66: =IF(AND($J66="Yes",$G66<>"Vendor day rates"),$I66-0.4*$P66,0) -> 0 | R66: =IFERROR(MATCH($K66,MonthList,0),0) -> 0 | S66: =IF(OR($J66<>"Yes",$K66=""),0,$Q66*MAX(0,7-$R66)/12) -> 0 | T66: =IF(OR($J66<>"Yes",$K66=""),0,$Q66*IF($R66<=7,12,19-$R66)/12) -> 0 | U66: =IF(AND($L66="Yes",$G66<>"Vendor day rates"),$I66-0.4*$P66,0) -> 0 | V66: =IFERROR(MATCH($M66,MonthList,0),0) -> 0 | W66: =IF(OR($L66<>"Yes",$M66=""),0,$U66*MAX(0,7-$V66)/12) -> 0 | X66: =IF(OR($L66<>"Yes",$M66=""),0,$U66*IF($V66<=7,12,19-$V66)/12) -> 0 | Y66: =IF(AND($N66="Yes",$G66<>"Vendor day rates"),$I66-0.4*$P66,0) -> 0 | Z66: =IFERROR(MATCH($O66,MonthList,0),0) -> 0 | AA66: =IF(OR($N66<>"Yes",$O66=""),0,$Y66*MAX(0,7-$Z66)/12) -> 0 | AB66: =IF(OR($N66<>"Yes",$O66=""),0,$Y66*IF($Z66<=7,12,19-$Z66)/12) -> 0 | AC66: =IF(OR($J66="Yes",$L66="Yes",$N66="Yes"),"Yes","No") -> No | AD66: =MAX($Q66,$U66,$Y66) -> 0 | AE66: =$AD66+ROW()*0.000000001 -> 6.6e-08 | AF66: =IF($J66="Yes","A","")&IF($L66="Yes","B","")&IF($N66="Yes","C","")
B67: R0063 | C67: Head of Technology, Commercial Fue | D67: Commercial Fuels | E67: Head of Technology | F67: NZ | G67: Filled | H67: 1 | I67: 0.2924 | J67: No | L67: No | N67: No | P67: 0.2924 | Q67: =IF(AND($J67="Yes",$G67<>"Vendor day rates"),$I67-0.4*$P67,0) -> 0 | R67: =IFERROR(MATCH($K67,MonthList,0),0) -> 0 | S67: =IF(OR($J67<>"Yes",$K67=""),0,$Q67*MAX(0,7-$R67)/12) -> 0 | T67: =IF(OR($J67<>"Yes",$K67=""),0,$Q67*IF($R67<=7,12,19-$R67)/12) -> 0 | U67: =IF(AND($L67="Yes",$G67<>"Vendor day rates"),$I67-0.4*$P67,0) -> 0 | V67: =IFERROR(MATCH($M67,MonthList,0),0) -> 0 | W67: =IF(OR($L67<>"Yes",$M67=""),0,$U67*MAX(0,7-$V67)/12) -> 0 | X67: =IF(OR($L67<>"Yes",$M67=""),0,$U67*IF($V67<=7,12,19-$V67)/12) -> 0 | Y67: =IF(AND($N67="Yes",$G67<>"Vendor day rates"),$I67-0.4*$P67,0) -> 0 | Z67: =IFERROR(MATCH($O67,MonthList,0),0) -> 0 | AA67: =IF(OR($N67<>"Yes",$O67=""),0,$Y67*MAX(0,7-$Z67)/12) -> 0 | AB67: =IF(OR($N67<>"Yes",$O67=""),0,$Y67*IF($Z67<=7,12,19-$Z67)/12) -> 0 | AC67: =IF(OR($J67="Yes",$L67="Yes",$N67="Yes"),"Yes","No") -> No | AD67: =MAX($Q67,$U67,$Y67) -> 0 | AE67: =$AD67+ROW()*0.000000001 -> 6.7e-08 | AF67: =IF($J67="Yes","A","")&IF($L67="Yes","B","")&IF($N67="Yes","C","")
B68: R0064 | C68: Head of Technology, B2B & Energy S | D68: B2B & Energy Solutions | E68: Head of Technology | F68: NZ | G68: Filled | H68: 1 | I68: 0.2738 | J68: No | L68: No | N68: No | P68: 0.2738 | Q68: =IF(AND($J68="Yes",$G68<>"Vendor day rates"),$I68-0.4*$P68,0) -> 0 | R68: =IFERROR(MATCH($K68,MonthList,0),0) -> 0 | S68: =IF(OR($J68<>"Yes",$K68=""),0,$Q68*MAX(0,7-$R68)/12) -> 0 | T68: =IF(OR($J68<>"Yes",$K68=""),0,$Q68*IF($R68<=7,12,19-$R68)/12) -> 0 | U68: =IF(AND($L68="Yes",$G68<>"Vendor day rates"),$I68-0.4*$P68,0) -> 0 | V68: =IFERROR(MATCH($M68,MonthList,0),0) -> 0 | W68: =IF(OR($L68<>"Yes",$M68=""),0,$U68*MAX(0,7-$V68)/12) -> 0 | X68: =IF(OR($L68<>"Yes",$M68=""),0,$U68*IF($V68<=7,12,19-$V68)/12) -> 0 | Y68: =IF(AND($N68="Yes",$G68<>"Vendor day rates"),$I68-0.4*$P68,0) -> 0 | Z68: =IFERROR(MATCH($O68,MonthList,0),0) -> 0 | AA68: =IF(OR($N68<>"Yes",$O68=""),0,$Y68*MAX(0,7-$Z68)/12) -> 0 | AB68: =IF(OR($N68<>"Yes",$O68=""),0,$Y68*IF($Z68<=7,12,19-$Z68)/12) -> 0 | AC68: =IF(OR($J68="Yes",$L68="Yes",$N68="Yes"),"Yes","No") -> No | AD68: =MAX($Q68,$U68,$Y68) -> 0 | AE68: =$AD68+ROW()*0.000000001 -> 6.8e-08 | AF68: =IF($J68="Yes","A","")&IF($L68="Yes","B","")&IF($N68="Yes","C","")
B69: R0065 | C69: Data Governance Lead | E69: Group Data | F69: AU | G69: Vacant, hire planned | H69: 1 | I69: 0.1948 | J69: No | L69: No | N69: No | P69: 0.3896 | Q69: =IF(AND($J69="Yes",$G69<>"Vendor day rates"),$I69-0.4*$P69,0) -> 0 | R69: =IFERROR(MATCH($K69,MonthList,0),0) -> 0 | S69: =IF(OR($J69<>"Yes",$K69=""),0,$Q69*MAX(0,7-$R69)/12) -> 0 | T69: =IF(OR($J69<>"Yes",$K69=""),0,$Q69*IF($R69<=7,12,19-$R69)/12) -> 0 | U69: =IF(AND($L69="Yes",$G69<>"Vendor day rates"),$I69-0.4*$P69,0) -> 0 | V69: =IFERROR(MATCH($M69,MonthList,0),0) -> 0 | W69: =IF(OR($L69<>"Yes",$M69=""),0,$U69*MAX(0,7-$V69)/12) -> 0 | X69: =IF(OR($L69<>"Yes",$M69=""),0,$U69*IF($V69<=7,12,19-$V69)/12) -> 0 | Y69: =IF(AND($N69="Yes",$G69<>"Vendor day rates"),$I69-0.4*$P69,0) -> 0 | Z69: =IFERROR(MATCH($O69,MonthList,0),0) -> 0 | AA69: =IF(OR($N69<>"Yes",$O69=""),0,$Y69*MAX(0,7-$Z69)/12) -> 0 | AB69: =IF(OR($N69<>"Yes",$O69=""),0,$Y69*IF($Z69<=7,12,19-$Z69)/12) -> 0 | AC69: =IF(OR($J69="Yes",$L69="Yes",$N69="Yes"),"Yes","No") -> No | AD69: =MAX($Q69,$U69,$Y69) -> 0 | AE69: =$AD69+ROW()*0.000000001 -> 6.9e-08 | AF69: =IF($J69="Yes","A","")&IF($L69="Yes","B","")&IF($N69="Yes","C","")
B70: R0066 | C70: Head of Technology, AU Retail | D70: Retail | E70: Head of Technology | F70: AU | G70: Filled | H70: 1 | I70: 0.186 | J70: No | L70: No | N70: No | P70: 0.186 | Q70: =IF(AND($J70="Yes",$G70<>"Vendor day rates"),$I70-0.4*$P70,0) -> 0 | R70: =IFERROR(MATCH($K70,MonthList,0),0) -> 0 | S70: =IF(OR($J70<>"Yes",$K70=""),0,$Q70*MAX(0,7-$R70)/12) -> 0 | T70: =IF(OR($J70<>"Yes",$K70=""),0,$Q70*IF($R70<=7,12,19-$R70)/12) -> 0 | U70: =IF(AND($L70="Yes",$G70<>"Vendor day rates"),$I70-0.4*$P70,0) -> 0 | V70: =IFERROR(MATCH($M70,MonthList,0),0) -> 0 | W70: =IF(OR($L70<>"Yes",$M70=""),0,$U70*MAX(0,7-$V70)/12) -> 0 | X70: =IF(OR($L70<>"Yes",$M70=""),0,$U70*IF($V70<=7,12,19-$V70)/12) -> 0 | Y70: =IF(AND($N70="Yes",$G70<>"Vendor day rates"),$I70-0.4*$P70,0) -> 0 | Z70: =IFERROR(MATCH($O70,MonthList,0),0) -> 0 | AA70: =IF(OR($N70<>"Yes",$O70=""),0,$Y70*MAX(0,7-$Z70)/12) -> 0 | AB70: =IF(OR($N70<>"Yes",$O70=""),0,$Y70*IF($Z70<=7,12,19-$Z70)/12) -> 0 | AC70: =IF(OR($J70="Yes",$L70="Yes",$N70="Yes"),"Yes","No") -> No | AD70: =MAX($Q70,$U70,$Y70) -> 0 | AE70: =$AD70+ROW()*0.000000001 -> 7e-08 | AF70: =IF($J70="Yes","A","")&IF($L70="Yes","B","")&IF($N70="Yes","C","")
B71: R0067 | C71: Head of Technology, Z and Group Re | D71: Z | E71: Head of Technology | F71: NZ | G71: Vacant, hire planned | H71: 1 | I71: 0.2914 | J71: No | L71: No | N71: No | P71: 0.2914 | Q71: =IF(AND($J71="Yes",$G71<>"Vendor day rates"),$I71-0.4*$P71,0) -> 0 | R71: =IFERROR(MATCH($K71,MonthList,0),0) -> 0 | S71: =IF(OR($J71<>"Yes",$K71=""),0,$Q71*MAX(0,7-$R71)/12) -> 0 | T71: =IF(OR($J71<>"Yes",$K71=""),0,$Q71*IF($R71<=7,12,19-$R71)/12) -> 0 | U71: =IF(AND($L71="Yes",$G71<>"Vendor day rates"),$I71-0.4*$P71,0) -> 0 | V71: =IFERROR(MATCH($M71,MonthList,0),0) -> 0 | W71: =IF(OR($L71<>"Yes",$M71=""),0,$U71*MAX(0,7-$V71)/12) -> 0 | X71: =IF(OR($L71<>"Yes",$M71=""),0,$U71*IF($V71<=7,12,19-$V71)/12) -> 0 | Y71: =IF(AND($N71="Yes",$G71<>"Vendor day rates"),$I71-0.4*$P71,0) -> 0 | Z71: =IFERROR(MATCH($O71,MonthList,0),0) -> 0 | AA71: =IF(OR($N71<>"Yes",$O71=""),0,$Y71*MAX(0,7-$Z71)/12) -> 0 | AB71: =IF(OR($N71<>"Yes",$O71=""),0,$Y71*IF($Z71<=7,12,19-$Z71)/12) -> 0 | AC71: =IF(OR($J71="Yes",$L71="Yes",$N71="Yes"),"Yes","No") -> No | AD71: =MAX($Q71,$U71,$Y71) -> 0 | AE71: =$AD71+ROW()*0.000000001 -> 7.1e-08 | AF71: =IF($J71="Yes","A","")&IF($L71="Yes","B","")&IF($N71="Yes","C","")
B72: R0068 | C72: Delivery Manager | D72: Z ENERGY (DIGITAL) | E72: Delivery Manager | F72: NZ | G72: Filled | H72: 1 | I72: 0.222 | J72: No | L72: No | N72: No | P72: 0.222 | Q72: =IF(AND($J72="Yes",$G72<>"Vendor day rates"),$I72-0.4*$P72,0) -> 0 | R72: =IFERROR(MATCH($K72,MonthList,0),0) -> 0 | S72: =IF(OR($J72<>"Yes",$K72=""),0,$Q72*MAX(0,7-$R72)/12) -> 0 | T72: =IF(OR($J72<>"Yes",$K72=""),0,$Q72*IF($R72<=7,12,19-$R72)/12) -> 0 | U72: =IF(AND($L72="Yes",$G72<>"Vendor day rates"),$I72-0.4*$P72,0) -> 0 | V72: =IFERROR(MATCH($M72,MonthList,0),0) -> 0 | W72: =IF(OR($L72<>"Yes",$M72=""),0,$U72*MAX(0,7-$V72)/12) -> 0 | X72: =IF(OR($L72<>"Yes",$M72=""),0,$U72*IF($V72<=7,12,19-$V72)/12) -> 0 | Y72: =IF(AND($N72="Yes",$G72<>"Vendor day rates"),$I72-0.4*$P72,0) -> 0 | Z72: =IFERROR(MATCH($O72,MonthList,0),0) -> 0 | AA72: =IF(OR($N72<>"Yes",$O72=""),0,$Y72*MAX(0,7-$Z72)/12) -> 0 | AB72: =IF(OR($N72<>"Yes",$O72=""),0,$Y72*IF($Z72<=7,12,19-$Z72)/12) -> 0 | AC72: =IF(OR($J72="Yes",$L72="Yes",$N72="Yes"),"Yes","No") -> No | AD72: =MAX($Q72,$U72,$Y72) -> 0 | AE72: =$AD72+ROW()*0.000000001 -> 7.2e-08 | AF72: =IF($J72="Yes","A","")&IF($L72="Yes","B","")&IF($N72="Yes","C","")
B73: R0069 | C73: Technology Manager – Data & Engine | D73: Z ENERGY (DIGITAL) | E73: Technology Manager | F73: NZ | G73: Filled | H73: 1 | I73: 0.2077 | J73: No | L73: No | N73: No | P73: 0.2077 | Q73: =IF(AND($J73="Yes",$G73<>"Vendor day rates"),$I73-0.4*$P73,0) -> 0 | R73: =IFERROR(MATCH($K73,MonthList,0),0) -> 0 | S73: =IF(OR($J73<>"Yes",$K73=""),0,$Q73*MAX(0,7-$R73)/12) -> 0 | T73: =IF(OR($J73<>"Yes",$K73=""),0,$Q73*IF($R73<=7,12,19-$R73)/12) -> 0 | U73: =IF(AND($L73="Yes",$G73<>"Vendor day rates"),$I73-0.4*$P73,0) -> 0 | V73: =IFERROR(MATCH($M73,MonthList,0),0) -> 0 | W73: =IF(OR($L73<>"Yes",$M73=""),0,$U73*MAX(0,7-$V73)/12) -> 0 | X73: =IF(OR($L73<>"Yes",$M73=""),0,$U73*IF($V73<=7,12,19-$V73)/12) -> 0 | Y73: =IF(AND($N73="Yes",$G73<>"Vendor day rates"),$I73-0.4*$P73,0) -> 0 | Z73: =IFERROR(MATCH($O73,MonthList,0),0) -> 0 | AA73: =IF(OR($N73<>"Yes",$O73=""),0,$Y73*MAX(0,7-$Z73)/12) -> 0 | AB73: =IF(OR($N73<>"Yes",$O73=""),0,$Y73*IF($Z73<=7,12,19-$Z73)/12) -> 0 | AC73: =IF(OR($J73="Yes",$L73="Yes",$N73="Yes"),"Yes","No") -> No | AD73: =MAX($Q73,$U73,$Y73) -> 0 | AE73: =$AD73+ROW()*0.000000001 -> 7.3e-08 | AF73: =IF($J73="Yes","A","")&IF($L73="Yes","B","")&IF($N73="Yes","C","")
B74: R0070 | C74: Technology Manager - Loyalty & Mar | D74: Z ENERGY (DIGITAL) | E74: Technology Manager | F74: NZ | G74: Filled | H74: 1 | I74: 0.2232 | J74: No | L74: No | N74: No | P74: 0.2232 | Q74: =IF(AND($J74="Yes",$G74<>"Vendor day rates"),$I74-0.4*$P74,0) -> 0 | R74: =IFERROR(MATCH($K74,MonthList,0),0) -> 0 | S74: =IF(OR($J74<>"Yes",$K74=""),0,$Q74*MAX(0,7-$R74)/12) -> 0 | T74: =IF(OR($J74<>"Yes",$K74=""),0,$Q74*IF($R74<=7,12,19-$R74)/12) -> 0 | U74: =IF(AND($L74="Yes",$G74<>"Vendor day rates"),$I74-0.4*$P74,0) -> 0 | V74: =IFERROR(MATCH($M74,MonthList,0),0) -> 0 | W74: =IF(OR($L74<>"Yes",$M74=""),0,$U74*MAX(0,7-$V74)/12) -> 0 | X74: =IF(OR($L74<>"Yes",$M74=""),0,$U74*IF($V74<=7,12,19-$V74)/12) -> 0 | Y74: =IF(AND($N74="Yes",$G74<>"Vendor day rates"),$I74-0.4*$P74,0) -> 0 | Z74: =IFERROR(MATCH($O74,MonthList,0),0) -> 0 | AA74: =IF(OR($N74<>"Yes",$O74=""),0,$Y74*MAX(0,7-$Z74)/12) -> 0 | AB74: =IF(OR($N74<>"Yes",$O74=""),0,$Y74*IF($Z74<=7,12,19-$Z74)/12) -> 0 | AC74: =IF(OR($J74="Yes",$L74="Yes",$N74="Yes"),"Yes","No") -> No | AD74: =MAX($Q74,$U74,$Y74) -> 0 | AE74: =$AD74+ROW()*0.000000001 -> 7.4e-08 | AF74: =IF($J74="Yes","A","")&IF($L74="Yes","B","")&IF($N74="Yes","C","")
B75: R0071 | C75: Head of AI enablement | D75: Ampol Customer | E75: Customer, AI | F75: AU | G75: Filled | H75: 1 | I75: 0.3397 | J75: No | L75: No | N75: No | P75: 0.3397 | Q75: =IF(AND($J75="Yes",$G75<>"Vendor day rates"),$I75-0.4*$P75,0) -> 0 | R75: =IFERROR(MATCH($K75,MonthList,0),0) -> 0 | S75: =IF(OR($J75<>"Yes",$K75=""),0,$Q75*MAX(0,7-$R75)/12) -> 0 | T75: =IF(OR($J75<>"Yes",$K75=""),0,$Q75*IF($R75<=7,12,19-$R75)/12) -> 0 | U75: =IF(AND($L75="Yes",$G75<>"Vendor day rates"),$I75-0.4*$P75,0) -> 0 | V75: =IFERROR(MATCH($M75,MonthList,0),0) -> 0 | W75: =IF(OR($L75<>"Yes",$M75=""),0,$U75*MAX(0,7-$V75)/12) -> 0 | X75: =IF(OR($L75<>"Yes",$M75=""),0,$U75*IF($V75<=7,12,19-$V75)/12) -> 0 | Y75: =IF(AND($N75="Yes",$G75<>"Vendor day rates"),$I75-0.4*$P75,0) -> 0 | Z75: =IFERROR(MATCH($O75,MonthList,0),0) -> 0 | AA75: =IF(OR($N75<>"Yes",$O75=""),0,$Y75*MAX(0,7-$Z75)/12) -> 0 | AB75: =IF(OR($N75<>"Yes",$O75=""),0,$Y75*IF($Z75<=7,12,19-$Z75)/12) -> 0 | AC75: =IF(OR($J75="Yes",$L75="Yes",$N75="Yes"),"Yes","No") -> No | AD75: =MAX($Q75,$U75,$Y75) -> 0 | AE75: =$AD75+ROW()*0.000000001 -> 7.5e-08 | AF75: =IF($J75="Yes","A","")&IF($L75="Yes","B","")&IF($N75="Yes","C","")
B76: R0072 | C76: Program Manager | D76: Ampol Customer | E76: EGI Customer | F76: AU | G76: Vacant, hire planned | H76: 1 | I76: 0.3049 | J76: No | L76: No | N76: No | P76: 0.3049 | Q76: =IF(AND($J76="Yes",$G76<>"Vendor day rates"),$I76-0.4*$P76,0) -> 0 | R76: =IFERROR(MATCH($K76,MonthList,0),0) -> 0 | S76: =IF(OR($J76<>"Yes",$K76=""),0,$Q76*MAX(0,7-$R76)/12) -> 0 | T76: =IF(OR($J76<>"Yes",$K76=""),0,$Q76*IF($R76<=7,12,19-$R76)/12) -> 0 | U76: =IF(AND($L76="Yes",$G76<>"Vendor day rates"),$I76-0.4*$P76,0) -> 0 | V76: =IFERROR(MATCH($M76,MonthList,0),0) -> 0 | W76: =IF(OR($L76<>"Yes",$M76=""),0,$U76*MAX(0,7-$V76)/12) -> 0 | X76: =IF(OR($L76<>"Yes",$M76=""),0,$U76*IF($V76<=7,12,19-$V76)/12) -> 0 | Y76: =IF(AND($N76="Yes",$G76<>"Vendor day rates"),$I76-0.4*$P76,0) -> 0 | Z76: =IFERROR(MATCH($O76,MonthList,0),0) -> 0 | AA76: =IF(OR($N76<>"Yes",$O76=""),0,$Y76*MAX(0,7-$Z76)/12) -> 0 | AB76: =IF(OR($N76<>"Yes",$O76=""),0,$Y76*IF($Z76<=7,12,19-$Z76)/12) -> 0 | AC76: =IF(OR($J76="Yes",$L76="Yes",$N76="Yes"),"Yes","No") -> No | AD76: =MAX($Q76,$U76,$Y76) -> 0 | AE76: =$AD76+ROW()*0.000000001 -> 7.6e-08 | AF76: =IF($J76="Yes","A","")&IF($L76="Yes","B","")&IF($N76="Yes","C","")
B77: R0073 | C77: Delivery Manager | D77: Ampol Customer | E77: Delivery Manager | F77: AU | G77: Filled | H77: 1 | I77: 0.3049 | J77: No | L77: No | N77: No | P77: 0.3049 | Q77: =IF(AND($J77="Yes",$G77<>"Vendor day rates"),$I77-0.4*$P77,0) -> 0 | R77: =IFERROR(MATCH($K77,MonthList,0),0) -> 0 | S77: =IF(OR($J77<>"Yes",$K77=""),0,$Q77*MAX(0,7-$R77)/12) -> 0 | T77: =IF(OR($J77<>"Yes",$K77=""),0,$Q77*IF($R77<=7,12,19-$R77)/12) -> 0 | U77: =IF(AND($L77="Yes",$G77<>"Vendor day rates"),$I77-0.4*$P77,0) -> 0 | V77: =IFERROR(MATCH($M77,MonthList,0),0) -> 0 | W77: =IF(OR($L77<>"Yes",$M77=""),0,$U77*MAX(0,7-$V77)/12) -> 0 | X77: =IF(OR($L77<>"Yes",$M77=""),0,$U77*IF($V77<=7,12,19-$V77)/12) -> 0 | Y77: =IF(AND($N77="Yes",$G77<>"Vendor day rates"),$I77-0.4*$P77,0) -> 0 | Z77: =IFERROR(MATCH($O77,MonthList,0),0) -> 0 | AA77: =IF(OR($N77<>"Yes",$O77=""),0,$Y77*MAX(0,7-$Z77)/12) -> 0 | AB77: =IF(OR($N77<>"Yes",$O77=""),0,$Y77*IF($Z77<=7,12,19-$Z77)/12) -> 0 | AC77: =IF(OR($J77="Yes",$L77="Yes",$N77="Yes"),"Yes","No") -> No | AD77: =MAX($Q77,$U77,$Y77) -> 0 | AE77: =$AD77+ROW()*0.000000001 -> 7.7e-08 | AF77: =IF($J77="Yes","A","")&IF($L77="Yes","B","")&IF($N77="Yes","C","")
B78: R0074 | C78: Design Manager | D78: Z ENERGY (DIGITAL) | E78: Z App and Web | F78: NZ | G78: Filled | H78: 1 | I78: 0.2092 | J78: No | L78: No | N78: No | P78: 0.2092 | Q78: =IF(AND($J78="Yes",$G78<>"Vendor day rates"),$I78-0.4*$P78,0) -> 0 | R78: =IFERROR(MATCH($K78,MonthList,0),0) -> 0 | S78: =IF(OR($J78<>"Yes",$K78=""),0,$Q78*MAX(0,7-$R78)/12) -> 0 | T78: =IF(OR($J78<>"Yes",$K78=""),0,$Q78*IF($R78<=7,12,19-$R78)/12) -> 0 | U78: =IF(AND($L78="Yes",$G78<>"Vendor day rates"),$I78-0.4*$P78,0) -> 0 | V78: =IFERROR(MATCH($M78,MonthList,0),0) -> 0 | W78: =IF(OR($L78<>"Yes",$M78=""),0,$U78*MAX(0,7-$V78)/12) -> 0 | X78: =IF(OR($L78<>"Yes",$M78=""),0,$U78*IF($V78<=7,12,19-$V78)/12) -> 0 | Y78: =IF(AND($N78="Yes",$G78<>"Vendor day rates"),$I78-0.4*$P78,0) -> 0 | Z78: =IFERROR(MATCH($O78,MonthList,0),0) -> 0 | AA78: =IF(OR($N78<>"Yes",$O78=""),0,$Y78*MAX(0,7-$Z78)/12) -> 0 | AB78: =IF(OR($N78<>"Yes",$O78=""),0,$Y78*IF($Z78<=7,12,19-$Z78)/12) -> 0 | AC78: =IF(OR($J78="Yes",$L78="Yes",$N78="Yes"),"Yes","No") -> No | AD78: =MAX($Q78,$U78,$Y78) -> 0 | AE78: =$AD78+ROW()*0.000000001 -> 7.8e-08 | AF78: =IF($J78="Yes","A","")&IF($L78="Yes","B","")&IF($N78="Yes","C","")
B79: R0075 | C79: Technology Manager - Digital | D79: Ampol Customer | E79: Technology Manager | F79: AU | G79: Filled | H79: 1 | I79: 0.3011 | J79: No | L79: No | N79: No | P79: 0.3011 | Q79: =IF(AND($J79="Yes",$G79<>"Vendor day rates"),$I79-0.4*$P79,0) -> 0 | R79: =IFERROR(MATCH($K79,MonthList,0),0) -> 0 | S79: =IF(OR($J79<>"Yes",$K79=""),0,$Q79*MAX(0,7-$R79)/12) -> 0 | T79: =IF(OR($J79<>"Yes",$K79=""),0,$Q79*IF($R79<=7,12,19-$R79)/12) -> 0 | U79: =IF(AND($L79="Yes",$G79<>"Vendor day rates"),$I79-0.4*$P79,0) -> 0 | V79: =IFERROR(MATCH($M79,MonthList,0),0) -> 0 | W79: =IF(OR($L79<>"Yes",$M79=""),0,$U79*MAX(0,7-$V79)/12) -> 0 | X79: =IF(OR($L79<>"Yes",$M79=""),0,$U79*IF($V79<=7,12,19-$V79)/12) -> 0 | Y79: =IF(AND($N79="Yes",$G79<>"Vendor day rates"),$I79-0.4*$P79,0) -> 0 | Z79: =IFERROR(MATCH($O79,MonthList,0),0) -> 0 | AA79: =IF(OR($N79<>"Yes",$O79=""),0,$Y79*MAX(0,7-$Z79)/12) -> 0 | AB79: =IF(OR($N79<>"Yes",$O79=""),0,$Y79*IF($Z79<=7,12,19-$Z79)/12) -> 0 | AC79: =IF(OR($J79="Yes",$L79="Yes",$N79="Yes"),"Yes","No") -> No | AD79: =MAX($Q79,$U79,$Y79) -> 0 | AE79: =$AD79+ROW()*0.000000001 -> 7.9e-08 | AF79: =IF($J79="Yes","A","")&IF($L79="Yes","B","")&IF($N79="Yes","C","")
B80: R0076 | C80: Principal Engineer | D80: EGI Integration | E80: EGI Customer | F80: AU | G80: Filled | H80: 1 | I80: 0.3049 | J80: No | L80: No | N80: No | P80: 0.3049 | Q80: =IF(AND($J80="Yes",$G80<>"Vendor day rates"),$I80-0.4*$P80,0) -> 0 | R80: =IFERROR(MATCH($K80,MonthList,0),0) -> 0 | S80: =IF(OR($J80<>"Yes",$K80=""),0,$Q80*MAX(0,7-$R80)/12) -> 0 | T80: =IF(OR($J80<>"Yes",$K80=""),0,$Q80*IF($R80<=7,12,19-$R80)/12) -> 0 | U80: =IF(AND($L80="Yes",$G80<>"Vendor day rates"),$I80-0.4*$P80,0) -> 0 | V80: =IFERROR(MATCH($M80,MonthList,0),0) -> 0 | W80: =IF(OR($L80<>"Yes",$M80=""),0,$U80*MAX(0,7-$V80)/12) -> 0 | X80: =IF(OR($L80<>"Yes",$M80=""),0,$U80*IF($V80<=7,12,19-$V80)/12) -> 0 | Y80: =IF(AND($N80="Yes",$G80<>"Vendor day rates"),$I80-0.4*$P80,0) -> 0 | Z80: =IFERROR(MATCH($O80,MonthList,0),0) -> 0 | AA80: =IF(OR($N80<>"Yes",$O80=""),0,$Y80*MAX(0,7-$Z80)/12) -> 0 | AB80: =IF(OR($N80<>"Yes",$O80=""),0,$Y80*IF($Z80<=7,12,19-$Z80)/12) -> 0 | AC80: =IF(OR($J80="Yes",$L80="Yes",$N80="Yes"),"Yes","No") -> No | AD80: =MAX($Q80,$U80,$Y80) -> 0 | AE80: =$AD80+ROW()*0.000000001 -> 8e-08 | AF80: =IF($J80="Yes","A","")&IF($L80="Yes","B","")&IF($N80="Yes","C","")
B81: R0077 | C81: Technology Manager, Engineering | D81: Ampol Customer | E81: Technology Manager | F81: AU | G81: Vacant, hire planned | H81: 1 | I81: 0.3049 | J81: No | L81: No | N81: No | P81: 0.3049 | Q81: =IF(AND($J81="Yes",$G81<>"Vendor day rates"),$I81-0.4*$P81,0) -> 0 | R81: =IFERROR(MATCH($K81,MonthList,0),0) -> 0 | S81: =IF(OR($J81<>"Yes",$K81=""),0,$Q81*MAX(0,7-$R81)/12) -> 0 | T81: =IF(OR($J81<>"Yes",$K81=""),0,$Q81*IF($R81<=7,12,19-$R81)/12) -> 0 | U81: =IF(AND($L81="Yes",$G81<>"Vendor day rates"),$I81-0.4*$P81,0) -> 0 | V81: =IFERROR(MATCH($M81,MonthList,0),0) -> 0 | W81: =IF(OR($L81<>"Yes",$M81=""),0,$U81*MAX(0,7-$V81)/12) -> 0 | X81: =IF(OR($L81<>"Yes",$M81=""),0,$U81*IF($V81<=7,12,19-$V81)/12) -> 0 | Y81: =IF(AND($N81="Yes",$G81<>"Vendor day rates"),$I81-0.4*$P81,0) -> 0 | Z81: =IFERROR(MATCH($O81,MonthList,0),0) -> 0 | AA81: =IF(OR($N81<>"Yes",$O81=""),0,$Y81*MAX(0,7-$Z81)/12) -> 0 | AB81: =IF(OR($N81<>"Yes",$O81=""),0,$Y81*IF($Z81<=7,12,19-$Z81)/12) -> 0 | AC81: =IF(OR($J81="Yes",$L81="Yes",$N81="Yes"),"Yes","No") -> No | AD81: =MAX($Q81,$U81,$Y81) -> 0 | AE81: =$AD81+ROW()*0.000000001 -> 8.1e-08 | AF81: =IF($J81="Yes","A","")&IF($L81="Yes","B","")&IF($N81="Yes","C","")
... B105: R0101 | C105: Program Manager - CTRM | D105: Commercial Fuels | E105: CTRM | F105: AU | G105: Filled | H105: 1 | I105: 0.3237 | J105: No | L105: No | N105: No | P105: 0.3237 | Q105: =IF(AND($J105="Yes",$G105<>"Vendor day rates"),$I105-0.4*$P105,0) -> 0 | R105: =IFERROR(MATCH($K105,MonthList,0),0) -> 0 | S105: =IF(OR($J105<>"Yes",$K105=""),0,$Q105*MAX(0,7-$R105)/12) -> 0 | T105: =IF(OR($J105<>"Yes",$K105=""),0,$Q105*IF($R105<=7,12,19-$R105)/12) -> 0 | U105: =IF(AND($L105="Yes",$G105<>"Vendor day rates"),$I105-0.4*$P105,0) -> 0 | V105: =IFERROR(MATCH($M105,MonthList,0),0) -> 0 | W105: =IF(OR($L105<>"Yes",$M105=""),0,$U105*MAX(0,7-$V105)/12) -> 0 | X105: =IF(OR($L105<>"Yes",$M105=""),0,$U105*IF($V105<=7,12,19-$V105)/12) -> 0 | Y105: =IF(AND($N105="Yes",$G105<>"Vendor day rates"),$I105-0.4*$P105,0) -> 0 | Z105: =IFERROR(MATCH($O105,MonthList,0),0) -> 0 | AA105: =IF(OR($N105<>"Yes",$O105=""),0,$Y105*MAX(0,7-$Z105)/12) -> 0 | AB105: =IF(OR($N105<>"Yes",$O105=""),0,$Y105*IF($Z105<=7,12,19-$Z105)/12) -> 0 | AC105: =IF(OR($J105="Yes",$L105="Yes",$N105="Yes"),"Yes","No") -> No | AD105: =MAX($Q105,$U105,$Y105) -> 0 | AE105: =$AD105+ROW()*0.000000001 -> 1.05e-07 | AF105: =IF($J105="Yes","A","")&IF($L105="Yes","B","")&IF($N105="Yes","C","")
B106: R0102 | C106: Domain Architect - Group Functions | E106: Architecture | F106: NZ | G106: Filled | H106: 1 | I106: 0.2427 | J106: No | L106: No | N106: No | P106: 0.2427 | Q106: =IF(AND($J106="Yes",$G106<>"Vendor day rates"),$I106-0.4*$P106,0) -> 0 | R106: =IFERROR(MATCH($K106,MonthList,0),0) -> 0 | S106: =IF(OR($J106<>"Yes",$K106=""),0,$Q106*MAX(0,7-$R106)/12) -> 0 | T106: =IF(OR($J106<>"Yes",$K106=""),0,$Q106*IF($R106<=7,12,19-$R106)/12) -> 0 | U106: =IF(AND($L106="Yes",$G106<>"Vendor day rates"),$I106-0.4*$P106,0) -> 0 | V106: =IFERROR(MATCH($M106,MonthList,0),0) -> 0 | W106: =IF(OR($L106<>"Yes",$M106=""),0,$U106*MAX(0,7-$V106)/12) -> 0 | X106: =IF(OR($L106<>"Yes",$M106=""),0,$U106*IF($V106<=7,12,19-$V106)/12) -> 0 | Y106: =IF(AND($N106="Yes",$G106<>"Vendor day rates"),$I106-0.4*$P106,0) -> 0 | Z106: =IFERROR(MATCH($O106,MonthList,0),0) -> 0 | AA106: =IF(OR($N106<>"Yes",$O106=""),0,$Y106*MAX(0,7-$Z106)/12) -> 0 | AB106: =IF(OR($N106<>"Yes",$O106=""),0,$Y106*IF($Z106<=7,12,19-$Z106)/12) -> 0 | AC106: =IF(OR($J106="Yes",$L106="Yes",$N106="Yes"),"Yes","No") -> No | AD106: =MAX($Q106,$U106,$Y106) -> 0 | AE106: =$AD106+ROW()*0.000000001 -> 1.06e-07 | AF106: =IF($J106="Yes","A","")&IF($L106="Yes","B","")&IF($N106="Yes","C","")
B107: R0103 | C107: Enterprise Architect | E107: Architecture | F107: NZ | G107: Filled | H107: 1 | I107: 0.2143 | J107: No | L107: No | N107: No | P107: 0.2143 | Q107: =IF(AND($J107="Yes",$G107<>"Vendor day rates"),$I107-0.4*$P107,0) -> 0 | R107: =IFERROR(MATCH($K107,MonthList,0),0) -> 0 | S107: =IF(OR($J107<>"Yes",$K107=""),0,$Q107*MAX(0,7-$R107)/12) -> 0 | T107: =IF(OR($J107<>"Yes",$K107=""),0,$Q107*IF($R107<=7,12,19-$R107)/12) -> 0 | U107: =IF(AND($L107="Yes",$G107<>"Vendor day rates"),$I107-0.4*$P107,0) -> 0 | V107: =IFERROR(MATCH($M107,MonthList,0),0) -> 0 | W107: =IF(OR($L107<>"Yes",$M107=""),0,$U107*MAX(0,7-$V107)/12) -> 0 | X107: =IF(OR($L107<>"Yes",$M107=""),0,$U107*IF($V107<=7,12,19-$V107)/12) -> 0 | Y107: =IF(AND($N107="Yes",$G107<>"Vendor day rates"),$I107-0.4*$P107,0) -> 0 | Z107: =IFERROR(MATCH($O107,MonthList,0),0) -> 0 | AA107: =IF(OR($N107<>"Yes",$O107=""),0,$Y107*MAX(0,7-$Z107)/12) -> 0 | AB107: =IF(OR($N107<>"Yes",$O107=""),0,$Y107*IF($Z107<=7,12,19-$Z107)/12) -> 0 | AC107: =IF(OR($J107="Yes",$L107="Yes",$N107="Yes"),"Yes","No") -> No | AD107: =MAX($Q107,$U107,$Y107) -> 0 | AE107: =$AD107+ROW()*0.000000001 -> 1.07e-07 | AF107: =IF($J107="Yes","A","")&IF($L107="Yes","B","")&IF($N107="Yes","C","")
B108: R0104 | C108: Domain Architect - CFE & Infrastru | E108: Architecture | F108: NZ | G108: Filled | H108: 1 | I108: 0.2369 | J108: No | L108: No | N108: No | P108: 0.2369 | Q108: =IF(AND($J108="Yes",$G108<>"Vendor day rates"),$I108-0.4*$P108,0) -> 0 | R108: =IFERROR(MATCH($K108,MonthList,0),0) -> 0 | S108: =IF(OR($J108<>"Yes",$K108=""),0,$Q108*MAX(0,7-$R108)/12) -> 0 | T108: =IF(OR($J108<>"Yes",$K108=""),0,$Q108*IF($R108<=7,12,19-$R108)/12) -> 0 | U108: =IF(AND($L108="Yes",$G108<>"Vendor day rates"),$I108-0.4*$P108,0) -> 0 | V108: =IFERROR(MATCH($M108,MonthList,0),0) -> 0 | W108: =IF(OR($L108<>"Yes",$M108=""),0,$U108*MAX(0,7-$V108)/12) -> 0 | X108: =IF(OR($L108<>"Yes",$M108=""),0,$U108*IF($V108<=7,12,19-$V108)/12) -> 0 | Y108: =IF(AND($N108="Yes",$G108<>"Vendor day rates"),$I108-0.4*$P108,0) -> 0 | Z108: =IFERROR(MATCH($O108,MonthList,0),0) -> 0 | AA108: =IF(OR($N108<>"Yes",$O108=""),0,$Y108*MAX(0,7-$Z108)/12) -> 0 | AB108: =IF(OR($N108<>"Yes",$O108=""),0,$Y108*IF($Z108<=7,12,19-$Z108)/12) -> 0 | AC108: =IF(OR($J108="Yes",$L108="Yes",$N108="Yes"),"Yes","No") -> No | AD108: =MAX($Q108,$U108,$Y108) -> 0 | AE108: =$AD108+ROW()*0.000000001 -> 1.08e-07 | AF108: =IF($J108="Yes","A","")&IF($L108="Yes","B","")&IF($N108="Yes","C","")
B109: R0105 | C109: Technology Manager, Enterprise Too | D109: TDD | E109: Technology Manager | F109: AU | G109: Filled | H109: 1 | I109: 0.2758 | J109: No | L109: No | N109: No | P109: 0.2758 | Q109: =IF(AND($J109="Yes",$G109<>"Vendor day rates"),$I109-0.4*$P109,0) -> 0 | R109: =IFERROR(MATCH($K109,MonthList,0),0) -> 0 | S109: =IF(OR($J109<>"Yes",$K109=""),0,$Q109*MAX(0,7-$R109)/12) -> 0 | T109: =IF(OR($J109<>"Yes",$K109=""),0,$Q109*IF($R109<=7,12,19-$R109)/12) -> 0 | U109: =IF(AND($L109="Yes",$G109<>"Vendor day rates"),$I109-0.4*$P109,0) -> 0 | V109: =IFERROR(MATCH($M109,MonthList,0),0) -> 0 | W109: =IF(OR($L109<>"Yes",$M109=""),0,$U109*MAX(0,7-$V109)/12) -> 0 | X109: =IF(OR($L109<>"Yes",$M109=""),0,$U109*IF($V109<=7,12,19-$V109)/12) -> 0 | Y109: =IF(AND($N109="Yes",$G109<>"Vendor day rates"),$I109-0.4*$P109,0) -> 0 | Z109: =IFERROR(MATCH($O109,MonthList,0),0) -> 0 | AA109: =IF(OR($N109<>"Yes",$O109=""),0,$Y109*MAX(0,7-$Z109)/12) -> 0 | AB109: =IF(OR($N109<>"Yes",$O109=""),0,$Y109*IF($Z109<=7,12,19-$Z109)/12) -> 0 | AC109: =IF(OR($J109="Yes",$L109="Yes",$N109="Yes"),"Yes","No") -> No | AD109: =MAX($Q109,$U109,$Y109) -> 0 | AE109: =$AD109+ROW()*0.000000001 -> 1.09e-07 | AF109: =IF($J109="Yes","A","")&IF($L109="Yes","B","")&IF($N109="Yes","C","")
B110: R0106 | C110: Technology Manager – DevOps and Qu | D110: TDD | E110: Technology Manager | F110: NZ | G110: Filled | H110: 1 | I110: 0.2215 | J110: No | L110: No | N110: No | P110: 0.2215 | Q110: =IF(AND($J110="Yes",$G110<>"Vendor day rates"),$I110-0.4*$P110,0) -> 0 | R110: =IFERROR(MATCH($K110,MonthList,0),0) -> 0 | S110: =IF(OR($J110<>"Yes",$K110=""),0,$Q110*MAX(0,7-$R110)/12) -> 0 | T110: =IF(OR($J110<>"Yes",$K110=""),0,$Q110*IF($R110<=7,12,19-$R110)/12) -> 0 | U110: =IF(AND($L110="Yes",$G110<>"Vendor day rates"),$I110-0.4*$P110,0) -> 0 | V110: =IFERROR(MATCH($M110,MonthList,0),0) -> 0 | W110: =IF(OR($L110<>"Yes",$M110=""),0,$U110*MAX(0,7-$V110)/12) -> 0 | X110: =IF(OR($L110<>"Yes",$M110=""),0,$U110*IF($V110<=7,12,19-$V110)/12) -> 0 | Y110: =IF(AND($N110="Yes",$G110<>"Vendor day rates"),$I110-0.4*$P110,0) -> 0 | Z110: =IFERROR(MATCH($O110,MonthList,0),0) -> 0 | AA110: =IF(OR($N110<>"Yes",$O110=""),0,$Y110*MAX(0,7-$Z110)/12) -> 0 | AB110: =IF(OR($N110<>"Yes",$O110=""),0,$Y110*IF($Z110<=7,12,19-$Z110)/12) -> 0 | AC110: =IF(OR($J110="Yes",$L110="Yes",$N110="Yes"),"Yes","No") -> No | AD110: =MAX($Q110,$U110,$Y110) -> 0 | AE110: =$AD110+ROW()*0.000000001 -> 1.1e-07 | AF110: =IF($J110="Yes","A","")&IF($L110="Yes","B","")&IF($N110="Yes","C","")
B111: R0107 | C111: Technology Manager, Engineering | D111: Z | E111: Technology Manager | F111: NZ | G111: Filled | H111: 1 | I111: 0.2365 | J111: No | L111: No | N111: No | P111: 0.2365 | Q111: =IF(AND($J111="Yes",$G111<>"Vendor day rates"),$I111-0.4*$P111,0) -> 0 | R111: =IFERROR(MATCH($K111,MonthList,0),0) -> 0 | S111: =IF(OR($J111<>"Yes",$K111=""),0,$Q111*MAX(0,7-$R111)/12) -> 0 | T111: =IF(OR($J111<>"Yes",$K111=""),0,$Q111*IF($R111<=7,12,19-$R111)/12) -> 0 | U111: =IF(AND($L111="Yes",$G111<>"Vendor day rates"),$I111-0.4*$P111,0) -> 0 | V111: =IFERROR(MATCH($M111,MonthList,0),0) -> 0 | W111: =IF(OR($L111<>"Yes",$M111=""),0,$U111*MAX(0,7-$V111)/12) -> 0 | X111: =IF(OR($L111<>"Yes",$M111=""),0,$U111*IF($V111<=7,12,19-$V111)/12) -> 0 | Y111: =IF(AND($N111="Yes",$G111<>"Vendor day rates"),$I111-0.4*$P111,0) -> 0 | Z111: =IFERROR(MATCH($O111,MonthList,0),0) -> 0 | AA111: =IF(OR($N111<>"Yes",$O111=""),0,$Y111*MAX(0,7-$Z111)/12) -> 0 | AB111: =IF(OR($N111<>"Yes",$O111=""),0,$Y111*IF($Z111<=7,12,19-$Z111)/12) -> 0 | AC111: =IF(OR($J111="Yes",$L111="Yes",$N111="Yes"),"Yes","No") -> No | AD111: =MAX($Q111,$U111,$Y111) -> 0 | AE111: =$AD111+ROW()*0.000000001 -> 1.11e-07 | AF111: =IF($J111="Yes","A","")&IF($L111="Yes","B","")&IF($N111="Yes","C","")
B112: R0108 | C112: Technology Manager, Data | D112: Z | E112: Technology Manager | F112: AU | G112: Filled | H112: 1 | I112: 0.2542 | J112: No | L112: No | N112: No | P112: 0.2542 | Q112: =IF(AND($J112="Yes",$G112<>"Vendor day rates"),$I112-0.4*$P112,0) -> 0 | R112: =IFERROR(MATCH($K112,MonthList,0),0) -> 0 | S112: =IF(OR($J112<>"Yes",$K112=""),0,$Q112*MAX(0,7-$R112)/12) -> 0 | T112: =IF(OR($J112<>"Yes",$K112=""),0,$Q112*IF($R112<=7,12,19-$R112)/12) -> 0 | U112: =IF(AND($L112="Yes",$G112<>"Vendor day rates"),$I112-0.4*$P112,0) -> 0 | V112: =IFERROR(MATCH($M112,MonthList,0),0) -> 0 | W112: =IF(OR($L112<>"Yes",$M112=""),0,$U112*MAX(0,7-$V112)/12) -> 0 | X112: =IF(OR($L112<>"Yes",$M112=""),0,$U112*IF($V112<=7,12,19-$V112)/12) -> 0 | Y112: =IF(AND($N112="Yes",$G112<>"Vendor day rates"),$I112-0.4*$P112,0) -> 0 | Z112: =IFERROR(MATCH($O112,MonthList,0),0) -> 0 | AA112: =IF(OR($N112<>"Yes",$O112=""),0,$Y112*MAX(0,7-$Z112)/12) -> 0 | AB112: =IF(OR($N112<>"Yes",$O112=""),0,$Y112*IF($Z112<=7,12,19-$Z112)/12) -> 0 | AC112: =IF(OR($J112="Yes",$L112="Yes",$N112="Yes"),"Yes","No") -> No | AD112: =MAX($Q112,$U112,$Y112) -> 0 | AE112: =$AD112+ROW()*0.000000001 -> 1.12e-07 | AF112: =IF($J112="Yes","A","")&IF($L112="Yes","B","")&IF($N112="Yes","C","")
B113: R0109 | C113: Delivery Excellence Manager | D113: NA | E113: Transformation | F113: AU | G113: Vacant, hire planned | H113: 1 | I113: 0.2758 | J113: No | L113: No | N113: No | P113: 0.2758 | Q113: =IF(AND($J113="Yes",$G113<>"Vendor day rates"),$I113-0.4*$P113,0) -> 0 | R113: =IFERROR(MATCH($K113,MonthList,0),0) -> 0 | S113: =IF(OR($J113<>"Yes",$K113=""),0,$Q113*MAX(0,7-$R113)/12) -> 0 | T113: =IF(OR($J113<>"Yes",$K113=""),0,$Q113*IF($R113<=7,12,19-$R113)/12) -> 0 | U113: =IF(AND($L113="Yes",$G113<>"Vendor day rates"),$I113-0.4*$P113,0) -> 0 | V113: =IFERROR(MATCH($M113,MonthList,0),0) -> 0 | W113: =IF(OR($L113<>"Yes",$M113=""),0,$U113*MAX(0,7-$V113)/12) -> 0 | X113: =IF(OR($L113<>"Yes",$M113=""),0,$U113*IF($V113<=7,12,19-$V113)/12) -> 0 | Y113: =IF(AND($N113="Yes",$G113<>"Vendor day rates"),$I113-0.4*$P113,0) -> 0 | Z113: =IFERROR(MATCH($O113,MonthList,0),0) -> 0 | AA113: =IF(OR($N113<>"Yes",$O113=""),0,$Y113*MAX(0,7-$Z113)/12) -> 0 | AB113: =IF(OR($N113<>"Yes",$O113=""),0,$Y113*IF($Z113<=7,12,19-$Z113)/12) -> 0 | AC113: =IF(OR($J113="Yes",$L113="Yes",$N113="Yes"),"Yes","No") -> No | AD113: =MAX($Q113,$U113,$Y113) -> 0 | AE113: =$AD113+ROW()*0.000000001 -> 1.13e-07 | AF113: =IF($J113="Yes","A","")&IF($L113="Yes","B","")&IF($N113="Yes","C","")
B114: R0110 | C114: Enterprise Architect | E114: Architecture | F114: AU | G114: Held today | H114: 1 | I114: 0 | J114: No | L114: No | N114: No | P114: 0.2758 | Q114: =IF(AND($J114="Yes",$G114<>"Vendor day rates"),$I114-0.4*$P114,0) -> 0 | R114: =IFERROR(MATCH($K114,MonthList,0),0) -> 0 | S114: =IF(OR($J114<>"Yes",$K114=""),0,$Q114*MAX(0,7-$R114)/12) -> 0 | T114: =IF(OR($J114<>"Yes",$K114=""),0,$Q114*IF($R114<=7,12,19-$R114)/12) -> 0 | U114: =IF(AND($L114="Yes",$G114<>"Vendor day rates"),$I114-0.4*$P114,0) -> 0 | V114: =IFERROR(MATCH($M114,MonthList,0),0) -> 0 | W114: =IF(OR($L114<>"Yes",$M114=""),0,$U114*MAX(0,7-$V114)/12) -> 0 | X114: =IF(OR($L114<>"Yes",$M114=""),0,$U114*IF($V114<=7,12,19-$V114)/12) -> 0 | Y114: =IF(AND($N114="Yes",$G114<>"Vendor day rates"),$I114-0.4*$P114,0) -> 0 | Z114: =IFERROR(MATCH($O114,MonthList,0),0) -> 0 | AA114: =IF(OR($N114<>"Yes",$O114=""),0,$Y114*MAX(0,7-$Z114)/12) -> 0 | AB114: =IF(OR($N114<>"Yes",$O114=""),0,$Y114*IF($Z114<=7,12,19-$Z114)/12) -> 0 | AC114: =IF(OR($J114="Yes",$L114="Yes",$N114="Yes"),"Yes","No") -> No | AD114: =MAX($Q114,$U114,$Y114) -> 0 | AE114: =$AD114+ROW()*0.000000001 -> 1.14e-07 | AF114: =IF($J114="Yes","A","")&IF($L114="Yes","B","")&IF($N114="Yes","C","")
B115: R0111 | C115: AI Capability Lead | E115: Technology Strategy & AI Cap | F115: AU | G115: Vacant, hire planned | H115: 1 | I115: 0.2758 | J115: No | L115: No | N115: No | P115: 0.2758 | Q115: =IF(AND($J115="Yes",$G115<>"Vendor day rates"),$I115-0.4*$P115,0) -> 0 | R115: =IFERROR(MATCH($K115,MonthList,0),0) -> 0 | S115: =IF(OR($J115<>"Yes",$K115=""),0,$Q115*MAX(0,7-$R115)/12) -> 0 | T115: =IF(OR($J115<>"Yes",$K115=""),0,$Q115*IF($R115<=7,12,19-$R115)/12) -> 0 | U115: =IF(AND($L115="Yes",$G115<>"Vendor day rates"),$I115-0.4*$P115,0) -> 0 | V115: =IFERROR(MATCH($M115,MonthList,0),0) -> 0 | W115: =IF(OR($L115<>"Yes",$M115=""),0,$U115*MAX(0,7-$V115)/12) -> 0 | X115: =IF(OR($L115<>"Yes",$M115=""),0,$U115*IF($V115<=7,12,19-$V115)/12) -> 0 | Y115: =IF(AND($N115="Yes",$G115<>"Vendor day rates"),$I115-0.4*$P115,0) -> 0 | Z115: =IFERROR(MATCH($O115,MonthList,0),0) -> 0 | AA115: =IF(OR($N115<>"Yes",$O115=""),0,$Y115*MAX(0,7-$Z115)/12) -> 0 | AB115: =IF(OR($N115<>"Yes",$O115=""),0,$Y115*IF($Z115<=7,12,19-$Z115)/12) -> 0 | AC115: =IF(OR($J115="Yes",$L115="Yes",$N115="Yes"),"Yes","No") -> No | AD115: =MAX($Q115,$U115,$Y115) -> 0 | AE115: =$AD115+ROW()*0.000000001 -> 1.15e-07 | AF115: =IF($J115="Yes","A","")&IF($L115="Yes","B","")&IF($N115="Yes","C","")
B116: R0112 | C116: Technology Manager, Integration & | D116: TDD | E116: Technology Manager | F116: NZ | G116: Filled | H116: 1 | I116: 0.2292 | J116: No | L116: No | N116: No | P116: 0.2292 | Q116: =IF(AND($J116="Yes",$G116<>"Vendor day rates"),$I116-0.4*$P116,0) -> 0 | R116: =IFERROR(MATCH($K116,MonthList,0),0) -> 0 | S116: =IF(OR($J116<>"Yes",$K116=""),0,$Q116*MAX(0,7-$R116)/12) -> 0 | T116: =IF(OR($J116<>"Yes",$K116=""),0,$Q116*IF($R116<=7,12,19-$R116)/12) -> 0 | U116: =IF(AND($L116="Yes",$G116<>"Vendor day rates"),$I116-0.4*$P116,0) -> 0 | V116: =IFERROR(MATCH($M116,MonthList,0),0) -> 0 | W116: =IF(OR($L116<>"Yes",$M116=""),0,$U116*MAX(0,7-$V116)/12) -> 0 | X116: =IF(OR($L116<>"Yes",$M116=""),0,$U116*IF($V116<=7,12,19-$V116)/12) -> 0 | Y116: =IF(AND($N116="Yes",$G116<>"Vendor day rates"),$I116-0.4*$P116,0) -> 0 | Z116: =IFERROR(MATCH($O116,MonthList,0),0) -> 0 | AA116: =IF(OR($N116<>"Yes",$O116=""),0,$Y116*MAX(0,7-$Z116)/12) -> 0 | AB116: =IF(OR($N116<>"Yes",$O116=""),0,$Y116*IF($Z116<=7,12,19-$Z116)/12) -> 0 | AC116: =IF(OR($J116="Yes",$L116="Yes",$N116="Yes"),"Yes","No") -> No | AD116: =MAX($Q116,$U116,$Y116) -> 0 | AE116: =$AD116+ROW()*0.000000001 -> 1.16e-07 | AF116: =IF($J116="Yes","A","")&IF($L116="Yes","B","")&IF($N116="Yes","C","")
B117: R0113 | C117: Delivery Manager | D117: TDD | E117: Delivery Manager | F117: AU | G117: Vacant, hire planned | H117: 1 | I117: 0.2758 | J117: No | L117: No | N117: No | P117: 0.2758 | Q117: =IF(AND($J117="Yes",$G117<>"Vendor day rates"),$I117-0.4*$P117,0) -> 0 | R117: =IFERROR(MATCH($K117,MonthList,0),0) -> 0 | S117: =IF(OR($J117<>"Yes",$K117=""),0,$Q117*MAX(0,7-$R117)/12) -> 0 | T117: =IF(OR($J117<>"Yes",$K117=""),0,$Q117*IF($R117<=7,12,19-$R117)/12) -> 0 | U117: =IF(AND($L117="Yes",$G117<>"Vendor day rates"),$I117-0.4*$P117,0) -> 0 | V117: =IFERROR(MATCH($M117,MonthList,0),0) -> 0 | W117: =IF(OR($L117<>"Yes",$M117=""),0,$U117*MAX(0,7-$V117)/12) -> 0 | X117: =IF(OR($L117<>"Yes",$M117=""),0,$U117*IF($V117<=7,12,19-$V117)/12) -> 0 | Y117: =IF(AND($N117="Yes",$G117<>"Vendor day rates"),$I117-0.4*$P117,0) -> 0 | Z117: =IFERROR(MATCH($O117,MonthList,0),0) -> 0 | AA117: =IF(OR($N117<>"Yes",$O117=""),0,$Y117*MAX(0,7-$Z117)/12) -> 0 | AB117: =IF(OR($N117<>"Yes",$O117=""),0,$Y117*IF($Z117<=7,12,19-$Z117)/12) -> 0 | AC117: =IF(OR($J117="Yes",$L117="Yes",$N117="Yes"),"Yes","No") -> No | AD117: =MAX($Q117,$U117,$Y117) -> 0 | AE117: =$AD117+ROW()*0.000000001 -> 1.17e-07 | AF117: =IF($J117="Yes","A","")&IF($L117="Yes","B","")&IF($N117="Yes","C","")
B118: R0114 | C118: Technology Manager – Cloud, Networ | D118: TDD | E118: Technology Manager | F118: AU | G118: Held today | H118: 1 | I118: 0 | J118: No | L118: No | N118: No | P118: 0.2758 | Q118: =IF(AND($J118="Yes",$G118<>"Vendor day rates"),$I118-0.4*$P118,0) -> 0 | R118: =IFERROR(MATCH($K118,MonthList,0),0) -> 0 | S118: =IF(OR($J118<>"Yes",$K118=""),0,$Q118*MAX(0,7-$R118)/12) -> 0 | T118: =IF(OR($J118<>"Yes",$K118=""),0,$Q118*IF($R118<=7,12,19-$R118)/12) -> 0 | U118: =IF(AND($L118="Yes",$G118<>"Vendor day rates"),$I118-0.4*$P118,0) -> 0 | V118: =IFERROR(MATCH($M118,MonthList,0),0) -> 0 | W118: =IF(OR($L118<>"Yes",$M118=""),0,$U118*MAX(0,7-$V118)/12) -> 0 | X118: =IF(OR($L118<>"Yes",$M118=""),0,$U118*IF($V118<=7,12,19-$V118)/12) -> 0 | Y118: =IF(AND($N118="Yes",$G118<>"Vendor day rates"),$I118-0.4*$P118,0) -> 0 | Z118: =IFERROR(MATCH($O118,MonthList,0),0) -> 0 | AA118: =IF(OR($N118<>"Yes",$O118=""),0,$Y118*MAX(0,7-$Z118)/12) -> 0 | AB118: =IF(OR($N118<>"Yes",$O118=""),0,$Y118*IF($Z118<=7,12,19-$Z118)/12) -> 0 | AC118: =IF(OR($J118="Yes",$L118="Yes",$N118="Yes"),"Yes","No") -> No | AD118: =MAX($Q118,$U118,$Y118) -> 0 | AE118: =$AD118+ROW()*0.000000001 -> 1.18e-07 | AF118: =IF($J118="Yes","A","")&IF($L118="Yes","B","")&IF($N118="Yes","C","")
B119: R0115 | C119: Technology Manager, Store Platform | D119: Retail | E119: Technology Manager | F119: AU | G119: Filled | H119: 1 | I119: 0.2578 | J119: No | L119: No | N119: No | P119: 0.2578 | Q119: =IF(AND($J119="Yes",$G119<>"Vendor day rates"),$I119-0.4*$P119,0) -> 0 | R119: =IFERROR(MATCH($K119,MonthList,0),0) -> 0 | S119: =IF(OR($J119<>"Yes",$K119=""),0,$Q119*MAX(0,7-$R119)/12) -> 0 | T119: =IF(OR($J119<>"Yes",$K119=""),0,$Q119*IF($R119<=7,12,19-$R119)/12) -> 0 | U119: =IF(AND($L119="Yes",$G119<>"Vendor day rates"),$I119-0.4*$P119,0) -> 0 | V119: =IFERROR(MATCH($M119,MonthList,0),0) -> 0 | W119: =IF(OR($L119<>"Yes",$M119=""),0,$U119*MAX(0,7-$V119)/12) -> 0 | X119: =IF(OR($L119<>"Yes",$M119=""),0,$U119*IF($V119<=7,12,19-$V119)/12) -> 0 | Y119: =IF(AND($N119="Yes",$G119<>"Vendor day rates"),$I119-0.4*$P119,0) -> 0 | Z119: =IFERROR(MATCH($O119,MonthList,0),0) -> 0 | AA119: =IF(OR($N119<>"Yes",$O119=""),0,$Y119*MAX(0,7-$Z119)/12) -> 0 | AB119: =IF(OR($N119<>"Yes",$O119=""),0,$Y119*IF($Z119<=7,12,19-$Z119)/12) -> 0 | AC119: =IF(OR($J119="Yes",$L119="Yes",$N119="Yes"),"Yes","No") -> No | AD119: =MAX($Q119,$U119,$Y119) -> 0 | AE119: =$AD119+ROW()*0.000000001 -> 1.19e-07 | AF119: =IF($J119="Yes","A","")&IF($L119="Yes","B","")&IF($N119="Yes","C","")
B120: R0116 | C120: Technology Manager, Site Systems | D120: Z | E120: Technology Manager | F120: NZ | G120: Filled | H120: 1 | I120: 0.2105 | J120: No | L120: No | N120: No | P120: 0.2105 | Q120: =IF(AND($J120="Yes",$G120<>"Vendor day rates"),$I120-0.4*$P120,0) -> 0 | R120: =IFERROR(MATCH($K120,MonthList,0),0) -> 0 | S120: =IF(OR($J120<>"Yes",$K120=""),0,$Q120*MAX(0,7-$R120)/12) -> 0 | T120: =IF(OR($J120<>"Yes",$K120=""),0,$Q120*IF($R120<=7,12,19-$R120)/12) -> 0 | U120: =IF(AND($L120="Yes",$G120<>"Vendor day rates"),$I120-0.4*$P120,0) -> 0 | V120: =IFERROR(MATCH($M120,MonthList,0),0) -> 0 | W120: =IF(OR($L120<>"Yes",$M120=""),0,$U120*MAX(0,7-$V120)/12) -> 0 | X120: =IF(OR($L120<>"Yes",$M120=""),0,$U120*IF($V120<=7,12,19-$V120)/12) -> 0 | Y120: =IF(AND($N120="Yes",$G120<>"Vendor day rates"),$I120-0.4*$P120,0) -> 0 | Z120: =IFERROR(MATCH($O120,MonthList,0),0) -> 0 | AA120: =IF(OR($N120<>"Yes",$O120=""),0,$Y120*MAX(0,7-$Z120)/12) -> 0 | AB120: =IF(OR($N120<>"Yes",$O120=""),0,$Y120*IF($Z120<=7,12,19-$Z120)/12) -> 0 | AC120: =IF(OR($J120="Yes",$L120="Yes",$N120="Yes"),"Yes","No") -> No | AD120: =MAX($Q120,$U120,$Y120) -> 0 | AE120: =$AD120+ROW()*0.000000001 -> 1.2e-07 | AF120: =IF($J120="Yes","A","")&IF($L120="Yes","B","")&IF($N120="Yes","C","")
B121: R0117 | C121: Delivery Manager | D121: Z | E121: Delivery Manager | F121: AU | G121: Vacant, hire planned | H121: 1 | I121: 0.2029 | J121: No | L121: No | N121: No | P121: 0.2029 | Q121: =IF(AND($J121="Yes",$G121<>"Vendor day rates"),$I121-0.4*$P121,0) -> 0 | R121: =IFERROR(MATCH($K121,MonthList,0),0) -> 0 | S121: =IF(OR($J121<>"Yes",$K121=""),0,$Q121*MAX(0,7-$R121)/12) -> 0 | T121: =IF(OR($J121<>"Yes",$K121=""),0,$Q121*IF($R121<=7,12,19-$R121)/12) -> 0 | U121: =IF(AND($L121="Yes",$G121<>"Vendor day rates"),$I121-0.4*$P121,0) -> 0 | V121: =IFERROR(MATCH($M121,MonthList,0),0) -> 0 | W121: =IF(OR($L121<>"Yes",$M121=""),0,$U121*MAX(0,7-$V121)/12) -> 0 | X121: =IF(OR($L121<>"Yes",$M121=""),0,$U121*IF($V121<=7,12,19-$V121)/12) -> 0 | Y121: =IF(AND($N121="Yes",$G121<>"Vendor day rates"),$I121-0.4*$P121,0) -> 0 | Z121: =IFERROR(MATCH($O121,MonthList,0),0) -> 0 | AA121: =IF(OR($N121<>"Yes",$O121=""),0,$Y121*MAX(0,7-$Z121)/12) -> 0 | AB121: =IF(OR($N121<>"Yes",$O121=""),0,$Y121*IF($Z121<=7,12,19-$Z121)/12) -> 0 | AC121: =IF(OR($J121="Yes",$L121="Yes",$N121="Yes"),"Yes","No") -> No | AD121: =MAX($Q121,$U121,$Y121) -> 0 | AE121: =$AD121+ROW()*0.000000001 -> 1.21e-07 | AF121: =IF($J121="Yes","A","")&IF($L121="Yes","B","")&IF($N121="Yes","C","")
B122: R0118 | C122: Delivery Assurance Manager | D122: NA | E122: Transformation | F122: AU | G122: Vacant, hire planned | H122: 1 | I122: 0.2758 | J122: No | L122: No | N122: No | P122: 0.2758 | Q122: =IF(AND($J122="Yes",$G122<>"Vendor day rates"),$I122-0.4*$P122,0) -> 0 | R122: =IFERROR(MATCH($K122,MonthList,0),0) -> 0 | S122: =IF(OR($J122<>"Yes",$K122=""),0,$Q122*MAX(0,7-$R122)/12) -> 0 | T122: =IF(OR($J122<>"Yes",$K122=""),0,$Q122*IF($R122<=7,12,19-$R122)/12) -> 0 | U122: =IF(AND($L122="Yes",$G122<>"Vendor day rates"),$I122-0.4*$P122,0) -> 0 | V122: =IFERROR(MATCH($M122,MonthList,0),0) -> 0 | W122: =IF(OR($L122<>"Yes",$M122=""),0,$U122*MAX(0,7-$V122)/12) -> 0 | X122: =IF(OR($L122<>"Yes",$M122=""),0,$U122*IF($V122<=7,12,19-$V122)/12) -> 0 | Y122: =IF(AND($N122="Yes",$G122<>"Vendor day rates"),$I122-0.4*$P122,0) -> 0 | Z122: =IFERROR(MATCH($O122,MonthList,0),0) -> 0 | AA122: =IF(OR($N122<>"Yes",$O122=""),0,$Y122*MAX(0,7-$Z122)/12) -> 0 | AB122: =IF(OR($N122<>"Yes",$O122=""),0,$Y122*IF($Z122<=7,12,19-$Z122)/12) -> 0 | AC122: =IF(OR($J122="Yes",$L122="Yes",$N122="Yes"),"Yes","No") -> No | AD122: =MAX($Q122,$U122,$Y122) -> 0 | AE122: =$AD122+ROW()*0.000000001 -> 1.22e-07 | AF122: =IF($J122="Yes","A","")&IF($L122="Yes","B","")&IF($N122="Yes","C","")
B123: R0119 | C123: Portfolio Reporting Manager | D123: NA | E123: Transformation | F123: AU | G123: Filled | H123: 1 | I123: 0.2933 | J123: No | L123: No | N123: No | P123: 0.2933 | Q123: =IF(AND($J123="Yes",$G123<>"Vendor day rates"),$I123-0.4*$P123,0) -> 0 | R123: =IFERROR(MATCH($K123,MonthList,0),0) -> 0 | S123: =IF(OR($J123<>"Yes",$K123=""),0,$Q123*MAX(0,7-$R123)/12) -> 0 | T123: =IF(OR($J123<>"Yes",$K123=""),0,$Q123*IF($R123<=7,12,19-$R123)/12) -> 0 | U123: =IF(AND($L123="Yes",$G123<>"Vendor day rates"),$I123-0.4*$P123,0) -> 0 | V123: =IFERROR(MATCH($M123,MonthList,0),0) -> 0 | W123: =IF(OR($L123<>"Yes",$M123=""),0,$U123*MAX(0,7-$V123)/12) -> 0 | X123: =IF(OR($L123<>"Yes",$M123=""),0,$U123*IF($V123<=7,12,19-$V123)/12) -> 0 | Y123: =IF(AND($N123="Yes",$G123<>"Vendor day rates"),$I123-0.4*$P123,0) -> 0 | Z123: =IFERROR(MATCH($O123,MonthList,0),0) -> 0 | AA123: =IF(OR($N123<>"Yes",$O123=""),0,$Y123*MAX(0,7-$Z123)/12) -> 0 | AB123: =IF(OR($N123<>"Yes",$O123=""),0,$Y123*IF($Z123<=7,12,19-$Z123)/12) -> 0 | AC123: =IF(OR($J123="Yes",$L123="Yes",$N123="Yes"),"Yes","No") -> No | AD123: =MAX($Q123,$U123,$Y123) -> 0 | AE123: =$AD123+ROW()*0.000000001 -> 1.23e-07 | AF123: =IF($J123="Yes","A","")&IF($L123="Yes","B","")&IF($N123="Yes","C","")
B124: R0120 | C124: Delivery Lead | D124: Infrastructure | E124: Data & Insights | F124: AU | G124: Filled | H124: 1 | I124: 0.2778 | J124: No | L124: No | N124: No | P124: 0.2778 | Q124: =IF(AND($J124="Yes",$G124<>"Vendor day rates"),$I124-0.4*$P124,0) -> 0 | R124: =IFERROR(MATCH($K124,MonthList,0),0) -> 0 | S124: =IF(OR($J124<>"Yes",$K124=""),0,$Q124*MAX(0,7-$R124)/12) -> 0 | T124: =IF(OR($J124<>"Yes",$K124=""),0,$Q124*IF($R124<=7,12,19-$R124)/12) -> 0 | U124: =IF(AND($L124="Yes",$G124<>"Vendor day rates"),$I124-0.4*$P124,0) -> 0 | V124: =IFERROR(MATCH($M124,MonthList,0),0) -> 0 | W124: =IF(OR($L124<>"Yes",$M124=""),0,$U124*MAX(0,7-$V124)/12) -> 0 | X124: =IF(OR($L124<>"Yes",$M124=""),0,$U124*IF($V124<=7,12,19-$V124)/12) -> 0 | Y124: =IF(AND($N124="Yes",$G124<>"Vendor day rates"),$I124-0.4*$P124,0) -> 0 | Z124: =IFERROR(MATCH($O124,MonthList,0),0) -> 0 | AA124: =IF(OR($N124<>"Yes",$O124=""),0,$Y124*MAX(0,7-$Z124)/12) -> 0 | AB124: =IF(OR($N124<>"Yes",$O124=""),0,$Y124*IF($Z124<=7,12,19-$Z124)/12) -> 0 | AC124: =IF(OR($J124="Yes",$L124="Yes",$N124="Yes"),"Yes","No") -> No | AD124: =MAX($Q124,$U124,$Y124) -> 0 | AE124: =$AD124+ROW()*0.000000001 -> 1.24e-07 | AF124: =IF($J124="Yes","A","")&IF($L124="Yes","B","")&IF($N124="Yes","C","")
B125: R0121 | C125: Program Manager POS | D125: Retail | E125: AmPOS | F125: NZ | G125: Filled | H125: 1 | I125: 0.202 | J125: No | L125: No | N125: No | P125: 0.202 | Q125: =IF(AND($J125="Yes",$G125<>"Vendor day rates"),$I125-0.4*$P125,0) -> 0 | R125: =IFERROR(MATCH($K125,MonthList,0),0) -> 0 | S125: =IF(OR($J125<>"Yes",$K125=""),0,$Q125*MAX(0,7-$R125)/12) -> 0 | T125: =IF(OR($J125<>"Yes",$K125=""),0,$Q125*IF($R125<=7,12,19-$R125)/12) -> 0 | U125: =IF(AND($L125="Yes",$G125<>"Vendor day rates"),$I125-0.4*$P125,0) -> 0 | V125: =IFERROR(MATCH($M125,MonthList,0),0) -> 0 | W125: =IF(OR($L125<>"Yes",$M125=""),0,$U125*MAX(0,7-$V125)/12) -> 0 | X125: =IF(OR($L125<>"Yes",$M125=""),0,$U125*IF($V125<=7,12,19-$V125)/12) -> 0 | Y125: =IF(AND($N125="Yes",$G125<>"Vendor day rates"),$I125-0.4*$P125,0) -> 0 | Z125: =IFERROR(MATCH($O125,MonthList,0),0) -> 0 | AA125: =IF(OR($N125<>"Yes",$O125=""),0,$Y125*MAX(0,7-$Z125)/12) -> 0 | AB125: =IF(OR($N125<>"Yes",$O125=""),0,$Y125*IF($Z125<=7,12,19-$Z125)/12) -> 0 | AC125: =IF(OR($J125="Yes",$L125="Yes",$N125="Yes"),"Yes","No") -> No | AD125: =MAX($Q125,$U125,$Y125) -> 0 | AE125: =$AD125+ROW()*0.000000001 -> 1.25e-07 | AF125: =IF($J125="Yes","A","")&IF($L125="Yes","B","")&IF($N125="Yes","C","")
B126: R0122 | C126: Technology Manager – P&C Platforms | D126: P&C | E126: Technology Manager | F126: AU | G126: Filled | H126: 1 | I126: 0.2964 | J126: No | L126: No | N126: No | P126: 0.2964 | Q126: =IF(AND($J126="Yes",$G126<>"Vendor day rates"),$I126-0.4*$P126,0) -> 0 | R126: =IFERROR(MATCH($K126,MonthList,0),0) -> 0 | S126: =IF(OR($J126<>"Yes",$K126=""),0,$Q126*MAX(0,7-$R126)/12) -> 0 | T126: =IF(OR($J126<>"Yes",$K126=""),0,$Q126*IF($R126<=7,12,19-$R126)/12) -> 0 | U126: =IF(AND($L126="Yes",$G126<>"Vendor day rates"),$I126-0.4*$P126,0) -> 0 | V126: =IFERROR(MATCH($M126,MonthList,0),0) -> 0 | W126: =IF(OR($L126<>"Yes",$M126=""),0,$U126*MAX(0,7-$V126)/12) -> 0 | X126: =IF(OR($L126<>"Yes",$M126=""),0,$U126*IF($V126<=7,12,19-$V126)/12) -> 0 | Y126: =IF(AND($N126="Yes",$G126<>"Vendor day rates"),$I126-0.4*$P126,0) -> 0 | Z126: =IFERROR(MATCH($O126,MonthList,0),0) -> 0 | AA126: =IF(OR($N126<>"Yes",$O126=""),0,$Y126*MAX(0,7-$Z126)/12) -> 0 | AB126: =IF(OR($N126<>"Yes",$O126=""),0,$Y126*IF($Z126<=7,12,19-$Z126)/12) -> 0 | AC126: =IF(OR($J126="Yes",$L126="Yes",$N126="Yes"),"Yes","No") -> No | AD126: =MAX($Q126,$U126,$Y126) -> 0 | AE126: =$AD126+ROW()*0.000000001 -> 1.26e-07 | AF126: =IF($J126="Yes","A","")&IF($L126="Yes","B","")&IF($N126="Yes","C","")
B127: R0123 | C127: Technology Manger - Finance Platfo | D127: Finance | E127: Technology Manager | F127: AU | G127: Filled | H127: 1 | I127: 0.3236 | J127: No | L127: No | N127: No | P127: 0.3236 | Q127: =IF(AND($J127="Yes",$G127<>"Vendor day rates"),$I127-0.4*$P127,0) -> 0 | R127: =IFERROR(MATCH($K127,MonthList,0),0) -> 0 | S127: =IF(OR($J127<>"Yes",$K127=""),0,$Q127*MAX(0,7-$R127)/12) -> 0 | T127: =IF(OR($J127<>"Yes",$K127=""),0,$Q127*IF($R127<=7,12,19-$R127)/12) -> 0 | U127: =IF(AND($L127="Yes",$G127<>"Vendor day rates"),$I127-0.4*$P127,0) -> 0 | V127: =IFERROR(MATCH($M127,MonthList,0),0) -> 0 | W127: =IF(OR($L127<>"Yes",$M127=""),0,$U127*MAX(0,7-$V127)/12) -> 0 | X127: =IF(OR($L127<>"Yes",$M127=""),0,$U127*IF($V127<=7,12,19-$V127)/12) -> 0 | Y127: =IF(AND($N127="Yes",$G127<>"Vendor day rates"),$I127-0.4*$P127,0) -> 0 | Z127: =IFERROR(MATCH($O127,MonthList,0),0) -> 0 | AA127: =IF(OR($N127<>"Yes",$O127=""),0,$Y127*MAX(0,7-$Z127)/12) -> 0 | AB127: =IF(OR($N127<>"Yes",$O127=""),0,$Y127*IF($Z127<=7,12,19-$Z127)/12) -> 0 | AC127: =IF(OR($J127="Yes",$L127="Yes",$N127="Yes"),"Yes","No") -> No | AD127: =MAX($Q127,$U127,$Y127) -> 0 | AE127: =$AD127+ROW()*0.000000001 -> 1.27e-07 | AF127: =IF($J127="Yes","A","")&IF($L127="Yes","B","")&IF($N127="Yes","C","")
... B201: R0197 | C201: Manager, Customer Support Operatio | D201: NA | E201: Service Op & Assurance | F201: AU | G201: Filled | H201: 1 | I201: 0.2433 | J201: No | L201: No | N201: No | P201: 0.2433 | Q201: =IF(AND($J201="Yes",$G201<>"Vendor day rates"),$I201-0.4*$P201,0) -> 0 | R201: =IFERROR(MATCH($K201,MonthList,0),0) -> 0 | S201: =IF(OR($J201<>"Yes",$K201=""),0,$Q201*MAX(0,7-$R201)/12) -> 0 | T201: =IF(OR($J201<>"Yes",$K201=""),0,$Q201*IF($R201<=7,12,19-$R201)/12) -> 0 | U201: =IF(AND($L201="Yes",$G201<>"Vendor day rates"),$I201-0.4*$P201,0) -> 0 | V201: =IFERROR(MATCH($M201,MonthList,0),0) -> 0 | W201: =IF(OR($L201<>"Yes",$M201=""),0,$U201*MAX(0,7-$V201)/12) -> 0 | X201: =IF(OR($L201<>"Yes",$M201=""),0,$U201*IF($V201<=7,12,19-$V201)/12) -> 0 | Y201: =IF(AND($N201="Yes",$G201<>"Vendor day rates"),$I201-0.4*$P201,0) -> 0 | Z201: =IFERROR(MATCH($O201,MonthList,0),0) -> 0 | AA201: =IF(OR($N201<>"Yes",$O201=""),0,$Y201*MAX(0,7-$Z201)/12) -> 0 | AB201: =IF(OR($N201<>"Yes",$O201=""),0,$Y201*IF($Z201<=7,12,19-$Z201)/12) -> 0 | AC201: =IF(OR($J201="Yes",$L201="Yes",$N201="Yes"),"Yes","No") -> No | AD201: =MAX($Q201,$U201,$Y201) -> 0 | AE201: =$AD201+ROW()*0.000000001 -> 2.01e-07 | AF201: =IF($J201="Yes","A","")&IF($L201="Yes","B","")&IF($N201="Yes","C","")
B202: R0198 | C202: Platform Architect | E202: Data Platforms | F202: AU | G202: Filled | H202: 1 | I202: 0.2656 | J202: No | L202: No | N202: No | P202: 0.2656 | Q202: =IF(AND($J202="Yes",$G202<>"Vendor day rates"),$I202-0.4*$P202,0) -> 0 | R202: =IFERROR(MATCH($K202,MonthList,0),0) -> 0 | S202: =IF(OR($J202<>"Yes",$K202=""),0,$Q202*MAX(0,7-$R202)/12) -> 0 | T202: =IF(OR($J202<>"Yes",$K202=""),0,$Q202*IF($R202<=7,12,19-$R202)/12) -> 0 | U202: =IF(AND($L202="Yes",$G202<>"Vendor day rates"),$I202-0.4*$P202,0) -> 0 | V202: =IFERROR(MATCH($M202,MonthList,0),0) -> 0 | W202: =IF(OR($L202<>"Yes",$M202=""),0,$U202*MAX(0,7-$V202)/12) -> 0 | X202: =IF(OR($L202<>"Yes",$M202=""),0,$U202*IF($V202<=7,12,19-$V202)/12) -> 0 | Y202: =IF(AND($N202="Yes",$G202<>"Vendor day rates"),$I202-0.4*$P202,0) -> 0 | Z202: =IFERROR(MATCH($O202,MonthList,0),0) -> 0 | AA202: =IF(OR($N202<>"Yes",$O202=""),0,$Y202*MAX(0,7-$Z202)/12) -> 0 | AB202: =IF(OR($N202<>"Yes",$O202=""),0,$Y202*IF($Z202<=7,12,19-$Z202)/12) -> 0 | AC202: =IF(OR($J202="Yes",$L202="Yes",$N202="Yes"),"Yes","No") -> No | AD202: =MAX($Q202,$U202,$Y202) -> 0 | AE202: =$AD202+ROW()*0.000000001 -> 2.02e-07 | AF202: =IF($J202="Yes","A","")&IF($L202="Yes","B","")&IF($N202="Yes","C","")
...

Sheet 3 Compare
B1: Compare your three lists
B2: Everything here moves the moment you set a role to Yes on the Pick roles tab. All figures are A$ millions.
B4: Measure | C4: ='1 Start here'!$B$8 -> Example | D4: ='1 Start here'!$E$8 -> List B | E4: ='1 Start here'!$H$8 -> List C | H4: Month | I4: ='1 Start here'!$B$8 -> Example | J4: ='1 Start here'!$E$8 -> List B | K4: ='1 Start here'!$H$8 -> List C
B5: Roles moved | C5: =COUNTIF('2 Pick roles'!$J$5:$J$544,"Yes") -> 4 | D5: =COUNTIF('2 Pick roles'!$L$5:$L$544,"Yes") -> 0 | E5: =COUNTIF('2 Pick roles'!$N$5:$N$544,"Yes") -> 0 | H5: ='4 Lists'!$B$2 -> Jul-2026 | I5: =SUMPRODUCT(('2 Pick roles'!$R$5:$R$544>=1)*('2 Pick roles'!$R$5:$R$544<=1)*'2 Pick roles'!$Q$5:$Q$544) -> 0 | J5: =SUMPRODUCT(('2 Pick roles'!$V$5:$V$544>=1)*('2 Pick roles'!$V$5:$V$544<=1)*'2 Pick roles'!$U$5:$U$544) -> 0 | K5: =SUMPRODUCT(('2 Pick roles'!$Z$5:$Z$544>=1)*('2 Pick roles'!$Z$5:$Z$544<=1)*'2 Pick roles'!$Y$5:$Y$544) -> 0
B6: People (FTE) | C6: =SUMIF('2 Pick roles'!$J$5:$J$544,"Yes",'2 Pick roles'!$H$5:$H$544) -> 4 | D6: =SUMIF('2 Pick roles'!$L$5:$L$544,"Yes",'2 Pick roles'!$H$5:$H$544) -> 0 | E6: =SUMIF('2 Pick roles'!$N$5:$N$544,"Yes",'2 Pick roles'!$H$5:$H$544) -> 0 | H6: ='4 Lists'!$B$3 -> Aug-2026 | I6: =SUMPRODUCT(('2 Pick roles'!$R$5:$R$544>=1)*('2 Pick roles'!$R$5:$R$544<=2)*'2 Pick roles'!$Q$5:$Q$544) -> 0 | J6: =SUMPRODUCT(('2 Pick roles'!$V$5:$V$544>=1)*('2 Pick roles'!$V$5:$V$544<=2)*'2 Pick roles'!$U$5:$U$544) -> 0 | K6: =SUMPRODUCT(('2 Pick roles'!$Z$5:$Z$544>=1)*('2 Pick roles'!$Z$5:$Z$544<=2)*'2 Pick roles'!$Y$5:$Y$544) -> 0
B7: Cost today | C7: =SUMIF('2 Pick roles'!$J$5:$J$544,"Yes",'2 Pick roles'!$I$5:$I$544) -> 0.7607 | D7: =SUMIF('2 Pick roles'!$L$5:$L$544,"Yes",'2 Pick roles'!$I$5:$I$544) -> 0 | E7: =SUMIF('2 Pick roles'!$N$5:$N$544,"Yes",'2 Pick roles'!$I$5:$I$544) -> 0 | H7: ='4 Lists'!$B$4 -> Sep-2026 | I7: =SUMPRODUCT(('2 Pick roles'!$R$5:$R$544>=1)*('2 Pick roles'!$R$5:$R$544<=3)*'2 Pick roles'!$Q$5:$Q$544) -> 0 | J7: =SUMPRODUCT(('2 Pick roles'!$V$5:$V$544>=1)*('2 Pick roles'!$V$5:$V$544<=3)*'2 Pick roles'!$U$5:$U$544) -> 0 | K7: =SUMPRODUCT(('2 Pick roles'!$Z$5:$Z$544>=1)*('2 Pick roles'!$Z$5:$Z$544<=3)*'2 Pick roles'!$Y$5:$Y$544) -> 0
B8: Cost at the offshore rate | C8: =C7-C9 -> 0.37104 | D8: =D7-D9 -> 0 | E8: =E7-E9 -> 0 | H8: ='4 Lists'!$B$5 -> Oct-2026 | I8: =SUMPRODUCT(('2 Pick roles'!$R$5:$R$544>=1)*('2 Pick roles'!$R$5:$R$544<=4)*'2 Pick roles'!$Q$5:$Q$544) -> 0.28472 | J8: =SUMPRODUCT(('2 Pick roles'!$V$5:$V$544>=1)*('2 Pick roles'!$V$5:$V$544<=4)*'2 Pick roles'!$U$5:$U$544) -> 0 | K8: =SUMPRODUCT(('2 Pick roles'!$Z$5:$Z$544>=1)*('2 Pick roles'!$Z$5:$Z$544<=4)*'2 Pick roles'!$Y$5:$Y$544) -> 0
B9: Cost taken out, full year | C9: =SUM('2 Pick roles'!$Q$5:$Q$544) -> 0.38966 | D9: =SUM('2 Pick roles'!$U$5:$U$544) -> 0 | E9: =SUM('2 Pick roles'!$Y$5:$Y$544) -> 0 | H9: ='4 Lists'!$B$6 -> Nov-2026 | I9: =SUMPRODUCT(('2 Pick roles'!$R$5:$R$544>=1)*('2 Pick roles'!$R$5:$R$544<=5)*'2 Pick roles'!$Q$5:$Q$544) -> 0.28472 | J9: =SUMPRODUCT(('2 Pick roles'!$V$5:$V$544>=1)*('2 Pick roles'!$V$5:$V$544<=5)*'2 Pick roles'!$U$5:$U$544) -> 0 | K9: =SUMPRODUCT(('2 Pick roles'!$Z$5:$Z$544>=1)*('2 Pick roles'!$Z$5:$Z$544<=5)*'2 Pick roles'!$Y$5:$Y$544) -> 0
B10: Taken out in 2026 | C10: =SUM('2 Pick roles'!$S$5:$S$544) -> 0.07118 | D10: =SUM('2 Pick roles'!$W$5:$W$544) -> 0 | E10: =SUM('2 Pick roles'!$AA$5:$AA$544) -> 0 | H10: ='4 Lists'!$B$7 -> Dec-2026 | I10: =SUMPRODUCT(('2 Pick roles'!$R$5:$R$544>=1)*('2 Pick roles'!$R$5:$R$544<=6)*'2 Pick roles'!$Q$5:$Q$544) -> 0.28472 | J10: =SUMPRODUCT(('2 Pick roles'!$V$5:$V$544>=1)*('2 Pick roles'!$V$5:$V$544<=6)*'2 Pick roles'!$U$5:$U$544) -> 0 | K10: =SUMPRODUCT(('2 Pick roles'!$Z$5:$Z$544>=1)*('2 Pick roles'!$Z$5:$Z$544<=6)*'2 Pick roles'!$Y$5:$Y$544) -> 0
B11: Taken out in 2027 | C11: =SUM('2 Pick roles'!$T$5:$T$544) -> 0.38966 | D11: =SUM('2 Pick roles'!$X$5:$X$544) -> 0 | E11: =SUM('2 Pick roles'!$AB$5:$AB$544) -> 0 | H11: ='4 Lists'!$B$8 -> Jan-2027 | I11: =SUMPRODUCT(('2 Pick roles'!$R$5:$R$544>=1)*('2 Pick roles'!$R$5:$R$544<=7)*'2 Pick roles'!$Q$5:$Q$544) -> 0.38966 | J11: =SUMPRODUCT(('2 Pick roles'!$V$5:$V$544>=1)*('2 Pick roles'!$V$5:$V$544<=7)*'2 Pick roles'!$U$5:$U$544) -> 0 | K11: =SUMPRODUCT(('2 Pick roles'!$Z$5:$Z$544>=1)*('2 Pick roles'!$Z$5:$Z$544<=7)*'2 Pick roles'!$Y$5:$Y$544) -> 0
H12: ='4 Lists'!$B$9 -> Feb-2027 | I12: =SUMPRODUCT(('2 Pick roles'!$R$5:$R$544>=1)*('2 Pick roles'!$R$5:$R$544<=8)*'2 Pick roles'!$Q$5:$Q$544) -> 0.38966 | J12: =SUMPRODUCT(('2 Pick roles'!$V$5:$V$544>=1)*('2 Pick roles'!$V$5:$V$544<=8)*'2 Pick roles'!$U$5:$U$544) -> 0 | K12: =SUMPRODUCT(('2 Pick roles'!$Z$5:$Z$544>=1)*('2 Pick roles'!$Z$5:$Z$544<=8)*'2 Pick roles'!$Y$5:$Y$544) -> 0
H13: ='4 Lists'!$B$10 -> Mar-2027 | I13: =SUMPRODUCT(('2 Pick roles'!$R$5:$R$544>=1)*('2 Pick roles'!$R$5:$R$544<=9)*'2 Pick roles'!$Q$5:$Q$544) -> 0.38966 | J13: =SUMPRODUCT(('2 Pick roles'!$V$5:$V$544>=1)*('2 Pick roles'!$V$5:$V$544<=9)*'2 Pick roles'!$U$5:$U$544) -> 0 | K13: =SUMPRODUCT(('2 Pick roles'!$Z$5:$Z$544>=1)*('2 Pick roles'!$Z$5:$Z$544<=9)*'2 Pick roles'!$Y$5:$Y$544) -> 0
B14: Cost taken out by portfolio, full year | H14: ='4 Lists'!$B$11 -> Apr-2027 | I14: =SUMPRODUCT(('2 Pick roles'!$R$5:$R$544>=1)*('2 Pick roles'!$R$5:$R$544<=10)*'2 Pick roles'!$Q$5:$Q$544) -> 0.38966 | J14: =SUMPRODUCT(('2 Pick roles'!$V$5:$V$544>=1)*('2 Pick roles'!$V$5:$V$544<=10)*'2 Pick roles'!$U$5:$U$544) -> 0 | K14: =SUMPRODUCT(('2 Pick roles'!$Z$5:$Z$544>=1)*('2 Pick roles'!$Z$5:$Z$544<=10)*'2 Pick roles'!$Y$5:$Y$544) -> 0
B15: Portfolio | C15: ='1 Start here'!$B$8 -> Example | D15: ='1 Start here'!$E$8 -> List B | E15: ='1 Start here'!$H$8 -> List C | H15: ='4 Lists'!$B$12 -> May-2027 | I15: =SUMPRODUCT(('2 Pick roles'!$R$5:$R$544>=1)*('2 Pick roles'!$R$5:$R$544<=11)*'2 Pick roles'!$Q$5:$Q$544) -> 0.38966 | J15: =SUMPRODUCT(('2 Pick roles'!$V$5:$V$544>=1)*('2 Pick roles'!$V$5:$V$544<=11)*'2 Pick roles'!$U$5:$U$544) -> 0 | K15: =SUMPRODUCT(('2 Pick roles'!$Z$5:$Z$544>=1)*('2 Pick roles'!$Z$5:$Z$544<=11)*'2 Pick roles'!$Y$5:$Y$544) -> 0
B16: EGI Integration | C16: =SUMIFS('2 Pick roles'!$Q$5:$Q$544,'2 Pick roles'!$D$5:$D$544,"EGI Integration") -> 0 | D16: =SUMIFS('2 Pick roles'!$U$5:$U$544,'2 Pick roles'!$D$5:$D$544,"EGI Integration") -> 0 | E16: =SUMIFS('2 Pick roles'!$Y$5:$Y$544,'2 Pick roles'!$D$5:$D$544,"EGI Integration") -> 0 | H16: ='4 Lists'!$B$13 -> Jun-2027 | I16: =SUMPRODUCT(('2 Pick roles'!$R$5:$R$544>=1)*('2 Pick roles'!$R$5:$R$544<=12)*'2 Pick roles'!$Q$5:$Q$544) -> 0.38966 | J16: =SUMPRODUCT(('2 Pick roles'!$V$5:$V$544>=1)*('2 Pick roles'!$V$5:$V$544<=12)*'2 Pick roles'!$U$5:$U$544) -> 0 | K16: =SUMPRODUCT(('2 Pick roles'!$Z$5:$Z$544>=1)*('2 Pick roles'!$Z$5:$Z$544<=12)*'2 Pick roles'!$Y$5:$Y$544) -> 0
B17: Ampol Customer | C17: =SUMIFS('2 Pick roles'!$Q$5:$Q$544,'2 Pick roles'!$D$5:$D$544,"Ampol Customer") -> 0.16376 | D17: =SUMIFS('2 Pick roles'!$U$5:$U$544,'2 Pick roles'!$D$5:$D$544,"Ampol Customer") -> 0 | E17: =SUMIFS('2 Pick roles'!$Y$5:$Y$544,'2 Pick roles'!$D$5:$D$544,"Ampol Customer") -> 0 | H17: ='4 Lists'!$B$14 -> Jul-2027 | I17: =SUMPRODUCT(('2 Pick roles'!$R$5:$R$544>=1)*('2 Pick roles'!$R$5:$R$544<=13)*'2 Pick roles'!$Q$5:$Q$544) -> 0.38966 | J17: =SUMPRODUCT(('2 Pick roles'!$V$5:$V$544>=1)*('2 Pick roles'!$V$5:$V$544<=13)*'2 Pick roles'!$U$5:$U$544) -> 0 | K17: =SUMPRODUCT(('2 Pick roles'!$Z$5:$Z$544>=1)*('2 Pick roles'!$Z$5:$Z$544<=13)*'2 Pick roles'!$Y$5:$Y$544) -> 0
B18: EGI | C18: =SUMIFS('2 Pick roles'!$Q$5:$Q$544,'2 Pick roles'!$D$5:$D$544,"EGI") -> 0 | D18: =SUMIFS('2 Pick roles'!$U$5:$U$544,'2 Pick roles'!$D$5:$D$544,"EGI") -> 0 | E18: =SUMIFS('2 Pick roles'!$Y$5:$Y$544,'2 Pick roles'!$D$5:$D$544,"EGI") -> 0 | H18: ='4 Lists'!$B$15 -> Aug-2027 | I18: =SUMPRODUCT(('2 Pick roles'!$R$5:$R$544>=1)*('2 Pick roles'!$R$5:$R$544<=14)*'2 Pick roles'!$Q$5:$Q$544) -> 0.38966 | J18: =SUMPRODUCT(('2 Pick roles'!$V$5:$V$544>=1)*('2 Pick roles'!$V$5:$V$544<=14)*'2 Pick roles'!$U$5:$U$544) -> 0 | K18: =SUMPRODUCT(('2 Pick roles'!$Z$5:$Z$544>=1)*('2 Pick roles'!$Z$5:$Z$544<=14)*'2 Pick roles'!$Y$5:$Y$544) -> 0
B19: Infrastructure | C19: =SUMIFS('2 Pick roles'!$Q$5:$Q$544,'2 Pick roles'!$D$5:$D$544,"Infrastructure") -> 0 | D19: =SUMIFS('2 Pick roles'!$U$5:$U$544,'2 Pick roles'!$D$5:$D$544,"Infrastructure") -> 0 | E19: =SUMIFS('2 Pick roles'!$Y$5:$Y$544,'2 Pick roles'!$D$5:$D$544,"Infrastructure") -> 0 | H19: ='4 Lists'!$B$16 -> Sep-2027 | I19: =SUMPRODUCT(('2 Pick roles'!$R$5:$R$544>=1)*('2 Pick roles'!$R$5:$R$544<=15)*'2 Pick roles'!$Q$5:$Q$544) -> 0.38966 | J19: =SUMPRODUCT(('2 Pick roles'!$V$5:$V$544>=1)*('2 Pick roles'!$V$5:$V$544<=15)*'2 Pick roles'!$U$5:$U$544) -> 0 | K19: =SUMPRODUCT(('2 Pick roles'!$Z$5:$Z$544>=1)*('2 Pick roles'!$Z$5:$Z$544<=15)*'2 Pick roles'!$Y$5:$Y$544) -> 0
B20: NA | C20: =SUMIFS('2 Pick roles'!$Q$5:$Q$544,'2 Pick roles'!$D$5:$D$544,"NA") -> 0 | D20: =SUMIFS('2 Pick roles'!$U$5:$U$544,'2 Pick roles'!$D$5:$D$544,"NA") -> 0 | E20: =SUMIFS('2 Pick roles'!$Y$5:$Y$544,'2 Pick roles'!$D$5:$D$544,"NA") -> 0 | H20: ='4 Lists'!$B$17 -> Oct-2027 | I20: =SUMPRODUCT(('2 Pick roles'!$R$5:$R$544>=1)*('2 Pick roles'!$R$5:$R$544<=16)*'2 Pick roles'!$Q$5:$Q$544) -> 0.38966 | J20: =SUMPRODUCT(('2 Pick roles'!$V$5:$V$544>=1)*('2 Pick roles'!$V$5:$V$544<=16)*'2 Pick roles'!$U$5:$U$544) -> 0 | K20: =SUMPRODUCT(('2 Pick roles'!$Z$5:$Z$544>=1)*('2 Pick roles'!$Z$5:$Z$544<=16)*'2 Pick roles'!$Y$5:$Y$544) -> 0
B21: Z ENERGY (DIGITAL) | C21: =SUMIFS('2 Pick roles'!$Q$5:$Q$544,'2 Pick roles'!$D$5:$D$544,"Z ENERGY (DIGITAL)") -> 0 | D21: =SUMIFS('2 Pick roles'!$U$5:$U$544,'2 Pick roles'!$D$5:$D$544,"Z ENERGY (DIGITAL)") -> 0 | E21: =SUMIFS('2 Pick roles'!$Y$5:$Y$544,'2 Pick roles'!$D$5:$D$544,"Z ENERGY (DIGITAL)") -> 0 | H21: ='4 Lists'!$B$18 -> Nov-2027 | I21: =SUMPRODUCT(('2 Pick roles'!$R$5:$R$544>=1)*('2 Pick roles'!$R$5:$R$544<=17)*'2 Pick roles'!$Q$5:$Q$544) -> 0.38966 | J21: =SUMPRODUCT(('2 Pick roles'!$V$5:$V$544>=1)*('2 Pick roles'!$V$5:$V$544<=17)*'2 Pick roles'!$U$5:$U$544) -> 0 | K21: =SUMPRODUCT(('2 Pick roles'!$Z$5:$Z$544>=1)*('2 Pick roles'!$Z$5:$Z$544<=17)*'2 Pick roles'!$Y$5:$Y$544) -> 0
B22: TDD | C22: =SUMIFS('2 Pick roles'!$Q$5:$Q$544,'2 Pick roles'!$D$5:$D$544,"TDD") -> 0 | D22: =SUMIFS('2 Pick roles'!$U$5:$U$544,'2 Pick roles'!$D$5:$D$544,"TDD") -> 0 | E22: =SUMIFS('2 Pick roles'!$Y$5:$Y$544,'2 Pick roles'!$D$5:$D$544,"TDD") -> 0 | H22: ='4 Lists'!$B$19 -> Dec-2027 | I22: =SUMPRODUCT(('2 Pick roles'!$R$5:$R$544>=1)*('2 Pick roles'!$R$5:$R$544<=18)*'2 Pick roles'!$Q$5:$Q$544) -> 0.38966 | J22: =SUMPRODUCT(('2 Pick roles'!$V$5:$V$544>=1)*('2 Pick roles'!$V$5:$V$544<=18)*'2 Pick roles'!$U$5:$U$544) -> 0 | K22: =SUMPRODUCT(('2 Pick roles'!$Z$5:$Z$544>=1)*('2 Pick roles'!$Z$5:$Z$544<=18)*'2 Pick roles'!$Y$5:$Y$544) -> 0
B23: P&C, Finance & Legal | C23: =SUMIFS('2 Pick roles'!$Q$5:$Q$544,'2 Pick roles'!$D$5:$D$544,"P&C, Finance & Legal") -> 0 | D23: =SUMIFS('2 Pick roles'!$U$5:$U$544,'2 Pick roles'!$D$5:$D$544,"P&C, Finance & Legal") -> 0 | E23: =SUMIFS('2 Pick roles'!$Y$5:$Y$544,'2 Pick roles'!$D$5:$D$544,"P&C, Finance & Legal") -> 0
B24: Enterprise Data | C24: =SUMIFS('2 Pick roles'!$Q$5:$Q$544,'2 Pick roles'!$D$5:$D$544,"Enterprise Data") -> 0 | D24: =SUMIFS('2 Pick roles'!$U$5:$U$544,'2 Pick roles'!$D$5:$D$544,"Enterprise Data") -> 0 | E24: =SUMIFS('2 Pick roles'!$Y$5:$Y$544,'2 Pick roles'!$D$5:$D$544,"Enterprise Data") -> 0 | H24: Cost taken out by year
B25: Commercial Fuels | C25: =SUMIFS('2 Pick roles'!$Q$5:$Q$544,'2 Pick roles'!$D$5:$D$544,"Commercial Fuels") -> 0 | D25: =SUMIFS('2 Pick roles'!$U$5:$U$544,'2 Pick roles'!$D$5:$D$544,"Commercial Fuels") -> 0 | E25: =SUMIFS('2 Pick roles'!$Y$5:$Y$544,'2 Pick roles'!$D$5:$D$544,"Commercial Fuels") -> 0 | H25: Year | I25: ='1 Start here'!$B$8 -> Example | J25: ='1 Start here'!$E$8 -> List B | K25: ='1 Start here'!$H$8 -> List C
B26: B2B & Energy Solutions | C26: =SUMIFS('2 Pick roles'!$Q$5:$Q$544,'2 Pick roles'!$D$5:$D$544,"B2B & Energy Solutions") -> 0 | D26: =SUMIFS('2 Pick roles'!$U$5:$U$544,'2 Pick roles'!$D$5:$D$544,"B2B & Energy Solutions") -> 0 | E26: =SUMIFS('2 Pick roles'!$Y$5:$Y$544,'2 Pick roles'!$D$5:$D$544,"B2B & Energy Solutions") -> 0 | H26: 2026 | I26: =C10 -> 0.07118 | J26: =D10 -> 0 | K26: =E10 -> 0
B27: Retail | C27: =SUMIFS('2 Pick roles'!$Q$5:$Q$544,'2 Pick roles'!$D$5:$D$544,"Retail") -> 0.12096 | D27: =SUMIFS('2 Pick roles'!$U$5:$U$544,'2 Pick roles'!$D$5:$D$544,"Retail") -> 0 | E27: =SUMIFS('2 Pick roles'!$Y$5:$Y$544,'2 Pick roles'!$D$5:$D$544,"Retail") -> 0 | H27: 2027 | I27: =C11 -> 0.38966 | J27: =D11 -> 0 | K27: =E11 -> 0
B28: Z | C28: =SUMIFS('2 Pick roles'!$Q$5:$Q$544,'2 Pick roles'!$D$5:$D$544,"Z") -> 0 | D28: =SUMIFS('2 Pick roles'!$U$5:$U$544,'2 Pick roles'!$D$5:$D$544,"Z") -> 0 | E28: =SUMIFS('2 Pick roles'!$Y$5:$Y$544,'2 Pick roles'!$D$5:$D$544,"Z") -> 0
B29: P&C | C29: =SUMIFS('2 Pick roles'!$Q$5:$Q$544,'2 Pick roles'!$D$5:$D$544,"P&C") -> 0 | D29: =SUMIFS('2 Pick roles'!$U$5:$U$544,'2 Pick roles'!$D$5:$D$544,"P&C") -> 0 | E29: =SUMIFS('2 Pick roles'!$Y$5:$Y$544,'2 Pick roles'!$D$5:$D$544,"P&C") -> 0
B30: Finance | C30: =SUMIFS('2 Pick roles'!$Q$5:$Q$544,'2 Pick roles'!$D$5:$D$544,"Finance") -> 0.10494 | D30: =SUMIFS('2 Pick roles'!$U$5:$U$544,'2 Pick roles'!$D$5:$D$544,"Finance") -> 0 | E30: =SUMIFS('2 Pick roles'!$Y$5:$Y$544,'2 Pick roles'!$D$5:$D$544,"Finance") -> 0
B31: Not mapped | C31: =SUM('2 Pick roles'!$Q$5:$Q$544)-(C16+C17+C18+C19+C20+C21+C22+C23+C24+C25+C26+C27+C28+C29+C30) -> 0 | D31: =SUM('2 Pick roles'!$U$5:$U$544)-(D16+D17+D18+D19+D20+D21+D22+D23+D24+D25+D26+D27+D28+D29+D30) -> 0 | E31: =SUM('2 Pick roles'!$Y$5:$Y$544)-(E16+E17+E18+E19+E20+E21+E22+E23+E24+E25+E26+E27+E28+E29+E30) -> 0
B32: Total | C32: =SUM(C16:C31) -> 0.38966 | D32: =SUM(D16:D31) -> 0 | E32: =SUM(E16:E31) -> 0
B33: Check against full year (0 = ties) | C33: =C32-C9 -> 0 | D33: =D32-D9 -> 0 | E33: =E32-E9 -> 0

Sheet 4 Lists
B1: Month list, used by the dropdowns. Do not change.
B2: Jul-2026 | C2: 1
B3: Aug-2026 | C3: 2
B4: Sep-2026 | C4: 3
B5: Oct-2026 | C5: 4
B6: Nov-2026 | C6: 5
B7: Dec-2026 | C7: 6
B8: Jan-2027 | C8: 7
B9: Feb-2027 | C9: 8
B10: Mar-2027 | C10: 9
B11: Apr-2027 | C11: 10
B12: May-2027 | C12: 11
B13: Jun-2027 | C13: 12
... B19: Dec-2027 | C19: 18
