Workbook

Sheet 1 Scenarios
B2: Offshore scenario model
B3: Edit only the blue cells: the three scenario names below, and the Offshore? and Start month columns on the 2 Roles tab. Everything else is locked (password with Lee).
B4: Scenario A name | C4: Example scenario | G4: Scenario A is loaded as a worked example with four roles offshored. Overwrite the toggles and the name with your own.
B5: Scenario B name | C5: Scenario B
B6: Scenario C name | C6: Scenario C
B8: Measure | C8: =C4 -> Example scenario | D8: =C5 -> Scenario B | E8: =C6 -> Scenario C
B9: Roles toggled on | C9: =COUNTIF('2 Roles'!K6:K545,"Yes") -> 4 | D9: =COUNTIF('2 Roles'!P6:P545,"Yes") -> 0 | E9: =COUNTIF('2 Roles'!U6:U545,"Yes") -> 0
B10: FTE of those roles | C10: =SUMIF('2 Roles'!K6:K545,"Yes",'2 Roles'!$H$6:$H$545) -> 4 | D10: =SUMIF('2 Roles'!P6:P545,"Yes",'2 Roles'!$H$6:$H$545) -> 0 | E10: =SUMIF('2 Roles'!U6:U545,"Yes",'2 Roles'!$H$6:$H$545) -> 0
B11: Cost of those roles today ($m) | C11: =SUMIF('2 Roles'!K6:K545,"Yes",'2 Roles'!$J$6:$J$545) -> 0.7607 | D11: =SUMIF('2 Roles'!P6:P545,"Yes",'2 Roles'!$J$6:$J$545) -> 0 | E11: =SUMIF('2 Roles'!U6:U545,"Yes",'2 Roles'!$J$6:$J$545) -> 0
B12: Cost of those roles at the rate ($m) | C12: =C11-C13 -> 0.37104 | D12: =D11-D13 -> 0 | E12: =E11-E13 -> 0
B13: Reduction of cost, full year ($m) | C13: =SUM('2 Roles'!M6:M545) -> 0.38966 | D13: =SUM('2 Roles'!R6:R545) -> 0 | E13: =SUM('2 Roles'!W6:W545) -> 0
B14: Impact in FY26 ($m) | C14: =SUM('2 Roles'!N6:N545) -> 0.07118 | D14: =SUM('2 Roles'!S6:S545) -> 0 | E14: =SUM('2 Roles'!X6:X545) -> 0
B15: Impact in FY27 ($m) | C15: =SUM('2 Roles'!O6:O545) -> 0.38966 | D15: =SUM('2 Roles'!T6:T545) -> 0 | E15: =SUM('2 Roles'!Y6:Y545) -> 0
B18: Reduction of cost by portfolio, full year ($m) | C18: =C4 -> Example scenario | D18: =C5 -> Scenario B | E18: =C6 -> Scenario C
B19: Ampol Customer | C19: =SUMIFS('2 Roles'!$M$6:$M$545,'2 Roles'!$D$6:$D$545,$B19) -> 0.16376 | D19: =SUMIFS('2 Roles'!$R$6:$R$545,'2 Roles'!$D$6:$D$545,$B19) -> 0 | E19: =SUMIFS('2 Roles'!$W$6:$W$545,'2 Roles'!$D$6:$D$545,$B19) -> 0
B20: B2B & Energy Solutions | C20: =SUMIFS('2 Roles'!$M$6:$M$545,'2 Roles'!$D$6:$D$545,$B20) -> 0 | D20: =SUMIFS('2 Roles'!$R$6:$R$545,'2 Roles'!$D$6:$D$545,$B20) -> 0 | E20: =SUMIFS('2 Roles'!$W$6:$W$545,'2 Roles'!$D$6:$D$545,$B20) -> 0
B21: Commercial Fuels | C21: =SUMIFS('2 Roles'!$M$6:$M$545,'2 Roles'!$D$6:$D$545,$B21) -> 0 | D21: =SUMIFS('2 Roles'!$R$6:$R$545,'2 Roles'!$D$6:$D$545,$B21) -> 0 | E21: =SUMIFS('2 Roles'!$W$6:$W$545,'2 Roles'!$D$6:$D$545,$B21) -> 0
B22: EGI | C22: =SUMIFS('2 Roles'!$M$6:$M$545,'2 Roles'!$D$6:$D$545,$B22) -> 0 | D22: =SUMIFS('2 Roles'!$R$6:$R$545,'2 Roles'!$D$6:$D$545,$B22) -> 0 | E22: =SUMIFS('2 Roles'!$W$6:$W$545,'2 Roles'!$D$6:$D$545,$B22) -> 0
B23: EGI Integration | C23: =SUMIFS('2 Roles'!$M$6:$M$545,'2 Roles'!$D$6:$D$545,$B23) -> 0 | D23: =SUMIFS('2 Roles'!$R$6:$R$545,'2 Roles'!$D$6:$D$545,$B23) -> 0 | E23: =SUMIFS('2 Roles'!$W$6:$W$545,'2 Roles'!$D$6:$D$545,$B23) -> 0
B24: Enterprise Data | C24: =SUMIFS('2 Roles'!$M$6:$M$545,'2 Roles'!$D$6:$D$545,$B24) -> 0 | D24: =SUMIFS('2 Roles'!$R$6:$R$545,'2 Roles'!$D$6:$D$545,$B24) -> 0 | E24: =SUMIFS('2 Roles'!$W$6:$W$545,'2 Roles'!$D$6:$D$545,$B24) -> 0
B25: Finance | C25: =SUMIFS('2 Roles'!$M$6:$M$545,'2 Roles'!$D$6:$D$545,$B25) -> 0.10494 | D25: =SUMIFS('2 Roles'!$R$6:$R$545,'2 Roles'!$D$6:$D$545,$B25) -> 0 | E25: =SUMIFS('2 Roles'!$W$6:$W$545,'2 Roles'!$D$6:$D$545,$B25) -> 0
B26: Infrastructure | C26: =SUMIFS('2 Roles'!$M$6:$M$545,'2 Roles'!$D$6:$D$545,$B26) -> 0 | D26: =SUMIFS('2 Roles'!$R$6:$R$545,'2 Roles'!$D$6:$D$545,$B26) -> 0 | E26: =SUMIFS('2 Roles'!$W$6:$W$545,'2 Roles'!$D$6:$D$545,$B26) -> 0
B27: NA | C27: =SUMIFS('2 Roles'!$M$6:$M$545,'2 Roles'!$D$6:$D$545,$B27) -> 0 | D27: =SUMIFS('2 Roles'!$R$6:$R$545,'2 Roles'!$D$6:$D$545,$B27) -> 0 | E27: =SUMIFS('2 Roles'!$W$6:$W$545,'2 Roles'!$D$6:$D$545,$B27) -> 0
B28: P&C | C28: =SUMIFS('2 Roles'!$M$6:$M$545,'2 Roles'!$D$6:$D$545,$B28) -> 0 | D28: =SUMIFS('2 Roles'!$R$6:$R$545,'2 Roles'!$D$6:$D$545,$B28) -> 0 | E28: =SUMIFS('2 Roles'!$W$6:$W$545,'2 Roles'!$D$6:$D$545,$B28) -> 0
B29: P&C, Finance & Legal | C29: =SUMIFS('2 Roles'!$M$6:$M$545,'2 Roles'!$D$6:$D$545,$B29) -> 0 | D29: =SUMIFS('2 Roles'!$R$6:$R$545,'2 Roles'!$D$6:$D$545,$B29) -> 0 | E29: =SUMIFS('2 Roles'!$W$6:$W$545,'2 Roles'!$D$6:$D$545,$B29) -> 0
B30: Retail | C30: =SUMIFS('2 Roles'!$M$6:$M$545,'2 Roles'!$D$6:$D$545,$B30) -> 0.12096 | D30: =SUMIFS('2 Roles'!$R$6:$R$545,'2 Roles'!$D$6:$D$545,$B30) -> 0 | E30: =SUMIFS('2 Roles'!$W$6:$W$545,'2 Roles'!$D$6:$D$545,$B30) -> 0
... B33: Z ENERGY (DIGITAL) | C33: =SUMIFS('2 Roles'!$M$6:$M$545,'2 Roles'!$D$6:$D$545,$B33) -> 0 | D33: =SUMIFS('2 Roles'!$R$6:$R$545,'2 Roles'!$D$6:$D$545,$B33) -> 0 | E33: =SUMIFS('2 Roles'!$W$6:$W$545,'2 Roles'!$D$6:$D$545,$B33) -> 0
B34: Not mapped to a portfolio | C34: =SUMIFS('2 Roles'!$M$6:$M$545,'2 Roles'!$D$6:$D$545,"=") -> 0 | D34: =SUMIFS('2 Roles'!$R$6:$R$545,'2 Roles'!$D$6:$D$545,"=") -> 0 | E34: =SUMIFS('2 Roles'!$W$6:$W$545,'2 Roles'!$D$6:$D$545,"=") -> 0
B35: Total | C35: =SUM(C19:C34) -> 0.38966 | D35: =SUM(D19:D34) -> 0 | E35: =SUM(E19:E34) -> 0
B36: Check against the full year row above (should be zero) | C36: =C35-C13 -> 0 | D36: =D35-D13 -> 0 | E36: =E35-E13 -> 0
B37: Built from the role mapping in TDD_FY27_Cost_Calc_0608 (11 August 2026), copied in full on the REVIEW tab. Cost in the book today: filled roles at mapped cost, planned hires at planned spend, held roles at zero, roles already at the offshore rate at 0.4, WiPro at vendor day rates.
B42: Chart data | C42: =C4 -> Example scenario | D42: =C5 -> Scenario B | E42: =C6 -> Scenario C
B43: Impact in FY26 ($m) | C43: =C14 -> 0.07118 | D43: =D14 -> 0 | E43: =E14 -> 0
B44: Impact in FY27 ($m) | C44: =C15 -> 0.38966 | D44: =D15 -> 0 | E44: =E15 -> 0
B45: Reduction of cost, full year ($m) | C45: =C16 -> 0 | D45: =D16 -> 0 | E45: =E16 -> 0

Sheet 2 Roles
B2: Roles and toggles
B3: Toggle Offshore? to Yes and pick a start month. Only the toggle and month cells can be edited. A role already at the offshore rate or on vendor day rates contributes nothing extra. A held role costs nothing today, so offshoring it shows as added cost.
K4: =CONCATENATE("Scenario ",'1 Scenarios'!C4) -> Scenario Example scenario | P4: =CONCATENATE("Scenario ",'1 Scenarios'!C5) -> Scenario Scenario B | U4: =CONCATENATE("Scenario ",'1 Scenarios'!C6) -> Scenario Scenario C
B5: Role ID | C5: Role | D5: Portfolio | E5: Squad or line | F5: Country | G5: Status in the model | H5: FTE | I5: Full onshore cost ($m) | J5: Cost in the book today ($m) | K5: Offshore? | L5: Start month | M5: Reduction a year ($m) | N5: Impact FY26 ($m) | O5: Impact FY27 ($m) | P5: Offshore? | Q5: Start month | R5: Reduction a year ($m) | S5: Impact FY26 ($m) | T5: Impact FY27 ($m) | U5: Offshore? | V5: Start month | W5: Reduction a year ($m) | X5: Impact FY26 ($m) | Y5: Impact FY27 ($m)
B6: R0001 | C6: Delivery Lead | D6: EGI Integration | E6: EGI Customer | F6: AU | G6: Filled | H6: 1 | I6: 0.2642 | J6: 0.2642 | K6: No | M6: =IF(AND($K6="Yes",$G6<>"Vendor day rates"),$J6-0.4*$I6,0) -> 0 | N6: =IF(OR($K6<>"Yes",$L6=""),0,$M6*MAX(0,7-MATCH($L6,MonthList,0))/12) -> 0 | O6: =IF(OR($K6<>"Yes",$L6=""),0,$M6*IF(MATCH($L6,MonthList,0)<=7,12,19-MATCH($L6,MonthList,0))/12) -> 0 | P6: No | R6: =IF(AND($P6="Yes",$G6<>"Vendor day rates"),$J6-0.4*$I6,0) -> 0 | S6: =IF(OR($P6<>"Yes",$Q6=""),0,$R6*MAX(0,7-MATCH($Q6,MonthList,0))/12) -> 0 | T6: =IF(OR($P6<>"Yes",$Q6=""),0,$R6*IF(MATCH($Q6,MonthList,0)<=7,12,19-MATCH($Q6,MonthList,0))/12) -> 0 | U6: No | W6: =IF(AND($U6="Yes",$G6<>"Vendor day rates"),$J6-0.4*$I6,0) -> 0 | X6: =IF(OR($U6<>"Yes",$V6=""),0,$W6*MAX(0,7-MATCH($V6,MonthList,0))/12) -> 0 | Y6: =IF(OR($U6<>"Yes",$V6=""),0,$W6*IF(MATCH($V6,MonthList,0)<=7,12,19-MATCH($V6,MonthList,0))/12) -> 0
B7: R0002 | C7: Snr Business Analyst | D7: Ampol Customer | E7: Ampol Web | F7: AU | G7: Filled | H7: 1 | I7: 0.2729 | J7: 0.2729 | K7: Yes | L7: Oct-2026 | M7: =IF(AND($K7="Yes",$G7<>"Vendor day rates"),$J7-0.4*$I7,0) -> 0.16374 | N7: =IF(OR($K7<>"Yes",$L7=""),0,$M7*MAX(0,7-MATCH($L7,MonthList,0))/12) -> 0.040935 | O7: =IF(OR($K7<>"Yes",$L7=""),0,$M7*IF(MATCH($L7,MonthList,0)<=7,12,19-MATCH($L7,MonthList,0))/12) -> 0.16374 | P7: No | R7: =IF(AND($P7="Yes",$G7<>"Vendor day rates"),$J7-0.4*$I7,0) -> 0 | S7: =IF(OR($P7<>"Yes",$Q7=""),0,$R7*MAX(0,7-MATCH($Q7,MonthList,0))/12) -> 0 | T7: =IF(OR($P7<>"Yes",$Q7=""),0,$R7*IF(MATCH($Q7,MonthList,0)<=7,12,19-MATCH($Q7,MonthList,0))/12) -> 0 | U7: No | W7: =IF(AND($U7="Yes",$G7<>"Vendor day rates"),$J7-0.4*$I7,0) -> 0 | X7: =IF(OR($U7<>"Yes",$V7=""),0,$W7*MAX(0,7-MATCH($V7,MonthList,0))/12) -> 0 | Y7: =IF(OR($U7<>"Yes",$V7=""),0,$W7*IF(MATCH($V7,MonthList,0)<=7,12,19-MATCH($V7,MonthList,0))/12) -> 0
B8: R0003 | C8: Snr Business Analyst | D8: Ampol Customer | E8: Ampol App | F8: AU | G8: Filled | H8: 1 | I8: 0.2591 | J8: 0.2591 | K8: No | M8: =IF(AND($K8="Yes",$G8<>"Vendor day rates"),$J8-0.4*$I8,0) -> 0 | N8: =IF(OR($K8<>"Yes",$L8=""),0,$M8*MAX(0,7-MATCH($L8,MonthList,0))/12) -> 0 | O8: =IF(OR($K8<>"Yes",$L8=""),0,$M8*IF(MATCH($L8,MonthList,0)<=7,12,19-MATCH($L8,MonthList,0))/12) -> 0 | P8: No | R8: =IF(AND($P8="Yes",$G8<>"Vendor day rates"),$J8-0.4*$I8,0) -> 0 | S8: =IF(OR($P8<>"Yes",$Q8=""),0,$R8*MAX(0,7-MATCH($Q8,MonthList,0))/12) -> 0 | T8: =IF(OR($P8<>"Yes",$Q8=""),0,$R8*IF(MATCH($Q8,MonthList,0)<=7,12,19-MATCH($Q8,MonthList,0))/12) -> 0 | U8: No | W8: =IF(AND($U8="Yes",$G8<>"Vendor day rates"),$J8-0.4*$I8,0) -> 0 | X8: =IF(OR($U8<>"Yes",$V8=""),0,$W8*MAX(0,7-MATCH($V8,MonthList,0))/12) -> 0 | Y8: =IF(OR($U8<>"Yes",$V8=""),0,$W8*IF(MATCH($V8,MonthList,0)<=7,12,19-MATCH($V8,MonthList,0))/12) -> 0
B9: R0004 | C9: Business Analyst (SAP Payroll) | D9: EGI | E9: EGI | F9: AU | G9: Filled | H9: 1 | I9: 0.2442 | J9: 0.2442 | K9: No | M9: =IF(AND($K9="Yes",$G9<>"Vendor day rates"),$J9-0.4*$I9,0) -> 0 | N9: =IF(OR($K9<>"Yes",$L9=""),0,$M9*MAX(0,7-MATCH($L9,MonthList,0))/12) -> 0 | O9: =IF(OR($K9<>"Yes",$L9=""),0,$M9*IF(MATCH($L9,MonthList,0)<=7,12,19-MATCH($L9,MonthList,0))/12) -> 0 | P9: No | R9: =IF(AND($P9="Yes",$G9<>"Vendor day rates"),$J9-0.4*$I9,0) -> 0 | S9: =IF(OR($P9<>"Yes",$Q9=""),0,$R9*MAX(0,7-MATCH($Q9,MonthList,0))/12) -> 0 | T9: =IF(OR($P9<>"Yes",$Q9=""),0,$R9*IF(MATCH($Q9,MonthList,0)<=7,12,19-MATCH($Q9,MonthList,0))/12) -> 0 | U9: No | W9: =IF(AND($U9="Yes",$G9<>"Vendor day rates"),$J9-0.4*$I9,0) -> 0 | X9: =IF(OR($U9<>"Yes",$V9=""),0,$W9*MAX(0,7-MATCH($V9,MonthList,0))/12) -> 0 | Y9: =IF(OR($U9<>"Yes",$V9=""),0,$W9*IF(MATCH($V9,MonthList,0)<=7,12,19-MATCH($V9,MonthList,0))/12) -> 0
B10: R0005 | C10: Project Manager (PEP13-EGI-UKG) | D10: EGI | E10: EGI | F10: AU | G10: Filled | H10: 1 | I10: 0.2442 | J10: 0.2442 | K10: No | M10: =IF(AND($K10="Yes",$G10<>"Vendor day rates"),$J10-0.4*$I10,0) -> 0 | N10: =IF(OR($K10<>"Yes",$L10=""),0,$M10*MAX(0,7-MATCH($L10,MonthList,0))/12) -> 0 | O10: =IF(OR($K10<>"Yes",$L10=""),0,$M10*IF(MATCH($L10,MonthList,0)<=7,12,19-MATCH($L10,MonthList,0))/12) -> 0 | P10: No | R10: =IF(AND($P10="Yes",$G10<>"Vendor day rates"),$J10-0.4*$I10,0) -> 0 | S10: =IF(OR($P10<>"Yes",$Q10=""),0,$R10*MAX(0,7-MATCH($Q10,MonthList,0))/12) -> 0 | T10: =IF(OR($P10<>"Yes",$Q10=""),0,$R10*IF(MATCH($Q10,MonthList,0)<=7,12,19-MATCH($Q10,MonthList,0))/12) -> 0 | U10: No | W10: =IF(AND($U10="Yes",$G10<>"Vendor day rates"),$J10-0.4*$I10,0) -> 0 | X10: =IF(OR($U10<>"Yes",$V10=""),0,$W10*MAX(0,7-MATCH($V10,MonthList,0))/12) -> 0 | Y10: =IF(OR($U10<>"Yes",$V10=""),0,$W10*IF(MATCH($V10,MonthList,0)<=7,12,19-MATCH($V10,MonthList,0))/12) -> 0
B11: R0006 | C11: Program Architect | D11: EGI | E11: EGI | F11: AU | G11: Filled | H11: 1 | I11: 0.3108 | J11: 0.3108 | K11: No | M11: =IF(AND($K11="Yes",$G11<>"Vendor day rates"),$J11-0.4*$I11,0) -> 0 | N11: =IF(OR($K11<>"Yes",$L11=""),0,$M11*MAX(0,7-MATCH($L11,MonthList,0))/12) -> 0 | O11: =IF(OR($K11<>"Yes",$L11=""),0,$M11*IF(MATCH($L11,MonthList,0)<=7,12,19-MATCH($L11,MonthList,0))/12) -> 0 | P11: No | R11: =IF(AND($P11="Yes",$G11<>"Vendor day rates"),$J11-0.4*$I11,0) -> 0 | S11: =IF(OR($P11<>"Yes",$Q11=""),0,$R11*MAX(0,7-MATCH($Q11,MonthList,0))/12) -> 0 | T11: =IF(OR($P11<>"Yes",$Q11=""),0,$R11*IF(MATCH($Q11,MonthList,0)<=7,12,19-MATCH($Q11,MonthList,0))/12) -> 0 | U11: No | W11: =IF(AND($U11="Yes",$G11<>"Vendor day rates"),$J11-0.4*$I11,0) -> 0 | X11: =IF(OR($U11<>"Yes",$V11=""),0,$W11*MAX(0,7-MATCH($V11,MonthList,0))/12) -> 0 | Y11: =IF(OR($U11<>"Yes",$V11=""),0,$W11*IF(MATCH($V11,MonthList,0)<=7,12,19-MATCH($V11,MonthList,0))/12) -> 0
B12: R0007 | C12: TDD Strategic Delivery | D12: EGI | E12: EGI | F12: AU | G12: Filled | H12: 1 | I12: 0.2775 | J12: 0.2775 | K12: No | M12: =IF(AND($K12="Yes",$G12<>"Vendor day rates"),$J12-0.4*$I12,0) -> 0 | N12: =IF(OR($K12<>"Yes",$L12=""),0,$M12*MAX(0,7-MATCH($L12,MonthList,0))/12) -> 0 | O12: =IF(OR($K12<>"Yes",$L12=""),0,$M12*IF(MATCH($L12,MonthList,0)<=7,12,19-MATCH($L12,MonthList,0))/12) -> 0 | P12: No | R12: =IF(AND($P12="Yes",$G12<>"Vendor day rates"),$J12-0.4*$I12,0) -> 0 | S12: =IF(OR($P12<>"Yes",$Q12=""),0,$R12*MAX(0,7-MATCH($Q12,MonthList,0))/12) -> 0 | T12: =IF(OR($P12<>"Yes",$Q12=""),0,$R12*IF(MATCH($Q12,MonthList,0)<=7,12,19-MATCH($Q12,MonthList,0))/12) -> 0 | U12: No | W12: =IF(AND($U12="Yes",$G12<>"Vendor day rates"),$J12-0.4*$I12,0) -> 0 | X12: =IF(OR($U12<>"Yes",$V12=""),0,$W12*MAX(0,7-MATCH($V12,MonthList,0))/12) -> 0 | Y12: =IF(OR($U12<>"Yes",$V12=""),0,$W12*IF(MATCH($V12,MonthList,0)<=7,12,19-MATCH($V12,MonthList,0))/12) -> 0
B13: R0008 | C13: Strategic Delivery Consultant | D13: EGI | E13: EGI | F13: AU | G13: Filled | H13: 1 | I13: 0.3013 | J13: 0.3013 | K13: No | M13: =IF(AND($K13="Yes",$G13<>"Vendor day rates"),$J13-0.4*$I13,0) -> 0 | N13: =IF(OR($K13<>"Yes",$L13=""),0,$M13*MAX(0,7-MATCH($L13,MonthList,0))/12) -> 0 | O13: =IF(OR($K13<>"Yes",$L13=""),0,$M13*IF(MATCH($L13,MonthList,0)<=7,12,19-MATCH($L13,MonthList,0))/12) -> 0 | P13: No | R13: =IF(AND($P13="Yes",$G13<>"Vendor day rates"),$J13-0.4*$I13,0) -> 0 | S13: =IF(OR($P13<>"Yes",$Q13=""),0,$R13*MAX(0,7-MATCH($Q13,MonthList,0))/12) -> 0 | T13: =IF(OR($P13<>"Yes",$Q13=""),0,$R13*IF(MATCH($Q13,MonthList,0)<=7,12,19-MATCH($Q13,MonthList,0))/12) -> 0 | U13: No | W13: =IF(AND($U13="Yes",$G13<>"Vendor day rates"),$J13-0.4*$I13,0) -> 0 | X13: =IF(OR($U13<>"Yes",$V13=""),0,$W13*MAX(0,7-MATCH($V13,MonthList,0))/12) -> 0 | Y13: =IF(OR($U13<>"Yes",$V13=""),0,$W13*IF(MATCH($V13,MonthList,0)<=7,12,19-MATCH($V13,MonthList,0))/12) -> 0
B14: R0009 | C14: Program Manager (PEP13-EGI-UKG) | D14: EGI | E14: EGI | F14: AU | G14: Filled | H14: 1 | I14: 0.3432 | J14: 0.3432 | K14: No | M14: =IF(AND($K14="Yes",$G14<>"Vendor day rates"),$J14-0.4*$I14,0) -> 0 | N14: =IF(OR($K14<>"Yes",$L14=""),0,$M14*MAX(0,7-MATCH($L14,MonthList,0))/12) -> 0 | O14: =IF(OR($K14<>"Yes",$L14=""),0,$M14*IF(MATCH($L14,MonthList,0)<=7,12,19-MATCH($L14,MonthList,0))/12) -> 0 | P14: No | R14: =IF(AND($P14="Yes",$G14<>"Vendor day rates"),$J14-0.4*$I14,0) -> 0 | S14: =IF(OR($P14<>"Yes",$Q14=""),0,$R14*MAX(0,7-MATCH($Q14,MonthList,0))/12) -> 0 | T14: =IF(OR($P14<>"Yes",$Q14=""),0,$R14*IF(MATCH($Q14,MonthList,0)<=7,12,19-MATCH($Q14,MonthList,0))/12) -> 0 | U14: No | W14: =IF(AND($U14="Yes",$G14<>"Vendor day rates"),$J14-0.4*$I14,0) -> 0 | X14: =IF(OR($U14<>"Yes",$V14=""),0,$W14*MAX(0,7-MATCH($V14,MonthList,0))/12) -> 0 | Y14: =IF(OR($U14<>"Yes",$V14=""),0,$W14*IF(MATCH($V14,MonthList,0)<=7,12,19-MATCH($V14,MonthList,0))/12) -> 0
B15: R0010 | C15: Program Manager Tech & P&C | D15: EGI | E15: EGI | F15: AU | G15: Filled | H15: 1 | I15: 0.2664 | J15: 0.2664 | K15: No | M15: =IF(AND($K15="Yes",$G15<>"Vendor day rates"),$J15-0.4*$I15,0) -> 0 | N15: =IF(OR($K15<>"Yes",$L15=""),0,$M15*MAX(0,7-MATCH($L15,MonthList,0))/12) -> 0 | O15: =IF(OR($K15<>"Yes",$L15=""),0,$M15*IF(MATCH($L15,MonthList,0)<=7,12,19-MATCH($L15,MonthList,0))/12) -> 0 | P15: No | R15: =IF(AND($P15="Yes",$G15<>"Vendor day rates"),$J15-0.4*$I15,0) -> 0 | S15: =IF(OR($P15<>"Yes",$Q15=""),0,$R15*MAX(0,7-MATCH($Q15,MonthList,0))/12) -> 0 | T15: =IF(OR($P15<>"Yes",$Q15=""),0,$R15*IF(MATCH($Q15,MonthList,0)<=7,12,19-MATCH($Q15,MonthList,0))/12) -> 0 | U15: No | W15: =IF(AND($U15="Yes",$G15<>"Vendor day rates"),$J15-0.4*$I15,0) -> 0 | X15: =IF(OR($U15<>"Yes",$V15=""),0,$W15*MAX(0,7-MATCH($V15,MonthList,0))/12) -> 0 | Y15: =IF(OR($U15<>"Yes",$V15=""),0,$W15*IF(MATCH($V15,MonthList,0)<=7,12,19-MATCH($V15,MonthList,0))/12) -> 0
B16: R0011 | C16: Project Manager Retail | D16: EGI | E16: EGI | F16: AU | G16: Filled | H16: 1 | I16: 0.4884 | J16: 0.4884 | K16: No | M16: =IF(AND($K16="Yes",$G16<>"Vendor day rates"),$J16-0.4*$I16,0) -> 0 | N16: =IF(OR($K16<>"Yes",$L16=""),0,$M16*MAX(0,7-MATCH($L16,MonthList,0))/12) -> 0 | O16: =IF(OR($K16<>"Yes",$L16=""),0,$M16*IF(MATCH($L16,MonthList,0)<=7,12,19-MATCH($L16,MonthList,0))/12) -> 0 | P16: No | R16: =IF(AND($P16="Yes",$G16<>"Vendor day rates"),$J16-0.4*$I16,0) -> 0 | S16: =IF(OR($P16<>"Yes",$Q16=""),0,$R16*MAX(0,7-MATCH($Q16,MonthList,0))/12) -> 0 | T16: =IF(OR($P16<>"Yes",$Q16=""),0,$R16*IF(MATCH($Q16,MonthList,0)<=7,12,19-MATCH($Q16,MonthList,0))/12) -> 0 | U16: No | W16: =IF(AND($U16="Yes",$G16<>"Vendor day rates"),$J16-0.4*$I16,0) -> 0 | X16: =IF(OR($U16<>"Yes",$V16=""),0,$W16*MAX(0,7-MATCH($V16,MonthList,0))/12) -> 0 | Y16: =IF(OR($U16<>"Yes",$V16=""),0,$W16*IF(MATCH($V16,MonthList,0)<=7,12,19-MATCH($V16,MonthList,0))/12) -> 0
B17: R0012 | C17: Strategic Delivery Consultant | D17: EGI | E17: EGI | F17: AU | G17: Filled | H17: 1 | I17: 0.2997 | J17: 0.2997 | K17: No | M17: =IF(AND($K17="Yes",$G17<>"Vendor day rates"),$J17-0.4*$I17,0) -> 0 | N17: =IF(OR($K17<>"Yes",$L17=""),0,$M17*MAX(0,7-MATCH($L17,MonthList,0))/12) -> 0 | O17: =IF(OR($K17<>"Yes",$L17=""),0,$M17*IF(MATCH($L17,MonthList,0)<=7,12,19-MATCH($L17,MonthList,0))/12) -> 0 | P17: No | R17: =IF(AND($P17="Yes",$G17<>"Vendor day rates"),$J17-0.4*$I17,0) -> 0 | S17: =IF(OR($P17<>"Yes",$Q17=""),0,$R17*MAX(0,7-MATCH($Q17,MonthList,0))/12) -> 0 | T17: =IF(OR($P17<>"Yes",$Q17=""),0,$R17*IF(MATCH($Q17,MonthList,0)<=7,12,19-MATCH($Q17,MonthList,0))/12) -> 0 | U17: No | W17: =IF(AND($U17="Yes",$G17<>"Vendor day rates"),$J17-0.4*$I17,0) -> 0 | X17: =IF(OR($U17<>"Yes",$V17=""),0,$W17*MAX(0,7-MATCH($V17,MonthList,0))/12) -> 0 | Y17: =IF(OR($U17<>"Yes",$V17=""),0,$W17*IF(MATCH($V17,MonthList,0)<=7,12,19-MATCH($V17,MonthList,0))/12) -> 0
B18: R0013 | C18: Strategic Delivery Consultant | D18: EGI | E18: EGI | F18: AU | G18: Filled | H18: 1 | I18: 0.2304 | J18: 0.2304 | K18: No | M18: =IF(AND($K18="Yes",$G18<>"Vendor day rates"),$J18-0.4*$I18,0) -> 0 | N18: =IF(OR($K18<>"Yes",$L18=""),0,$M18*MAX(0,7-MATCH($L18,MonthList,0))/12) -> 0 | O18: =IF(OR($K18<>"Yes",$L18=""),0,$M18*IF(MATCH($L18,MonthList,0)<=7,12,19-MATCH($L18,MonthList,0))/12) -> 0 | P18: No | R18: =IF(AND($P18="Yes",$G18<>"Vendor day rates"),$J18-0.4*$I18,0) -> 0 | S18: =IF(OR($P18<>"Yes",$Q18=""),0,$R18*MAX(0,7-MATCH($Q18,MonthList,0))/12) -> 0 | T18: =IF(OR($P18<>"Yes",$Q18=""),0,$R18*IF(MATCH($Q18,MonthList,0)<=7,12,19-MATCH($Q18,MonthList,0))/12) -> 0 | U18: No | W18: =IF(AND($U18="Yes",$G18<>"Vendor day rates"),$J18-0.4*$I18,0) -> 0 | X18: =IF(OR($U18<>"Yes",$V18=""),0,$W18*MAX(0,7-MATCH($V18,MonthList,0))/12) -> 0 | Y18: =IF(OR($U18<>"Yes",$V18=""),0,$W18*IF(MATCH($V18,MonthList,0)<=7,12,19-MATCH($V18,MonthList,0))/12) -> 0
B19: R0014 | C19: Project Manager Deployment | E19: EGI | F19: AU | G19: Filled | H19: 1 | I19: 0.2664 | J19: 0.2664 | K19: No | M19: =IF(AND($K19="Yes",$G19<>"Vendor day rates"),$J19-0.4*$I19,0) -> 0 | N19: =IF(OR($K19<>"Yes",$L19=""),0,$M19*MAX(0,7-MATCH($L19,MonthList,0))/12) -> 0 | O19: =IF(OR($K19<>"Yes",$L19=""),0,$M19*IF(MATCH($L19,MonthList,0)<=7,12,19-MATCH($L19,MonthList,0))/12) -> 0 | P19: No | R19: =IF(AND($P19="Yes",$G19<>"Vendor day rates"),$J19-0.4*$I19,0) -> 0 | S19: =IF(OR($P19<>"Yes",$Q19=""),0,$R19*MAX(0,7-MATCH($Q19,MonthList,0))/12) -> 0 | T19: =IF(OR($P19<>"Yes",$Q19=""),0,$R19*IF(MATCH($Q19,MonthList,0)<=7,12,19-MATCH($Q19,MonthList,0))/12) -> 0 | U19: No | W19: =IF(AND($U19="Yes",$G19<>"Vendor day rates"),$J19-0.4*$I19,0) -> 0 | X19: =IF(OR($U19<>"Yes",$V19=""),0,$W19*MAX(0,7-MATCH($V19,MonthList,0))/12) -> 0 | Y19: =IF(OR($U19<>"Yes",$V19=""),0,$W19*IF(MATCH($V19,MonthList,0)<=7,12,19-MATCH($V19,MonthList,0))/12) -> 0
B20: R0015 | C20: Reporting Analyst | D20: Infrastructure | E20: Data & Insights | F20: AU | G20: Filled | H20: 1 | I20: 0.1976 | J20: 0.1976 | K20: No | M20: =IF(AND($K20="Yes",$G20<>"Vendor day rates"),$J20-0.4*$I20,0) -> 0 | N20: =IF(OR($K20<>"Yes",$L20=""),0,$M20*MAX(0,7-MATCH($L20,MonthList,0))/12) -> 0 | O20: =IF(OR($K20<>"Yes",$L20=""),0,$M20*IF(MATCH($L20,MonthList,0)<=7,12,19-MATCH($L20,MonthList,0))/12) -> 0 | P20: No | R20: =IF(AND($P20="Yes",$G20<>"Vendor day rates"),$J20-0.4*$I20,0) -> 0 | S20: =IF(OR($P20<>"Yes",$Q20=""),0,$R20*MAX(0,7-MATCH($Q20,MonthList,0))/12) -> 0 | T20: =IF(OR($P20<>"Yes",$Q20=""),0,$R20*IF(MATCH($Q20,MonthList,0)<=7,12,19-MATCH($Q20,MonthList,0))/12) -> 0 | U20: No | W20: =IF(AND($U20="Yes",$G20<>"Vendor day rates"),$J20-0.4*$I20,0) -> 0 | X20: =IF(OR($U20<>"Yes",$V20=""),0,$W20*MAX(0,7-MATCH($V20,MonthList,0))/12) -> 0 | Y20: =IF(OR($U20<>"Yes",$V20=""),0,$W20*IF(MATCH($V20,MonthList,0)<=7,12,19-MATCH($V20,MonthList,0))/12) -> 0
B21: R0016 | C21: QA / Tester / Mid | D21: Ampol Customer | E21: Ampol Loyalty & Martech | F21: AU | G21: Vendor day rates | H21: 1 | I21: 0.0733 | J21: 0.0733 | K21: No | M21: =IF(AND($K21="Yes",$G21<>"Vendor day rates"),$J21-0.4*$I21,0) -> 0 | N21: =IF(OR($K21<>"Yes",$L21=""),0,$M21*MAX(0,7-MATCH($L21,MonthList,0))/12) -> 0 | O21: =IF(OR($K21<>"Yes",$L21=""),0,$M21*IF(MATCH($L21,MonthList,0)<=7,12,19-MATCH($L21,MonthList,0))/12) -> 0 | P21: No | R21: =IF(AND($P21="Yes",$G21<>"Vendor day rates"),$J21-0.4*$I21,0) -> 0 | S21: =IF(OR($P21<>"Yes",$Q21=""),0,$R21*MAX(0,7-MATCH($Q21,MonthList,0))/12) -> 0 | T21: =IF(OR($P21<>"Yes",$Q21=""),0,$R21*IF(MATCH($Q21,MonthList,0)<=7,12,19-MATCH($Q21,MonthList,0))/12) -> 0 | U21: No | W21: =IF(AND($U21="Yes",$G21<>"Vendor day rates"),$J21-0.4*$I21,0) -> 0 | X21: =IF(OR($U21<>"Yes",$V21=""),0,$W21*MAX(0,7-MATCH($V21,MonthList,0))/12) -> 0 | Y21: =IF(OR($U21<>"Yes",$V21=""),0,$W21*IF(MATCH($V21,MonthList,0)<=7,12,19-MATCH($V21,MonthList,0))/12) -> 0
B22: R0017 | C22: Systems Analyst / Mid | D22: Ampol Customer | E22: Ampol Loyalty & Martech | F22: AU | G22: Vendor day rates | H22: 1 | I22: 0.0733 | J22: 0.0733 | K22: No | M22: =IF(AND($K22="Yes",$G22<>"Vendor day rates"),$J22-0.4*$I22,0) -> 0 | N22: =IF(OR($K22<>"Yes",$L22=""),0,$M22*MAX(0,7-MATCH($L22,MonthList,0))/12) -> 0 | O22: =IF(OR($K22<>"Yes",$L22=""),0,$M22*IF(MATCH($L22,MonthList,0)<=7,12,19-MATCH($L22,MonthList,0))/12) -> 0 | P22: No | R22: =IF(AND($P22="Yes",$G22<>"Vendor day rates"),$J22-0.4*$I22,0) -> 0 | S22: =IF(OR($P22<>"Yes",$Q22=""),0,$R22*MAX(0,7-MATCH($Q22,MonthList,0))/12) -> 0 | T22: =IF(OR($P22<>"Yes",$Q22=""),0,$R22*IF(MATCH($Q22,MonthList,0)<=7,12,19-MATCH($Q22,MonthList,0))/12) -> 0 | U22: No | W22: =IF(AND($U22="Yes",$G22<>"Vendor day rates"),$J22-0.4*$I22,0) -> 0 | X22: =IF(OR($U22<>"Yes",$V22=""),0,$W22*MAX(0,7-MATCH($V22,MonthList,0))/12) -> 0 | Y22: =IF(OR($U22<>"Yes",$V22=""),0,$W22*IF(MATCH($V22,MonthList,0)<=7,12,19-MATCH($V22,MonthList,0))/12) -> 0
B23: R0018 | C23: Data Migration Lead | D23: EGI Integration | E23: EGI TDD | F23: AU | G23: Filled | H23: 1 | I23: 0.2997 | J23: 0.2997 | K23: No | M23: =IF(AND($K23="Yes",$G23<>"Vendor day rates"),$J23-0.4*$I23,0) -> 0 | N23: =IF(OR($K23<>"Yes",$L23=""),0,$M23*MAX(0,7-MATCH($L23,MonthList,0))/12) -> 0 | O23: =IF(OR($K23<>"Yes",$L23=""),0,$M23*IF(MATCH($L23,MonthList,0)<=7,12,19-MATCH($L23,MonthList,0))/12) -> 0 | P23: No | R23: =IF(AND($P23="Yes",$G23<>"Vendor day rates"),$J23-0.4*$I23,0) -> 0 | S23: =IF(OR($P23<>"Yes",$Q23=""),0,$R23*MAX(0,7-MATCH($Q23,MonthList,0))/12) -> 0 | T23: =IF(OR($P23<>"Yes",$Q23=""),0,$R23*IF(MATCH($Q23,MonthList,0)<=7,12,19-MATCH($Q23,MonthList,0))/12) -> 0 | U23: No | W23: =IF(AND($U23="Yes",$G23<>"Vendor day rates"),$J23-0.4*$I23,0) -> 0 | X23: =IF(OR($U23<>"Yes",$V23=""),0,$W23*MAX(0,7-MATCH($V23,MonthList,0))/12) -> 0 | Y23: =IF(OR($U23<>"Yes",$V23=""),0,$W23*IF(MATCH($V23,MonthList,0)<=7,12,19-MATCH($V23,MonthList,0))/12) -> 0
B24: R0019 | C24: .NET Back End Developer / Mid | D24: Ampol Customer | E24: Digital Operations | F24: AU | G24: Vendor day rates | H24: 1 | I24: 0.0733 | J24: 0.0733 | K24: No | M24: =IF(AND($K24="Yes",$G24<>"Vendor day rates"),$J24-0.4*$I24,0) -> 0 | N24: =IF(OR($K24<>"Yes",$L24=""),0,$M24*MAX(0,7-MATCH($L24,MonthList,0))/12) -> 0 | O24: =IF(OR($K24<>"Yes",$L24=""),0,$M24*IF(MATCH($L24,MonthList,0)<=7,12,19-MATCH($L24,MonthList,0))/12) -> 0 | P24: No | R24: =IF(AND($P24="Yes",$G24<>"Vendor day rates"),$J24-0.4*$I24,0) -> 0 | S24: =IF(OR($P24<>"Yes",$Q24=""),0,$R24*MAX(0,7-MATCH($Q24,MonthList,0))/12) -> 0 | T24: =IF(OR($P24<>"Yes",$Q24=""),0,$R24*IF(MATCH($Q24,MonthList,0)<=7,12,19-MATCH($Q24,MonthList,0))/12) -> 0 | U24: No | W24: =IF(AND($U24="Yes",$G24<>"Vendor day rates"),$J24-0.4*$I24,0) -> 0 | X24: =IF(OR($U24<>"Yes",$V24=""),0,$W24*MAX(0,7-MATCH($V24,MonthList,0))/12) -> 0 | Y24: =IF(OR($U24<>"Yes",$V24=""),0,$W24*IF(MATCH($V24,MonthList,0)<=7,12,19-MATCH($V24,MonthList,0))/12) -> 0
B25: R0020 | C25: .NET Back End Developer / Mid | D25: Ampol Customer | E25: Digital Operations | F25: AU | G25: Vendor day rates | H25: 1 | I25: 0.0733 | J25: 0.0733 | K25: No | M25: =IF(AND($K25="Yes",$G25<>"Vendor day rates"),$J25-0.4*$I25,0) -> 0 | N25: =IF(OR($K25<>"Yes",$L25=""),0,$M25*MAX(0,7-MATCH($L25,MonthList,0))/12) -> 0 | O25: =IF(OR($K25<>"Yes",$L25=""),0,$M25*IF(MATCH($L25,MonthList,0)<=7,12,19-MATCH($L25,MonthList,0))/12) -> 0 | P25: No | R25: =IF(AND($P25="Yes",$G25<>"Vendor day rates"),$J25-0.4*$I25,0) -> 0 | S25: =IF(OR($P25<>"Yes",$Q25=""),0,$R25*MAX(0,7-MATCH($Q25,MonthList,0))/12) -> 0 | T25: =IF(OR($P25<>"Yes",$Q25=""),0,$R25*IF(MATCH($Q25,MonthList,0)<=7,12,19-MATCH($Q25,MonthList,0))/12) -> 0 | U25: No | W25: =IF(AND($U25="Yes",$G25<>"Vendor day rates"),$J25-0.4*$I25,0) -> 0 | X25: =IF(OR($U25<>"Yes",$V25=""),0,$W25*MAX(0,7-MATCH($V25,MonthList,0))/12) -> 0 | Y25: =IF(OR($U25<>"Yes",$V25=""),0,$W25*IF(MATCH($V25,MonthList,0)<=7,12,19-MATCH($V25,MonthList,0))/12) -> 0
B26: R0021 | C26: .NET Back End Developer / Mid | D26: Ampol Customer | E26: Digital Operations | F26: AU | G26: Vendor day rates | H26: 1 | I26: 0.0733 | J26: 0.0733 | K26: No | M26: =IF(AND($K26="Yes",$G26<>"Vendor day rates"),$J26-0.4*$I26,0) -> 0 | N26: =IF(OR($K26<>"Yes",$L26=""),0,$M26*MAX(0,7-MATCH($L26,MonthList,0))/12) -> 0 | O26: =IF(OR($K26<>"Yes",$L26=""),0,$M26*IF(MATCH($L26,MonthList,0)<=7,12,19-MATCH($L26,MonthList,0))/12) -> 0 | P26: No | R26: =IF(AND($P26="Yes",$G26<>"Vendor day rates"),$J26-0.4*$I26,0) -> 0 | S26: =IF(OR($P26<>"Yes",$Q26=""),0,$R26*MAX(0,7-MATCH($Q26,MonthList,0))/12) -> 0 | T26: =IF(OR($P26<>"Yes",$Q26=""),0,$R26*IF(MATCH($Q26,MonthList,0)<=7,12,19-MATCH($Q26,MonthList,0))/12) -> 0 | U26: No | W26: =IF(AND($U26="Yes",$G26<>"Vendor day rates"),$J26-0.4*$I26,0) -> 0 | X26: =IF(OR($U26<>"Yes",$V26=""),0,$W26*MAX(0,7-MATCH($V26,MonthList,0))/12) -> 0 | Y26: =IF(OR($U26<>"Yes",$V26=""),0,$W26*IF(MATCH($V26,MonthList,0)<=7,12,19-MATCH($V26,MonthList,0))/12) -> 0
B27: R0022 | C27: QA / Tester / Mid | D27: Ampol Customer | E27: Digital Operations | F27: AU | G27: Vendor day rates | H27: 1 | I27: 0.0733 | J27: 0.0733 | K27: No | M27: =IF(AND($K27="Yes",$G27<>"Vendor day rates"),$J27-0.4*$I27,0) -> 0 | N27: =IF(OR($K27<>"Yes",$L27=""),0,$M27*MAX(0,7-MATCH($L27,MonthList,0))/12) -> 0 | O27: =IF(OR($K27<>"Yes",$L27=""),0,$M27*IF(MATCH($L27,MonthList,0)<=7,12,19-MATCH($L27,MonthList,0))/12) -> 0 | P27: No | R27: =IF(AND($P27="Yes",$G27<>"Vendor day rates"),$J27-0.4*$I27,0) -> 0 | S27: =IF(OR($P27<>"Yes",$Q27=""),0,$R27*MAX(0,7-MATCH($Q27,MonthList,0))/12) -> 0 | T27: =IF(OR($P27<>"Yes",$Q27=""),0,$R27*IF(MATCH($Q27,MonthList,0)<=7,12,19-MATCH($Q27,MonthList,0))/12) -> 0 | U27: No | W27: =IF(AND($U27="Yes",$G27<>"Vendor day rates"),$J27-0.4*$I27,0) -> 0 | X27: =IF(OR($U27<>"Yes",$V27=""),0,$W27*MAX(0,7-MATCH($V27,MonthList,0))/12) -> 0 | Y27: =IF(OR($U27<>"Yes",$V27=""),0,$W27*IF(MATCH($V27,MonthList,0)<=7,12,19-MATCH($V27,MonthList,0))/12) -> 0
B28: R0023 | C28: Integration Architect (C) - Boomi | D28: EGI | E28: EGI TDD | F28: AU | G28: Filled | H28: 1 | I28: 0.3481 | J28: 0.3481 | K28: No | M28: =IF(AND($K28="Yes",$G28<>"Vendor day rates"),$J28-0.4*$I28,0) -> 0 | N28: =IF(OR($K28<>"Yes",$L28=""),0,$M28*MAX(0,7-MATCH($L28,MonthList,0))/12) -> 0 | O28: =IF(OR($K28<>"Yes",$L28=""),0,$M28*IF(MATCH($L28,MonthList,0)<=7,12,19-MATCH($L28,MonthList,0))/12) -> 0 | P28: No | R28: =IF(AND($P28="Yes",$G28<>"Vendor day rates"),$J28-0.4*$I28,0) -> 0 | S28: =IF(OR($P28<>"Yes",$Q28=""),0,$R28*MAX(0,7-MATCH($Q28,MonthList,0))/12) -> 0 | T28: =IF(OR($P28<>"Yes",$Q28=""),0,$R28*IF(MATCH($Q28,MonthList,0)<=7,12,19-MATCH($Q28,MonthList,0))/12) -> 0 | U28: No | W28: =IF(AND($U28="Yes",$G28<>"Vendor day rates"),$J28-0.4*$I28,0) -> 0 | X28: =IF(OR($U28<>"Yes",$V28=""),0,$W28*MAX(0,7-MATCH($V28,MonthList,0))/12) -> 0 | Y28: =IF(OR($U28<>"Yes",$V28=""),0,$W28*IF(MATCH($V28,MonthList,0)<=7,12,19-MATCH($V28,MonthList,0))/12) -> 0
B29: R0024 | C29: Integration Architect (C) | D29: EGI | E29: EGI TDD | F29: NZ | G29: Filled | H29: 1 | I29: 0.2664 | J29: 0.2664 | K29: No | M29: =IF(AND($K29="Yes",$G29<>"Vendor day rates"),$J29-0.4*$I29,0) -> 0 | N29: =IF(OR($K29<>"Yes",$L29=""),0,$M29*MAX(0,7-MATCH($L29,MonthList,0))/12) -> 0 | O29: =IF(OR($K29<>"Yes",$L29=""),0,$M29*IF(MATCH($L29,MonthList,0)<=7,12,19-MATCH($L29,MonthList,0))/12) -> 0 | P29: No | R29: =IF(AND($P29="Yes",$G29<>"Vendor day rates"),$J29-0.4*$I29,0) -> 0 | S29: =IF(OR($P29<>"Yes",$Q29=""),0,$R29*MAX(0,7-MATCH($Q29,MonthList,0))/12) -> 0 | T29: =IF(OR($P29<>"Yes",$Q29=""),0,$R29*IF(MATCH($Q29,MonthList,0)<=7,12,19-MATCH($Q29,MonthList,0))/12) -> 0 | U29: No | W29: =IF(AND($U29="Yes",$G29<>"Vendor day rates"),$J29-0.4*$I29,0) -> 0 | X29: =IF(OR($U29<>"Yes",$V29=""),0,$W29*MAX(0,7-MATCH($V29,MonthList,0))/12) -> 0 | Y29: =IF(OR($U29<>"Yes",$V29=""),0,$W29*IF(MATCH($V29,MonthList,0)<=7,12,19-MATCH($V29,MonthList,0))/12) -> 0
B30: R0025 | C30: Engineer - Mobile | D30: Ampol Customer | E30: Ampol App | F30: AU | G30: Filled | H30: 1 | I30: 0.1909 | J30: 0.1909 | K30: No | M30: =IF(AND($K30="Yes",$G30<>"Vendor day rates"),$J30-0.4*$I30,0) -> 0 | N30: =IF(OR($K30<>"Yes",$L30=""),0,$M30*MAX(0,7-MATCH($L30,MonthList,0))/12) -> 0 | O30: =IF(OR($K30<>"Yes",$L30=""),0,$M30*IF(MATCH($L30,MonthList,0)<=7,12,19-MATCH($L30,MonthList,0))/12) -> 0 | P30: No | R30: =IF(AND($P30="Yes",$G30<>"Vendor day rates"),$J30-0.4*$I30,0) -> 0 | S30: =IF(OR($P30<>"Yes",$Q30=""),0,$R30*MAX(0,7-MATCH($Q30,MonthList,0))/12) -> 0 | T30: =IF(OR($P30<>"Yes",$Q30=""),0,$R30*IF(MATCH($Q30,MonthList,0)<=7,12,19-MATCH($Q30,MonthList,0))/12) -> 0 | U30: No | W30: =IF(AND($U30="Yes",$G30<>"Vendor day rates"),$J30-0.4*$I30,0) -> 0 | X30: =IF(OR($U30<>"Yes",$V30=""),0,$W30*MAX(0,7-MATCH($V30,MonthList,0))/12) -> 0 | Y30: =IF(OR($U30<>"Yes",$V30=""),0,$W30*IF(MATCH($V30,MonthList,0)<=7,12,19-MATCH($V30,MonthList,0))/12) -> 0
B31: R0026 | C31: Solution Architect | D31: Ampol Customer | E31: Ampol Web | F31: AU | G31: Filled | H31: 1 | I31: 0.3219 | J31: 0.3219 | K31: No | M31: =IF(AND($K31="Yes",$G31<>"Vendor day rates"),$J31-0.4*$I31,0) -> 0 | N31: =IF(OR($K31<>"Yes",$L31=""),0,$M31*MAX(0,7-MATCH($L31,MonthList,0))/12) -> 0 | O31: =IF(OR($K31<>"Yes",$L31=""),0,$M31*IF(MATCH($L31,MonthList,0)<=7,12,19-MATCH($L31,MonthList,0))/12) -> 0 | P31: No | R31: =IF(AND($P31="Yes",$G31<>"Vendor day rates"),$J31-0.4*$I31,0) -> 0 | S31: =IF(OR($P31<>"Yes",$Q31=""),0,$R31*MAX(0,7-MATCH($Q31,MonthList,0))/12) -> 0 | T31: =IF(OR($P31<>"Yes",$Q31=""),0,$R31*IF(MATCH($Q31,MonthList,0)<=7,12,19-MATCH($Q31,MonthList,0))/12) -> 0 | U31: No | W31: =IF(AND($U31="Yes",$G31<>"Vendor day rates"),$J31-0.4*$I31,0) -> 0 | X31: =IF(OR($U31<>"Yes",$V31=""),0,$W31*MAX(0,7-MATCH($V31,MonthList,0))/12) -> 0 | Y31: =IF(OR($U31<>"Yes",$V31=""),0,$W31*IF(MATCH($V31,MonthList,0)<=7,12,19-MATCH($V31,MonthList,0))/12) -> 0
... B33: R0028 | C33: Quality Assurance | D33: Ampol Customer | E33: Ampol App | F33: AU | G33: Already at the offshore rate | H33: 1 | I33: 0.1792 | J33: 0.0717 | K33: No | M33: =IF(AND($K33="Yes",$G33<>"Vendor day rates"),$J33-0.4*$I33,0) -> 0 | N33: =IF(OR($K33<>"Yes",$L33=""),0,$M33*MAX(0,7-MATCH($L33,MonthList,0))/12) -> 0 | O33: =IF(OR($K33<>"Yes",$L33=""),0,$M33*IF(MATCH($L33,MonthList,0)<=7,12,19-MATCH($L33,MonthList,0))/12) -> 0 | P33: No | R33: =IF(AND($P33="Yes",$G33<>"Vendor day rates"),$J33-0.4*$I33,0) -> 0 | S33: =IF(OR($P33<>"Yes",$Q33=""),0,$R33*MAX(0,7-MATCH($Q33,MonthList,0))/12) -> 0 | T33: =IF(OR($P33<>"Yes",$Q33=""),0,$R33*IF(MATCH($Q33,MonthList,0)<=7,12,19-MATCH($Q33,MonthList,0))/12) -> 0 | U33: No | W33: =IF(AND($U33="Yes",$G33<>"Vendor day rates"),$J33-0.4*$I33,0) -> 0 | X33: =IF(OR($U33<>"Yes",$V33=""),0,$W33*MAX(0,7-MATCH($V33,MonthList,0))/12) -> 0 | Y33: =IF(OR($U33<>"Yes",$V33=""),0,$W33*IF(MATCH($V33,MonthList,0)<=7,12,19-MATCH($V33,MonthList,0))/12) -> 0
B34: R0029 | C34: Lead Engineer - Mobile | D34: Ampol Customer | E34: Ampol App | F34: AU | G34: Already at the offshore rate | H34: 1 | I34: 0.2782 | J34: 0.1113 | K34: Yes | L34: Oct-2026 | M34: =IF(AND($K34="Yes",$G34<>"Vendor day rates"),$J34-0.4*$I34,0) -> 2e-05 | N34: =IF(OR($K34<>"Yes",$L34=""),0,$M34*MAX(0,7-MATCH($L34,MonthList,0))/12) -> 5e-06 | O34: =IF(OR($K34<>"Yes",$L34=""),0,$M34*IF(MATCH($L34,MonthList,0)<=7,12,19-MATCH($L34,MonthList,0))/12) -> 2e-05 | P34: No | R34: =IF(AND($P34="Yes",$G34<>"Vendor day rates"),$J34-0.4*$I34,0) -> 0 | S34: =IF(OR($P34<>"Yes",$Q34=""),0,$R34*MAX(0,7-MATCH($Q34,MonthList,0))/12) -> 0 | T34: =IF(OR($P34<>"Yes",$Q34=""),0,$R34*IF(MATCH($Q34,MonthList,0)<=7,12,19-MATCH($Q34,MonthList,0))/12) -> 0 | U34: No | W34: =IF(AND($U34="Yes",$G34<>"Vendor day rates"),$J34-0.4*$I34,0) -> 0 | X34: =IF(OR($U34<>"Yes",$V34=""),0,$W34*MAX(0,7-MATCH($V34,MonthList,0))/12) -> 0 | Y34: =IF(OR($U34<>"Yes",$V34=""),0,$W34*IF(MATCH($V34,MonthList,0)<=7,12,19-MATCH($V34,MonthList,0))/12) -> 0
B35: R0030 | C35: Solution Architect | D35: Ampol Customer | E35: Ampol Web | F35: AU | G35: Filled | H35: 1 | I35: 0.2431 | J35: 0.2431 | K35: No | M35: =IF(AND($K35="Yes",$G35<>"Vendor day rates"),$J35-0.4*$I35,0) -> 0 | N35: =IF(OR($K35<>"Yes",$L35=""),0,$M35*MAX(0,7-MATCH($L35,MonthList,0))/12) -> 0 | O35: =IF(OR($K35<>"Yes",$L35=""),0,$M35*IF(MATCH($L35,MonthList,0)<=7,12,19-MATCH($L35,MonthList,0))/12) -> 0 | P35: No | R35: =IF(AND($P35="Yes",$G35<>"Vendor day rates"),$J35-0.4*$I35,0) -> 0 | S35: =IF(OR($P35<>"Yes",$Q35=""),0,$R35*MAX(0,7-MATCH($Q35,MonthList,0))/12) -> 0 | T35: =IF(OR($P35<>"Yes",$Q35=""),0,$R35*IF(MATCH($Q35,MonthList,0)<=7,12,19-MATCH($Q35,MonthList,0))/12) -> 0 | U35: No | W35: =IF(AND($U35="Yes",$G35<>"Vendor day rates"),$J35-0.4*$I35,0) -> 0 | X35: =IF(OR($U35<>"Yes",$V35=""),0,$W35*MAX(0,7-MATCH($V35,MonthList,0))/12) -> 0 | Y35: =IF(OR($U35<>"Yes",$V35=""),0,$W35*IF(MATCH($V35,MonthList,0)<=7,12,19-MATCH($V35,MonthList,0))/12) -> 0
B36: R0031 | C36: Quality Assurance | D36: EGI Integration | E36: EGI Customer | F36: AU | G36: Filled | H36: 1 | I36: 0.2697 | J36: 0.2697 | K36: No | M36: =IF(AND($K36="Yes",$G36<>"Vendor day rates"),$J36-0.4*$I36,0) -> 0 | N36: =IF(OR($K36<>"Yes",$L36=""),0,$M36*MAX(0,7-MATCH($L36,MonthList,0))/12) -> 0 | O36: =IF(OR($K36<>"Yes",$L36=""),0,$M36*IF(MATCH($L36,MonthList,0)<=7,12,19-MATCH($L36,MonthList,0))/12) -> 0 | P36: No | R36: =IF(AND($P36="Yes",$G36<>"Vendor day rates"),$J36-0.4*$I36,0) -> 0 | S36: =IF(OR($P36<>"Yes",$Q36=""),0,$R36*MAX(0,7-MATCH($Q36,MonthList,0))/12) -> 0 | T36: =IF(OR($P36<>"Yes",$Q36=""),0,$R36*IF(MATCH($Q36,MonthList,0)<=7,12,19-MATCH($Q36,MonthList,0))/12) -> 0 | U36: No | W36: =IF(AND($U36="Yes",$G36<>"Vendor day rates"),$J36-0.4*$I36,0) -> 0 | X36: =IF(OR($U36<>"Yes",$V36=""),0,$W36*MAX(0,7-MATCH($V36,MonthList,0))/12) -> 0 | Y36: =IF(OR($U36<>"Yes",$V36=""),0,$W36*IF(MATCH($V36,MonthList,0)<=7,12,19-MATCH($V36,MonthList,0))/12) -> 0
B37: R0032 | C37: Delivery Lead - Integration | D37: EGI | E37: EGI | F37: AU | G37: Filled | H37: 1 | I37: 0.2735 | J37: 0.2735 | K37: No | M37: =IF(AND($K37="Yes",$G37<>"Vendor day rates"),$J37-0.4*$I37,0) -> 0 | N37: =IF(OR($K37<>"Yes",$L37=""),0,$M37*MAX(0,7-MATCH($L37,MonthList,0))/12) -> 0 | O37: =IF(OR($K37<>"Yes",$L37=""),0,$M37*IF(MATCH($L37,MonthList,0)<=7,12,19-MATCH($L37,MonthList,0))/12) -> 0 | P37: No | R37: =IF(AND($P37="Yes",$G37<>"Vendor day rates"),$J37-0.4*$I37,0) -> 0 | S37: =IF(OR($P37<>"Yes",$Q37=""),0,$R37*MAX(0,7-MATCH($Q37,MonthList,0))/12) -> 0 | T37: =IF(OR($P37<>"Yes",$Q37=""),0,$R37*IF(MATCH($Q37,MonthList,0)<=7,12,19-MATCH($Q37,MonthList,0))/12) -> 0 | U37: No | W37: =IF(AND($U37="Yes",$G37<>"Vendor day rates"),$J37-0.4*$I37,0) -> 0 | X37: =IF(OR($U37<>"Yes",$V37=""),0,$W37*MAX(0,7-MATCH($V37,MonthList,0))/12) -> 0 | Y37: =IF(OR($U37<>"Yes",$V37=""),0,$W37*IF(MATCH($V37,MonthList,0)<=7,12,19-MATCH($V37,MonthList,0))/12) -> 0
B38: R0033 | C38: SAP Solution Architect | E38: SAP ERP | F38: AU | G38: Filled | H38: 1 | I38: 0.3552 | J38: 0.3552 | K38: No | M38: =IF(AND($K38="Yes",$G38<>"Vendor day rates"),$J38-0.4*$I38,0) -> 0 | N38: =IF(OR($K38<>"Yes",$L38=""),0,$M38*MAX(0,7-MATCH($L38,MonthList,0))/12) -> 0 | O38: =IF(OR($K38<>"Yes",$L38=""),0,$M38*IF(MATCH($L38,MonthList,0)<=7,12,19-MATCH($L38,MonthList,0))/12) -> 0 | P38: No | R38: =IF(AND($P38="Yes",$G38<>"Vendor day rates"),$J38-0.4*$I38,0) -> 0 | S38: =IF(OR($P38<>"Yes",$Q38=""),0,$R38*MAX(0,7-MATCH($Q38,MonthList,0))/12) -> 0 | T38: =IF(OR($P38<>"Yes",$Q38=""),0,$R38*IF(MATCH($Q38,MonthList,0)<=7,12,19-MATCH($Q38,MonthList,0))/12) -> 0 | U38: No | W38: =IF(AND($U38="Yes",$G38<>"Vendor day rates"),$J38-0.4*$I38,0) -> 0 | X38: =IF(OR($U38<>"Yes",$V38=""),0,$W38*MAX(0,7-MATCH($V38,MonthList,0))/12) -> 0 | Y38: =IF(OR($U38<>"Yes",$V38=""),0,$W38*IF(MATCH($V38,MonthList,0)<=7,12,19-MATCH($V38,MonthList,0))/12) -> 0
B39: R0034 | C39: Project Manger | D39: EGI | E39: EGI | F39: AU | G39: Filled | H39: 1 | I39: 0.222 | J39: 0.222 | K39: No | M39: =IF(AND($K39="Yes",$G39<>"Vendor day rates"),$J39-0.4*$I39,0) -> 0 | N39: =IF(OR($K39<>"Yes",$L39=""),0,$M39*MAX(0,7-MATCH($L39,MonthList,0))/12) -> 0 | O39: =IF(OR($K39<>"Yes",$L39=""),0,$M39*IF(MATCH($L39,MonthList,0)<=7,12,19-MATCH($L39,MonthList,0))/12) -> 0 | P39: No | R39: =IF(AND($P39="Yes",$G39<>"Vendor day rates"),$J39-0.4*$I39,0) -> 0 | S39: =IF(OR($P39<>"Yes",$Q39=""),0,$R39*MAX(0,7-MATCH($Q39,MonthList,0))/12) -> 0 | T39: =IF(OR($P39<>"Yes",$Q39=""),0,$R39*IF(MATCH($Q39,MonthList,0)<=7,12,19-MATCH($Q39,MonthList,0))/12) -> 0 | U39: No | W39: =IF(AND($U39="Yes",$G39<>"Vendor day rates"),$J39-0.4*$I39,0) -> 0 | X39: =IF(OR($U39<>"Yes",$V39=""),0,$W39*MAX(0,7-MATCH($V39,MonthList,0))/12) -> 0 | Y39: =IF(OR($U39<>"Yes",$V39=""),0,$W39*IF(MATCH($V39,MonthList,0)<=7,12,19-MATCH($V39,MonthList,0))/12) -> 0
B40: R0035 | C40: strategic program architect | D40: EGI | E40: EGI | F40: AU | G40: Filled | H40: 1 | I40: 0.333 | J40: 0.333 | K40: No | M40: =IF(AND($K40="Yes",$G40<>"Vendor day rates"),$J40-0.4*$I40,0) -> 0 | N40: =IF(OR($K40<>"Yes",$L40=""),0,$M40*MAX(0,7-MATCH($L40,MonthList,0))/12) -> 0 | O40: =IF(OR($K40<>"Yes",$L40=""),0,$M40*IF(MATCH($L40,MonthList,0)<=7,12,19-MATCH($L40,MonthList,0))/12) -> 0 | P40: No | R40: =IF(AND($P40="Yes",$G40<>"Vendor day rates"),$J40-0.4*$I40,0) -> 0 | S40: =IF(OR($P40<>"Yes",$Q40=""),0,$R40*MAX(0,7-MATCH($Q40,MonthList,0))/12) -> 0 | T40: =IF(OR($P40<>"Yes",$Q40=""),0,$R40*IF(MATCH($Q40,MonthList,0)<=7,12,19-MATCH($Q40,MonthList,0))/12) -> 0 | U40: No | W40: =IF(AND($U40="Yes",$G40<>"Vendor day rates"),$J40-0.4*$I40,0) -> 0 | X40: =IF(OR($U40<>"Yes",$V40=""),0,$W40*MAX(0,7-MATCH($V40,MonthList,0))/12) -> 0 | Y40: =IF(OR($U40<>"Yes",$V40=""),0,$W40*IF(MATCH($V40,MonthList,0)<=7,12,19-MATCH($V40,MonthList,0))/12) -> 0
B41: R0036 | C41: Engineer - BE | D41: Ampol Customer | E41: Ampol Web | F41: AU | G41: Already at the offshore rate | H41: 1 | I41: 0.2775 | J41: 0.111 | K41: No | M41: =IF(AND($K41="Yes",$G41<>"Vendor day rates"),$J41-0.4*$I41,0) -> 0 | N41: =IF(OR($K41<>"Yes",$L41=""),0,$M41*MAX(0,7-MATCH($L41,MonthList,0))/12) -> 0 | O41: =IF(OR($K41<>"Yes",$L41=""),0,$M41*IF(MATCH($L41,MonthList,0)<=7,12,19-MATCH($L41,MonthList,0))/12) -> 0 | P41: No | R41: =IF(AND($P41="Yes",$G41<>"Vendor day rates"),$J41-0.4*$I41,0) -> 0 | S41: =IF(OR($P41<>"Yes",$Q41=""),0,$R41*MAX(0,7-MATCH($Q41,MonthList,0))/12) -> 0 | T41: =IF(OR($P41<>"Yes",$Q41=""),0,$R41*IF(MATCH($Q41,MonthList,0)<=7,12,19-MATCH($Q41,MonthList,0))/12) -> 0 | U41: No | W41: =IF(AND($U41="Yes",$G41<>"Vendor day rates"),$J41-0.4*$I41,0) -> 0 | X41: =IF(OR($U41<>"Yes",$V41=""),0,$W41*MAX(0,7-MATCH($V41,MonthList,0))/12) -> 0 | Y41: =IF(OR($U41<>"Yes",$V41=""),0,$W41*IF(MATCH($V41,MonthList,0)<=7,12,19-MATCH($V41,MonthList,0))/12) -> 0
B42: R0037 | C42: Engineer - BE | D42: Ampol Customer | E42: Ampol App | F42: AU | G42: Already at the offshore rate | H42: 1 | I42: 0.2705 | J42: 0.1082 | K42: No | M42: =IF(AND($K42="Yes",$G42<>"Vendor day rates"),$J42-0.4*$I42,0) -> 0 | N42: =IF(OR($K42<>"Yes",$L42=""),0,$M42*MAX(0,7-MATCH($L42,MonthList,0))/12) -> 0 | O42: =IF(OR($K42<>"Yes",$L42=""),0,$M42*IF(MATCH($L42,MonthList,0)<=7,12,19-MATCH($L42,MonthList,0))/12) -> 0 | P42: No | R42: =IF(AND($P42="Yes",$G42<>"Vendor day rates"),$J42-0.4*$I42,0) -> 0 | S42: =IF(OR($P42<>"Yes",$Q42=""),0,$R42*MAX(0,7-MATCH($Q42,MonthList,0))/12) -> 0 | T42: =IF(OR($P42<>"Yes",$Q42=""),0,$R42*IF(MATCH($Q42,MonthList,0)<=7,12,19-MATCH($Q42,MonthList,0))/12) -> 0 | U42: No | W42: =IF(AND($U42="Yes",$G42<>"Vendor day rates"),$J42-0.4*$I42,0) -> 0 | X42: =IF(OR($U42<>"Yes",$V42=""),0,$W42*MAX(0,7-MATCH($V42,MonthList,0))/12) -> 0 | Y42: =IF(OR($U42<>"Yes",$V42=""),0,$W42*IF(MATCH($V42,MonthList,0)<=7,12,19-MATCH($V42,MonthList,0))/12) -> 0
B43: R0038 | C43: Engineer - BE | D43: EGI Integration | E43: EGI Customer | F43: AU | G43: Filled | H43: 1 | I43: 0 | J43: 0 | K43: No | M43: =IF(AND($K43="Yes",$G43<>"Vendor day rates"),$J43-0.4*$I43,0) -> 0 | N43: =IF(OR($K43<>"Yes",$L43=""),0,$M43*MAX(0,7-MATCH($L43,MonthList,0))/12) -> 0 | O43: =IF(OR($K43<>"Yes",$L43=""),0,$M43*IF(MATCH($L43,MonthList,0)<=7,12,19-MATCH($L43,MonthList,0))/12) -> 0 | P43: No | R43: =IF(AND($P43="Yes",$G43<>"Vendor day rates"),$J43-0.4*$I43,0) -> 0 | S43: =IF(OR($P43<>"Yes",$Q43=""),0,$R43*MAX(0,7-MATCH($Q43,MonthList,0))/12) -> 0 | T43: =IF(OR($P43<>"Yes",$Q43=""),0,$R43*IF(MATCH($Q43,MonthList,0)<=7,12,19-MATCH($Q43,MonthList,0))/12) -> 0 | U43: No | W43: =IF(AND($U43="Yes",$G43<>"Vendor day rates"),$J43-0.4*$I43,0) -> 0 | X43: =IF(OR($U43<>"Yes",$V43=""),0,$W43*MAX(0,7-MATCH($V43,MonthList,0))/12) -> 0 | Y43: =IF(OR($U43<>"Yes",$V43=""),0,$W43*IF(MATCH($V43,MonthList,0)<=7,12,19-MATCH($V43,MonthList,0))/12) -> 0
B44: R0039 | C44: Engineer - BE | D44: EGI Integration | E44: EGI Customer | F44: AU | G44: Filled | H44: 1 | I44: 0.2642 | J44: 0.2642 | K44: No | M44: =IF(AND($K44="Yes",$G44<>"Vendor day rates"),$J44-0.4*$I44,0) -> 0 | N44: =IF(OR($K44<>"Yes",$L44=""),0,$M44*MAX(0,7-MATCH($L44,MonthList,0))/12) -> 0 | O44: =IF(OR($K44<>"Yes",$L44=""),0,$M44*IF(MATCH($L44,MonthList,0)<=7,12,19-MATCH($L44,MonthList,0))/12) -> 0 | P44: No | R44: =IF(AND($P44="Yes",$G44<>"Vendor day rates"),$J44-0.4*$I44,0) -> 0 | S44: =IF(OR($P44<>"Yes",$Q44=""),0,$R44*MAX(0,7-MATCH($Q44,MonthList,0))/12) -> 0 | T44: =IF(OR($P44<>"Yes",$Q44=""),0,$R44*IF(MATCH($Q44,MonthList,0)<=7,12,19-MATCH($Q44,MonthList,0))/12) -> 0 | U44: No | W44: =IF(AND($U44="Yes",$G44<>"Vendor day rates"),$J44-0.4*$I44,0) -> 0 | X44: =IF(OR($U44<>"Yes",$V44=""),0,$W44*MAX(0,7-MATCH($V44,MonthList,0))/12) -> 0 | Y44: =IF(OR($U44<>"Yes",$V44=""),0,$W44*IF(MATCH($V44,MonthList,0)<=7,12,19-MATCH($V44,MonthList,0))/12) -> 0
B45: R0040 | C45: Business Analyst | D45: EGI Integration | E45: EGI Retail | F45: AU | G45: Filled | H45: 1 | I45: 0.222 | J45: 0.222 | K45: No | M45: =IF(AND($K45="Yes",$G45<>"Vendor day rates"),$J45-0.4*$I45,0) -> 0 | N45: =IF(OR($K45<>"Yes",$L45=""),0,$M45*MAX(0,7-MATCH($L45,MonthList,0))/12) -> 0 | O45: =IF(OR($K45<>"Yes",$L45=""),0,$M45*IF(MATCH($L45,MonthList,0)<=7,12,19-MATCH($L45,MonthList,0))/12) -> 0 | P45: No | R45: =IF(AND($P45="Yes",$G45<>"Vendor day rates"),$J45-0.4*$I45,0) -> 0 | S45: =IF(OR($P45<>"Yes",$Q45=""),0,$R45*MAX(0,7-MATCH($Q45,MonthList,0))/12) -> 0 | T45: =IF(OR($P45<>"Yes",$Q45=""),0,$R45*IF(MATCH($Q45,MonthList,0)<=7,12,19-MATCH($Q45,MonthList,0))/12) -> 0 | U45: No | W45: =IF(AND($U45="Yes",$G45<>"Vendor day rates"),$J45-0.4*$I45,0) -> 0 | X45: =IF(OR($U45<>"Yes",$V45=""),0,$W45*MAX(0,7-MATCH($V45,MonthList,0))/12) -> 0 | Y45: =IF(OR($U45<>"Yes",$V45=""),0,$W45*IF(MATCH($V45,MonthList,0)<=7,12,19-MATCH($V45,MonthList,0))/12) -> 0
B46: R0041 | C46: DeveloperSAP ECC | D46: EGI | E46: EGI | F46: AU | G46: Filled | H46: 1 | I46: 0.2775 | J46: 0.2775 | K46: No | M46: =IF(AND($K46="Yes",$G46<>"Vendor day rates"),$J46-0.4*$I46,0) -> 0 | N46: =IF(OR($K46<>"Yes",$L46=""),0,$M46*MAX(0,7-MATCH($L46,MonthList,0))/12) -> 0 | O46: =IF(OR($K46<>"Yes",$L46=""),0,$M46*IF(MATCH($L46,MonthList,0)<=7,12,19-MATCH($L46,MonthList,0))/12) -> 0 | P46: No | R46: =IF(AND($P46="Yes",$G46<>"Vendor day rates"),$J46-0.4*$I46,0) -> 0 | S46: =IF(OR($P46<>"Yes",$Q46=""),0,$R46*MAX(0,7-MATCH($Q46,MonthList,0))/12) -> 0 | T46: =IF(OR($P46<>"Yes",$Q46=""),0,$R46*IF(MATCH($Q46,MonthList,0)<=7,12,19-MATCH($Q46,MonthList,0))/12) -> 0 | U46: No | W46: =IF(AND($U46="Yes",$G46<>"Vendor day rates"),$J46-0.4*$I46,0) -> 0 | X46: =IF(OR($U46<>"Yes",$V46=""),0,$W46*MAX(0,7-MATCH($V46,MonthList,0))/12) -> 0 | Y46: =IF(OR($U46<>"Yes",$V46=""),0,$W46*IF(MATCH($V46,MonthList,0)<=7,12,19-MATCH($V46,MonthList,0))/12) -> 0
B47: R0042 | C47: Commercial Director | D47: NA | E47: Commercial | F47: AU | G47: Vacant, hire planned | H47: 1 | I47: 0.4395 | J47: 0.4395 | K47: No | M47: =IF(AND($K47="Yes",$G47<>"Vendor day rates"),$J47-0.4*$I47,0) -> 0 | N47: =IF(OR($K47<>"Yes",$L47=""),0,$M47*MAX(0,7-MATCH($L47,MonthList,0))/12) -> 0 | O47: =IF(OR($K47<>"Yes",$L47=""),0,$M47*IF(MATCH($L47,MonthList,0)<=7,12,19-MATCH($L47,MonthList,0))/12) -> 0 | P47: No | R47: =IF(AND($P47="Yes",$G47<>"Vendor day rates"),$J47-0.4*$I47,0) -> 0 | S47: =IF(OR($P47<>"Yes",$Q47=""),0,$R47*MAX(0,7-MATCH($Q47,MonthList,0))/12) -> 0 | T47: =IF(OR($P47<>"Yes",$Q47=""),0,$R47*IF(MATCH($Q47,MonthList,0)<=7,12,19-MATCH($Q47,MonthList,0))/12) -> 0 | U47: No | W47: =IF(AND($U47="Yes",$G47<>"Vendor day rates"),$J47-0.4*$I47,0) -> 0 | X47: =IF(OR($U47<>"Yes",$V47=""),0,$W47*MAX(0,7-MATCH($V47,MonthList,0))/12) -> 0 | Y47: =IF(OR($U47<>"Yes",$V47=""),0,$W47*IF(MATCH($V47,MonthList,0)<=7,12,19-MATCH($V47,MonthList,0))/12) -> 0
B48: R0043 | C48: Head of Technology, Loyalty & Mart | D48: Z ENERGY (DIGITAL) | E48: Head of Technology | F48: NZ | G48: Filled | H48: 1 | I48: 0.3011 | J48: 0.3011 | K48: No | M48: =IF(AND($K48="Yes",$G48<>"Vendor day rates"),$J48-0.4*$I48,0) -> 0 | N48: =IF(OR($K48<>"Yes",$L48=""),0,$M48*MAX(0,7-MATCH($L48,MonthList,0))/12) -> 0 | O48: =IF(OR($K48<>"Yes",$L48=""),0,$M48*IF(MATCH($L48,MonthList,0)<=7,12,19-MATCH($L48,MonthList,0))/12) -> 0 | P48: No | R48: =IF(AND($P48="Yes",$G48<>"Vendor day rates"),$J48-0.4*$I48,0) -> 0 | S48: =IF(OR($P48<>"Yes",$Q48=""),0,$R48*MAX(0,7-MATCH($Q48,MonthList,0))/12) -> 0 | T48: =IF(OR($P48<>"Yes",$Q48=""),0,$R48*IF(MATCH($Q48,MonthList,0)<=7,12,19-MATCH($Q48,MonthList,0))/12) -> 0 | U48: No | W48: =IF(AND($U48="Yes",$G48<>"Vendor day rates"),$J48-0.4*$I48,0) -> 0 | X48: =IF(OR($U48<>"Yes",$V48=""),0,$W48*MAX(0,7-MATCH($V48,MonthList,0))/12) -> 0 | Y48: =IF(OR($U48<>"Yes",$V48=""),0,$W48*IF(MATCH($V48,MonthList,0)<=7,12,19-MATCH($V48,MonthList,0))/12) -> 0
B49: R0044 | C49: Head of Technology - Digital | D49: Ampol Customer | E49: Head of Technology | F49: NZ | G49: Filled | H49: 1 | I49: 0.2743 | J49: 0.2743 | K49: No | M49: =IF(AND($K49="Yes",$G49<>"Vendor day rates"),$J49-0.4*$I49,0) -> 0 | N49: =IF(OR($K49<>"Yes",$L49=""),0,$M49*MAX(0,7-MATCH($L49,MonthList,0))/12) -> 0 | O49: =IF(OR($K49<>"Yes",$L49=""),0,$M49*IF(MATCH($L49,MonthList,0)<=7,12,19-MATCH($L49,MonthList,0))/12) -> 0 | P49: No | R49: =IF(AND($P49="Yes",$G49<>"Vendor day rates"),$J49-0.4*$I49,0) -> 0 | S49: =IF(OR($P49<>"Yes",$Q49=""),0,$R49*MAX(0,7-MATCH($Q49,MonthList,0))/12) -> 0 | T49: =IF(OR($P49<>"Yes",$Q49=""),0,$R49*IF(MATCH($Q49,MonthList,0)<=7,12,19-MATCH($Q49,MonthList,0))/12) -> 0 | U49: No | W49: =IF(AND($U49="Yes",$G49<>"Vendor day rates"),$J49-0.4*$I49,0) -> 0 | X49: =IF(OR($U49<>"Yes",$V49=""),0,$W49*MAX(0,7-MATCH($V49,MonthList,0))/12) -> 0 | Y49: =IF(OR($U49<>"Yes",$V49=""),0,$W49*IF(MATCH($V49,MonthList,0)<=7,12,19-MATCH($V49,MonthList,0))/12) -> 0
B50: R0045 | C50: Head of Technology - TDD & Enginee | D50: TDD | E50: Head of Technology | F50: AU | G50: Vacant, hire planned | H50: 1 | I50: 0.333 | J50: 0.333 | K50: No | M50: =IF(AND($K50="Yes",$G50<>"Vendor day rates"),$J50-0.4*$I50,0) -> 0 | N50: =IF(OR($K50<>"Yes",$L50=""),0,$M50*MAX(0,7-MATCH($L50,MonthList,0))/12) -> 0 | O50: =IF(OR($K50<>"Yes",$L50=""),0,$M50*IF(MATCH($L50,MonthList,0)<=7,12,19-MATCH($L50,MonthList,0))/12) -> 0 | P50: No | R50: =IF(AND($P50="Yes",$G50<>"Vendor day rates"),$J50-0.4*$I50,0) -> 0 | S50: =IF(OR($P50<>"Yes",$Q50=""),0,$R50*MAX(0,7-MATCH($Q50,MonthList,0))/12) -> 0 | T50: =IF(OR($P50<>"Yes",$Q50=""),0,$R50*IF(MATCH($Q50,MonthList,0)<=7,12,19-MATCH($Q50,MonthList,0))/12) -> 0 | U50: No | W50: =IF(AND($U50="Yes",$G50<>"Vendor day rates"),$J50-0.4*$I50,0) -> 0 | X50: =IF(OR($U50<>"Yes",$V50=""),0,$W50*MAX(0,7-MATCH($V50,MonthList,0))/12) -> 0 | Y50: =IF(OR($U50<>"Yes",$V50=""),0,$W50*IF(MATCH($V50,MonthList,0)<=7,12,19-MATCH($V50,MonthList,0))/12) -> 0
... B55: R0050 | C55: Technology Manager, Data Engineeri | D55: Enterprise Data | E55: Technology Manager | F55: NZ | G55: Filled | H55: 1 | I55: 0.3209 | J55: 0.3209 | K55: No | M55: =IF(AND($K55="Yes",$G55<>"Vendor day rates"),$J55-0.4*$I55,0) -> 0 | N55: =IF(OR($K55<>"Yes",$L55=""),0,$M55*MAX(0,7-MATCH($L55,MonthList,0))/12) -> 0 | O55: =IF(OR($K55<>"Yes",$L55=""),0,$M55*IF(MATCH($L55,MonthList,0)<=7,12,19-MATCH($L55,MonthList,0))/12) -> 0 | P55: No | R55: =IF(AND($P55="Yes",$G55<>"Vendor day rates"),$J55-0.4*$I55,0) -> 0 | S55: =IF(OR($P55<>"Yes",$Q55=""),0,$R55*MAX(0,7-MATCH($Q55,MonthList,0))/12) -> 0 | T55: =IF(OR($P55<>"Yes",$Q55=""),0,$R55*IF(MATCH($Q55,MonthList,0)<=7,12,19-MATCH($Q55,MonthList,0))/12) -> 0 | U55: No | W55: =IF(AND($U55="Yes",$G55<>"Vendor day rates"),$J55-0.4*$I55,0) -> 0 | X55: =IF(OR($U55<>"Yes",$V55=""),0,$W55*MAX(0,7-MATCH($V55,MonthList,0))/12) -> 0 | Y55: =IF(OR($U55<>"Yes",$V55=""),0,$W55*IF(MATCH($V55,MonthList,0)<=7,12,19-MATCH($V55,MonthList,0))/12) -> 0
B56: R0051 | C56: Principal, Data Architecture & Gov | E56: Group Data | F56: AU | G56: Filled | H56: 1 | I56: 0.3891 | J56: 0.3891 | K56: No | M56: =IF(AND($K56="Yes",$G56<>"Vendor day rates"),$J56-0.4*$I56,0) -> 0 | N56: =IF(OR($K56<>"Yes",$L56=""),0,$M56*MAX(0,7-MATCH($L56,MonthList,0))/12) -> 0 | O56: =IF(OR($K56<>"Yes",$L56=""),0,$M56*IF(MATCH($L56,MonthList,0)<=7,12,19-MATCH($L56,MonthList,0))/12) -> 0 | P56: No | R56: =IF(AND($P56="Yes",$G56<>"Vendor day rates"),$J56-0.4*$I56,0) -> 0 | S56: =IF(OR($P56<>"Yes",$Q56=""),0,$R56*MAX(0,7-MATCH($Q56,MonthList,0))/12) -> 0 | T56: =IF(OR($P56<>"Yes",$Q56=""),0,$R56*IF(MATCH($Q56,MonthList,0)<=7,12,19-MATCH($Q56,MonthList,0))/12) -> 0 | U56: No | W56: =IF(AND($U56="Yes",$G56<>"Vendor day rates"),$J56-0.4*$I56,0) -> 0 | X56: =IF(OR($U56<>"Yes",$V56=""),0,$W56*MAX(0,7-MATCH($V56,MonthList,0))/12) -> 0 | Y56: =IF(OR($U56<>"Yes",$V56=""),0,$W56*IF(MATCH($V56,MonthList,0)<=7,12,19-MATCH($V56,MonthList,0))/12) -> 0
B57: R0052 | C57: Head of Technology, Group Data | D57: Enterprise Data | E57: Head of Technology | F57: AU | G57: Filled | H57: 1 | I57: 0.4098 | J57: 0.4098 | K57: No | M57: =IF(AND($K57="Yes",$G57<>"Vendor day rates"),$J57-0.4*$I57,0) -> 0 | N57: =IF(OR($K57<>"Yes",$L57=""),0,$M57*MAX(0,7-MATCH($L57,MonthList,0))/12) -> 0 | O57: =IF(OR($K57<>"Yes",$L57=""),0,$M57*IF(MATCH($L57,MonthList,0)<=7,12,19-MATCH($L57,MonthList,0))/12) -> 0 | P57: No | R57: =IF(AND($P57="Yes",$G57<>"Vendor day rates"),$J57-0.4*$I57,0) -> 0 | S57: =IF(OR($P57<>"Yes",$Q57=""),0,$R57*MAX(0,7-MATCH($Q57,MonthList,0))/12) -> 0 | T57: =IF(OR($P57<>"Yes",$Q57=""),0,$R57*IF(MATCH($Q57,MonthList,0)<=7,12,19-MATCH($Q57,MonthList,0))/12) -> 0 | U57: No | W57: =IF(AND($U57="Yes",$G57<>"Vendor day rates"),$J57-0.4*$I57,0) -> 0 | X57: =IF(OR($U57<>"Yes",$V57=""),0,$W57*MAX(0,7-MATCH($V57,MonthList,0))/12) -> 0 | Y57: =IF(OR($U57<>"Yes",$V57=""),0,$W57*IF(MATCH($V57,MonthList,0)<=7,12,19-MATCH($V57,MonthList,0))/12) -> 0
B58: R0053 | C58: Delivery Manager, Strategy, Archit | E58: Leadership | F58: AU | G58: Filled | H58: 1 | I58: 0.3691 | J58: 0.3691 | K58: No | M58: =IF(AND($K58="Yes",$G58<>"Vendor day rates"),$J58-0.4*$I58,0) -> 0 | N58: =IF(OR($K58<>"Yes",$L58=""),0,$M58*MAX(0,7-MATCH($L58,MonthList,0))/12) -> 0 | O58: =IF(OR($K58<>"Yes",$L58=""),0,$M58*IF(MATCH($L58,MonthList,0)<=7,12,19-MATCH($L58,MonthList,0))/12) -> 0 | P58: No | R58: =IF(AND($P58="Yes",$G58<>"Vendor day rates"),$J58-0.4*$I58,0) -> 0 | S58: =IF(OR($P58<>"Yes",$Q58=""),0,$R58*MAX(0,7-MATCH($Q58,MonthList,0))/12) -> 0 | T58: =IF(OR($P58<>"Yes",$Q58=""),0,$R58*IF(MATCH($Q58,MonthList,0)<=7,12,19-MATCH($Q58,MonthList,0))/12) -> 0 | U58: No | W58: =IF(AND($U58="Yes",$G58<>"Vendor day rates"),$J58-0.4*$I58,0) -> 0 | X58: =IF(OR($U58<>"Yes",$V58=""),0,$W58*MAX(0,7-MATCH($V58,MonthList,0))/12) -> 0 | Y58: =IF(OR($U58<>"Yes",$V58=""),0,$W58*IF(MATCH($V58,MonthList,0)<=7,12,19-MATCH($V58,MonthList,0))/12) -> 0
B59: R0054 | C59: Head of Architecture | E59: Leadership | F59: AU | G59: Vacant, hire planned | H59: 1 | I59: 0.335 | J59: 0.335 | K59: No | M59: =IF(AND($K59="Yes",$G59<>"Vendor day rates"),$J59-0.4*$I59,0) -> 0 | N59: =IF(OR($K59<>"Yes",$L59=""),0,$M59*MAX(0,7-MATCH($L59,MonthList,0))/12) -> 0 | O59: =IF(OR($K59<>"Yes",$L59=""),0,$M59*IF(MATCH($L59,MonthList,0)<=7,12,19-MATCH($L59,MonthList,0))/12) -> 0 | P59: No | R59: =IF(AND($P59="Yes",$G59<>"Vendor day rates"),$J59-0.4*$I59,0) -> 0 | S59: =IF(OR($P59<>"Yes",$Q59=""),0,$R59*MAX(0,7-MATCH($Q59,MonthList,0))/12) -> 0 | T59: =IF(OR($P59<>"Yes",$Q59=""),0,$R59*IF(MATCH($Q59,MonthList,0)<=7,12,19-MATCH($Q59,MonthList,0))/12) -> 0 | U59: No | W59: =IF(AND($U59="Yes",$G59<>"Vendor day rates"),$J59-0.4*$I59,0) -> 0 | X59: =IF(OR($U59<>"Yes",$V59=""),0,$W59*MAX(0,7-MATCH($V59,MonthList,0))/12) -> 0 | Y59: =IF(OR($U59<>"Yes",$V59=""),0,$W59*IF(MATCH($V59,MonthList,0)<=7,12,19-MATCH($V59,MonthList,0))/12) -> 0
B60: R0055 | C60: Head of Technology Strategy & AI C | E60: Leadership | F60: AU | G60: Vacant, hire planned | H60: 1 | I60: 0.333 | J60: 0.333 | K60: No | M60: =IF(AND($K60="Yes",$G60<>"Vendor day rates"),$J60-0.4*$I60,0) -> 0 | N60: =IF(OR($K60<>"Yes",$L60=""),0,$M60*MAX(0,7-MATCH($L60,MonthList,0))/12) -> 0 | O60: =IF(OR($K60<>"Yes",$L60=""),0,$M60*IF(MATCH($L60,MonthList,0)<=7,12,19-MATCH($L60,MonthList,0))/12) -> 0 | P60: No | R60: =IF(AND($P60="Yes",$G60<>"Vendor day rates"),$J60-0.4*$I60,0) -> 0 | S60: =IF(OR($P60<>"Yes",$Q60=""),0,$R60*MAX(0,7-MATCH($Q60,MonthList,0))/12) -> 0 | T60: =IF(OR($P60<>"Yes",$Q60=""),0,$R60*IF(MATCH($Q60,MonthList,0)<=7,12,19-MATCH($Q60,MonthList,0))/12) -> 0 | U60: No | W60: =IF(AND($U60="Yes",$G60<>"Vendor day rates"),$J60-0.4*$I60,0) -> 0 | X60: =IF(OR($U60<>"Yes",$V60=""),0,$W60*MAX(0,7-MATCH($V60,MonthList,0))/12) -> 0 | Y60: =IF(OR($U60<>"Yes",$V60=""),0,$W60*IF(MATCH($V60,MonthList,0)<=7,12,19-MATCH($V60,MonthList,0))/12) -> 0
B61: R0056 | C61: TDD BP - Infrastructure | D61: NA | E61: TDD Business Partner | F61: AU | G61: Filled | H61: 1 | I61: 0.2972 | J61: 0.2972 | K61: No | M61: =IF(AND($K61="Yes",$G61<>"Vendor day rates"),$J61-0.4*$I61,0) -> 0 | N61: =IF(OR($K61<>"Yes",$L61=""),0,$M61*MAX(0,7-MATCH($L61,MonthList,0))/12) -> 0 | O61: =IF(OR($K61<>"Yes",$L61=""),0,$M61*IF(MATCH($L61,MonthList,0)<=7,12,19-MATCH($L61,MonthList,0))/12) -> 0 | P61: No | R61: =IF(AND($P61="Yes",$G61<>"Vendor day rates"),$J61-0.4*$I61,0) -> 0 | S61: =IF(OR($P61<>"Yes",$Q61=""),0,$R61*MAX(0,7-MATCH($Q61,MonthList,0))/12) -> 0 | T61: =IF(OR($P61<>"Yes",$Q61=""),0,$R61*IF(MATCH($Q61,MonthList,0)<=7,12,19-MATCH($Q61,MonthList,0))/12) -> 0 | U61: No | W61: =IF(AND($U61="Yes",$G61<>"Vendor day rates"),$J61-0.4*$I61,0) -> 0 | X61: =IF(OR($U61<>"Yes",$V61=""),0,$W61*MAX(0,7-MATCH($V61,MonthList,0))/12) -> 0 | Y61: =IF(OR($U61<>"Yes",$V61=""),0,$W61*IF(MATCH($V61,MonthList,0)<=7,12,19-MATCH($V61,MonthList,0))/12) -> 0
B62: R0057 | C62: TDD BP - T&S | D62: NA | E62: TDD Business Partner | F62: AU | G62: Filled | H62: 1 | I62: 0.6661 | J62: 0.6661 | K62: No | M62: =IF(AND($K62="Yes",$G62<>"Vendor day rates"),$J62-0.4*$I62,0) -> 0 | N62: =IF(OR($K62<>"Yes",$L62=""),0,$M62*MAX(0,7-MATCH($L62,MonthList,0))/12) -> 0 | O62: =IF(OR($K62<>"Yes",$L62=""),0,$M62*IF(MATCH($L62,MonthList,0)<=7,12,19-MATCH($L62,MonthList,0))/12) -> 0 | P62: No | R62: =IF(AND($P62="Yes",$G62<>"Vendor day rates"),$J62-0.4*$I62,0) -> 0 | S62: =IF(OR($P62<>"Yes",$Q62=""),0,$R62*MAX(0,7-MATCH($Q62,MonthList,0))/12) -> 0 | T62: =IF(OR($P62<>"Yes",$Q62=""),0,$R62*IF(MATCH($Q62,MonthList,0)<=7,12,19-MATCH($Q62,MonthList,0))/12) -> 0 | U62: No | W62: =IF(AND($U62="Yes",$G62<>"Vendor day rates"),$J62-0.4*$I62,0) -> 0 | X62: =IF(OR($U62<>"Yes",$V62=""),0,$W62*MAX(0,7-MATCH($V62,MonthList,0))/12) -> 0 | Y62: =IF(OR($U62<>"Yes",$V62=""),0,$W62*IF(MATCH($V62,MonthList,0)<=7,12,19-MATCH($V62,MonthList,0))/12) -> 0
B63: R0058 | C63: TDD BP - Z | D63: NA | E63: TDD Business Partner | F63: NZ | G63: Filled | H63: 1 | I63: 0.2914 | J63: 0.2914 | K63: No | M63: =IF(AND($K63="Yes",$G63<>"Vendor day rates"),$J63-0.4*$I63,0) -> 0 | N63: =IF(OR($K63<>"Yes",$L63=""),0,$M63*MAX(0,7-MATCH($L63,MonthList,0))/12) -> 0 | O63: =IF(OR($K63<>"Yes",$L63=""),0,$M63*IF(MATCH($L63,MonthList,0)<=7,12,19-MATCH($L63,MonthList,0))/12) -> 0 | P63: No | R63: =IF(AND($P63="Yes",$G63<>"Vendor day rates"),$J63-0.4*$I63,0) -> 0 | S63: =IF(OR($P63<>"Yes",$Q63=""),0,$R63*MAX(0,7-MATCH($Q63,MonthList,0))/12) -> 0 | T63: =IF(OR($P63<>"Yes",$Q63=""),0,$R63*IF(MATCH($Q63,MonthList,0)<=7,12,19-MATCH($Q63,MonthList,0))/12) -> 0 | U63: No | W63: =IF(AND($U63="Yes",$G63<>"Vendor day rates"),$J63-0.4*$I63,0) -> 0 | X63: =IF(OR($U63<>"Yes",$V63=""),0,$W63*MAX(0,7-MATCH($V63,MonthList,0))/12) -> 0 | Y63: =IF(OR($U63<>"Yes",$V63=""),0,$W63*IF(MATCH($V63,MonthList,0)<=7,12,19-MATCH($V63,MonthList,0))/12) -> 0
B64: R0059 | C64: TDD BP - Retail & Customer - Store | D64: NA | E64: TDD Business Partner | F64: AU | G64: Filled | H64: 1 | I64: 0.4174 | J64: 0.4174 | K64: No | M64: =IF(AND($K64="Yes",$G64<>"Vendor day rates"),$J64-0.4*$I64,0) -> 0 | N64: =IF(OR($K64<>"Yes",$L64=""),0,$M64*MAX(0,7-MATCH($L64,MonthList,0))/12) -> 0 | O64: =IF(OR($K64<>"Yes",$L64=""),0,$M64*IF(MATCH($L64,MonthList,0)<=7,12,19-MATCH($L64,MonthList,0))/12) -> 0 | P64: No | R64: =IF(AND($P64="Yes",$G64<>"Vendor day rates"),$J64-0.4*$I64,0) -> 0 | S64: =IF(OR($P64<>"Yes",$Q64=""),0,$R64*MAX(0,7-MATCH($Q64,MonthList,0))/12) -> 0 | T64: =IF(OR($P64<>"Yes",$Q64=""),0,$R64*IF(MATCH($Q64,MonthList,0)<=7,12,19-MATCH($Q64,MonthList,0))/12) -> 0 | U64: No | W64: =IF(AND($U64="Yes",$G64<>"Vendor day rates"),$J64-0.4*$I64,0) -> 0 | X64: =IF(OR($U64<>"Yes",$V64=""),0,$W64*MAX(0,7-MATCH($V64,MonthList,0))/12) -> 0 | Y64: =IF(OR($U64<>"Yes",$V64=""),0,$W64*IF(MATCH($V64,MonthList,0)<=7,12,19-MATCH($V64,MonthList,0))/12) -> 0
B65: R0060 | C65: TDD BP - ES | D65: NA | E65: TDD Business Partner | F65: AU | G65: Filled | H65: 1 | I65: 0.3434 | J65: 0.3434 | K65: No | M65: =IF(AND($K65="Yes",$G65<>"Vendor day rates"),$J65-0.4*$I65,0) -> 0 | N65: =IF(OR($K65<>"Yes",$L65=""),0,$M65*MAX(0,7-MATCH($L65,MonthList,0))/12) -> 0 | O65: =IF(OR($K65<>"Yes",$L65=""),0,$M65*IF(MATCH($L65,MonthList,0)<=7,12,19-MATCH($L65,MonthList,0))/12) -> 0 | P65: No | R65: =IF(AND($P65="Yes",$G65<>"Vendor day rates"),$J65-0.4*$I65,0) -> 0 | S65: =IF(OR($P65<>"Yes",$Q65=""),0,$R65*MAX(0,7-MATCH($Q65,MonthList,0))/12) -> 0 | T65: =IF(OR($P65<>"Yes",$Q65=""),0,$R65*IF(MATCH($Q65,MonthList,0)<=7,12,19-MATCH($Q65,MonthList,0))/12) -> 0 | U65: No | W65: =IF(AND($U65="Yes",$G65<>"Vendor day rates"),$J65-0.4*$I65,0) -> 0 | X65: =IF(OR($U65<>"Yes",$V65=""),0,$W65*MAX(0,7-MATCH($V65,MonthList,0))/12) -> 0 | Y65: =IF(OR($U65<>"Yes",$V65=""),0,$W65*IF(MATCH($V65,MonthList,0)<=7,12,19-MATCH($V65,MonthList,0))/12) -> 0
B66: R0061 | C66: Head of Transformation | D66: NA | E66: Transformation | F66: AU | G66: Filled | H66: 1 | I66: 0.3679 | J66: 0.3679 | K66: No | M66: =IF(AND($K66="Yes",$G66<>"Vendor day rates"),$J66-0.4*$I66,0) -> 0 | N66: =IF(OR($K66<>"Yes",$L66=""),0,$M66*MAX(0,7-MATCH($L66,MonthList,0))/12) -> 0 | O66: =IF(OR($K66<>"Yes",$L66=""),0,$M66*IF(MATCH($L66,MonthList,0)<=7,12,19-MATCH($L66,MonthList,0))/12) -> 0 | P66: No | R66: =IF(AND($P66="Yes",$G66<>"Vendor day rates"),$J66-0.4*$I66,0) -> 0 | S66: =IF(OR($P66<>"Yes",$Q66=""),0,$R66*MAX(0,7-MATCH($Q66,MonthList,0))/12) -> 0 | T66: =IF(OR($P66<>"Yes",$Q66=""),0,$R66*IF(MATCH($Q66,MonthList,0)<=7,12,19-MATCH($Q66,MonthList,0))/12) -> 0 | U66: No | W66: =IF(AND($U66="Yes",$G66<>"Vendor day rates"),$J66-0.4*$I66,0) -> 0 | X66: =IF(OR($U66<>"Yes",$V66=""),0,$W66*MAX(0,7-MATCH($V66,MonthList,0))/12) -> 0 | Y66: =IF(OR($U66<>"Yes",$V66=""),0,$W66*IF(MATCH($V66,MonthList,0)<=7,12,19-MATCH($V66,MonthList,0))/12) -> 0
B67: R0062 | C67: Head of Technology, Fuel Infrastru | D67: Infrastructure | E67: Head of Technology | F67: AU | G67: Filled | H67: 1 | I67: 0.3636 | J67: 0.3636 | K67: No | M67: =IF(AND($K67="Yes",$G67<>"Vendor day rates"),$J67-0.4*$I67,0) -> 0 | N67: =IF(OR($K67<>"Yes",$L67=""),0,$M67*MAX(0,7-MATCH($L67,MonthList,0))/12) -> 0 | O67: =IF(OR($K67<>"Yes",$L67=""),0,$M67*IF(MATCH($L67,MonthList,0)<=7,12,19-MATCH($L67,MonthList,0))/12) -> 0 | P67: No | R67: =IF(AND($P67="Yes",$G67<>"Vendor day rates"),$J67-0.4*$I67,0) -> 0 | S67: =IF(OR($P67<>"Yes",$Q67=""),0,$R67*MAX(0,7-MATCH($Q67,MonthList,0))/12) -> 0 | T67: =IF(OR($P67<>"Yes",$Q67=""),0,$R67*IF(MATCH($Q67,MonthList,0)<=7,12,19-MATCH($Q67,MonthList,0))/12) -> 0 | U67: No | W67: =IF(AND($U67="Yes",$G67<>"Vendor day rates"),$J67-0.4*$I67,0) -> 0 | X67: =IF(OR($U67<>"Yes",$V67=""),0,$W67*MAX(0,7-MATCH($V67,MonthList,0))/12) -> 0 | Y67: =IF(OR($U67<>"Yes",$V67=""),0,$W67*IF(MATCH($V67,MonthList,0)<=7,12,19-MATCH($V67,MonthList,0))/12) -> 0
B68: R0063 | C68: Head of Technology, Commercial Fue | D68: Commercial Fuels | E68: Head of Technology | F68: NZ | G68: Filled | H68: 1 | I68: 0.2924 | J68: 0.2924 | K68: No | M68: =IF(AND($K68="Yes",$G68<>"Vendor day rates"),$J68-0.4*$I68,0) -> 0 | N68: =IF(OR($K68<>"Yes",$L68=""),0,$M68*MAX(0,7-MATCH($L68,MonthList,0))/12) -> 0 | O68: =IF(OR($K68<>"Yes",$L68=""),0,$M68*IF(MATCH($L68,MonthList,0)<=7,12,19-MATCH($L68,MonthList,0))/12) -> 0 | P68: No | R68: =IF(AND($P68="Yes",$G68<>"Vendor day rates"),$J68-0.4*$I68,0) -> 0 | S68: =IF(OR($P68<>"Yes",$Q68=""),0,$R68*MAX(0,7-MATCH($Q68,MonthList,0))/12) -> 0 | T68: =IF(OR($P68<>"Yes",$Q68=""),0,$R68*IF(MATCH($Q68,MonthList,0)<=7,12,19-MATCH($Q68,MonthList,0))/12) -> 0 | U68: No | W68: =IF(AND($U68="Yes",$G68<>"Vendor day rates"),$J68-0.4*$I68,0) -> 0 | X68: =IF(OR($U68<>"Yes",$V68=""),0,$W68*MAX(0,7-MATCH($V68,MonthList,0))/12) -> 0 | Y68: =IF(OR($U68<>"Yes",$V68=""),0,$W68*IF(MATCH($V68,MonthList,0)<=7,12,19-MATCH($V68,MonthList,0))/12) -> 0
B69: R0064 | C69: Head of Technology, B2B & Energy S | D69: B2B & Energy Solutions | E69: Head of Technology | F69: NZ | G69: Filled | H69: 1 | I69: 0.2738 | J69: 0.2738 | K69: No | M69: =IF(AND($K69="Yes",$G69<>"Vendor day rates"),$J69-0.4*$I69,0) -> 0 | N69: =IF(OR($K69<>"Yes",$L69=""),0,$M69*MAX(0,7-MATCH($L69,MonthList,0))/12) -> 0 | O69: =IF(OR($K69<>"Yes",$L69=""),0,$M69*IF(MATCH($L69,MonthList,0)<=7,12,19-MATCH($L69,MonthList,0))/12) -> 0 | P69: No | R69: =IF(AND($P69="Yes",$G69<>"Vendor day rates"),$J69-0.4*$I69,0) -> 0 | S69: =IF(OR($P69<>"Yes",$Q69=""),0,$R69*MAX(0,7-MATCH($Q69,MonthList,0))/12) -> 0 | T69: =IF(OR($P69<>"Yes",$Q69=""),0,$R69*IF(MATCH($Q69,MonthList,0)<=7,12,19-MATCH($Q69,MonthList,0))/12) -> 0 | U69: No | W69: =IF(AND($U69="Yes",$G69<>"Vendor day rates"),$J69-0.4*$I69,0) -> 0 | X69: =IF(OR($U69<>"Yes",$V69=""),0,$W69*MAX(0,7-MATCH($V69,MonthList,0))/12) -> 0 | Y69: =IF(OR($U69<>"Yes",$V69=""),0,$W69*IF(MATCH($V69,MonthList,0)<=7,12,19-MATCH($V69,MonthList,0))/12) -> 0
B70: R0065 | C70: Data Governance Lead | E70: Group Data | F70: AU | G70: Vacant, hire planned | H70: 1 | I70: 0.3896 | J70: 0.1948 | K70: No | M70: =IF(AND($K70="Yes",$G70<>"Vendor day rates"),$J70-0.4*$I70,0) -> 0 | N70: =IF(OR($K70<>"Yes",$L70=""),0,$M70*MAX(0,7-MATCH($L70,MonthList,0))/12) -> 0 | O70: =IF(OR($K70<>"Yes",$L70=""),0,$M70*IF(MATCH($L70,MonthList,0)<=7,12,19-MATCH($L70,MonthList,0))/12) -> 0 | P70: No | R70: =IF(AND($P70="Yes",$G70<>"Vendor day rates"),$J70-0.4*$I70,0) -> 0 | S70: =IF(OR($P70<>"Yes",$Q70=""),0,$R70*MAX(0,7-MATCH($Q70,MonthList,0))/12) -> 0 | T70: =IF(OR($P70<>"Yes",$Q70=""),0,$R70*IF(MATCH($Q70,MonthList,0)<=7,12,19-MATCH($Q70,MonthList,0))/12) -> 0 | U70: No | W70: =IF(AND($U70="Yes",$G70<>"Vendor day rates"),$J70-0.4*$I70,0) -> 0 | X70: =IF(OR($U70<>"Yes",$V70=""),0,$W70*MAX(0,7-MATCH($V70,MonthList,0))/12) -> 0 | Y70: =IF(OR($U70<>"Yes",$V70=""),0,$W70*IF(MATCH($V70,MonthList,0)<=7,12,19-MATCH($V70,MonthList,0))/12) -> 0
B71: R0066 | C71: Head of Technology, AU Retail | D71: Retail | E71: Head of Technology | F71: AU | G71: Filled | H71: 1 | I71: 0.186 | J71: 0.186 | K71: No | M71: =IF(AND($K71="Yes",$G71<>"Vendor day rates"),$J71-0.4*$I71,0) -> 0 | N71: =IF(OR($K71<>"Yes",$L71=""),0,$M71*MAX(0,7-MATCH($L71,MonthList,0))/12) -> 0 | O71: =IF(OR($K71<>"Yes",$L71=""),0,$M71*IF(MATCH($L71,MonthList,0)<=7,12,19-MATCH($L71,MonthList,0))/12) -> 0 | P71: No | R71: =IF(AND($P71="Yes",$G71<>"Vendor day rates"),$J71-0.4*$I71,0) -> 0 | S71: =IF(OR($P71<>"Yes",$Q71=""),0,$R71*MAX(0,7-MATCH($Q71,MonthList,0))/12) -> 0 | T71: =IF(OR($P71<>"Yes",$Q71=""),0,$R71*IF(MATCH($Q71,MonthList,0)<=7,12,19-MATCH($Q71,MonthList,0))/12) -> 0 | U71: No | W71: =IF(AND($U71="Yes",$G71<>"Vendor day rates"),$J71-0.4*$I71,0) -> 0 | X71: =IF(OR($U71<>"Yes",$V71=""),0,$W71*MAX(0,7-MATCH($V71,MonthList,0))/12) -> 0 | Y71: =IF(OR($U71<>"Yes",$V71=""),0,$W71*IF(MATCH($V71,MonthList,0)<=7,12,19-MATCH($V71,MonthList,0))/12) -> 0
B72: R0067 | C72: Head of Technology, Z and Group Re | D72: Z | E72: Head of Technology | F72: NZ | G72: Vacant, hire planned | H72: 1 | I72: 0.2914 | J72: 0.2914 | K72: No | M72: =IF(AND($K72="Yes",$G72<>"Vendor day rates"),$J72-0.4*$I72,0) -> 0 | N72: =IF(OR($K72<>"Yes",$L72=""),0,$M72*MAX(0,7-MATCH($L72,MonthList,0))/12) -> 0 | O72: =IF(OR($K72<>"Yes",$L72=""),0,$M72*IF(MATCH($L72,MonthList,0)<=7,12,19-MATCH($L72,MonthList,0))/12) -> 0 | P72: No | R72: =IF(AND($P72="Yes",$G72<>"Vendor day rates"),$J72-0.4*$I72,0) -> 0 | S72: =IF(OR($P72<>"Yes",$Q72=""),0,$R72*MAX(0,7-MATCH($Q72,MonthList,0))/12) -> 0 | T72: =IF(OR($P72<>"Yes",$Q72=""),0,$R72*IF(MATCH($Q72,MonthList,0)<=7,12,19-MATCH($Q72,MonthList,0))/12) -> 0 | U72: No | W72: =IF(AND($U72="Yes",$G72<>"Vendor day rates"),$J72-0.4*$I72,0) -> 0 | X72: =IF(OR($U72<>"Yes",$V72=""),0,$W72*MAX(0,7-MATCH($V72,MonthList,0))/12) -> 0 | Y72: =IF(OR($U72<>"Yes",$V72=""),0,$W72*IF(MATCH($V72,MonthList,0)<=7,12,19-MATCH($V72,MonthList,0))/12) -> 0
B73: R0068 | C73: Delivery Manager | D73: Z ENERGY (DIGITAL) | E73: Delivery Manager | F73: NZ | G73: Filled | H73: 1 | I73: 0.222 | J73: 0.222 | K73: No | M73: =IF(AND($K73="Yes",$G73<>"Vendor day rates"),$J73-0.4*$I73,0) -> 0 | N73: =IF(OR($K73<>"Yes",$L73=""),0,$M73*MAX(0,7-MATCH($L73,MonthList,0))/12) -> 0 | O73: =IF(OR($K73<>"Yes",$L73=""),0,$M73*IF(MATCH($L73,MonthList,0)<=7,12,19-MATCH($L73,MonthList,0))/12) -> 0 | P73: No | R73: =IF(AND($P73="Yes",$G73<>"Vendor day rates"),$J73-0.4*$I73,0) -> 0 | S73: =IF(OR($P73<>"Yes",$Q73=""),0,$R73*MAX(0,7-MATCH($Q73,MonthList,0))/12) -> 0 | T73: =IF(OR($P73<>"Yes",$Q73=""),0,$R73*IF(MATCH($Q73,MonthList,0)<=7,12,19-MATCH($Q73,MonthList,0))/12) -> 0 | U73: No | W73: =IF(AND($U73="Yes",$G73<>"Vendor day rates"),$J73-0.4*$I73,0) -> 0 | X73: =IF(OR($U73<>"Yes",$V73=""),0,$W73*MAX(0,7-MATCH($V73,MonthList,0))/12) -> 0 | Y73: =IF(OR($U73<>"Yes",$V73=""),0,$W73*IF(MATCH($V73,MonthList,0)<=7,12,19-MATCH($V73,MonthList,0))/12) -> 0
B74: R0069 | C74: Technology Manager – Data & Engine | D74: Z ENERGY (DIGITAL) | E74: Technology Manager | F74: NZ | G74: Filled | H74: 1 | I74: 0.2077 | J74: 0.2077 | K74: No | M74: =IF(AND($K74="Yes",$G74<>"Vendor day rates"),$J74-0.4*$I74,0) -> 0 | N74: =IF(OR($K74<>"Yes",$L74=""),0,$M74*MAX(0,7-MATCH($L74,MonthList,0))/12) -> 0 | O74: =IF(OR($K74<>"Yes",$L74=""),0,$M74*IF(MATCH($L74,MonthList,0)<=7,12,19-MATCH($L74,MonthList,0))/12) -> 0 | P74: No | R74: =IF(AND($P74="Yes",$G74<>"Vendor day rates"),$J74-0.4*$I74,0) -> 0 | S74: =IF(OR($P74<>"Yes",$Q74=""),0,$R74*MAX(0,7-MATCH($Q74,MonthList,0))/12) -> 0 | T74: =IF(OR($P74<>"Yes",$Q74=""),0,$R74*IF(MATCH($Q74,MonthList,0)<=7,12,19-MATCH($Q74,MonthList,0))/12) -> 0 | U74: No | W74: =IF(AND($U74="Yes",$G74<>"Vendor day rates"),$J74-0.4*$I74,0) -> 0 | X74: =IF(OR($U74<>"Yes",$V74=""),0,$W74*MAX(0,7-MATCH($V74,MonthList,0))/12) -> 0 | Y74: =IF(OR($U74<>"Yes",$V74=""),0,$W74*IF(MATCH($V74,MonthList,0)<=7,12,19-MATCH($V74,MonthList,0))/12) -> 0
B75: R0070 | C75: Technology Manager - Loyalty & Mar | D75: Z ENERGY (DIGITAL) | E75: Technology Manager | F75: NZ | G75: Filled | H75: 1 | I75: 0.2232 | J75: 0.2232 | K75: No | M75: =IF(AND($K75="Yes",$G75<>"Vendor day rates"),$J75-0.4*$I75,0) -> 0 | N75: =IF(OR($K75<>"Yes",$L75=""),0,$M75*MAX(0,7-MATCH($L75,MonthList,0))/12) -> 0 | O75: =IF(OR($K75<>"Yes",$L75=""),0,$M75*IF(MATCH($L75,MonthList,0)<=7,12,19-MATCH($L75,MonthList,0))/12) -> 0 | P75: No | R75: =IF(AND($P75="Yes",$G75<>"Vendor day rates"),$J75-0.4*$I75,0) -> 0 | S75: =IF(OR($P75<>"Yes",$Q75=""),0,$R75*MAX(0,7-MATCH($Q75,MonthList,0))/12) -> 0 | T75: =IF(OR($P75<>"Yes",$Q75=""),0,$R75*IF(MATCH($Q75,MonthList,0)<=7,12,19-MATCH($Q75,MonthList,0))/12) -> 0 | U75: No | W75: =IF(AND($U75="Yes",$G75<>"Vendor day rates"),$J75-0.4*$I75,0) -> 0 | X75: =IF(OR($U75<>"Yes",$V75=""),0,$W75*MAX(0,7-MATCH($V75,MonthList,0))/12) -> 0 | Y75: =IF(OR($U75<>"Yes",$V75=""),0,$W75*IF(MATCH($V75,MonthList,0)<=7,12,19-MATCH($V75,MonthList,0))/12) -> 0
B76: R0071 | C76: Head of AI enablement | D76: Ampol Customer | E76: Customer, AI | F76: AU | G76: Filled | H76: 1 | I76: 0.3397 | J76: 0.3397 | K76: No | M76: =IF(AND($K76="Yes",$G76<>"Vendor day rates"),$J76-0.4*$I76,0) -> 0 | N76: =IF(OR($K76<>"Yes",$L76=""),0,$M76*MAX(0,7-MATCH($L76,MonthList,0))/12) -> 0 | O76: =IF(OR($K76<>"Yes",$L76=""),0,$M76*IF(MATCH($L76,MonthList,0)<=7,12,19-MATCH($L76,MonthList,0))/12) -> 0 | P76: No | R76: =IF(AND($P76="Yes",$G76<>"Vendor day rates"),$J76-0.4*$I76,0) -> 0 | S76: =IF(OR($P76<>"Yes",$Q76=""),0,$R76*MAX(0,7-MATCH($Q76,MonthList,0))/12) -> 0 | T76: =IF(OR($P76<>"Yes",$Q76=""),0,$R76*IF(MATCH($Q76,MonthList,0)<=7,12,19-MATCH($Q76,MonthList,0))/12) -> 0 | U76: No | W76: =IF(AND($U76="Yes",$G76<>"Vendor day rates"),$J76-0.4*$I76,0) -> 0 | X76: =IF(OR($U76<>"Yes",$V76=""),0,$W76*MAX(0,7-MATCH($V76,MonthList,0))/12) -> 0 | Y76: =IF(OR($U76<>"Yes",$V76=""),0,$W76*IF(MATCH($V76,MonthList,0)<=7,12,19-MATCH($V76,MonthList,0))/12) -> 0
B77: R0072 | C77: Program Manager | D77: Ampol Customer | E77: EGI Customer | F77: AU | G77: Vacant, hire planned | H77: 1 | I77: 0.3049 | J77: 0.3049 | K77: No | M77: =IF(AND($K77="Yes",$G77<>"Vendor day rates"),$J77-0.4*$I77,0) -> 0 | N77: =IF(OR($K77<>"Yes",$L77=""),0,$M77*MAX(0,7-MATCH($L77,MonthList,0))/12) -> 0 | O77: =IF(OR($K77<>"Yes",$L77=""),0,$M77*IF(MATCH($L77,MonthList,0)<=7,12,19-MATCH($L77,MonthList,0))/12) -> 0 | P77: No | R77: =IF(AND($P77="Yes",$G77<>"Vendor day rates"),$J77-0.4*$I77,0) -> 0 | S77: =IF(OR($P77<>"Yes",$Q77=""),0,$R77*MAX(0,7-MATCH($Q77,MonthList,0))/12) -> 0 | T77: =IF(OR($P77<>"Yes",$Q77=""),0,$R77*IF(MATCH($Q77,MonthList,0)<=7,12,19-MATCH($Q77,MonthList,0))/12) -> 0 | U77: No | W77: =IF(AND($U77="Yes",$G77<>"Vendor day rates"),$J77-0.4*$I77,0) -> 0 | X77: =IF(OR($U77<>"Yes",$V77=""),0,$W77*MAX(0,7-MATCH($V77,MonthList,0))/12) -> 0 | Y77: =IF(OR($U77<>"Yes",$V77=""),0,$W77*IF(MATCH($V77,MonthList,0)<=7,12,19-MATCH($V77,MonthList,0))/12) -> 0
B78: R0073 | C78: Delivery Manager | D78: Ampol Customer | E78: Delivery Manager | F78: AU | G78: Filled | H78: 1 | I78: 0.3049 | J78: 0.3049 | K78: No | M78: =IF(AND($K78="Yes",$G78<>"Vendor day rates"),$J78-0.4*$I78,0) -> 0 | N78: =IF(OR($K78<>"Yes",$L78=""),0,$M78*MAX(0,7-MATCH($L78,MonthList,0))/12) -> 0 | O78: =IF(OR($K78<>"Yes",$L78=""),0,$M78*IF(MATCH($L78,MonthList,0)<=7,12,19-MATCH($L78,MonthList,0))/12) -> 0 | P78: No | R78: =IF(AND($P78="Yes",$G78<>"Vendor day rates"),$J78-0.4*$I78,0) -> 0 | S78: =IF(OR($P78<>"Yes",$Q78=""),0,$R78*MAX(0,7-MATCH($Q78,MonthList,0))/12) -> 0 | T78: =IF(OR($P78<>"Yes",$Q78=""),0,$R78*IF(MATCH($Q78,MonthList,0)<=7,12,19-MATCH($Q78,MonthList,0))/12) -> 0 | U78: No | W78: =IF(AND($U78="Yes",$G78<>"Vendor day rates"),$J78-0.4*$I78,0) -> 0 | X78: =IF(OR($U78<>"Yes",$V78=""),0,$W78*MAX(0,7-MATCH($V78,MonthList,0))/12) -> 0 | Y78: =IF(OR($U78<>"Yes",$V78=""),0,$W78*IF(MATCH($V78,MonthList,0)<=7,12,19-MATCH($V78,MonthList,0))/12) -> 0
B79: R0074 | C79: Design Manager | D79: Z ENERGY (DIGITAL) | E79: Z App and Web | F79: NZ | G79: Filled | H79: 1 | I79: 0.2092 | J79: 0.2092 | K79: No | M79: =IF(AND($K79="Yes",$G79<>"Vendor day rates"),$J79-0.4*$I79,0) -> 0 | N79: =IF(OR($K79<>"Yes",$L79=""),0,$M79*MAX(0,7-MATCH($L79,MonthList,0))/12) -> 0 | O79: =IF(OR($K79<>"Yes",$L79=""),0,$M79*IF(MATCH($L79,MonthList,0)<=7,12,19-MATCH($L79,MonthList,0))/12) -> 0 | P79: No | R79: =IF(AND($P79="Yes",$G79<>"Vendor day rates"),$J79-0.4*$I79,0) -> 0 | S79: =IF(OR($P79<>"Yes",$Q79=""),0,$R79*MAX(0,7-MATCH($Q79,MonthList,0))/12) -> 0 | T79: =IF(OR($P79<>"Yes",$Q79=""),0,$R79*IF(MATCH($Q79,MonthList,0)<=7,12,19-MATCH($Q79,MonthList,0))/12) -> 0 | U79: No | W79: =IF(AND($U79="Yes",$G79<>"Vendor day rates"),$J79-0.4*$I79,0) -> 0 | X79: =IF(OR($U79<>"Yes",$V79=""),0,$W79*MAX(0,7-MATCH($V79,MonthList,0))/12) -> 0 | Y79: =IF(OR($U79<>"Yes",$V79=""),0,$W79*IF(MATCH($V79,MonthList,0)<=7,12,19-MATCH($V79,MonthList,0))/12) -> 0
B80: R0075 | C80: Technology Manager - Digital | D80: Ampol Customer | E80: Technology Manager | F80: AU | G80: Filled | H80: 1 | I80: 0.3011 | J80: 0.3011 | K80: No | M80: =IF(AND($K80="Yes",$G80<>"Vendor day rates"),$J80-0.4*$I80,0) -> 0 | N80: =IF(OR($K80<>"Yes",$L80=""),0,$M80*MAX(0,7-MATCH($L80,MonthList,0))/12) -> 0 | O80: =IF(OR($K80<>"Yes",$L80=""),0,$M80*IF(MATCH($L80,MonthList,0)<=7,12,19-MATCH($L80,MonthList,0))/12) -> 0 | P80: No | R80: =IF(AND($P80="Yes",$G80<>"Vendor day rates"),$J80-0.4*$I80,0) -> 0 | S80: =IF(OR($P80<>"Yes",$Q80=""),0,$R80*MAX(0,7-MATCH($Q80,MonthList,0))/12) -> 0 | T80: =IF(OR($P80<>"Yes",$Q80=""),0,$R80*IF(MATCH($Q80,MonthList,0)<=7,12,19-MATCH($Q80,MonthList,0))/12) -> 0 | U80: No | W80: =IF(AND($U80="Yes",$G80<>"Vendor day rates"),$J80-0.4*$I80,0) -> 0 | X80: =IF(OR($U80<>"Yes",$V80=""),0,$W80*MAX(0,7-MATCH($V80,MonthList,0))/12) -> 0 | Y80: =IF(OR($U80<>"Yes",$V80=""),0,$W80*IF(MATCH($V80,MonthList,0)<=7,12,19-MATCH($V80,MonthList,0))/12) -> 0
B81: R0076 | C81: Principal Engineer | D81: EGI Integration | E81: EGI Customer | F81: AU | G81: Filled | H81: 1 | I81: 0.3049 | J81: 0.3049 | K81: No | M81: =IF(AND($K81="Yes",$G81<>"Vendor day rates"),$J81-0.4*$I81,0) -> 0 | N81: =IF(OR($K81<>"Yes",$L81=""),0,$M81*MAX(0,7-MATCH($L81,MonthList,0))/12) -> 0 | O81: =IF(OR($K81<>"Yes",$L81=""),0,$M81*IF(MATCH($L81,MonthList,0)<=7,12,19-MATCH($L81,MonthList,0))/12) -> 0 | P81: No | R81: =IF(AND($P81="Yes",$G81<>"Vendor day rates"),$J81-0.4*$I81,0) -> 0 | S81: =IF(OR($P81<>"Yes",$Q81=""),0,$R81*MAX(0,7-MATCH($Q81,MonthList,0))/12) -> 0 | T81: =IF(OR($P81<>"Yes",$Q81=""),0,$R81*IF(MATCH($Q81,MonthList,0)<=7,12,19-MATCH($Q81,MonthList,0))/12) -> 0 | U81: No | W81: =IF(AND($U81="Yes",$G81<>"Vendor day rates"),$J81-0.4*$I81,0) -> 0 | X81: =IF(OR($U81<>"Yes",$V81=""),0,$W81*MAX(0,7-MATCH($V81,MonthList,0))/12) -> 0 | Y81: =IF(OR($U81<>"Yes",$V81=""),0,$W81*IF(MATCH($V81,MonthList,0)<=7,12,19-MATCH($V81,MonthList,0))/12) -> 0
B82: R0077 | C82: Technology Manager, Engineering | D82: Ampol Customer | E82: Technology Manager | F82: AU | G82: Vacant, hire planned | H82: 1 | I82: 0.3049 | J82: 0.3049 | K82: No | M82: =IF(AND($K82="Yes",$G82<>"Vendor day rates"),$J82-0.4*$I82,0) -> 0 | N82: =IF(OR($K82<>"Yes",$L82=""),0,$M82*MAX(0,7-MATCH($L82,MonthList,0))/12) -> 0 | O82: =IF(OR($K82<>"Yes",$L82=""),0,$M82*IF(MATCH($L82,MonthList,0)<=7,12,19-MATCH($L82,MonthList,0))/12) -> 0 | P82: No | R82: =IF(AND($P82="Yes",$G82<>"Vendor day rates"),$J82-0.4*$I82,0) -> 0 | S82: =IF(OR($P82<>"Yes",$Q82=""),0,$R82*MAX(0,7-MATCH($Q82,MonthList,0))/12) -> 0 | T82: =IF(OR($P82<>"Yes",$Q82=""),0,$R82*IF(MATCH($Q82,MonthList,0)<=7,12,19-MATCH($Q82,MonthList,0))/12) -> 0 | U82: No | W82: =IF(AND($U82="Yes",$G82<>"Vendor day rates"),$J82-0.4*$I82,0) -> 0 | X82: =IF(OR($U82<>"Yes",$V82=""),0,$W82*MAX(0,7-MATCH($V82,MonthList,0))/12) -> 0 | Y82: =IF(OR($U82<>"Yes",$V82=""),0,$W82*IF(MATCH($V82,MonthList,0)<=7,12,19-MATCH($V82,MonthList,0))/12) -> 0
... B106: R0101 | C106: Program Manager - CTRM | D106: Commercial Fuels | E106: CTRM | F106: AU | G106: Filled | H106: 1 | I106: 0.3237 | J106: 0.3237 | K106: No | M106: =IF(AND($K106="Yes",$G106<>"Vendor day rates"),$J106-0.4*$I106,0) -> 0 | N106: =IF(OR($K106<>"Yes",$L106=""),0,$M106*MAX(0,7-MATCH($L106,MonthList,0))/12) -> 0 | O106: =IF(OR($K106<>"Yes",$L106=""),0,$M106*IF(MATCH($L106,MonthList,0)<=7,12,19-MATCH($L106,MonthList,0))/12) -> 0 | P106: No | R106: =IF(AND($P106="Yes",$G106<>"Vendor day rates"),$J106-0.4*$I106,0) -> 0 | S106: =IF(OR($P106<>"Yes",$Q106=""),0,$R106*MAX(0,7-MATCH($Q106,MonthList,0))/12) -> 0 | T106: =IF(OR($P106<>"Yes",$Q106=""),0,$R106*IF(MATCH($Q106,MonthList,0)<=7,12,19-MATCH($Q106,MonthList,0))/12) -> 0 | U106: No | W106: =IF(AND($U106="Yes",$G106<>"Vendor day rates"),$J106-0.4*$I106,0) -> 0 | X106: =IF(OR($U106<>"Yes",$V106=""),0,$W106*MAX(0,7-MATCH($V106,MonthList,0))/12) -> 0 | Y106: =IF(OR($U106<>"Yes",$V106=""),0,$W106*IF(MATCH($V106,MonthList,0)<=7,12,19-MATCH($V106,MonthList,0))/12) -> 0
B107: R0102 | C107: Domain Architect - Group Functions | E107: Architecture | F107: NZ | G107: Filled | H107: 1 | I107: 0.2427 | J107: 0.2427 | K107: No | M107: =IF(AND($K107="Yes",$G107<>"Vendor day rates"),$J107-0.4*$I107,0) -> 0 | N107: =IF(OR($K107<>"Yes",$L107=""),0,$M107*MAX(0,7-MATCH($L107,MonthList,0))/12) -> 0 | O107: =IF(OR($K107<>"Yes",$L107=""),0,$M107*IF(MATCH($L107,MonthList,0)<=7,12,19-MATCH($L107,MonthList,0))/12) -> 0 | P107: No | R107: =IF(AND($P107="Yes",$G107<>"Vendor day rates"),$J107-0.4*$I107,0) -> 0 | S107: =IF(OR($P107<>"Yes",$Q107=""),0,$R107*MAX(0,7-MATCH($Q107,MonthList,0))/12) -> 0 | T107: =IF(OR($P107<>"Yes",$Q107=""),0,$R107*IF(MATCH($Q107,MonthList,0)<=7,12,19-MATCH($Q107,MonthList,0))/12) -> 0 | U107: No | W107: =IF(AND($U107="Yes",$G107<>"Vendor day rates"),$J107-0.4*$I107,0) -> 0 | X107: =IF(OR($U107<>"Yes",$V107=""),0,$W107*MAX(0,7-MATCH($V107,MonthList,0))/12) -> 0 | Y107: =IF(OR($U107<>"Yes",$V107=""),0,$W107*IF(MATCH($V107,MonthList,0)<=7,12,19-MATCH($V107,MonthList,0))/12) -> 0
B108: R0103 | C108: Enterprise Architect | E108: Architecture | F108: NZ | G108: Filled | H108: 1 | I108: 0.2143 | J108: 0.2143 | K108: No | M108: =IF(AND($K108="Yes",$G108<>"Vendor day rates"),$J108-0.4*$I108,0) -> 0 | N108: =IF(OR($K108<>"Yes",$L108=""),0,$M108*MAX(0,7-MATCH($L108,MonthList,0))/12) -> 0 | O108: =IF(OR($K108<>"Yes",$L108=""),0,$M108*IF(MATCH($L108,MonthList,0)<=7,12,19-MATCH($L108,MonthList,0))/12) -> 0 | P108: No | R108: =IF(AND($P108="Yes",$G108<>"Vendor day rates"),$J108-0.4*$I108,0) -> 0 | S108: =IF(OR($P108<>"Yes",$Q108=""),0,$R108*MAX(0,7-MATCH($Q108,MonthList,0))/12) -> 0 | T108: =IF(OR($P108<>"Yes",$Q108=""),0,$R108*IF(MATCH($Q108,MonthList,0)<=7,12,19-MATCH($Q108,MonthList,0))/12) -> 0 | U108: No | W108: =IF(AND($U108="Yes",$G108<>"Vendor day rates"),$J108-0.4*$I108,0) -> 0 | X108: =IF(OR($U108<>"Yes",$V108=""),0,$W108*MAX(0,7-MATCH($V108,MonthList,0))/12) -> 0 | Y108: =IF(OR($U108<>"Yes",$V108=""),0,$W108*IF(MATCH($V108,MonthList,0)<=7,12,19-MATCH($V108,MonthList,0))/12) -> 0
B109: R0104 | C109: Domain Architect - CFE & Infrastru | E109: Architecture | F109: NZ | G109: Filled | H109: 1 | I109: 0.2369 | J109: 0.2369 | K109: No | M109: =IF(AND($K109="Yes",$G109<>"Vendor day rates"),$J109-0.4*$I109,0) -> 0 | N109: =IF(OR($K109<>"Yes",$L109=""),0,$M109*MAX(0,7-MATCH($L109,MonthList,0))/12) -> 0 | O109: =IF(OR($K109<>"Yes",$L109=""),0,$M109*IF(MATCH($L109,MonthList,0)<=7,12,19-MATCH($L109,MonthList,0))/12) -> 0 | P109: No | R109: =IF(AND($P109="Yes",$G109<>"Vendor day rates"),$J109-0.4*$I109,0) -> 0 | S109: =IF(OR($P109<>"Yes",$Q109=""),0,$R109*MAX(0,7-MATCH($Q109,MonthList,0))/12) -> 0 | T109: =IF(OR($P109<>"Yes",$Q109=""),0,$R109*IF(MATCH($Q109,MonthList,0)<=7,12,19-MATCH($Q109,MonthList,0))/12) -> 0 | U109: No | W109: =IF(AND($U109="Yes",$G109<>"Vendor day rates"),$J109-0.4*$I109,0) -> 0 | X109: =IF(OR($U109<>"Yes",$V109=""),0,$W109*MAX(0,7-MATCH($V109,MonthList,0))/12) -> 0 | Y109: =IF(OR($U109<>"Yes",$V109=""),0,$W109*IF(MATCH($V109,MonthList,0)<=7,12,19-MATCH($V109,MonthList,0))/12) -> 0
B110: R0105 | C110: Technology Manager, Enterprise Too | D110: TDD | E110: Technology Manager | F110: AU | G110: Filled | H110: 1 | I110: 0.2758 | J110: 0.2758 | K110: No | M110: =IF(AND($K110="Yes",$G110<>"Vendor day rates"),$J110-0.4*$I110,0) -> 0 | N110: =IF(OR($K110<>"Yes",$L110=""),0,$M110*MAX(0,7-MATCH($L110,MonthList,0))/12) -> 0 | O110: =IF(OR($K110<>"Yes",$L110=""),0,$M110*IF(MATCH($L110,MonthList,0)<=7,12,19-MATCH($L110,MonthList,0))/12) -> 0 | P110: No | R110: =IF(AND($P110="Yes",$G110<>"Vendor day rates"),$J110-0.4*$I110,0) -> 0 | S110: =IF(OR($P110<>"Yes",$Q110=""),0,$R110*MAX(0,7-MATCH($Q110,MonthList,0))/12) -> 0 | T110: =IF(OR($P110<>"Yes",$Q110=""),0,$R110*IF(MATCH($Q110,MonthList,0)<=7,12,19-MATCH($Q110,MonthList,0))/12) -> 0 | U110: No | W110: =IF(AND($U110="Yes",$G110<>"Vendor day rates"),$J110-0.4*$I110,0) -> 0 | X110: =IF(OR($U110<>"Yes",$V110=""),0,$W110*MAX(0,7-MATCH($V110,MonthList,0))/12) -> 0 | Y110: =IF(OR($U110<>"Yes",$V110=""),0,$W110*IF(MATCH($V110,MonthList,0)<=7,12,19-MATCH($V110,MonthList,0))/12) -> 0
B111: R0106 | C111: Technology Manager – DevOps and Qu | D111: TDD | E111: Technology Manager | F111: NZ | G111: Filled | H111: 1 | I111: 0.2215 | J111: 0.2215 | K111: No | M111: =IF(AND($K111="Yes",$G111<>"Vendor day rates"),$J111-0.4*$I111,0) -> 0 | N111: =IF(OR($K111<>"Yes",$L111=""),0,$M111*MAX(0,7-MATCH($L111,MonthList,0))/12) -> 0 | O111: =IF(OR($K111<>"Yes",$L111=""),0,$M111*IF(MATCH($L111,MonthList,0)<=7,12,19-MATCH($L111,MonthList,0))/12) -> 0 | P111: No | R111: =IF(AND($P111="Yes",$G111<>"Vendor day rates"),$J111-0.4*$I111,0) -> 0 | S111: =IF(OR($P111<>"Yes",$Q111=""),0,$R111*MAX(0,7-MATCH($Q111,MonthList,0))/12) -> 0 | T111: =IF(OR($P111<>"Yes",$Q111=""),0,$R111*IF(MATCH($Q111,MonthList,0)<=7,12,19-MATCH($Q111,MonthList,0))/12) -> 0 | U111: No | W111: =IF(AND($U111="Yes",$G111<>"Vendor day rates"),$J111-0.4*$I111,0) -> 0 | X111: =IF(OR($U111<>"Yes",$V111=""),0,$W111*MAX(0,7-MATCH($V111,MonthList,0))/12) -> 0 | Y111: =IF(OR($U111<>"Yes",$V111=""),0,$W111*IF(MATCH($V111,MonthList,0)<=7,12,19-MATCH($V111,MonthList,0))/12) -> 0
B112: R0107 | C112: Technology Manager, Engineering | D112: Z | E112: Technology Manager | F112: NZ | G112: Filled | H112: 1 | I112: 0.2365 | J112: 0.2365 | K112: No | M112: =IF(AND($K112="Yes",$G112<>"Vendor day rates"),$J112-0.4*$I112,0) -> 0 | N112: =IF(OR($K112<>"Yes",$L112=""),0,$M112*MAX(0,7-MATCH($L112,MonthList,0))/12) -> 0 | O112: =IF(OR($K112<>"Yes",$L112=""),0,$M112*IF(MATCH($L112,MonthList,0)<=7,12,19-MATCH($L112,MonthList,0))/12) -> 0 | P112: No | R112: =IF(AND($P112="Yes",$G112<>"Vendor day rates"),$J112-0.4*$I112,0) -> 0 | S112: =IF(OR($P112<>"Yes",$Q112=""),0,$R112*MAX(0,7-MATCH($Q112,MonthList,0))/12) -> 0 | T112: =IF(OR($P112<>"Yes",$Q112=""),0,$R112*IF(MATCH($Q112,MonthList,0)<=7,12,19-MATCH($Q112,MonthList,0))/12) -> 0 | U112: No | W112: =IF(AND($U112="Yes",$G112<>"Vendor day rates"),$J112-0.4*$I112,0) -> 0 | X112: =IF(OR($U112<>"Yes",$V112=""),0,$W112*MAX(0,7-MATCH($V112,MonthList,0))/12) -> 0 | Y112: =IF(OR($U112<>"Yes",$V112=""),0,$W112*IF(MATCH($V112,MonthList,0)<=7,12,19-MATCH($V112,MonthList,0))/12) -> 0
B113: R0108 | C113: Technology Manager, Data | D113: Z | E113: Technology Manager | F113: AU | G113: Filled | H113: 1 | I113: 0.2542 | J113: 0.2542 | K113: No | M113: =IF(AND($K113="Yes",$G113<>"Vendor day rates"),$J113-0.4*$I113,0) -> 0 | N113: =IF(OR($K113<>"Yes",$L113=""),0,$M113*MAX(0,7-MATCH($L113,MonthList,0))/12) -> 0 | O113: =IF(OR($K113<>"Yes",$L113=""),0,$M113*IF(MATCH($L113,MonthList,0)<=7,12,19-MATCH($L113,MonthList,0))/12) -> 0 | P113: No | R113: =IF(AND($P113="Yes",$G113<>"Vendor day rates"),$J113-0.4*$I113,0) -> 0 | S113: =IF(OR($P113<>"Yes",$Q113=""),0,$R113*MAX(0,7-MATCH($Q113,MonthList,0))/12) -> 0 | T113: =IF(OR($P113<>"Yes",$Q113=""),0,$R113*IF(MATCH($Q113,MonthList,0)<=7,12,19-MATCH($Q113,MonthList,0))/12) -> 0 | U113: No | W113: =IF(AND($U113="Yes",$G113<>"Vendor day rates"),$J113-0.4*$I113,0) -> 0 | X113: =IF(OR($U113<>"Yes",$V113=""),0,$W113*MAX(0,7-MATCH($V113,MonthList,0))/12) -> 0 | Y113: =IF(OR($U113<>"Yes",$V113=""),0,$W113*IF(MATCH($V113,MonthList,0)<=7,12,19-MATCH($V113,MonthList,0))/12) -> 0
B114: R0109 | C114: Delivery Excellence Manager | D114: NA | E114: Transformation | F114: AU | G114: Vacant, hire planned | H114: 1 | I114: 0.2758 | J114: 0.2758 | K114: No | M114: =IF(AND($K114="Yes",$G114<>"Vendor day rates"),$J114-0.4*$I114,0) -> 0 | N114: =IF(OR($K114<>"Yes",$L114=""),0,$M114*MAX(0,7-MATCH($L114,MonthList,0))/12) -> 0 | O114: =IF(OR($K114<>"Yes",$L114=""),0,$M114*IF(MATCH($L114,MonthList,0)<=7,12,19-MATCH($L114,MonthList,0))/12) -> 0 | P114: No | R114: =IF(AND($P114="Yes",$G114<>"Vendor day rates"),$J114-0.4*$I114,0) -> 0 | S114: =IF(OR($P114<>"Yes",$Q114=""),0,$R114*MAX(0,7-MATCH($Q114,MonthList,0))/12) -> 0 | T114: =IF(OR($P114<>"Yes",$Q114=""),0,$R114*IF(MATCH($Q114,MonthList,0)<=7,12,19-MATCH($Q114,MonthList,0))/12) -> 0 | U114: No | W114: =IF(AND($U114="Yes",$G114<>"Vendor day rates"),$J114-0.4*$I114,0) -> 0 | X114: =IF(OR($U114<>"Yes",$V114=""),0,$W114*MAX(0,7-MATCH($V114,MonthList,0))/12) -> 0 | Y114: =IF(OR($U114<>"Yes",$V114=""),0,$W114*IF(MATCH($V114,MonthList,0)<=7,12,19-MATCH($V114,MonthList,0))/12) -> 0
B115: R0110 | C115: Enterprise Architect | E115: Architecture | F115: AU | G115: Held today | H115: 1 | I115: 0.2758 | J115: 0 | K115: No | M115: =IF(AND($K115="Yes",$G115<>"Vendor day rates"),$J115-0.4*$I115,0) -> 0 | N115: =IF(OR($K115<>"Yes",$L115=""),0,$M115*MAX(0,7-MATCH($L115,MonthList,0))/12) -> 0 | O115: =IF(OR($K115<>"Yes",$L115=""),0,$M115*IF(MATCH($L115,MonthList,0)<=7,12,19-MATCH($L115,MonthList,0))/12) -> 0 | P115: No | R115: =IF(AND($P115="Yes",$G115<>"Vendor day rates"),$J115-0.4*$I115,0) -> 0 | S115: =IF(OR($P115<>"Yes",$Q115=""),0,$R115*MAX(0,7-MATCH($Q115,MonthList,0))/12) -> 0 | T115: =IF(OR($P115<>"Yes",$Q115=""),0,$R115*IF(MATCH($Q115,MonthList,0)<=7,12,19-MATCH($Q115,MonthList,0))/12) -> 0 | U115: No | W115: =IF(AND($U115="Yes",$G115<>"Vendor day rates"),$J115-0.4*$I115,0) -> 0 | X115: =IF(OR($U115<>"Yes",$V115=""),0,$W115*MAX(0,7-MATCH($V115,MonthList,0))/12) -> 0 | Y115: =IF(OR($U115<>"Yes",$V115=""),0,$W115*IF(MATCH($V115,MonthList,0)<=7,12,19-MATCH($V115,MonthList,0))/12) -> 0
B116: R0111 | C116: AI Capability Lead | E116: Technology Strategy & AI Cap | F116: AU | G116: Vacant, hire planned | H116: 1 | I116: 0.2758 | J116: 0.2758 | K116: No | M116: =IF(AND($K116="Yes",$G116<>"Vendor day rates"),$J116-0.4*$I116,0) -> 0 | N116: =IF(OR($K116<>"Yes",$L116=""),0,$M116*MAX(0,7-MATCH($L116,MonthList,0))/12) -> 0 | O116: =IF(OR($K116<>"Yes",$L116=""),0,$M116*IF(MATCH($L116,MonthList,0)<=7,12,19-MATCH($L116,MonthList,0))/12) -> 0 | P116: No | R116: =IF(AND($P116="Yes",$G116<>"Vendor day rates"),$J116-0.4*$I116,0) -> 0 | S116: =IF(OR($P116<>"Yes",$Q116=""),0,$R116*MAX(0,7-MATCH($Q116,MonthList,0))/12) -> 0 | T116: =IF(OR($P116<>"Yes",$Q116=""),0,$R116*IF(MATCH($Q116,MonthList,0)<=7,12,19-MATCH($Q116,MonthList,0))/12) -> 0 | U116: No | W116: =IF(AND($U116="Yes",$G116<>"Vendor day rates"),$J116-0.4*$I116,0) -> 0 | X116: =IF(OR($U116<>"Yes",$V116=""),0,$W116*MAX(0,7-MATCH($V116,MonthList,0))/12) -> 0 | Y116: =IF(OR($U116<>"Yes",$V116=""),0,$W116*IF(MATCH($V116,MonthList,0)<=7,12,19-MATCH($V116,MonthList,0))/12) -> 0
B117: R0112 | C117: Technology Manager, Integration & | D117: TDD | E117: Technology Manager | F117: NZ | G117: Filled | H117: 1 | I117: 0.2292 | J117: 0.2292 | K117: No | M117: =IF(AND($K117="Yes",$G117<>"Vendor day rates"),$J117-0.4*$I117,0) -> 0 | N117: =IF(OR($K117<>"Yes",$L117=""),0,$M117*MAX(0,7-MATCH($L117,MonthList,0))/12) -> 0 | O117: =IF(OR($K117<>"Yes",$L117=""),0,$M117*IF(MATCH($L117,MonthList,0)<=7,12,19-MATCH($L117,MonthList,0))/12) -> 0 | P117: No | R117: =IF(AND($P117="Yes",$G117<>"Vendor day rates"),$J117-0.4*$I117,0) -> 0 | S117: =IF(OR($P117<>"Yes",$Q117=""),0,$R117*MAX(0,7-MATCH($Q117,MonthList,0))/12) -> 0 | T117: =IF(OR($P117<>"Yes",$Q117=""),0,$R117*IF(MATCH($Q117,MonthList,0)<=7,12,19-MATCH($Q117,MonthList,0))/12) -> 0 | U117: No | W117: =IF(AND($U117="Yes",$G117<>"Vendor day rates"),$J117-0.4*$I117,0) -> 0 | X117: =IF(OR($U117<>"Yes",$V117=""),0,$W117*MAX(0,7-MATCH($V117,MonthList,0))/12) -> 0 | Y117: =IF(OR($U117<>"Yes",$V117=""),0,$W117*IF(MATCH($V117,MonthList,0)<=7,12,19-MATCH($V117,MonthList,0))/12) -> 0
B118: R0113 | C118: Delivery Manager | D118: TDD | E118: Delivery Manager | F118: AU | G118: Vacant, hire planned | H118: 1 | I118: 0.2758 | J118: 0.2758 | K118: No | M118: =IF(AND($K118="Yes",$G118<>"Vendor day rates"),$J118-0.4*$I118,0) -> 0 | N118: =IF(OR($K118<>"Yes",$L118=""),0,$M118*MAX(0,7-MATCH($L118,MonthList,0))/12) -> 0 | O118: =IF(OR($K118<>"Yes",$L118=""),0,$M118*IF(MATCH($L118,MonthList,0)<=7,12,19-MATCH($L118,MonthList,0))/12) -> 0 | P118: No | R118: =IF(AND($P118="Yes",$G118<>"Vendor day rates"),$J118-0.4*$I118,0) -> 0 | S118: =IF(OR($P118<>"Yes",$Q118=""),0,$R118*MAX(0,7-MATCH($Q118,MonthList,0))/12) -> 0 | T118: =IF(OR($P118<>"Yes",$Q118=""),0,$R118*IF(MATCH($Q118,MonthList,0)<=7,12,19-MATCH($Q118,MonthList,0))/12) -> 0 | U118: No | W118: =IF(AND($U118="Yes",$G118<>"Vendor day rates"),$J118-0.4*$I118,0) -> 0 | X118: =IF(OR($U118<>"Yes",$V118=""),0,$W118*MAX(0,7-MATCH($V118,MonthList,0))/12) -> 0 | Y118: =IF(OR($U118<>"Yes",$V118=""),0,$W118*IF(MATCH($V118,MonthList,0)<=7,12,19-MATCH($V118,MonthList,0))/12) -> 0
B119: R0114 | C119: Technology Manager – Cloud, Networ | D119: TDD | E119: Technology Manager | F119: AU | G119: Held today | H119: 1 | I119: 0.2758 | J119: 0 | K119: No | M119: =IF(AND($K119="Yes",$G119<>"Vendor day rates"),$J119-0.4*$I119,0) -> 0 | N119: =IF(OR($K119<>"Yes",$L119=""),0,$M119*MAX(0,7-MATCH($L119,MonthList,0))/12) -> 0 | O119: =IF(OR($K119<>"Yes",$L119=""),0,$M119*IF(MATCH($L119,MonthList,0)<=7,12,19-MATCH($L119,MonthList,0))/12) -> 0 | P119: No | R119: =IF(AND($P119="Yes",$G119<>"Vendor day rates"),$J119-0.4*$I119,0) -> 0 | S119: =IF(OR($P119<>"Yes",$Q119=""),0,$R119*MAX(0,7-MATCH($Q119,MonthList,0))/12) -> 0 | T119: =IF(OR($P119<>"Yes",$Q119=""),0,$R119*IF(MATCH($Q119,MonthList,0)<=7,12,19-MATCH($Q119,MonthList,0))/12) -> 0 | U119: No | W119: =IF(AND($U119="Yes",$G119<>"Vendor day rates"),$J119-0.4*$I119,0) -> 0 | X119: =IF(OR($U119<>"Yes",$V119=""),0,$W119*MAX(0,7-MATCH($V119,MonthList,0))/12) -> 0 | Y119: =IF(OR($U119<>"Yes",$V119=""),0,$W119*IF(MATCH($V119,MonthList,0)<=7,12,19-MATCH($V119,MonthList,0))/12) -> 0
B120: R0115 | C120: Technology Manager, Store Platform | D120: Retail | E120: Technology Manager | F120: AU | G120: Filled | H120: 1 | I120: 0.2578 | J120: 0.2578 | K120: No | M120: =IF(AND($K120="Yes",$G120<>"Vendor day rates"),$J120-0.4*$I120,0) -> 0 | N120: =IF(OR($K120<>"Yes",$L120=""),0,$M120*MAX(0,7-MATCH($L120,MonthList,0))/12) -> 0 | O120: =IF(OR($K120<>"Yes",$L120=""),0,$M120*IF(MATCH($L120,MonthList,0)<=7,12,19-MATCH($L120,MonthList,0))/12) -> 0 | P120: No | R120: =IF(AND($P120="Yes",$G120<>"Vendor day rates"),$J120-0.4*$I120,0) -> 0 | S120: =IF(OR($P120<>"Yes",$Q120=""),0,$R120*MAX(0,7-MATCH($Q120,MonthList,0))/12) -> 0 | T120: =IF(OR($P120<>"Yes",$Q120=""),0,$R120*IF(MATCH($Q120,MonthList,0)<=7,12,19-MATCH($Q120,MonthList,0))/12) -> 0 | U120: No | W120: =IF(AND($U120="Yes",$G120<>"Vendor day rates"),$J120-0.4*$I120,0) -> 0 | X120: =IF(OR($U120<>"Yes",$V120=""),0,$W120*MAX(0,7-MATCH($V120,MonthList,0))/12) -> 0 | Y120: =IF(OR($U120<>"Yes",$V120=""),0,$W120*IF(MATCH($V120,MonthList,0)<=7,12,19-MATCH($V120,MonthList,0))/12) -> 0
B121: R0116 | C121: Technology Manager, Site Systems | D121: Z | E121: Technology Manager | F121: NZ | G121: Filled | H121: 1 | I121: 0.2105 | J121: 0.2105 | K121: No | M121: =IF(AND($K121="Yes",$G121<>"Vendor day rates"),$J121-0.4*$I121,0) -> 0 | N121: =IF(OR($K121<>"Yes",$L121=""),0,$M121*MAX(0,7-MATCH($L121,MonthList,0))/12) -> 0 | O121: =IF(OR($K121<>"Yes",$L121=""),0,$M121*IF(MATCH($L121,MonthList,0)<=7,12,19-MATCH($L121,MonthList,0))/12) -> 0 | P121: No | R121: =IF(AND($P121="Yes",$G121<>"Vendor day rates"),$J121-0.4*$I121,0) -> 0 | S121: =IF(OR($P121<>"Yes",$Q121=""),0,$R121*MAX(0,7-MATCH($Q121,MonthList,0))/12) -> 0 | T121: =IF(OR($P121<>"Yes",$Q121=""),0,$R121*IF(MATCH($Q121,MonthList,0)<=7,12,19-MATCH($Q121,MonthList,0))/12) -> 0 | U121: No | W121: =IF(AND($U121="Yes",$G121<>"Vendor day rates"),$J121-0.4*$I121,0) -> 0 | X121: =IF(OR($U121<>"Yes",$V121=""),0,$W121*MAX(0,7-MATCH($V121,MonthList,0))/12) -> 0 | Y121: =IF(OR($U121<>"Yes",$V121=""),0,$W121*IF(MATCH($V121,MonthList,0)<=7,12,19-MATCH($V121,MonthList,0))/12) -> 0
B122: R0117 | C122: Delivery Manager | D122: Z | E122: Delivery Manager | F122: AU | G122: Vacant, hire planned | H122: 1 | I122: 0.2029 | J122: 0.2029 | K122: No | M122: =IF(AND($K122="Yes",$G122<>"Vendor day rates"),$J122-0.4*$I122,0) -> 0 | N122: =IF(OR($K122<>"Yes",$L122=""),0,$M122*MAX(0,7-MATCH($L122,MonthList,0))/12) -> 0 | O122: =IF(OR($K122<>"Yes",$L122=""),0,$M122*IF(MATCH($L122,MonthList,0)<=7,12,19-MATCH($L122,MonthList,0))/12) -> 0 | P122: No | R122: =IF(AND($P122="Yes",$G122<>"Vendor day rates"),$J122-0.4*$I122,0) -> 0 | S122: =IF(OR($P122<>"Yes",$Q122=""),0,$R122*MAX(0,7-MATCH($Q122,MonthList,0))/12) -> 0 | T122: =IF(OR($P122<>"Yes",$Q122=""),0,$R122*IF(MATCH($Q122,MonthList,0)<=7,12,19-MATCH($Q122,MonthList,0))/12) -> 0 | U122: No | W122: =IF(AND($U122="Yes",$G122<>"Vendor day rates"),$J122-0.4*$I122,0) -> 0 | X122: =IF(OR($U122<>"Yes",$V122=""),0,$W122*MAX(0,7-MATCH($V122,MonthList,0))/12) -> 0 | Y122: =IF(OR($U122<>"Yes",$V122=""),0,$W122*IF(MATCH($V122,MonthList,0)<=7,12,19-MATCH($V122,MonthList,0))/12) -> 0
B123: R0118 | C123: Delivery Assurance Manager | D123: NA | E123: Transformation | F123: AU | G123: Vacant, hire planned | H123: 1 | I123: 0.2758 | J123: 0.2758 | K123: No | M123: =IF(AND($K123="Yes",$G123<>"Vendor day rates"),$J123-0.4*$I123,0) -> 0 | N123: =IF(OR($K123<>"Yes",$L123=""),0,$M123*MAX(0,7-MATCH($L123,MonthList,0))/12) -> 0 | O123: =IF(OR($K123<>"Yes",$L123=""),0,$M123*IF(MATCH($L123,MonthList,0)<=7,12,19-MATCH($L123,MonthList,0))/12) -> 0 | P123: No | R123: =IF(AND($P123="Yes",$G123<>"Vendor day rates"),$J123-0.4*$I123,0) -> 0 | S123: =IF(OR($P123<>"Yes",$Q123=""),0,$R123*MAX(0,7-MATCH($Q123,MonthList,0))/12) -> 0 | T123: =IF(OR($P123<>"Yes",$Q123=""),0,$R123*IF(MATCH($Q123,MonthList,0)<=7,12,19-MATCH($Q123,MonthList,0))/12) -> 0 | U123: No | W123: =IF(AND($U123="Yes",$G123<>"Vendor day rates"),$J123-0.4*$I123,0) -> 0 | X123: =IF(OR($U123<>"Yes",$V123=""),0,$W123*MAX(0,7-MATCH($V123,MonthList,0))/12) -> 0 | Y123: =IF(OR($U123<>"Yes",$V123=""),0,$W123*IF(MATCH($V123,MonthList,0)<=7,12,19-MATCH($V123,MonthList,0))/12) -> 0
B124: R0119 | C124: Portfolio Reporting Manager | D124: NA | E124: Transformation | F124: AU | G124: Filled | H124: 1 | I124: 0.2933 | J124: 0.2933 | K124: No | M124: =IF(AND($K124="Yes",$G124<>"Vendor day rates"),$J124-0.4*$I124,0) -> 0 | N124: =IF(OR($K124<>"Yes",$L124=""),0,$M124*MAX(0,7-MATCH($L124,MonthList,0))/12) -> 0 | O124: =IF(OR($K124<>"Yes",$L124=""),0,$M124*IF(MATCH($L124,MonthList,0)<=7,12,19-MATCH($L124,MonthList,0))/12) -> 0 | P124: No | R124: =IF(AND($P124="Yes",$G124<>"Vendor day rates"),$J124-0.4*$I124,0) -> 0 | S124: =IF(OR($P124<>"Yes",$Q124=""),0,$R124*MAX(0,7-MATCH($Q124,MonthList,0))/12) -> 0 | T124: =IF(OR($P124<>"Yes",$Q124=""),0,$R124*IF(MATCH($Q124,MonthList,0)<=7,12,19-MATCH($Q124,MonthList,0))/12) -> 0 | U124: No | W124: =IF(AND($U124="Yes",$G124<>"Vendor day rates"),$J124-0.4*$I124,0) -> 0 | X124: =IF(OR($U124<>"Yes",$V124=""),0,$W124*MAX(0,7-MATCH($V124,MonthList,0))/12) -> 0 | Y124: =IF(OR($U124<>"Yes",$V124=""),0,$W124*IF(MATCH($V124,MonthList,0)<=7,12,19-MATCH($V124,MonthList,0))/12) -> 0
B125: R0120 | C125: Delivery Lead | D125: Infrastructure | E125: Data & Insights | F125: AU | G125: Filled | H125: 1 | I125: 0.2778 | J125: 0.2778 | K125: No | M125: =IF(AND($K125="Yes",$G125<>"Vendor day rates"),$J125-0.4*$I125,0) -> 0 | N125: =IF(OR($K125<>"Yes",$L125=""),0,$M125*MAX(0,7-MATCH($L125,MonthList,0))/12) -> 0 | O125: =IF(OR($K125<>"Yes",$L125=""),0,$M125*IF(MATCH($L125,MonthList,0)<=7,12,19-MATCH($L125,MonthList,0))/12) -> 0 | P125: No | R125: =IF(AND($P125="Yes",$G125<>"Vendor day rates"),$J125-0.4*$I125,0) -> 0 | S125: =IF(OR($P125<>"Yes",$Q125=""),0,$R125*MAX(0,7-MATCH($Q125,MonthList,0))/12) -> 0 | T125: =IF(OR($P125<>"Yes",$Q125=""),0,$R125*IF(MATCH($Q125,MonthList,0)<=7,12,19-MATCH($Q125,MonthList,0))/12) -> 0 | U125: No | W125: =IF(AND($U125="Yes",$G125<>"Vendor day rates"),$J125-0.4*$I125,0) -> 0 | X125: =IF(OR($U125<>"Yes",$V125=""),0,$W125*MAX(0,7-MATCH($V125,MonthList,0))/12) -> 0 | Y125: =IF(OR($U125<>"Yes",$V125=""),0,$W125*IF(MATCH($V125,MonthList,0)<=7,12,19-MATCH($V125,MonthList,0))/12) -> 0
B126: R0121 | C126: Program Manager POS | D126: Retail | E126: AmPOS | F126: NZ | G126: Filled | H126: 1 | I126: 0.202 | J126: 0.202 | K126: No | M126: =IF(AND($K126="Yes",$G126<>"Vendor day rates"),$J126-0.4*$I126,0) -> 0 | N126: =IF(OR($K126<>"Yes",$L126=""),0,$M126*MAX(0,7-MATCH($L126,MonthList,0))/12) -> 0 | O126: =IF(OR($K126<>"Yes",$L126=""),0,$M126*IF(MATCH($L126,MonthList,0)<=7,12,19-MATCH($L126,MonthList,0))/12) -> 0 | P126: No | R126: =IF(AND($P126="Yes",$G126<>"Vendor day rates"),$J126-0.4*$I126,0) -> 0 | S126: =IF(OR($P126<>"Yes",$Q126=""),0,$R126*MAX(0,7-MATCH($Q126,MonthList,0))/12) -> 0 | T126: =IF(OR($P126<>"Yes",$Q126=""),0,$R126*IF(MATCH($Q126,MonthList,0)<=7,12,19-MATCH($Q126,MonthList,0))/12) -> 0 | U126: No | W126: =IF(AND($U126="Yes",$G126<>"Vendor day rates"),$J126-0.4*$I126,0) -> 0 | X126: =IF(OR($U126<>"Yes",$V126=""),0,$W126*MAX(0,7-MATCH($V126,MonthList,0))/12) -> 0 | Y126: =IF(OR($U126<>"Yes",$V126=""),0,$W126*IF(MATCH($V126,MonthList,0)<=7,12,19-MATCH($V126,MonthList,0))/12) -> 0
B127: R0122 | C127: Technology Manager – P&C Platforms | D127: P&C | E127: Technology Manager | F127: AU | G127: Filled | H127: 1 | I127: 0.2964 | J127: 0.2964 | K127: No | M127: =IF(AND($K127="Yes",$G127<>"Vendor day rates"),$J127-0.4*$I127,0) -> 0 | N127: =IF(OR($K127<>"Yes",$L127=""),0,$M127*MAX(0,7-MATCH($L127,MonthList,0))/12) -> 0 | O127: =IF(OR($K127<>"Yes",$L127=""),0,$M127*IF(MATCH($L127,MonthList,0)<=7,12,19-MATCH($L127,MonthList,0))/12) -> 0 | P127: No | R127: =IF(AND($P127="Yes",$G127<>"Vendor day rates"),$J127-0.4*$I127,0) -> 0 | S127: =IF(OR($P127<>"Yes",$Q127=""),0,$R127*MAX(0,7-MATCH($Q127,MonthList,0))/12) -> 0 | T127: =IF(OR($P127<>"Yes",$Q127=""),0,$R127*IF(MATCH($Q127,MonthList,0)<=7,12,19-MATCH($Q127,MonthList,0))/12) -> 0 | U127: No | W127: =IF(AND($U127="Yes",$G127<>"Vendor day rates"),$J127-0.4*$I127,0) -> 0 | X127: =IF(OR($U127<>"Yes",$V127=""),0,$W127*MAX(0,7-MATCH($V127,MonthList,0))/12) -> 0 | Y127: =IF(OR($U127<>"Yes",$V127=""),0,$W127*IF(MATCH($V127,MonthList,0)<=7,12,19-MATCH($V127,MonthList,0))/12) -> 0
B128: R0123 | C128: Technology Manger - Finance Platfo | D128: Finance | E128: Technology Manager | F128: AU | G128: Filled | H128: 1 | I128: 0.3236 | J128: 0.3236 | K128: No | M128: =IF(AND($K128="Yes",$G128<>"Vendor day rates"),$J128-0.4*$I128,0) -> 0 | N128: =IF(OR($K128<>"Yes",$L128=""),0,$M128*MAX(0,7-MATCH($L128,MonthList,0))/12) -> 0 | O128: =IF(OR($K128<>"Yes",$L128=""),0,$M128*IF(MATCH($L128,MonthList,0)<=7,12,19-MATCH($L128,MonthList,0))/12) -> 0 | P128: No | R128: =IF(AND($P128="Yes",$G128<>"Vendor day rates"),$J128-0.4*$I128,0) -> 0 | S128: =IF(OR($P128<>"Yes",$Q128=""),0,$R128*MAX(0,7-MATCH($Q128,MonthList,0))/12) -> 0 | T128: =IF(OR($P128<>"Yes",$Q128=""),0,$R128*IF(MATCH($Q128,MonthList,0)<=7,12,19-MATCH($Q128,MonthList,0))/12) -> 0 | U128: No | W128: =IF(AND($U128="Yes",$G128<>"Vendor day rates"),$J128-0.4*$I128,0) -> 0 | X128: =IF(OR($U128<>"Yes",$V128=""),0,$W128*MAX(0,7-MATCH($V128,MonthList,0))/12) -> 0 | Y128: =IF(OR($U128<>"Yes",$V128=""),0,$W128*IF(MATCH($V128,MonthList,0)<=7,12,19-MATCH($V128,MonthList,0))/12) -> 0
... B202: R0197 | C202: Manager, Customer Support Operatio | D202: NA | E202: Service Op & Assurance | F202: AU | G202: Filled | H202: 1 | I202: 0.2433 | J202: 0.2433 | K202: No | M202: =IF(AND($K202="Yes",$G202<>"Vendor day rates"),$J202-0.4*$I202,0) -> 0 | N202: =IF(OR($K202<>"Yes",$L202=""),0,$M202*MAX(0,7-MATCH($L202,MonthList,0))/12) -> 0 | O202: =IF(OR($K202<>"Yes",$L202=""),0,$M202*IF(MATCH($L202,MonthList,0)<=7,12,19-MATCH($L202,MonthList,0))/12) -> 0 | P202: No | R202: =IF(AND($P202="Yes",$G202<>"Vendor day rates"),$J202-0.4*$I202,0) -> 0 | S202: =IF(OR($P202<>"Yes",$Q202=""),0,$R202*MAX(0,7-MATCH($Q202,MonthList,0))/12) -> 0 | T202: =IF(OR($P202<>"Yes",$Q202=""),0,$R202*IF(MATCH($Q202,MonthList,0)<=7,12,19-MATCH($Q202,MonthList,0))/12) -> 0 | U202: No | W202: =IF(AND($U202="Yes",$G202<>"Vendor day rates"),$J202-0.4*$I202,0) -> 0 | X202: =IF(OR($U202<>"Yes",$V202=""),0,$W202*MAX(0,7-MATCH($V202,MonthList,0))/12) -> 0 | Y202: =IF(OR($U202<>"Yes",$V202=""),0,$W202*IF(MATCH($V202,MonthList,0)<=7,12,19-MATCH($V202,MonthList,0))/12) -> 0
...

Sheet REVIEW - Complete Role Mapping
A1: EE Number | B1: Name | C1: EE Number | D1: Position Title | E1: Reports to name | F1: Reports to Position | G1: Division (GM) | H1: Department (GM-1) | I1: Team (GM-2) | J1: Portfolio | K1: Platform | L1: Squad | M1: CC | N1: Country | O1: Job Level | P1: FTE | Q1: Vacant Column | R1: Type | S1: Unit | T1: day rate | U1: FTE Base Local | V1: FTE Base AUD | W1: STI | X1: Payroll | Y1: Pensions | Z1: medical | AA1: CPI | AB1: Full Cost AUD | AC1: MyHR ee no | AE1: Effective cost (AUD) | AF1: MStatus | AG1: Ring fenced | AH1: MTab | AI1: Leadership | AJ1: Squad (canonical, from col L) | AK1: Overhead line | AL1: Squad or overhead line | AM1: EGI funded | AN1: Status (PCM) | AO1: Commentry (PCM) | AP1: End date (PCM) | AQ1: Role ID | AR1: Country side (AU or NZ)
A2: C | B2: Alan Peng | C2: C | D2: Delivery Lead | E2: Adriel Jeyanandhan | F2: Delivery Manager, Digital | G2: Customer | H2: Digital | I2: Digital, Delivery | J2: EGI Integration | K2: EGI | L2: EGI Customer | N2: Australia | O2: NA | P2: 1 | R2: Contractor | S2: Day | T2: 1190 | AB2: 264180 | AC2: End Date: 28/08/2026 | AE2: 264180 | AF2: Filled | AG2: 0 | AH2: Customer | AI2: 0 | AJ2: EGI Customer | AK2: Squad | AL2: EGI Customer | AM2: 1 | AN2: Filled | AO2: End Date: 28/08/2026 | AP2: 46262 | AQ2: R0001 | AR2: AU
A3: C | B3: Lily Fong | C3: C | D3: Snr Business Analyst | E3: Adriel Jeyanandhan | F3: Delivery Manager, Digital | G3: Customer | H3: Digital | I3: Digital, Delivery | J3: Ampol Customer | K3: Ampol Digital | L3: Ampol Web | N3: Australia | O3: NA | P3: 1 | R3: Contractor (CXC) | S3: Day | T3: 1229.2 | AB3: 272882.4 | AC3: End Date: 8/08/2026 | AE3: 272882.4 | AF3: Filled | AG3: 0 | AH3: Customer | AI3: 0 | AJ3: Ampol Web | AK3: Squad | AL3: Ampol Web | AM3: 0 | AN3: Filled | AO3: End Date: 8/08/2026 | AP3: 46242 | AQ3: R0002 | AR3: AU
A4: C | B4: Peter (Won) Lee | C4: C | D4: Snr Business Analyst | E4: Adriel Jeyanandhan | F4: Delivery Manager, Digital | G4: Customer | H4: Digital | I4: Digital, Delivery | J4: Ampol Customer | K4: Ampol Digital | L4: Ampol App | N4: Australia | O4: NA | P4: 1 | R4: Contractor | S4: Day | T4: 1167 | AB4: 259074 | AC4: End Date: 2/01/2027 | AE4: 259074 | AF4: Filled | AG4: 0 | AH4: Customer | AI4: 0 | AJ4: Ampol App | AK4: Squad | AL4: Ampol App | AM4: 0 | AN4: Filled | AO4: End Date: 2/01/2027 | AP4: 46389 | AQ4: R0003 | AR4: AU
A5: C | B5: Harish Dasari | C5: C | D5: Business Analyst (SAP Payroll) | E5: Areum Kim-Lee | F5: GM TDD, EGI | G5: EGI | H5: EGI | I5: EGI | J5: EGI | K5: EGI | L5: EGI | N5: Australia | O5: na | P5: 1 | R5: cxc | S5: daily | T5: 1100 | U5: 0 | AB5: 244200 | AE5: 244200 | AF5: Filled | AG5: 0 | AH5: EGI | AI5: 0 | AJ5: EGI | AK5: Squad | AL5: EGI | AM5: 1 | AQ5: R0004 | AR5: AU
A6: C | B6: Niall Greene | C6: C | D6: Project Manager (PEP13-EGI-UKG) | E6: Areum Kim-Lee | F6: GM TDD, EGI | G6: EGI | H6: EGI | I6: EGI | J6: EGI | K6: EGI | L6: EGI | N6: Australia | O6: NA | P6: 1 | R6: cxc | S6: Daily | T6: 1100 | U6: 0 | AB6: 244200 | AE6: 244200 | AF6: Filled | AG6: 0 | AH6: EGI | AI6: 0 | AJ6: EGI | AK6: Squad | AL6: EGI | AM6: 1 | AQ6: R0005 | AR6: AU
A7: c | B7: Paul Hassey | C7: c | D7: Program Architect | E7: Ed Tacey | G7: EGI | H7: EGI | I7: EGI | J7: EGI | K7: EGI | L7: EGI | N7: Australia | O7: na | P7: 1 | R7: cxc | S7: Daily | T7: 1400 | U7: 0 | AB7: 310800 | AE7: 310800 | AF7: Filled | AG7: 0 | AH7: EGI | AI7: 0 | AJ7: EGI | AK7: Squad | AL7: EGI | AM7: 1 | AQ7: R0006 | AR7: AU
A8: C | B8: Ahmed Yehya | C8: C | D8: TDD Strategic Delivery | E8: Greg Cassis | F8: GM TDD, EGI | G8: EGI | H8: EGI | I8: EGI | J8: EGI | K8: EGI | L8: EGI | N8: Australia | O8: na | P8: 1 | R8: cxc | S8: Daily | T8: 1250 | U8: 0 | AB8: 277500 | AE8: 277500 | AF8: Filled | AG8: 0 | AH8: EGI | AI8: 0 | AJ8: EGI | AK8: Squad | AL8: EGI | AM8: 1 | AQ8: R0007 | AR8: AU
A9: C | B9: Anthony Huynh | C9: C | D9: Strategic Delivery Consultant | E9: Greg Cassis | F9: GM TDD, EGI | G9: EGI | H9: EGI | I9: EGI | J9: EGI | K9: EGI | L9: EGI | N9: australia | O9: NA | P9: 1 | R9: cxc | S9: daily | T9: 1357 | U9: 0 | AB9: 301254 | AE9: 301254 | AF9: Filled | AG9: 0 | AH9: EGI | AI9: 0 | AJ9: EGI | AK9: Squad | AL9: EGI | AM9: 1 | AQ9: R0008 | AR9: AU
A10: C | B10: Areum Kim Lee | C10: C | D10: Program Manager (PEP13-EGI-UKG) | E10: Greg Cassis | F10: GM TDD, EGI | G10: EGI | H10: EGI | I10: EGI | J10: EGI | K10: EGI | L10: EGI | N10: Australia | O10: NA | P10: 1 | R10: cxc | S10: Daily | T10: 1545.76 | U10: 0 | AB10: 343158.72 | AE10: 343158.72 | AF10: Filled | AG10: 0 | AH10: EGI | AI10: 0 | AJ10: EGI | AK10: Squad | AL10: EGI | AM10: 1 | AQ10: R0009 | AR10: AU
A11: C | B11: James Munt | C11: C | D11: Program Manager Tech & P&C | E11: Greg Cassis | F11: GM TDD, EGI | G11: EGI | H11: EGI | I11: EGI | J11: EGI | K11: EGI | L11: EGI | N11: Australia | O11: na | P11: 1 | R11: cxc | S11: daily | T11: 1200 | U11: 0 | AB11: 266400 | AE11: 266400 | AF11: Filled | AG11: 0 | AH11: EGI | AI11: 0 | AJ11: EGI | AK11: Squad | AL11: EGI | AM11: 1 | AQ11: R0010 | AR11: AU
A12: c | B12: Jason McNamara | C12: c | D12: Project Manager Retail | E12: Greg Cassis | F12: GM TDD, EGI | G12: EGI | H12: EGI | I12: EGI | J12: EGI | K12: EGI | L12: EGI | N12: Australia | O12: na | P12: 1 | R12: cxc | S12: daily | T12: 2200 | U12: 0 | AB12: 488400 | AE12: 488400 | AF12: Filled | AG12: 0 | AH12: EGI | AI12: 0 | AJ12: EGI | AK12: Squad | AL12: EGI | AM12: 1 | AQ12: R0011 | AR12: AU
A13: c | B13: Karl Reyneke | C13: c | D13: Strategic Delivery Consultant | E13: Greg Cassis | F13: GM TDD, EGI | G13: EGI | H13: EGI | I13: EGI | J13: EGI | K13: EGI | L13: EGI | N13: australia | O13: na | P13: 1 | R13: cxc | S13: daily | T13: 1350 | U13: 0 | AB13: 299700 | AE13: 299700 | AF13: Filled | AG13: 0 | AH13: EGI | AI13: 0 | AJ13: EGI | AK13: Squad | AL13: EGI | AM13: 1 | AQ13: R0012 | AR13: AU
A14: c | B14: michelle Siegman | C14: c | D14: Strategic Delivery Consultant | E14: Greg Cassis | F14: GM TDD, EGI | G14: EGI | H14: EGI | I14: EGI | J14: EGI | K14: EGI | L14: EGI | N14: Australia | O14: na | P14: 1 | R14: cxc | S14: Daily | T14: 1038 | U14: 0 | AB14: 230436 | AE14: 230436 | AF14: Filled | AG14: 0 | AH14: EGI | AI14: 0 | AJ14: EGI | AK14: Squad | AL14: EGI | AM14: 1 | AQ14: R0013 | AR14: AU
A15: c | B15: vijay Solanki | C15: c | D15: Project Manager Deployment | E15: greg Cassis | G15: EGI | K15: EGI | L15: EGI | N15: Australia | O15: na | P15: 1 | R15: cxc | S15: Daily | T15: 1200 | U15: 0 | AB15: 266400 | AE15: 266400 | AF15: Filled | AG15: 0 | AH15: EGI | AI15: 0 | AJ15: EGI | AK15: Squad | AL15: EGI | AM15: 1 | AQ15: R0014 | AR15: AU
A16: C | B16: Simrat Singh | C16: C | D16: Reporting Analyst | E16: Jaya Ganasan | F16: Technology Manager, TDD Refinery | G16: TDD CFE&I | H16: Fuel Infrastructure | I16: Refinery Applications | J16: Infrastructure | K16: Data & Insights | L16: Data & Insights | N16: Australia | O16: NA | P16: 1 | R16: cxc | S16: Daily | T16: 890 | U16: 0 | AB16: 197580 | AE16: 197580 | AF16: Filled | AG16: 0 | AH16: Infrastructure | AI16: 0 | AJ16: Data & Insights | AK16: Squad | AL16: Data & Insights | AM16: 0 | AQ16: R0015 | AR16: AU
A17: W- Vacant | B17: Vacant | C17: W- Vacant | D17: QA / Tester / Mid | E17: Jill Martin | F17: Delivery Manager, Loyalty | G17: Customer | H17: Loyalty & Martech | I17: Loyalty, Delivery | J17: Ampol Customer | K17: Ampol Loyalty & Martech | L17: Ampol Loyalty & Martech | N17: WIPRO | O17: NA | P17: 1 | R17: WIPRO - vacant | S17: 222 | T17: 330 | AB17: 73260 | AE17: 73260 | AF17: Vacant | AG17: 0 | AH17: Customer | AI17: 0 | AJ17: Ampol Loyalty & Martech | AK17: Squad | AL17: Ampol Loyalty & Martech | AM17: 0 | AN17: Wipro | AQ17: R0016 | AR17: AU
A18: W- Vacant | B18: Vacant | C18: W- Vacant | D18: Systems Analyst / Mid | E18: Jill Martin | F18: Delivery Manager, Loyalty | G18: Customer | H18: Loyalty & Martech | I18: Loyalty, Delivery | J18: Ampol Customer | K18: Ampol Loyalty & Martech | L18: Ampol Loyalty & Martech | N18: WIPRO | O18: NA | P18: 1 | R18: WIPRO - vacant | S18: 222 | T18: 330 | AB18: 73260 | AE18: 73260 | AF18: Vacant | AG18: 0 | AH18: Customer | AI18: 0 | AJ18: Ampol Loyalty & Martech | AK18: Squad | AL18: Ampol Loyalty & Martech | AM18: 0 | AN18: Wipro | AQ18: R0017 | AR18: AU
A19: C | B19: Viren Khatri | C19: C | D19: Data Migration Lead | E19: Manjot Kaur | F19: Technology Manager, Data | G19: Ampol Retail & Z | H19: Z & Group Retail | I19: Z & Group Retail, Data | J19: EGI Integration | K19: EGI | L19: EGI TDD | N19: Australia | O19: NA | P19: 1 | R19: cxc | S19: Daily | T19: 1350 | U19: 0 | AB19: 299700 | AE19: 299700 | AF19: Filled | AG19: 0 | AH19: TDD Group Functions | AI19: 0 | AJ19: EGI TDD | AK19: Squad | AL19: EGI TDD | AM19: 1 | AQ19: R0018 | AR19: AU
A20: W-106200 | B20: Emile Violi - QA Wipro | C20: W-106200 | D20: .NET Back End Developer / Mid | E20: Mark Wilson | F20: Digital Support Manager(AU) | G20: Customer | H20: Digital | I20: Digital Support (AU) | J20: Ampol Customer | K20: Ampol Digital | L20: Digital Operations | N20: WIPRO | O20: NA | P20: 1 | R20: WIPRO - filled | S20: 222 | T20: 330 | AB20: 73260 | AE20: 73260 | AF20: Filled | AG20: 0 | AH20: Customer | AI20: 0 | AJ20: Digital Operations | AK20: Squad | AL20: Digital Operations | AM20: 0 | AN20: Filled | AQ20: R0019 | AR20: AU
A21: W- Vacant | B21: Vacant | C21: W- Vacant | D21: .NET Back End Developer / Mid | E21: Mark Wilson | F21: Digital Support Manager(AU) | G21: Customer | H21: Digital | I21: Digital Support (AU) | J21: Ampol Customer | K21: Ampol Digital | L21: Digital Operations | N21: WIPRO | O21: NA | P21: 1 | R21: WIPRO - vacant | S21: 222 | T21: 330 | AB21: 73260 | AE21: 73260 | AF21: Vacant | AG21: 0 | AH21: Customer | AI21: 0 | AJ21: Digital Operations | AK21: Squad | AL21: Digital Operations | AM21: 0 | AN21: Wipro | AQ21: R0020 | AR21: AU
A22: W- Vacant | B22: Vacant | C22: W- Vacant | D22: .NET Back End Developer / Mid | E22: Mark Wilson | F22: Digital Support Manager(AU) | G22: Customer | H22: Digital | I22: Digital Support (AU) | J22: Ampol Customer | K22: Ampol Digital | L22: Digital Operations | N22: WIPRO | O22: NA | P22: 1 | R22: WIPRO - vacant | S22: 222 | T22: 330 | AB22: 73260 | AE22: 73260 | AF22: Vacant | AG22: 0 | AH22: Customer | AI22: 0 | AJ22: Digital Operations | AK22: Squad | AL22: Digital Operations | AM22: 0 | AN22: Wipro | AQ22: R0021 | AR22: AU
A23: W- Vacant | B23: Vacant | C23: W- Vacant | D23: QA / Tester / Mid | E23: Mark Wilson | F23: Digital Support Manager(AU) | G23: Customer | H23: Digital | I23: Digital Support (AU) | J23: Ampol Customer | K23: Ampol Digital | L23: Digital Operations | N23: WIPRO | O23: NA | P23: 1 | R23: WIPRO - vacant | S23: 222 | T23: 330 | AB23: 73260 | AE23: 73260 | AF23: Vacant | AG23: 0 | AH23: Customer | AI23: 0 | AJ23: Digital Operations | AK23: Squad | AL23: Digital Operations | AM23: 0 | AN23: Wipro | AQ23: R0022 | AR23: AU
A24: C | B24: Arun Tahlan | C24: C | D24: Integration Architect (C) - Boomi | E24: Mike Seales | F24: Technology Manager Integration & Process Managemetn | G24: TDD Group Functions | H24: TDD & Engineering | I24: Integration & Process Management | J24: EGI | K24: EGI | L24: EGI TDD | N24: Australia | O24: NA | P24: 1 | R24: cxc | S24: Daily | T24: 1568 | U24: 0 | AB24: 348096 | AE24: 348096 | AF24: Filled | AG24: 0 | AH24: TDD Group Functions | AI24: 0 | AJ24: EGI TDD | AK24: Squad | AL24: EGI TDD | AM24: 1 | AQ24: R0023 | AR24: AU
A25: C | B25: Kris Thornley | C25: C | D25: Integration Architect (C) | E25: Mike Seales | F25: Technology Manager Integration & Process Managemetn | G25: TDD Group Functions | H25: TDD & Engineering | I25: Integration & Process Management | J25: EGI | K25: EGI | L25: EGI TDD | N25: NZ | O25: NA | P25: 1 | R25: Contractor | S25: cant find this person | T25: 1200 | U25: 0 | AB25: 266400 | AE25: 266400 | AF25: Filled | AG25: 0 | AH25: TDD Group Functions | AI25: 0 | AJ25: EGI TDD | AK25: Squad | AL25: EGI TDD | AM25: 1 | AQ25: R0024 | AR25: NZ
A26: C | B26: Annabel Phu | C26: C | D26: Engineer - Mobile | E26: Mitesh Shah | F26: Technology Manager, Digitial | G26: Customer | H26: Digital | I26: Digital, Tech | J26: Ampol Customer | K26: Ampol Digital | L26: Ampol App | N26: Australia | O26: NA | P26: 1 | R26: Contractor | S26: Day | T26: 860 | AB26: 190920 | AC26: Jac: Don’t know end Date | AE26: 190920 | AF26: Filled | AG26: 0 | AH26: Customer | AI26: 0 | AJ26: Ampol App | AK26: Squad | AL26: Ampol App | AM26: 0 | AN26: Filled | AO26: Jac: Don’t know end Date | AQ26: R0025 | AR26: AU
A27: C | B27: Jordan Askwith | C27: C | D27: Solution Architect | E27: Mitesh Shah | F27: Technology Manager, Digitial | G27: Customer | H27: Digital | I27: Digital, Tech | J27: Ampol Customer | K27: Ampol Digital | L27: Ampol Web | N27: Australia | O27: NA | P27: 1 | R27: Contractor (Digizoo) | S27: Day | T27: 1450 | AB27: 321900 | AC27: Jac: Don’t know end date | AE27: 321900 | AF27: Filled | AG27: 0 | AH27: Customer | AI27: 0 | AJ27: Ampol Web | AK27: Squad | AL27: Ampol Web | AM27: 0 | AN27: Filled | AO27: Jac: Don’t know end date | AQ27: R0026 | AR27: AU
A28: c | B28: Kanika Narula | C28: c | D28: Business Analyst Digital | E28: Mitesh Shah | F28: Technology Manager, Digitial | G28: EGI | H28: EGI | I28: EGI | J28: EGI | K28: EGI | L28: EGI | N28: Australia | O28: na | P28: 1 | R28: cxc | S28: daily | T28: 1078.84 | U28: 0 | AB28: 239502.48 | AE28: 239502.48 | AF28: Filled | AG28: 0 | AH28: EGI | AI28: 0 | AJ28: EGI | AK28: Squad | AL28: EGI | AM28: 1 | AQ28: R0027 | AR28: AU
A29: C | B29: Phillip Kewley | C29: C | D29: Quality Assurance | E29: Mitesh Shah | F29: Technology Manager, Digitial | G29: Customer | H29: Digital | I29: Digital, Tech | J29: Ampol Customer | K29: Ampol Digital | L29: Ampol App | N29: Australia | O29: NA | P29: 1 | R29: Contractor | S29: Day | T29: 807.2 | AB29: 179198.4 | AC29: End Date: 30/10/26 | AE29: 179198.4 | AF29: Filled | AG29: 0 | AH29: Customer | AI29: 0 | AJ29: Ampol App | AK29: Squad | AL29: Ampol App | AM29: 0 | AN29: Filled | AO29: End Date: 30/10/26 | AP29: 46326 | AQ29: R0028 | AR29: AU
A30: C | B30: Sheetal Karkera | C30: C | D30: Lead Engineer - Mobile | E30: Mitesh Shah | F30: Technology Manager, Digitial | G30: Customer | H30: Digital | I30: Digital, Tech | J30: Ampol Customer | K30: Ampol Digital | L30: Ampol App | N30: Australia | O30: NA | P30: 1 | R30: Contractor | S30: Day | T30: 1253 | AB30: 278166 | AC30: End Date: 21/08/2026 | AE30: 278166 | AF30: Filled | AG30: 0 | AH30: Customer | AI30: 0 | AJ30: Ampol App | AK30: Squad | AL30: Ampol App | AM30: 0 | AN30: Filled | AO30: End Date: 21/08/2026 | AP30: 46255 | AQ30: R0029 | AR30: AU
A31: =#N/A -> #N/A | B31: Shreema Das | C31: =#N/A -> #N/A | D31: Solution Architect | E31: Mitesh Shah | F31: Technology Manager, Digitial | G31: Customer | H31: Digital | I31: Digital, Tech | J31: Ampol Customer | K31: Ampol Digital | L31: Ampol Web | N31: Australia | O31: NA | P31: 1 | R31: Permanent - Part Time | U31: 190000 | V31: 190000 | W31: 0.12 | X31: 0.055 | Y31: 0.12 | AA31: 0.04 | AB31: 243090.15 | AC31: Joins Perm in August | AE31: 243090.15 | AF31: Filled | AG31: 0 | AH31: Customer | AI31: 0 | AJ31: Ampol Web | AK31: Squad | AL31: Ampol Web | AM31: 0 | AN31: Filled | AO31: Joins Perm in August NOTE: Shreema Das is in the Ampol Web Squad | AQ31: R0030 | AR31: AU
A32: C | B32: Waheed Malek | C32: C | D32: Quality Assurance | E32: Mitesh Shah | F32: Technology Manager, Digitial | G32: Customer | H32: Digital | I32: Digital, Tech | J32: EGI Integration | K32: EGI | L32: EGI Customer | N32: Australia | O32: NA | P32: 1 | R32: Contractor | S32: Daily | T32: 1215 | AB32: 269730 | AC32: End Date: 21/09/2026 | AE32: 269730 | AF32: Filled | AG32: 0 | AH32: Customer | AI32: 0 | AJ32: EGI Customer | AK32: Squad | AL32: EGI Customer | AM32: 1 | AN32: Filled | AO32: End Date: 21/09/2026 | AP32: 46286 | AQ32: R0031 | AR32: AU
A33: C | B33: Winnie Fernandes | C33: C | D33: Delivery Lead - Integration | E33: Moitri Pal | F33: Program Manager - EGI | G33: EGI | H33: EGI | I33: EGI | J33: EGI | K33: EGI | L33: EGI | N33: Australia | O33: NA | P33: 1 | R33: cxc | S33: Daily | T33: 1232 | U33: 0 | AB33: 273504 | AE33: 273504 | AF33: Filled | AG33: 0 | AH33: EGI | AI33: 0 | AJ33: EGI | AK33: Squad | AL33: EGI | AM33: 1 | AQ33: R0032 | AR33: AU
A34: c | B34: Jens Tom | C34: c | D34: SAP Solution Architect | E34: Shane Ker | F34: Solution Architect SAP | G34: TDD Group Functions | O34: na | P34: 1 | R34: cxc | S34: daily | T34: 1600 | U34: 0 | AB34: 355200 | AE34: 355200 | AF34: Filled | AG34: 0 | AH34: TDD Group Functions | AI34: 0 | AJ34: SAP ERP | AK34: Squad | AL34: SAP ERP | AM34: 0 | AO34: NOT IN MY ORG CHART | AQ34: R0033 | AR34: AU
A35: C | B35: Ernesto Pereira | C35: C | D35: Project Manger | E35: Trena Foote | F35: Project Manger | G35: EGI | H35: EGI | I35: EGI | J35: EGI | K35: EGI | L35: EGI | N35: Australia | O35: na | P35: 1 | R35: cxc | S35: daily | T35: 1000 | U35: 0 | AB35: 222000 | AE35: 222000 | AF35: Filled | AG35: 0 | AH35: EGI | AI35: 0 | AJ35: EGI | AK35: Squad | AL35: EGI | AM35: 1 | AQ35: R0034 | AR35: AU
A36: c | B36: Jason Sipkovic | C36: c | D36: strategic program architect | E36: Trena Foote | F36: Project Manger | G36: EGI | H36: EGI | I36: EGI | J36: EGI | K36: EGI | L36: EGI | N36: Australia | O36: na | P36: 1 | R36: cxc | S36: daily | T36: 1500 | U36: 0 | AB36: 333000 | AE36: 333000 | AF36: Filled | AG36: 0 | AH36: EGI | AI36: 0 | AJ36: EGI | AK36: Squad | AL36: EGI | AM36: 1 | AQ36: R0035 | AR36: AU
A37: C | B37: Aaron (Ming) Lu | C37: C | D37: Engineer - BE | E37: Vacant | F37: Technology Manager, Digital Engineering | G37: Customer | H37: Digital | I37: Tech, Digital Engineering | J37: Ampol Customer | K37: Ampol Digital | L37: Ampol Web | N37: Australia | O37: NA | P37: 1 | R37: Contractor | S37: Day | T37: 1250 | AB37: 277500 | AC37: End date:10/07/2026 | AE37: 277500 | AF37: Filled | AG37: 0 | AH37: Customer | AI37: 0 | AJ37: Ampol Web | AK37: Squad | AL37: Ampol Web | AM37: 0 | AN37: Filled | AO37: End date:10/07/2026 | AP37: 46213 | AQ37: R0036 | AR37: AU
A38: C | B38: Anup Antony | C38: C | D38: Engineer - BE | E38: Vacant | F38: Technology Manager, Digital Engineering | G38: Customer | H38: Digital | I38: Tech, Digital Engineering | J38: Ampol Customer | K38: Ampol Digital | L38: Ampol App | N38: Australia | O38: NA | P38: 1 | R38: Contractor | S38: Day | T38: 1218.5777 | AB38: 270524.25 | AC38: End Date: 31/01/2027 | AE38: 270524.25 | AF38: Filled | AG38: 0 | AH38: Customer | AI38: 0 | AJ38: Ampol App | AK38: Squad | AL38: Ampol App | AM38: 0 | AN38: Filled | AO38: End Date: 31/01/2027 | AP38: 46418 | AQ38: R0037 | AR38: AU
B39: Rob Jadrjevic | D39: Engineer - BE | E39: Vacant | F39: Technology Manager, Digital Engineering | G39: Customer | H39: Digital | I39: Tech, Digital Engineering | J39: EGI Integration | K39: EGI | L39: EGI Customer | N39: Australia | O39: NA | P39: 1 | AB39: 0 | AC39: Jac: Cant find tthis record | AE39: 0 | AF39: Filled | AG39: 0 | AH39: Customer | AI39: 0 | AJ39: EGI Customer | AK39: Squad | AL39: EGI Customer | AM39: 1 | AN39: Filled | AO39: Jac: Cant find tthis record | AQ39: R0038 | AR39: AU
A40: C | B40: Swapnil Pithwa | C40: C | D40: Engineer - BE | E40: Vacant | F40: Technology Manager, Digital Engineering | G40: Customer | H40: Digital | I40: Tech, Digital Engineering | J40: EGI Integration | K40: EGI | L40: EGI Customer | N40: Australia | O40: NA | P40: 1 | R40: Contractor | S40: Day | T40: 1190 | AB40: 264180 | AC40: End Date: 20/08/2026 | AE40: 264180 | AF40: Filled | AG40: 0 | AH40: Customer | AI40: 0 | AJ40: EGI Customer | AK40: Squad | AL40: EGI Customer | AM40: 1 | AN40: Filled | AO40: End Date: 20/08/2026 | AP40: 46254 | AQ40: R0039 | AR40: AU
A41: C | B41: Alex Prakhiy | C41: C | D41: Business Analyst | E41: Vanessa Allen | F41: Delivery Manager, Ampol Retail | G41: Ampol Retail & Z | H41: Ampol Retail | I41: Ampol Retail, Delivery | J41: EGI Integration | K41: EGI | L41: EGI Retail | N41: Australia | O41: NA | P41: 1 | R41: cxc | S41: Daily | T41: 1000 | U41: 0 | AB41: 222000 | AE41: 222000 | AF41: Filled | AG41: 0 | AH41: Ampol Retail | AI41: 0 | AJ41: EGI Retail | AK41: Squad | AL41: EGI Retail | AM41: 1 | AQ41: R0040 | AR41: AU
A42: C | B42: Ashish Gupte | C42: C | D42: DeveloperSAP ECC | E42: Vasso Vucovic | F42: Head of Technology Finance, P&C Legal | G42: TDD Group Functions | H42: EGI | I42: EGI | J42: EGI | K42: EGI | L42: EGI | N42: australia | O42: na | P42: 1 | R42: cxc | S42: Daily | T42: 1250 | U42: 0 | AB42: 277500 | AE42: 277500 | AF42: Filled | AG42: 0 | AH42: EGI | AI42: 0 | AJ42: EGI | AK42: Squad | AL42: EGI | AM42: 1 | AQ42: R0041 | AR42: AU
A43: V | B43: Vacant | C43: V | D43: Commercial Director | E43: Michael Schofield | F43: GM TDD, Partnering & Transformation | G43: Partnering & Transformation | H43: Commercial | I43: NA | J43: NA | K43: NA | L43: NA | N43: Australia | O43: LSB | P43: 1 | R43: v | U43: 300000 | V43: 300000 | W43: 0.25 | X43: 0.055 | Y43: 0.12 | AA43: 0.04 | AB43: 439500 | AE43: 439500 | AF43: Vacant | AG43: 0 | AH43: COE BP&T | AI43: 0 | AJ43: Commercial | AK43: Squad | AL43: Commercial | AM43: 0 | AQ43: R0042 | AR43: AU
A44: 115527 | B44: Andy Stewart | C44: 115527 | D44: Head of Technology, Loyalty & Martech | E44: Harley Giles | F44: GM TDD, Customer | G44: Customer | H44: Loyalty & Martech | J44: Z ENERGY (DIGITAL) | K44: Portfolio Leadership | L44: Heads of Customer Portfolio | N44: NZ | O44: CSC (Always) | P44: 1 | R44: Permanent - Full Time | U44: 253260 | V44: 232999.2 | W44: 0.2 | Y44: 0.05 | Z44: 2910 | AA44: 0.03 | AB44: 301148.98 | AE44: 301148.98 | AF44: Filled | AG44: 0 | AH44: Customer | AI44: 0 | AJ44: Head of Technology | AK44: Head of Technology | AL44: Head of Technology | AM44: 0 | AN44: Filled | AQ44: R0043 | AR44: NZ
A45: 115519 | B45: Shona Paul | C45: 115519 | D45: Head of Technology - Digital | E45: Harley Giles | F45: GM TDD, Customer | G45: Customer | H45: Digital | J45: Ampol Customer | K45: Portfolio Leadership | L45: Heads of Customer Portfolio | N45: NZ | O45: CSC (Always) | P45: 1 | R45: Permanent - Full Time | U45: 230470 | V45: 212032.4 | W45: 0.2 | Y45: 0.05 | Z45: 2910 | AA45: 0.03 | AB45: 274311.47 | AE45: 274311.47 | AF45: Filled | AG45: 0 | AH45: Customer | AI45: 0 | AJ45: Head of Technology | AK45: Head of Technology | AL45: Head of Technology | AM45: 0 | AN45: Filled | AQ45: R0044 | AR45: NZ
A46: V | B46: Vacant | C46: V | D46: Head of Technology - TDD & Engineering Capability Lead | E46: Emily Mogic | F46: GM TDD, Group Function | G46: TDD Group Functions | H46: TDD & Engineering | I46: na | J46: TDD | K46: TDD | L46: Leadership | N46: Australia | O46: CSC | P46: 1 | R46: v | U46: 235350 | V46: 235350 | W46: 0.2 | X46: 0.055 | Y46: 0.12 | AA46: 0.04 | AB46: 333020.25 | AE46: 333020.25 | AF46: Vacant | AG46: 0 | AH46: TDD Group Functions | AI46: 1 | AJ46: Leadership | AK46: Head of Technology | AL46: Head of Technology | AM46: 0 | AQ46: R0045 | AR46: AU
A47: 4818 | B47: Vaso Vukovic | C47: 4818 | D47: Head of Technology - P&C, Finance & Legal | E47: Emily Mogic | F47: GM TDD, Group Function | G47: TDD Group Functions | H47: P&C, Finance & Legal | I47: na | J47: P&C, Finance & Legal | K47: P&C, Finance & Legal | L47: Leadership | N47: Australia | O47: CSC | P47: 1 | R47: Permanent - Full Time | U47: 257420 | V47: 257420 | W47: 0.2 | X47: 0.055 | Y47: 0.12 | AA47: 0.04 | AB47: 364249.3 | AE47: 364249.3 | AF47: Filled | AG47: 0 | AH47: P&C | AI47: 1 | AJ47: Leadership | AK47: Head of Technology | AL47: Head of Technology | AM47: 0 | AQ47: R0046 | AR47: AU
A48: 100825 | B48: James Byrne | C48: 100825 | D48: Head of Cyber Strategy & Technology | E48: Frances Bouzo | F48: Manager Customer Support Operations | G48: Cyber, Risk & Operations | H48: Cyber Strat & Tech | I48: NA | J48: NA | K48: NA | L48: NA | N48: Australia | O48: CSC | P48: 1 | R48: Permanent - Full Time | U48: 270380 | V48: 270380 | W48: 0.2 | X48: 0.055 | Y48: 0.12 | AA48: 0.04 | AB48: 382587.7 | AE48: 382587.7 | AF48: Filled | AG48: 0 | AH48: COE Cyber | AI48: 0 | AJ48: Cyber Strat & Tech | AK48: Head of Technology | AL48: Cyber Strat & Tech | AM48: 0 | AQ48: R0047 | AR48: AU
A49: 105647 | B49: Rajini Onteddu Reddy | C49: 105647 | D49: Head of Service Operations & Assurance | E49: Frances Bouzo | F49: Manager Service Management & Major Incident Management Lead | G49: Cyber, Risk & Operations | H49: Service Op & Assurance | I49: NA | J49: NA | K49: NA | L49: NA | N49: Australia | O49: CSC | P49: 1 | R49: Permanent - Full Time | U49: 283160 | V49: 283160 | W49: 0.2 | X49: 0.055 | Y49: 0.12 | AA49: 0.04 | AB49: 400671.4 | AE49: 400671.4 | AF49: Filled | AG49: 0 | AH49: COE Service Ops | AI49: 0 | AJ49: Service Op & Assurance | AK49: Head of Technology | AL49: Service Op & Assurance | AM49: 0 | AQ49: R0048 | AR49: AU
A50: 106830 | B50: Moitri Pal | C50: 106830 | D50: Portfolio Mnager | E50: Greg Cassis | F50: GM TDD, EGI | G50: EGI | H50: EGI | I50: EGI | J50: EGI | K50: EGI | L50: EGI | N50: Australia | O50: CSC | P50: 1 | R50: Permanent - Full Time | U50: 230010 | V50: 230010 | W50: 0.2 | X50: 0.055 | Y50: 0.12 | AA50: 0.04 | AB50: 325464.15 | AE50: 325464.15 | AF50: Filled | AG50: 0 | AH50: EGI | AI50: 0 | AJ50: EGI | AK50: Squad | AL50: EGI | AM50: 1 | AQ50: R0049 | AR50: AU
A51: 116999 | B51: Jason Gleason | C51: 116999 | D51: Technology Manager, Data Engineering & Platforms | E51: James Holgate | F51: Head of Technology, Group Data | G51: Strategy, Architecture & Data | H51: Group Data | I51: Data Engineering & Platforms | J51: Enterprise Data | K51: Leadership | N51: NZ | O51: CSC | P51: 1 | R51: Permanent - Full Time | U51: 270000 | V51: 248400 | W51: 0.2 | Y51: 0.05 | Z51: 2910 | AA51: 0.03 | AB51: 320862 | AC51: 116999 | AE51: 320862 | AF51: Filled | AG51: 0 | AH51: Enterprise Data | AI51: 1 | AJ51: Leadership | AK51: Technology Manager | AL51: Technology Manager | AM51: 0 | AQ51: R0050 | AR51: NZ
A52: 110144 | B52: Sanjay Tikoo | C52: 110144 | D52: Principal, Data Architecture & Governance | E52: James Holgate | F52: Head of Technology, Group Data | G52: Strategy, Architecture & Data | H52: Group Data | I52: Data Capability | N52: Australia | O52: CSC | P52: 1 | R52: Permanent - Full Time | U52: 275000 | V52: 275000 | W52: 0.2 | X52: 0.055 | Y52: 0.12 | AA52: 0.04 | AB52: 389125 | AE52: 389125 | AF52: Filled | AG52: 0 | AH52: COE SA&D | AI52: 0 | AJ52: Group Data | AK52: Squad | AL52: Group Data | AM52: 0 | AQ52: R0051 | AR52: AU
A53: 80469 | B53: James Holgate | C53: 80469 | D53: Head of Technology, Group Data | E53: Matt Ashley | F53: GM TDD, Strategy, Architecture, Data | G53: Strategy, Architecture & Data | H53: Group Data | I53: Leadership | J53: Enterprise Data | K53: Leadership | N53: Australia | O53: CSC | P53: 1 | R53: Permanent - Full Time | U53: 289580 | V53: 289580 | W53: 0.2 | X53: 0.055 | Y53: 0.12 | AA53: 0.04 | AB53: 409755.7 | AE53: 409755.7 | AF53: Filled | AG53: 0 | AH53: Enterprise Data | AI53: 1 | AJ53: Leadership | AK53: Head of Technology | AL53: Head of Technology | AM53: 0 | AQ53: R0052 | AR53: AU
A54: 113381 | B54: Joel Vijayakumar | C54: 113381 | D54: Delivery Manager, Strategy, Architecture & Data | E54: Matt Ashley | F54: GM TDD, Strategy, Architecture, Data | G54: Strategy, Architecture & Data | H54: Delivery, SADA | K54: Leadership | N54: Australia | O54: CSC | P54: 1 | R54: Permanent - Full Time | U54: 260840 | V54: 260840 | W54: 0.2 | X54: 0.055 | Y54: 0.12 | AA54: 0.04 | AB54: 369088.6 | AE54: 369088.6 | AF54: Filled | AG54: 0 | AH54: COE SA&D | AI54: 1 | AJ54: Leadership | AK54: Delivery Manager | AL54: Leadership | AM54: 0 | AQ54: R0053 | AR54: AU
A55: V | B55: Vacant | C55: V | D55: Head of Architecture | E55: Matt Ashley | F55: GM TDD, Strategy, Architecture, Data | G55: Strategy, Architecture & Data | H55: Architecture | I55: Architecture | K55: Leadership | N55: Australia | O55: CSC | P55: 1 | R55: v | U55: 236730 | V55: 236730 | W55: 0.2 | X55: 0.055 | Y55: 0.12 | AA55: 0.04 | AB55: 334972.95 | AE55: 334972.95 | AF55: Vacant | AG55: 0 | AH55: COE SA&D | AI55: 1 | AJ55: Leadership | AK55: Head of Technology | AL55: Leadership | AM55: 0 | AQ55: R0054 | AR55: AU
A56: V | B56: Vacant | C56: V | D56: Head of Technology Strategy & AI Capability | E56: Matt Ashley | F56: GM TDD, Strategy, Architecture, Data | G56: Strategy, Architecture & Data | H56: Technology Strategy & AI Capability | I56: Technology Strategy & AI Capability | K56: Leadership | N56: Australia | O56: CSC | P56: 1 | R56: v | U56: 235350 | V56: 235350 | W56: 0.2 | X56: 0.055 | Y56: 0.12 | AA56: 0.04 | AB56: 333020.25 | AE56: 333020.25 | AF56: Vacant | AG56: 0 | AH56: COE SA&D | AI56: 1 | AJ56: Leadership | AK56: Head of Technology | AL56: Leadership | AM56: 0 | AQ56: R0055 | AR56: AU
A57: 102411 | B57: Conli Mills | C57: 102411 | D57: TDD BP - Infrastructure | E57: Michael Schofield | F57: GM TDD, Partnering & Transformation | G57: Partnering & Transformation | H57: TDD Business Partner | I57: NA | J57: NA | K57: NA | L57: NA | N57: Australia | O57: CSC | P57: 1 | R57: Permanent - Full Time | U57: 210000 | V57: 210000 | W57: 0.2 | X57: 0.055 | Y57: 0.12 | AA57: 0.04 | AB57: 297150 | AE57: 297150 | AF57: Filled | AG57: 0 | AH57: COE BP&T | AI57: 0 | AJ57: TDD Business Partner | AK57: Business Partner | AL57: TDD Business Partner | AM57: 0 | AQ57: R0056 | AR57: AU
A58: 116540 | B58: Neil Reilly | C58: 116540 | D58: TDD BP - T&S | E58: Michael Schofield | F58: GM TDD, Partnering & Transformation | G58: Partnering & Transformation | H58: TDD Business Partner | I58: NA | J58: NA | K58: NA | L58: NA | N58: Singapore | O58: CSC | P58: 1 | R58: Permanent - Full Time | U58: 350000 | V58: 423500 | W58: 0.35 | Y58: 0.17 | Z58: 3310 | AA58: 0.045 | AB58: 666087.5 | AE58: 666087.5 | AF58: Filled | AG58: 0 | AH58: COE BP&T | AI58: 0 | AJ58: TDD Business Partner | AK58: Business Partner | AL58: TDD Business Partner | AM58: 0 | AQ58: R0057 | AR58: AU
A59: 116452 | B59: Shelley Crawford | C59: 116452 | D59: TDD BP - Z | E59: Michael Schofield | F59: GM TDD, Partnering & Transformation | G59: Partnering & Transformation | H59: TDD Business Partner | I59: NA | J59: NA | K59: NA | L59: NA | N59: NZ | O59: CSC | P59: 1 | R59: Permanent - Full Time | U59: 245000 | V59: 225400 | W59: 0.2 | Y59: 0.05 | Z59: 2910 | AA59: 0.03 | AB59: 291422 | AE59: 291422 | AF59: Filled | AG59: 0 | AH59: COE BP&T | AI59: 0 | AJ59: TDD Business Partner | AK59: Business Partner | AL59: TDD Business Partner | AM59: 0 | AQ59: R0058 | AR59: NZ
A60: 113935 | B60: Thomas Reid | C60: 113935 | D60: TDD BP - Retail & Customer - Store Digital | E60: Michael Schofield | F60: GM TDD, Partnering & Transformation | G60: Partnering & Transformation | H60: TDD Business Partner | I60: NA | J60: NA | K60: NA | L60: NA | N60: Australia | O60: CSC | P60: 1 | R60: Permanent - Full Time | U60: 295000 | V60: 295000 | W60: 0.2 | X60: 0.055 | Y60: 0.12 | AA60: 0.04 | AB60: 417425 | AE60: 417425 | AF60: Filled | AG60: 0 | AH60: COE BP&T | AI60: 0 | AJ60: TDD Business Partner | AK60: Business Partner | AL60: TDD Business Partner | AM60: 0 | AQ60: R0059 | AR60: AU
A61: 101862 | B61: Vaughn Scott | C61: 101862 | D61: TDD BP - ES | E61: Michael Schofield | F61: GM TDD, Partnering & Transformation | G61: Partnering & Transformation | H61: TDD Business Partner | I61: NA | J61: NA | K61: NA | L61: NA | N61: Australia | O61: CSC | P61: 1 | R61: Permanent - Full Time | U61: 242660 | V61: 242660 | W61: 0.2 | X61: 0.055 | Y61: 0.12 | AA61: 0.04 | AB61: 343363.9 | AE61: 343363.9 | AF61: Filled | AG61: 0 | AH61: COE BP&T | AI61: 0 | AJ61: TDD Business Partner | AK61: Business Partner | AL61: TDD Business Partner | AM61: 0 | AQ61: R0060 | AR61: AU
A62: 117837 | B62: Sarsha Tanner | C62: 117837 | D62: Head of Transformation | E62: Michael Schofield | F62: Head of Service Operatoins & Assurance | G62: Partnering & Transformation | H62: Transformation | I62: NA | J62: NA | K62: NA | L62: NA | N62: Australia | O62: CSC | P62: 1 | R62: v | U62: 260000 | V62: 260000 | W62: 0.2 | X62: 0.055 | Y62: 0.12 | AA62: 0.04 | AB62: 367900 | AE62: 367900 | AF62: Filled | AG62: 0 | AH62: COE BP&T | AI62: 0 | AJ62: Transformation | AK62: Head of Technology | AL62: Transformation | AM62: 0 | AQ62: R0061 | AR62: AU
A63: 97098 | B63: Amish Pandit | C63: 97098 | D63: Head of Technology, Fuel Infrastructure | E63: Roanne Steele | F63: GM TDD, CFE&I | G63: TDD CFE&I | H63: Fuel Infrastructure | I63: Leadership | J63: Infrastructure | K63: Leadership | L63: Leadership | N63: Australia | O63: CSC | P63: 1 | R63: Permanent - Full Time | U63: 256980 | V63: 256980 | W63: 0.2 | X63: 0.055 | Y63: 0.12 | AA63: 0.04 | AB63: 363626.7 | AE63: 363626.7 | AF63: Filled | AG63: 0 | AH63: Infrastructure | AI63: 1 | AJ63: Leadership | AK63: Head of Technology | AL63: Head of Technology | AM63: 0 | AQ63: R0062 | AR63: AU
A64: 115488 | B64: Nakul Bharade | C64: 115488 | D64: Head of Technology, Commercial Fuels | E64: Roanne Steele | F64: GM TDD, CFE&I | G64: TDD CFE&I | H64: Commercial Fuels | I64: Leadership | J64: Commercial Fuels | K64: Leadership | L64: Leadership | N64: NZ | O64: CSC | P64: 1 | R64: Permanent - Full Time | U64: 245860 | V64: 226191.2 | W64: 0.2 | Y64: 0.05 | Z64: 2910 | AA64: 0.03 | AB64: 292434.74 | AE64: 292434.74 | AF64: Filled | AG64: 0 | AH64: Commercial Fuels | AI64: 1 | AJ64: Leadership | AK64: Head of Technology | AL64: Head of Technology | AM64: 0 | AQ64: R0063 | AR64: NZ
A65: 113574 | B65: Liesl Tye | C65: 113574 | D65: Head of Technology, B2B & Energy Solutions | E65: Roanne Steele | F65: GM TDD, CFE&I | G65: TDD CFE&I | H65: B2B & Energy Solutions | I65: Leadership | J65: B2B & Energy Solutions | K65: Leadership | L65: Leadership | N65: NZ | O65: CSC | P65: 1 | R65: Permanent - Full Time | U65: 230000 | V65: 211600 | W65: 0.2 | Y65: 0.05 | Z65: 2910 | AA65: 0.03 | AB65: 273758 | AE65: 273758 | AF65: Filled | AG65: 0 | AH65: Energy Solutions & B2B | AI65: 1 | AJ65: Leadership | AK65: Head of Technology | AL65: Head of Technology | AM65: 0 | AQ65: R0064 | AR65: NZ
A66: V | B66: Vacant | C66: V | D66: Data Governance Lead | E66: Sanjay Tikoo | F66: Data Capability Manager | G66: Strategy, Architecture & Data | H66: Group Data | I66: Data Capability | N66: australia | O66: CSC | P66: 1 | R66: V | U66: 275340 | V66: 275340 | W66: 0.2 | X66: 0.055 | Y66: 0.12 | AA66: 0.04 | AB66: 389606.1 | AE66: 389606.1 | AF66: Vacant | AG66: 0 | AH66: COE SA&D | AI66: 0 | AJ66: Group Data | AK66: Squad | AL66: Group Data | AM66: 0 | AQ66: R0065 | AR66: AU
A67: 110852 | B67: Madan Murthy | C67: 110852 | D67: Head of Technology, AU Retail | E67: Vance Anderson | F67: GM TDD, Ampol Retail & Z | G67: Ampol Retail & Z | H67: Ampol Retail | I67: na | J67: Retail | K67: (All Retail) | L67: Leadership | N67: Australia | O67: CSC | P67: 1 | R67: Permanent - Full Time | U67: 139350 | V67: 139350 | W67: 0.12 | X67: 0.055 | Y67: 0.12 | AA67: 0.04 | AB67: 186032.25 | AE67: 186032.25 | AF67: Filled | AG67: 0 | AH67: Ampol Retail | AI67: 1 | AJ67: Leadership | AK67: Head of Technology | AL67: Head of Technology | AM67: 0 | AQ67: R0066 | AR67: AU
A68: V | B68: Vacant | C68: V | D68: Head of Technology, Z and Group Retail Platforms | E68: Vance Anderson | F68: GM TDD, Ampol Retail & Z | G68: Ampol Retail & Z | H68: Z & Group Retail | I68: na | J68: Z | K68: Z Customer & Z Supply | L68: Leadership | N68: NZ | O68: CSC | P68: 1 | R68: v | U68: 245000 | V68: 225400 | W68: 0.2 | Y68: 0.05 | Z68: 2910 | AA68: 0.03 | AB68: 291422 | AE68: 291422 | AF68: Vacant | AG68: 0 | AH68: Z Retail | AI68: 1 | AJ68: Leadership | AK68: Head of Technology | AL68: Head of Technology | AM68: 0 | AQ68: R0067 | AR68: NZ
A69: 113555 | B69: Jill Martin | C69: 113555 | D69: Delivery Manager | E69: Andy Stewart | F69: Head of Technology, Loyalty & Martech | G69: Customer | H69: Loyalty & Martech | I69: Loyalty, Delivery | J69: Z ENERGY (DIGITAL) | K69: Z Loyalty & Martech | L69: Delivery Manager | N69: NZ | O69: CSB (Often) | P69: 1 | R69: Permanent - Full Time | U69: 193630 | V69: 178139.6 | W69: 0.15 | Y69: 0.05 | Z69: 2910 | AA69: 0.03 | AB69: 222021.71 | AE69: 222021.71 | AF69: Filled | AG69: 0 | AH69: Customer | AI69: 0 | AJ69: Delivery Manager | AK69: Delivery Manager | AL69: Delivery Manager | AM69: 0 | AN69: Filled | AQ69: R0068 | AR69: NZ
A70: 114753 | B70: Zoe Udy | C70: 114753 | D70: Technology Manager – Data & Engineering | E70: Andy Stewart | F70: Head of Technology, Loyalty & Martech | G70: Customer | H70: Loyalty & Martech | I70: Loyalty, Data & Engineering | J70: Z ENERGY (DIGITAL) | K70: Z Loyalty & Martech | L70: Technology Manager | N70: NZ | O70: CSB (Often) | P70: 1 | R70: Permanent - Full Time | U70: 180980 | V70: 166501.6 | W70: 0.15 | Y70: 0.05 | Z70: 2910 | AA70: 0.03 | AB70: 207706.97 | AE70: 207706.97 | AF70: Filled | AG70: 0 | AH70: Customer | AI70: 0 | AJ70: Technology Manager | AK70: Technology Manager | AL70: Technology Manager | AM70: 0 | AN70: Filled | AQ70: R0069 | AR70: NZ
A71: 113568 | B71: Kris Hamilton | C71: 113568 | D71: Technology Manager - Loyalty & Martech | E71: Andy Stewart | F71: Head of Technology, Loyalty & Martech | G71: Customer | H71: Loyalty & Martech | I71: Loyalty, Tech | J71: Z ENERGY (DIGITAL) | K71: Z Loyalty & Martech | L71: Technology Manager | N71: NZ | O71: CSB (Often) | P71: 1 | R71: Permanent - Full Time | U71: 194670 | V71: 179096.4 | W71: 0.15 | Y71: 0.05 | Z71: 2910 | AA71: 0.03 | AB71: 223198.57 | AE71: 223198.57 | AF71: Filled | AG71: 0 | AH71: Customer | AI71: 0 | AJ71: Technology Manager | AK71: Technology Manager | AL71: Technology Manager | AM71: 0 | AN71: Filled | AQ71: R0070 | AR71: NZ
A72: 96283 | B72: Ed Tacey | C72: 96283 | D72: Head of AI enablement | E72: Harley Giles | F72: GM TDD, Customer | G72: Customer | H72: Customer, AI Enablement | J72: Ampol Customer | K72: AI Enablement & Program Management | L72: Customer, AI | N72: Australia | O72: CSC | P72: 1 | R72: Permanent - Full Time | U72: 236730 | V72: 236730 | W72: 0.14 | X72: 0.055 | Y72: 0.2 | AA72: 0.04 | AB72: 339707.55 | AE72: 339707.55 | AF72: Filled | AG72: 0 | AH72: Customer | AI72: 0 | AJ72: Customer, AI | AK72: Squad | AL72: Customer, AI | AM72: 0 | AQ72: R0071 | AR72: AU
A73: V | B73: Vacant | C73: V | D73: Program Manager | E73: Harley Giles | F73: GM TDD, Customer | G73: Customer | H73: Customer, PMO | J73: Ampol Customer | K73: EGI Customer | L73: Programme Management | N73: Australia | O73: CSB (Often) | P73: 1 | R73: Vacant | U73: 225020 | V73: 225020 | W73: 0.14 | X73: 0.055 | Y73: 0.12 | AA73: 0.04 | AB73: 304902.1 | AE73: 304902.1 | AF73: Vacant | AG73: 0 | AH73: Customer | AI73: 0 | AJ73: Programme Management | AK73: Squad | AL73: EGI Customer | AM73: 1 | AN73: Vacant | AQ73: R0072 | AR73: AU
A74: 114123 | B74: Adriel Jeyanandhan | C74: 114123 | D74: Delivery Manager | E74: Shona Paul | F74: Head of Technology, Digital | G74: Customer | H74: Digital | I74: Digital, Delivery | J74: Ampol Customer | K74: Ampol Digital | L74: Delivery Manager | N74: Australia | O74: CSB (Often) | P74: 1 | R74: Permanent - Full Time | U74: 225020 | V74: 225020 | W74: 0.14 | X74: 0.055 | Y74: 0.12 | AA74: 0.04 | AB74: 304902.1 | AE74: 304902.1 | AF74: Filled | AG74: 0 | AH74: Customer | AI74: 0 | AJ74: Delivery Manager | AK74: Delivery Manager | AL74: Delivery Manager | AM74: 0 | AN74: Filled | AQ74: R0073 | AR74: AU
A75: 115528 | B75: Byron Thornhill | C75: 115528 | D75: Design Manager | E75: Shona Paul | F75: Head of Technology, Digital | G75: Customer | H75: Digital | I75: Digital, Design | J75: Z ENERGY (DIGITAL) | K75: Z Energy (Digitial) | L75: Z App and Web | N75: NZ | O75: CSB (Often) | P75: 1 | R75: Permanent - Full Time | U75: 190000 | V75: 174800 | W75: 0.1 | Y75: 0.05 | Z75: 2910 | AA75: 0.03 | AB75: 209174 | AE75: 209174 | AF75: Filled | AG75: 0 | AH75: Customer | AI75: 0 | AJ75: Z App and Web | AK75: Squad | AL75: Z App and Web | AM75: 0 | AN75: Filled | AQ75: R0074 | AR75: NZ
A76: 97200 | B76: Mitesh Shah | C76: 97200 | D76: Technology Manager - Digital | E76: Shona Paul | F76: Head of Technology, Digital | G76: Customer | H76: Digital | I76: Tech, Digital | J76: Ampol Customer | K76: Ampol Digital | L76: Technology Manager | N76: Australia | O76: CSB (Often) | P76: 1 | R76: Permanent - Full Time | U76: c | V76: 222190 | W76: 0.14 | X76: 0.055 | Y76: 0.12 | AA76: 0.04 | AB76: 301067.45 | AE76: 301067.45 | AF76: Filled | AG76: 0 | AH76: Customer | AI76: 0 | AJ76: Technology Manager | AK76: Technology Manager | AL76: Technology Manager | AM76: 0 | AN76: Filled | AQ76: R0075 | AR76: AU
A77: 88332 | B77: Safiq Iqbal | C77: 88332 | D77: Principal Engineer | E77: Shona Paul | F77: Head of Technology, Digital | G77: Customer | H77: Digital | I77: EGI | J77: EGI Integration | K77: EGI | L77: EGI Customer | N77: Australia | O77: CSB (Often) | P77: 1 | R77: Permanent - Full time | U77: 211070 | V77: 211070 | W77: 0.14 | X77: 0.055 | Y77: 0.12 | AA77: 0.04 | AB77: 304903.1 | AE77: 304903.1 | AF77: Filled | AG77: 0 | AH77: Customer | AI77: 0 | AJ77: EGI Customer | AK77: Squad | AL77: EGI Customer | AM77: 1 | AN77: Filled | AQ77: R0076 | AR77: AU
A78: V | B78: Vacant | C78: V | D78: Technology Manager, Engineering | E78: Shona Paul | F78: Head of Technology, Digital | G78: Customer | H78: Digital | I78: Tech, Digital Engineering | J78: Ampol Customer | K78: Ampol Digital | L78: Technology Manager | N78: Australia | O78: CSB (Often) | P78: 1 | R78: Vacant | U78: 225020 | V78: 225020 | W78: 0.14 | X78: 0.055 | Y78: 0.12 | AA78: 0.04 | AB78: 304902.1 | AE78: 304902.1 | AF78: Vacant | AG78: 0 | AH78: Customer | AI78: 0 | AJ78: Technology Manager | AK78: Technology Manager | AL78: Technology Manager | AM78: 0 | AN78: Vacant | AQ78: R0077 | AR78: AU
A79: 2967 | B79: Chris Camacho | C79: 2967 | D79: Senior Systems Analyst | E79: Jaya Ganasan | F79: Technology Manager, TDD Refinery | G79: TDD CFE&I | H79: Fuel Infrastructure | I79: Refinery Applications | J79: Infrastructure | K79: Manufacturing | L79: Manuacturing Group Projects | N79: Australia | O79: CSB | P79: 1 | R79: Permanent - Full Time | U79: 166090 | V79: 166090 | W79: 0.14 | X79: 0.055 | Y79: 0.12 | AA79: 0.04 | AB79: 225051.95 | AE79: 225051.95 | AF79: Filled | AG79: 0 | AH79: Infrastructure | AI79: 0 | AJ79: Manufacturing Group Projects | AK79: Squad | AL79: Manufacturing Group Projects | AM79: 0 | AQ79: R0078 | AR79: AU
A80: 101861 | B80: Prem Shetty | C80: 101861 | D80: Delivery manager | E80: Amish Pandit | F80: Head of Technology, Fuel Infrastructure | G80: TDD CFE&I | H80: Fuel Infrastructure | I80: Fuel Infrastructure, Delivery | J80: Infrastructure | K80: Leadership | L80: Leadership | N80: Australia | O80: CSB | P80: 1 | R80: Permanent - Full Time | U80: 233760 | V80: 233760 | W80: 0.14 | X80: 0.055 | Y80: 0.12 | AA80: 0.04 | AB80: 316744.8 | AE80: 316744.8 | AF80: Filled | AG80: 0 | AH80: Infrastructure | AI80: 1 | AJ80: Leadership | AK80: Delivery Manager | AL80: Delivery Manager | AM80: 0 | AQ80: R0079 | AR80: AU
A81: 109475 | B81: Jaya Ganasan | C81: 109475 | D81: B2B & Energy+B452:I452 | E81: Amish Pandit | F81: Head of Technology, Fuel Infrastructure | G81: TDD CFE&I | H81: Fuel Infrastructure | I81: Refinery Applications | J81: Infrastructure | K81: Manufacturing | L81: Manufacturing Group Projects | N81: Australia | O81: CSB | P81: 1 | R81: Permanent - Full Time | U81: 190180 | V81: 190180 | W81: 0.14 | X81: 0.055 | Y81: 0.12 | AA81: 0.04 | AB81: 257693.9 | AE81: 257693.9 | AF81: Filled | AG81: 0 | AH81: Infrastructure | AI81: 0 | AJ81: Manufacturing Group Projects | AK81: Squad | AL81: Manufacturing Group Projects | AM81: 0 | AQ81: R0080 | AR81: AU
A82: 106555 | B82: Karla Orozco Loza | C82: 106555 | D82: Technology Manager, Future Infrastructure | E82: Amish Pandit | F82: Head of Technology, Fuel Infrastructure | G82: TDD CFE&I | H82: Fuel Infrastructure | I82: Technology - Distribution | J82: Infrastructure | K82: Distribution | L82: Leadership | N82: Australia | O82: CSB | P82: 1 | R82: Permanent - Full Time | U82: 183820 | V82: 183820 | W82: 0.14 | X82: 0.055 | Y82: 0.12 | AA82: 0.04 | AB82: 249076.1 | AE82: 249076.1 | AF82: Filled | AG82: 0 | AH82: Infrastructure | AI82: 1 | AJ82: Leadership | AK82: Technology Manager | AL82: Technology Manager | AM82: 0 | AQ82: R0081 | AR82: AU
A83: V | B83: Vacant | C83: V | D83: Technology Manager Data | E83: Amish Pandit | F83: Head of Technology, Fuel Infrastructure | G83: TDD CFE&I | H83: Fuel Infrastructure | I83: Fuel Infrastructure, Data | J83: Infrastructure | K83: Leadership | L83: Leadership | N83: Australia | O83: CSB | P83: 1 | R83: v | U83: 203550 | V83: 203550 | W83: 0.14 | X83: 0.055 | Y83: 0.12 | AA83: 0.04 | AB83: 275810.25 | AE83: 275810.25 | AF83: Vacant | AG83: 0 | AH83: Infrastructure | AI83: 1 | AJ83: Leadership | AK83: Technology Manager | AL83: Technology Manager | AM83: 0 | AQ83: R0082 | AR83: AU
A84: 98823 | B84: Brian Gates | C84: 98823 | D84: Manager Risk & Resilience | E84: Frances Bouzo | F84: CISO | G84: Cyber, Risk & Operations | H84: Cyber Risk | I84: Risk & Resilience | J84: NA | K84: NA | L84: NA | N84: Australia | O84: CSB | P84: 1 | R84: Permanent - Full Time | U84: 211840 | V84: 211840 | W84: 0.14 | X84: 0.055 | Y84: 0.12 | AA84: 0.04 | AB84: 287043.2 | AE84: 287043.2 | AF84: Filled | AG84: 0 | AH84: COE Cyber | AI84: 0 | AJ84: Cyber Risk | AK84: Squad | AL84: Cyber Risk | AM84: 0 | AQ84: R0083 | AR84: AU
A85: 101700 | B85: Diya Thomas | C85: 101700 | D85: Manager Cyber Security GRC | E85: Frances Bouzo | F85: Manager Cyber Security Operations | G85: Cyber, Risk & Operations | H85: Cyber GRC | I85: NA | J85: NA | K85: NA | L85: NA | N85: Australia | O85: CSB | P85: 1 | R85: Permanent - Full Time | U85: 211840 | V85: 211840 | W85: 0.14 | X85: 0.055 | Y85: 0.12 | AA85: 0.04 | AB85: 287043.2 | AE85: 287043.2 | AF85: Filled | AG85: 0 | AH85: COE Cyber | AI85: 0 | AJ85: Cyber GRC | AK85: Squad | AL85: Cyber GRC | AM85: 0 | AQ85: R0084 | AR85: AU
A86: 101504 | B86: Steven Atcheson | C86: 101504 | D86: Manager Cyber Security Operations | E86: Frances Bouzo | F86: Manager, Risk & Resilience | G86: Cyber, Risk & Operations | H86: Cyber Sec Ops | I86: NA | J86: NA | K86: NA | L86: NA | N86: Australia | O86: CSB | P86: 1 | R86: Permanent - Full Time | U86: 233630 | V86: 233630 | W86: 0.14 | X86: 0.055 | Y86: 0.12 | AA86: 0.04 | AB86: 316568.65 | AE86: 316568.65 | AF86: Filled | AG86: 0 | AH86: COE Cyber | AI86: 0 | AJ86: Cyber Sec Ops | AK86: Squad | AL86: Cyber Sec Ops | AM86: 0 | AQ86: R0085 | AR86: AU
A87: 101830 | B87: Vivienne Vasak | C87: 101830 | D87: Portfolio Manager Cyber Security | E87: James Byrne | F87: Manager Service Perforance & Assurance | G87: Cyber, Risk & Operations | H87: Cyber Strat & Tech | I87: NA | J87: NA | K87: NA | L87: NA | N87: Australia | O87: CSB | P87: 1 | R87: Permanent - Full Time | U87: 232970 | V87: 232970 | W87: 0.14 | X87: 0.055 | Y87: 0.12 | AA87: 0.04 | AB87: 315674.35 | AE87: 315674.35 | AF87: Filled | AG87: 0 | AH87: TDD Cyber | AI87: 0 | AJ87: Cyber Uplift | AK87: Squad | AL87: Cyber Uplift | AM87: 0 | AQ87: R0086 | AR87: AU
A88: 113956 | B88: Deepali Mahajan | C88: 113956 | D88: Data Operations Manager | E88: James Holgate | F88: Head of Technology, Group Data | G88: Strategy, Architecture & Data | H88: Group Data | I88: Data Operations | J88: Enterprise Data | K88: Leadership | N88: Australia | O88: CSB | P88: 1 | R88: Permanent - Full Time | U88: 218390 | V88: 218390 | W88: 0.14 | X88: 0.055 | Y88: 0.12 | AA88: 0.04 | AB88: 295918.45 | AE88: 295918.45 | AF88: Filled | AG88: 0 | AH88: Enterprise Data | AI88: 1 | AJ88: Leadership | AK88: Squad | AL88: Leadership | AM88: 0 | AQ88: R0087 | AR88: AU
A89: 114067 | B89: Jonathan Robinson | C89: 114067 | D89: Technology Manager Data Science | E89: James Holgate | F89: Head of Technology, Group Data | G89: Strategy, Architecture & Data | H89: Group Data | I89: Data Science | J89: Enterprise Data | K89: Leadership | N89: Australia | O89: CSB | P89: 1 | R89: Permanent - Full Time | U89: 243850 | V89: 243850 | W89: 0.14 | X89: 0.055 | Y89: 0.12 | AA89: 0.04 | AB89: 330416.75 | AE89: 330416.75 | AF89: Filled | AG89: 0 | AH89: Enterprise Data | AI89: 1 | AJ89: Leadership | AK89: Technology Manager | AL89: Technology Manager | AM89: 0 | AQ89: R0088 | AR89: AU
A90: 115524 | B90: Tim Snedden | C90: 115524 | D90: Delivery Lead | E90: Joel Vijayakumar | F90: Delivery Manager, Strategy, Architecture & Data | G90: Strategy, Architecture & Data | H90: Delivery, SADA | J90: Enterprise Data | K90: Group Data | L90: Data Platform | N90: NZ | O90: CSB | P90: 1 | R90: Permanent - Full Time | U90: 161600 | V90: 148672 | W90: 0.15 | Y90: 0.05 | Z90: 2910 | AA90: 0.03 | AB90: 185776.56 | AC90: 15175 | AE90: 185776.56 | AF90: Filled | AG90: 0 | AH90: Enterprise Data | AI90: 0 | AJ90: Data Platforms | AK90: Squad | AL90: Data Platforms | AM90: 0 | AQ90: R0089 | AR90: NZ
A91: 115518 | B91: Hitesh Patel | C91: 115518 | D91: Technology Manager, Energy Solutions | E91: Liesl Tye | F91: Head of Technology, B2B & Energy Solutions | G91: TDD CFE&I | H91: B2B & Energy Solutions | I91: Technology Energy Solutions | J91: B2B & Energy Solutions | K91: Leadership | L91: Leadership | N91: NZ | O91: CSB | P91: 1 | R91: Permanent - Full Time | U91: 182640 | V91: 168028.8 | W91: 0.15 | Y91: 0.05 | Z91: 2910 | AA91: 0.03 | AB91: 209585.42 | AE91: 209585.42 | AF91: Filled | AG91: 0 | AH91: Energy Solutions & B2B | AI91: 1 | AJ91: Leadership | AK91: Technology Manager | AL91: Technology Manager | AM91: 0 | AQ91: R0090 | AR91: NZ
A92: 6748 | B92: Elle Spencer | C92: 6748 | D92: Technology Manager - B2B | E92: Liesl Tye | F92: Head of Technology, B2B & Energy Solutions | G92: TDD CFE&I | H92: B2B & Energy Solutions | I92: Technology B2B | J92: B2B & Energy Solutions | K92: Leadership | L92: Leadership | N92: Australia | O92: CSB | P92: 1 | R92: Permanent - Full Time | U92: 217390 | V92: 217390 | W92: 0.14 | X92: 0.055 | Y92: 0.12 | AA92: 0.04 | AB92: 294563.45 | AE92: 294563.45 | AF92: Filled | AG92: 0 | AH92: Energy Solutions & B2B | AI92: 1 | AJ92: Leadership | AK92: Technology Manager | AL92: Technology Manager | AM92: 0 | AQ92: R0091 | AR92: AU
A93: V | B93: Vacant | C93: V | D93: Delivery manager | E93: Liesl Tye | F93: Head of Technology, B2B & Energy Solutions | G93: TDD CFE&I | H93: B2B & Energy Solutions | I93: Leadership | J93: B2B & Energy Solutions | K93: Leadership | L93: Leadership | N93: Australia | O93: CSB | P93: 1 | R93: V | U93: 203550 | V93: 203550 | W93: 0.14 | X93: 0.055 | Y93: 0.12 | AA93: 0.04 | AB93: 275810.25 | AE93: 275810.25 | AF93: Vacant | AG93: 0 | AH93: Energy Solutions & B2B | AI93: 1 | AJ93: Leadership | AK93: Delivery Manager | AL93: Delivery Manager | AM93: 0 | AQ93: R0092 | AR93: AU
A94: 95285 | B94: Tracy Lee Reaper | C94: 95285 | D94: Technology Manager, Merchandising & WFM | E94: Madan Murthy | F94: Head of Technology, Ampol Retail | G94: Ampol Retail & Z | H94: Ampol Retail | I94: Ampol Retail, Merch & RTA | J94: Retail | K94: Above Store | L94: Leadership | N94: Australia | O94: CSB | P94: 1 | R94: Permanent - Full Time | U94: 195680 | V94: 180025.6 | W94: 0.15 | Y94: 0.05 | Z94: 2910 | AA94: 0.03 | AB94: 224341.49 | AE94: 224341.49 | AF94: Filled | AG94: 0 | AH94: Ampol Retail | AI94: 1 | AJ94: Leadership | AK94: Technology Manager | AL94: Technology Manager | AM94: 0 | AQ94: R0093 | AR94: AU
A95: 86604 | B95: Vanessa Allen | C95: 86604 | D95: Delivery Manager | E95: Madan Murthy | F95: Head of Technology, Ampol Retail | G95: Ampol Retail & Z | H95: Ampol Retail | I95: Ampol Retail, Delivery | J95: Retail | K95: (All Retail) | L95: Leadership | N95: Australia | O95: CSB | P95: 0.7 | R95: Permanent - Part Time | U95: 223570 | V95: 223570 | W95: 0.14 | X95: 0.055 | Y95: 0.12 | AA95: 0.04 | AB95: 302937.35 | AE95: 212056.14 | AF95: Filled | AG95: 0 | AH95: Ampol Retail | AI95: 1 | AJ95: Leadership | AK95: Delivery Manager | AL95: Delivery Manager | AM95: 0 | AQ95: R0094 | AR95: AU
A96: 8904 | B96: Vedran Jukic | C96: 8904 | D96: Technology Manager, Retail | E96: Madan Murthy | F96: Head of Technology, Ampol Retail | G96: Ampol Retail & Z | H96: Ampol Retail | I96: Ampol Retail, Technology | J96: Retail | K96: Store Operations, Network & QSR, Deployment | L96: Leadership | N96: Australia | O96: CSB | P96: 1 | R96: Permanent - Full Time | U96: 210000 | V96: 210000 | W96: 0.14 | X96: 0.055 | Y96: 0.12 | AA96: 0.04 | AB96: 284550 | AE96: 284550 | AF96: Filled | AG96: 0 | AH96: Ampol Retail | AI96: 1 | AJ96: Leadership | AK96: Technology Manager | AL96: Technology Manager | AM96: 0 | AQ96: R0095 | AR96: AU
A97: 117553 | B97: Malcolm Deare | C97: 117553 | D97: TDD BP, Group Functions | E97: Michael Schofield | F97: GM TDD, Partnering & Transformation | G97: Partnering & Transformation | H97: TDD Business Partner | I97: NA | J97: NA | K97: NA | L97: NA | N97: Australia | O97: CSB | P97: 1 | R97: Permanent - Full Time | U97: 220000 | V97: 220000 | W97: 0.14 | X97: 0.055 | Y97: 0.12 | AA97: 0.04 | AB97: 298100 | AE97: 298100 | AF97: Filled | AG97: 0 | AH97: COE BP&T | AI97: 0 | AJ97: TDD Business Partner | AK97: Business Partner | AL97: TDD Business Partner | AM97: 0 | AQ97: R0096 | AR97: AU
A98: 13925 | B98: Allan Francia | C98: 13925 | D98: Technology Manager - T&S | E98: Nakul Bharade | F98: Head of Technology, Commercial Fuels | G98: TDD CFE&I | H98: Commercial Fuels | I98: Technology, Trading & Shipping | J98: Commercial Fuels | K98: Leadership | L98: Leadership | N98: Australia | O98: CSB | P98: 1 | R98: Permanent - Full Time | U98: 212020 | V98: 212020 | W98: 0.14 | X98: 0.055 | Y98: 0.12 | AA98: 0.04 | AB98: 287287.1 | AE98: 287287.1 | AF98: Filled | AG98: 0 | AH98: Commercial Fuels | AI98: 1 | AJ98: Leadership | AK98: Technology Manager | AL98: Technology Manager | AM98: 0 | AQ98: R0097 | AR98: AU
A99: V | B99: Vacant | C99: V | D99: Delivery Manager | E99: Nakul Bharade | F99: Head of Technology, Commercial Fuels | G99: TDD CFE&I | H99: Commercial Fuels | I99: Delivery, Commercial Fuels | J99: Commercial Fuels | K99: Leadership | L99: Leadership | N99: Australia | O99: CSB | P99: 1 | R99: V | U99: 203550 | V99: 203550 | W99: 0.14 | X99: 0.055 | Y99: 0.12 | AA99: 0.04 | AB99: 275810.25 | AE99: 275810.25 | AF99: Vacant | AG99: 0 | AH99: Commercial Fuels | AI99: 1 | AJ99: Leadership | AK99: Delivery Manager | AL99: Delivery Manager | AM99: 0 | AQ99: R0098 | AR99: AU
A100: V | B100: Vacant | C100: V | D100: Technology Manager, Data | E100: Nakul Bharade | F100: Head of Technology, Commercial Fuels | G100: TDD CFE&I | H100: Commercial Fuels | I100: Technology, T&S Data | J100: Commercial Fuels | K100: Leadership | L100: Leadership | N100: Australia | O100: CSB | P100: 1 | R100: v | U100: 203550 | V100: 203550 | W100: 0.14 | X100: 0.055 | Y100: 0.12 | AA100: 0.04 | AB100: 275810.25 | AE100: 275810.25 | AF100: Vacant | AG100: 0 | AH100: Commercial Fuels | AI100: 1 | AJ100: Leadership | AK100: Technology Manager | AL100: Technology Manager | AM100: 0 | AQ100: R0099 | AR100: AU
...

Sheet 3 Lists
B1: Month list, used by the dropdowns. Do not change.
B2: Jul-2026 | C2: 1
B3: Aug-2026 | C3: 2
B4: Sep-2026 | C4: 3
B5: Oct-2026 | C5: 4
B6: Nov-2026 | C6: 5
B7: Dec-2026 | C7: 6
B8: Jan-2027 | C8: 7
B9: Feb-2027 | C9: 8
B10: Mar-2027 | C10: 9
B11: Apr-2027 | C11: 10
B12: May-2027 | C12: 11
B13: Jun-2027 | C13: 12
... B19: Dec-2027 | C19: 18
